Workbook

Sheet Свод
A1: СВОД: ТО АПС, АУПТ, СОУЭ — АО «РИР Энерго» «Воронежская генерация», 2027 г.
A2: Внутренний документ НЕОСТРОЙ — заказчику не передавать. Все суммы — руб. без НДС за 12 месяцев 2027 г.
B4: Статья себестоимости | C4: Сумма, руб. | D4: Доля | G4: Откуда
B5: ФОТ техников ТО (штат, Воронеж) | C5: ='Персонал ТО'!C16 -> 10290000 | D5: =C5/C$10 -> 0.63360262 | G5: Персонал ТО: численность × на руки × 1,5 × 14
B6: Расходники к работам | C6: =Работы!O109 -> 197111.89 | D6: =C6/C$10 -> 0.012137085 | G6: % к оплате труда (ELM, справочник)
B7: Субподряд и прочие прямые разовых работ (ЦСМ, ЭТЛ, аренда опрессовочного оборудования) | C7: =Работы!P109 -> 89170 | D7: =C7/C$10 -> 0.005490607 | G7: Работы, раздел «Разовые»
B8: Материалы ЗИП (с/с) | C8: =Материалы!M22 -> 177141.03 | D8: =C8/C$10 -> 0.010907388 | G8: Материалы
B9: Косвенные проекта | C9: =Косвенные!G21 -> 5487040.2 | D9: =C9/C$10 -> 0.3378623 | G9: Косвенные
B10: ПОЛНАЯ СЕБЕСТОИМОСТЬ | C10: =SUM(C5:C9) -> 16240463 | D10: =SUM(D5:D9) -> 1
B12: Коммерческое предложение | C12: Сумма, руб. | D12: Доля | G12: Откуда
B13: Регламентное ТО (12 мес.) | C13: =Работы!J99 -> 17898182 | D13: =C13/C$16 -> 0.92870877 | G13: Работы
B14: Разовые работы 2027 | C14: =Работы!J107 -> 1206585 | D14: =C14/C$16 -> 0.062607814 | G14: Работы
B15: Материалы ЗИП | C15: =Материалы!Q22 -> 167347.83 | D15: =C15/C$16 -> 0.008683418 | G15: Материалы
B16: КП БЕЗ НДС | C16: =SUM(C13:C15) -> 19272115
B17: НДС 22 % | C17: =ROUND(C16*0.22,2) -> 4239865.3
B18: КП С НДС | C18: =C16+C17 -> 23511980
B19: КП в месяц без НДС (регламентное ТО) | C19: =Работы!K99 -> 1491515.2
B21: Показатели | C21: Значение | G21: Комментарий
B22: Наценка = КП ÷ с/с − 1 | C22: =C16/C10-1 -> 0.18667275
B23: Маржа = 1 − с/с ÷ КП | C23: =1-C10/C16 -> 0.15730769
B24: Маржа, руб. | C24: =C16-C10 -> 3031651.8
B25: Тип тендера | C25: Госзакупки 44-ФЗ / 223-ФЗ
B26: Целевой диапазон наценки (лист «Тип тендера») | C26: 15–30 %
B27: Проверка по типу тендера | C27: =IF(C22<0.15,"НИЖЕ 15 % — согласование ГД",IF(C22>0.3,"выше диапазона","в диапазоне")) -> в диапазоне
B28: Наценка на материалы (средняя) | C28: =Материалы!Q22/Материалы!M22-1 -> -0.055284764
B29: Наценка на работы (ТО + разовые) к прямой с/с работ + косвенным | C29: =(Работы!J109)/(Свод!C10-Материалы!M22)-1 -> 0.18934097
B30: НМЦК | C30: не опубликована в папке лота | G30: В папке только ТЗ. Минимально допустимая цена = с/с × 1,15 (строка 36)
B32: Сценарии | C32: КП б/НДС | D32: Маржа, руб. | E32: Маржа, % | F32: Наценка | G32: Комментарий
B33: Базовый | C33: =ROUND($C$16*1,2) -> 19272115 | D33: =C33-$C$10 -> 3031651.8 | E33: =D33/C33 -> 0.15730769 | F33: =C33/$C$10-1 -> 0.18667275
B34: Переторжка −5 % | C34: =ROUND($C$16*0.95,2) -> 18308509 | D34: =C34-$C$10 -> 2068046.1 | E34: =D34/C34 -> 0.11295546 | F34: =C34/$C$10-1 -> 0.12733911
B35: Переторжка −10 % | C35: =ROUND($C$16*0.9,2) -> 17344903 | D35: =C35-$C$10 -> 1104440.3 | E35: =D35/C35 -> 0.063675209 | F35: =C35/$C$10-1 -> 0.068005471
B36: Минимальная цена (наценка 15 %, ниже — только ГД) | C36: =ROUND($C$10*1.15,2) -> 18676533 | D36: =C36-$C$10 -> 2436069.5 | E36: =D36/C36 -> 0.13043478 | F36: =C36/$C$10-1 -> 0.15 | G36: =TEXT(1-C36/C16,"0.0%")&" — максимальная скидка от КП" -> 3.1% — максимальная скидка от КП

Sheet Паспорт тендера
A1: ПАСПОРТ ТЕНДЕРА
A3: Заказчик | B3: АО «РИР Энерго», филиал «Воронежская генерация» (группа Росатом), закупка по 223-ФЗ: план закупки на 2027 г., закупка № 637, лот 1, спецификация 1
A4: Предмет | B4: Оказание услуг по ТО установок автоматической пожарной сигнализации (АПС), автоматических установок пожаротушения (АУПТ) и систем оповещения и управления эвакуацией (СОУЭ); плановая и предупредительная замена вышедшего из строя оборудования; ведение документации
A5: Объекты и адреса | B5: г. Воронеж: ПП ТЭЦ-1 (ул. Лебедева, 2), ПП ТЭЦ-2 (пр. Ясный, 1а), ПП Тепловые сети (ул. С. Перовской, 7; ул. Пешестрелецкая, 84; пр. Ясный, 1а; ул. Лебедева, 2), ПП ГТС (ул. Кольцовская, 78; ул. Плехановская, 17; ул. Туполева, 31к; ул. Б. Хмельницкого, 79к) — 10 адресов
A6: Регион | B6: Воронеж (регион): тарификатор СПб/Мск не применим напрямую → цены — рынок Воронежа/ЦФО; персонал — местный найм; доставка материалов 10 % (параметр «Регион»)
A7: Объём (Прил. 1–8) | B7: АПС/СОУЭ: ~120 ППК и пультов, 146 блоков, 67 источников питания, 76 АКБ, 3 569 автоматических извещателей + 70 взрывозащищённых + 26 пламени + 5 линейных, 1 920 м термокабеля, 558 ручных/УДП/ЭДУ, 224 охранных, 880 оповещателей, 5 приборов речевого оповещения, 4 модуля «Буран», ~52,7 км шлейфов. АУПТ ТЭЦ-1/ТЭЦ-2: 9,6 км трубопроводов, 217 ручных и 64 электрифицированных задвижек/затворов, 987 оросителей/пеногенераторов/стволов, 40 манометров и сигнализаторов, 8 насосов, 3 бака
A8: Периодичность (Прил. 9, 10) | B8: АПС: ежемесячно — осмотр, контроль индикации, питания, проверка работоспособности; ежеквартально (мар, июн, сен, дек) — профилактика; июнь — измерение сопротивления заземления. АУПТ: ежемесячно — узлы, оросители, трубопроводы; фев/май/авг/ноя — вводы, арматура, задвижки с ЭП и схемы пуска; май, ноябрь — манометры; май — полная проверка манометров с опломбированием/клеймением; 1 раз в 3 года — опрессовка, промывка и опробование с реальным пуском: ТЭЦ-2 (ГК, ПГУ-115, ВК, МН) — июль–август 2027; ТЭЦ-1 — проведено в июне–июле 2026, в 2027 не требуется
A9: Срок | B9: 2027 год (12 месяцев); точные даты начала/окончания — в проекте договора (в папке лота нет)
A10: НМЦК | B10: Не опубликована: на b2b-center (лот № 57697, организатор АО «Квадра-ГК» для АО «РИР Энерго» — «Воронежская генерация») начальная цена 0, оценивается цена с НДС; вскрытие 30.10.2026 08:00 МСК. Аналог 2023 г. (ЕИС 32211915005) — НМЦК 2 399 999 руб.
A11: Форма КП | B11: Формы заказчика нет → наша форма КП (xlsx) + письмо на бланке
A12: Цены с НДС / без | B12: Не указано; считаем без НДС, НДС 22 % сверху
A13: Оплата | B13: В течение 7 рабочих дней от даты подписания акта оказанных услуг (раздел ТЗ). Аванса нет
A14: Гарантия | B14: Работоспособность систем в течение срока договора; устранение дефектов за свой счёт, гарантийный период продлевается на время гарантийных работ (п. 3.3)
... A18: ОКПД2 | B18: 43.21.10.140 (в ТЗ — монтаж систем пожарной и охранной сигнализации; для услуги ТО обычно 33.12/80.20 — несоответствие, вопрос заказчику не критичен)

Sheet Ставки ТО
A1: СТАВКИ ТО ПО ВИДАМ ОБОРУДОВАНИЯ: РЫНОК, ЦЕНА КП, НОРМА ТРУДОЗАТРАТ
A2: Работ нет в тарификаторе v2 → цена = рынок подрядчиков (б/НДС, руб. за ед. в месяц), норма — чел.-ч на ед. в месяц в среднем за год (ежемесячные операции + ежеквартальная профилактика + годовые проверки). Жёлтые ячейки — вводные.
A4: Код | B4: Услуга | C4: Ед. | D4: Норма, чел.-ч/ед./мес | E4: Основание нормы | F4: Рынок 1, руб/ед/мес б/НДС | G4: Источник 1 | H4: Рынок 2 | I4: Источник 2 | J4: Рынок 3 | K4: Источник 3 | L4: Медиана рынка | M4: Коэф. к рынку | N4: ЦЕНА КП, руб/ед/мес б/НДС | O4: Примечание
A5: PPK | B5: ТО прибора приёмно-контрольного, пульта, прибора управления (С2000М, Сигнал-20П/10, Гранит, С2000-АСПТ, Рубеж-20П и др.) | C5: шт | D5: 1 | E5: Экспертно 1,0 ч/мес (между пультом 1,0 и ППК средней ёмкости 3,0 ч/мес по нормативы МВД (у.у. = 1,67 ч/мес), ivtechno.ru) | F5: 500 | G5: Пожарный Арсенал, Воронеж (pozharsenal.ru), «от» | H5: 1431 | I5: Прейскурант 2661 × 39,43 (t-as.ru, расчёт): 371 + 106 × 10 ШС | J5: 1800 | K5: Квазар-Сервис, Краснодар (ecq.ru), ППК до 16 ШС | L5: =MEDIAN(F5,H5,J5) -> 1431 | M5: 2.53 | N5: =ROUND(L5*M5,2) -> 3620.43 | O5: Москва 2 090–2 600 (Стройпожсервис, montage-ssb) — не брали; коэф. 2.53 — цена от с/с (наценка ≈ 17 %): по рыночной медиане КП не покрывает с/с штатного ТО
A6: BLOCK | B6: ТО блока системы (С2000-КДЛ, СП1/СП2, КПБ, БКИ, ПИ, ПТ, БРИЗ, барьеры искрозащиты и др.) | C6: шт | D6: 0.2 | E6: Адресный расширитель 0,33 ч/мес (нормативы МВД (у.у. = 1,67 ч/мес), ivtechno.ru); экспертно 0,2 — проверка в составе ППК | F6: 49 | G6: samss.ru, Самара, руб/мес, блок управления | H6: 95 | I6: Стройпожсервис, Москва (stroipozhservis.ru), релейный блок | J6: 100 | K6: ООО «Интех», Воронеж (inteh36.ru), «от» | L6: =MEDIAN(F6,H6,J6) -> 95 | M6: 2.53 | N6: =ROUND(L6*M6,2) -> 240.35 | O6: коэф. 2.53 — цена от с/с (наценка ≈ 17 %): по рыночной медиане КП не покрывает с/с штатного ТО
A7: PSU | B7: ТО источника электропитания резервированного (РИП, Скат, ИВЭПР, ББП) | C7: шт | D7: 0.25 | E7: РИП с АКБ 0,5 ч/мес (нормативы МВД (у.у. = 1,67 ч/мес), ivtechno.ru); экспертно 0,25 (АКБ — отдельной строкой) | F7: 80 | G7: Квазар-Сервис, Краснодар (ecq.ru), ИБП | H7: 195 | I7: Стройпожсервис, Москва (stroipozhservis.ru) | J7: 200 | K7: Пожарный Арсенал, Воронеж (pozharsenal.ru), «от» | L7: =MEDIAN(F7,H7,J7) -> 195 | M7: 2.53 | N7: =ROUND(L7*M7,2) -> 493.35 | O7: коэф. 2.53 — цена от с/с (наценка ≈ 17 %): по рыночной медиане КП не покрывает с/с штатного ТО
A8: AKB | B8: ТО аккумуляторной батареи (контроль напряжения и ёмкости) | C8: шт | D8: 0.05 | E8: Экспертно: замер напряжения/ёмкости при ТО РИП | F8: 82 | G8: СБ-ГРУПП, Москва (ooosbg.ru), 100 с НДС ÷ 1,22 | H8: 95 | I8: Стройпожсервис, Москва (stroipozhservis.ru) | J8: 150 | K8: Формула охраны, Москва (naoxrane.ru), 2021 | L8: =MEDIAN(F8,H8,J8) -> 95 | M8: 2.53 | N8: =ROUND(L8*M8,2) -> 240.35 | O8: коэф. 2.53 — цена от с/с (наценка ≈ 17 %): по рыночной медиане КП не покрывает с/с штатного ТО
A9: DET_AUTO | B9: ТО извещателя пожарного автоматического точечного (дымового, теплового) | C9: шт | D9: 0.04 | E9: Экспертно: ежемес. осмотр + проверка аэрозолем 1 раз в квартал ~6 мин/шт; верхняя граница — дымовой 0,17 ч/мес (нормативы МВД (у.у. = 1,67 ч/мес), ivtechno.ru) | F9: 30 | G9: Пожарный Арсенал, Воронеж (pozharsenal.ru), «от» | H9: 40 | I9: Квазар-Сервис, Краснодар (ecq.ru), адресный дымовой | J9: 49 | K9: samss.ru, Самара, руб/мес | L9: =MEDIAN(F9,H9,J9) -> 40 | M9: 2.53 | N9: =ROUND(L9*M9,2) -> 101.2 | O9: Москва 48–60 (Стройпожсервис, Контур); коэф. 2.53 — цена от с/с (наценка ≈ 17 %): по рыночной медиане КП не покрывает с/с штатного ТО
A10: DET_EX | B10: ТО извещателя пожарного во взрывозащищённом/искробезопасном исполнении | C10: шт | D10: 0.15 | E10: Экспертно: × 3–4 к обычному (наряд-допуск, взрывоопасная зона) | F10: 95 | G10: Стройпожсервис, Москва (stroipozhservis.ru) | H10: 100 | I10: montage-ssb, Мск/СПб (city-ser.com) | L10: =MEDIAN(F10,H10,J10) -> 97.5 | M10: 2.53 | N10: =ROUND(L10*M10,2) -> 246.68 | O10: коэф. 2.53 — цена от с/с (наценка ≈ 17 %): по рыночной медиане КП не покрывает с/с штатного ТО
A11: DET_FLAME | B11: ТО извещателя пожарного пламени (Спектрон, Пульсар, Набат) | C11: шт | D11: 0.15 | E11: Экспертно: проверка тест-фонарём | F11: 50 | G11: montage-ssb, Мск/СПб (city-ser.com) | H11: 41 | I11: СБ-ГРУПП, 50 с НДС ÷ 1,22 | J11: 60 | K11: Контур безопасности, Москва (scontur.ru) | L11: =MEDIAN(F11,H11,J11) -> 50 | M11: 2.53 | N11: =ROUND(L11*M11,2) -> 126.5 | O11: коэф. 2.53 — цена от с/с (наценка ≈ 17 %): по рыночной медиане КП не покрывает с/с штатного ТО
A12: LINEAR | B12: ТО извещателя пожарного дымового линейного ИПДЛ | C12: к-т | D12: 0.3 | E12: ИПДЛ 0,5 ч/мес (нормативы МВД (у.у. = 1,67 ч/мес), ivtechno.ru); экспертно 0,3 | F12: 145 | G12: Стройпожсервис, Москва (stroipozhservis.ru) | H12: 200 | I12: Квазар-Сервис, Краснодар (ecq.ru) | J12: 440 | K12: samss.ru, Самара, руб/мес | L12: =MEDIAN(F12,H12,J12) -> 200 | M12: 2.53 | N12: =ROUND(L12*M12,2) -> 506 | O12: коэф. 2.53 — цена от с/с (наценка ≈ 17 %): по рыночной медиане КП не покрывает с/с штатного ТО
A13: THERMO | B13: ТО линейного теплового извещателя (термокабель) | C13: 100 м | D13: 0.15 | E13: Экспертно: осмотр трассы, проверка шлейфа на 100 м | F13: 150 | G13: ОЦЕНКА по аналогии с ИПДЛ (1 зона ≈ 100 м); рыночной цены нет — montage-ssb «договорная» | L13: =MEDIAN(F13,H13,J13) -> 150 | M13: 2.53 | N13: =ROUND(L13*M13,2) -> 379.5 | O13: ОЦЕНКА — уточнить запросом у ВДПО Воронеж / ИПС / Интех; коэф. 2.53 — цена от с/с (наценка ≈ 17 %): по рыночной медиане КП не покрывает с/с штатного ТО
A14: DET_MAN | B14: ТО извещателя пожарного ручного, УДП, ЭДУ | C14: шт | D14: 0.04 | E14: Экспертно, как автоматический извещатель | F14: 30 | G14: Пожарный Арсенал, Воронеж (pozharsenal.ru), «от» | H14: 35 | I14: Квазар-Сервис, Краснодар (ecq.ru) | J14: 49 | K14: samss.ru, Самара, руб/мес | L14: =MEDIAN(F14,H14,J14) -> 35 | M14: 2.53 | N14: =ROUND(L14*M14,2) -> 88.55 | O14: коэф. 2.53 — цена от с/с (наценка ≈ 17 %): по рыночной медиане КП не покрывает с/с штатного ТО
A15: DET_SEC | B15: ТО извещателя охранного (магнитоконтактного, ИК) в составе систем | C15: шт | D15: 0.03 | E15: Экспертно | F15: 25 | G15: Формула охраны, тепловой/простой | H15: 30 | I15: Пожарный Арсенал, Воронеж (pozharsenal.ru), «от» | J15: 49 | K15: samss.ru, Самара, руб/мес | L15: =MEDIAN(F15,H15,J15) -> 30 | M15: 2.53 | N15: =ROUND(L15*M15,2) -> 75.9 | O15: коэф. 2.53 — цена от с/с (наценка ≈ 17 %): по рыночной медиане КП не покрывает с/с штатного ТО
A16: ANN | B16: ТО оповещателя (светового, звукового, речевого, табло «Выход») | C16: шт | D16: 0.04 | E16: Оповещатель 0,17 ч/мес (нормативы МВД (у.у. = 1,67 ч/мес), ivtechno.ru) — верхняя граница; экспертно 0,04 (проверка зонами при пуске) | F16: 40 | G16: Квазар-Сервис, Краснодар (ecq.ru), световой/звуковой | H16: 49 | I16: samss.ru, Самара, руб/мес | J16: 50 | K16: montage-ssb, Мск/СПб (city-ser.com) | L16: =MEDIAN(F16,H16,J16) -> 49 | M16: 2.53 | N16: =ROUND(L16*M16,2) -> 123.97 | O16: коэф. 2.53 — цена от с/с (наценка ≈ 17 %): по рыночной медиане КП не покрывает с/с штатного ТО
A17: SOUE | B17: ТО прибора речевого оповещения СОУЭ (Орфей, Рокот, Соната) | C17: шт | D17: 1 | E17: Экспертно (как ППК) | F17: 340 | G17: samss.ru, Самара, руб/мес, блок управления СОУЭ | H17: 500 | I17: Квазар-Сервис, Краснодар (ecq.ru), предусилитель | J17: 800 | K17: montage-ssb, Мск/СПб (city-ser.com), блок речевого оповещения | L17: =MEDIAN(F17,H17,J17) -> 500 | M17: 2.53 | N17: =ROUND(L17*M17,2) -> 1265 | O17: коэф. 2.53 — цена от с/с (наценка ≈ 17 %): по рыночной медиане КП не покрывает с/с штатного ТО
A18: MPP | B18: ТО модуля порошкового пожаротушения (Буран-8взр) | C18: шт | D18: 0.3 | E18: Экспертно: осмотр, контроль цепей пуска | F18: 375 | G18: Нормативные затраты МВД 4 500/год | H18: 450 | I18: k-systemy.ru, Красноярск | J18: 725 | K18: ogneboy.ru, 1–10 модулей 2 900 / 4 мод. | L18: =MEDIAN(F18,H18,J18) -> 450 | M18: 2.53 | N18: =ROUND(L18*M18,2) -> 1138.5 | O18: коэф. 2.53 — цена от с/с (наценка ≈ 17 %): по рыночной медиане КП не покрывает с/с штатного ТО
A19: SW | B19: Сопровождение ПО АРМ «Орион Про» (резервное копирование баз, проверка связи) | C19: к-т | D19: 2 | E19: Экспертно: резервное копирование БД, проверка связи ППК–АРМ | F19: 1639 | G19: СБ-ГРУПП, АРМ 2 000 с НДС ÷ 1,22 | H19: 1700 | I19: Квазар-Сервис, Краснодар (ecq.ru), АРМ | J19: 1990 | K19: Стройпожсервис, Москва (stroipozhservis.ru), АРМ | L19: =MEDIAN(F19,H19,J19) -> 1700 | M19: 2.53 | N19: =ROUND(L19*M19,2) -> 4301 | O19: коэф. 2.53 — цена от с/с (наценка ≈ 17 %): по рыночной медиане КП не покрывает с/с штатного ТО
A20: CABLE | B20: ТО шлейфов сигнализации и линий связи (осмотр, измерение параметров) | C20: 100 м | D20: 0.02 | E20: Экспертно: шлейф контролируется ППК; осмотр трасс + выборочные замеры | F20: 10 | G20: ОЦЕНКА: на рынке входит в цену ТО ППК; отдельной цены нет | L20: =MEDIAN(F20,H20,J20) -> 10 | M20: 2.53 | N20: =ROUND(L20*M20,2) -> 25.3 | O20: ОЦЕНКА — 10 руб./100 м/мес; коэф. 2.53 — цена от с/с (наценка ≈ 17 %): по рыночной медиане КП не покрывает с/с штатного ТО
A21: BOX | B21: ТО коробок коммутационных/распределительных, шкафов, автоматов питания | C21: шт | D21: 0.03 | E21: Экспертно: осмотр, протяжка | F21: 10 | G21: ОЦЕНКА: на рынке входит в ТО системы | L21: =MEDIAN(F21,H21,J21) -> 10 | M21: 2.53 | N21: =ROUND(L21*M21,2) -> 25.3 | O21: ОЦЕНКА; коэф. 2.53 — цена от с/с (наценка ≈ 17 %): по рыночной медиане КП не покрывает с/с штатного ТО
A22: PIPE | B22: ТО трубопроводов АУПТ (течи, уклоны, крепления, окраска) | C22: 100 м | D22: 0.25 | E22: 3,7–7,1 чел.-ч/год на 100 м (РТМ 25.488-82 (ТО + текущий ремонт), meganorm.ru) ≈ 0,3–0,6 ч/мес; экспертно 0,25 (без ремонта) | F22: 200 | G22: ОЦЕНКА; рынок даёт ТО АУПТ по площади от 35 руб/м² (Центр «Каска», Воронеж) — к метражу не приводится | L22: =MEDIAN(F22,H22,J22) -> 200 | M22: 2.53 | N22: =ROUND(L22*M22,2) -> 506 | O22: ОЦЕНКА — уточнить запросом; коэф. 2.53 — цена от с/с (наценка ≈ 17 %): по рыночной медиане КП не покрывает с/с штатного ТО
A23: VALVE_MAN | B23: ТО запорной арматуры с ручным приводом (задвижки, затворы, вентили, клапаны, краны) | C23: шт | D23: 0.25 | E23: 7,9–13,8 чел.-ч/год (РТМ 25.488-82 (ТО + текущий ремонт), meganorm.ru) ≈ 0,7–1,1 ч/мес с ремонтом; экспертно 0,25 | F23: 150 | G23: ОЦЕНКА: поштучной цены нет (рынок — в составе узла управления 750–800 руб/мес) | L23: =MEDIAN(F23,H23,J23) -> 150 | M23: 2.53 | N23: =ROUND(L23*M23,2) -> 379.5 | O23: ОЦЕНКА; коэф. 2.53 — цена от с/с (наценка ≈ 17 %): по рыночной медиане КП не покрывает с/с штатного ТО
A24: VALVE_EL | B24: ТО задвижки/затвора с электроприводом и схемой управления | C24: шт | D24: 1 | E24: 27,6 чел.-ч/год мех.+эл. часть (РТМ 25.488-82), 34,9 (ПП РФ 2072) ≈ 2,3–2,9 ч/мес; экспертно 1,0 | F24: 750 | G24: mk-gost.ru, Саратов: разовая проверка 2 000–2 500, ежеквартально → ÷ 3 | H24: 800 | I24: Прейскурант 2661 × 39,43 (t-as.ru, расчёт): узел управления ≈ 800 | L24: =MEDIAN(F24,H24,J24) -> 775 | M24: 2.53 | N24: =ROUND(L24*M24,2) -> 1960.75 | O24: коэф. 2.53 — цена от с/с (наценка ≈ 17 %): по рыночной медиане КП не покрывает с/с штатного ТО
A25: SPRINK | B25: ТО оросителя, пеногенератора, лафетного ствола (осмотр, очистка) | C25: шт | D25: 0.03 | E25: 1,2–1,8 чел.-ч/год (РТМ 25.488-82 (ТО + текущий ремонт), meganorm.ru) ≈ 0,1–0,15 ч/мес; экспертно 0,03 (осмотр без демонтажа) | F25: 2 | G25: k-systemy.ru: 200 руб. за 100 оросителей | H25: 26 | I25: Прейскурант 2661 × 39,43 (t-as.ru, расчёт): 260 на 10 оросителей | L25: =MEDIAN(F25,H25,J25) -> 14 | M25: 2.53 | N25: =ROUND(L25*M25,2) -> 35.42 | O25: коэф. 2.53 — цена от с/с (наценка ≈ 17 %): по рыночной медиане КП не покрывает с/с штатного ТО
A26: GAUGE | B26: ТО манометра, сигнализатора/реле давления | C26: шт | D26: 0.25 | E26: 6,3–18,6 чел.-ч/год (РТМ 25.488-82 (ТО + текущий ремонт), meganorm.ru); экспертно 0,25 | F26: 138 | G26: Прейскурант 2661 × 39,43 (t-as.ru, расчёт): сигнализатор давления | L26: =MEDIAN(F26,H26,J26) -> 138 | M26: 2.53 | N26: =ROUND(L26*M26,2) -> 349.14 | O26: Цены ТО манометра в месяц на рынке нет; коэф. 2.53 — цена от с/с (наценка ≈ 17 %): по рыночной медиане КП не покрывает с/с штатного ТО
A27: PUMP | B27: ТО насосного агрегата пожаротушения | C27: шт | D27: 4 | E27: 35–176 чел.-ч/год (РТМ 25.488-82 (ТО + текущий ремонт), meganorm.ru), 96 (ПП РФ 2072) ≈ 3–15 ч/мес; экспертно 4,0 | F27: 1995 | G27: Инфомакс, Москва: насосная до 100 м² | H27: 2646 | I27: Прейскурант 2661 × 39,43 (t-as.ru, расчёт): технолог. часть насосной | J27: 6000 | K27: k-systemy.ru: насосная станция | L27: =MEDIAN(F27,H27,J27) -> 2646 | M27: 2.53 | N27: =ROUND(L27*M27,2) -> 6694.38 | O27: коэф. 2.53 — цена от с/с (наценка ≈ 17 %): по рыночной медиане КП не покрывает с/с штатного ТО
A28: TANK | B28: ТО бака (пенообразователя, мембранного) | C28: шт | D28: 1 | E28: Экспертно | F28: 300 | G28: ОЦЕНКА | L28: =MEDIAN(F28,H28,J28) -> 300 | M28: 2.53 | N28: =ROUND(L28*M28,2) -> 759 | O28: ОЦЕНКА; коэф. 2.53 — цена от с/с (наценка ≈ 17 %): по рыночной медиане КП не покрывает с/с штатного ТО

Sheet Работы
A1: РАБОТЫ: РЕГЛАМЕНТНОЕ ТО ПО ОБЪЕКТАМ И ВИДАМ ОБОРУДОВАНИЯ + РАЗОВЫЕ РАБОТЫ 2027
A2: Кол-во — из Приложений 1–8 ТЗ (кабель и трубы пересчитаны в 100 м). Цена КП — лист «Ставки ТО». С/с труда = чел.-ч × себестоимость чел.-ч (лист «Персонал ТО»). Расходники — % к оплате труда (ELM).
A4: № | B4: Объект | C4: Код | D4: Услуга | E4: Ед. | F4: Кол-во | G4: Сопоставление с тарификатором | H4: Цена КП, руб/ед/мес | I4: Мес. | J4: КП в год, руб. б/НДС | K4: КП в месяц, руб. | L4: Норма, чел.-ч/ед/мес | M4: Чел.-ч/год | N4: С/с труда, руб. | O4: Расходники, руб. | P4: Субподряд/прочие прямые, руб. | Q4: Прямая с/с, руб. | R4: Маржа строки, руб. | S4: Маржа, %
A5: ПП ТЭЦ-1 (ул. Лебедева, 2) — АПС, СОУЭ (Прил. 1)
A6: 1 | B6: ПП ТЭЦ-1 (ул. Лебедева, 2) | C6: PPK | D6: ТО прибора приёмно-контрольного, пульта, прибора управления (С2000М, Сигнал-20П/10, Гранит, С2000-АСПТ, Рубеж-20П и др.) | E6: шт | F6: 34 | G6: нет в тарификаторе → рынок | H6: ='Ставки ТО'!$N$5 -> 3620.43 | I6: 12 | J6: =K6*I6 -> 1477135.4 | K6: =ROUND(F6*H6,2) -> 123094.62 | L6: ='Ставки ТО'!$D$5 -> 1 | M6: =F6*L6*I6 -> 408 | N6: =M6*'Персонал ТО'!$C$17*(1+'Персонал ТО'!$C$9) -> 473833.73 | O6: =N6*0.02 -> 9476.6746 | P6: 0 | Q6: =N6+O6+P6 -> 483310.41 | R6: =J6-Q6 -> 993825.03 | S6: =IF(J6>0,R6/J6,"") -> 0.67280563
A7: 2 | B7: ПП ТЭЦ-1 (ул. Лебедева, 2) | C7: BLOCK | D7: ТО блока системы (С2000-КДЛ, СП1/СП2, КПБ, БКИ, ПИ, ПТ, БРИЗ, барьеры искрозащиты и др.) | E7: шт | F7: 12 | G7: нет в тарификаторе → рынок | H7: ='Ставки ТО'!$N$6 -> 240.35 | I7: 12 | J7: =K7*I7 -> 34610.4 | K7: =ROUND(F7*H7,2) -> 2884.2 | L7: ='Ставки ТО'!$D$6 -> 0.2 | M7: =F7*L7*I7 -> 28.8 | N7: =M7*'Персонал ТО'!$C$17*(1+'Персонал ТО'!$C$9) -> 33447.087 | O7: =N7*0.02 -> 668.94174 | P7: 0 | Q7: =N7+O7+P7 -> 34116.029 | R7: =J7-Q7 -> 494.37137 | S7: =IF(J7>0,R7/J7,"") -> 0.014283896
A8: 3 | B8: ПП ТЭЦ-1 (ул. Лебедева, 2) | C8: PSU | D8: ТО источника электропитания резервированного (РИП, Скат, ИВЭПР, ББП) | E8: шт | F8: 9 | G8: нет в тарификаторе → рынок | H8: ='Ставки ТО'!$N$7 -> 493.35 | I8: 12 | J8: =K8*I8 -> 53281.8 | K8: =ROUND(F8*H8,2) -> 4440.15 | L8: ='Ставки ТО'!$D$7 -> 0.25 | M8: =F8*L8*I8 -> 27 | N8: =M8*'Персонал ТО'!$C$17*(1+'Персонал ТО'!$C$9) -> 31356.644 | O8: =N8*0.02 -> 627.13288 | P8: 0 | Q8: =N8+O8+P8 -> 31983.777 | R8: =J8-Q8 -> 21298.023 | S8: =IF(J8>0,R8/J8,"") -> 0.39972417
A9: 4 | B9: ПП ТЭЦ-1 (ул. Лебедева, 2) | C9: AKB | D9: ТО аккумуляторной батареи (контроль напряжения и ёмкости) | E9: шт | F9: 21 | G9: нет в тарификаторе → рынок | H9: ='Ставки ТО'!$N$8 -> 240.35 | I9: 12 | J9: =K9*I9 -> 60568.2 | K9: =ROUND(F9*H9,2) -> 5047.35 | L9: ='Ставки ТО'!$D$8 -> 0.05 | M9: =F9*L9*I9 -> 12.6 | N9: =M9*'Персонал ТО'!$C$17*(1+'Персонал ТО'!$C$9) -> 14633.101 | O9: =N9*0.02 -> 292.66201 | P9: 0 | Q9: =N9+O9+P9 -> 14925.763 | R9: =J9-Q9 -> 45642.437 | S9: =IF(J9>0,R9/J9,"") -> 0.75357097
A10: 5 | B10: ПП ТЭЦ-1 (ул. Лебедева, 2) | C10: DET_AUTO | D10: ТО извещателя пожарного автоматического точечного (дымового, теплового) | E10: шт | F10: 1318 | G10: нет в тарификаторе → рынок | H10: ='Ставки ТО'!$N$9 -> 101.2 | I10: 12 | J10: =K10*I10 -> 1600579.2 | K10: =ROUND(F10*H10,2) -> 133381.6 | L10: ='Ставки ТО'!$D$9 -> 0.04 | M10: =F10*L10*I10 -> 632.64 | N10: =M10*'Персонал ТО'!$C$17*(1+'Персонал ТО'!$C$9) -> 734721.01 | O10: =N10*0.02 -> 14694.42 | P10: 0 | Q10: =N10+O10+P10 -> 749415.43 | R10: =J10-Q10 -> 851163.77 | S10: =IF(J10>0,R10/J10,"") -> 0.53178485
A11: 6 | B11: ПП ТЭЦ-1 (ул. Лебедева, 2) | C11: DET_FLAME | D11: ТО извещателя пожарного пламени (Спектрон, Пульсар, Набат) | E11: шт | F11: 12 | G11: нет в тарификаторе → рынок | H11: ='Ставки ТО'!$N$11 -> 126.5 | I11: 12 | J11: =K11*I11 -> 18216 | K11: =ROUND(F11*H11,2) -> 1518 | L11: ='Ставки ТО'!$D$11 -> 0.15 | M11: =F11*L11*I11 -> 21.6 | N11: =M11*'Персонал ТО'!$C$17*(1+'Персонал ТО'!$C$9) -> 25085.315 | O11: =N11*0.02 -> 501.7063 | P11: 0 | Q11: =N11+O11+P11 -> 25587.021 | R11: =J11-Q11 -> -7371.0215 | S11: =IF(J11>0,R11/J11,"") -> -0.40464545
A12: 7 | B12: ПП ТЭЦ-1 (ул. Лебедева, 2) | C12: DET_MAN | D12: ТО извещателя пожарного ручного, УДП, ЭДУ | E12: шт | F12: 144 | G12: нет в тарификаторе → рынок | H12: ='Ставки ТО'!$N$14 -> 88.55 | I12: 12 | J12: =K12*I12 -> 153014.4 | K12: =ROUND(F12*H12,2) -> 12751.2 | L12: ='Ставки ТО'!$D$14 -> 0.04 | M12: =F12*L12*I12 -> 69.12 | N12: =M12*'Персонал ТО'!$C$17*(1+'Персонал ТО'!$C$9) -> 80273.009 | O12: =N12*0.02 -> 1605.4602 | P12: 0 | Q12: =N12+O12+P12 -> 81878.469 | R12: =J12-Q12 -> 71135.931 | S12: =IF(J12>0,R12/J12,"") -> 0.46489697
A13: 8 | B13: ПП ТЭЦ-1 (ул. Лебедева, 2) | C13: ANN | D13: ТО оповещателя (светового, звукового, речевого, табло «Выход») | E13: шт | F13: 205 | G13: нет в тарификаторе → рынок | H13: ='Ставки ТО'!$N$16 -> 123.97 | I13: 12 | J13: =K13*I13 -> 304966.2 | K13: =ROUND(F13*H13,2) -> 25413.85 | L13: ='Ставки ТО'!$D$16 -> 0.04 | M13: =F13*L13*I13 -> 98.4 | N13: =M13*'Персонал ТО'!$C$17*(1+'Персонал ТО'!$C$9) -> 114277.55 | O13: =N13*0.02 -> 2285.5509 | P13: 0 | Q13: =N13+O13+P13 -> 116563.1 | R13: =J13-Q13 -> 188403.1 | S13: =IF(J13>0,R13/J13,"") -> 0.61778355
A14: 9 | B14: ПП ТЭЦ-1 (ул. Лебедева, 2) | C14: SOUE | D14: ТО прибора речевого оповещения СОУЭ (Орфей, Рокот, Соната) | E14: шт | F14: 4 | G14: нет в тарификаторе → рынок | H14: ='Ставки ТО'!$N$17 -> 1265 | I14: 12 | J14: =K14*I14 -> 60720 | K14: =ROUND(F14*H14,2) -> 5060 | L14: ='Ставки ТО'!$D$17 -> 1 | M14: =F14*L14*I14 -> 48 | N14: =M14*'Персонал ТО'!$C$17*(1+'Персонал ТО'!$C$9) -> 55745.145 | O14: =N14*0.02 -> 1114.9029 | P14: 0 | Q14: =N14+O14+P14 -> 56860.048 | R14: =J14-Q14 -> 3859.9523 | S14: =IF(J14>0,R14/J14,"") -> 0.063569702
A15: 10 | B15: ПП ТЭЦ-1 (ул. Лебедева, 2) | C15: CABLE | D15: ТО шлейфов сигнализации и линий связи (осмотр, измерение параметров) | E15: 100 м | F15: 162.2 | G15: нет в тарификаторе → рынок | H15: ='Ставки ТО'!$N$20 -> 25.3 | I15: 12 | J15: =K15*I15 -> 49243.92 | K15: =ROUND(F15*H15,2) -> 4103.66 | L15: ='Ставки ТО'!$D$20 -> 0.02 | M15: =F15*L15*I15 -> 38.928 | N15: =M15*'Персонал ТО'!$C$17*(1+'Персонал ТО'!$C$9) -> 45209.312 | O15: =N15*0.02 -> 904.18625 | P15: 0 | Q15: =N15+O15+P15 -> 46113.499 | R15: =J15-Q15 -> 3130.4213 | S15: =IF(J15>0,R15/J15,"") -> 0.063569702
A16: 11 | B16: ПП ТЭЦ-1 (ул. Лебедева, 2) | C16: BOX | D16: ТО коробок коммутационных/распределительных, шкафов, автоматов питания | E16: шт | F16: 201 | G16: нет в тарификаторе → рынок | H16: ='Ставки ТО'!$N$21 -> 25.3 | I16: 12 | J16: =K16*I16 -> 61023.6 | K16: =ROUND(F16*H16,2) -> 5085.3 | L16: ='Ставки ТО'!$D$21 -> 0.03 | M16: =F16*L16*I16 -> 72.36 | N16: =M16*'Персонал ТО'!$C$17*(1+'Персонал ТО'!$C$9) -> 84035.806 | O16: =N16*0.02 -> 1680.7161 | P16: 0 | Q16: =N16+O16+P16 -> 85716.522 | R16: =J16-Q16 -> -24692.922 | S16: =IF(J16>0,R16/J16,"") -> -0.40464545
D17: Итого по объекту | J17: =SUM(J6:J16) -> 3873359.2 | K17: =SUM(K6:K16) -> 322779.93 | M17: =SUM(M6:M16) -> 1457.448 | N17: =SUM(N6:N16) -> 1692617.7 | O17: =SUM(O6:O16) -> 33852.354 | P17: =SUM(P6:P16) -> 0 | Q17: =SUM(Q6:Q16) -> 1726470.1 | R17: =SUM(R6:R16) -> 2146889.1
A18: ПГУ-223 ПП ТЭЦ-1 — АПС, управление АУПТ (Прил. 2)
A19: 12 | B19: ПГУ-223 ПП ТЭЦ-1 | C19: PPK | D19: ТО прибора приёмно-контрольного, пульта, прибора управления (С2000М, Сигнал-20П/10, Гранит, С2000-АСПТ, Рубеж-20П и др.) | E19: шт | F19: 22 | G19: нет в тарификаторе → рынок | H19: ='Ставки ТО'!$N$5 -> 3620.43 | I19: 12 | J19: =K19*I19 -> 955793.52 | K19: =ROUND(F19*H19,2) -> 79649.46 | L19: ='Ставки ТО'!$D$5 -> 1 | M19: =F19*L19*I19 -> 264 | N19: =M19*'Персонал ТО'!$C$17*(1+'Персонал ТО'!$C$9) -> 306598.3 | O19: =N19*0.02 -> 6131.9659 | P19: 0 | Q19: =N19+O19+P19 -> 312730.26 | R19: =J19-Q19 -> 643063.26 | S19: =IF(J19>0,R19/J19,"") -> 0.67280563
A20: 13 | B20: ПГУ-223 ПП ТЭЦ-1 | C20: BLOCK | D20: ТО блока системы (С2000-КДЛ, СП1/СП2, КПБ, БКИ, ПИ, ПТ, БРИЗ, барьеры искрозащиты и др.) | E20: шт | F20: 45 | G20: нет в тарификаторе → рынок | H20: ='Ставки ТО'!$N$6 -> 240.35 | I20: 12 | J20: =K20*I20 -> 129789 | K20: =ROUND(F20*H20,2) -> 10815.75 | L20: ='Ставки ТО'!$D$6 -> 0.2 | M20: =F20*L20*I20 -> 108 | N20: =M20*'Персонал ТО'!$C$17*(1+'Персонал ТО'!$C$9) -> 125426.58 | O20: =N20*0.02 -> 2508.5315 | P20: 0 | Q20: =N20+O20+P20 -> 127935.11 | R20: =J20-Q20 -> 1853.8926 | S20: =IF(J20>0,R20/J20,"") -> 0.014283896
A21: 14 | B21: ПГУ-223 ПП ТЭЦ-1 | C21: PSU | D21: ТО источника электропитания резервированного (РИП, Скат, ИВЭПР, ББП) | E21: шт | F21: 26 | G21: нет в тарификаторе → рынок | H21: ='Ставки ТО'!$N$7 -> 493.35 | I21: 12 | J21: =K21*I21 -> 153925.2 | K21: =ROUND(F21*H21,2) -> 12827.1 | L21: ='Ставки ТО'!$D$7 -> 0.25 | M21: =F21*L21*I21 -> 78 | N21: =M21*'Персонал ТО'!$C$17*(1+'Персонал ТО'!$C$9) -> 90585.86 | O21: =N21*0.02 -> 1811.7172 | P21: 0 | Q21: =N21+O21+P21 -> 92397.578 | R21: =J21-Q21 -> 61527.622 | S21: =IF(J21>0,R21/J21,"") -> 0.39972417
A22: 15 | B22: ПГУ-223 ПП ТЭЦ-1 | C22: AKB | D22: ТО аккумуляторной батареи (контроль напряжения и ёмкости) | E22: шт | F22: 35 | G22: нет в тарификаторе → рынок | H22: ='Ставки ТО'!$N$8 -> 240.35 | I22: 12 | J22: =K22*I22 -> 100947 | K22: =ROUND(F22*H22,2) -> 8412.25 | L22: ='Ставки ТО'!$D$8 -> 0.05 | M22: =F22*L22*I22 -> 21 | N22: =M22*'Персонал ТО'!$C$17*(1+'Персонал ТО'!$C$9) -> 24388.501 | O22: =N22*0.02 -> 487.77002 | P22: 0 | Q22: =N22+O22+P22 -> 24876.271 | R22: =J22-Q22 -> 76070.729 | S22: =IF(J22>0,R22/J22,"") -> 0.75357097
A23: 16 | B23: ПГУ-223 ПП ТЭЦ-1 | C23: DET_AUTO | D23: ТО извещателя пожарного автоматического точечного (дымового, теплового) | E23: шт | F23: 436 | G23: нет в тарификаторе → рынок | H23: ='Ставки ТО'!$N$9 -> 101.2 | I23: 12 | J23: =K23*I23 -> 529478.4 | K23: =ROUND(F23*H23,2) -> 44123.2 | L23: ='Ставки ТО'!$D$9 -> 0.04 | M23: =F23*L23*I23 -> 209.28 | N23: =M23*'Персонал ТО'!$C$17*(1+'Персонал ТО'!$C$9) -> 243048.83 | O23: =N23*0.02 -> 4860.9766 | P23: 0 | Q23: =N23+O23+P23 -> 247909.81 | R23: =J23-Q23 -> 281568.59 | S23: =IF(J23>0,R23/J23,"") -> 0.53178485
A24: 17 | B24: ПГУ-223 ПП ТЭЦ-1 | C24: DET_EX | D24: ТО извещателя пожарного во взрывозащищённом/искробезопасном исполнении | E24: шт | F24: 12 | G24: нет в тарификаторе → рынок | H24: ='Ставки ТО'!$N$10 -> 246.68 | I24: 12 | J24: =K24*I24 -> 35521.92 | K24: =ROUND(F24*H24,2) -> 2960.16 | L24: ='Ставки ТО'!$D$10 -> 0.15 | M24: =F24*L24*I24 -> 21.6 | N24: =M24*'Персонал ТО'!$C$17*(1+'Персонал ТО'!$C$9) -> 25085.315 | O24: =N24*0.02 -> 501.7063 | P24: 0 | Q24: =N24+O24+P24 -> 25587.021 | R24: =J24-Q24 -> 9934.8985 | S24: =IF(J24>0,R24/J24,"") -> 0.2796836
A25: 18 | B25: ПГУ-223 ПП ТЭЦ-1 | C25: DET_FLAME | D25: ТО извещателя пожарного пламени (Спектрон, Пульсар, Набат) | E25: шт | F25: 14 | G25: нет в тарификаторе → рынок | H25: ='Ставки ТО'!$N$11 -> 126.5 | I25: 12 | J25: =K25*I25 -> 21252 | K25: =ROUND(F25*H25,2) -> 1771 | L25: ='Ставки ТО'!$D$11 -> 0.15 | M25: =F25*L25*I25 -> 25.2 | N25: =M25*'Персонал ТО'!$C$17*(1+'Персонал ТО'!$C$9) -> 29266.201 | O25: =N25*0.02 -> 585.32402 | P25: 0 | Q25: =N25+O25+P25 -> 29851.525 | R25: =J25-Q25 -> -8599.5251 | S25: =IF(J25>0,R25/J25,"") -> -0.40464545
A26: 19 | B26: ПГУ-223 ПП ТЭЦ-1 | C26: THERMO | D26: ТО линейного теплового извещателя (термокабель) | E26: 100 м | F26: 14.2 | G26: нет в тарификаторе → рынок | H26: ='Ставки ТО'!$N$13 -> 379.5 | I26: 12 | J26: =K26*I26 -> 64666.8 | K26: =ROUND(F26*H26,2) -> 5388.9 | L26: ='Ставки ТО'!$D$13 -> 0.15 | M26: =F26*L26*I26 -> 25.56 | N26: =M26*'Персонал ТО'!$C$17*(1+'Персонал ТО'!$C$9) -> 29684.29 | O26: =N26*0.02 -> 593.68579 | P26: 0 | Q26: =N26+O26+P26 -> 30277.975 | R26: =J26-Q26 -> 34388.825 | S26: =IF(J26>0,R26/J26,"") -> 0.53178485
A27: 20 | B27: ПГУ-223 ПП ТЭЦ-1 | C27: DET_MAN | D27: ТО извещателя пожарного ручного, УДП, ЭДУ | E27: шт | F27: 201 | G27: нет в тарификаторе → рынок | H27: ='Ставки ТО'!$N$14 -> 88.55 | I27: 12 | J27: =K27*I27 -> 213582.6 | K27: =ROUND(F27*H27,2) -> 17798.55 | L27: ='Ставки ТО'!$D$14 -> 0.04 | M27: =F27*L27*I27 -> 96.48 | N27: =M27*'Персонал ТО'!$C$17*(1+'Персонал ТО'!$C$9) -> 112047.74 | O27: =N27*0.02 -> 2240.9548 | P27: 0 | Q27: =N27+O27+P27 -> 114288.7 | R27: =J27-Q27 -> 99293.904 | S27: =IF(J27>0,R27/J27,"") -> 0.46489697
A28: 21 | B28: ПГУ-223 ПП ТЭЦ-1 | C28: DET_SEC | D28: ТО извещателя охранного (магнитоконтактного, ИК) в составе систем | E28: шт | F28: 190 | G28: нет в тарификаторе → рынок | H28: ='Ставки ТО'!$N$15 -> 75.9 | I28: 12 | J28: =K28*I28 -> 173052 | K28: =ROUND(F28*H28,2) -> 14421 | L28: ='Ставки ТО'!$D$15 -> 0.03 | M28: =F28*L28*I28 -> 68.4 | N28: =M28*'Персонал ТО'!$C$17*(1+'Персонал ТО'!$C$9) -> 79436.831 | O28: =N28*0.02 -> 1588.7366 | P28: 0 | Q28: =N28+O28+P28 -> 81025.568 | R28: =J28-Q28 -> 92026.432 | S28: =IF(J28>0,R28/J28,"") -> 0.53178485
A29: 22 | B29: ПГУ-223 ПП ТЭЦ-1 | C29: ANN | D29: ТО оповещателя (светового, звукового, речевого, табло «Выход») | E29: шт | F29: 283 | G29: нет в тарификаторе → рынок | H29: ='Ставки ТО'!$N$16 -> 123.97 | I29: 12 | J29: =K29*I29 -> 421002.12 | K29: =ROUND(F29*H29,2) -> 35083.51 | L29: ='Ставки ТО'!$D$16 -> 0.04 | M29: =F29*L29*I29 -> 135.84 | N29: =M29*'Персонал ТО'!$C$17*(1+'Персонал ТО'!$C$9) -> 157758.76 | O29: =N29*0.02 -> 3155.1752 | P29: 0 | Q29: =N29+O29+P29 -> 160913.94 | R29: =J29-Q29 -> 260088.18 | S29: =IF(J29>0,R29/J29,"") -> 0.61778355
A30: 23 | B30: ПГУ-223 ПП ТЭЦ-1 | C30: SW | D30: Сопровождение ПО АРМ «Орион Про» (резервное копирование баз, проверка связи) | E30: к-т | F30: 1 | G30: нет в тарификаторе → рынок | H30: ='Ставки ТО'!$N$19 -> 4301 | I30: 12 | J30: =K30*I30 -> 51612 | K30: =ROUND(F30*H30,2) -> 4301 | L30: ='Ставки ТО'!$D$19 -> 2 | M30: =F30*L30*I30 -> 24 | N30: =M30*'Персонал ТО'!$C$17*(1+'Персонал ТО'!$C$9) -> 27872.572 | O30: =N30*0.02 -> 557.45145 | P30: 0 | Q30: =N30+O30+P30 -> 28430.024 | R30: =J30-Q30 -> 23181.976 | S30: =IF(J30>0,R30/J30,"") -> 0.44915865
A31: 24 | B31: ПГУ-223 ПП ТЭЦ-1 | C31: CABLE | D31: ТО шлейфов сигнализации и линий связи (осмотр, измерение параметров) | E31: 100 м | F31: 121.505 | G31: нет в тарификаторе → рынок | H31: ='Ставки ТО'!$N$20 -> 25.3 | I31: 12 | J31: =K31*I31 -> 36888.96 | K31: =ROUND(F31*H31,2) -> 3074.08 | L31: ='Ставки ТО'!$D$20 -> 0.02 | M31: =F31*L31*I31 -> 29.1612 | N31: =M31*'Персонал ТО'!$C$17*(1+'Персонал ТО'!$C$9) -> 33866.569 | O31: =N31*0.02 -> 677.33138 | P31: 0 | Q31: =N31+O31+P31 -> 34543.9 | R31: =J31-Q31 -> 2345.0595 | S31: =IF(J31>0,R31/J31,"") -> 0.063570768
D32: Итого по объекту | J32: =SUM(J19:J31) -> 2887511.5 | K32: =SUM(K19:K31) -> 240625.96 | M32: =SUM(M19:M31) -> 1106.5212 | N32: =SUM(N19:N31) -> 1285066.3 | O32: =SUM(O19:O31) -> 25701.327 | P32: =SUM(P19:P31) -> 0 | Q32: =SUM(Q19:Q31) -> 1310767.7 | R32: =SUM(R19:R31) -> 1576743.8
A33: ПП ТЭЦ-2, старая часть (пр. Ясный, 1а) — АПС, СОУЭ (Прил. 3)
A34: 25 | B34: ПП ТЭЦ-2, старая часть (пр. Ясный, 1а) | C34: PPK | D34: ТО прибора приёмно-контрольного, пульта, прибора управления (С2000М, Сигнал-20П/10, Гранит, С2000-АСПТ, Рубеж-20П и др.) | E34: шт | F34: 22 | G34: нет в тарификаторе → рынок | H34: ='Ставки ТО'!$N$5 -> 3620.43 | I34: 12 | J34: =K34*I34 -> 955793.52 | K34: =ROUND(F34*H34,2) -> 79649.46 | L34: ='Ставки ТО'!$D$5 -> 1 | M34: =F34*L34*I34 -> 264 | N34: =M34*'Персонал ТО'!$C$17*(1+'Персонал ТО'!$C$9) -> 306598.3 | O34: =N34*0.02 -> 6131.9659 | P34: 0 | Q34: =N34+O34+P34 -> 312730.26 | R34: =J34-Q34 -> 643063.26 | S34: =IF(J34>0,R34/J34,"") -> 0.67280563
A35: 26 | B35: ПП ТЭЦ-2, старая часть (пр. Ясный, 1а) | C35: BLOCK | D35: ТО блока системы (С2000-КДЛ, СП1/СП2, КПБ, БКИ, ПИ, ПТ, БРИЗ, барьеры искрозащиты и др.) | E35: шт | F35: 34 | G35: нет в тарификаторе → рынок | H35: ='Ставки ТО'!$N$6 -> 240.35 | I35: 12 | J35: =K35*I35 -> 98062.8 | K35: =ROUND(F35*H35,2) -> 8171.9 | L35: ='Ставки ТО'!$D$6 -> 0.2 | M35: =F35*L35*I35 -> 81.6 | N35: =M35*'Персонал ТО'!$C$17*(1+'Персонал ТО'!$C$9) -> 94766.746 | O35: =N35*0.02 -> 1895.3349 | P35: 0 | Q35: =N35+O35+P35 -> 96662.081 | R35: =J35-Q35 -> 1400.7189 | S35: =IF(J35>0,R35/J35,"") -> 0.014283896
A36: 27 | B36: ПП ТЭЦ-2, старая часть (пр. Ясный, 1а) | C36: PSU | D36: ТО источника электропитания резервированного (РИП, Скат, ИВЭПР, ББП) | E36: шт | F36: 19 | G36: нет в тарификаторе → рынок | H36: ='Ставки ТО'!$N$7 -> 493.35 | I36: 12 | J36: =K36*I36 -> 112483.8 | K36: =ROUND(F36*H36,2) -> 9373.65 | L36: ='Ставки ТО'!$D$7 -> 0.25 | M36: =F36*L36*I36 -> 57 | N36: =M36*'Персонал ТО'!$C$17*(1+'Персонал ТО'!$C$9) -> 66197.359 | O36: =N36*0.02 -> 1323.9472 | P36: 0 | Q36: =N36+O36+P36 -> 67521.307 | R36: =J36-Q36 -> 44962.493 | S36: =IF(J36>0,R36/J36,"") -> 0.39972417
A37: 28 | B37: ПП ТЭЦ-2, старая часть (пр. Ясный, 1а) | C37: AKB | D37: ТО аккумуляторной батареи (контроль напряжения и ёмкости) | E37: шт | F37: 14 | G37: нет в тарификаторе → рынок | H37: ='Ставки ТО'!$N$8 -> 240.35 | I37: 12 | J37: =K37*I37 -> 40378.8 | K37: =ROUND(F37*H37,2) -> 3364.9 | L37: ='Ставки ТО'!$D$8 -> 0.05 | M37: =F37*L37*I37 -> 8.4 | N37: =M37*'Персонал ТО'!$C$17*(1+'Персонал ТО'!$C$9) -> 9755.4003 | O37: =N37*0.02 -> 195.10801 | P37: 0 | Q37: =N37+O37+P37 -> 9950.5084 | R37: =J37-Q37 -> 30428.292 | S37: =IF(J37>0,R37/J37,"") -> 0.75357097
A38: 29 | B38: ПП ТЭЦ-2, старая часть (пр. Ясный, 1а) | C38: DET_AUTO | D38: ТО извещателя пожарного автоматического точечного (дымового, теплового) | E38: шт | F38: 773 | G38: нет в тарификаторе → рынок | H38: ='Ставки ТО'!$N$9 -> 101.2 | I38: 12 | J38: =K38*I38 -> 938731.2 | K38: =ROUND(F38*H38,2) -> 78227.6 | L38: ='Ставки ТО'!$D$9 -> 0.04 | M38: =F38*L38*I38 -> 371.04 | N38: =M38*'Персонал ТО'!$C$17*(1+'Персонал ТО'!$C$9) -> 430909.97 | O38: =N38*0.02 -> 8618.1994 | P38: 0 | Q38: =N38+O38+P38 -> 439528.17 | R38: =J38-Q38 -> 499203.03 | S38: =IF(J38>0,R38/J38,"") -> 0.53178485
A39: 30 | B39: ПП ТЭЦ-2, старая часть (пр. Ясный, 1а) | C39: DET_EX | D39: ТО извещателя пожарного во взрывозащищённом/искробезопасном исполнении | E39: шт | F39: 25 | G39: нет в тарификаторе → рынок | H39: ='Ставки ТО'!$N$10 -> 246.68 | I39: 12 | J39: =K39*I39 -> 74004 | K39: =ROUND(F39*H39,2) -> 6167 | L39: ='Ставки ТО'!$D$10 -> 0.15 | M39: =F39*L39*I39 -> 45 | N39: =M39*'Персонал ТО'!$C$17*(1+'Персонал ТО'!$C$9) -> 52261.073 | O39: =N39*0.02 -> 1045.2215 | P39: 0 | Q39: =N39+O39+P39 -> 53306.295 | R39: =J39-Q39 -> 20697.705 | S39: =IF(J39>0,R39/J39,"") -> 0.2796836
A40: 31 | B40: ПП ТЭЦ-2, старая часть (пр. Ясный, 1а) | C40: LINEAR | D40: ТО извещателя пожарного дымового линейного ИПДЛ | E40: к-т | F40: 5 | G40: нет в тарификаторе → рынок | H40: ='Ставки ТО'!$N$12 -> 506 | I40: 12 | J40: =K40*I40 -> 30360 | K40: =ROUND(F40*H40,2) -> 2530 | L40: ='Ставки ТО'!$D$12 -> 0.3 | M40: =F40*L40*I40 -> 18 | N40: =M40*'Персонал ТО'!$C$17*(1+'Персонал ТО'!$C$9) -> 20904.429 | O40: =N40*0.02 -> 418.08859 | P40: 0 | Q40: =N40+O40+P40 -> 21322.518 | R40: =J40-Q40 -> 9037.4821 | S40: =IF(J40>0,R40/J40,"") -> 0.29767728
A41: 32 | B41: ПП ТЭЦ-2, старая часть (пр. Ясный, 1а) | C41: THERMO | D41: ТО линейного теплового извещателя (термокабель) | E41: 100 м | F41: 5 | G41: нет в тарификаторе → рынок | H41: ='Ставки ТО'!$N$13 -> 379.5 | I41: 12 | J41: =K41*I41 -> 22770 | K41: =ROUND(F41*H41,2) -> 1897.5 | L41: ='Ставки ТО'!$D$13 -> 0.15 | M41: =F41*L41*I41 -> 9 | N41: =M41*'Персонал ТО'!$C$17*(1+'Персонал ТО'!$C$9) -> 10452.215 | O41: =N41*0.02 -> 209.04429 | P41: 0 | Q41: =N41+O41+P41 -> 10661.259 | R41: =J41-Q41 -> 12108.741 | S41: =IF(J41>0,R41/J41,"") -> 0.53178485
A42: 33 | B42: ПП ТЭЦ-2, старая часть (пр. Ясный, 1а) | C42: DET_MAN | D42: ТО извещателя пожарного ручного, УДП, ЭДУ | E42: шт | F42: 95 | G42: нет в тарификаторе → рынок | H42: ='Ставки ТО'!$N$14 -> 88.55 | I42: 12 | J42: =K42*I42 -> 100947 | K42: =ROUND(F42*H42,2) -> 8412.25 | L42: ='Ставки ТО'!$D$14 -> 0.04 | M42: =F42*L42*I42 -> 45.6 | N42: =M42*'Персонал ТО'!$C$17*(1+'Персонал ТО'!$C$9) -> 52957.888 | O42: =N42*0.02 -> 1059.1578 | P42: 0 | Q42: =N42+O42+P42 -> 54017.045 | R42: =J42-Q42 -> 46929.955 | S42: =IF(J42>0,R42/J42,"") -> 0.46489697
A43: 34 | B43: ПП ТЭЦ-2, старая часть (пр. Ясный, 1а) | C43: DET_SEC | D43: ТО извещателя охранного (магнитоконтактного, ИК) в составе систем | E43: шт | F43: 34 | G43: нет в тарификаторе → рынок | H43: ='Ставки ТО'!$N$15 -> 75.9 | I43: 12 | J43: =K43*I43 -> 30967.2 | K43: =ROUND(F43*H43,2) -> 2580.6 | L43: ='Ставки ТО'!$D$15 -> 0.03 | M43: =F43*L43*I43 -> 12.24 | N43: =M43*'Персонал ТО'!$C$17*(1+'Персонал ТО'!$C$9) -> 14215.012 | O43: =N43*0.02 -> 284.30024 | P43: 0 | Q43: =N43+O43+P43 -> 14499.312 | R43: =J43-Q43 -> 16467.888 | S43: =IF(J43>0,R43/J43,"") -> 0.53178485
A44: 35 | B44: ПП ТЭЦ-2, старая часть (пр. Ясный, 1а) | C44: ANN | D44: ТО оповещателя (светового, звукового, речевого, табло «Выход») | E44: шт | F44: 144 | G44: нет в тарификаторе → рынок | H44: ='Ставки ТО'!$N$16 -> 123.97 | I44: 12 | J44: =K44*I44 -> 214220.16 | K44: =ROUND(F44*H44,2) -> 17851.68 | L44: ='Ставки ТО'!$D$16 -> 0.04 | M44: =F44*L44*I44 -> 69.12 | N44: =M44*'Персонал ТО'!$C$17*(1+'Персонал ТО'!$C$9) -> 80273.009 | O44: =N44*0.02 -> 1605.4602 | P44: 0 | Q44: =N44+O44+P44 -> 81878.469 | R44: =J44-Q44 -> 132341.69 | S44: =IF(J44>0,R44/J44,"") -> 0.61778355
A45: 36 | B45: ПП ТЭЦ-2, старая часть (пр. Ясный, 1а) | C45: SOUE | D45: ТО прибора речевого оповещения СОУЭ (Орфей, Рокот, Соната) | E45: шт | F45: 1 | G45: нет в тарификаторе → рынок | H45: ='Ставки ТО'!$N$17 -> 1265 | I45: 12 | J45: =K45*I45 -> 15180 | K45: =ROUND(F45*H45,2) -> 1265 | L45: ='Ставки ТО'!$D$17 -> 1 | M45: =F45*L45*I45 -> 12 | N45: =M45*'Персонал ТО'!$C$17*(1+'Персонал ТО'!$C$9) -> 13936.286 | O45: =N45*0.02 -> 278.72572 | P45: 0 | Q45: =N45+O45+P45 -> 14215.012 | R45: =J45-Q45 -> 964.98807 | S45: =IF(J45>0,R45/J45,"") -> 0.063569702
A46: 37 | B46: ПП ТЭЦ-2, старая часть (пр. Ясный, 1а) | C46: SW | D46: Сопровождение ПО АРМ «Орион Про» (резервное копирование баз, проверка связи) | E46: к-т | F46: 1 | G46: нет в тарификаторе → рынок | H46: ='Ставки ТО'!$N$19 -> 4301 | I46: 12 | J46: =K46*I46 -> 51612 | K46: =ROUND(F46*H46,2) -> 4301 | L46: ='Ставки ТО'!$D$19 -> 2 | M46: =F46*L46*I46 -> 24 | N46: =M46*'Персонал ТО'!$C$17*(1+'Персонал ТО'!$C$9) -> 27872.572 | O46: =N46*0.02 -> 557.45145 | P46: 0 | Q46: =N46+O46+P46 -> 28430.024 | R46: =J46-Q46 -> 23181.976 | S46: =IF(J46>0,R46/J46,"") -> 0.44915865
A47: 38 | B47: ПП ТЭЦ-2, старая часть (пр. Ясный, 1а) | C47: CABLE | D47: ТО шлейфов сигнализации и линий связи (осмотр, измерение параметров) | E47: 100 м | F47: 83.1 | G47: нет в тарификаторе → рынок | H47: ='Ставки ТО'!$N$20 -> 25.3 | I47: 12 | J47: =K47*I47 -> 25229.16 | K47: =ROUND(F47*H47,2) -> 2102.43 | L47: ='Ставки ТО'!$D$20 -> 0.02 | M47: =F47*L47*I47 -> 19.944 | N47: =M47*'Персонал ТО'!$C$17*(1+'Персонал ТО'!$C$9) -> 23162.108 | O47: =N47*0.02 -> 463.24215 | P47: 0 | Q47: =N47+O47+P47 -> 23625.35 | R47: =J47-Q47 -> 1603.8102 | S47: =IF(J47>0,R47/J47,"") -> 0.063569702
D48: Итого по объекту | J48: =SUM(J34:J47) -> 2710739.6 | K48: =SUM(K34:K47) -> 225894.97 | M48: =SUM(M34:M47) -> 1036.944 | N48: =SUM(N34:N47) -> 1204262.4 | O48: =SUM(O34:O47) -> 24085.247 | P48: =SUM(P34:P47) -> 0 | Q48: =SUM(Q34:Q47) -> 1228347.6 | R48: =SUM(R34:R47) -> 1482392
A49: ПГУ-115 ПП ТЭЦ-2 — АПС, порошковое АУПТ (Прил. 4)
A50: 39 | B50: ПГУ-115 ПП ТЭЦ-2 | C50: PPK | D50: ТО прибора приёмно-контрольного, пульта, прибора управления (С2000М, Сигнал-20П/10, Гранит, С2000-АСПТ, Рубеж-20П и др.) | E50: шт | F50: 5 | G50: нет в тарификаторе → рынок | H50: ='Ставки ТО'!$N$5 -> 3620.43 | I50: 12 | J50: =K50*I50 -> 217225.8 | K50: =ROUND(F50*H50,2) -> 18102.15 | L50: ='Ставки ТО'!$D$5 -> 1 | M50: =F50*L50*I50 -> 60 | N50: =M50*'Персонал ТО'!$C$17*(1+'Персонал ТО'!$C$9) -> 69681.431 | O50: =N50*0.02 -> 1393.6286 | P50: 0 | Q50: =N50+O50+P50 -> 71075.06 | R50: =J50-Q50 -> 146150.74 | S50: =IF(J50>0,R50/J50,"") -> 0.67280563
A51: 40 | B51: ПГУ-115 ПП ТЭЦ-2 | C51: BLOCK | D51: ТО блока системы (С2000-КДЛ, СП1/СП2, КПБ, БКИ, ПИ, ПТ, БРИЗ, барьеры искрозащиты и др.) | E51: шт | F51: 47 | G51: нет в тарификаторе → рынок | H51: ='Ставки ТО'!$N$6 -> 240.35 | I51: 12 | J51: =K51*I51 -> 135557.4 | K51: =ROUND(F51*H51,2) -> 11296.45 | L51: ='Ставки ТО'!$D$6 -> 0.2 | M51: =F51*L51*I51 -> 112.8 | N51: =M51*'Персонал ТО'!$C$17*(1+'Персонал ТО'!$C$9) -> 131001.09 | O51: =N51*0.02 -> 2620.0218 | P51: 0 | Q51: =N51+O51+P51 -> 133621.11 | R51: =J51-Q51 -> 1936.2878 | S51: =IF(J51>0,R51/J51,"") -> 0.014283896
A52: 41 | B52: ПГУ-115 ПП ТЭЦ-2 | C52: PSU | D52: ТО источника электропитания резервированного (РИП, Скат, ИВЭПР, ББП) | E52: шт | F52: 3 | G52: нет в тарификаторе → рынок | H52: ='Ставки ТО'!$N$7 -> 493.35 | I52: 12 | J52: =K52*I52 -> 17760.6 | K52: =ROUND(F52*H52,2) -> 1480.05 | L52: ='Ставки ТО'!$D$7 -> 0.25 | M52: =F52*L52*I52 -> 9 | N52: =M52*'Персонал ТО'!$C$17*(1+'Персонал ТО'!$C$9) -> 10452.215 | O52: =N52*0.02 -> 209.04429 | P52: 0 | Q52: =N52+O52+P52 -> 10661.259 | R52: =J52-Q52 -> 7099.3411 | S52: =IF(J52>0,R52/J52,"") -> 0.39972417
A53: 42 | B53: ПГУ-115 ПП ТЭЦ-2 | C53: DET_AUTO | D53: ТО извещателя пожарного автоматического точечного (дымового, теплового) | E53: шт | F53: 157 | G53: нет в тарификаторе → рынок | H53: ='Ставки ТО'!$N$9 -> 101.2 | I53: 12 | J53: =K53*I53 -> 190660.8 | K53: =ROUND(F53*H53,2) -> 15888.4 | L53: ='Ставки ТО'!$D$9 -> 0.04 | M53: =F53*L53*I53 -> 75.36 | N53: =M53*'Персонал ТО'!$C$17*(1+'Персонал ТО'!$C$9) -> 87519.877 | O53: =N53*0.02 -> 1750.3975 | P53: 0 | Q53: =N53+O53+P53 -> 89270.275 | R53: =J53-Q53 -> 101390.53 | S53: =IF(J53>0,R53/J53,"") -> 0.53178485
A54: 43 | B54: ПГУ-115 ПП ТЭЦ-2 | C54: DET_EX | D54: ТО извещателя пожарного во взрывозащищённом/искробезопасном исполнении | E54: шт | F54: 4 | G54: нет в тарификаторе → рынок | H54: ='Ставки ТО'!$N$10 -> 246.68 | I54: 12 | J54: =K54*I54 -> 11840.64 | K54: =ROUND(F54*H54,2) -> 986.72 | L54: ='Ставки ТО'!$D$10 -> 0.15 | M54: =F54*L54*I54 -> 7.2 | N54: =M54*'Персонал ТО'!$C$17*(1+'Персонал ТО'!$C$9) -> 8361.7717 | O54: =N54*0.02 -> 167.23543 | P54: 0 | Q54: =N54+O54+P54 -> 8529.0072 | R54: =J54-Q54 -> 3311.6328 | S54: =IF(J54>0,R54/J54,"") -> 0.2796836
A55: 44 | B55: ПГУ-115 ПП ТЭЦ-2 | C55: DET_MAN | D55: ТО извещателя пожарного ручного, УДП, ЭДУ | E55: шт | F55: 16 | G55: нет в тарификаторе → рынок | H55: ='Ставки ТО'!$N$14 -> 88.55 | I55: 12 | J55: =K55*I55 -> 17001.6 | K55: =ROUND(F55*H55,2) -> 1416.8 | L55: ='Ставки ТО'!$D$14 -> 0.04 | M55: =F55*L55*I55 -> 7.68 | N55: =M55*'Персонал ТО'!$C$17*(1+'Персонал ТО'!$C$9) -> 8919.2232 | O55: =N55*0.02 -> 178.38446 | P55: 0 | Q55: =N55+O55+P55 -> 9097.6076 | R55: =J55-Q55 -> 7903.9924 | S55: =IF(J55>0,R55/J55,"") -> 0.46489697
A56: 45 | B56: ПГУ-115 ПП ТЭЦ-2 | C56: ANN | D56: ТО оповещателя (светового, звукового, речевого, табло «Выход») | E56: шт | F56: 45 | G56: нет в тарификаторе → рынок | H56: ='Ставки ТО'!$N$16 -> 123.97 | I56: 12 | J56: =K56*I56 -> 66943.8 | K56: =ROUND(F56*H56,2) -> 5578.65 | L56: ='Ставки ТО'!$D$16 -> 0.04 | M56: =F56*L56*I56 -> 21.6 | N56: =M56*'Персонал ТО'!$C$17*(1+'Персонал ТО'!$C$9) -> 25085.315 | O56: =N56*0.02 -> 501.7063 | P56: 0 | Q56: =N56+O56+P56 -> 25587.021 | R56: =J56-Q56 -> 41356.779 | S56: =IF(J56>0,R56/J56,"") -> 0.61778355
A57: 46 | B57: ПГУ-115 ПП ТЭЦ-2 | C57: MPP | D57: ТО модуля порошкового пожаротушения (Буран-8взр) | E57: шт | F57: 4 | G57: нет в тарификаторе → рынок | H57: ='Ставки ТО'!$N$18 -> 1138.5 | I57: 12 | J57: =K57*I57 -> 54648 | K57: =ROUND(F57*H57,2) -> 4554 | L57: ='Ставки ТО'!$D$18 -> 0.3 | M57: =F57*L57*I57 -> 14.4 | N57: =M57*'Персонал ТО'!$C$17*(1+'Персонал ТО'!$C$9) -> 16723.543 | O57: =N57*0.02 -> 334.47087 | P57: 0 | Q57: =N57+O57+P57 -> 17058.014 | R57: =J57-Q57 -> 37589.986 | S57: =IF(J57>0,R57/J57,"") -> 0.68785657
A58: 47 | B58: ПГУ-115 ПП ТЭЦ-2 | C58: SW | D58: Сопровождение ПО АРМ «Орион Про» (резервное копирование баз, проверка связи) | E58: к-т | F58: 1 | G58: нет в тарификаторе → рынок | H58: ='Ставки ТО'!$N$19 -> 4301 | I58: 12 | J58: =K58*I58 -> 51612 | K58: =ROUND(F58*H58,2) -> 4301 | L58: ='Ставки ТО'!$D$19 -> 2 | M58: =F58*L58*I58 -> 24 | N58: =M58*'Персонал ТО'!$C$17*(1+'Персонал ТО'!$C$9) -> 27872.572 | O58: =N58*0.02 -> 557.45145 | P58: 0 | Q58: =N58+O58+P58 -> 28430.024 | R58: =J58-Q58 -> 23181.976 | S58: =IF(J58>0,R58/J58,"") -> 0.44915865
A59: 48 | B59: ПГУ-115 ПП ТЭЦ-2 | C59: CABLE | D59: ТО шлейфов сигнализации и линий связи (осмотр, измерение параметров) | E59: 100 м | F59: 30.8 | G59: нет в тарификаторе → рынок | H59: ='Ставки ТО'!$N$20 -> 25.3 | I59: 12 | J59: =K59*I59 -> 9350.88 | K59: =ROUND(F59*H59,2) -> 779.24 | L59: ='Ставки ТО'!$D$20 -> 0.02 | M59: =F59*L59*I59 -> 7.392 | N59: =M59*'Персонал ТО'!$C$17*(1+'Персонал ТО'!$C$9) -> 8584.7523 | O59: =N59*0.02 -> 171.69505 | P59: 0 | Q59: =N59+O59+P59 -> 8756.4473 | R59: =J59-Q59 -> 594.43265 | S59: =IF(J59>0,R59/J59,"") -> 0.063569702
D60: Итого по объекту | J60: =SUM(J50:J59) -> 772601.52 | K60: =SUM(K50:K59) -> 64383.46 | M60: =SUM(M50:M59) -> 339.432 | N60: =SUM(N50:N59) -> 394201.79 | O60: =SUM(O50:O59) -> 7884.0358 | P60: =SUM(P50:P59) -> 0 | Q60: =SUM(Q50:Q59) -> 402085.83 | R60: =SUM(R50:R59) -> 370515.69
A61: ПП Тепловые сети (ул. С. Перовской, 7; Пешестрелецкая, 84; Ясный, 1а; Лебедева, 2) — АПС, СОУЭ (Прил. 5)
A62: 49 | B62: ПП Тепловые сети (ул. С. Перовской, 7; Пешестрелецкая, 84; Ясный, 1а; Лебедева, 2) | C62: PPK | D62: ТО прибора приёмно-контрольного, пульта, прибора управления (С2000М, Сигнал-20П/10, Гранит, С2000-АСПТ, Рубеж-20П и др.) | E62: шт | F62: 31 | G62: нет в тарификаторе → рынок | H62: ='Ставки ТО'!$N$5 -> 3620.43 | I62: 12 | J62: =K62*I62 -> 1346800 | K62: =ROUND(F62*H62,2) -> 112233.33 | L62: ='Ставки ТО'!$D$5 -> 1 | M62: =F62*L62*I62 -> 372 | N62: =M62*'Персонал ТО'!$C$17*(1+'Персонал ТО'!$C$9) -> 432024.87 | O62: =N62*0.02 -> 8640.4974 | P62: 0 | Q62: =N62+O62+P62 -> 440665.37 | R62: =J62-Q62 -> 906134.59 | S62: =IF(J62>0,R62/J62,"") -> 0.67280563
A63: 50 | B63: ПП Тепловые сети (ул. С. Перовской, 7; Пешестрелецкая, 84; Ясный, 1а; Лебедева, 2) | C63: BLOCK | D63: ТО блока системы (С2000-КДЛ, СП1/СП2, КПБ, БКИ, ПИ, ПТ, БРИЗ, барьеры искрозащиты и др.) | E63: шт | F63: 7 | G63: нет в тарификаторе → рынок | H63: ='Ставки ТО'!$N$6 -> 240.35 | I63: 12 | J63: =K63*I63 -> 20189.4 | K63: =ROUND(F63*H63,2) -> 1682.45 | L63: ='Ставки ТО'!$D$6 -> 0.2 | M63: =F63*L63*I63 -> 16.8 | N63: =M63*'Персонал ТО'!$C$17*(1+'Персонал ТО'!$C$9) -> 19510.801 | O63: =N63*0.02 -> 390.21601 | P63: 0 | Q63: =N63+O63+P63 -> 19901.017 | R63: =J63-Q63 -> 288.3833 | S63: =IF(J63>0,R63/J63,"") -> 0.014283896
A64: 51 | B64: ПП Тепловые сети (ул. С. Перовской, 7; Пешестрелецкая, 84; Ясный, 1а; Лебедева, 2) | C64: PSU | D64: ТО источника электропитания резервированного (РИП, Скат, ИВЭПР, ББП) | E64: шт | F64: 9 | G64: нет в тарификаторе → рынок | H64: ='Ставки ТО'!$N$7 -> 493.35 | I64: 12 | J64: =K64*I64 -> 53281.8 | K64: =ROUND(F64*H64,2) -> 4440.15 | L64: ='Ставки ТО'!$D$7 -> 0.25 | M64: =F64*L64*I64 -> 27 | N64: =M64*'Персонал ТО'!$C$17*(1+'Персонал ТО'!$C$9) -> 31356.644 | O64: =N64*0.02 -> 627.13288 | P64: 0 | Q64: =N64+O64+P64 -> 31983.777 | R64: =J64-Q64 -> 21298.023 | S64: =IF(J64>0,R64/J64,"") -> 0.39972417
A65: 52 | B65: ПП Тепловые сети (ул. С. Перовской, 7; Пешестрелецкая, 84; Ясный, 1а; Лебедева, 2) | C65: AKB | D65: ТО аккумуляторной батареи (контроль напряжения и ёмкости) | E65: шт | F65: 4 | G65: нет в тарификаторе → рынок | H65: ='Ставки ТО'!$N$8 -> 240.35 | I65: 12 | J65: =K65*I65 -> 11536.8 | K65: =ROUND(F65*H65,2) -> 961.4 | L65: ='Ставки ТО'!$D$8 -> 0.05 | M65: =F65*L65*I65 -> 2.4 | N65: =M65*'Персонал ТО'!$C$17*(1+'Персонал ТО'!$C$9) -> 2787.2572 | O65: =N65*0.02 -> 55.745145 | P65: 0 | Q65: =N65+O65+P65 -> 2843.0024 | R65: =J65-Q65 -> 8693.7976 | S65: =IF(J65>0,R65/J65,"") -> 0.75357097
A66: 53 | B66: ПП Тепловые сети (ул. С. Перовской, 7; Пешестрелецкая, 84; Ясный, 1а; Лебедева, 2) | C66: DET_AUTO | D66: ТО извещателя пожарного автоматического точечного (дымового, теплового) | E66: шт | F66: 698 | G66: нет в тарификаторе → рынок | H66: ='Ставки ТО'!$N$9 -> 101.2 | I66: 12 | J66: =K66*I66 -> 847651.2 | K66: =ROUND(F66*H66,2) -> 70637.6 | L66: ='Ставки ТО'!$D$9 -> 0.04 | M66: =F66*L66*I66 -> 335.04 | N66: =M66*'Персонал ТО'!$C$17*(1+'Персонал ТО'!$C$9) -> 389101.11 | O66: =N66*0.02 -> 7782.0222 | P66: 0 | Q66: =N66+O66+P66 -> 396883.13 | R66: =J66-Q66 -> 450768.07 | S66: =IF(J66>0,R66/J66,"") -> 0.53178485
A67: 54 | B67: ПП Тепловые сети (ул. С. Перовской, 7; Пешестрелецкая, 84; Ясный, 1а; Лебедева, 2) | C67: DET_EX | D67: ТО извещателя пожарного во взрывозащищённом/искробезопасном исполнении | E67: шт | F67: 29 | G67: нет в тарификаторе → рынок | H67: ='Ставки ТО'!$N$10 -> 246.68 | I67: 12 | J67: =K67*I67 -> 85844.64 | K67: =ROUND(F67*H67,2) -> 7153.72 | L67: ='Ставки ТО'!$D$10 -> 0.15 | M67: =F67*L67*I67 -> 52.2 | N67: =M67*'Персонал ТО'!$C$17*(1+'Персонал ТО'!$C$9) -> 60622.845 | O67: =N67*0.02 -> 1212.4569 | P67: 0 | Q67: =N67+O67+P67 -> 61835.302 | R67: =J67-Q67 -> 24009.338 | S67: =IF(J67>0,R67/J67,"") -> 0.2796836
A68: 55 | B68: ПП Тепловые сети (ул. С. Перовской, 7; Пешестрелецкая, 84; Ясный, 1а; Лебедева, 2) | C68: DET_MAN | D68: ТО извещателя пожарного ручного, УДП, ЭДУ | E68: шт | F68: 83 | G68: нет в тарификаторе → рынок | H68: ='Ставки ТО'!$N$14 -> 88.55 | I68: 12 | J68: =K68*I68 -> 88195.8 | K68: =ROUND(F68*H68,2) -> 7349.65 | L68: ='Ставки ТО'!$D$14 -> 0.04 | M68: =F68*L68*I68 -> 39.84 | N68: =M68*'Персонал ТО'!$C$17*(1+'Персонал ТО'!$C$9) -> 46268.47 | O68: =N68*0.02 -> 925.3694 | P68: 0 | Q68: =N68+O68+P68 -> 47193.84 | R68: =J68-Q68 -> 41001.96 | S68: =IF(J68>0,R68/J68,"") -> 0.46489697
A69: 56 | B69: ПП Тепловые сети (ул. С. Перовской, 7; Пешестрелецкая, 84; Ясный, 1а; Лебедева, 2) | C69: ANN | D69: ТО оповещателя (светового, звукового, речевого, табло «Выход») | E69: шт | F69: 162 | G69: нет в тарификаторе → рынок | H69: ='Ставки ТО'!$N$16 -> 123.97 | I69: 12 | J69: =K69*I69 -> 240997.68 | K69: =ROUND(F69*H69,2) -> 20083.14 | L69: ='Ставки ТО'!$D$16 -> 0.04 | M69: =F69*L69*I69 -> 77.76 | N69: =M69*'Персонал ТО'!$C$17*(1+'Персонал ТО'!$C$9) -> 90307.135 | O69: =N69*0.02 -> 1806.1427 | P69: 0 | Q69: =N69+O69+P69 -> 92113.277 | R69: =J69-Q69 -> 148884.4 | S69: =IF(J69>0,R69/J69,"") -> 0.61778355
A70: 57 | B70: ПП Тепловые сети (ул. С. Перовской, 7; Пешестрелецкая, 84; Ясный, 1а; Лебедева, 2) | C70: CABLE | D70: ТО шлейфов сигнализации и линий связи (осмотр, измерение параметров) | E70: 100 м | F70: 94.75 | G70: нет в тарификаторе → рынок | H70: ='Ставки ТО'!$N$20 -> 25.3 | I70: 12 | J70: =K70*I70 -> 28766.16 | K70: =ROUND(F70*H70,2) -> 2397.18 | L70: ='Ставки ТО'!$D$20 -> 0.02 | M70: =F70*L70*I70 -> 22.74 | N70: =M70*'Персонал ТО'!$C$17*(1+'Персонал ТО'!$C$9) -> 26409.262 | O70: =N70*0.02 -> 528.18525 | P70: 0 | Q70: =N70+O70+P70 -> 26937.448 | R70: =J70-Q70 -> 1828.7124 | S70: =IF(J70>0,R70/J70,"") -> 0.063571655
D71: Итого по объекту | J71: =SUM(J62:J70) -> 2723263.4 | K71: =SUM(K62:K70) -> 226938.62 | M71: =SUM(M62:M70) -> 945.78 | N71: =SUM(N62:N70) -> 1098388.4 | O71: =SUM(O62:O70) -> 21967.768 | P71: =SUM(P62:P70) -> 0 | Q71: =SUM(Q62:Q70) -> 1120356.2 | R71: =SUM(R62:R70) -> 1602907.3
A72: АУПТ ПП ТЭЦ-1 — водяное пожаротушение (Прил. 6)
A73: 58 | B73: АУПТ ПП ТЭЦ-1 | C73: PIPE | D73: ТО трубопроводов АУПТ (течи, уклоны, крепления, окраска) | E73: 100 м | F73: 43.23 | G73: нет в тарификаторе → рынок | H73: ='Ставки ТО'!$N$22 -> 506 | I73: 12 | J73: =K73*I73 -> 262492.56 | K73: =ROUND(F73*H73,2) -> 21874.38 | L73: ='Ставки ТО'!$D$22 -> 0.25 | M73: =F73*L73*I73 -> 129.69 | N73: =M73*'Персонал ТО'!$C$17*(1+'Персонал ТО'!$C$9) -> 150616.41 | O73: =N73*0.02 -> 3012.3283 | P73: 0 | Q73: =N73+O73+P73 -> 153628.74 | R73: =J73-Q73 -> 108863.82 | S73: =IF(J73>0,R73/J73,"") -> 0.41473106
A74: 59 | B74: АУПТ ПП ТЭЦ-1 | C74: VALVE_MAN | D74: ТО запорной арматуры с ручным приводом (задвижки, затворы, вентили, клапаны, краны) | E74: шт | F74: 119 | G74: нет в тарификаторе → рынок | H74: ='Ставки ТО'!$N$23 -> 379.5 | I74: 12 | J74: =K74*I74 -> 541926 | K74: =ROUND(F74*H74,2) -> 45160.5 | L74: ='Ставки ТО'!$D$23 -> 0.25 | M74: =F74*L74*I74 -> 357 | N74: =M74*'Персонал ТО'!$C$17*(1+'Персонал ТО'!$C$9) -> 414604.51 | O74: =N74*0.02 -> 8292.0903 | P74: 0 | Q74: =N74+O74+P74 -> 422896.6 | R74: =J74-Q74 -> 119029.4 | S74: =IF(J74>0,R74/J74,"") -> 0.21964142
A75: 60 | B75: АУПТ ПП ТЭЦ-1 | C75: VALVE_EL | D75: ТО задвижки/затвора с электроприводом и схемой управления | E75: шт | F75: 31 | G75: нет в тарификаторе → рынок | H75: ='Ставки ТО'!$N$24 -> 1960.75 | I75: 12 | J75: =K75*I75 -> 729399 | K75: =ROUND(F75*H75,2) -> 60783.25 | L75: ='Ставки ТО'!$D$24 -> 1 | M75: =F75*L75*I75 -> 372 | N75: =M75*'Персонал ТО'!$C$17*(1+'Персонал ТО'!$C$9) -> 432024.87 | O75: =N75*0.02 -> 8640.4974 | P75: 0 | Q75: =N75+O75+P75 -> 440665.37 | R75: =J75-Q75 -> 288733.63 | S75: =IF(J75>0,R75/J75,"") -> 0.39585142
A76: 61 | B76: АУПТ ПП ТЭЦ-1 | C76: SPRINK | D76: ТО оросителя, пеногенератора, лафетного ствола (осмотр, очистка) | E76: шт | F76: 738 | G76: нет в тарификаторе → рынок | H76: ='Ставки ТО'!$N$25 -> 35.42 | I76: 12 | J76: =K76*I76 -> 313679.52 | K76: =ROUND(F76*H76,2) -> 26139.96 | L76: ='Ставки ТО'!$D$25 -> 0.03 | M76: =F76*L76*I76 -> 265.68 | N76: =M76*'Персонал ТО'!$C$17*(1+'Персонал ТО'!$C$9) -> 308549.38 | O76: =N76*0.02 -> 6170.9875 | P76: 0 | Q76: =N76+O76+P76 -> 314720.36 | R76: =J76-Q76 -> -1040.8442 | S76: =IF(J76>0,R76/J76,"") -> -0.0033181769
A77: 62 | B77: АУПТ ПП ТЭЦ-1 | C77: GAUGE | D77: ТО манометра, сигнализатора/реле давления | E77: шт | F77: 4 | G77: нет в тарификаторе → рынок | H77: ='Ставки ТО'!$N$26 -> 349.14 | I77: 12 | J77: =K77*I77 -> 16758.72 | K77: =ROUND(F77*H77,2) -> 1396.56 | L77: ='Ставки ТО'!$D$26 -> 0.25 | M77: =F77*L77*I77 -> 12 | N77: =M77*'Персонал ТО'!$C$17*(1+'Персонал ТО'!$C$9) -> 13936.286 | O77: =N77*0.02 -> 278.72572 | P77: 0 | Q77: =N77+O77+P77 -> 14215.012 | R77: =J77-Q77 -> 2543.7081 | S77: =IF(J77>0,R77/J77,"") -> 0.15178415
D78: Итого по объекту | J78: =SUM(J73:J77) -> 1864255.8 | K78: =SUM(K73:K77) -> 155354.65 | M78: =SUM(M73:M77) -> 1136.37 | N78: =SUM(N73:N77) -> 1319731.5 | O78: =SUM(O73:O77) -> 26394.629 | P78: =SUM(P73:P77) -> 0 | Q78: =SUM(Q73:Q77) -> 1346126.1 | R78: =SUM(R73:R77) -> 518129.71
A79: АУПТ ПП ТЭЦ-2 — водяное и пенное пожаротушение (Прил. 7)
A80: 63 | B80: АУПТ ПП ТЭЦ-2 | C80: PIPE | D80: ТО трубопроводов АУПТ (течи, уклоны, крепления, окраска) | E80: 100 м | F80: 53.12 | G80: нет в тарификаторе → рынок | H80: ='Ставки ТО'!$N$22 -> 506 | I80: 12 | J80: =K80*I80 -> 322544.64 | K80: =ROUND(F80*H80,2) -> 26878.72 | L80: ='Ставки ТО'!$D$22 -> 0.25 | M80: =F80*L80*I80 -> 159.36 | N80: =M80*'Персонал ТО'!$C$17*(1+'Персонал ТО'!$C$9) -> 185073.88 | O80: =N80*0.02 -> 3701.4776 | P80: 0 | Q80: =N80+O80+P80 -> 188775.36 | R80: =J80-Q80 -> 133769.28 | S80: =IF(J80>0,R80/J80,"") -> 0.41473106
A81: 64 | B81: АУПТ ПП ТЭЦ-2 | C81: VALVE_MAN | D81: ТО запорной арматуры с ручным приводом (задвижки, затворы, вентили, клапаны, краны) | E81: шт | F81: 98 | G81: нет в тарификаторе → рынок | H81: ='Ставки ТО'!$N$23 -> 379.5 | I81: 12 | J81: =K81*I81 -> 446292 | K81: =ROUND(F81*H81,2) -> 37191 | L81: ='Ставки ТО'!$D$23 -> 0.25 | M81: =F81*L81*I81 -> 294 | N81: =M81*'Персонал ТО'!$C$17*(1+'Персонал ТО'!$C$9) -> 341439.01 | O81: =N81*0.02 -> 6828.7802 | P81: 0 | Q81: =N81+O81+P81 -> 348267.79 | R81: =J81-Q81 -> 98024.208 | S81: =IF(J81>0,R81/J81,"") -> 0.21964142
A82: 65 | B82: АУПТ ПП ТЭЦ-2 | C82: VALVE_EL | D82: ТО задвижки/затвора с электроприводом и схемой управления | E82: шт | F82: 33 | G82: нет в тарификаторе → рынок | H82: ='Ставки ТО'!$N$24 -> 1960.75 | I82: 12 | J82: =K82*I82 -> 776457 | K82: =ROUND(F82*H82,2) -> 64704.75 | L82: ='Ставки ТО'!$D$24 -> 1 | M82: =F82*L82*I82 -> 396 | N82: =M82*'Персонал ТО'!$C$17*(1+'Персонал ТО'!$C$9) -> 459897.44 | O82: =N82*0.02 -> 9197.9489 | P82: 0 | Q82: =N82+O82+P82 -> 469095.39 | R82: =J82-Q82 -> 307361.61 | S82: =IF(J82>0,R82/J82,"") -> 0.39585142
A83: 66 | B83: АУПТ ПП ТЭЦ-2 | C83: SPRINK | D83: ТО оросителя, пеногенератора, лафетного ствола (осмотр, очистка) | E83: шт | F83: 249 | G83: нет в тарификаторе → рынок | H83: ='Ставки ТО'!$N$25 -> 35.42 | I83: 12 | J83: =K83*I83 -> 105834.96 | K83: =ROUND(F83*H83,2) -> 8819.58 | L83: ='Ставки ТО'!$D$25 -> 0.03 | M83: =F83*L83*I83 -> 89.64 | N83: =M83*'Персонал ТО'!$C$17*(1+'Персонал ТО'!$C$9) -> 104104.06 | O83: =N83*0.02 -> 2082.0812 | P83: 0 | Q83: =N83+O83+P83 -> 106186.14 | R83: =J83-Q83 -> -351.17912 | S83: =IF(J83>0,R83/J83,"") -> -0.0033181769
A84: 67 | B84: АУПТ ПП ТЭЦ-2 | C84: GAUGE | D84: ТО манометра, сигнализатора/реле давления | E84: шт | F84: 36 | G84: нет в тарификаторе → рынок | H84: ='Ставки ТО'!$N$26 -> 349.14 | I84: 12 | J84: =K84*I84 -> 150828.48 | K84: =ROUND(F84*H84,2) -> 12569.04 | L84: ='Ставки ТО'!$D$26 -> 0.25 | M84: =F84*L84*I84 -> 108 | N84: =M84*'Персонал ТО'!$C$17*(1+'Персонал ТО'!$C$9) -> 125426.58 | O84: =N84*0.02 -> 2508.5315 | P84: 0 | Q84: =N84+O84+P84 -> 127935.11 | R84: =J84-Q84 -> 22893.373 | S84: =IF(J84>0,R84/J84,"") -> 0.15178415
A85: 68 | B85: АУПТ ПП ТЭЦ-2 | C85: PUMP | D85: ТО насосного агрегата пожаротушения | E85: шт | F85: 8 | G85: нет в тарификаторе → рынок | H85: ='Ставки ТО'!$N$27 -> 6694.38 | I85: 12 | J85: =K85*I85 -> 642660.48 | K85: =ROUND(F85*H85,2) -> 53555.04 | L85: ='Ставки ТО'!$D$27 -> 4 | M85: =F85*L85*I85 -> 384 | N85: =M85*'Персонал ТО'!$C$17*(1+'Персонал ТО'!$C$9) -> 445961.16 | O85: =N85*0.02 -> 8919.2232 | P85: 0 | Q85: =N85+O85+P85 -> 454880.38 | R85: =J85-Q85 -> 187780.1 | S85: =IF(J85>0,R85/J85,"") -> 0.29219176
A86: 69 | B86: АУПТ ПП ТЭЦ-2 | C86: TANK | D86: ТО бака (пенообразователя, мембранного) | E86: шт | F86: 3 | G86: нет в тарификаторе → рынок | H86: ='Ставки ТО'!$N$28 -> 759 | I86: 12 | J86: =K86*I86 -> 27324 | K86: =ROUND(F86*H86,2) -> 2277 | L86: ='Ставки ТО'!$D$28 -> 1 | M86: =F86*L86*I86 -> 36 | N86: =M86*'Персонал ТО'!$C$17*(1+'Персонал ТО'!$C$9) -> 41808.859 | O86: =N86*0.02 -> 836.17717 | P86: 0 | Q86: =N86+O86+P86 -> 42645.036 | R86: =J86-Q86 -> -15321.036 | S86: =IF(J86>0,R86/J86,"") -> -0.56071716
D87: Итого по объекту | J87: =SUM(J80:J86) -> 2471941.6 | K87: =SUM(K80:K86) -> 205995.13 | M87: =SUM(M80:M86) -> 1467 | N87: =SUM(N80:N86) -> 1703711 | O87: =SUM(O80:O86) -> 34074.22 | P87: =SUM(P80:P86) -> 0 | Q87: =SUM(Q80:Q86) -> 1737785.2 | R87: =SUM(R80:R86) -> 734156.35
A88: ПП Городские тепловые сети (Кольцовская, 78; Плехановская, 17; Туполева, 31к; Б. Хмельницкого, 79к) — АПС, СОУЭ (Прил. 8)
A89: 70 | B89: ПП Городские тепловые сети (Кольцовская, 78; Плехановская, 17; Туполева, 31к; Б. Хмельницкого, 79к) | C89: PPK | D89: ТО прибора приёмно-контрольного, пульта, прибора управления (С2000М, Сигнал-20П/10, Гранит, С2000-АСПТ, Рубеж-20П и др.) | E89: шт | F89: 6 | G89: нет в тарификаторе → рынок | H89: ='Ставки ТО'!$N$5 -> 3620.43 | I89: 12 | J89: =K89*I89 -> 260670.96 | K89: =ROUND(F89*H89,2) -> 21722.58 | L89: ='Ставки ТО'!$D$5 -> 1 | M89: =F89*L89*I89 -> 72 | N89: =M89*'Персонал ТО'!$C$17*(1+'Персонал ТО'!$C$9) -> 83617.717 | O89: =N89*0.02 -> 1672.3543 | P89: 0 | Q89: =N89+O89+P89 -> 85290.072 | R89: =J89-Q89 -> 175380.89 | S89: =IF(J89>0,R89/J89,"") -> 0.67280563
A90: 71 | B90: ПП Городские тепловые сети (Кольцовская, 78; Плехановская, 17; Туполева, 31к; Б. Хмельницкого, 79к) | C90: BLOCK | D90: ТО блока системы (С2000-КДЛ, СП1/СП2, КПБ, БКИ, ПИ, ПТ, БРИЗ, барьеры искрозащиты и др.) | E90: шт | F90: 1 | G90: нет в тарификаторе → рынок | H90: ='Ставки ТО'!$N$6 -> 240.35 | I90: 12 | J90: =K90*I90 -> 2884.2 | K90: =ROUND(F90*H90,2) -> 240.35 | L90: ='Ставки ТО'!$D$6 -> 0.2 | M90: =F90*L90*I90 -> 2.4 | N90: =M90*'Персонал ТО'!$C$17*(1+'Персонал ТО'!$C$9) -> 2787.2572 | O90: =N90*0.02 -> 55.745145 | P90: 0 | Q90: =N90+O90+P90 -> 2843.0024 | R90: =J90-Q90 -> 41.197614 | S90: =IF(J90>0,R90/J90,"") -> 0.014283896
A91: 72 | B91: ПП Городские тепловые сети (Кольцовская, 78; Плехановская, 17; Туполева, 31к; Б. Хмельницкого, 79к) | C91: PSU | D91: ТО источника электропитания резервированного (РИП, Скат, ИВЭПР, ББП) | E91: шт | F91: 1 | G91: нет в тарификаторе → рынок | H91: ='Ставки ТО'!$N$7 -> 493.35 | I91: 12 | J91: =K91*I91 -> 5920.2 | K91: =ROUND(F91*H91,2) -> 493.35 | L91: ='Ставки ТО'!$D$7 -> 0.25 | M91: =F91*L91*I91 -> 3 | N91: =M91*'Персонал ТО'!$C$17*(1+'Персонал ТО'!$C$9) -> 3484.0716 | O91: =N91*0.02 -> 69.681431 | P91: 0 | Q91: =N91+O91+P91 -> 3553.753 | R91: =J91-Q91 -> 2366.447 | S91: =IF(J91>0,R91/J91,"") -> 0.39972417
A92: 73 | B92: ПП Городские тепловые сети (Кольцовская, 78; Плехановская, 17; Туполева, 31к; Б. Хмельницкого, 79к) | C92: AKB | D92: ТО аккумуляторной батареи (контроль напряжения и ёмкости) | E92: шт | F92: 2 | G92: нет в тарификаторе → рынок | H92: ='Ставки ТО'!$N$8 -> 240.35 | I92: 12 | J92: =K92*I92 -> 5768.4 | K92: =ROUND(F92*H92,2) -> 480.7 | L92: ='Ставки ТО'!$D$8 -> 0.05 | M92: =F92*L92*I92 -> 1.2 | N92: =M92*'Персонал ТО'!$C$17*(1+'Персонал ТО'!$C$9) -> 1393.6286 | O92: =N92*0.02 -> 27.872572 | P92: 0 | Q92: =N92+O92+P92 -> 1421.5012 | R92: =J92-Q92 -> 4346.8988 | S92: =IF(J92>0,R92/J92,"") -> 0.75357097
A93: 74 | B93: ПП Городские тепловые сети (Кольцовская, 78; Плехановская, 17; Туполева, 31к; Б. Хмельницкого, 79к) | C93: DET_AUTO | D93: ТО извещателя пожарного автоматического точечного (дымового, теплового) | E93: шт | F93: 187 | G93: нет в тарификаторе → рынок | H93: ='Ставки ТО'!$N$9 -> 101.2 | I93: 12 | J93: =K93*I93 -> 227092.8 | K93: =ROUND(F93*H93,2) -> 18924.4 | L93: ='Ставки ТО'!$D$9 -> 0.04 | M93: =F93*L93*I93 -> 89.76 | N93: =M93*'Персонал ТО'!$C$17*(1+'Персонал ТО'!$C$9) -> 104243.42 | O93: =N93*0.02 -> 2084.8684 | P93: 0 | Q93: =N93+O93+P93 -> 106328.29 | R93: =J93-Q93 -> 120764.51 | S93: =IF(J93>0,R93/J93,"") -> 0.53178485
A94: 75 | B94: ПП Городские тепловые сети (Кольцовская, 78; Плехановская, 17; Туполева, 31к; Б. Хмельницкого, 79к) | C94: DET_MAN | D94: ТО извещателя пожарного ручного, УДП, ЭДУ | E94: шт | F94: 19 | G94: нет в тарификаторе → рынок | H94: ='Ставки ТО'!$N$14 -> 88.55 | I94: 12 | J94: =K94*I94 -> 20189.4 | K94: =ROUND(F94*H94,2) -> 1682.45 | L94: ='Ставки ТО'!$D$14 -> 0.04 | M94: =F94*L94*I94 -> 9.12 | N94: =M94*'Персонал ТО'!$C$17*(1+'Персонал ТО'!$C$9) -> 10591.578 | O94: =N94*0.02 -> 211.83155 | P94: 0 | Q94: =N94+O94+P94 -> 10803.409 | R94: =J94-Q94 -> 9385.9909 | S94: =IF(J94>0,R94/J94,"") -> 0.46489697
A95: 76 | B95: ПП Городские тепловые сети (Кольцовская, 78; Плехановская, 17; Туполева, 31к; Б. Хмельницкого, 79к) | C95: ANN | D95: ТО оповещателя (светового, звукового, речевого, табло «Выход») | E95: шт | F95: 41 | G95: нет в тарификаторе → рынок | H95: ='Ставки ТО'!$N$16 -> 123.97 | I95: 12 | J95: =K95*I95 -> 60993.24 | K95: =ROUND(F95*H95,2) -> 5082.77 | L95: ='Ставки ТО'!$D$16 -> 0.04 | M95: =F95*L95*I95 -> 19.68 | N95: =M95*'Персонал ТО'!$C$17*(1+'Персонал ТО'!$C$9) -> 22855.509 | O95: =N95*0.02 -> 457.11019 | P95: 0 | Q95: =N95+O95+P95 -> 23312.62 | R95: =J95-Q95 -> 37680.62 | S95: =IF(J95>0,R95/J95,"") -> 0.61778355
A96: 77 | B96: ПП Городские тепловые сети (Кольцовская, 78; Плехановская, 17; Туполева, 31к; Б. Хмельницкого, 79к) | C96: CABLE | D96: ТО шлейфов сигнализации и линий связи (осмотр, измерение параметров) | E96: 100 м | F96: 34.2 | G96: нет в тарификаторе → рынок | H96: ='Ставки ТО'!$N$20 -> 25.3 | I96: 12 | J96: =K96*I96 -> 10383.12 | K96: =ROUND(F96*H96,2) -> 865.26 | L96: ='Ставки ТО'!$D$20 -> 0.02 | M96: =F96*L96*I96 -> 8.208 | N96: =M96*'Персонал ТО'!$C$17*(1+'Персонал ТО'!$C$9) -> 9532.4198 | O96: =N96*0.02 -> 190.6484 | P96: 0 | Q96: =N96+O96+P96 -> 9723.0682 | R96: =J96-Q96 -> 660.05184 | S96: =IF(J96>0,R96/J96,"") -> 0.063569702
A97: 78 | B97: ПП Городские тепловые сети (Кольцовская, 78; Плехановская, 17; Туполева, 31к; Б. Хмельницкого, 79к) | C97: BOX | D97: ТО коробок коммутационных/распределительных, шкафов, автоматов питания | E97: шт | F97: 2 | G97: нет в тарификаторе → рынок | H97: ='Ставки ТО'!$N$21 -> 25.3 | I97: 12 | J97: =K97*I97 -> 607.2 | K97: =ROUND(F97*H97,2) -> 50.6 | L97: ='Ставки ТО'!$D$21 -> 0.03 | M97: =F97*L97*I97 -> 0.72 | N97: =M97*'Персонал ТО'!$C$17*(1+'Персонал ТО'!$C$9) -> 836.17717 | O97: =N97*0.02 -> 16.723543 | P97: 0 | Q97: =N97+O97+P97 -> 852.90072 | R97: =J97-Q97 -> -245.70072 | S97: =IF(J97>0,R97/J97,"") -> -0.40464545
D98: Итого по объекту | J98: =SUM(J89:J97) -> 594509.52 | K98: =SUM(K89:K97) -> 49542.46 | M98: =SUM(M89:M97) -> 206.088 | N98: =SUM(N89:N97) -> 239341.78 | O98: =SUM(O89:O97) -> 4786.8356 | P98: =SUM(P89:P97) -> 0 | Q98: =SUM(Q89:Q97) -> 244128.61 | R98: =SUM(R89:R97) -> 350380.91
D99: ИТОГО РЕГЛАМЕНТНОЕ ТО | J99: =J6+J7+J8+J9+J10+J11+J12+J13+J14+J15+J16+J19+J20+J21+J22+J23+J24+J25+J26+J27+J28+J29+J30+J31+J34+J35+J36+J37+J38+J39+J40+J41+J42+J43+J44+J45+J46+J47+J50+J51+J52+J53+J54+J55+J56+J57+J58+J59+J62+J63+J64+J65+J66+J67+J68+J69+J70+J73+J74+J75+J76+J77+J80+J81+J82+J83+J84+J85+J86+J89+J90+J91+J92+J93+J94+J95+J96+J97 -> 17898182 | K99: =K6+K7+K8+K9+K10+K11+K12+K13+K14+K15+K16+K19+K20+K21+K22+K23+K24+K25+K26+K27+K28+K29+K30+K31+K34+K35+K36+K37+K38+K39+K40+K41+K42+K43+K44+K45+K46+K47+K50+K51+K52+K53+K54+K55+K56+K57+K58+K59+K62+K63+K64+K65+K66+K67+K68+K69+K70+K73+K74+K75+K76+K77+K80+K81+K82+K83+K84+K85+K86+K89+K90+K91+K92+K93+K94+K95+K96+K97 -> 1491515.2 | M99: =M6+M7+M8+M9+M10+M11+M12+M13+M14+M15+M16+M19+M20+M21+M22+M23+M24+M25+M26+M27+M28+M29+M30+M31+M34+M35+M36+M37+M38+M39+M40+M41+M42+M43+M44+M45+M46+M47+M50+M51+M52+M53+M54+M55+M56+M57+M58+M59+M62+M63+M64+M65+M66+M67+M68+M69+M70+M73+M74+M75+M76+M77+M80+M81+M82+M83+M84+M85+M86+M89+M90+M91+M92+M93+M94+M95+M96+M97 -> 7695.5832 | N99: =N6+N7+N8+N9+N10+N11+N12+N13+N14+N15+N16+N19+N20+N21+N22+N23+N24+N25+N26+N27+N28+N29+N30+N31+N34+N35+N36+N37+N38+N39+N40+N41+N42+N43+N44+N45+N46+N47+N50+N51+N52+N53+N54+N55+N56+N57+N58+N59+N62+N63+N64+N65+N66+N67+N68+N69+N70+N73+N74+N75+N76+N77+N80+N81+N82+N83+N84+N85+N86+N89+N90+N91+N92+N93+N94+N95+N96+N97 -> 8937320.8 | O99: =O6+O7+O8+O9+O10+O11+O12+O13+O14+O15+O16+O19+O20+O21+O22+O23+O24+O25+O26+O27+O28+O29+O30+O31+O34+O35+O36+O37+O38+O39+O40+O41+O42+O43+O44+O45+O46+O47+O50+O51+O52+O53+O54+O55+O56+O57+O58+O59+O62+O63+O64+O65+O66+O67+O68+O69+O70+O73+O74+O75+O76+O77+O80+O81+O82+O83+O84+O85+O86+O89+O90+O91+O92+O93+O94+O95+O96+O97 -> 178746.42 | P99: =P6+P7+P8+P9+P10+P11+P12+P13+P14+P15+P16+P19+P20+P21+P22+P23+P24+P25+P26+P27+P28+P29+P30+P31+P34+P35+P36+P37+P38+P39+P40+P41+P42+P43+P44+P45+P46+P47+P50+P51+P52+P53+P54+P55+P56+P57+P58+P59+P62+P63+P64+P65+P66+P67+P68+P69+P70+P73+P74+P75+P76+P77+P80+P81+P82+P83+P84+P85+P86+P89+P90+P91+P92+P93+P94+P95+P96+P97 -> 0 | Q99: =Q6+Q7+Q8+Q9+Q10+Q11+Q12+Q13+Q14+Q15+Q16+Q19+Q20+Q21+Q22+Q23+Q24+Q25+Q26+Q27+Q28+Q29+Q30+Q31+Q34+Q35+Q36+Q37+Q38+Q39+Q40+Q41+Q42+Q43+Q44+Q45+Q46+Q47+Q50+Q51+Q52+Q53+Q54+Q55+Q56+Q57+Q58+Q59+Q62+Q63+Q64+Q65+Q66+Q67+Q68+Q69+Q70+Q73+Q74+Q75+Q76+Q77+Q80+Q81+Q82+Q83+Q84+Q85+Q86+Q89+Q90+Q91+Q92+Q93+Q94+Q95+Q96+Q97 -> 9116067.3 | R99: =R6+R7+R8+R9+R10+R11+R12+R13+R14+R15+R16+R19+R20+R21+R22+R23+R24+R25+R26+R27+R28+R29+R30+R31+R34+R35+R36+R37+R38+R39+R40+R41+R42+R43+R44+R45+R46+R47+R50+R51+R52+R53+R54+R55+R56+R57+R58+R59+R62+R63+R64+R65+R66+R67+R68+R69+R70+R73+R74+R75+R76+R77+R80+R81+R82+R83+R84+R85+R86+R89+R90+R91+R92+R93+R94+R95+R96+R97 -> 8782114.9 | S99: =R99/J99 -> 0.49067077
A101: РАЗОВЫЕ РАБОТЫ 2027 (по Приложению 10 и п. 2.2.2 ТЗ)
A102: 79 | B102: ПП ТЭЦ-2 | C102: HYD | D102: Гидравлические испытания (опрессовка) и промывка трубопроводов АУПТ (системы ГК, ПГУ-115, ВК, МН) | E102: м | F102: 5312 | G102: нет в тарификаторе → рынок | H102: 180 | I102: 1 | J102: =K102*I102 -> 956160 | K102: =ROUND(F102*H102,2) -> 956160 | L102: 0.12 | M102: =F102*L102 -> 637.44 | N102: =M102*'Персонал ТО'!$C$17*(1+'Персонал ТО'!$C$9) -> 740295.52 | O102: =N102*0.02 -> 14805.91 | P102: =F102*10 -> 53120 | Q102: =N102+O102+P102 -> 808221.43 | R102: =J102-Q102 -> 147938.57 | S102: =IF(J102>0,R102/J102,"") -> 0.15472156 | T102: Прил. 10: 1 раз в 3 года, ТЭЦ-2 — июль–август 2027. Длина — трубопроводы Прил. 7. Рынок: Инфомакс гидроиспытания 18 + промывка 9 руб/м (Мск); kc-spb гидродинамическая промывка от 160 руб/м; Прейскурант 2661 ≈ 483 руб/м → медиана 160; цена КП 180 — от с/с (наценка ≈ 17 %). Субподряд 10 руб/м — аренда опрессовщика, вода, слив (оценка). Норма 0,12 ч/м — экспертно
...

Sheet Персонал ТО
A1: ПЕРСОНАЛ ТО: ТРУДОЁМКОСТЬ → ЧИСЛЕННОСТЬ → ФОТ
A2: Техники ТО — штатные работники (лицензия МЧС требует работников в штате лицензиата). ФОТ = на руки × 1,5 (налоги и взносы) × 14/12 в годовом расчёте.
B4: Показатель | C4: Значение | D4: Основание
B5: Трудоёмкость регламентного ТО, чел.-ч/год | C5: =Работы!M99 -> 7695.5832 | D5: Лист «Работы», итог регламентного ТО (кол-во × норма × 12 мес.)
B6: Трудоёмкость разовых работ (гидроиспытания, поверка, ЭТЛ), чел.-ч/год | C6: =Работы!M107 -> 790.69 | D6: Лист «Работы», разовые работы
B7: Первичное обследование систем (январь–февраль), чел.-ч | C7: 260 | D7: Первичное обследование (п. 3.2.1 ТЗ): ~20 % месячной трудоёмкости ТО × 2 мес. ≈ 260 чел.-ч
B8: Замена вышедшего из строя оборудования (ЗИП), чел.-ч/год | C8: =Материалы!N22 -> 114.05 | D8: Лист «Материалы», чел.-ч на замену
B9: Оформление журналов, актов, паспортов, отчётов — % к трудоёмкости | C9: 0.1 | D9: Журналы ТО и ППР, акты, паспорта установок, ежемесячные отчёты — экспертно 10 %
B10: ИТОГО трудоёмкость, чел.-ч/год | C10: =(C5+C6+C7+C8)*(1+C9) -> 9746.3555
B11: Фонд рабочего времени 1 работника, ч/год (40-часовая неделя, 2027) | C11: 1812 | D11: Норма 2027 при 40-ч неделе 1 972 ч (КонсультантПлюс, производственный календарь 2027) − отпуск 20 раб. дней (160 ч)
B12: Коэффициент использования (переезды между 10 площадками, наряды-допуски, инструктажи) | C12: 0.8 | D12: Экспертно 0,80: основная часть оборудования на 2 промплощадках (ТЭЦ-1, ТЭЦ-2), 8 городских адресов; потери — наряды-допуски, инструктажи, переезды
B13: Требуемая численность техников, чел. (расчёт) | C13: =C10/(C11*C12) -> 6.7234792
B14: Принятая численность техников, чел. (целая) | C14: =ROUNDUP(C13,0) -> 7
B15: Оплата техника на руки, руб./мес (Воронеж) | C15: 70000 | D15: 70 000 руб./мес на руки: Воронеж 2026 — монтажник-слаботочник медиана 75 тыс. (ГородРабот, май 2026), Галерея Чижова 55–75 тыс., ТЕКС Групп 70–120 тыс., НПО РИФ от 70 тыс., ВДПО Воронеж от 80 тыс. (hh.ru, careerist, dreamjob)
B16: ФОТ техников за год, руб. = чел. × на руки × 1,5 × 14 | C16: =C14*C15*1.5*14 -> 10290000 | D16: ×1,5 — НДФЛ сверху «на руки» и страховые взносы; ×14 — 12 мес. × 14/12 (отпускные, замены, премии) по правилу промта
B17: Себестоимость 1 чел.-ч для распределения по строкам, руб. | C17: =C16/C10 -> 1055.7793

Sheet Материалы
A1: МАТЕРИАЛЫ: ЗИП ДЛЯ ПЛАНОВОЙ И ПРЕДУПРЕДИТЕЛЬНОЙ ЗАМЕНЫ (п. 2.1.2, 2.2.3 ТЗ)
A2: Объёмы замены в ТЗ не заданы → допущение: доля парка оборудования в год (колонка E). С/с = закупка × (1+отходы) × (1+доставка) × (1+резерв роста + стоимость денег). Наценка — раздельная форма.
A4: № | B4: Материал / оборудование | C4: Ед. | D4: Парк по ТЗ | E4: Доля замены в год | F4: Кол-во | G4: Закупка б/НДС, руб/ед | H4: Категория (справочник) | I4: Отходы | J4: Доставка | K4: Резерв + деньги | L4: С/с за ед. | M4: С/с всего | N4: Чел.-ч на замену (всего) | O4: Наценка | P4: Цена КП за ед. (не выше розницы) | Q4: КП всего | R4: Розница б/НДС (макс. источник) | S4: Проверка ≤ розницы | T4: С/с труда на замену, руб.
A5: 1 | B5: Извещатель дымовой ИП 212-141 (Рубеж) или аналог | C5: шт | D5: 3569 | E5: 0.02 | F5: =MAX(1,ROUND(D5*E5,0)) -> 71 | G5: ='Цены материалов (источники)'!J5 -> 368.85 | H5: Электроустановочные изделия, щиты, автоматы | I5: 0.01 | J5: 0.1 | K5: 0.105 | L5: =ROUND(G5*(1+I5)*(1+J5)*(1+K5),2) -> 452.82 | M5: =L5*F5 -> 32150.22 | N5: =F5*0.5 -> 35.5 | O5: 0.12 | P5: =ROUND(MIN(L5*(1+O5),R5),2) -> 488.52 | Q5: =P5*F5 -> 34684.92 | R5: ='Цены материалов (источники)'!K5 -> 488.52 | S5: =IF(L5*(1+O5)<=R5,"ок",IF(P5>=L5,"ограничено розницей","розница ниже с/с")) -> ограничено розницей | T5: =N5*'Персонал ТО'!$C$17*(1+'Персонал ТО'!$C$9) -> 41228.18
A6: 2 | B6: Извещатель адресный ДИП-34А-04 (Болид) | C6: шт | D6: 3569 | E6: 0.005 | F6: =MAX(1,ROUND(D6*E6,0)) -> 18 | G6: ='Цены материалов (источники)'!J6 -> 959.02 | H6: Электроустановочные изделия, щиты, автоматы | I6: 0.01 | J6: 0.1 | K6: 0.105 | L6: =ROUND(G6*(1+I6)*(1+J6)*(1+K6),2) -> 1177.35 | M6: =L6*F6 -> 21192.3 | N6: =F6*0.5 -> 9 | O6: 0.12 | P6: =ROUND(MIN(L6*(1+O6),R6),2) -> 1318.63 | Q6: =P6*F6 -> 23735.34 | R6: ='Цены материалов (источники)'!K6 -> 1477.05 | S6: =IF(L6*(1+O6)<=R6,"ок",IF(P6>=L6,"ограничено розницей","розница ниже с/с")) -> ок | T6: =N6*'Персонал ТО'!$C$17*(1+'Персонал ТО'!$C$9) -> 10452.215
A7: 3 | B7: Извещатель тепловой ИП 103-5/1-А3 | C7: шт | D7: 3569 | E7: 0.01 | F7: =MAX(1,ROUND(D7*E7,0)) -> 36 | G7: ='Цены материалов (источники)'!J7 -> 87.05 | H7: Электроустановочные изделия, щиты, автоматы | I7: 0.01 | J7: 0.1 | K7: 0.105 | L7: =ROUND(G7*(1+I7)*(1+J7)*(1+K7),2) -> 106.87 | M7: =L7*F7 -> 3847.32 | N7: =F7*0.5 -> 18 | O7: 0.12 | P7: =ROUND(MIN(L7*(1+O7),R7),2) -> 96.72 | Q7: =P7*F7 -> 3481.92 | R7: ='Цены материалов (источники)'!K7 -> 96.72 | S7: =IF(L7*(1+O7)<=R7,"ок",IF(P7>=L7,"ограничено розницей","розница ниже с/с")) -> розница ниже с/с | T7: =N7*'Персонал ТО'!$C$17*(1+'Персонал ТО'!$C$9) -> 20904.429
A8: 4 | B8: Извещатель ручной ИПР 513-10 (Рубеж) | C8: шт | D8: 558 | E8: 0.01 | F8: =MAX(1,ROUND(D8*E8,0)) -> 6 | G8: ='Цены материалов (источники)'!J8 -> 317.21 | H8: Электроустановочные изделия, щиты, автоматы | I8: 0.01 | J8: 0.1 | K8: 0.105 | L8: =ROUND(G8*(1+I8)*(1+J8)*(1+K8),2) -> 389.42 | M8: =L8*F8 -> 2336.52 | N8: =F8*0.5 -> 3 | O8: 0.12 | P8: =ROUND(MIN(L8*(1+O8),R8),2) -> 318.03 | Q8: =P8*F8 -> 1908.18 | R8: ='Цены материалов (источники)'!K8 -> 318.03 | S8: =IF(L8*(1+O8)<=R8,"ок",IF(P8>=L8,"ограничено розницей","розница ниже с/с")) -> розница ниже с/с | T8: =N8*'Персонал ТО'!$C$17*(1+'Персонал ТО'!$C$9) -> 3484.0716
A9: 5 | B9: Извещатель ручной адресный ИПР 513-3АМ (Болид) | C9: шт | D9: 558 | E9: 0.005 | F9: =MAX(1,ROUND(D9*E9,0)) -> 3 | G9: ='Цены материалов (источники)'!J9 -> 781.97 | H9: Электроустановочные изделия, щиты, автоматы | I9: 0.01 | J9: 0.1 | K9: 0.105 | L9: =ROUND(G9*(1+I9)*(1+J9)*(1+K9),2) -> 959.99 | M9: =L9*F9 -> 2879.97 | N9: =F9*0.5 -> 1.5 | O9: 0.12 | P9: =ROUND(MIN(L9*(1+O9),R9),2) -> 936 | Q9: =P9*F9 -> 2808 | R9: ='Цены материалов (источники)'!K9 -> 936 | S9: =IF(L9*(1+O9)<=R9,"ок",IF(P9>=L9,"ограничено розницей","розница ниже с/с")) -> розница ниже с/с | T9: =N9*'Персонал ТО'!$C$17*(1+'Персонал ТО'!$C$9) -> 1742.0358
A10: 6 | B10: Оповещатель светозвуковой Маяк-12-КП | C10: шт | D10: 880 | E10: 0.01 | F10: =MAX(1,ROUND(D10*E10,0)) -> 9 | G10: ='Цены материалов (источники)'!J10 -> 551.64 | H10: Электроустановочные изделия, щиты, автоматы | I10: 0.01 | J10: 0.1 | K10: 0.105 | L10: =ROUND(G10*(1+I10)*(1+J10)*(1+K10),2) -> 677.22 | M10: =L10*F10 -> 6094.98 | N10: =F10*0.5 -> 4.5 | O10: 0.12 | P10: =ROUND(MIN(L10*(1+O10),R10),2) -> 727.87 | Q10: =P10*F10 -> 6550.83 | R10: ='Цены материалов (источники)'!K10 -> 727.87 | S10: =IF(L10*(1+O10)<=R10,"ок",IF(P10>=L10,"ограничено розницей","розница ниже с/с")) -> ограничено розницей | T10: =N10*'Персонал ТО'!$C$17*(1+'Персонал ТО'!$C$9) -> 5226.1073
A11: 7 | B11: Табло «Выход» Молния-12 | C11: шт | D11: 880 | E11: 0.005 | F11: =MAX(1,ROUND(D11*E11,0)) -> 4 | G11: ='Цены материалов (источники)'!J11 -> 282.79 | H11: Электроустановочные изделия, щиты, автоматы | I11: 0.01 | J11: 0.1 | K11: 0.105 | L11: =ROUND(G11*(1+I11)*(1+J11)*(1+K11),2) -> 347.17 | M11: =L11*F11 -> 1388.68 | N11: =F11*0.5 -> 2 | O11: 0.12 | P11: =ROUND(MIN(L11*(1+O11),R11),2) -> 291.8 | Q11: =P11*F11 -> 1167.2 | R11: ='Цены материалов (источники)'!K11 -> 291.8 | S11: =IF(L11*(1+O11)<=R11,"ок",IF(P11>=L11,"ограничено розницей","розница ниже с/с")) -> розница ниже с/с | T11: =N11*'Персонал ТО'!$C$17*(1+'Персонал ТО'!$C$9) -> 2322.7144
A12: 8 | B12: Оповещатель звуковой Маяк-12-3М | C12: шт | D12: 880 | E12: 0.005 | F12: =MAX(1,ROUND(D12*E12,0)) -> 4 | G12: ='Цены материалов (источники)'!J12 -> 210.66 | H12: Электроустановочные изделия, щиты, автоматы | I12: 0.01 | J12: 0.1 | K12: 0.105 | L12: =ROUND(G12*(1+I12)*(1+J12)*(1+K12),2) -> 258.62 | M12: =L12*F12 -> 1034.48 | N12: =F12*0.5 -> 2 | O12: 0.12 | P12: =ROUND(MIN(L12*(1+O12),R12),2) -> 289.65 | Q12: =P12*F12 -> 1158.6 | R12: ='Цены материалов (источники)'!K12 -> 407.38 | S12: =IF(L12*(1+O12)<=R12,"ок",IF(P12>=L12,"ограничено розницей","розница ниже с/с")) -> ок | T12: =N12*'Персонал ТО'!$C$17*(1+'Персонал ТО'!$C$9) -> 2322.7144
A13: 9 | B13: Аккумулятор 12 В 7 А·ч Delta DTM 1207 | C13: шт | D13: 40 | E13: 0.25 | F13: =MAX(1,ROUND(D13*E13,0)) -> 10 | G13: ='Цены материалов (источники)'!J13 -> 1640.98 | H13: Электроустановочные изделия, щиты, автоматы | I13: 0 | J13: 0.1 | K13: 0.105 | L13: =ROUND(G13*(1+I13)*(1+J13)*(1+K13),2) -> 1994.61 | M13: =L13*F13 -> 19946.1 | N13: =F13*0.3 -> 3 | O13: 0.12 | P13: =ROUND(MIN(L13*(1+O13),R13),2) -> 1649.18 | Q13: =P13*F13 -> 16491.8 | R13: ='Цены материалов (источники)'!K13 -> 1649.18 | S13: =IF(L13*(1+O13)<=R13,"ок",IF(P13>=L13,"ограничено розницей","розница ниже с/с")) -> розница ниже с/с | T13: =N13*'Персонал ТО'!$C$17*(1+'Персонал ТО'!$C$9) -> 3484.0716
A14: 10 | B14: Аккумулятор 12 В 12 А·ч Delta DTM 1212 | C14: шт | D14: 20 | E14: 0.25 | F14: =MAX(1,ROUND(D14*E14,0)) -> 5 | G14: ='Цены материалов (источники)'!J14 -> 2671.31 | H14: Электроустановочные изделия, щиты, автоматы | I14: 0 | J14: 0.1 | K14: 0.105 | L14: =ROUND(G14*(1+I14)*(1+J14)*(1+K14),2) -> 3246.98 | M14: =L14*F14 -> 16234.9 | N14: =F14*0.3 -> 1.5 | O14: 0.12 | P14: =ROUND(MIN(L14*(1+O14),R14),2) -> 3001.64 | Q14: =P14*F14 -> 15008.2 | R14: ='Цены материалов (источники)'!K14 -> 3001.64 | S14: =IF(L14*(1+O14)<=R14,"ок",IF(P14>=L14,"ограничено розницей","розница ниже с/с")) -> розница ниже с/с | T14: =N14*'Персонал ТО'!$C$17*(1+'Персонал ТО'!$C$9) -> 1742.0358
A15: 11 | B15: Аккумулятор 12 В 17 А·ч Delta DTM 1217 | C15: шт | D15: 10 | E15: 0.25 | F15: =MAX(1,ROUND(D15*E15,0)) -> 3 | G15: ='Цены материалов (источники)'!J15 -> 3945.08 | H15: Электроустановочные изделия, щиты, автоматы | I15: 0 | J15: 0.1 | K15: 0.105 | L15: =ROUND(G15*(1+I15)*(1+J15)*(1+K15),2) -> 4795.24 | M15: =L15*F15 -> 14385.72 | N15: =F15*0.3 -> 0.9 | O15: 0.12 | P15: =ROUND(MIN(L15*(1+O15),R15),2) -> 3952.46 | Q15: =P15*F15 -> 11857.38 | R15: ='Цены материалов (источники)'!K15 -> 3952.46 | S15: =IF(L15*(1+O15)<=R15,"ок",IF(P15>=L15,"ограничено розницей","розница ниже с/с")) -> розница ниже с/с | T15: =N15*'Персонал ТО'!$C$17*(1+'Персонал ТО'!$C$9) -> 1045.2215
A16: 12 | B16: Аккумулятор 12 В 40 А·ч Delta DTM 1240 L | C16: шт | D16: 6 | E16: 0.25 | F16: =MAX(1,ROUND(D16*E16,0)) -> 2 | G16: ='Цены материалов (источники)'!J16 -> 10869.67 | H16: Электроустановочные изделия, щиты, автоматы | I16: 0 | J16: 0.1 | K16: 0.105 | L16: =ROUND(G16*(1+I16)*(1+J16)*(1+K16),2) -> 13212.08 | M16: =L16*F16 -> 26424.16 | N16: =F16*0.5 -> 1 | O16: 0.12 | P16: =ROUND(MIN(L16*(1+O16),R16),2) -> 10876.77 | Q16: =P16*F16 -> 21753.54 | R16: ='Цены материалов (источники)'!K16 -> 10876.77 | S16: =IF(L16*(1+O16)<=R16,"ок",IF(P16>=L16,"ограничено розницей","розница ниже с/с")) -> розница ниже с/с | T16: =N16*'Персонал ТО'!$C$17*(1+'Персонал ТО'!$C$9) -> 1161.3572
A17: 13 | B17: Источник питания РИП-12 исп.01 (Болид) | C17: шт | D17: 67 | E17: 0.03 | F17: =MAX(1,ROUND(D17*E17,0)) -> 2 | G17: ='Цены материалов (источники)'!J17 -> 5413.97 | H17: Электроустановочные изделия, щиты, автоматы | I17: 0 | J17: 0.1 | K17: 0.105 | L17: =ROUND(G17*(1+I17)*(1+J17)*(1+K17),2) -> 6580.68 | M17: =L17*F17 -> 13161.36 | N17: =F17*1 -> 2 | O17: 0.12 | P17: =ROUND(MIN(L17*(1+O17),R17),2) -> 5504.2 | Q17: =P17*F17 -> 11008.4 | R17: ='Цены материалов (источники)'!K17 -> 5504.2 | S17: =IF(L17*(1+O17)<=R17,"ок",IF(P17>=L17,"ограничено розницей","розница ниже с/с")) -> розница ниже с/с | T17: =N17*'Персонал ТО'!$C$17*(1+'Персонал ТО'!$C$9) -> 2322.7144
A18: 14 | B18: Кабель КПСнг(А)-FRLS 1×2×0,75 | C18: м | D18: 52655 | E18: 0.005 | F18: =MAX(1,ROUND(D18*E18,0)) -> 263 | G18: ='Цены материалов (источники)'!J18 -> 21.25 | H18: Кабель и провод | I18: 0.04 | J18: 0.1 | K18: 0.105 | L18: =ROUND(G18*(1+I18)*(1+J18)*(1+K18),2) -> 26.86 | M18: =L18*F18 -> 7064.18 | N18: =F18*0.05 -> 13.15 | O18: 0.12 | P18: =ROUND(MIN(L18*(1+O18),R18),2) -> 29.48 | Q18: =P18*F18 -> 7753.24 | R18: ='Цены материалов (источники)'!K18 -> 29.48 | S18: =IF(L18*(1+O18)<=R18,"ок",IF(P18>=L18,"ограничено розницей","розница ниже с/с")) -> ограничено розницей | T18: =N18*'Персонал ТО'!$C$17*(1+'Персонал ТО'!$C$9) -> 15271.847
A19: 15 | B19: Манометр МП-100 0–1,6 МПа | C19: шт | D19: 35 | E19: 0.1 | F19: =MAX(1,ROUND(D19*E19,0)) -> 4 | G19: ='Цены материалов (источники)'!J19 -> 523.25 | H19: Трубы и фитинги ВиК, отопления | I19: 0 | J19: 0.1 | K19: 0.105 | L19: =ROUND(G19*(1+I19)*(1+J19)*(1+K19),2) -> 636.01 | M19: =L19*F19 -> 2544.04 | N19: =F19*0.5 -> 2 | O19: 0.12 | P19: =ROUND(MIN(L19*(1+O19),R19),2) -> 659.02 | Q19: =P19*F19 -> 2636.08 | R19: ='Цены материалов (источники)'!K19 -> 659.02 | S19: =IF(L19*(1+O19)<=R19,"ок",IF(P19>=L19,"ограничено розницей","розница ниже с/с")) -> ограничено розницей | T19: =N19*'Персонал ТО'!$C$17*(1+'Персонал ТО'!$C$9) -> 2322.7144
A20: 16 | B20: Ороситель спринклерный СВН-15 (68 °С) | C20: шт | D20: 987 | E20: 0.01 | F20: =MAX(1,ROUND(D20*E20,0)) -> 10 | G20: ='Цены материалов (источники)'!J20 -> 413.11 | H20: Трубы и фитинги ВиК, отопления | I20: 0 | J20: 0.1 | K20: 0.105 | L20: =ROUND(G20*(1+I20)*(1+J20)*(1+K20),2) -> 502.14 | M20: =L20*F20 -> 5021.4 | N20: =F20*1 -> 10 | O20: 0.12 | P20: =ROUND(MIN(L20*(1+O20),R20),2) -> 413.11 | Q20: =P20*F20 -> 4131.1 | R20: ='Цены материалов (источники)'!K20 -> 413.11 | S20: =IF(L20*(1+O20)<=R20,"ок",IF(P20>=L20,"ограничено розницей","розница ниже с/с")) -> розница ниже с/с | T20: =N20*'Персонал ТО'!$C$17*(1+'Персонал ТО'!$C$9) -> 11613.572
A21: 17 | B21: Ороситель дренчерный ДВН-15 | C21: шт | D21: 987 | E21: 0.005 | F21: =MAX(1,ROUND(D21*E21,0)) -> 5 | G21: ='Цены материалов (источники)'!J21 -> 236.07 | H21: Трубы и фитинги ВиК, отопления | I21: 0 | J21: 0.1 | K21: 0.105 | L21: =ROUND(G21*(1+I21)*(1+J21)*(1+K21),2) -> 286.94 | M21: =L21*F21 -> 1434.7 | N21: =F21*1 -> 5 | O21: 0.12 | P21: =ROUND(MIN(L21*(1+O21),R21),2) -> 242.62 | Q21: =P21*F21 -> 1213.1 | R21: ='Цены материалов (источники)'!K21 -> 242.62 | S21: =IF(L21*(1+O21)<=R21,"ок",IF(P21>=L21,"ограничено розницей","розница ниже с/с")) -> розница ниже с/с | T21: =N21*'Персонал ТО'!$C$17*(1+'Персонал ТО'!$C$9) -> 5806.7859
B22: ИТОГО ЗИП | M22: =SUM(M5:M21) -> 177141.03 | N22: =SUM(N5:N21) -> 114.05 | Q22: =SUM(Q5:Q21) -> 167347.83 | T22: =SUM(T5:T21) -> 132452.79
B24: Параметры: доставка — «Регион» по листу «Параметры» справочника материалов; резерв роста цен — закупки равномерно в течение 2027 г., в среднем через 8 мес. после КП → (8 − 2) × 1,25 % = 7,5 %; стоимость денег — закупка без аванса, оплата через ~1,5 мес. → 3 %.

Sheet Цены материалов (источники)
A1: ЦЕНЫ МАТЕРИАЛОВ (ИСТОЧНИКИ)
A2: Цены сайтов с НДС 22 % → ÷ 1,22. Закупка = минимальная цена без НДС. Дата проверки — 28.10.2026.
A4: № | B4: Позиция | C4: Ед. | D4: Магазин 1 | E4: Цена 1 с НДС | F4: URL 1 | G4: Магазин 2 | H4: Цена 2 с НДС | I4: URL 2 | J4: Закупка б/НДС = мин ÷ 1,22 | K4: Розница б/НДС = макс ÷ 1,22 | L4: Отметка
A5: 1 | B5: Извещатель дымовой ИП 212-141 (Рубеж) или аналог | C5: шт | D5: Тинко | E5: 596 | F5: https://www.tinko.ru/catalog/product/208489/ | G5: Сектор СБ | H5: 450 | I5: https://sector-sb.ru/catalog/ops/izveschateli_pojarnye/izveschateli_dymovye/ip_212-141 | J5: =ROUND(MIN(E5,H5)/1.22,2) -> 368.85 | K5: =ROUND(MAX(E5,H5)/1.22,2) -> 488.52 | L5: Замена ИП 212-41М (снят с производства с 2022)
A6: 2 | B6: Извещатель адресный ДИП-34А-04 (Болид) | C6: шт | D6: Юнитрекс | E6: 1802 | F6: https://unitrex.ru/catalog/ohranno-pojarnaya-signalizaciya/integrirovannaya-sistema-orion/adresno-analogovaya-sistema-na-baze-s2000-kdl/dip-34a-04 | G6: Альфа-сети | H6: 1170 | I6: https://alphanets.ru/catalog/bolid-dip-34a-04-dymovoy-optiko-elektronnyy-pozharnyy-izveshc | J6: =ROUND(MIN(E6,H6)/1.22,2) -> 959.02 | K6: =ROUND(MAX(E6,H6)/1.22,2) -> 1477.05 | L6: Мин. цена 1 170 сильно ниже рынка (X-Com 1 841) — проверить
A7: 3 | B7: Извещатель тепловой ИП 103-5/1-А3 | C7: шт | D7: Тинко | E7: 118 | F7: https://www.tinko.ru/catalog/product/005010/ | G7: Тинко-СБ | H7: 106.2 | I7: https://tinko-sb.ru/products/ip-103-5-1-a3-5010/ | J7: =ROUND(MIN(E7,H7)/1.22,2) -> 87.05 | K7: =ROUND(MAX(E7,H7)/1.22,2) -> 96.72
A8: 4 | B8: Извещатель ручной ИПР 513-10 (Рубеж) | C8: шт | D8: Тинко | E8: 388 | F8: https://www.tinko.ru/catalog/product/205151/ | G8: ТК «ИВС» | H8: 387 | I8: https://tkivs.ru/unit.php?id_unit=1147 | J8: =ROUND(MIN(E8,H8)/1.22,2) -> 317.21 | K8: =ROUND(MAX(E8,H8)/1.22,2) -> 318.03
A9: 5 | B9: Извещатель ручной адресный ИПР 513-3АМ (Болид) | C9: шт | D9: Тинко | E9: 1141.92 | F9: https://www.tinko.ru/catalog/product/224799/ | G9: РВН-Групп | H9: 954 | I9: https://rvn-group.ru/catalog/okhranno_pozharnye_sistemy/adresnye_sistemy_bolid/izveshchateli_bolid/22121/ | J9: =ROUND(MIN(E9,H9)/1.22,2) -> 781.97 | K9: =ROUND(MAX(E9,H9)/1.22,2) -> 936
A10: 6 | B10: Оповещатель светозвуковой Маяк-12-КП | C10: шт | D10: Тинко-СБ | E10: 888 | F10: https://tinko-sb.ru/products/mayak-12kp-19230/ | G10: Enex | H10: 673 | I10: https://enex.market/product/kombinirovannyy-svetozvukovoy-opoveshchatel-mayak-12-kp/ | J10: =ROUND(MIN(E10,H10)/1.22,2) -> 551.64 | K10: =ROUND(MAX(E10,H10)/1.22,2) -> 727.87
A11: 7 | B11: Табло «Выход» Молния-12 | C11: шт | D11: Тинко | E11: 356 | F11: https://www.tinko.ru/catalog/product/309882/ | G11: Мегаполис | H11: 345 | I11: https://www.megapolys.com/catalog/tekhnicheskie_sredstva_bezopasnosti/196514/ | J11: =ROUND(MIN(E11,H11)/1.22,2) -> 282.79 | K11: =ROUND(MAX(E11,H11)/1.22,2) -> 291.8
A12: 8 | B12: Оповещатель звуковой Маяк-12-3М | C12: шт | D12: Тинко | E12: 497 | F12: https://www.tinko.ru/catalog/product/200098/ | G12: Радтек | H12: 257 | I12: https://radtek.ru/catalog/pozharnye_opoveshchateli/opoveshchateli_pozharnye_zvukovye/seriya_mayak2/ | J12: =ROUND(MIN(E12,H12)/1.22,2) -> 210.66 | K12: =ROUND(MAX(E12,H12)/1.22,2) -> 407.38 | L12: Мин. цена — страница каталога, проверить
A13: 9 | B13: Аккумулятор 12 В 7 А·ч Delta DTM 1207 | C13: шт | D13: delta-battery.ru | E13: 2002 | F13: https://www.delta-battery.ru/catalog/dtm/delta-dtm-1207/ | G13: СЕК-ГРУПП | H13: 2012 | I13: https://sec-group.ru/p/delta-18539/ | J13: =ROUND(MIN(E13,H13)/1.22,2) -> 1640.98 | K13: =ROUND(MAX(E13,H13)/1.22,2) -> 1649.18 | L13: Парк по ёмкостям — допущение (76 АКБ всего), срок службы 4–5 лет → 25 %/год
A14: 10 | B14: Аккумулятор 12 В 12 А·ч Delta DTM 1212 | C14: шт | D14: DSSL | E14: 3259 | F14: https://www.dssl.ru/products/dtm-1212-akkumulyatornaya-batareya/ | G14: СЕК-ГРУПП | H14: 3662 | I14: https://sec-group.ru/p/delta-18540/ | J14: =ROUND(MIN(E14,H14)/1.22,2) -> 2671.31 | K14: =ROUND(MAX(E14,H14)/1.22,2) -> 3001.64
A15: 11 | B15: Аккумулятор 12 В 17 А·ч Delta DTM 1217 | C15: шт | D15: delta-battery.ru | E15: 4813 | F15: https://www.delta-battery.ru/catalog/dtm/delta-dtm-1217/ | G15: АктивСБ | H15: 4822 | I15: https://www.aktivsb.ru/prod-22791.html | J15: =ROUND(MIN(E15,H15)/1.22,2) -> 3945.08 | K15: =ROUND(MAX(E15,H15)/1.22,2) -> 3952.46
A16: 12 | B16: Аккумулятор 12 В 40 А·ч Delta DTM 1240 L | C16: шт | D16: delta-battery.ru | E16: 13261 | F16: https://www.delta-battery.ru/catalog/dtm-l/delta-dtm-1240-l/ | G16: Сатро-Паладин | H16: 13269.66 | I16: https://satro-paladin.com/catalog/product/15300/ | J16: =ROUND(MIN(E16,H16)/1.22,2) -> 10869.67 | K16: =ROUND(MAX(E16,H16)/1.22,2) -> 10876.77
A17: 13 | B17: Источник питания РИП-12 исп.01 (Болид) | C17: шт | D17: Тинко | E17: 6715.12 | F17: https://www.tinko.ru/catalog/product/008539/ | G17: ЦСБ-Про | H17: 6605.04 | I17: https://www.csbpro.ru/catalog/bolid/rip_12_isp_01_istochnik_pitaniya_12v_3a/ | J17: =ROUND(MIN(E17,H17)/1.22,2) -> 5413.97 | K17: =ROUND(MAX(E17,H17)/1.22,2) -> 5504.2
A18: 14 | B18: Кабель КПСнг(А)-FRLS 1×2×0,75 | C18: м | D18: Тинко | E18: 35.97 | F18: https://www.tinko.ru/catalog/product/216213/ | G18: elgroup24 (ИВКЗ) | H18: 25.92 | I18: https://elgroup24.ru/kpsng-a-frls-series-750/ | J18: =ROUND(MIN(E18,H18)/1.22,2) -> 21.25 | K18: =ROUND(MAX(E18,H18)/1.22,2) -> 29.48 | L18: Мин. — малоизвестный магазин; Тинко 35,97
A19: 15 | B19: Манометр МП-100 0–1,6 МПа | C19: шт | D19: ОСТ-М | E19: 638.37 | F19: https://www.ost-m.ru/catalog/truboprovodnaya_armatura_pribory_ucheta_i_kipia_manometry_i_komplektuyushchie_manometry_tekhnicheskie_mp_100_mp_160/ | G19: Сантур | H19: 804 | I19: https://santur.ru/product/00000002376 | J19: =ROUND(MIN(E19,H19)/1.22,2) -> 523.25 | K19: =ROUND(MAX(E19,H19)/1.22,2) -> 659.02
A20: 16 | B20: Ороситель спринклерный СВН-15 (68 °С) | C20: шт | D20: Сатро-Паладин | E20: 504 | F20: https://satro-paladin.com/catalog/product/107170/ | G20: Спецавтоматика Бийск | H20: 504 | I20: https://sa-biysk.ru/catalog/1368/17147/ | J20: =ROUND(MIN(E20,H20)/1.22,2) -> 413.11 | K20: =ROUND(MAX(E20,H20)/1.22,2) -> 413.11
A21: 17 | B21: Ороситель дренчерный ДВН-15 | C21: шт | D21: Сатро-Паладин | E21: 288 | F21: https://satro-paladin.com/catalog/product/108074/ | G21: АльфаВодоСтрой | H21: 296 | I21: https://awstroy.ru/product/orositel-drenchernyj-dvo0-rno0-77-r1-2-v3-dvn-15-vodyanoj/ | J21: =ROUND(MIN(E21,H21)/1.22,2) -> 236.07 | K21: =ROUND(MAX(E21,H21)/1.22,2) -> 242.62

Sheet Косвенные
A1: КОСВЕННЫЕ РАСХОДЫ ПРОЕКТА
A2: Каждая статья — с расчётом. Жёлтые — вводные.
A4: № | B4: Статья | C4: Кол-во | D4: Ед. | E4: Ставка, руб. | F4: Множитель | G4: Сумма, руб./год | H4: Расчёт / основание
A5: 1 | B5: Мастер/инженер ТО в Воронеже (штат, 1 чел.) | C5: 1 | D5: чел. | E5: 110000 | F5: 21 | G5: =C5*E5*F5 -> 2310000 | H5: На руки 110 тыс./мес (инженер по обслуживанию слаботочных систем от 105 тыс., инженер ОПС от 100 тыс., прораб СС 135–150 тыс. — dreamjob, Воронеж 2026) × 1,5 × 14
A6: 2 | B6: Руководитель проекта (СПб), доля ставки | C6: 0.15 | D6: ставки | E6: 150000 | F6: 21 | G6: =C6*E6*F6 -> 472500 | H6: Экспертно: 0,15 ставки × 150 тыс. на руки × 1,5 × 14 — контроль, отчётность, взаимодействие с заказчиком
A7: 3 | B7: Командировки РП/мобилизация СПб–Воронеж | C7: 6 | D7: поездок | E7: 20140 | F7: 1 | G7: =C7*E7*F7 -> 120840 | H7: Самолёт туда-обратно 2 × 4 170 (aviadzen) + гостиница 3 ночи × 3 000 (101hotels, 3*) + суточные 4 × 700 = 20 140 руб.
A8: 4 | B8: Аренда автомобиля (Lada Granta) для объезда 10 адресов | C8: 12 | D8: мес. | E8: 39000 | F8: 1 | G8: =C8*E8*F8 -> 468000 | H8: BookingCar Воронеж 1 560 руб/сут − 17 % при аренде от 30 дней ≈ 1 300 × 30 = 39 000 руб/мес
A9: 5 | B9: Топливо | C9: 12 | D9: мес. | E9: 12400 | F9: 1 | G9: =C9*E9*F9 -> 148800 | H9: 2 000 км/мес × 8 л/100 км = 160 л × 77,50 руб/л (АИ-92 Воронеж 28.10.2026, gdebenzin.net) ≈ 12 400
A10: 6 | B10: Обучение и допуски: ПБ, ЭБ III гр., работы на высоте, медосмотр | C10: 1 | D10: чел. | E10: 15000 | F10: 1 | G10: =('Персонал ТО'!$C$14+1)*E10*F10 -> 120000 | H10: ПБ 3 500 + ЭБ 4 000 + высота 4 000 (ВУЦ «Охрана труда», Воронеж) + медосмотр 3 500 (ПрофиМед) = 15 000 руб/чел; техники + мастер
A11: 7 | B11: СИЗ и спецодежда | C11: 1 | D11: чел. | E11: 15000 | F11: 1 | G11: =('Персонал ТО'!$C$14+1)*E11*F11 -> 120000 | H11: ОЦЕНКА 15 000 руб/чел/год: костюм, обувь, каска, очки, перчатки (п. 3.4 ТЗ — СИЗ за счёт исполнителя)
A12: 8 | B12: Расходник для проверки извещателей (аэрозоль ТА-01) | C12: 24 | D12: баллон | E12: 1185.25 | F12: 1 | G12: =C12*E12*F12 -> 28446 | H12: АктивСБ 1 446 с НДС ÷ 1,22 = 1 185,25; 3 569 извещателей ежеквартально ≈ 600 проверок на баллон → 24 шт/год
A13: 9 | B13: Инструмент и приборы (стремянки, мультиметры, тестеры тепловых/линейных извещателей, удочка) | C13: 1 | D13: компл. | E13: 120000 | F13: 1 | G13: =C13*E13*F13 -> 120000 | H13: ОЦЕНКА 120 тыс. руб. на 1 год использования
A14: 10 | B14: Поверка приборов (мегаомметр, измеритель заземления) | C14: 1 | D14: компл. | E14: 3533 | F14: 1 | G14: =C14*E14*F14 -> 3533 | H14: Воронежский ЦСМ, прил. 1 с 01.01.2026: мегаомметр 1 228 + измеритель заземления 2 305
A15: 11 | B15: Связь, ноутбук, ПО для «Орион Про» | C15: 12 | D15: мес. | E15: 5000 | F15: 1 | G15: =C15*E15*F15 -> 60000 | H15: ОЦЕНКА: 3 SIM × 700 + амортизация ноутбука
A16: 12 | B16: Склад/помещение для ЗИП и инструмента в Воронеже | C16: 12 | D16: мес. | E16: 15000 | F16: 1 | G16: =C16*E16*F16 -> 180000 | H16: ОЦЕНКА; если заказчик предоставит помещение на ТЭЦ — исключить (вопрос заказчику)
A17: 13 | B17: Банковская гарантия исполнения (если потребуют) | C17: 1 | E17: 0.0016 | F17: 1 | G17: =(SUM(Свод!$C$5:$C$8)+SUM(G5:G16))*1.2*1.22*E17 -> 34914.741 | H17: Документации о закупке нет → допущение: обеспечение 5 % цены с НДС, ставка 3,2 % годовых (УБРиР, trillioncredit)
A18: 14 | B18: Финансирование кассового разрыва | C18: 1.25 | D18: мес. разрыва | E18: 0.02 | F18: 12 | G18: =(SUM(Свод!$C$5:$C$8)+SUM(G5:G17))/12*C18*E18*F18 -> 373511.42 | H18: Аванса нет, оплата 7 р.д. после акта → средний разрыв ≈ 1,25 мес. затрат × 2 %/мес × 12 мес. (см. «Кэш-план»)
A19: 15 | B19: Резерв гарантийных обязательств | C19: 1 | E19: 0.01 | F19: 1 | G19: =(SUM(Свод!$C$5:$C$8)+SUM(G5:G18))*E19 -> 153139.68 | H19: 1 % (диапазон промта 1–2 %): устранение дефектов за свой счёт (п. 3.3 ТЗ)
A20: 16 | B20: Резерв рисков | C20: 1 | E20: 0.05 | F20: 1 | G20: =(SUM(Свод!$C$5:$C$8)+SUM(G5:G19))*E20 -> 773355.39 | H20: 5 % (верх диапазона 3–5 %): нет проекта договора и штрафов, объёмы ЗИП не заданы, допуск на ТЭЦ, ошибки в перечнях ТЗ
B21: ИТОГО КОСВЕННЫЕ | G21: =SUM(G5:G20) -> 5487040.2

Sheet Риски и вопросы
A1: РИСКИ И ВОПРОСЫ
A3: № | B3: Описание | C3: Влияние на цену, руб. | D3: Что спросить у заказчика | E3: Допущение, с которым посчитано
A4: 1 | B4: НМЦК не опубликована (b2b-center № 57697: «начальная цена 0», оценивается цена с НДС). Аналог 2023 г. (ЕИС 32211915005) — НМЦК 2 399 999 руб. | C4: см. отчёт | D4: Ориентир бюджета на 2027 г.? Объём аналога 2023 г. совпадает? | E4: Цена — по рынку подрядчиков за единицу оборудования
A5: 2 | B5: Проекта договора нет: штрафы, обеспечение, порядок приёмки неизвестны | C5: резерв 5 % | D5: Предоставить проект договора; размер обеспечения заявки/исполнения | E5: БГ 5 % — заложена; штрафы — в резерве рисков
A6: 3 | B6: Объём ЗИП не задан («плановая и предупредительная замена») | C6: ЗИП — лимит | D6: Кто поставляет оборудование для замены? Оплата по факту или в цене ТО? | E6: ЗИП — отдельный лимит по % парка, оплата по факту
A7: 4 | B7: В перечнях ТЗ ошибки: кабель Туполева/Хмельницкого указан в «шт» (400, 10), строки задублированы; огнезадерживающие клапаны упомянуты, но в перечнях нет | C7: небольшое | D7: Подтвердить перечни Прил. 5, 8; входят ли клапаны ОЗК | E7: Посчитано как в ТЗ («шт» → м); клапаны не включены
A8: 5 | B8: Опробование АУПТ с реальным пуском на ТЭЦ-2 — нет рыночной цены, возможен большой объём (насосы, слив, восстановление) | C8: до +200 тыс. | D8: Состав работ при пуске, кто восстанавливает систему, вода и слив за чей счёт | E8: 33 000 руб/система (рынок ≈ 17 500, оценка) + 24 ч
A9: 6 | B9: Допуск персонала на ТЭЦ (наряды, инструктажи, ФНиП) снижает выработку | C9: ФОТ | D9: Режим доступа, часы работы, сопровождение | E9: Коэф. использования 0,80
A10: 7 | B10: Найм 6–7 техников в Воронеже к 01.01.2027 (рынок 70–120 тыс.) | C10: ФОТ ±15 % | D10: — | E10: На руки 70 тыс.
A11: 8 | B11: Цены рынка за ед. — в основном «от», без указания НДС, в Воронеже открытых прайсов мало | C11: выручка ±20 % | D11: — | E11: Медиана 3 источников, приняты как без НДС

Sheet Добавить в тарификатор
A1: ДОБАВИТЬ В ТАРИФИКАТОР
A2: Работ ТО пожарной автоматики в тарификаторе v2 нет (есть только 2.44 и 15.7 — монтаж/демонтаж извещателей). Предлагаемые новые артикулы.
A4: Предлагаемый артикул | B4: Вид работ | C4: Ед. | D4: Специальность | E4: Рынок Воронеж/ЦФО, руб/ед/мес б/НДС | F4: Норма, чел.-ч/ед/мес | G4: Основание | H4: Примечание
A5: 20.1.N1 | B5: ТО прибора приёмно-контрольного, пульта, прибора управления (С2000М, Сигнал-20П/10, Гранит, С2000-АСПТ, Рубеж-20П и др.) | C5: шт/мес | D5: ETL/ELM | E5: ='Ставки ТО'!L5 -> 1431 | F5: 1 | G5: Экспертно 1,0 ч/мес (между пультом 1,0 и ППК средней ёмкости 3,0 ч/мес по нормативы МВД (у.у. = 1,67 ч/мес), ivtechno.ru) | H5: Новый раздел «20 ТО систем пожарной автоматики»; цены СПб/Мск — отдельно уточнить
A6: 20.1.N2 | B6: ТО блока системы (С2000-КДЛ, СП1/СП2, КПБ, БКИ, ПИ, ПТ, БРИЗ, барьеры искрозащиты и др.) | C6: шт/мес | D6: ETL/ELM | E6: ='Ставки ТО'!L6 -> 95 | F6: 0.2 | G6: Адресный расширитель 0,33 ч/мес (нормативы МВД (у.у. = 1,67 ч/мес), ivtechno.ru); экспертно 0,2 — проверка в составе ППК | H6: Новый раздел «20 ТО систем пожарной автоматики»; цены СПб/Мск — отдельно уточнить
A7: 20.1.N3 | B7: ТО источника электропитания резервированного (РИП, Скат, ИВЭПР, ББП) | C7: шт/мес | D7: ETL/ELM | E7: ='Ставки ТО'!L7 -> 195 | F7: 0.25 | G7: РИП с АКБ 0,5 ч/мес (нормативы МВД (у.у. = 1,67 ч/мес), ivtechno.ru); экспертно 0,25 (АКБ — отдельной строкой) | H7: Новый раздел «20 ТО систем пожарной автоматики»; цены СПб/Мск — отдельно уточнить
A8: 20.1.N4 | B8: ТО аккумуляторной батареи (контроль напряжения и ёмкости) | C8: шт/мес | D8: ETL/ELM | E8: ='Ставки ТО'!L8 -> 95 | F8: 0.05 | G8: Экспертно: замер напряжения/ёмкости при ТО РИП | H8: Новый раздел «20 ТО систем пожарной автоматики»; цены СПб/Мск — отдельно уточнить
A9: 20.1.N5 | B9: ТО извещателя пожарного автоматического точечного (дымового, теплового) | C9: шт/мес | D9: ETL/ELM | E9: ='Ставки ТО'!L9 -> 40 | F9: 0.04 | G9: Экспертно: ежемес. осмотр + проверка аэрозолем 1 раз в квартал ~6 мин/шт; верхняя граница — дымовой 0,17 ч/мес (нормативы МВД (у.у. = 1,67 ч/мес), ivtechno.ru) | H9: Новый раздел «20 ТО систем пожарной автоматики»; цены СПб/Мск — отдельно уточнить
A10: 20.1.N6 | B10: ТО извещателя пожарного во взрывозащищённом/искробезопасном исполнении | C10: шт/мес | D10: ETL/ELM | E10: ='Ставки ТО'!L10 -> 97.5 | F10: 0.15 | G10: Экспертно: × 3–4 к обычному (наряд-допуск, взрывоопасная зона) | H10: Новый раздел «20 ТО систем пожарной автоматики»; цены СПб/Мск — отдельно уточнить
A11: 20.1.N7 | B11: ТО извещателя пожарного пламени (Спектрон, Пульсар, Набат) | C11: шт/мес | D11: ETL/ELM | E11: ='Ставки ТО'!L11 -> 50 | F11: 0.15 | G11: Экспертно: проверка тест-фонарём | H11: Новый раздел «20 ТО систем пожарной автоматики»; цены СПб/Мск — отдельно уточнить
A12: 20.1.N8 | B12: ТО извещателя пожарного дымового линейного ИПДЛ | C12: к-т/мес | D12: ETL/ELM | E12: ='Ставки ТО'!L12 -> 200 | F12: 0.3 | G12: ИПДЛ 0,5 ч/мес (нормативы МВД (у.у. = 1,67 ч/мес), ivtechno.ru); экспертно 0,3 | H12: Новый раздел «20 ТО систем пожарной автоматики»; цены СПб/Мск — отдельно уточнить
A13: 20.1.N9 | B13: ТО линейного теплового извещателя (термокабель) | C13: 100 м/мес | D13: ETL/ELM | E13: ='Ставки ТО'!L13 -> 150 | F13: 0.15 | G13: Экспертно: осмотр трассы, проверка шлейфа на 100 м | H13: Новый раздел «20 ТО систем пожарной автоматики»; цены СПб/Мск — отдельно уточнить
A14: 20.1.N10 | B14: ТО извещателя пожарного ручного, УДП, ЭДУ | C14: шт/мес | D14: ETL/ELM | E14: ='Ставки ТО'!L14 -> 35 | F14: 0.04 | G14: Экспертно, как автоматический извещатель | H14: Новый раздел «20 ТО систем пожарной автоматики»; цены СПб/Мск — отдельно уточнить
A15: 20.1.N11 | B15: ТО извещателя охранного (магнитоконтактного, ИК) в составе систем | C15: шт/мес | D15: ETL/ELM | E15: ='Ставки ТО'!L15 -> 30 | F15: 0.03 | G15: Экспертно | H15: Новый раздел «20 ТО систем пожарной автоматики»; цены СПб/Мск — отдельно уточнить
A16: 20.1.N12 | B16: ТО оповещателя (светового, звукового, речевого, табло «Выход») | C16: шт/мес | D16: ETL/ELM | E16: ='Ставки ТО'!L16 -> 49 | F16: 0.04 | G16: Оповещатель 0,17 ч/мес (нормативы МВД (у.у. = 1,67 ч/мес), ivtechno.ru) — верхняя граница; экспертно 0,04 (проверка зонами при пуске) | H16: Новый раздел «20 ТО систем пожарной автоматики»; цены СПб/Мск — отдельно уточнить
... A28: 20.1.N24 | B28: ТО бака (пенообразователя, мембранного) | C28: шт/мес | D28: ETL/ELM | E28: ='Ставки ТО'!L28 -> 300 | F28: 1 | G28: Экспертно | H28: Новый раздел «20 ТО систем пожарной автоматики»; цены СПб/Мск — отдельно уточнить
A29: 20.2.N | B29: Гидравлические испытания (опрессовка) и промывка трубопроводов АУПТ (системы ГК, ПГУ-115, ВК, МН) | C29: м | D29: SAN/ETL | E29: 180 | F29: 0.12 | G29: Прил. 10: 1 раз в 3 года, ТЭЦ-2 — июль–август 2027. Длина — трубопроводы Прил. 7. Рынок: Инфомакс гидроиспытания 18 + промывка 9 руб/м (Мск); kc-spb гидродинамическая промывка от 160 руб/м; Прейскурант 2661 ≈ 483 руб/м → медиана 160; цена КП 180 — от с/с (наценка ≈ 17 %). Субподряд 10 руб/м — аренда опрессовщика, вода, слив (оценка). Норма 0,12 ч/м — экспертно
A30: 20.2.N | B30: Опробование АУПТ с реальным пуском (составление программы, пуск, акт) | C30: система | D30: SAN/ETL | E30: 33000 | F30: 24 | G30: Рыночной цены нет (не найдено). Ориентиры: испытание пожарного водопровода от 10 000 (Контур, Мск), ТО насосной от 25 000 (U-NET) → 17 500 (оценка); цена КП 33 000 — от с/с (наценка ≈ 17 %). Норма 24 ч на систему — экспертно (бригада 3 чел. × 8 ч)
A31: 20.2.N | B31: Поверка манометров АУПТ с демонтажем/монтажем и опломбированием | C31: шт | D31: SAN/ETL | E31: 800 | F31: 0.5 | G31: Прил. 10: май — полная проверка манометров с опломбированием/клеймением. 35 шт. — манометры Прил. 6–7. Цена КП — тарификатор v2, п. 9.2.96 «поверка манометра» 800 руб. Субподряд: ФБУ «Воронежский ЦСМ» 108,04 руб. (КТ 1–2,5), ЭКМ 130 (ЮСТИР) + доставка ≈ 150. Норма 0,5 ч — демонтаж/монтаж, заглушка, доставка
A32: 20.2.N | B32: Измерение сопротивления металлосвязи (заземления) оборудования АПС/СОУЭ с протоколами ЭТЛ | C32: точка | D32: SAN/ETL | E32: 115 | F32: 0.05 | G32: Прил. 9: июнь — измерение сопротивления заземления. 395 точек = ППК 120 + РИП 67 + СОУЭ 5 + шкафы/коробки 203 (допущение). Рынок Воронеж: ЭТЛ «Пространство света» 40 руб/точка, ЛАЭР от 75 → медиана 57,5; цена КП 115 — от с/с (с сопровождением нашего техника). Субподряд — ЭТЛ Воронеж 40 руб/точка; наш техник сопровождает 0,05 ч/точка
A33: 20.2.N | B33: Измерение сопротивления заземляющих устройств (по объектам) | C33: объект | D33: SAN/ETL | E33: 4500 | F33: 2 | G33: ЛАЭР Воронеж: заземляющее устройство от 1 500 руб/система. Цена КП 4 500 — от с/с (субподряд 1 500 + 2 ч техника + выезд); рынок ≈ 1 500–1 800. 10 адресов

Sheet График и ресурсы
A1: КАРТА РЕАЛИЗАЦИИ: ГРАФИК ПО МЕСЯЦАМ 2027 И РЕСУРСЫ
A2: По Приложениям 9 и 10 ТЗ. Х — операция выполняется в месяце.
A4: Вид работ | B4: янв | C4: фев | D4: мар | E4: апр | F4: май | G4: июн | H4: июл | I4: авг | J4: сен | K4: окт | L4: ноя | M4: дек
A5: Первичное обследование систем, сверка перечней, приём документации | B5: Х | C5: Х
A6: АПС/СОУЭ: ежемесячное ТО (осмотр, индикация, питание, работоспособность) | B6: Х | C6: Х | D6: Х | E6: Х | F6: Х | G6: Х | H6: Х | I6: Х | J6: Х | K6: Х | L6: Х | M6: Х
A7: АПС/СОУЭ: ежеквартальная профилактика | D7: Х | G7: Х | J7: Х | M7: Х
A8: АПС: измерение сопротивления заземления (ЭТЛ) | G8: Х
A9: АУПТ: ежемесячное ТО узлов, оросителей, трубопроводов | B9: Х | C9: Х | D9: Х | E9: Х | F9: Х | G9: Х | H9: Х | I9: Х | J9: Х | K9: Х | L9: Х | M9: Х
A10: АУПТ: вводы, арматура, задвижки с ЭП, схемы пуска | C10: Х | F10: Х | I10: Х | L10: Х
A11: АУПТ: проверка манометров | F11: Х | L11: Х
A12: АУПТ: поверка манометров с опломбированием (ЦСМ) | F12: Х
A13: АУПТ ТЭЦ-2: опрессовка, промывка, пуск (ГК, ПГУ-115, ВК, МН) | H13: Х | I13: Х
A14: Замена вышедшего из строя оборудования (ЗИП) — по факту | B14: Х | C14: Х | D14: Х | E14: Х | F14: Х | G14: Х | H14: Х | I14: Х | J14: Х | K14: Х | L14: Х | M14: Х
A15: Ежемесячные акты и отчёты, журналы ТО | B15: Х | C15: Х | D15: Х | E15: Х | F15: Х | G15: Х | H15: Х | I15: Х | J15: Х | K15: Х | L15: Х | M15: Х
A17: Ресурсы и выручка (руб. без НДС) | B17: янв | C17: фев | D17: мар | E17: апр | F17: май | G17: июн | H17: июл | I17: авг | J17: сен | K17: окт | L17: ноя | M17: дек | N17: Итого
A18: Выручка: регламентное ТО | B18: =Работы!$K$99 -> 1491515.2 | C18: =Работы!$K$99 -> 1491515.2 | D18: =Работы!$K$99 -> 1491515.2 | E18: =Работы!$K$99 -> 1491515.2 | F18: =Работы!$K$99 -> 1491515.2 | G18: =Работы!$K$99 -> 1491515.2 | H18: =Работы!$K$99 -> 1491515.2 | I18: =Работы!$K$99 -> 1491515.2 | ... M18: =Работы!$K$99 -> 1491515.2 | N18: =SUM(B18:M18) -> 17898182
A19: Выручка: разовые работы | B19: =0 -> 0 | C19: =0 -> 0 | D19: =0 -> 0 | E19: =0 -> 0 | F19: =Работы!J104*1 -> 28000 | G19: =Работы!J105*1+Работы!J106*1 -> 90425 | H19: =Работы!J102*0.5 -> 478080 | I19: =Работы!J102*0.5+Работы!J103*1 -> 610080 | J19: =0 -> 0 | K19: =0 -> 0 | L19: =0 -> 0 | M19: =0 -> 0 | N19: =SUM(B19:M19) -> 1206585
A20: Выручка: ЗИП (замена по факту, равномерно) | B20: =Материалы!$Q$22/12 -> 13945.653 | C20: =Материалы!$Q$22/12 -> 13945.653 | D20: =Материалы!$Q$22/12 -> 13945.653 | E20: =Материалы!$Q$22/12 -> 13945.653 | F20: =Материалы!$Q$22/12 -> 13945.653 | G20: =Материалы!$Q$22/12 -> 13945.653 | H20: =Материалы!$Q$22/12 -> 13945.653 | I20: =Материалы!$Q$22/12 -> 13945.653 | ... M20: =Материалы!$Q$22/12 -> 13945.653 | N20: =SUM(B20:M20) -> 167347.83
A21: ВЫРУЧКА ВСЕГО | B21: =B18+B19+B20 -> 1505460.8 | C21: =C18+C19+C20 -> 1505460.8 | D21: =D18+D19+D20 -> 1505460.8 | E21: =E18+E19+E20 -> 1505460.8 | F21: =F18+F19+F20 -> 1533460.8 | G21: =G18+G19+G20 -> 1595885.8 | H21: =H18+H19+H20 -> 1983540.8 | I21: =I18+I19+I20 -> 2115540.8 | ... M21: =M18+M19+M20 -> 1505460.8 | N21: =SUM(B21:M21) -> 19272115
A22: Чел.-ч: регламентное ТО и оформление | B22: =Работы!$M$99/12*(1+'Персонал ТО'!$C$9) -> 705.42846 | C22: =Работы!$M$99/12*(1+'Персонал ТО'!$C$9) -> 705.42846 | D22: =Работы!$M$99/12*(1+'Персонал ТО'!$C$9) -> 705.42846 | E22: =Работы!$M$99/12*(1+'Персонал ТО'!$C$9) -> 705.42846 | F22: =Работы!$M$99/12*(1+'Персонал ТО'!$C$9) -> 705.42846 | G22: =Работы!$M$99/12*(1+'Персонал ТО'!$C$9) -> 705.42846 | H22: =Работы!$M$99/12*(1+'Персонал ТО'!$C$9) -> 705.42846 | I22: =Работы!$M$99/12*(1+'Персонал ТО'!$C$9) -> 705.42846 | ... M22: =Работы!$M$99/12*(1+'Персонал ТО'!$C$9) -> 705.42846 | N22: =SUM(B22:M22) -> 8465.1415
A23: Чел.-ч: разовые работы | B23: =0*(1+'Персонал ТО'!$C$9) -> 0 | C23: =0*(1+'Персонал ТО'!$C$9) -> 0 | D23: =0*(1+'Персонал ТО'!$C$9) -> 0 | E23: =0*(1+'Персонал ТО'!$C$9) -> 0 | F23: =Работы!M104*1*(1+'Персонал ТО'!$C$9) -> 19.25 | G23: =Работы!M105*1+Работы!M106*1*(1+'Персонал ТО'!$C$9) -> 41.75 | H23: =Работы!M102*0.5*(1+'Персонал ТО'!$C$9) -> 350.592 | I23: =Работы!M102*0.5+Работы!M103*1*(1+'Персонал ТО'!$C$9) -> 424.32 | J23: =0*(1+'Персонал ТО'!$C$9) -> 0 | K23: =0*(1+'Персонал ТО'!$C$9) -> 0 | L23: =0*(1+'Персонал ТО'!$C$9) -> 0 | M23: =0*(1+'Персонал ТО'!$C$9) -> 0 | N23: =SUM(B23:M23) -> 835.912
A24: Чел.-ч: первичное обследование | B24: ='Персонал ТО'!$C$7/2*(1+'Персонал ТО'!$C$9) -> 143 | C24: ='Персонал ТО'!$C$7/2*(1+'Персонал ТО'!$C$9) -> 143 | D24: =0 -> 0 | E24: =0 -> 0 | F24: =0 -> 0 | G24: =0 -> 0 | H24: =0 -> 0 | I24: =0 -> 0 | J24: =0 -> 0 | K24: =0 -> 0 | ... M24: =0 -> 0 | N24: =SUM(B24:M24) -> 286
A25: Чел.-ч: замена ЗИП | B25: =Материалы!$N$22/12*(1+'Персонал ТО'!$C$9) -> 10.454583 | C25: =Материалы!$N$22/12*(1+'Персонал ТО'!$C$9) -> 10.454583 | D25: =Материалы!$N$22/12*(1+'Персонал ТО'!$C$9) -> 10.454583 | E25: =Материалы!$N$22/12*(1+'Персонал ТО'!$C$9) -> 10.454583 | F25: =Материалы!$N$22/12*(1+'Персонал ТО'!$C$9) -> 10.454583 | G25: =Материалы!$N$22/12*(1+'Персонал ТО'!$C$9) -> 10.454583 | H25: =Материалы!$N$22/12*(1+'Персонал ТО'!$C$9) -> 10.454583 | I25: =Материалы!$N$22/12*(1+'Персонал ТО'!$C$9) -> 10.454583 | ... M25: =Материалы!$N$22/12*(1+'Персонал ТО'!$C$9) -> 10.454583 | N25: =SUM(B25:M25) -> 125.455
A26: Чел.-ч всего | B26: =SUM(B22:B25) -> 858.88304 | C26: =SUM(C22:C25) -> 858.88304 | D26: =SUM(D22:D25) -> 715.88304 | E26: =SUM(E22:E25) -> 715.88304 | F26: =SUM(F22:F25) -> 735.13304 | G26: =SUM(G22:G25) -> 757.63304 | H26: =SUM(H22:H25) -> 1066.475 | I26: =SUM(I22:I25) -> 1140.203 | ... M26: =SUM(M22:M25) -> 715.88304 | N26: =SUM(B26:M26) -> 9712.5085
A27: Требуется техников, чел. (при коэф. использования) | B27: =B26/('Персонал ТО'!$C$11/12*'Персонал ТО'!$C$12) -> 7.109959 | C27: =C26/('Персонал ТО'!$C$11/12*'Персонал ТО'!$C$12) -> 7.109959 | D27: =D26/('Персонал ТО'!$C$11/12*'Персонал ТО'!$C$12) -> 5.9261841 | E27: =E26/('Персонал ТО'!$C$11/12*'Персонал ТО'!$C$12) -> 5.9261841 | F27: =F26/('Персонал ТО'!$C$11/12*'Персонал ТО'!$C$12) -> 6.0855384 | G27: =G26/('Персонал ТО'!$C$11/12*'Персонал ТО'!$C$12) -> 6.2717967 | H27: =H26/('Персонал ТО'!$C$11/12*'Персонал ТО'!$C$12) -> 8.8284358 | I27: =I26/('Персонал ТО'!$C$11/12*'Персонал ТО'!$C$12) -> 9.4387669 | ... M27: =M26/('Персонал ТО'!$C$11/12*'Персонал ТО'!$C$12) -> 5.9261841 | N27: =SUM(B27:M27) -> 80.401561
A28: Принято техников в штате, чел. | B28: ='Персонал ТО'!$C$14 -> 7 | C28: ='Персонал ТО'!$C$14 -> 7 | D28: ='Персонал ТО'!$C$14 -> 7 | E28: ='Персонал ТО'!$C$14 -> 7 | F28: ='Персонал ТО'!$C$14 -> 7 | G28: ='Персонал ТО'!$C$14 -> 7 | H28: ='Персонал ТО'!$C$14 -> 7 | I28: ='Персонал ТО'!$C$14 -> 7 | ... M28: ='Персонал ТО'!$C$14 -> 7 | N28: =SUM(B28:M28) -> 84
A30: Ресурсы: штат техников (лист «Персонал ТО») + мастер в Воронеже; пики — июнь (ЭТЛ, квартальная профилактика) и июль–август (гидроиспытания ТЭЦ-2) — закрываются перераспределением ежемесячного ТО и сверхурочными; ЭТЛ и ЦСМ — субподряд.

Sheet Кэш-план
A1: КЭШ-ПЛАН 2027, руб. без НДС
A2: Акт — по итогам месяца; оплата в течение 7 рабочих дней после подписания акта → поступление в следующем месяце (декабрь — в январе 2028). Аванса нет. НДС не моделируется.
A4: Статья | B4: янв | C4: фев | D4: мар | E4: апр | F4: май | G4: июн | H4: июл | I4: авг | J4: сен | K4: окт | L4: ноя | M4: дек | N4: Итого
A5: Поступления от заказчика (выручка прошлого месяца) | B5: =0 -> 0 | C5: ='График и ресурсы'!B21 -> 1505460.8 | D5: ='График и ресурсы'!C21 -> 1505460.8 | E5: ='График и ресурсы'!D21 -> 1505460.8 | F5: ='График и ресурсы'!E21 -> 1505460.8 | G5: ='График и ресурсы'!F21 -> 1533460.8 | H5: ='График и ресурсы'!G21 -> 1595885.8 | I5: ='График и ресурсы'!H21 -> 1983540.8 | J5: ='График и ресурсы'!I21 -> 2115540.8 | ... M5: ='График и ресурсы'!L21 -> 1505460.8 | N5: =SUM(B5:M5) -> 17766654
A6: ФОТ техников (с налогами) | B6: =-'Персонал ТО'!$C$16/12 -> -857500 | C6: =-'Персонал ТО'!$C$16/12 -> -857500 | D6: =-'Персонал ТО'!$C$16/12 -> -857500 | E6: =-'Персонал ТО'!$C$16/12 -> -857500 | F6: =-'Персонал ТО'!$C$16/12 -> -857500 | G6: =-'Персонал ТО'!$C$16/12 -> -857500 | H6: =-'Персонал ТО'!$C$16/12 -> -857500 | I6: =-'Персонал ТО'!$C$16/12 -> -857500 | ... M6: =-'Персонал ТО'!$C$16/12 -> -857500 | N6: =SUM(B6:M6) -> -10290000
A7: Косвенные (ИТР, транспорт, допуски, резервы — равномерно) | B7: =-Косвенные!$G$21/12 -> -457253.35 | C7: =-Косвенные!$G$21/12 -> -457253.35 | D7: =-Косвенные!$G$21/12 -> -457253.35 | E7: =-Косвенные!$G$21/12 -> -457253.35 | F7: =-Косвенные!$G$21/12 -> -457253.35 | G7: =-Косвенные!$G$21/12 -> -457253.35 | H7: =-Косвенные!$G$21/12 -> -457253.35 | I7: =-Косвенные!$G$21/12 -> -457253.35 | ... M7: =-Косвенные!$G$21/12 -> -457253.35 | N7: =SUM(B7:M7) -> -5487040.2
A8: Закупка ЗИП (с/с) | B8: =-Материалы!$M$22/12 -> -14761.753 | C8: =-Материалы!$M$22/12 -> -14761.753 | D8: =-Материалы!$M$22/12 -> -14761.753 | E8: =-Материалы!$M$22/12 -> -14761.753 | F8: =-Материалы!$M$22/12 -> -14761.753 | G8: =-Материалы!$M$22/12 -> -14761.753 | H8: =-Материалы!$M$22/12 -> -14761.753 | I8: =-Материалы!$M$22/12 -> -14761.753 | ... M8: =-Материалы!$M$22/12 -> -14761.753 | N8: =SUM(B8:M8) -> -177141.03
A9: Субподряд и расходники разовых работ | B9: =-(0) -> 0 | C9: =-(0) -> 0 | D9: =-(0) -> 0 | E9: =-(0) -> 0 | F9: =-((Работы!P104+Работы!O104)*1) -> -5656.475 | G9: =-((Работы!P105+Работы!O105)*1+(Работы!P106+Работы!O106)*1) -> -31723.279 | H9: =-((Работы!P102+Работы!O102)*0.5) -> -33962.955 | I9: =-((Работы!P102+Работы!O102)*0.5+(Работы!P103+Работы!O103)*1) -> -36192.761 | J9: =-(0) -> 0 | K9: =-(0) -> 0 | L9: =-(0) -> 0 | M9: =-(0) -> 0 | N9: =SUM(B9:M9) -> -107535.47
A10: Расходники регламентного ТО | B10: =-Работы!$O$99/12 -> -14895.535 | C10: =-Работы!$O$99/12 -> -14895.535 | D10: =-Работы!$O$99/12 -> -14895.535 | E10: =-Работы!$O$99/12 -> -14895.535 | F10: =-Работы!$O$99/12 -> -14895.535 | G10: =-Работы!$O$99/12 -> -14895.535 | H10: =-Работы!$O$99/12 -> -14895.535 | I10: =-Работы!$O$99/12 -> -14895.535 | ... M10: =-Работы!$O$99/12 -> -14895.535 | N10: =SUM(B10:M10) -> -178746.42
A11: Сальдо месяца | B11: =SUM(B5:B10) -> -1344410.6 | C11: =SUM(C5:C10) -> 161050.19 | D11: =SUM(D5:D10) -> 161050.19 | E11: =SUM(E5:E10) -> 161050.19 | F11: =SUM(F5:F10) -> 155393.72 | G11: =SUM(G5:G10) -> 157326.91 | H11: =SUM(H5:H10) -> 217512.24 | I11: =SUM(I5:I10) -> 602937.43 | ... M11: =SUM(M5:M10) -> 161050.19 | N11: =SUM(B11:M11) -> 1526191
A12: Нарастающий итог | B12: =B11 -> -1344410.6 | C12: =B12+C11 -> -1183360.4 | D12: =C12+D11 -> -1022310.3 | E12: =D12+E11 -> -861260.06 | F12: =E12+F11 -> -705866.34 | G12: =F12+G11 -> -548539.43 | H12: =G12+H11 -> -331027.19 | I12: =H12+I11 -> 271910.24 | J12: =I12+J11 -> 1043040.4 | ... M12: =L12+M11 -> 1526191 | N12: =M12 -> 1526191
A14: Максимальный кассовый разрыв, руб. | B14: =-MIN(B12:M12) -> 1344410.6
A15: Стоимость разрыва (2 %/мес × средний разрыв × 12), руб. — учтена в «Косвенных» строкой «Финансирование»
A16: Поступление за декабрь 2027 приходит в январе 2028 — в итог года не попадает (дебиторка на 31.12).

Sheet Контрольные точки
A1: КОНТРОЛЬНЫЕ ТОЧКИ И РИСКИ РЕАЛИЗАЦИИ
A3: Контрольная точка | B3: Срок | C3: Ответственный | D3: Примечание
A4: Подача заявки на b2b-center (№ 57697) | B4: до 30.10.2026 08:00 МСК | C4: Тендерный отдел | D4: Вскрытие 30.10.2026
A5: Подписание договора | B5: декабрь 2026 | C5: ГД | D5: Проект договора не получен
A6: Найм техников (Воронеж), обучение, медосмотр, допуски | B6: до 25.12.2026 | C6: РП | D6: 6–7 чел. + мастер
A7: Допуск на ТЭЦ, инструктажи, приказы | B7: до 10.01.2027 | C7: Мастер
A8: Акт первичного обследования | B8: февраль 2027 | C8: Мастер | D8: Фиксируем исходное состояние систем
A9: Поверка манометров | B9: май 2027 | C9: Мастер | D9: ЦСМ Воронеж
A10: Измерения ЭТЛ | B10: июнь 2027 | C10: Мастер | D10: Субподряд ЭТЛ
A11: Гидроиспытания и пуск АУПТ ТЭЦ-2 | B11: июль–август 2027 | C11: РП | D11: Программа испытаний согласовать в мае
A12: Ежемесячные акты | B12: до 5 числа след. месяца | C12: Мастер | D12: Оплата 7 р.д. после акта
A14: Риск реализации | B14: Владелец | C14: Мера | D14: Влияние
A15: Не успеть набрать штат к 01.01.2027 | B15: РП | C15: Начать найм сразу после итогов | D15: Срыв ТО → штрафы
A16: Исходное состояние систем хуже ожидаемого | B16: Мастер | C16: Акт первичного обследования с дефектной ведомостью | D16: Ремонт вне цены ТО
A17: Задержка подписания актов | B17: РП | C17: Акты до 5 числа, электронный документооборот | D17: Кассовый разрыв
A18: Рост цен на ЗИП | B18: Снабжение | C18: Резерв 7,5 % в с/с ЗИП | D18: Маржа ЗИП

Sheet Оборудование (ТЗ)
A1: ОБОРУДОВАНИЕ ПО ПРИЛОЖЕНИЯМ 1–8 ТЗ С ПРИСВОЕННЫМ КОДОМ УСЛУГИ
A2: Исходные строки ТЗ без изменений; кол-во — как в ТЗ (кабель и трубы в м).
A4: Прил. | B4: Раздел / помещение | C4: № | D4: Наименование | E4: Ед. | F4: Кол-во (как в ТЗ) | G4: Кол-во (число) | H4: Код услуги | I4: Примечание ТЗ
A5: 1 | B5: 1. Теплая стоянка автомобилей. | C5: 1.1 | D5: Прибор приемно-контрольный «Гранит-2» | E5: шт. | F5: 1 | G5: 1 | H5: PPK
A6: 1 | B6: 1. Теплая стоянка автомобилей. | C6: 1.2 | D6: Прибор приемно-контрольный «ППС-10» | E6: шт. | F6: 2 | G6: 2 | H6: PPK
A7: 1 | B7: 1. Теплая стоянка автомобилей. | C7: 1.3 | D7: Прибор приемно-контрольный «Сигнал-44» | E7: шт. | F7: 1 | G7: 1 | H7: PPK
A8: 1 | B8: 1. Теплая стоянка автомобилей. | C8: 1.4 | D8: Извещатель пожарный тепловой ИП 103-5 | E8: шт. | F8: 21 | G8: 21 | H8: DET_AUTO
A9: 1 | B9: 1. Теплая стоянка автомобилей. | C9: 1.5 | D9: Извещатель пожарный ручной ИР-1 | E9: шт. | F9: 3 | G9: 3 | H9: DET_MAN
A10: 1 | B10: 1. Теплая стоянка автомобилей. | C10: 1.6 | D10: Световое табло «Выход» | E10: шт. | F10: 3 | G10: 3 | H10: ANN
A11: 1 | B11: 1. Теплая стоянка автомобилей. | C11: 1.7 | D11: Оповещатель светозвуковой «Маяк-12КП » | E11: шт. | F11: 3 | G11: 3 | H11: ANN
A12: 1 | B12: 1. Теплая стоянка автомобилей. | C12: 1.8 | D12: Кабель FRLS 4*0.5 | E12: м. | F12: 200 | G12: 200 | H12: CABLE
A13: 1 | B13: 2. Помещение ООТиПБ | C13: 2.1 | D13: Извещатель пожарный дымовой ИП212-141 | E13: шт. | F13: 30 | G13: 30 | H13: DET_AUTO
A14: 1 | B14: 2. Помещение ООТиПБ | C14: 2.2 | D14: Извещатель пожарный ручной ИР-1 | E14: шт. | F14: 2 | G14: 2 | H14: DET_MAN
A15: 1 | B15: 2. Помещение ООТиПБ | C15: 2.3 | D15: Оповещатель светозвуковой «Маяк-12КП » | E15: шт. | F15: 1 | G15: 1 | H15: ANN
A16: 1 | B16: 2. Помещение ООТиПБ | C16: 2.4 | D16: Световое табло «Выход» | E16: шт. | F16: 2 | G16: 2 | H16: ANN
... A272: 2 | B272: 5. Маслохозяйство. Маслоаппаратная. (ПГУ 223 МВт) | C272: 5.15 | D272: Провод установочный ПВ-3 1х6.0 мм | E272: м. | F272: 2.5 | G272: 2.5 | H272: CABLE
A273: 2 | B273: 6. Главный корпус.(ПГУ 223 МВт) | C273: 6.1 | D273: Программное обеспечение «Орион Про» | G273: 0 | H273: SW
A274: 2 | B274: 6. Главный корпус.(ПГУ 223 МВт) | C274: 6.2 | D274: Пульт контроля и управления С2000М | E274: шт. | F274: 1 | G274: 1 | H274: PPK
A275: 2 | B275: 6. Главный корпус.(ПГУ 223 МВт) | C275: 6.3 | D275: Прибор управления автоматическими средствами пожаротушения и оповещателями «С2000-АСПТ» | E275: шт. | F275: 2 | G275: 2 | H275: ANN
A276: 2 | B276: 6. Главный корпус.(ПГУ 223 МВт) | C276: 6.4 | D276: Контролёр двухпроводной линии связи «С2000-КДЛ» | E276: шт. | F276: 10 | G276: 10 | H276: BLOCK
A277: 2 | B277: 6. Главный корпус.(ПГУ 223 МВт) | C277: 6.5 | D277: Исполнительный релейный блок «С2000-СП1» | E277: шт. | F277: 10 | G277: 10 | H277: BLOCK
A278: 2 | B278: 6. Главный корпус.(ПГУ 223 МВт) | C278: 6.6 | D278: Преобразователь интерфейсов «С2000-ПИ» | E278: шт. | F278: 1 | G278: 1 | H278: BLOCK
A279: 2 | B279: 6. Главный корпус.(ПГУ 223 МВт) | C279: 6.7 | D279: Пульт управления «С2000-ПУ» | E279: шт. | F279: 2 | G279: 2 | H279: BLOCK
A280: 2 | B280: 6. Главный корпус.(ПГУ 223 МВт) | C280: 6.8 | D280: Блок контрольно-пусковой «С2000-КПБ» | E280: шт. | F280: 6 | G280: 6 | H280: ANN
A281: 2 | B281: 6. Главный корпус.(ПГУ 223 МВт) | C281: 6.9 | D281: Прибор приёмно-контрольный охранно-пожарный адресный «Сигнал-20П SMD» | E281: шт. | F281: 1 | G281: 1 | H281: PPK
A282: 2 | B282: 6. Главный корпус.(ПГУ 223 МВт) | C282: 6.10 | D282: Прибор приёмно-контрольный охранно-пожарный «Сигнал-10» | E282: шт. | F282: 12 | G282: 12 | H282: PPK
A283: 2 | B283: 6. Главный корпус.(ПГУ 223 МВт) | C283: 6.11 | D283: Блок индикации системы пожаротушения «С2000-ПТ» | E283: шт. | F283: 6 | G283: 6 | H283: BLOCK
A284: 2 | B284: 6. Главный корпус.(ПГУ 223 МВт) | C284: 6.12 | D284: Блок индикации с клавиатурой «С2000-БКИ» | E284: шт. | F284: 6 | G284: 6 | H284: BLOCK
A285: 2 | B285: 6. Главный корпус.(ПГУ 223 МВт) | C285: 6.13 | D285: Извещатель пожарный ручной ИПР 513-3АМ | E285: шт. | F285: 42 | G285: 42 | H285: DET_MAN
... A342: 2 | B342: 8. Блочный пункт подготовки газа. (ПГУ 223 МВт) | C342: 8.15 | D342: Резервный источник питания «Скат-1200» | E342: шт. | F342: 2 | G342: 2 | H342: PSU
A343: 2 | B343: 8. Блочный пункт подготовки газа. (ПГУ 223 МВт) | C343: 8.16 | D343: Аккумуляторная батарея 12В. 4.5А/ч | F343: 6 | G343: 6 | H343: AKB
A344: 2 | B344: 8. Блочный пункт подготовки газа. (ПГУ 223 МВт) | C344: 8.17 | D344: Аккумуляторная батарея 12В. 17А/ч | F344: 1 | G344: 1 | H344: AKB
A345: 3 | B345: 1. Одноэтажное здание АБК | C345: 1.1. | D345: Извещатель дымовой оптико-электронный точечный ИП 212-34А | E345: шт | F345: 18 | G345: 18 | H345: DET_AUTO
A346: 3 | B346: 1. Одноэтажное здание АБК | C346: 1.2. | D346: Извещатель пожарный ручной адресный электроконтактный ИПР 513-3АМ | E346: шт | F346: 2 | G346: 2 | H346: DET_MAN
A347: 3 | B347: 1. Одноэтажное здание АБК | C347: 1.3. | D347: Оповещатель пожарный световое табло Молния-12 «Выход» | E347: шт | F347: 2 | G347: 2 | H347: ANN
A348: 3 | B348: 1. Одноэтажное здание АБК | C348: 1.4. | D348: Оповещатель пожарный звуковой «Маяк-12-3М1» | E348: шт | F348: 3 | G348: 3 | H348: ANN
A349: 3 | B349: 1. Одноэтажное здание АБК | C349: 1.5. | D349: Оповещательсвето-звуковой «УСС-М-12» | E349: шт | F349: 2 | G349: 2 | H349: ANN
A350: 3 | B350: 1. Одноэтажное здание АБК | C350: 1.6. | D350: Контроллер двухпроводной линии «С2000-КДЛ» | E350: шт | F350: 1 | G350: 1 | H350: BLOCK
A351: 3 | B351: 1. Одноэтажное здание АБК | C351: 1.7. | D351: Модуль релейный «С2000-СП1» | E351: шт | F351: 1 | G351: 1 | H351: BLOCK
A352: 3 | B352: 1. Одноэтажное здание АБК | C352: 1.8. | D352: Блок контрольно-пусковой «С2000-КПБ» | E352: шт | F352: 1 | G352: 1 | H352: ANN
A353: 3 | B353: 1. Одноэтажное здание АБК | C353: 1.9. | D353: Блок защиты линии «С2000-БЗЛ» | E353: шт | F353: 1 | G353: 1 | H353: BLOCK
A354: 3 | B354: 1. Одноэтажное здание АБК | C354: 1.10. | D354: Источник питания БРП 12-3/7 | E354: шт | F354: 1 | G354: 1 | H354: PSU
A355: 3 | B355: 1. Одноэтажное здание АБК | C355: 1.11. | D355: Извещатель охранный оптико-электронный «С2000-ИК» | E355: шт | F355: 18 | G355: 18 | H355: DET_SEC
A356: 3 | B356: 1. Одноэтажное здание АБК | C356: 1.12. | D356: Блок разветвительно-изолирующий «БРИЗ» | E356: шт | F356: 3 | G356: 3 | H356: BLOCK
... A655: 5 | B655: 14. Помещения административного здания АБК-4, проезд Ясный, 1а | C655: 14.15 | D655: Кабель парной скрутки КПСЭСнг(A)-FRLS 2х2х0,5 | E655: м | F655: 10 | G655: 10 | H655: CABLE
A656: 6 | B656: Ввод технической воды №1 | D656: Труба Ø 219х6 Ст20 | E656: м. | F656: 52 | G656: 52 | H656: PIPE
A657: 6 | B657: Ввод технической воды №1 | D657: Труба Ø 32х2 Ст20 | E657: м. | F657: 124 | G657: 124 | H657: PIPE | I657: Обогрев
A658: 6 | B658: Ввод технической воды №1 | D658: Задвижка ДУ200. Ру25 | E658: шт. | F658: 1 | G658: 1 | H658: VALVE_MAN | I658: С ручным приводом
A659: 6 | B659: Ввод технической воды №2 | D659: Труба Ø 219х6 Ст20 | E659: м. | F659: 59 | G659: 59 | H659: PIPE
A660: 6 | B660: Ввод технической воды №2 | D660: Труба Ø 32х2 Ст20 | E660: м. | F660: 128 | G660: 128 | H660: PIPE | I660: Обогрев
A661: 6 | B661: Ввод технической воды №2 | D661: Задвижка ДУ200. Ру25 | E661: шт. | F661: 1 | G661: 1 | H661: VALVE_MAN | I661: С ручным приводом
A662: 6 | B662: Коллектор | D662: Труба Ø 219х6 Ст20 | E662: м. | F662: 23 | G662: 23 | H662: PIPE
A663: 6 | B663: Коллектор | D663: Задвижка 30ч6бр ДУ200. Ру10 | E663: шт. | F663: 5 | G663: 5 | H663: VALVE_MAN
A664: 6 | B664: Коллектор | D664: Манометр | E664: шт. | F664: 1 | G664: 1 | H664: GAUGE
A665: 6 | B665: Луч №1 | D665: Труба Ø 159х4.5 Ст20 | E665: м. | F665: 320 | G665: 320 | H665: PIPE
A666: 6 | B666: Луч №1 | D666: Задвижка 30ч6бр ДУ150. Ру10 | E666: шт. | F666: 1 | G666: 1 | H666: VALVE_MAN | I666: С ручным приводом
A667: 6 | B667: Луч №1 | D667: Задвижка СТ25 ЛDN150 Ру16 | E667: шт. | F667: 1 | G667: 1 | H667: VALVE_EL | I667: С электроприводом
A668: 6 | B668: Луч №1 | D668: Ороситель ДВМ | E668: шт. | F668: 40 | G668: 40 | H668: SPRINK
A669: 6 | B669: Луч №2 | D669: Труба Ø 108х3 Ст20 | E669: м. | F669: 192 | G669: 192 | H669: PIPE
A670: 6 | B670: Луч №2 | D670: Задвижка 30ч6бр ДУ100. Ру10 | E670: шт. | F670: 1 | G670: 1 | H670: VALVE_MAN | I670: С ручным приводом
A671: 6 | B671: Луч №2 | D671: Задвижка СТ25 ЛDN100 Ру16 | E671: шт. | F671: 1 | G671: 1 | H671: VALVE_EL | I671: С электроприводом
A672: 6 | B672: Луч №2 | D672: Ороситель ДВМ | E672: шт. | F672: 24 | G672: 24 | H672: SPRINK
A673: 6 | B673: Луч №3 | D673: Труба Ø 89х3 Ст20 | E673: м. | F673: 129 | G673: 129 | H673: PIPE
A674: 6 | B674: Луч №3 | D674: Задвижка 30ч6бр ДУ100. Ру10 | E674: шт. | F674: 1 | G674: 1 | H674: VALVE_MAN | I674: С ручным приводом
A675: 6 | B675: Луч №3 | D675: Задвижка СТ25 ЛDN100 Ру16 | E675: шт. | F675: 1 | G675: 1 | H675: VALVE_EL | I675: С электроприводом
A676: 6 | B676: Луч №3 | D676: Ороситель ДВМ | E676: шт. | F676: 27 | G676: 27 | H676: SPRINK
A677: 6 | B677: Луч №4 | D677: Труба Ø 108х3 Ст20 | E677: м. | F677: 37 | G677: 37 | H677: PIPE
A678: 6 | B678: Луч №4 | D678: Задвижка 30ч6бр ДУ100. Ру10 | E678: шт. | F678: 1 | G678: 1 | H678: VALVE_MAN | I678: С ручным приводом
A679: 6 | B679: Луч №4 | D679: Задвижка 30ч6бр ДУ100. Ру10 | E679: шт. | F679: 1 | G679: 1 | H679: VALVE_EL | I679: С электроприводом
A680: 6 | B680: Луч №4 | D680: Ороситель ДВМ | E680: шт. | F680: 25 | G680: 25 | H680: SPRINK
A681: 6 | B681: Луч №5 | D681: Труба Ø 108х3 Ст20 | E681: м. | F681: 42 | G681: 42 | H681: PIPE
A682: 6 | B682: Луч №5 | D682: Задвижка 30ч6бр ДУ100. Ру10 | E682: шт. | F682: 1 | G682: 1 | H682: VALVE_MAN | I682: С ручным приводом
A683: 6 | B683: Луч №5 | D683: Задвижка 30ч6бр ДУ100. Ру10 | E683: шт. | F683: 1 | G683: 1 | H683: VALVE_EL | I683: С электроприводом
A684: 6 | B684: Луч №5 | D684: Ороситель ДВМ | E684: шт. | F684: 11 | G684: 11 | H684: SPRINK
A685: 6 | B685: Луч №6 | D685: Труба Ø 89х3 Ст20 | E685: м. | F685: 24 | G685: 24 | H685: PIPE
A686: 6 | B686: Луч №6 | D686: Задвижка 30ч6бр ДУ100. Ру10 | E686: шт. | F686: 1 | G686: 1 | H686: VALVE_MAN | I686: С ручным приводом
A687: 6 | B687: Луч №6 | D687: Задвижка СТ25 ЛDN100 Ру16 | E687: шт. | F687: 1 | G687: 1 | H687: VALVE_EL | I687: С электроприводом
A688: 6 | B688: Луч №6 | D688: Ороситель ДВМ | E688: шт. | F688: 16 | G688: 16 | H688: SPRINK
A689: 6 | B689: Луч №7 | D689: Труба Ø 108х3 Ст20 | E689: м. | F689: 62 | G689: 62 | H689: PIPE
A690: 6 | B690: Луч №7 | D690: Задвижка 30ч6бр ДУ100. Ру10 | E690: шт. | F690: 1 | G690: 1 | H690: VALVE_MAN | I690: С ручным приводом
A691: 6 | B691: Луч №7 | D691: Задвижка СТ25 ЛDN100 Ру16 | E691: шт. | F691: 1 | G691: 1 | H691: VALVE_EL | I691: С электроприводом
A692: 6 | B692: Луч №7 | D692: Ороситель ДВМ | E692: шт. | F692: 13 | G692: 13 | H692: SPRINK
A693: 6 | B693: Луч №8 | D693: Труба Ø 108х3 Ст20 | E693: м. | F693: 45 | G693: 45 | H693: PIPE
A694: 6 | B694: Луч №8 | D694: Задвижка 30ч6бр ДУ200. Ру10 | E694: шт. | F694: 1 | G694: 1 | H694: VALVE_MAN | I694: С ручным приводом
A695: 6 | B695: Луч №8 | D695: Задвижка 30ч6бр ДУ150. Ру10 | E695: шт. | F695: 1 | G695: 1 | H695: VALVE_EL | I695: С электроприводом
A696: 6 | B696: Луч №8 | D696: Ороситель ДВМ | E696: шт. | F696: 32 | G696: 32 | H696: SPRINK
A697: 6 | B697: Луч №9 | D697: Труба Ø 159х4.5 Ст20 | E697: м. | F697: 23 | G697: 23 | H697: PIPE
A698: 6 | B698: Луч №9 | D698: Задвижка 30ч6бр ДУ150. Ру10 | E698: шт. | F698: 1 | G698: 1 | H698: VALVE_MAN | I698: С ручным приводом
A699: 6 | B699: Луч №9 | D699: Задвижка 30ч6бр ДУ150. Ру10 | E699: шт. | F699: 1 | G699: 1 | H699: VALVE_EL | I699: С электроприводом
A700: 6 | B700: Луч №9 | D700: Ороситель ДВМ | E700: шт. | F700: 15 | G700: 15 | H700: SPRINK
A701: 6 | B701: Луч №10 | D701: Труба Ø 159х4.5 Ст20 | E701: м. | F701: 90 | G701: 90 | H701: PIPE
A702: 6 | B702: Луч №10 | D702: Задвижка 30ч6бр ДУ150. Ру10 | E702: шт. | F702: 1 | G702: 1 | H702: VALVE_MAN | I702: С ручным приводом
A703: 6 | B703: Луч №10 | D703: Задвижка 30ч6бр ДУ200. Ру10 | E703: шт. | F703: 1 | G703: 1 | H703: VALVE_EL | I703: С электроприводом
A704: 6 | B704: Луч №10 | D704: Ороситель ДВМ | E704: шт. | F704: 20 | G704: 20 | H704: SPRINK
A705: 6 | B705: Луч №11 | D705: Труба Ø 159х4.5 Ст20 | E705: м. | F705: 42 | G705: 42 | H705: PIPE
A706: 6 | B706: Луч №11 | D706: Труба Ø 108х3 Ст20 | E706: м. | F706: 28 | G706: 28 | H706: PIPE
A707: 6 | B707: Луч №11 | D707: Задвижка ДУ150. Ру25 | E707: шт. | F707: 1 | G707: 1 | H707: VALVE_MAN | I707: С ручным приводом
A708: 6 | B708: Луч №11 | D708: Задвижка СТ25 ЛDN200. Ру16 | E708: шт. | F708: 1 | G708: 1 | H708: VALVE_EL | I708: С электроприводом
A709: 6 | B709: Луч №11 | D709: Ороситель ДВМ | E709: шт. | F709: 34 | G709: 34 | H709: SPRINK
A710: 6 | B710: Луч №12 | D710: Труба Ø 89х3 Ст20 | E710: м. | F710: 17 | G710: 17 | H710: PIPE
...
