Workbook

Sheet Свод
A1: Бюджет себестоимости. Заказчику не отправлять.
A2: 235114, ПАО МТС, замена 65 фанкойлов, Петровский бульвар, 12, стр. 3
A3: Первичный расчёт. В заявку не класть: нет метров труб и кабеля, нет проекта, нет цен арматуры и пультов, ночной коэффициент не заложен.
A5: Показатель
A6: Закупка оборудования б/НДС | B6: =SUMPRODUCT(B25:B28,D25:D28)
A7: Доставка 3% | B7: =SUMPRODUCT(B25:B28,E25:E28)-B6
A8: Себестоимость оборудования | B8: =SUMPRODUCT(B25:B28,E25:E28)
A9: Оплата бригаде | B9: =Работы!G12
A10: Расходники 2% к бригаде | B10: =ROUND(B9*Параметры!B5,2)
A11: Полная себестоимость посчитанной части | B11: =B8+B9+B10
A12: КП материалы б/НДС | B12: =SUMPRODUCT(B25:B28,F25:F28)
A13: КП работы б/НДС | B13: =Работы!E12
A14: КП посчитанной части б/НДС | B14: =B12+B13
A15: Непредвиденные 5% по формуле формы | B15: =ROUND(B14*0.05,2)
A16: КП б/НДС с непредвиденными | B16: =B14+B15
A17: НДС 22% | B17: =ROUND(B16*0.22,2)
A18: КП с НДС | B18: =B16+B17
A19: Наценка на посчитанную себестоимость | B19: =IF(B11=0,"",B16/B11-1)
A20: Маржа | B20: =IF(B16=0,"",1-B11/B16)
A23: Оборудование
A24: Позиция | B24: Кол-во | C24: Цена сайта с НДС | D24: Без НДС | E24: С/с с доставкой | F24: КП за ед. | G24: С/с итого | H24: КП итого
A25: Фанкойл 4,20 кВт, аналог MDV MDKG-V500C | B25: 23 | C25: 160000 | D25: =ROUND(C25/1.22,2) | E25: =ROUND(D25*(1+Параметры!B3),2) | F25: =ROUND(E25*(1+Параметры!B4),2) | G25: =E25*B25 | H25: =F25*B25
A26: Фанкойл 5,35 кВт, аналог Dantex DF-600DL | B26: 32 | C26: 41440 | D26: =ROUND(C26/1.22,2) | E26: =ROUND(D26*(1+Параметры!B3),2) | F26: =ROUND(E26*(1+Параметры!B4),2) | G26: =E26*B26 | H26: =F26*B26
A27: Фанкойл 6,66 кВт, аналог SHUFT SFF-800 | B27: 6 | C27: 83990 | D27: =ROUND(C27/1.22,2) | E27: =ROUND(D27*(1+Параметры!B3),2) | F27: =ROUND(E27*(1+Параметры!B4),2) | G27: =E27*B27 | H27: =F27*B27
A28: Дополнительные точки, временно класс 5,35 | B28: 4 | C28: 41440 | D28: =ROUND(C28/1.22,2) | E28: =ROUND(D28*(1+Параметры!B3),2) | F28: =ROUND(E28*(1+Параметры!B4),2) | G28: =E28*B28 | H28: =F28*B28
A30: Диапазон наценки для сетей — 30–40%. Если наценка ниже, цену в заявку не отправлять без решения генерального директора. Непосчитанные трубы, кабель, арматура и проект наценку ещё снизят.

Sheet Работы
A1: Строка | B1: Работа | C1: Кол-во | D1: Цена КП | E1: Сумма КП | F1: Оплата бригаде за ед. | G1: Оплата бригаде | H1: Артикул | I1: Сопоставление | J1: Примечание
A2: 58 | B2: Демонтаж существующих фанкойлов | C2: 64 | D2: 4224 | E2: =C2*D2 | F2: 2415 | G2: =C2*F2 | H2: 1.9.11 | I2: аналог | J2: Демонтаж внутреннего блока 5–8 кВт. Старые блоки Daikin разной мощности, в строке они одной кучей.
A3: 67 | B3: Монтаж нового фанкойла | C3: 23 | D3: 5760 | E3: =C3*D3 | F3: 3200 | G3: =C3*F3 | H3: 9.3.145 | I3: оценка доли | J3: Расценка сплита 9 ч включает наружный блок и фреон. Их в лоте нет. Заложено 3 чел.-ч из 9.
A4: 68 | B4: Монтаж нового фанкойла | C4: 32 | D4: 7040 | E4: =C4*D4 | F4: 4100 | G4: =C4*F4 | H4: 9.3.146 | I4: оценка доли | J4: То же для мощности до 8 кВт: 3 чел.-ч из 11 ч расценки сплита.
A5: 69 | B5: Монтаж нового фанкойла | C5: 6 | D5: 7040 | E5: =C5*D5 | F5: 4100 | G5: =C5*F5 | H5: 9.3.146 | I5: оценка доли | J5: 6 блоков 6,66 кВт. Та же доля расценки до 8 кВт.
A6: 70 | B6: Монтаж новых фанкойлов в дополнительных точках | C6: 4 | D6: 7040 | E6: =C6*D6 | F6: 4100 | G6: =C6*F6 | H6: 9.3.146 | I6: оценка доли | J6: 4 точки без подтверждённой мощности. Временно как до 8 кВт.
A7: 71 | B7: Монтаж запорных кранов | C7: 130 | D7: 805 | E7: =C7*D7 | F7: 499 | G7: =C7*F7 | H7: 9.2.65 | I7: аналог | J7: Установка муфтового крана. Материал крана не оценён.
A8: 72 | B8: Монтаж сетчатых фильтров | C8: 65 | D8: 805 | E8: =C8*D8 | F8: 499 | G8: =C8*F8 | H8: 9.2.65 | I8: аналог | J8: Фильтр как муфтовая арматура. Материал не оценён.
A9: 73 | B9: Монтаж и настройка балансировочного клапана | C9: 65 | D9: 1035 | E9: =C9*D9 | F9: 642 | G9: =C9*F9 | H9: 9.2.N9 | I9: аналог | J9: Балансировочный клапан Ду15–32, только работа.
A10: 74 | B10: Монтаж двухходового регулирующего клапана и подключение привода | C10: 65 | D10: 6900 | E10: =C10*D10 | F10: 4278 | G10: =C10*F10 | H10: 9.2.59 | I10: аналог | J10: Двух/трёхходовой клапан с сервоприводом, только работа. Клапан в закупку не заложен.
A11: 102 | B11: Пуск и проверка вентилятора | C11: 65 | D11: 5800 | E11: =C11*D11 | F11: 3480 | G11: =C11*F11 | H11: 9.3.60 | I11: аналог | J11: Разовое обслуживание до 7 кВт как пакет проверок на точку. Строки 74–77 и 79–81 отдельно не суммируются, чтобы не удвоить пусконаладку.
B12: Итого | E12: =SUM(E2:E11) | G12: =SUM(G2:G11)

Sheet Цены материалов (источники)
A1: Позиция | B1: Магазин | C1: URL | D1: Дата | E1: Цена с НДС | F1: Цена без НДС | G1: Ед. | H1: Отметка
A2: MDV MDKG-V500C, холод 4,47 / тепло 4,84 кВт | B2: ВЕНТАР-С | C2: https://ventar-s.ru/category/importnoe-oborudovanie/mdv/fankojly-mdv/nastennye-fankojly-mdv/ | D2: 2026-10-28 | E2: 160000 | F2: 131147.54 | G2: шт | H2: запросить КП
A3: MDV MDKG-V500C | B3: mdv.sale | C3: https://www.mdv.sale/catalog/dvukhtrubnye-2183/ | D3: 2026-10-28 | E3: 160000 | F3: 131147.54 | G3: шт | H3: запросить КП
A4: Dantex DF-600DL, холод 5,64 кВт, напольно-потолочный | B4: fankoyl.ru | C4: https://fankoyl.ru/fankoyl-po-moshchnosti-kvt/fankoyl-5-kvt/fankoyl-5-kvt-napolno-potolochniy/ | D4: 2026-10-28 | E4: 41440 | F4: 33967.21 | G4: шт | H4: запросить КП
A5: SHUFT SFF-500, холод 5,30 кВт | B5: ЕвроКлимат | C5: https://euroclimate.org/kondicionery/fancoily/napolno_potolochnye_fankoily | D5: 2026-10-28 | E5: 67990 | F5: 55729.51 | G5: шт | H5: холод чуть ниже 5,35, в минимум не взят
A6: SHUFT SFF-800, холод 7,00 кВт | B6: ЕвроКлимат | C6: https://euroclimate.org/kondicionery/fancoily/napolno_potolochnye_fankoily | D6: 2026-10-28 | E6: 83990 | F6: 68844.26 | G6: шт | H6: оценка: один источник, запросить КП

Sheet Параметры
A1: Параметр | B1: Значение
A2: НДС в цене сайта | B2: 0.22
A3: Доставка Москва | B3: 0.03
A4: Наценка оборудования, раздельная форма | B4: 0.1
A5: Расходники к бригаде HOL/SAN | B5: 0.02
A6: Отходы оборудования | B6: 0
A7: Рост цен | B7: 0
A8: Стоимость денег | B8: 0
A10: Аванс 50% по ТЗ. Закупку фанкойлов считаем из аванса, поэтому стоимость денег 0. Срок закупки внутри 2 месяцев, резерв роста 0. Ночные работы по ТЗ (18:00–06:00) в расценки не заложены.

Sheet Риски и вопросы
A1: № | B1: Риск | C1: Влияние | D1: Что сделать
A2: 1 | B2: Метры труб, дренажа, кабеля и гильз в форме пустые | C2: В цену не входят. Могут быть сопоставимы с арматурой. | D2: Обследование до подачи, иначе не подавать твёрдую цену.
A3: 2 | B3: Арматура, фильтры, клапаны, K-Flex, пульты, крепёж — цены закупки нет | C3: В КП только работа по кранам и клапанам. | D3: Запросить КП поставщика.
A4: 3 | B4: Проект, обследование, исполнительная документация не оценены | C4: Раздел 1 пустой. | D4: Оценить проектировщиком.
A5: 4 | B5: Ночные и выходные работы по ТЗ | C5: Дневные расценки. Ночь удорожает бригаду. | D5: Согласовать коэффициент.
A6: 5 | B6: Монтаж фанкойла — доля расценки сплита, не отдельная позиция тарификатора | C6: Можно ошибиться в 3 чел.-ч. | D6: Добавить в тарификатор монтаж водяного фанкойла.
A7: 6 | B7: Опыт: один договор за 2 года не меньше 18 млн | C7: Допуск, не цена. | D7: Проверить референс до решения об участии.
A8: 7 | B8: Форма считает непредвиденные 5% на всю сумму, текст формы говорит, что на подготовительные они не начисляются | C8: Пока раздел 1 пустой, расхождения нет. | D8: Не править формулу формы.
A9: 8 | B9: ИТР, пропуска, ночной допуск, вывоз мусора отдельно не заложены | C9: Себестоимость выше посчитанной. | D9: Добавить до решения об участии.
A10: 9 | B10: Гарантия 36 месяцев при заводской 12 | C10: Резерв на гарантию не заложен. | D10: Заложить 1–2% после полной сметы.

Sheet Добавить в тарификатор
A1: Работа | B1: Почему
A2: Монтаж водяного настенного/консольного фанкойла без наружного блока | B2: Сейчас взята треть расценки сплит-системы
A3: Пусконаладка замены фанкойла на существующей чиллерной системе | B3: Сейчас аналог разового обслуживания
