Workbook
Name VAT_DIV: Параметры!$B$4
Name DELIV: Параметры!$B$5
Name GROWTH: Параметры!$B$6
Name MONEY: Параметры!$B$7
Name P_LOG: Параметры!$B$8
Name P_ITR: Параметры!$B$9
Name P_HOLD: Параметры!$B$10
Name P_WAR: Параметры!$B$11
Name P_RISK: Параметры!$B$12

Sheet Свод
A1: Бюджет себестоимости — OZON склады МСК-2
A3: Статья | B3: Значение
A4: Материалы, с/с | B4: =SUM(Материалы!S4:S800)
A5: Оплата бригадам | B5: =SUM(Работы!L4:L800)
A6: Расходники | B6: =SUM(Работы!M4:M800)
A7: Косвенные | B7: =Косвенные!C9
A8: Полная себестоимость | B8: =B4+B5+B6+B7
A9: КП работ (с косвенными) | B9: =SUM(Работы!Q4:Q800)
A10: КП материалов | B10: =SUM(Материалы!T4:T800)
A11: КП без НДС | B11: =B9+B10
A12: НДС 22 % | B12: =B11*(VAT_DIV-1)
A13: КП с НДС | B13: =B11*VAT_DIV
A14: Наценка на с/с | B14: =IF(B8=0,0,B11/B8-1)
A15: Маржа | B15: =IF(B11=0,0,1-B8/B11)
A16: Диапазон типа тендера | B16: 15% – 25%
A17: Переторжка −5 % (КП б/НДС) | B17: =B11*0.95
A18: Маржа при −5 % | B18: =IF(B17=0,0,1-B8/B17)
A19: Переторжка −10 % (КП б/НДС) | B19: =B11*0.9
A20: Маржа при −10 % | B20: =IF(B19=0,0,1-B8/B19)
A21: Минимальная цена, наценка 15 % | B21: =B8*1.15
A22: Трудоёмкость, чел.-ч | B22: =SUM(Работы!U4:U800)
A23: Проверка: сумма единичных цен × объём | B23: =SUMPRODUCT(Работы!T4:T672,Работы!D4:D672)
A24: Расхождение проверки и КП | B24: =B23-B11
A26: Жёлтые ячейки — ввод. Зелёные — формулы. Объём на листе «Форма», колонка G. Заказчику этот файл не передавать.

Sheet Параметры
A1: Параметры расчёта — жёлтые ячейки можно менять, остальное пересчитается
A3: Параметр | B3: Значение | C3: Что это
A4: НДС, делитель | B4: 1.22 | C4: Цена с НДС делится на это число
A5: Доставка | B5: 0.05 | C5: Подмосковье, доля к закупке
A6: Резерв роста | B6: 0 | C6: 0: закупка под заявку
A7: Стоимость денег | B7: 0.04 | C7: Постоплата около 2 месяцев
A8: Разъезды | B8: 0.1 | C8: Доля от оплаты бригадам
A9: Мастер на заявках | B9: 0.08 | C9: Доля от оплаты бригадам
A10: Удержание цены | B10: 0.04 | C10: Доля от закупки материалов без НДС
A11: Гарантия | B11: 0.015 | C11: Доля от бригады и закупки
A12: Риски склада | B12: 0.03 | C12: Доля от бригады и закупки

Sheet Расходники
A1: Процент расходников к оплате бригаде. Жёлтое можно менять.
A3: Код | B3: Процент | C3: Кто
A4: BET | B4: 0.02 | C4: Бетонщик / арматурщик
A5: BLG | B5: 0.02 | C5: Благоустройство
A6: DER | B6: 0.02 | C6: Дезинфектор (ОЗДС)
A7: DVR | B7: 0.02 | C7: Двери, окна, перегородки
A8: ELM | B8: 0.02 | C8: Электромонтажник
A9: ETL | B9: 0.01 | C9: Электролаборатория / ПНР
A10: FAS | B10: 0.02 | C10: Фасадчик / промальп
A11: HOL | B11: 0.02 | C11: Холодильщик / кондиционеры
A12: KAM | B12: 0.02 | C12: Каменщик
A13: KRO | B13: 0.02 | C13: Кровельщик
A14: NAR | B14: 0.02 | C14: Наружные сети
A15: OTD | B15: 0.03 | C15: Отделочник
... A23: ZEM | B23: 0.01 | C23: Землекоп

Sheet Работы
A1: Работы. Жёлтые — ввод (цена КП, бригада, норма). Объём берётся с листа «Форма».
A3: Артикул | B3: Позиция ВОР | C3: Ед. | D3: Объём | E3: Метка | F3: Код | G3: КП тарифа | H3: Бригада | I3: Норма, чел.-ч | J3: Подтянута | K3: % расходников | L3: Оплата бригаде | M3: Расходники | N3: С/с материалов | O3: Прямая с/с | P3: Косвенные | Q3: КП работ | R3: Работа за ед. | S3: Материалы за ед. | T3: Услуга за ед. | U3: Чел.-ч
A4: 9.1.34 | B4: 2. Гидродинамическим спосбом включая вызов спец.техники | C4: м.п. | D4: =IF('Форма'!G2="","",'Форма'!G2) | E4: точно | F4: SAN | G4: 202 | H4: 125 | I4: 0.08 | K4: =IF(F4="",0,IFERROR(VLOOKUP(F4,Расходники!$A$4:$B$23,2,FALSE),0)) | L4: =H4*D4 | M4: =L4*K4 | N4: =SUMIF(Материалы!$A$4:$A$800,SUBSTITUTE(SUBSTITUTE(SUBSTITUTE(B4,"~","~~"),"*","~*"),"?","~?"),Материалы!$S$4:$S$800) | O4: =L4+M4+N4 | P4: =IF(SUM($O$4:$O$672)=0,0,Косвенные!$C$9*O4/SUM($O$4:$O$672)) | Q4: =G4*D4+P4 | R4: =IF(D4=0,0,Q4/D4) | S4: =IF(D4=0,0,SUMIF(Материалы!$A$4:$A$800,SUBSTITUTE(SUBSTITUTE(SUBSTITUTE(B4,"~","~~"),"*","~*"),"?","~?"),Материалы!$T$4:$T$800)/D4) | T4: =R4+S4 | U4: =I4*D4
A5: 11.2.N1 | B5: 3. Ручным способом с применением спец.инструмента | C5: м.п. | D5: =IF('Форма'!G3="","",'Форма'!G3) | E5: аналог (11.2.N1) | F5: SAN | G5: 288 | H5: 172 | I5: 0.05 | K5: =IF(F5="",0,IFERROR(VLOOKUP(F5,Расходники!$A$4:$B$23,2,FALSE),0)) | L5: =H5*D5 | M5: =L5*K5 | N5: =SUMIF(Материалы!$A$4:$A$800,SUBSTITUTE(SUBSTITUTE(SUBSTITUTE(B5,"~","~~"),"*","~*"),"?","~?"),Материалы!$S$4:$S$800) | O5: =L5+M5+N5 | P5: =IF(SUM($O$4:$O$672)=0,0,Косвенные!$C$9*O5/SUM($O$4:$O$672)) | Q5: =G5*D5+P5 | R5: =IF(D5=0,0,Q5/D5) | S5: =IF(D5=0,0,SUMIF(Материалы!$A$4:$A$800,SUBSTITUTE(SUBSTITUTE(SUBSTITUTE(B5,"~","~~"),"*","~*"),"?","~?"),Материалы!$T$4:$T$800)/D5) | T5: =R5+S5 | U5: =I5*D5
B6: 4. Ручная очистка пескоуловителя объемом до 1м3 включая разбоку и сборку,утилизацию мусора | C6: шт. | D6: =IF('Форма'!G4="","",'Форма'!G4) | E6: нет в тарификаторе | F6: SAN | G6: 6270 | H6: 3060 | I6: 3 | K6: =IF(F6="",0,IFERROR(VLOOKUP(F6,Расходники!$A$4:$B$23,2,FALSE),0)) | L6: =H6*D6 | M6: =L6*K6 | N6: =SUMIF(Материалы!$A$4:$A$800,SUBSTITUTE(SUBSTITUTE(SUBSTITUTE(B6,"~","~~"),"*","~*"),"?","~?"),Материалы!$S$4:$S$800) | O6: =L6+M6+N6 | P6: =IF(SUM($O$4:$O$672)=0,0,Косвенные!$C$9*O6/SUM($O$4:$O$672)) | Q6: =G6*D6+P6 | R6: =IF(D6=0,0,Q6/D6) | S6: =IF(D6=0,0,SUMIF(Материалы!$A$4:$A$800,SUBSTITUTE(SUBSTITUTE(SUBSTITUTE(B6,"~","~~"),"*","~*"),"?","~?"),Материалы!$T$4:$T$800)/D6) | T6: =R6+S6 | U6: =I6*D6
B7: 5. Диагностика и дефектовка: Проверка механизма подъема (пружин или гидравлики), состояния аппарели и шарнирных соединений. | C7: шт. | D7: =IF('Форма'!G5="","",'Форма'!G5) | E7: нет в тарификаторе | F7: VOR | G7: 4710 | H7: 2160 | I7: 1.5 | K7: =IF(F7="",0,IFERROR(VLOOKUP(F7,Расходники!$A$4:$B$23,2,FALSE),0)) | L7: =H7*D7 | M7: =L7*K7 | N7: =SUMIF(Материалы!$A$4:$A$800,SUBSTITUTE(SUBSTITUTE(SUBSTITUTE(B7,"~","~~"),"*","~*"),"?","~?"),Материалы!$S$4:$S$800) | O7: =L7+M7+N7 | P7: =IF(SUM($O$4:$O$672)=0,0,Косвенные!$C$9*O7/SUM($O$4:$O$672)) | Q7: =G7*D7+P7 | R7: =IF(D7=0,0,Q7/D7) | S7: =IF(D7=0,0,SUMIF(Материалы!$A$4:$A$800,SUBSTITUTE(SUBSTITUTE(SUBSTITUTE(B7,"~","~~"),"*","~*"),"?","~?"),Материалы!$T$4:$T$800)/D7) | T7: =R7+S7 | U7: =I7*D7
B8: 6. Восстановление шарниров: Замена осей крепления, шплинтов, втулок и очистка петель от загрязнений. | C8: шт. | D8: =IF('Форма'!G6="","",'Форма'!G6) | E8: нет в тарификаторе | F8: VOR | G8: 6280 | H8: 2880 | I8: 2 | K8: =IF(F8="",0,IFERROR(VLOOKUP(F8,Расходники!$A$4:$B$23,2,FALSE),0)) | L8: =H8*D8 | M8: =L8*K8 | N8: =SUMIF(Материалы!$A$4:$A$800,SUBSTITUTE(SUBSTITUTE(SUBSTITUTE(B8,"~","~~"),"*","~*"),"?","~?"),Материалы!$S$4:$S$800) | O8: =L8+M8+N8 | P8: =IF(SUM($O$4:$O$672)=0,0,Косвенные!$C$9*O8/SUM($O$4:$O$672)) | Q8: =G8*D8+P8 | R8: =IF(D8=0,0,Q8/D8) | S8: =IF(D8=0,0,SUMIF(Материалы!$A$4:$A$800,SUBSTITUTE(SUBSTITUTE(SUBSTITUTE(B8,"~","~~"),"*","~*"),"?","~?"),Материалы!$T$4:$T$800)/D8) | T8: =R8+S8 | U8: =I8*D8
B9: 7. Сварочные работы, усиление или замена листов с противоскользящим покрытием. | C9: шт. | D9: =IF('Форма'!G7="","",'Форма'!G7) | E9: аналог (14.11) | F9: SVA | G9: 6840 | H9: 3240 | I9: 3 | K9: =IF(F9="",0,IFERROR(VLOOKUP(F9,Расходники!$A$4:$B$23,2,FALSE),0)) | L9: =H9*D9 | M9: =L9*K9 | N9: =SUMIF(Материалы!$A$4:$A$800,SUBSTITUTE(SUBSTITUTE(SUBSTITUTE(B9,"~","~~"),"*","~*"),"?","~?"),Материалы!$S$4:$S$800) | O9: =L9+M9+N9 | P9: =IF(SUM($O$4:$O$672)=0,0,Косвенные!$C$9*O9/SUM($O$4:$O$672)) | Q9: =G9*D9+P9 | R9: =IF(D9=0,0,Q9/D9) | S9: =IF(D9=0,0,SUMIF(Материалы!$A$4:$A$800,SUBSTITUTE(SUBSTITUTE(SUBSTITUTE(B9,"~","~~"),"*","~*"),"?","~?"),Материалы!$T$4:$T$800)/D9) | T9: =R9+S9 | U9: =I9*D9
B10: 8. Замена пружин для плавного опускания/поднятия. | C10: шт. | D10: =IF('Форма'!G8="","",'Форма'!G8) | E10: нет в тарификаторе | F10: VOR | G10: 4710 | H10: 2160 | I10: 1.5 | K10: =IF(F10="",0,IFERROR(VLOOKUP(F10,Расходники!$A$4:$B$23,2,FALSE),0)) | L10: =H10*D10 | M10: =L10*K10 | N10: =SUMIF(Материалы!$A$4:$A$800,SUBSTITUTE(SUBSTITUTE(SUBSTITUTE(B10,"~","~~"),"*","~*"),"?","~?"),Материалы!$S$4:$S$800) | O10: =L10+M10+N10 | P10: =IF(SUM($O$4:$O$672)=0,0,Косвенные!$C$9*O10/SUM($O$4:$O$672)) | Q10: =G10*D10+P10 | R10: =IF(D10=0,0,Q10/D10) | S10: =IF(D10=0,0,SUMIF(Материалы!$A$4:$A$800,SUBSTITUTE(SUBSTITUTE(SUBSTITUTE(B10,"~","~~"),"*","~*"),"?","~?"),Материалы!$T$4:$T$800)/D10) | T10: =R10+S10 | U10: =I10*D10
B11: 9. Демонтажные работы, включая резку. | C11: шт. | D11: =IF('Форма'!G9="","",'Форма'!G9) | E11: нет в тарификаторе | F11: SVA | G11: 5700 | H11: 2700 | I11: 2.5 | K11: =IF(F11="",0,IFERROR(VLOOKUP(F11,Расходники!$A$4:$B$23,2,FALSE),0)) | L11: =H11*D11 | M11: =L11*K11 | N11: =SUMIF(Материалы!$A$4:$A$800,SUBSTITUTE(SUBSTITUTE(SUBSTITUTE(B11,"~","~~"),"*","~*"),"?","~?"),Материалы!$S$4:$S$800) | O11: =L11+M11+N11 | P11: =IF(SUM($O$4:$O$672)=0,0,Косвенные!$C$9*O11/SUM($O$4:$O$672)) | Q11: =G11*D11+P11 | R11: =IF(D11=0,0,Q11/D11) | S11: =IF(D11=0,0,SUMIF(Материалы!$A$4:$A$800,SUBSTITUTE(SUBSTITUTE(SUBSTITUTE(B11,"~","~~"),"*","~*"),"?","~?"),Материалы!$T$4:$T$800)/D11) | T11: =R11+S11 | U11: =I11*D11
A12: 9.1.3 | B12: 10. Замена арматуры сливного бачка типа «Компакт» (включая материалы и з/части) | C12: шт. | D12: =IF('Форма'!G10="","",'Форма'!G10) | E12: точно | F12: SAN | G12: 1725 | H12: 1069 | I12: 0.8 | K12: =IF(F12="",0,IFERROR(VLOOKUP(F12,Расходники!$A$4:$B$23,2,FALSE),0)) | L12: =H12*D12 | M12: =L12*K12 | N12: =SUMIF(Материалы!$A$4:$A$800,SUBSTITUTE(SUBSTITUTE(SUBSTITUTE(B12,"~","~~"),"*","~*"),"?","~?"),Материалы!$S$4:$S$800) | O12: =L12+M12+N12 | P12: =IF(SUM($O$4:$O$672)=0,0,Косвенные!$C$9*O12/SUM($O$4:$O$672)) | Q12: =G12*D12+P12 | R12: =IF(D12=0,0,Q12/D12) | S12: =IF(D12=0,0,SUMIF(Материалы!$A$4:$A$800,SUBSTITUTE(SUBSTITUTE(SUBSTITUTE(B12,"~","~~"),"*","~*"),"?","~?"),Материалы!$T$4:$T$800)/D12) | T12: =R12+S12 | U12: =I12*D12
B13: 11. Замена сливного бачка унитаза типа «Компакт» (включая материалы и з/части) | C13: шт. | D13: =IF('Форма'!G11="","",'Форма'!G11) | E13: аналог (9.1.3) | F13: SAN | G13: 2508 | H13: 1224 | I13: 1.2 | K13: =IF(F13="",0,IFERROR(VLOOKUP(F13,Расходники!$A$4:$B$23,2,FALSE),0)) | L13: =H13*D13 | M13: =L13*K13 | N13: =SUMIF(Материалы!$A$4:$A$800,SUBSTITUTE(SUBSTITUTE(SUBSTITUTE(B13,"~","~~"),"*","~*"),"?","~?"),Материалы!$S$4:$S$800) | O13: =L13+M13+N13 | P13: =IF(SUM($O$4:$O$672)=0,0,Косвенные!$C$9*O13/SUM($O$4:$O$672)) | Q13: =G13*D13+P13 | R13: =IF(D13=0,0,Q13/D13) | S13: =IF(D13=0,0,SUMIF(Материалы!$A$4:$A$800,SUBSTITUTE(SUBSTITUTE(SUBSTITUTE(B13,"~","~~"),"*","~*"),"?","~?"),Материалы!$T$4:$T$800)/D13) | T13: =R13+S13 | U13: =I13*D13
A14: 9.1.72 | B14: 12. Замена унитаза типа «Компакт» (включая материалы и з/части) | C14: шт. | D14: =IF('Форма'!G12="","",'Форма'!G12) | E14: точно | F14: SAN | G14: 3220 | H14: 1996 | I14: 2 | K14: =IF(F14="",0,IFERROR(VLOOKUP(F14,Расходники!$A$4:$B$23,2,FALSE),0)) | L14: =H14*D14 | M14: =L14*K14 | N14: =SUMIF(Материалы!$A$4:$A$800,SUBSTITUTE(SUBSTITUTE(SUBSTITUTE(B14,"~","~~"),"*","~*"),"?","~?"),Материалы!$S$4:$S$800) | O14: =L14+M14+N14 | P14: =IF(SUM($O$4:$O$672)=0,0,Косвенные!$C$9*O14/SUM($O$4:$O$672)) | Q14: =G14*D14+P14 | R14: =IF(D14=0,0,Q14/D14) | S14: =IF(D14=0,0,SUMIF(Материалы!$A$4:$A$800,SUBSTITUTE(SUBSTITUTE(SUBSTITUTE(B14,"~","~~"),"*","~*"),"?","~?"),Материалы!$T$4:$T$800)/D14) | T14: =R14+S14 | U14: =I14*D14
B15: 13. Замена гибкой подводки сантехнической до 60 см (включая материалы и з/части) | C15: шт. | D15: =IF('Форма'!G13="","",'Форма'!G13) | E15: аналог (9.2.72) | F15: SAN | G15: 836 | H15: 408 | I15: 0.4 | K15: =IF(F15="",0,IFERROR(VLOOKUP(F15,Расходники!$A$4:$B$23,2,FALSE),0)) | L15: =H15*D15 | M15: =L15*K15 | N15: =SUMIF(Материалы!$A$4:$A$800,SUBSTITUTE(SUBSTITUTE(SUBSTITUTE(B15,"~","~~"),"*","~*"),"?","~?"),Материалы!$S$4:$S$800) | O15: =L15+M15+N15 | P15: =IF(SUM($O$4:$O$672)=0,0,Косвенные!$C$9*O15/SUM($O$4:$O$672)) | Q15: =G15*D15+P15 | R15: =IF(D15=0,0,Q15/D15) | S15: =IF(D15=0,0,SUMIF(Материалы!$A$4:$A$800,SUBSTITUTE(SUBSTITUTE(SUBSTITUTE(B15,"~","~~"),"*","~*"),"?","~?"),Материалы!$T$4:$T$800)/D15) | T15: =R15+S15 | U15: =I15*D15
B16: 14. Замена смесителя раковины (включая материалы и з/части) | C16: шт. | D16: =IF('Форма'!G14="","",'Форма'!G14) | E16: нет в тарификаторе | F16: SAN | G16: 2090 | H16: 1020 | I16: 1 | K16: =IF(F16="",0,IFERROR(VLOOKUP(F16,Расходники!$A$4:$B$23,2,FALSE),0)) | L16: =H16*D16 | M16: =L16*K16 | N16: =SUMIF(Материалы!$A$4:$A$800,SUBSTITUTE(SUBSTITUTE(SUBSTITUTE(B16,"~","~~"),"*","~*"),"?","~?"),Материалы!$S$4:$S$800) | O16: =L16+M16+N16 | P16: =IF(SUM($O$4:$O$672)=0,0,Косвенные!$C$9*O16/SUM($O$4:$O$672)) | Q16: =G16*D16+P16 | R16: =IF(D16=0,0,Q16/D16) | S16: =IF(D16=0,0,SUMIF(Материалы!$A$4:$A$800,SUBSTITUTE(SUBSTITUTE(SUBSTITUTE(B16,"~","~~"),"*","~*"),"?","~?"),Материалы!$T$4:$T$800)/D16) | T16: =R16+S16 | U16: =I16*D16
A17: 9.1.63 | B17: 15. Замена раковины керамической с пьедесталом (включая материалы и з/части) | C17: шт. | D17: =IF('Форма'!G15="","",'Форма'!G15) | E17: точно | F17: SAN | G17: 2300 | H17: 1426 | I17: 1.5 | K17: =IF(F17="",0,IFERROR(VLOOKUP(F17,Расходники!$A$4:$B$23,2,FALSE),0)) | L17: =H17*D17 | M17: =L17*K17 | N17: =SUMIF(Материалы!$A$4:$A$800,SUBSTITUTE(SUBSTITUTE(SUBSTITUTE(B17,"~","~~"),"*","~*"),"?","~?"),Материалы!$S$4:$S$800) | O17: =L17+M17+N17 | P17: =IF(SUM($O$4:$O$672)=0,0,Косвенные!$C$9*O17/SUM($O$4:$O$672)) | Q17: =G17*D17+P17 | R17: =IF(D17=0,0,Q17/D17) | S17: =IF(D17=0,0,SUMIF(Материалы!$A$4:$A$800,SUBSTITUTE(SUBSTITUTE(SUBSTITUTE(B17,"~","~~"),"*","~*"),"?","~?"),Материалы!$T$4:$T$800)/D17) | T17: =R17+S17 | U17: =I17*D17
A18: 9.1.64 | B18: 16. Замена раковины металлической (включая материалы и з/части) | C18: шт. | D18: =IF('Форма'!G16="","",'Форма'!G16) | E18: точно | F18: SAN | G18: 2070 | H18: 1283 | I18: 1.4 | K18: =IF(F18="",0,IFERROR(VLOOKUP(F18,Расходники!$A$4:$B$23,2,FALSE),0)) | L18: =H18*D18 | M18: =L18*K18 | N18: =SUMIF(Материалы!$A$4:$A$800,SUBSTITUTE(SUBSTITUTE(SUBSTITUTE(B18,"~","~~"),"*","~*"),"?","~?"),Материалы!$S$4:$S$800) | O18: =L18+M18+N18 | P18: =IF(SUM($O$4:$O$672)=0,0,Косвенные!$C$9*O18/SUM($O$4:$O$672)) | Q18: =G18*D18+P18 | R18: =IF(D18=0,0,Q18/D18) | S18: =IF(D18=0,0,SUMIF(Материалы!$A$4:$A$800,SUBSTITUTE(SUBSTITUTE(SUBSTITUTE(B18,"~","~~"),"*","~*"),"?","~?"),Материалы!$T$4:$T$800)/D18) | T18: =R18+S18 | U18: =I18*D18
B19: 17. Замена смесителя для ванны с душевой лейкой (включая материалы и з/части) | C19: шт. | D19: =IF('Форма'!G17="","",'Форма'!G17) | E19: нет в тарификаторе | F19: SAN | G19: 2508 | H19: 1224 | I19: 1.2 | K19: =IF(F19="",0,IFERROR(VLOOKUP(F19,Расходники!$A$4:$B$23,2,FALSE),0)) | L19: =H19*D19 | M19: =L19*K19 | N19: =SUMIF(Материалы!$A$4:$A$800,SUBSTITUTE(SUBSTITUTE(SUBSTITUTE(B19,"~","~~"),"*","~*"),"?","~?"),Материалы!$S$4:$S$800) | O19: =L19+M19+N19 | P19: =IF(SUM($O$4:$O$672)=0,0,Косвенные!$C$9*O19/SUM($O$4:$O$672)) | Q19: =G19*D19+P19 | R19: =IF(D19=0,0,Q19/D19) | S19: =IF(D19=0,0,SUMIF(Материалы!$A$4:$A$800,SUBSTITUTE(SUBSTITUTE(SUBSTITUTE(B19,"~","~~"),"*","~*"),"?","~?"),Материалы!$T$4:$T$800)/D19) | T19: =R19+S19 | U19: =I19*D19
B20: 18. Замена душевого поддона 90*90 см (включая материалы и з/части) | C20: шт. | D20: =IF('Форма'!G18="","",'Форма'!G18) | E20: нет в тарификаторе | F20: SAN | G20: 1672 | H20: 816 | I20: 0.8 | K20: =IF(F20="",0,IFERROR(VLOOKUP(F20,Расходники!$A$4:$B$23,2,FALSE),0)) | L20: =H20*D20 | M20: =L20*K20 | N20: =SUMIF(Материалы!$A$4:$A$800,SUBSTITUTE(SUBSTITUTE(SUBSTITUTE(B20,"~","~~"),"*","~*"),"?","~?"),Материалы!$S$4:$S$800) | O20: =L20+M20+N20 | P20: =IF(SUM($O$4:$O$672)=0,0,Косвенные!$C$9*O20/SUM($O$4:$O$672)) | Q20: =G20*D20+P20 | R20: =IF(D20=0,0,Q20/D20) | S20: =IF(D20=0,0,SUMIF(Материалы!$A$4:$A$800,SUBSTITUTE(SUBSTITUTE(SUBSTITUTE(B20,"~","~~"),"*","~*"),"?","~?"),Материалы!$T$4:$T$800)/D20) | T20: =R20+S20 | U20: =I20*D20
A21: 9.1.64 | B21: 19. Замена сифона раковины (включая материалы и з/части) | C21: шт. | D21: =IF('Форма'!G19="","",'Форма'!G19) | E21: точно | F21: SAN | G21: 2070 | H21: 1283 | I21: 1.4 | K21: =IF(F21="",0,IFERROR(VLOOKUP(F21,Расходники!$A$4:$B$23,2,FALSE),0)) | L21: =H21*D21 | M21: =L21*K21 | N21: =SUMIF(Материалы!$A$4:$A$800,SUBSTITUTE(SUBSTITUTE(SUBSTITUTE(B21,"~","~~"),"*","~*"),"?","~?"),Материалы!$S$4:$S$800) | O21: =L21+M21+N21 | P21: =IF(SUM($O$4:$O$672)=0,0,Косвенные!$C$9*O21/SUM($O$4:$O$672)) | Q21: =G21*D21+P21 | R21: =IF(D21=0,0,Q21/D21) | S21: =IF(D21=0,0,SUMIF(Материалы!$A$4:$A$800,SUBSTITUTE(SUBSTITUTE(SUBSTITUTE(B21,"~","~~"),"*","~*"),"?","~?"),Материалы!$T$4:$T$800)/D21) | T21: =R21+S21 | U21: =I21*D21
B22: 20. Замена крана писсуара (включая материалы и з/части) | C22: шт. | D22: =IF('Форма'!G20="","",'Форма'!G20) | E22: аналог (9.1.N12) | F22: SAN | G22: 1672 | H22: 816 | I22: 0.8 | K22: =IF(F22="",0,IFERROR(VLOOKUP(F22,Расходники!$A$4:$B$23,2,FALSE),0)) | L22: =H22*D22 | M22: =L22*K22 | N22: =SUMIF(Материалы!$A$4:$A$800,SUBSTITUTE(SUBSTITUTE(SUBSTITUTE(B22,"~","~~"),"*","~*"),"?","~?"),Материалы!$S$4:$S$800) | O22: =L22+M22+N22 | P22: =IF(SUM($O$4:$O$672)=0,0,Косвенные!$C$9*O22/SUM($O$4:$O$672)) | Q22: =G22*D22+P22 | R22: =IF(D22=0,0,Q22/D22) | S22: =IF(D22=0,0,SUMIF(Материалы!$A$4:$A$800,SUBSTITUTE(SUBSTITUTE(SUBSTITUTE(B22,"~","~~"),"*","~*"),"?","~?"),Материалы!$T$4:$T$800)/D22) | T22: =R22+S22 | U22: =I22*D22
A23: 9.4.37 | B23: 21. Прокладка трубопровода ХВС, ГВС из полипропиленовых труб Ø20-32 мм (включая материалы, комплетующие и з/части) за 1 п.м. | C23: м.п. | D23: =IF('Форма'!G21="","",'Форма'!G21) | E23: точно | F23: SAN | G23: 483 | H23: 299 | I23: 0.3 | K23: =IF(F23="",0,IFERROR(VLOOKUP(F23,Расходники!$A$4:$B$23,2,FALSE),0)) | L23: =H23*D23 | M23: =L23*K23 | N23: =SUMIF(Материалы!$A$4:$A$800,SUBSTITUTE(SUBSTITUTE(SUBSTITUTE(B23,"~","~~"),"*","~*"),"?","~?"),Материалы!$S$4:$S$800) | O23: =L23+M23+N23 | P23: =IF(SUM($O$4:$O$672)=0,0,Косвенные!$C$9*O23/SUM($O$4:$O$672)) | Q23: =G23*D23+P23 | R23: =IF(D23=0,0,Q23/D23) | S23: =IF(D23=0,0,SUMIF(Материалы!$A$4:$A$800,SUBSTITUTE(SUBSTITUTE(SUBSTITUTE(B23,"~","~~"),"*","~*"),"?","~?"),Материалы!$T$4:$T$800)/D23) | T23: =R23+S23 | U23: =I23*D23
B24: 22. Прокладка трубопровода внутренней канализации Ø40 мм (включая материалы и з/части) за 1 п.м. | C24: м.п. | D24: =IF('Форма'!G22="","",'Форма'!G22) | E24: аналог (9.4.35) | F24: SAN | G24: 585.2 | H24: 285.6 | I24: 0.28 | K24: =IF(F24="",0,IFERROR(VLOOKUP(F24,Расходники!$A$4:$B$23,2,FALSE),0)) | L24: =H24*D24 | M24: =L24*K24 | N24: =SUMIF(Материалы!$A$4:$A$800,SUBSTITUTE(SUBSTITUTE(SUBSTITUTE(B24,"~","~~"),"*","~*"),"?","~?"),Материалы!$S$4:$S$800) | O24: =L24+M24+N24 | P24: =IF(SUM($O$4:$O$672)=0,0,Косвенные!$C$9*O24/SUM($O$4:$O$672)) | Q24: =G24*D24+P24 | R24: =IF(D24=0,0,Q24/D24) | S24: =IF(D24=0,0,SUMIF(Материалы!$A$4:$A$800,SUBSTITUTE(SUBSTITUTE(SUBSTITUTE(B24,"~","~~"),"*","~*"),"?","~?"),Материалы!$T$4:$T$800)/D24) | T24: =R24+S24 | U24: =I24*D24
B25: 23. Прокладка трубопровода внутренней канализации Ø50 мм (включая материалы и з/части) за 1 п.м. | C25: м.п. | D25: =IF('Форма'!G23="","",'Форма'!G23) | E25: аналог (9.4.35) | F25: SAN | G25: 585.2 | H25: 285.6 | I25: 0.28 | K25: =IF(F25="",0,IFERROR(VLOOKUP(F25,Расходники!$A$4:$B$23,2,FALSE),0)) | L25: =H25*D25 | M25: =L25*K25 | N25: =SUMIF(Материалы!$A$4:$A$800,SUBSTITUTE(SUBSTITUTE(SUBSTITUTE(B25,"~","~~"),"*","~*"),"?","~?"),Материалы!$S$4:$S$800) | O25: =L25+M25+N25 | P25: =IF(SUM($O$4:$O$672)=0,0,Косвенные!$C$9*O25/SUM($O$4:$O$672)) | Q25: =G25*D25+P25 | R25: =IF(D25=0,0,Q25/D25) | S25: =IF(D25=0,0,SUMIF(Материалы!$A$4:$A$800,SUBSTITUTE(SUBSTITUTE(SUBSTITUTE(B25,"~","~~"),"*","~*"),"?","~?"),Материалы!$T$4:$T$800)/D25) | T25: =R25+S25 | U25: =I25*D25
B26: 24. Прокладка трубопровода внутренней канализации Ø100 мм (включая материалы и з/части) за 1 п.м. | C26: м.п. | D26: =IF('Форма'!G24="","",'Форма'!G24) | E26: аналог (9.4.35) | F26: SAN | G26: 585.2 | H26: 285.6 | I26: 0.28 | K26: =IF(F26="",0,IFERROR(VLOOKUP(F26,Расходники!$A$4:$B$23,2,FALSE),0)) | L26: =H26*D26 | M26: =L26*K26 | N26: =SUMIF(Материалы!$A$4:$A$800,SUBSTITUTE(SUBSTITUTE(SUBSTITUTE(B26,"~","~~"),"*","~*"),"?","~?"),Материалы!$S$4:$S$800) | O26: =L26+M26+N26 | P26: =IF(SUM($O$4:$O$672)=0,0,Косвенные!$C$9*O26/SUM($O$4:$O$672)) | Q26: =G26*D26+P26 | R26: =IF(D26=0,0,Q26/D26) | S26: =IF(D26=0,0,SUMIF(Материалы!$A$4:$A$800,SUBSTITUTE(SUBSTITUTE(SUBSTITUTE(B26,"~","~~"),"*","~*"),"?","~?"),Материалы!$T$4:$T$800)/D26) | T26: =R26+S26 | U26: =I26*D26
B27: 25. Устранение протечек в сантехническом оборудовании (включая материалы и з/части) за 1 ед. | C27: шт. | D27: =IF('Форма'!G25="","",'Форма'!G25) | E27: нет в тарификаторе | F27: SAN | G27: 2090 | H27: 1020 | I27: 1 | K27: =IF(F27="",0,IFERROR(VLOOKUP(F27,Расходники!$A$4:$B$23,2,FALSE),0)) | L27: =H27*D27 | M27: =L27*K27 | N27: =SUMIF(Материалы!$A$4:$A$800,SUBSTITUTE(SUBSTITUTE(SUBSTITUTE(B27,"~","~~"),"*","~*"),"?","~?"),Материалы!$S$4:$S$800) | O27: =L27+M27+N27 | P27: =IF(SUM($O$4:$O$672)=0,0,Косвенные!$C$9*O27/SUM($O$4:$O$672)) | Q27: =G27*D27+P27 | R27: =IF(D27=0,0,Q27/D27) | S27: =IF(D27=0,0,SUMIF(Материалы!$A$4:$A$800,SUBSTITUTE(SUBSTITUTE(SUBSTITUTE(B27,"~","~~"),"*","~*"),"?","~?"),Материалы!$T$4:$T$800)/D27) | T27: =R27+S27 | U27: =I27*D27
A28: 9.4.N1 | B28: 26. Замена запорной арматуры трубопроводов (включая материалы и з/части) за 1 ед. | C28: шт. | D28: =IF('Форма'!G26="","",'Форма'!G26) | E28: точно | F28: SAN | G28: 1380 | H28: 856 | I28: 0.8 | K28: =IF(F28="",0,IFERROR(VLOOKUP(F28,Расходники!$A$4:$B$23,2,FALSE),0)) | L28: =H28*D28 | M28: =L28*K28 | N28: =SUMIF(Материалы!$A$4:$A$800,SUBSTITUTE(SUBSTITUTE(SUBSTITUTE(B28,"~","~~"),"*","~*"),"?","~?"),Материалы!$S$4:$S$800) | O28: =L28+M28+N28 | P28: =IF(SUM($O$4:$O$672)=0,0,Косвенные!$C$9*O28/SUM($O$4:$O$672)) | Q28: =G28*D28+P28 | R28: =IF(D28=0,0,Q28/D28) | S28: =IF(D28=0,0,SUMIF(Материалы!$A$4:$A$800,SUBSTITUTE(SUBSTITUTE(SUBSTITUTE(B28,"~","~~"),"*","~*"),"?","~?"),Материалы!$T$4:$T$800)/D28) | T28: =R28+S28 | U28: =I28*D28
B29: 27. Подключение к системе ХВС, ГВС приборов (водонагреватель, кулер, пурифайр, стиральная машинка и т.д.) (включая материалы, комплектующие, фитинги, з/части и т.д.) за 1 ед. | C29: шт. | D29: =IF('Форма'!G27="","",'Форма'!G27) | E29: нет в тарификаторе | F29: SAN | G29: 2508 | H29: 1224 | I29: 1.2 | K29: =IF(F29="",0,IFERROR(VLOOKUP(F29,Расходники!$A$4:$B$23,2,FALSE),0)) | L29: =H29*D29 | M29: =L29*K29 | N29: =SUMIF(Материалы!$A$4:$A$800,SUBSTITUTE(SUBSTITUTE(SUBSTITUTE(B29,"~","~~"),"*","~*"),"?","~?"),Материалы!$S$4:$S$800) | O29: =L29+M29+N29 | P29: =IF(SUM($O$4:$O$672)=0,0,Косвенные!$C$9*O29/SUM($O$4:$O$672)) | Q29: =G29*D29+P29 | R29: =IF(D29=0,0,Q29/D29) | S29: =IF(D29=0,0,SUMIF(Материалы!$A$4:$A$800,SUBSTITUTE(SUBSTITUTE(SUBSTITUTE(B29,"~","~~"),"*","~*"),"?","~?"),Материалы!$T$4:$T$800)/D29) | T29: =R29+S29 | U29: =I29*D29
B30: 28. Стоимость нормо-часа для работ, не вошедших в основной перечень | C30: н/час | D30: =IF('Форма'!G28="","",'Форма'!G28) | E30: нет в тарификаторе | F30: SAN | G30: 2090 | H30: 1020 | I30: 1 | K30: =IF(F30="",0,IFERROR(VLOOKUP(F30,Расходники!$A$4:$B$23,2,FALSE),0)) | L30: =H30*D30 | M30: =L30*K30 | N30: =SUMIF(Материалы!$A$4:$A$800,SUBSTITUTE(SUBSTITUTE(SUBSTITUTE(B30,"~","~~"),"*","~*"),"?","~?"),Материалы!$S$4:$S$800) | O30: =L30+M30+N30 | P30: =IF(SUM($O$4:$O$672)=0,0,Косвенные!$C$9*O30/SUM($O$4:$O$672)) | Q30: =G30*D30+P30 | R30: =IF(D30=0,0,Q30/D30) | S30: =IF(D30=0,0,SUMIF(Материалы!$A$4:$A$800,SUBSTITUTE(SUBSTITUTE(SUBSTITUTE(B30,"~","~~"),"*","~*"),"?","~?"),Материалы!$T$4:$T$800)/D30) | T30: =R30+S30 | U30: =I30*D30
B31: 29. Планка примыкания верхняя, нижняя 150 х 250 с полимерным покрытием по RAL по согласованию | C31: п.м | D31: =IF('Форма'!G29="","",'Форма'!G29) | E31: аналог (6.2.5) | F31: KRO | G31: 452.5 | H31: 237.5 | I31: 0.25 | K31: =IF(F31="",0,IFERROR(VLOOKUP(F31,Расходники!$A$4:$B$23,2,FALSE),0)) | L31: =H31*D31 | M31: =L31*K31 | N31: =SUMIF(Материалы!$A$4:$A$800,SUBSTITUTE(SUBSTITUTE(SUBSTITUTE(B31,"~","~~"),"*","~*"),"?","~?"),Материалы!$S$4:$S$800) | O31: =L31+M31+N31 | P31: =IF(SUM($O$4:$O$672)=0,0,Косвенные!$C$9*O31/SUM($O$4:$O$672)) | Q31: =G31*D31+P31 | R31: =IF(D31=0,0,Q31/D31) | S31: =IF(D31=0,0,SUMIF(Материалы!$A$4:$A$800,SUBSTITUTE(SUBSTITUTE(SUBSTITUTE(B31,"~","~~"),"*","~*"),"?","~?"),Материалы!$T$4:$T$800)/D31) | T31: =R31+S31 | U31: =I31*D31
A32: 5.5.2 | B32: 30. Монтаж профлиста С8-115 - 0,50 окрашенный | C32: м2 | D32: =IF('Форма'!G30="","",'Форма'!G30) | E32: аналог (5.5.2) по готовому каркасу | F32: FAS | G32: 600 | H32: 350 | I32: 0.3 | K32: =IF(F32="",0,IFERROR(VLOOKUP(F32,Расходники!$A$4:$B$23,2,FALSE),0)) | L32: =H32*D32 | M32: =L32*K32 | N32: =SUMIF(Материалы!$A$4:$A$800,SUBSTITUTE(SUBSTITUTE(SUBSTITUTE(B32,"~","~~"),"*","~*"),"?","~?"),Материалы!$S$4:$S$800) | O32: =L32+M32+N32 | P32: =IF(SUM($O$4:$O$672)=0,0,Косвенные!$C$9*O32/SUM($O$4:$O$672)) | Q32: =G32*D32+P32 | R32: =IF(D32=0,0,Q32/D32) | S32: =IF(D32=0,0,SUMIF(Материалы!$A$4:$A$800,SUBSTITUTE(SUBSTITUTE(SUBSTITUTE(B32,"~","~~"),"*","~*"),"?","~?"),Материалы!$T$4:$T$800)/D32) | T32: =R32+S32 | U32: =I32*D32
A33: 5.5.2 | B33: 31. Монтаж профлиста С8, 0,45мм | C33: м2 | D33: =IF('Форма'!G31="","",'Форма'!G31) | E33: аналог (5.5.2) по готовому каркасу | F33: FAS | G33: 600 | H33: 350 | I33: 0.3 | K33: =IF(F33="",0,IFERROR(VLOOKUP(F33,Расходники!$A$4:$B$23,2,FALSE),0)) | L33: =H33*D33 | M33: =L33*K33 | N33: =SUMIF(Материалы!$A$4:$A$800,SUBSTITUTE(SUBSTITUTE(SUBSTITUTE(B33,"~","~~"),"*","~*"),"?","~?"),Материалы!$S$4:$S$800) | O33: =L33+M33+N33 | P33: =IF(SUM($O$4:$O$672)=0,0,Косвенные!$C$9*O33/SUM($O$4:$O$672)) | Q33: =G33*D33+P33 | R33: =IF(D33=0,0,Q33/D33) | S33: =IF(D33=0,0,SUMIF(Материалы!$A$4:$A$800,SUBSTITUTE(SUBSTITUTE(SUBSTITUTE(B33,"~","~~"),"*","~*"),"?","~?"),Материалы!$T$4:$T$800)/D33) | T33: =R33+S33 | U33: =I33*D33
A34: 5.5.2 | B34: 32. Монтаж профлиста С20, 0,45мм | C34: м2 | D34: =IF('Форма'!G32="","",'Форма'!G32) | E34: аналог (5.5.2) по готовому каркасу | F34: FAS | G34: 600 | H34: 350 | I34: 0.3 | K34: =IF(F34="",0,IFERROR(VLOOKUP(F34,Расходники!$A$4:$B$23,2,FALSE),0)) | L34: =H34*D34 | M34: =L34*K34 | N34: =SUMIF(Материалы!$A$4:$A$800,SUBSTITUTE(SUBSTITUTE(SUBSTITUTE(B34,"~","~~"),"*","~*"),"?","~?"),Материалы!$S$4:$S$800) | O34: =L34+M34+N34 | P34: =IF(SUM($O$4:$O$672)=0,0,Косвенные!$C$9*O34/SUM($O$4:$O$672)) | Q34: =G34*D34+P34 | R34: =IF(D34=0,0,Q34/D34) | S34: =IF(D34=0,0,SUMIF(Материалы!$A$4:$A$800,SUBSTITUTE(SUBSTITUTE(SUBSTITUTE(B34,"~","~~"),"*","~*"),"?","~?"),Материалы!$T$4:$T$800)/D34) | T34: =R34+S34 | U34: =I34*D34
B35: 33. Поручни из нержавеющей стали ( с 3 ригелями ) | C35: м.п. | D35: =IF('Форма'!G33="","",'Форма'!G33) | E35: аналог (5.1.10) | F35: SVA | G35: 1824 | H35: 864 | I35: 0.8 | K35: =IF(F35="",0,IFERROR(VLOOKUP(F35,Расходники!$A$4:$B$23,2,FALSE),0)) | L35: =H35*D35 | M35: =L35*K35 | N35: =SUMIF(Материалы!$A$4:$A$800,SUBSTITUTE(SUBSTITUTE(SUBSTITUTE(B35,"~","~~"),"*","~*"),"?","~?"),Материалы!$S$4:$S$800) | O35: =L35+M35+N35 | P35: =IF(SUM($O$4:$O$672)=0,0,Косвенные!$C$9*O35/SUM($O$4:$O$672)) | Q35: =G35*D35+P35 | R35: =IF(D35=0,0,Q35/D35) | S35: =IF(D35=0,0,SUMIF(Материалы!$A$4:$A$800,SUBSTITUTE(SUBSTITUTE(SUBSTITUTE(B35,"~","~~"),"*","~*"),"?","~?"),Материалы!$T$4:$T$800)/D35) | T35: =R35+S35 | U35: =I35*D35
B36: 34. Поручни из нержавеющей стали ( с 2 ригелями, с двойным ) | C36: м.п. | D36: =IF('Форма'!G34="","",'Форма'!G34) | E36: аналог (5.1.10) | F36: SVA | G36: 1824 | H36: 864 | I36: 0.8 | K36: =IF(F36="",0,IFERROR(VLOOKUP(F36,Расходники!$A$4:$B$23,2,FALSE),0)) | L36: =H36*D36 | M36: =L36*K36 | N36: =SUMIF(Материалы!$A$4:$A$800,SUBSTITUTE(SUBSTITUTE(SUBSTITUTE(B36,"~","~~"),"*","~*"),"?","~?"),Материалы!$S$4:$S$800) | O36: =L36+M36+N36 | P36: =IF(SUM($O$4:$O$672)=0,0,Косвенные!$C$9*O36/SUM($O$4:$O$672)) | Q36: =G36*D36+P36 | R36: =IF(D36=0,0,Q36/D36) | S36: =IF(D36=0,0,SUMIF(Материалы!$A$4:$A$800,SUBSTITUTE(SUBSTITUTE(SUBSTITUTE(B36,"~","~~"),"*","~*"),"?","~?"),Материалы!$T$4:$T$800)/D36) | T36: =R36+S36 | U36: =I36*D36
A37: 7.2.25 | B37: 35. Керамогранит 300х300х8 мм типа "Эстима" (цвет белый )RW-01 (вкл. За основу клей, грунтовку, затирку швов) | C37: м2 | D37: =IF('Форма'!G35="","",'Форма'!G35) | E37: точно | F37: PLI | G37: 2160 | H37: 1150 | I37: 1.5 | J37: да | K37: =IF(F37="",0,IFERROR(VLOOKUP(F37,Расходники!$A$4:$B$23,2,FALSE),0)) | L37: =H37*D37 | M37: =L37*K37 | N37: =SUMIF(Материалы!$A$4:$A$800,SUBSTITUTE(SUBSTITUTE(SUBSTITUTE(B37,"~","~~"),"*","~*"),"?","~?"),Материалы!$S$4:$S$800) | O37: =L37+M37+N37 | P37: =IF(SUM($O$4:$O$672)=0,0,Косвенные!$C$9*O37/SUM($O$4:$O$672)) | Q37: =G37*D37+P37 | R37: =IF(D37=0,0,Q37/D37) | S37: =IF(D37=0,0,SUMIF(Материалы!$A$4:$A$800,SUBSTITUTE(SUBSTITUTE(SUBSTITUTE(B37,"~","~~"),"*","~*"),"?","~?"),Материалы!$T$4:$T$800)/D37) | T37: =R37+S37 | U37: =I37*D37
A38: 7.2.25 | B38: 36. Керамогранит 400х400х9 мм типа "Эстима" (цвет белый))RW-01 (вкл. За основу клей, грунтовку, затирку швов) | C38: м2 | D38: =IF('Форма'!G36="","",'Форма'!G36) | E38: точно | F38: PLI | G38: 2160 | H38: 1150 | I38: 1.5 | J38: да | K38: =IF(F38="",0,IFERROR(VLOOKUP(F38,Расходники!$A$4:$B$23,2,FALSE),0)) | L38: =H38*D38 | M38: =L38*K38 | N38: =SUMIF(Материалы!$A$4:$A$800,SUBSTITUTE(SUBSTITUTE(SUBSTITUTE(B38,"~","~~"),"*","~*"),"?","~?"),Материалы!$S$4:$S$800) | O38: =L38+M38+N38 | P38: =IF(SUM($O$4:$O$672)=0,0,Косвенные!$C$9*O38/SUM($O$4:$O$672)) | Q38: =G38*D38+P38 | R38: =IF(D38=0,0,Q38/D38) | S38: =IF(D38=0,0,SUMIF(Материалы!$A$4:$A$800,SUBSTITUTE(SUBSTITUTE(SUBSTITUTE(B38,"~","~~"),"*","~*"),"?","~?"),Материалы!$T$4:$T$800)/D38) | T38: =R38+S38 | U38: =I38*D38
A39: 7.2.25 | B39: 37. Керамогранит 600х600х10 мм типа "Эстима" (цвет белый))RW-01 (вкл. За основу клей, грунтовку, затирку швов) | C39: м2 | D39: =IF('Форма'!G37="","",'Форма'!G37) | E39: точно | F39: PLI | G39: 2160 | H39: 1150 | I39: 1.5 | J39: да | K39: =IF(F39="",0,IFERROR(VLOOKUP(F39,Расходники!$A$4:$B$23,2,FALSE),0)) | L39: =H39*D39 | M39: =L39*K39 | N39: =SUMIF(Материалы!$A$4:$A$800,SUBSTITUTE(SUBSTITUTE(SUBSTITUTE(B39,"~","~~"),"*","~*"),"?","~?"),Материалы!$S$4:$S$800) | O39: =L39+M39+N39 | P39: =IF(SUM($O$4:$O$672)=0,0,Косвенные!$C$9*O39/SUM($O$4:$O$672)) | Q39: =G39*D39+P39 | R39: =IF(D39=0,0,Q39/D39) | S39: =IF(D39=0,0,SUMIF(Материалы!$A$4:$A$800,SUBSTITUTE(SUBSTITUTE(SUBSTITUTE(B39,"~","~~"),"*","~*"),"?","~?"),Материалы!$T$4:$T$800)/D39) | T39: =R39+S39 | U39: =I39*D39
A40: 7.2.25 | B40: 38. Плитка керамогранита 200*200*12 мм типа "Эстима" (цвет-серый ) ST-101 (вкл. За основу клей, грунтовку, затирку швов) | C40: м2 | D40: =IF('Форма'!G38="","",'Форма'!G38) | E40: точно | F40: PLI | G40: 2160 | H40: 1150 | I40: 1.5 | J40: да | K40: =IF(F40="",0,IFERROR(VLOOKUP(F40,Расходники!$A$4:$B$23,2,FALSE),0)) | L40: =H40*D40 | M40: =L40*K40 | N40: =SUMIF(Материалы!$A$4:$A$800,SUBSTITUTE(SUBSTITUTE(SUBSTITUTE(B40,"~","~~"),"*","~*"),"?","~?"),Материалы!$S$4:$S$800) | O40: =L40+M40+N40 | P40: =IF(SUM($O$4:$O$672)=0,0,Косвенные!$C$9*O40/SUM($O$4:$O$672)) | Q40: =G40*D40+P40 | R40: =IF(D40=0,0,Q40/D40) | S40: =IF(D40=0,0,SUMIF(Материалы!$A$4:$A$800,SUBSTITUTE(SUBSTITUTE(SUBSTITUTE(B40,"~","~~"),"*","~*"),"?","~?"),Материалы!$T$4:$T$800)/D40) | T40: =R40+S40 | U40: =I40*D40
A41: 7.2.25 | B41: 39. Плитка керамогранита 300*300*12 мм типа "Эстима" (цвет-серый ) ST-101 (вкл. За основу клей, грунтовку, затирку швов) | C41: м2 | D41: =IF('Форма'!G39="","",'Форма'!G39) | E41: точно | F41: PLI | G41: 2160 | H41: 1150 | I41: 1.5 | J41: да | K41: =IF(F41="",0,IFERROR(VLOOKUP(F41,Расходники!$A$4:$B$23,2,FALSE),0)) | L41: =H41*D41 | M41: =L41*K41 | N41: =SUMIF(Материалы!$A$4:$A$800,SUBSTITUTE(SUBSTITUTE(SUBSTITUTE(B41,"~","~~"),"*","~*"),"?","~?"),Материалы!$S$4:$S$800) | O41: =L41+M41+N41 | P41: =IF(SUM($O$4:$O$672)=0,0,Косвенные!$C$9*O41/SUM($O$4:$O$672)) | Q41: =G41*D41+P41 | R41: =IF(D41=0,0,Q41/D41) | S41: =IF(D41=0,0,SUMIF(Материалы!$A$4:$A$800,SUBSTITUTE(SUBSTITUTE(SUBSTITUTE(B41,"~","~~"),"*","~*"),"?","~?"),Материалы!$T$4:$T$800)/D41) | T41: =R41+S41 | U41: =I41*D41
A42: 7.2.25 | B42: 40. Плитка керамогранита 300*300*8 мм типа "Эстима"(цвет-серый ) ST-03 (вкл. За основу клей, грунтовку, затирку швов) | C42: м2 | D42: =IF('Форма'!G40="","",'Форма'!G40) | E42: точно | F42: PLI | G42: 2160 | H42: 1150 | I42: 1.5 | J42: да | K42: =IF(F42="",0,IFERROR(VLOOKUP(F42,Расходники!$A$4:$B$23,2,FALSE),0)) | L42: =H42*D42 | M42: =L42*K42 | N42: =SUMIF(Материалы!$A$4:$A$800,SUBSTITUTE(SUBSTITUTE(SUBSTITUTE(B42,"~","~~"),"*","~*"),"?","~?"),Материалы!$S$4:$S$800) | O42: =L42+M42+N42 | P42: =IF(SUM($O$4:$O$672)=0,0,Косвенные!$C$9*O42/SUM($O$4:$O$672)) | Q42: =G42*D42+P42 | R42: =IF(D42=0,0,Q42/D42) | S42: =IF(D42=0,0,SUMIF(Материалы!$A$4:$A$800,SUBSTITUTE(SUBSTITUTE(SUBSTITUTE(B42,"~","~~"),"*","~*"),"?","~?"),Материалы!$T$4:$T$800)/D42) | T42: =R42+S42 | U42: =I42*D42
A43: 7.2.25 | B43: 41. Плитка Керамогранит 400х400х9 мм типа "Эстима"(цвет-серый ) ST-03 (вкл. За основу клей, грунтовку, затирку швов) | C43: м2 | D43: =IF('Форма'!G41="","",'Форма'!G41) | E43: точно | F43: PLI | G43: 2160 | H43: 1150 | I43: 1.5 | J43: да | K43: =IF(F43="",0,IFERROR(VLOOKUP(F43,Расходники!$A$4:$B$23,2,FALSE),0)) | L43: =H43*D43 | M43: =L43*K43 | N43: =SUMIF(Материалы!$A$4:$A$800,SUBSTITUTE(SUBSTITUTE(SUBSTITUTE(B43,"~","~~"),"*","~*"),"?","~?"),Материалы!$S$4:$S$800) | O43: =L43+M43+N43 | P43: =IF(SUM($O$4:$O$672)=0,0,Косвенные!$C$9*O43/SUM($O$4:$O$672)) | Q43: =G43*D43+P43 | R43: =IF(D43=0,0,Q43/D43) | S43: =IF(D43=0,0,SUMIF(Материалы!$A$4:$A$800,SUBSTITUTE(SUBSTITUTE(SUBSTITUTE(B43,"~","~~"),"*","~*"),"?","~?"),Материалы!$T$4:$T$800)/D43) | T43: =R43+S43 | U43: =I43*D43
A44: 7.2.25 | B44: 42. Плитка керамогранита 600*600*10 мм типа "Эстима"(цвет-серый ) ST-03 (вкл. За основу клей, грунтовку, затирку швов) | C44: м2 | D44: =IF('Форма'!G42="","",'Форма'!G42) | E44: точно | F44: PLI | G44: 2160 | H44: 1150 | I44: 1.5 | J44: да | K44: =IF(F44="",0,IFERROR(VLOOKUP(F44,Расходники!$A$4:$B$23,2,FALSE),0)) | L44: =H44*D44 | M44: =L44*K44 | N44: =SUMIF(Материалы!$A$4:$A$800,SUBSTITUTE(SUBSTITUTE(SUBSTITUTE(B44,"~","~~"),"*","~*"),"?","~?"),Материалы!$S$4:$S$800) | O44: =L44+M44+N44 | P44: =IF(SUM($O$4:$O$672)=0,0,Косвенные!$C$9*O44/SUM($O$4:$O$672)) | Q44: =G44*D44+P44 | R44: =IF(D44=0,0,Q44/D44) | S44: =IF(D44=0,0,SUMIF(Материалы!$A$4:$A$800,SUBSTITUTE(SUBSTITUTE(SUBSTITUTE(B44,"~","~~"),"*","~*"),"?","~?"),Материалы!$T$4:$T$800)/D44) | T44: =R44+S44 | U44: =I44*D44
A45: 7.2.25 | B45: 43. Керамогранит для пола 200х200х12 мм (полосы, PEI 4) глазурованный (полосатая) (вкл. За основу клей, грунтовку, затирку швов) | C45: м2 | D45: =IF('Форма'!G43="","",'Форма'!G43) | E45: точно | F45: PLI | G45: 2160 | H45: 1150 | I45: 1.5 | J45: да | K45: =IF(F45="",0,IFERROR(VLOOKUP(F45,Расходники!$A$4:$B$23,2,FALSE),0)) | L45: =H45*D45 | M45: =L45*K45 | N45: =SUMIF(Материалы!$A$4:$A$800,SUBSTITUTE(SUBSTITUTE(SUBSTITUTE(B45,"~","~~"),"*","~*"),"?","~?"),Материалы!$S$4:$S$800) | O45: =L45+M45+N45 | P45: =IF(SUM($O$4:$O$672)=0,0,Косвенные!$C$9*O45/SUM($O$4:$O$672)) | Q45: =G45*D45+P45 | R45: =IF(D45=0,0,Q45/D45) | S45: =IF(D45=0,0,SUMIF(Материалы!$A$4:$A$800,SUBSTITUTE(SUBSTITUTE(SUBSTITUTE(B45,"~","~~"),"*","~*"),"?","~?"),Материалы!$T$4:$T$800)/D45) | T45: =R45+S45 | U45: =I45*D45
A46: 7.2.25 | B46: 44. Керамогранит Техногрес 300х300х12мм соль-перец | C46: м2 | D46: =IF('Форма'!G44="","",'Форма'!G44) | E46: точно | F46: PLI | G46: 2160 | H46: 1150 | I46: 1.5 | J46: да | K46: =IF(F46="",0,IFERROR(VLOOKUP(F46,Расходники!$A$4:$B$23,2,FALSE),0)) | L46: =H46*D46 | M46: =L46*K46 | N46: =SUMIF(Материалы!$A$4:$A$800,SUBSTITUTE(SUBSTITUTE(SUBSTITUTE(B46,"~","~~"),"*","~*"),"?","~?"),Материалы!$S$4:$S$800) | O46: =L46+M46+N46 | P46: =IF(SUM($O$4:$O$672)=0,0,Косвенные!$C$9*O46/SUM($O$4:$O$672)) | Q46: =G46*D46+P46 | R46: =IF(D46=0,0,Q46/D46) | S46: =IF(D46=0,0,SUMIF(Материалы!$A$4:$A$800,SUBSTITUTE(SUBSTITUTE(SUBSTITUTE(B46,"~","~~"),"*","~*"),"?","~?"),Материалы!$T$4:$T$800)/D46) | T46: =R46+S46 | U46: =I46*D46
A47: 7.3.9 | B47: 45. Плинтус напольный пластиковый 55 x 22 мм типа "Идеал" с кабель каналом | C47: м.п. | D47: =IF('Форма'!G45="","",'Форма'!G45) | E47: точно | F47: PLI | G47: 175 | H47: 105 | I47: 0.1 | K47: =IF(F47="",0,IFERROR(VLOOKUP(F47,Расходники!$A$4:$B$23,2,FALSE),0)) | L47: =H47*D47 | M47: =L47*K47 | N47: =SUMIF(Материалы!$A$4:$A$800,SUBSTITUTE(SUBSTITUTE(SUBSTITUTE(B47,"~","~~"),"*","~*"),"?","~?"),Материалы!$S$4:$S$800) | O47: =L47+M47+N47 | P47: =IF(SUM($O$4:$O$672)=0,0,Косвенные!$C$9*O47/SUM($O$4:$O$672)) | Q47: =G47*D47+P47 | R47: =IF(D47=0,0,Q47/D47) | S47: =IF(D47=0,0,SUMIF(Материалы!$A$4:$A$800,SUBSTITUTE(SUBSTITUTE(SUBSTITUTE(B47,"~","~~"),"*","~*"),"?","~?"),Материалы!$T$4:$T$800)/D47) | T47: =R47+S47 | U47: =I47*D47
A48: 7.2.21 | B48: 46. Линолеум коммерческий толщиной не менее 2 мм (типа "Tarket" серии "Optima") | C48: м2 | D48: =IF('Форма'!G46="","",'Форма'!G46) | E48: точно | F48: PLI | G48: 450 | H48: 270 | I48: 0.25 | K48: =IF(F48="",0,IFERROR(VLOOKUP(F48,Расходники!$A$4:$B$23,2,FALSE),0)) | L48: =H48*D48 | M48: =L48*K48 | N48: =SUMIF(Материалы!$A$4:$A$800,SUBSTITUTE(SUBSTITUTE(SUBSTITUTE(B48,"~","~~"),"*","~*"),"?","~?"),Материалы!$S$4:$S$800) | O48: =L48+M48+N48 | P48: =IF(SUM($O$4:$O$672)=0,0,Косвенные!$C$9*O48/SUM($O$4:$O$672)) | Q48: =G48*D48+P48 | R48: =IF(D48=0,0,Q48/D48) | S48: =IF(D48=0,0,SUMIF(Материалы!$A$4:$A$800,SUBSTITUTE(SUBSTITUTE(SUBSTITUTE(B48,"~","~~"),"*","~*"),"?","~?"),Материалы!$T$4:$T$800)/D48) | T48: =R48+S48 | U48: =I48*D48
A49: 8.2.N7 | B49: 47. Текстура: гладкая типа Апельсиновая корка. Цвет: RAL 7040 | C49: м2 | D49: =IF('Форма'!G47="","",'Форма'!G47) | E49: аналог (8.2.N7) | F49: OTD | G49: 440 | H49: 265 | I49: 0.25 | K49: =IF(F49="",0,IFERROR(VLOOKUP(F49,Расходники!$A$4:$B$23,2,FALSE),0)) | L49: =H49*D49 | M49: =L49*K49 | N49: =SUMIF(Материалы!$A$4:$A$800,SUBSTITUTE(SUBSTITUTE(SUBSTITUTE(B49,"~","~~"),"*","~*"),"?","~?"),Материалы!$S$4:$S$800) | O49: =L49+M49+N49 | P49: =IF(SUM($O$4:$O$672)=0,0,Косвенные!$C$9*O49/SUM($O$4:$O$672)) | Q49: =G49*D49+P49 | R49: =IF(D49=0,0,Q49/D49) | S49: =IF(D49=0,0,SUMIF(Материалы!$A$4:$A$800,SUBSTITUTE(SUBSTITUTE(SUBSTITUTE(B49,"~","~~"),"*","~*"),"?","~?"),Материалы!$T$4:$T$800)/D49) | T49: =R49+S49 | U49: =I49*D49
B50: 48. Противоскользящие полосы | C50: м.п. | D50: =IF('Форма'!G48="","",'Форма'!G48) | E50: нет в тарификаторе | F50: PLI | G50: 190 | H50: 108 | I50: 0.1 | K50: =IF(F50="",0,IFERROR(VLOOKUP(F50,Расходники!$A$4:$B$23,2,FALSE),0)) | L50: =H50*D50 | M50: =L50*K50 | N50: =SUMIF(Материалы!$A$4:$A$800,SUBSTITUTE(SUBSTITUTE(SUBSTITUTE(B50,"~","~~"),"*","~*"),"?","~?"),Материалы!$S$4:$S$800) | O50: =L50+M50+N50 | P50: =IF(SUM($O$4:$O$672)=0,0,Косвенные!$C$9*O50/SUM($O$4:$O$672)) | Q50: =G50*D50+P50 | R50: =IF(D50=0,0,Q50/D50) | S50: =IF(D50=0,0,SUMIF(Материалы!$A$4:$A$800,SUBSTITUTE(SUBSTITUTE(SUBSTITUTE(B50,"~","~~"),"*","~*"),"?","~?"),Материалы!$T$4:$T$800)/D50) | T50: =R50+S50 | U50: =I50*D50
B51: 49. Подвесной потолок типа "ARMSTRONG"(комплект) | C51: м2 | D51: =IF('Форма'!G49="","",'Форма'!G49) | E51: нет в тарификаторе | F51: OTD | G51: 513 | H51: 270 | I51: 0.3 | K51: =IF(F51="",0,IFERROR(VLOOKUP(F51,Расходники!$A$4:$B$23,2,FALSE),0)) | L51: =H51*D51 | M51: =L51*K51 | N51: =SUMIF(Материалы!$A$4:$A$800,SUBSTITUTE(SUBSTITUTE(SUBSTITUTE(B51,"~","~~"),"*","~*"),"?","~?"),Материалы!$S$4:$S$800) | O51: =L51+M51+N51 | P51: =IF(SUM($O$4:$O$672)=0,0,Косвенные!$C$9*O51/SUM($O$4:$O$672)) | Q51: =G51*D51+P51 | R51: =IF(D51=0,0,Q51/D51) | S51: =IF(D51=0,0,SUMIF(Материалы!$A$4:$A$800,SUBSTITUTE(SUBSTITUTE(SUBSTITUTE(B51,"~","~~"),"*","~*"),"?","~?"),Материалы!$T$4:$T$800)/D51) | T51: =R51+S51 | U51: =I51*D51
B52: 50. Профильный материал для панели ЛГКЛ, направляющие, алюмин. профили ОМЕГА (вкл. крепежные элементы) | C52: м2 | D52: =IF('Форма'!G50="","",'Форма'!G50) | E52: аналог (8.1.22), только каркас | F52: OTD | G52: 598.5 | H52: 315 | I52: 0.35 | K52: =IF(F52="",0,IFERROR(VLOOKUP(F52,Расходники!$A$4:$B$23,2,FALSE),0)) | L52: =H52*D52 | M52: =L52*K52 | N52: =SUMIF(Материалы!$A$4:$A$800,SUBSTITUTE(SUBSTITUTE(SUBSTITUTE(B52,"~","~~"),"*","~*"),"?","~?"),Материалы!$S$4:$S$800) | O52: =L52+M52+N52 | P52: =IF(SUM($O$4:$O$672)=0,0,Косвенные!$C$9*O52/SUM($O$4:$O$672)) | Q52: =G52*D52+P52 | R52: =IF(D52=0,0,Q52/D52) | S52: =IF(D52=0,0,SUMIF(Материалы!$A$4:$A$800,SUBSTITUTE(SUBSTITUTE(SUBSTITUTE(B52,"~","~~"),"*","~*"),"?","~?"),Материалы!$T$4:$T$800)/D52) | T52: =R52+S52 | U52: =I52*D52
B53: 51. Панель ЛГКЛ (цвет RAL 6019, фактура «шагрень» или аналог) типа GYPROC (толщина 12,5 мм) | C53: м2 | D53: =IF('Форма'!G51="","",'Форма'!G51) | E53: аналог (8.2.17) облицовка | F53: OTD | G53: 598.5 | H53: 315 | I53: 0.35 | K53: =IF(F53="",0,IFERROR(VLOOKUP(F53,Расходники!$A$4:$B$23,2,FALSE),0)) | L53: =H53*D53 | M53: =L53*K53 | N53: =SUMIF(Материалы!$A$4:$A$800,SUBSTITUTE(SUBSTITUTE(SUBSTITUTE(B53,"~","~~"),"*","~*"),"?","~?"),Материалы!$S$4:$S$800) | O53: =L53+M53+N53 | P53: =IF(SUM($O$4:$O$672)=0,0,Косвенные!$C$9*O53/SUM($O$4:$O$672)) | Q53: =G53*D53+P53 | R53: =IF(D53=0,0,Q53/D53) | S53: =IF(D53=0,0,SUMIF(Материалы!$A$4:$A$800,SUBSTITUTE(SUBSTITUTE(SUBSTITUTE(B53,"~","~~"),"*","~*"),"?","~?"),Материалы!$T$4:$T$800)/D53) | T53: =R53+S53 | U53: =I53*D53
A54: 7.2.25 | B54: 52. Кафельная настенная плитка Kerama Marazzi 200x200 ( цвет-белый) (вкл. За основу клей, грунтовку, затирку швов) | C54: м2 | D54: =IF('Форма'!G52="","",'Форма'!G52) | E54: точно | F54: PLI | G54: 2160 | H54: 1150 | I54: 1.5 | J54: да | K54: =IF(F54="",0,IFERROR(VLOOKUP(F54,Расходники!$A$4:$B$23,2,FALSE),0)) | L54: =H54*D54 | M54: =L54*K54 | N54: =SUMIF(Материалы!$A$4:$A$800,SUBSTITUTE(SUBSTITUTE(SUBSTITUTE(B54,"~","~~"),"*","~*"),"?","~?"),Материалы!$S$4:$S$800) | O54: =L54+M54+N54 | P54: =IF(SUM($O$4:$O$672)=0,0,Косвенные!$C$9*O54/SUM($O$4:$O$672)) | Q54: =G54*D54+P54 | R54: =IF(D54=0,0,Q54/D54) | S54: =IF(D54=0,0,SUMIF(Материалы!$A$4:$A$800,SUBSTITUTE(SUBSTITUTE(SUBSTITUTE(B54,"~","~~"),"*","~*"),"?","~?"),Материалы!$T$4:$T$800)/D54) | T54: =R54+S54 | U54: =I54*D54
A55: 7.2.25 | B55: 53. Кафельная настенная плитка Kerama Marazzi 200x300 ( цвет-белый) (вкл. За основу клей, грунтовку, затирку швов) | C55: м2 | D55: =IF('Форма'!G53="","",'Форма'!G53) | E55: точно | F55: PLI | G55: 2160 | H55: 1150 | I55: 1.5 | J55: да | K55: =IF(F55="",0,IFERROR(VLOOKUP(F55,Расходники!$A$4:$B$23,2,FALSE),0)) | L55: =H55*D55 | M55: =L55*K55 | N55: =SUMIF(Материалы!$A$4:$A$800,SUBSTITUTE(SUBSTITUTE(SUBSTITUTE(B55,"~","~~"),"*","~*"),"?","~?"),Материалы!$S$4:$S$800) | O55: =L55+M55+N55 | P55: =IF(SUM($O$4:$O$672)=0,0,Косвенные!$C$9*O55/SUM($O$4:$O$672)) | Q55: =G55*D55+P55 | R55: =IF(D55=0,0,Q55/D55) | S55: =IF(D55=0,0,SUMIF(Материалы!$A$4:$A$800,SUBSTITUTE(SUBSTITUTE(SUBSTITUTE(B55,"~","~~"),"*","~*"),"?","~?"),Материалы!$T$4:$T$800)/D55) | T55: =R55+S55 | U55: =I55*D55
A56: 7.2.25 | B56: 54. Кафельная настенная плитка Kerama Marazzi 200x200 (оранжевый) (вкл. За основу клей, грунтовку, затирку швов) | C56: м2 | D56: =IF('Форма'!G54="","",'Форма'!G54) | E56: точно | F56: PLI | G56: 2160 | H56: 1150 | I56: 1.5 | J56: да | K56: =IF(F56="",0,IFERROR(VLOOKUP(F56,Расходники!$A$4:$B$23,2,FALSE),0)) | L56: =H56*D56 | M56: =L56*K56 | N56: =SUMIF(Материалы!$A$4:$A$800,SUBSTITUTE(SUBSTITUTE(SUBSTITUTE(B56,"~","~~"),"*","~*"),"?","~?"),Материалы!$S$4:$S$800) | O56: =L56+M56+N56 | P56: =IF(SUM($O$4:$O$672)=0,0,Косвенные!$C$9*O56/SUM($O$4:$O$672)) | Q56: =G56*D56+P56 | R56: =IF(D56=0,0,Q56/D56) | S56: =IF(D56=0,0,SUMIF(Материалы!$A$4:$A$800,SUBSTITUTE(SUBSTITUTE(SUBSTITUTE(B56,"~","~~"),"*","~*"),"?","~?"),Материалы!$T$4:$T$800)/D56) | T56: =R56+S56 | U56: =I56*D56
A57: 7.2.25 | B57: 55. Кафельная настенная плитка 200x200 (цвет серый, RAL ) (вкл. За основу клей, грунтовку, затирку швов белого цвета) | C57: м2 | D57: =IF('Форма'!G55="","",'Форма'!G55) | E57: точно | F57: PLI | G57: 2160 | H57: 1150 | I57: 1.5 | J57: да | K57: =IF(F57="",0,IFERROR(VLOOKUP(F57,Расходники!$A$4:$B$23,2,FALSE),0)) | L57: =H57*D57 | M57: =L57*K57 | N57: =SUMIF(Материалы!$A$4:$A$800,SUBSTITUTE(SUBSTITUTE(SUBSTITUTE(B57,"~","~~"),"*","~*"),"?","~?"),Материалы!$S$4:$S$800) | O57: =L57+M57+N57 | P57: =IF(SUM($O$4:$O$672)=0,0,Косвенные!$C$9*O57/SUM($O$4:$O$672)) | Q57: =G57*D57+P57 | R57: =IF(D57=0,0,Q57/D57) | S57: =IF(D57=0,0,SUMIF(Материалы!$A$4:$A$800,SUBSTITUTE(SUBSTITUTE(SUBSTITUTE(B57,"~","~~"),"*","~*"),"?","~?"),Материалы!$T$4:$T$800)/D57) | T57: =R57+S57 | U57: =I57*D57
A58: 5.4.2 | B58: 56. Сэндвич панель толщина 120 мм (ППУ) или аналог | C58: м2 | D58: =IF('Форма'!G56="","",'Форма'!G56) | E58: аналог (5.4.2), в тарифе работа без панели | F58: FAS | G58: 1450 | H58: 840 | I58: 0.7 | K58: =IF(F58="",0,IFERROR(VLOOKUP(F58,Расходники!$A$4:$B$23,2,FALSE),0)) | L58: =H58*D58 | M58: =L58*K58 | N58: =SUMIF(Материалы!$A$4:$A$800,SUBSTITUTE(SUBSTITUTE(SUBSTITUTE(B58,"~","~~"),"*","~*"),"?","~?"),Материалы!$S$4:$S$800) | O58: =L58+M58+N58 | P58: =IF(SUM($O$4:$O$672)=0,0,Косвенные!$C$9*O58/SUM($O$4:$O$672)) | Q58: =G58*D58+P58 | R58: =IF(D58=0,0,Q58/D58) | S58: =IF(D58=0,0,SUMIF(Материалы!$A$4:$A$800,SUBSTITUTE(SUBSTITUTE(SUBSTITUTE(B58,"~","~~"),"*","~*"),"?","~?"),Материалы!$T$4:$T$800)/D58) | T58: =R58+S58 | U58: =I58*D58
A59: 5.4.2 | B59: 57. Сендвич-панель стеновая ППУ (ПИР) 100мм или аналог | C59: м2 | D59: =IF('Форма'!G57="","",'Форма'!G57) | E59: аналог (5.4.2), в тарифе работа без панели | F59: FAS | G59: 1450 | H59: 840 | I59: 0.7 | K59: =IF(F59="",0,IFERROR(VLOOKUP(F59,Расходники!$A$4:$B$23,2,FALSE),0)) | L59: =H59*D59 | M59: =L59*K59 | N59: =SUMIF(Материалы!$A$4:$A$800,SUBSTITUTE(SUBSTITUTE(SUBSTITUTE(B59,"~","~~"),"*","~*"),"?","~?"),Материалы!$S$4:$S$800) | O59: =L59+M59+N59 | P59: =IF(SUM($O$4:$O$672)=0,0,Косвенные!$C$9*O59/SUM($O$4:$O$672)) | Q59: =G59*D59+P59 | R59: =IF(D59=0,0,Q59/D59) | S59: =IF(D59=0,0,SUMIF(Материалы!$A$4:$A$800,SUBSTITUTE(SUBSTITUTE(SUBSTITUTE(B59,"~","~~"),"*","~*"),"?","~?"),Материалы!$T$4:$T$800)/D59) | T59: =R59+S59 | U59: =I59*D59
A60: 5.4.2 | B60: 58. Сэндвич панели стеновые | толщина 80 мм | базальтовые, трехслойные металлические, негорючие (огнестойкость по ei - 45)/ или аналог | C60: м2 | D60: =IF('Форма'!G58="","",'Форма'!G58) | E60: аналог (5.4.2), в тарифе работа без панели | F60: FAS | G60: 1450 | H60: 840 | I60: 0.7 | K60: =IF(F60="",0,IFERROR(VLOOKUP(F60,Расходники!$A$4:$B$23,2,FALSE),0)) | L60: =H60*D60 | M60: =L60*K60 | N60: =SUMIF(Материалы!$A$4:$A$800,SUBSTITUTE(SUBSTITUTE(SUBSTITUTE(B60,"~","~~"),"*","~*"),"?","~?"),Материалы!$S$4:$S$800) | O60: =L60+M60+N60 | P60: =IF(SUM($O$4:$O$672)=0,0,Косвенные!$C$9*O60/SUM($O$4:$O$672)) | Q60: =G60*D60+P60 | R60: =IF(D60=0,0,Q60/D60) | S60: =IF(D60=0,0,SUMIF(Материалы!$A$4:$A$800,SUBSTITUTE(SUBSTITUTE(SUBSTITUTE(B60,"~","~~"),"*","~*"),"?","~?"),Материалы!$T$4:$T$800)/D60) | T60: =R60+S60 | U60: =I60*D60
B61: 59. Профильный материал для гипсокартона, направляющие (вкл. крепежные элементы) | C61: м2 | D61: =IF('Форма'!G59="","",'Форма'!G59) | E61: аналог (8.1.22), только каркас | F61: OTD | G61: 598.5 | H61: 315 | I61: 0.35 | K61: =IF(F61="",0,IFERROR(VLOOKUP(F61,Расходники!$A$4:$B$23,2,FALSE),0)) | L61: =H61*D61 | M61: =L61*K61 | N61: =SUMIF(Материалы!$A$4:$A$800,SUBSTITUTE(SUBSTITUTE(SUBSTITUTE(B61,"~","~~"),"*","~*"),"?","~?"),Материалы!$S$4:$S$800) | O61: =L61+M61+N61 | P61: =IF(SUM($O$4:$O$672)=0,0,Косвенные!$C$9*O61/SUM($O$4:$O$672)) | Q61: =G61*D61+P61 | R61: =IF(D61=0,0,Q61/D61) | S61: =IF(D61=0,0,SUMIF(Материалы!$A$4:$A$800,SUBSTITUTE(SUBSTITUTE(SUBSTITUTE(B61,"~","~~"),"*","~*"),"?","~?"),Материалы!$T$4:$T$800)/D61) | T61: =R61+S61 | U61: =I61*D61
B62: 60. Гипсокартон ГКЛВ (влагостойкий гипсокартон) типа Knauf (толщина 10мм) | C62: м2 | D62: =IF('Форма'!G60="","",'Форма'!G60) | E62: аналог (8.2.17) облицовка | F62: OTD | G62: 598.5 | H62: 315 | I62: 0.35 | K62: =IF(F62="",0,IFERROR(VLOOKUP(F62,Расходники!$A$4:$B$23,2,FALSE),0)) | L62: =H62*D62 | M62: =L62*K62 | N62: =SUMIF(Материалы!$A$4:$A$800,SUBSTITUTE(SUBSTITUTE(SUBSTITUTE(B62,"~","~~"),"*","~*"),"?","~?"),Материалы!$S$4:$S$800) | O62: =L62+M62+N62 | P62: =IF(SUM($O$4:$O$672)=0,0,Косвенные!$C$9*O62/SUM($O$4:$O$672)) | Q62: =G62*D62+P62 | R62: =IF(D62=0,0,Q62/D62) | S62: =IF(D62=0,0,SUMIF(Материалы!$A$4:$A$800,SUBSTITUTE(SUBSTITUTE(SUBSTITUTE(B62,"~","~~"),"*","~*"),"?","~?"),Материалы!$T$4:$T$800)/D62) | T62: =R62+S62 | U62: =I62*D62
B63: 61. Гипсокартон ГКЛ (обычный гипсокартон) типа Knauf (толщина 10мм) | C63: м2 | D63: =IF('Форма'!G61="","",'Форма'!G61) | E63: аналог (8.2.17) облицовка | F63: OTD | G63: 598.5 | H63: 315 | I63: 0.35 | K63: =IF(F63="",0,IFERROR(VLOOKUP(F63,Расходники!$A$4:$B$23,2,FALSE),0)) | L63: =H63*D63 | M63: =L63*K63 | N63: =SUMIF(Материалы!$A$4:$A$800,SUBSTITUTE(SUBSTITUTE(SUBSTITUTE(B63,"~","~~"),"*","~*"),"?","~?"),Материалы!$S$4:$S$800) | O63: =L63+M63+N63 | P63: =IF(SUM($O$4:$O$672)=0,0,Косвенные!$C$9*O63/SUM($O$4:$O$672)) | Q63: =G63*D63+P63 | R63: =IF(D63=0,0,Q63/D63) | S63: =IF(D63=0,0,SUMIF(Материалы!$A$4:$A$800,SUBSTITUTE(SUBSTITUTE(SUBSTITUTE(B63,"~","~~"),"*","~*"),"?","~?"),Материалы!$T$4:$T$800)/D63) | T63: =R63+S63 | U63: =I63*D63
B64: 62. профиль для монтажа гипсокартона ПН 50х40 (вкл. крепежные элементы) | C64: м.п. | D64: =IF('Форма'!G62="","",'Форма'!G62) | E64: нет в тарификаторе | F64: OTD | G64: 205.2 | H64: 108 | I64: 0.12 | K64: =IF(F64="",0,IFERROR(VLOOKUP(F64,Расходники!$A$4:$B$23,2,FALSE),0)) | L64: =H64*D64 | M64: =L64*K64 | N64: =SUMIF(Материалы!$A$4:$A$800,SUBSTITUTE(SUBSTITUTE(SUBSTITUTE(B64,"~","~~"),"*","~*"),"?","~?"),Материалы!$S$4:$S$800) | O64: =L64+M64+N64 | P64: =IF(SUM($O$4:$O$672)=0,0,Косвенные!$C$9*O64/SUM($O$4:$O$672)) | Q64: =G64*D64+P64 | R64: =IF(D64=0,0,Q64/D64) | S64: =IF(D64=0,0,SUMIF(Материалы!$A$4:$A$800,SUBSTITUTE(SUBSTITUTE(SUBSTITUTE(B64,"~","~~"),"*","~*"),"?","~?"),Материалы!$T$4:$T$800)/D64) | T64: =R64+S64 | U64: =I64*D64
B65: 63. профиль для монтажа гипсокартона ПС 50х50 (вкл. крепежные элементы) | C65: м.п. | D65: =IF('Форма'!G63="","",'Форма'!G63) | E65: нет в тарификаторе | F65: OTD | G65: 205.2 | H65: 108 | I65: 0.12 | K65: =IF(F65="",0,IFERROR(VLOOKUP(F65,Расходники!$A$4:$B$23,2,FALSE),0)) | L65: =H65*D65 | M65: =L65*K65 | N65: =SUMIF(Материалы!$A$4:$A$800,SUBSTITUTE(SUBSTITUTE(SUBSTITUTE(B65,"~","~~"),"*","~*"),"?","~?"),Материалы!$S$4:$S$800) | O65: =L65+M65+N65 | P65: =IF(SUM($O$4:$O$672)=0,0,Косвенные!$C$9*O65/SUM($O$4:$O$672)) | Q65: =G65*D65+P65 | R65: =IF(D65=0,0,Q65/D65) | S65: =IF(D65=0,0,SUMIF(Материалы!$A$4:$A$800,SUBSTITUTE(SUBSTITUTE(SUBSTITUTE(B65,"~","~~"),"*","~*"),"?","~?"),Материалы!$T$4:$T$800)/D65) | T65: =R65+S65 | U65: =I65*D65
A66: 8.2.34 | B66: 64. Краска-эмаль типа Хамерайт (цвет по выбору) в 2 слоя | C66: м2 | D66: =IF('Форма'!G64="","",'Форма'!G64) | E66: аналог (8.2.34) | F66: OTD | G66: 360 | H66: 210 | I66: 0.2 | K66: =IF(F66="",0,IFERROR(VLOOKUP(F66,Расходники!$A$4:$B$23,2,FALSE),0)) | L66: =H66*D66 | M66: =L66*K66 | N66: =SUMIF(Материалы!$A$4:$A$800,SUBSTITUTE(SUBSTITUTE(SUBSTITUTE(B66,"~","~~"),"*","~*"),"?","~?"),Материалы!$S$4:$S$800) | O66: =L66+M66+N66 | P66: =IF(SUM($O$4:$O$672)=0,0,Косвенные!$C$9*O66/SUM($O$4:$O$672)) | Q66: =G66*D66+P66 | R66: =IF(D66=0,0,Q66/D66) | S66: =IF(D66=0,0,SUMIF(Материалы!$A$4:$A$800,SUBSTITUTE(SUBSTITUTE(SUBSTITUTE(B66,"~","~~"),"*","~*"),"?","~?"),Материалы!$T$4:$T$800)/D66) | T66: =R66+S66 | U66: =I66*D66
A67: 8.2.34 | B67: 65. Краска водоэмульсионная типа Dufa Mattlatex Russia (цвет по выбору) в 2 слоя | C67: м2 | D67: =IF('Форма'!G65="","",'Форма'!G65) | E67: аналог (8.2.34) | F67: OTD | G67: 360 | H67: 210 | I67: 0.2 | K67: =IF(F67="",0,IFERROR(VLOOKUP(F67,Расходники!$A$4:$B$23,2,FALSE),0)) | L67: =H67*D67 | M67: =L67*K67 | N67: =SUMIF(Материалы!$A$4:$A$800,SUBSTITUTE(SUBSTITUTE(SUBSTITUTE(B67,"~","~~"),"*","~*"),"?","~?"),Материалы!$S$4:$S$800) | O67: =L67+M67+N67 | P67: =IF(SUM($O$4:$O$672)=0,0,Косвенные!$C$9*O67/SUM($O$4:$O$672)) | Q67: =G67*D67+P67 | R67: =IF(D67=0,0,Q67/D67) | S67: =IF(D67=0,0,SUMIF(Материалы!$A$4:$A$800,SUBSTITUTE(SUBSTITUTE(SUBSTITUTE(B67,"~","~~"),"*","~*"),"?","~?"),Материалы!$T$4:$T$800)/D67) | T67: =R67+S67 | U67: =I67*D67
A68: 5.5.18 | B68: 66. Краска водоэмульсионная наружная типа Dufa Fassadenfarbe (цвет по выбору) в 2 слоя. | C68: м2 | D68: =IF('Форма'!G66="","",'Форма'!G66) | E68: аналог (5.5.18) | F68: OTD | G68: 380 | H68: 220 | I68: 0.2 | K68: =IF(F68="",0,IFERROR(VLOOKUP(F68,Расходники!$A$4:$B$23,2,FALSE),0)) | L68: =H68*D68 | M68: =L68*K68 | N68: =SUMIF(Материалы!$A$4:$A$800,SUBSTITUTE(SUBSTITUTE(SUBSTITUTE(B68,"~","~~"),"*","~*"),"?","~?"),Материалы!$S$4:$S$800) | O68: =L68+M68+N68 | P68: =IF(SUM($O$4:$O$672)=0,0,Косвенные!$C$9*O68/SUM($O$4:$O$672)) | Q68: =G68*D68+P68 | R68: =IF(D68=0,0,Q68/D68) | S68: =IF(D68=0,0,SUMIF(Материалы!$A$4:$A$800,SUBSTITUTE(SUBSTITUTE(SUBSTITUTE(B68,"~","~~"),"*","~*"),"?","~?"),Материалы!$T$4:$T$800)/D68) | T68: =R68+S68 | U68: =I68*D68
B69: 67. Штукатурка наружная типа "KNAUF sockelputz" | C69: м2 | D69: =IF('Форма'!G67="","",'Форма'!G67) | E69: нет в тарификаторе | F69: OTD | G69: 940.5 | H69: 495 | I69: 0.55 | K69: =IF(F69="",0,IFERROR(VLOOKUP(F69,Расходники!$A$4:$B$23,2,FALSE),0)) | L69: =H69*D69 | M69: =L69*K69 | N69: =SUMIF(Материалы!$A$4:$A$800,SUBSTITUTE(SUBSTITUTE(SUBSTITUTE(B69,"~","~~"),"*","~*"),"?","~?"),Материалы!$S$4:$S$800) | O69: =L69+M69+N69 | P69: =IF(SUM($O$4:$O$672)=0,0,Косвенные!$C$9*O69/SUM($O$4:$O$672)) | Q69: =G69*D69+P69 | R69: =IF(D69=0,0,Q69/D69) | S69: =IF(D69=0,0,SUMIF(Материалы!$A$4:$A$800,SUBSTITUTE(SUBSTITUTE(SUBSTITUTE(B69,"~","~~"),"*","~*"),"?","~?"),Материалы!$T$4:$T$800)/D69) | T69: =R69+S69 | U69: =I69*D69
A70: 8.2.38 | B70: 68. Шпаклевка типа UNIS фасадная | C70: м2 | D70: =IF('Форма'!G68="","",'Форма'!G68) | E70: аналог (8.2.38) | F70: OTD | G70: 540 | H70: 310 | I70: 0.45 | J70: да | K70: =IF(F70="",0,IFERROR(VLOOKUP(F70,Расходники!$A$4:$B$23,2,FALSE),0)) | L70: =H70*D70 | M70: =L70*K70 | N70: =SUMIF(Материалы!$A$4:$A$800,SUBSTITUTE(SUBSTITUTE(SUBSTITUTE(B70,"~","~~"),"*","~*"),"?","~?"),Материалы!$S$4:$S$800) | O70: =L70+M70+N70 | P70: =IF(SUM($O$4:$O$672)=0,0,Косвенные!$C$9*O70/SUM($O$4:$O$672)) | Q70: =G70*D70+P70 | R70: =IF(D70=0,0,Q70/D70) | S70: =IF(D70=0,0,SUMIF(Материалы!$A$4:$A$800,SUBSTITUTE(SUBSTITUTE(SUBSTITUTE(B70,"~","~~"),"*","~*"),"?","~?"),Материалы!$T$4:$T$800)/D70) | T70: =R70+S70 | U70: =I70*D70
A71: 5.5.14 | B71: 69. Грунтовка типа UNIS универсальная в 2 слоя | C71: м2 | D71: =IF('Форма'!G69="","",'Форма'!G69) | E71: точно | F71: OTD | G71: 80 | H71: 46 | I71: 0.04 | K71: =IF(F71="",0,IFERROR(VLOOKUP(F71,Расходники!$A$4:$B$23,2,FALSE),0)) | L71: =H71*D71 | M71: =L71*K71 | N71: =SUMIF(Материалы!$A$4:$A$800,SUBSTITUTE(SUBSTITUTE(SUBSTITUTE(B71,"~","~~"),"*","~*"),"?","~?"),Материалы!$S$4:$S$800) | O71: =L71+M71+N71 | P71: =IF(SUM($O$4:$O$672)=0,0,Косвенные!$C$9*O71/SUM($O$4:$O$672)) | Q71: =G71*D71+P71 | R71: =IF(D71=0,0,Q71/D71) | S71: =IF(D71=0,0,SUMIF(Материалы!$A$4:$A$800,SUBSTITUTE(SUBSTITUTE(SUBSTITUTE(B71,"~","~~"),"*","~*"),"?","~?"),Материалы!$T$4:$T$800)/D71) | T71: =R71+S71 | U71: =I71*D71
B72: 70. Штукатурка внутренняя типа "KNAUF MP 75" | C72: м2 | D72: =IF('Форма'!G70="","",'Форма'!G70) | E72: нет в тарификаторе | F72: OTD | G72: 940.5 | H72: 495 | I72: 0.55 | K72: =IF(F72="",0,IFERROR(VLOOKUP(F72,Расходники!$A$4:$B$23,2,FALSE),0)) | L72: =H72*D72 | M72: =L72*K72 | N72: =SUMIF(Материалы!$A$4:$A$800,SUBSTITUTE(SUBSTITUTE(SUBSTITUTE(B72,"~","~~"),"*","~*"),"?","~?"),Материалы!$S$4:$S$800) | O72: =L72+M72+N72 | P72: =IF(SUM($O$4:$O$672)=0,0,Косвенные!$C$9*O72/SUM($O$4:$O$672)) | Q72: =G72*D72+P72 | R72: =IF(D72=0,0,Q72/D72) | S72: =IF(D72=0,0,SUMIF(Материалы!$A$4:$A$800,SUBSTITUTE(SUBSTITUTE(SUBSTITUTE(B72,"~","~~"),"*","~*"),"?","~?"),Материалы!$T$4:$T$800)/D72) | T72: =R72+S72 | U72: =I72*D72
A73: 8.2.38 | B73: 71. Шпаклевка гипсовая типа "Unis БЛИК" | C73: м2 | D73: =IF('Форма'!G71="","",'Форма'!G71) | E73: аналог (8.2.38) | F73: OTD | G73: 540 | H73: 310 | I73: 0.45 | J73: да | K73: =IF(F73="",0,IFERROR(VLOOKUP(F73,Расходники!$A$4:$B$23,2,FALSE),0)) | L73: =H73*D73 | M73: =L73*K73 | N73: =SUMIF(Материалы!$A$4:$A$800,SUBSTITUTE(SUBSTITUTE(SUBSTITUTE(B73,"~","~~"),"*","~*"),"?","~?"),Материалы!$S$4:$S$800) | O73: =L73+M73+N73 | P73: =IF(SUM($O$4:$O$672)=0,0,Косвенные!$C$9*O73/SUM($O$4:$O$672)) | Q73: =G73*D73+P73 | R73: =IF(D73=0,0,Q73/D73) | S73: =IF(D73=0,0,SUMIF(Материалы!$A$4:$A$800,SUBSTITUTE(SUBSTITUTE(SUBSTITUTE(B73,"~","~~"),"*","~*"),"?","~?"),Материалы!$T$4:$T$800)/D73) | T73: =R73+S73 | U73: =I73*D73
B74: 72. Панель Випрок ламинированная 3000х1200х12,5 | C74: м2 | D74: =IF('Форма'!G72="","",'Форма'!G72) | E74: аналог (8.2.17) облицовка | F74: OTD | G74: 598.5 | H74: 315 | I74: 0.35 | K74: =IF(F74="",0,IFERROR(VLOOKUP(F74,Расходники!$A$4:$B$23,2,FALSE),0)) | L74: =H74*D74 | M74: =L74*K74 | N74: =SUMIF(Материалы!$A$4:$A$800,SUBSTITUTE(SUBSTITUTE(SUBSTITUTE(B74,"~","~~"),"*","~*"),"?","~?"),Материалы!$S$4:$S$800) | O74: =L74+M74+N74 | P74: =IF(SUM($O$4:$O$672)=0,0,Косвенные!$C$9*O74/SUM($O$4:$O$672)) | Q74: =G74*D74+P74 | R74: =IF(D74=0,0,Q74/D74) | S74: =IF(D74=0,0,SUMIF(Материалы!$A$4:$A$800,SUBSTITUTE(SUBSTITUTE(SUBSTITUTE(B74,"~","~~"),"*","~*"),"?","~?"),Материалы!$T$4:$T$800)/D74) | T74: =R74+S74 | U74: =I74*D74
B75: 73. Профиль Кнауф ПН 100х40з3000 | C75: п.м | D75: =IF('Форма'!G73="","",'Форма'!G73) | E75: нет в тарификаторе | F75: OTD | G75: 256.5 | H75: 135 | I75: 0.15 | K75: =IF(F75="",0,IFERROR(VLOOKUP(F75,Расходники!$A$4:$B$23,2,FALSE),0)) | L75: =H75*D75 | M75: =L75*K75 | N75: =SUMIF(Материалы!$A$4:$A$800,SUBSTITUTE(SUBSTITUTE(SUBSTITUTE(B75,"~","~~"),"*","~*"),"?","~?"),Материалы!$S$4:$S$800) | O75: =L75+M75+N75 | P75: =IF(SUM($O$4:$O$672)=0,0,Косвенные!$C$9*O75/SUM($O$4:$O$672)) | Q75: =G75*D75+P75 | R75: =IF(D75=0,0,Q75/D75) | S75: =IF(D75=0,0,SUMIF(Материалы!$A$4:$A$800,SUBSTITUTE(SUBSTITUTE(SUBSTITUTE(B75,"~","~~"),"*","~*"),"?","~?"),Материалы!$T$4:$T$800)/D75) | T75: =R75+S75 | U75: =I75*D75
B76: 74. Профиль Кнауф ПС 100x50х3000 | C76: п.м | D76: =IF('Форма'!G74="","",'Форма'!G74) | E76: нет в тарификаторе | F76: OTD | G76: 256.5 | H76: 135 | I76: 0.15 | K76: =IF(F76="",0,IFERROR(VLOOKUP(F76,Расходники!$A$4:$B$23,2,FALSE),0)) | L76: =H76*D76 | M76: =L76*K76 | N76: =SUMIF(Материалы!$A$4:$A$800,SUBSTITUTE(SUBSTITUTE(SUBSTITUTE(B76,"~","~~"),"*","~*"),"?","~?"),Материалы!$S$4:$S$800) | O76: =L76+M76+N76 | P76: =IF(SUM($O$4:$O$672)=0,0,Косвенные!$C$9*O76/SUM($O$4:$O$672)) | Q76: =G76*D76+P76 | R76: =IF(D76=0,0,Q76/D76) | S76: =IF(D76=0,0,SUMIF(Материалы!$A$4:$A$800,SUBSTITUTE(SUBSTITUTE(SUBSTITUTE(B76,"~","~~"),"*","~*"),"?","~?"),Материалы!$T$4:$T$800)/D76) | T76: =R76+S76 | U76: =I76*D76
B77: 75. Лента уплотнительная 50 мм | C77: м.п. | D77: =IF('Форма'!G75="","",'Форма'!G75) | E77: нет в тарификаторе | F77: OTD | G77: 85.5 | H77: 45 | I77: 0.05 | K77: =IF(F77="",0,IFERROR(VLOOKUP(F77,Расходники!$A$4:$B$23,2,FALSE),0)) | L77: =H77*D77 | M77: =L77*K77 | N77: =SUMIF(Материалы!$A$4:$A$800,SUBSTITUTE(SUBSTITUTE(SUBSTITUTE(B77,"~","~~"),"*","~*"),"?","~?"),Материалы!$S$4:$S$800) | O77: =L77+M77+N77 | P77: =IF(SUM($O$4:$O$672)=0,0,Косвенные!$C$9*O77/SUM($O$4:$O$672)) | Q77: =G77*D77+P77 | R77: =IF(D77=0,0,Q77/D77) | S77: =IF(D77=0,0,SUMIF(Материалы!$A$4:$A$800,SUBSTITUTE(SUBSTITUTE(SUBSTITUTE(B77,"~","~~"),"*","~*"),"?","~?"),Материалы!$T$4:$T$800)/D77) | T77: =R77+S77 | U77: =I77*D77
B78: 76. Уголок пластиковый 25х25 мм | C78: м.п. | D78: =IF('Форма'!G76="","",'Форма'!G76) | E78: нет в тарификаторе | F78: OTD | G78: 136.8 | H78: 72 | I78: 0.08 | K78: =IF(F78="",0,IFERROR(VLOOKUP(F78,Расходники!$A$4:$B$23,2,FALSE),0)) | L78: =H78*D78 | M78: =L78*K78 | N78: =SUMIF(Материалы!$A$4:$A$800,SUBSTITUTE(SUBSTITUTE(SUBSTITUTE(B78,"~","~~"),"*","~*"),"?","~?"),Материалы!$S$4:$S$800) | O78: =L78+M78+N78 | P78: =IF(SUM($O$4:$O$672)=0,0,Косвенные!$C$9*O78/SUM($O$4:$O$672)) | Q78: =G78*D78+P78 | R78: =IF(D78=0,0,Q78/D78) | S78: =IF(D78=0,0,SUMIF(Материалы!$A$4:$A$800,SUBSTITUTE(SUBSTITUTE(SUBSTITUTE(B78,"~","~~"),"*","~*"),"?","~?"),Материалы!$T$4:$T$800)/D78) | T78: =R78+S78 | U78: =I78*D78
A79: 8.2.38 | B79: 77. Полимерная шпатлевка LR для внутренних работ. Рекомендуется для устранения мельчайших дефектов поверхности. CERESIT CT 127 (или аналог) | C79: м2 | D79: =IF('Форма'!G77="","",'Форма'!G77) | E79: аналог (8.2.38) | F79: OTD | G79: 540 | H79: 310 | I79: 0.45 | J79: да | K79: =IF(F79="",0,IFERROR(VLOOKUP(F79,Расходники!$A$4:$B$23,2,FALSE),0)) | L79: =H79*D79 | M79: =L79*K79 | N79: =SUMIF(Материалы!$A$4:$A$800,SUBSTITUTE(SUBSTITUTE(SUBSTITUTE(B79,"~","~~"),"*","~*"),"?","~?"),Материалы!$S$4:$S$800) | O79: =L79+M79+N79 | P79: =IF(SUM($O$4:$O$672)=0,0,Косвенные!$C$9*O79/SUM($O$4:$O$672)) | Q79: =G79*D79+P79 | R79: =IF(D79=0,0,Q79/D79) | S79: =IF(D79=0,0,SUMIF(Материалы!$A$4:$A$800,SUBSTITUTE(SUBSTITUTE(SUBSTITUTE(B79,"~","~~"),"*","~*"),"?","~?"),Материалы!$T$4:$T$800)/D79) | T79: =R79+S79 | U79: =I79*D79
A80: 8.2.38 | B80: 78. Полимерная шпатлевка KR для внутренних работ. Применяется для заделки трещин выбоин и др. дефектов поверхностей. CERESIT CT 127 (или аналог) | C80: м2 | D80: =IF('Форма'!G78="","",'Форма'!G78) | E80: аналог (8.2.38) | F80: OTD | G80: 540 | H80: 310 | I80: 0.45 | J80: да | K80: =IF(F80="",0,IFERROR(VLOOKUP(F80,Расходники!$A$4:$B$23,2,FALSE),0)) | L80: =H80*D80 | M80: =L80*K80 | N80: =SUMIF(Материалы!$A$4:$A$800,SUBSTITUTE(SUBSTITUTE(SUBSTITUTE(B80,"~","~~"),"*","~*"),"?","~?"),Материалы!$S$4:$S$800) | O80: =L80+M80+N80 | P80: =IF(SUM($O$4:$O$672)=0,0,Косвенные!$C$9*O80/SUM($O$4:$O$672)) | Q80: =G80*D80+P80 | R80: =IF(D80=0,0,Q80/D80) | S80: =IF(D80=0,0,SUMIF(Материалы!$A$4:$A$800,SUBSTITUTE(SUBSTITUTE(SUBSTITUTE(B80,"~","~~"),"*","~*"),"?","~?"),Материалы!$T$4:$T$800)/D80) | T80: =R80+S80 | U80: =I80*D80
B81: 79. Фасадная финишная шпаклевка, серая. Рекомендуется для выравнивания поверхностей фасадов зданий , заделки выбоин , трещин, раковин слоем до 6 мм . CERESIT CT 225 (или аналог) | C81: м2 | D81: =IF('Форма'!G79="","",'Форма'!G79) | E81: аналог (9.1.64), единица приведена к нормо-часам | F81: SAN | G81: 2926 | H81: 1428 | I81: 1.4 | K81: =IF(F81="",0,IFERROR(VLOOKUP(F81,Расходники!$A$4:$B$23,2,FALSE),0)) | L81: =H81*D81 | M81: =L81*K81 | N81: =SUMIF(Материалы!$A$4:$A$800,SUBSTITUTE(SUBSTITUTE(SUBSTITUTE(B81,"~","~~"),"*","~*"),"?","~?"),Материалы!$S$4:$S$800) | O81: =L81+M81+N81 | P81: =IF(SUM($O$4:$O$672)=0,0,Косвенные!$C$9*O81/SUM($O$4:$O$672)) | Q81: =G81*D81+P81 | R81: =IF(D81=0,0,Q81/D81) | S81: =IF(D81=0,0,SUMIF(Материалы!$A$4:$A$800,SUBSTITUTE(SUBSTITUTE(SUBSTITUTE(B81,"~","~~"),"*","~*"),"?","~?"),Материалы!$T$4:$T$800)/D81) | T81: =R81+S81 | U81: =I81*D81
A82: 8.2.N7 | B82: 80. Финишная полимерная шпаклевка для внутренних работ.Рекомендуется для шпаклевания штукатурных и бетонных поверхностей стен и потолков перед оклейкой обоев или окраской. CERESIT | C82: м2 | D82: =IF('Форма'!G80="","",'Форма'!G80) | E82: аналог (8.2.N7) | F82: OTD | G82: 440 | H82: 265 | I82: 0.25 | K82: =IF(F82="",0,IFERROR(VLOOKUP(F82,Расходники!$A$4:$B$23,2,FALSE),0)) | L82: =H82*D82 | M82: =L82*K82 | N82: =SUMIF(Материалы!$A$4:$A$800,SUBSTITUTE(SUBSTITUTE(SUBSTITUTE(B82,"~","~~"),"*","~*"),"?","~?"),Материалы!$S$4:$S$800) | O82: =L82+M82+N82 | P82: =IF(SUM($O$4:$O$672)=0,0,Косвенные!$C$9*O82/SUM($O$4:$O$672)) | Q82: =G82*D82+P82 | R82: =IF(D82=0,0,Q82/D82) | S82: =IF(D82=0,0,SUMIF(Материалы!$A$4:$A$800,SUBSTITUTE(SUBSTITUTE(SUBSTITUTE(B82,"~","~~"),"*","~*"),"?","~?"),Материалы!$T$4:$T$800)/D82) | T82: =R82+S82 | U82: =I82*D82
A83: 5.5.14 | B83: 81. Грунтовка для обработки гладких оснований . Рекомендуется для обработки слабо впитывающих Оснований к нанесению различных отделочных материалов перед нанесением гипсовых и цеме | C83: м2 | D83: =IF('Форма'!G81="","",'Форма'!G81) | E83: точно | F83: OTD | G83: 80 | H83: 46 | I83: 0.04 | K83: =IF(F83="",0,IFERROR(VLOOKUP(F83,Расходники!$A$4:$B$23,2,FALSE),0)) | L83: =H83*D83 | M83: =L83*K83 | N83: =SUMIF(Материалы!$A$4:$A$800,SUBSTITUTE(SUBSTITUTE(SUBSTITUTE(B83,"~","~~"),"*","~*"),"?","~?"),Материалы!$S$4:$S$800) | O83: =L83+M83+N83 | P83: =IF(SUM($O$4:$O$672)=0,0,Косвенные!$C$9*O83/SUM($O$4:$O$672)) | Q83: =G83*D83+P83 | R83: =IF(D83=0,0,Q83/D83) | S83: =IF(D83=0,0,SUMIF(Материалы!$A$4:$A$800,SUBSTITUTE(SUBSTITUTE(SUBSTITUTE(B83,"~","~~"),"*","~*"),"?","~?"),Материалы!$T$4:$T$800)/D83) | T83: =R83+S83 | U83: =I83*D83
B84: 82. Универсальная самовыравнивающаяся смесь . Финишный ровнитель для тщательного выравнивания и последующей укладки декоративных напольных покрытий, нанесения тонкослойных наливных | C84: м2 | D84: =IF('Форма'!G82="","",'Форма'!G82) | E84: нет в тарификаторе | F84: OTD | G84: 940.5 | H84: 495 | I84: 0.55 | K84: =IF(F84="",0,IFERROR(VLOOKUP(F84,Расходники!$A$4:$B$23,2,FALSE),0)) | L84: =H84*D84 | M84: =L84*K84 | N84: =SUMIF(Материалы!$A$4:$A$800,SUBSTITUTE(SUBSTITUTE(SUBSTITUTE(B84,"~","~~"),"*","~*"),"?","~?"),Материалы!$S$4:$S$800) | O84: =L84+M84+N84 | P84: =IF(SUM($O$4:$O$672)=0,0,Косвенные!$C$9*O84/SUM($O$4:$O$672)) | Q84: =G84*D84+P84 | R84: =IF(D84=0,0,Q84/D84) | S84: =IF(D84=0,0,SUMIF(Материалы!$A$4:$A$800,SUBSTITUTE(SUBSTITUTE(SUBSTITUTE(B84,"~","~~"),"*","~*"),"?","~?"),Материалы!$T$4:$T$800)/D84) | T84: =R84+S84 | U84: =I84*D84
B85: 83. Уголок пластиковый 25х25 мм | C85: м.п. | D85: =IF('Форма'!G83="","",'Форма'!G83) | E85: нет в тарификаторе | F85: OTD | G85: 136.8 | H85: 72 | I85: 0.08 | K85: =IF(F85="",0,IFERROR(VLOOKUP(F85,Расходники!$A$4:$B$23,2,FALSE),0)) | L85: =H85*D85 | M85: =L85*K85 | N85: =SUMIF(Материалы!$A$4:$A$800,SUBSTITUTE(SUBSTITUTE(SUBSTITUTE(B85,"~","~~"),"*","~*"),"?","~?"),Материалы!$S$4:$S$800) | O85: =L85+M85+N85 | P85: =IF(SUM($O$4:$O$672)=0,0,Косвенные!$C$9*O85/SUM($O$4:$O$672)) | Q85: =G85*D85+P85 | R85: =IF(D85=0,0,Q85/D85) | S85: =IF(D85=0,0,SUMIF(Материалы!$A$4:$A$800,SUBSTITUTE(SUBSTITUTE(SUBSTITUTE(B85,"~","~~"),"*","~*"),"?","~?"),Материалы!$T$4:$T$800)/D85) | T85: =R85+S85 | U85: =I85*D85
B86: 84. Уголок пластиковый 40х40 мм | C86: м.п. | D86: =IF('Форма'!G84="","",'Форма'!G84) | E86: нет в тарификаторе | F86: OTD | G86: 136.8 | H86: 72 | I86: 0.08 | K86: =IF(F86="",0,IFERROR(VLOOKUP(F86,Расходники!$A$4:$B$23,2,FALSE),0)) | L86: =H86*D86 | M86: =L86*K86 | N86: =SUMIF(Материалы!$A$4:$A$800,SUBSTITUTE(SUBSTITUTE(SUBSTITUTE(B86,"~","~~"),"*","~*"),"?","~?"),Материалы!$S$4:$S$800) | O86: =L86+M86+N86 | P86: =IF(SUM($O$4:$O$672)=0,0,Косвенные!$C$9*O86/SUM($O$4:$O$672)) | Q86: =G86*D86+P86 | R86: =IF(D86=0,0,Q86/D86) | S86: =IF(D86=0,0,SUMIF(Материалы!$A$4:$A$800,SUBSTITUTE(SUBSTITUTE(SUBSTITUTE(B86,"~","~~"),"*","~*"),"?","~?"),Материалы!$T$4:$T$800)/D86) | T86: =R86+S86 | U86: =I86*D86
B87: 85. Уголок пластиковый 60х60 мм | C87: м.п. | D87: =IF('Форма'!G85="","",'Форма'!G85) | E87: нет в тарификаторе | F87: OTD | G87: 136.8 | H87: 72 | I87: 0.08 | K87: =IF(F87="",0,IFERROR(VLOOKUP(F87,Расходники!$A$4:$B$23,2,FALSE),0)) | L87: =H87*D87 | M87: =L87*K87 | N87: =SUMIF(Материалы!$A$4:$A$800,SUBSTITUTE(SUBSTITUTE(SUBSTITUTE(B87,"~","~~"),"*","~*"),"?","~?"),Материалы!$S$4:$S$800) | O87: =L87+M87+N87 | P87: =IF(SUM($O$4:$O$672)=0,0,Косвенные!$C$9*O87/SUM($O$4:$O$672)) | Q87: =G87*D87+P87 | R87: =IF(D87=0,0,Q87/D87) | S87: =IF(D87=0,0,SUMIF(Материалы!$A$4:$A$800,SUBSTITUTE(SUBSTITUTE(SUBSTITUTE(B87,"~","~~"),"*","~*"),"?","~?"),Материалы!$T$4:$T$800)/D87) | T87: =R87+S87 | U87: =I87*D87
B88: 86. Алмазное бурение. Диаметр отверстия от 50 мм до 200 мм включительно (Бетон) | C88: см. | D88: =IF('Форма'!G86="","",'Форма'!G86) | E88: нет в тарификаторе | F88: BET | G88: 95 | H88: 55 | I88: 0.08 | K88: =IF(F88="",0,IFERROR(VLOOKUP(F88,Расходники!$A$4:$B$23,2,FALSE),0)) | L88: =H88*D88 | M88: =L88*K88 | N88: =SUMIF(Материалы!$A$4:$A$800,SUBSTITUTE(SUBSTITUTE(SUBSTITUTE(B88,"~","~~"),"*","~*"),"?","~?"),Материалы!$S$4:$S$800) | O88: =L88+M88+N88 | P88: =IF(SUM($O$4:$O$672)=0,0,Косвенные!$C$9*O88/SUM($O$4:$O$672)) | Q88: =G88*D88+P88 | R88: =IF(D88=0,0,Q88/D88) | S88: =IF(D88=0,0,SUMIF(Материалы!$A$4:$A$800,SUBSTITUTE(SUBSTITUTE(SUBSTITUTE(B88,"~","~~"),"*","~*"),"?","~?"),Материалы!$T$4:$T$800)/D88) | T88: =R88+S88 | U88: =I88*D88
B89: 87. Стопор дверной типа Amig 103 | C89: шт. | D89: =IF('Форма'!G87="","",'Форма'!G87) | E89: аналог (12.7.N5) | F89: DVR | G89: 570 | H89: 285 | I89: 0.3 | K89: =IF(F89="",0,IFERROR(VLOOKUP(F89,Расходники!$A$4:$B$23,2,FALSE),0)) | L89: =H89*D89 | M89: =L89*K89 | N89: =SUMIF(Материалы!$A$4:$A$800,SUBSTITUTE(SUBSTITUTE(SUBSTITUTE(B89,"~","~~"),"*","~*"),"?","~?"),Материалы!$S$4:$S$800) | O89: =L89+M89+N89 | P89: =IF(SUM($O$4:$O$672)=0,0,Косвенные!$C$9*O89/SUM($O$4:$O$672)) | Q89: =G89*D89+P89 | R89: =IF(D89=0,0,Q89/D89) | S89: =IF(D89=0,0,SUMIF(Материалы!$A$4:$A$800,SUBSTITUTE(SUBSTITUTE(SUBSTITUTE(B89,"~","~~"),"*","~*"),"?","~?"),Материалы!$T$4:$T$800)/D89) | T89: =R89+S89 | U89: =I89*D89
B90: 88. Шпингалет APEX 100 мм. | C90: шт. | D90: =IF('Форма'!G88="","",'Форма'!G88) | E90: аналог (12.7.N5) | F90: DVR | G90: 570 | H90: 285 | I90: 0.3 | K90: =IF(F90="",0,IFERROR(VLOOKUP(F90,Расходники!$A$4:$B$23,2,FALSE),0)) | L90: =H90*D90 | M90: =L90*K90 | N90: =SUMIF(Материалы!$A$4:$A$800,SUBSTITUTE(SUBSTITUTE(SUBSTITUTE(B90,"~","~~"),"*","~*"),"?","~?"),Материалы!$S$4:$S$800) | O90: =L90+M90+N90 | P90: =IF(SUM($O$4:$O$672)=0,0,Косвенные!$C$9*O90/SUM($O$4:$O$672)) | Q90: =G90*D90+P90 | R90: =IF(D90=0,0,Q90/D90) | S90: =IF(D90=0,0,SUMIF(Материалы!$A$4:$A$800,SUBSTITUTE(SUBSTITUTE(SUBSTITUTE(B90,"~","~~"),"*","~*"),"?","~?"),Материалы!$T$4:$T$800)/D90) | T90: =R90+S90 | U90: =I90*D90
B91: 89. Наличники дверные пвх | C91: м.п. | D91: =IF('Форма'!G89="","",'Форма'!G89) | E91: аналог (12.7.N5) | F91: DVR | G91: 570 | H91: 285 | I91: 0.3 | K91: =IF(F91="",0,IFERROR(VLOOKUP(F91,Расходники!$A$4:$B$23,2,FALSE),0)) | L91: =H91*D91 | M91: =L91*K91 | N91: =SUMIF(Материалы!$A$4:$A$800,SUBSTITUTE(SUBSTITUTE(SUBSTITUTE(B91,"~","~~"),"*","~*"),"?","~?"),Материалы!$S$4:$S$800) | O91: =L91+M91+N91 | P91: =IF(SUM($O$4:$O$672)=0,0,Косвенные!$C$9*O91/SUM($O$4:$O$672)) | Q91: =G91*D91+P91 | R91: =IF(D91=0,0,Q91/D91) | S91: =IF(D91=0,0,SUMIF(Материалы!$A$4:$A$800,SUBSTITUTE(SUBSTITUTE(SUBSTITUTE(B91,"~","~~"),"*","~*"),"?","~?"),Материалы!$T$4:$T$800)/D91) | T91: =R91+S91 | U91: =I91*D91
B92: 90. Засов дверной (Москва-№6) | C92: шт. | D92: =IF('Форма'!G90="","",'Форма'!G90) | E92: аналог (12.7.N5) | F92: DVR | G92: 570 | H92: 285 | I92: 0.3 | K92: =IF(F92="",0,IFERROR(VLOOKUP(F92,Расходники!$A$4:$B$23,2,FALSE),0)) | L92: =H92*D92 | M92: =L92*K92 | N92: =SUMIF(Материалы!$A$4:$A$800,SUBSTITUTE(SUBSTITUTE(SUBSTITUTE(B92,"~","~~"),"*","~*"),"?","~?"),Материалы!$S$4:$S$800) | O92: =L92+M92+N92 | P92: =IF(SUM($O$4:$O$672)=0,0,Косвенные!$C$9*O92/SUM($O$4:$O$672)) | Q92: =G92*D92+P92 | R92: =IF(D92=0,0,Q92/D92) | S92: =IF(D92=0,0,SUMIF(Материалы!$A$4:$A$800,SUBSTITUTE(SUBSTITUTE(SUBSTITUTE(B92,"~","~~"),"*","~*"),"?","~?"),Материалы!$T$4:$T$800)/D92) | T92: =R92+S92 | U92: =I92*D92
B93: 91. Упор дверной напольный "Крит" УД-П60/50-Цн | C93: шт. | D93: =IF('Форма'!G91="","",'Форма'!G91) | E93: аналог (12.7.N5) | F93: DVR | G93: 570 | H93: 285 | I93: 0.3 | K93: =IF(F93="",0,IFERROR(VLOOKUP(F93,Расходники!$A$4:$B$23,2,FALSE),0)) | L93: =H93*D93 | M93: =L93*K93 | N93: =SUMIF(Материалы!$A$4:$A$800,SUBSTITUTE(SUBSTITUTE(SUBSTITUTE(B93,"~","~~"),"*","~*"),"?","~?"),Материалы!$S$4:$S$800) | O93: =L93+M93+N93 | P93: =IF(SUM($O$4:$O$672)=0,0,Косвенные!$C$9*O93/SUM($O$4:$O$672)) | Q93: =G93*D93+P93 | R93: =IF(D93=0,0,Q93/D93) | S93: =IF(D93=0,0,SUMIF(Материалы!$A$4:$A$800,SUBSTITUTE(SUBSTITUTE(SUBSTITUTE(B93,"~","~~"),"*","~*"),"?","~?"),Материалы!$T$4:$T$800)/D93) | T93: =R93+S93 | U93: =I93*D93
B94: 92. Фиксатор (стопор) открытого положения двери типа Palladium "КН" (любой цвет по RAL) | C94: шт. | D94: =IF('Форма'!G92="","",'Форма'!G92) | E94: аналог (12.7.N5) | F94: DVR | G94: 570 | H94: 285 | I94: 0.3 | K94: =IF(F94="",0,IFERROR(VLOOKUP(F94,Расходники!$A$4:$B$23,2,FALSE),0)) | L94: =H94*D94 | M94: =L94*K94 | N94: =SUMIF(Материалы!$A$4:$A$800,SUBSTITUTE(SUBSTITUTE(SUBSTITUTE(B94,"~","~~"),"*","~*"),"?","~?"),Материалы!$S$4:$S$800) | O94: =L94+M94+N94 | P94: =IF(SUM($O$4:$O$672)=0,0,Косвенные!$C$9*O94/SUM($O$4:$O$672)) | Q94: =G94*D94+P94 | R94: =IF(D94=0,0,Q94/D94) | S94: =IF(D94=0,0,SUMIF(Материалы!$A$4:$A$800,SUBSTITUTE(SUBSTITUTE(SUBSTITUTE(B94,"~","~~"),"*","~*"),"?","~?"),Материалы!$T$4:$T$800)/D94) | T94: =R94+S94 | U94: =I94*D94
A95: 10.3.19 | B95: 93. Концевой выключатель кнопочного типа "Elfin limit switch 050f02" | C95: шт. | D95: =IF('Форма'!G93="","",'Форма'!G93) | E95: аналог (10.3.19) | F95: ELM | G95: 544 | H95: 330 | I95: 0.4 | J95: да | K95: =IF(F95="",0,IFERROR(VLOOKUP(F95,Расходники!$A$4:$B$23,2,FALSE),0)) | L95: =H95*D95 | M95: =L95*K95 | N95: =SUMIF(Материалы!$A$4:$A$800,SUBSTITUTE(SUBSTITUTE(SUBSTITUTE(B95,"~","~~"),"*","~*"),"?","~?"),Материалы!$S$4:$S$800) | O95: =L95+M95+N95 | P95: =IF(SUM($O$4:$O$672)=0,0,Косвенные!$C$9*O95/SUM($O$4:$O$672)) | Q95: =G95*D95+P95 | R95: =IF(D95=0,0,Q95/D95) | S95: =IF(D95=0,0,SUMIF(Материалы!$A$4:$A$800,SUBSTITUTE(SUBSTITUTE(SUBSTITUTE(B95,"~","~~"),"*","~*"),"?","~?"),Материалы!$T$4:$T$800)/D95) | T95: =R95+S95 | U95: =I95*D95
A96: 12.7.4 | B96: 94. Петля СТН (белая) "Сатурн" | C96: шт. | D96: =IF('Форма'!G94="","",'Форма'!G94) | E96: аналог (12.7.4) | F96: DVR | G96: 690 | H96: 428 | I96: 0.4 | K96: =IF(F96="",0,IFERROR(VLOOKUP(F96,Расходники!$A$4:$B$23,2,FALSE),0)) | L96: =H96*D96 | M96: =L96*K96 | N96: =SUMIF(Материалы!$A$4:$A$800,SUBSTITUTE(SUBSTITUTE(SUBSTITUTE(B96,"~","~~"),"*","~*"),"?","~?"),Материалы!$S$4:$S$800) | O96: =L96+M96+N96 | P96: =IF(SUM($O$4:$O$672)=0,0,Косвенные!$C$9*O96/SUM($O$4:$O$672)) | Q96: =G96*D96+P96 | R96: =IF(D96=0,0,Q96/D96) | S96: =IF(D96=0,0,SUMIF(Материалы!$A$4:$A$800,SUBSTITUTE(SUBSTITUTE(SUBSTITUTE(B96,"~","~~"),"*","~*"),"?","~?"),Материалы!$T$4:$T$800)/D96) | T96: =R96+S96 | U96: =I96*D96
A97: 12.7.4 | B97: 95. Петля дверная трёхсекционная с крепежом | C97: шт. | D97: =IF('Форма'!G95="","",'Форма'!G95) | E97: аналог (12.7.4) | F97: DVR | G97: 690 | H97: 428 | I97: 0.4 | K97: =IF(F97="",0,IFERROR(VLOOKUP(F97,Расходники!$A$4:$B$23,2,FALSE),0)) | L97: =H97*D97 | M97: =L97*K97 | N97: =SUMIF(Материалы!$A$4:$A$800,SUBSTITUTE(SUBSTITUTE(SUBSTITUTE(B97,"~","~~"),"*","~*"),"?","~?"),Материалы!$S$4:$S$800) | O97: =L97+M97+N97 | P97: =IF(SUM($O$4:$O$672)=0,0,Косвенные!$C$9*O97/SUM($O$4:$O$672)) | Q97: =G97*D97+P97 | R97: =IF(D97=0,0,Q97/D97) | S97: =IF(D97=0,0,SUMIF(Материалы!$A$4:$A$800,SUBSTITUTE(SUBSTITUTE(SUBSTITUTE(B97,"~","~~"),"*","~*"),"?","~?"),Материалы!$T$4:$T$800)/D97) | T97: =R97+S97 | U97: =I97*D97
A98: 12.7.4 | B98: 96. Петля типа FT 65 | C98: шт. | D98: =IF('Форма'!G96="","",'Форма'!G96) | E98: аналог (12.7.4) | F98: DVR | G98: 690 | H98: 428 | I98: 0.4 | K98: =IF(F98="",0,IFERROR(VLOOKUP(F98,Расходники!$A$4:$B$23,2,FALSE),0)) | L98: =H98*D98 | M98: =L98*K98 | N98: =SUMIF(Материалы!$A$4:$A$800,SUBSTITUTE(SUBSTITUTE(SUBSTITUTE(B98,"~","~~"),"*","~*"),"?","~?"),Материалы!$S$4:$S$800) | O98: =L98+M98+N98 | P98: =IF(SUM($O$4:$O$672)=0,0,Косвенные!$C$9*O98/SUM($O$4:$O$672)) | Q98: =G98*D98+P98 | R98: =IF(D98=0,0,Q98/D98) | S98: =IF(D98=0,0,SUMIF(Материалы!$A$4:$A$800,SUBSTITUTE(SUBSTITUTE(SUBSTITUTE(B98,"~","~~"),"*","~*"),"?","~?"),Материалы!$T$4:$T$800)/D98) | T98: =R98+S98 | U98: =I98*D98
A99: 12.7.4 | B99: 97. Петля карточная типа Amig-1007-100*70 (латунь) универс. | C99: шт. | D99: =IF('Форма'!G97="","",'Форма'!G97) | E99: аналог (12.7.4) | F99: DVR | G99: 690 | H99: 428 | I99: 0.4 | K99: =IF(F99="",0,IFERROR(VLOOKUP(F99,Расходники!$A$4:$B$23,2,FALSE),0)) | L99: =H99*D99 | M99: =L99*K99 | N99: =SUMIF(Материалы!$A$4:$A$800,SUBSTITUTE(SUBSTITUTE(SUBSTITUTE(B99,"~","~~"),"*","~*"),"?","~?"),Материалы!$S$4:$S$800) | O99: =L99+M99+N99 | P99: =IF(SUM($O$4:$O$672)=0,0,Косвенные!$C$9*O99/SUM($O$4:$O$672)) | Q99: =G99*D99+P99 | R99: =IF(D99=0,0,Q99/D99) | S99: =IF(D99=0,0,SUMIF(Материалы!$A$4:$A$800,SUBSTITUTE(SUBSTITUTE(SUBSTITUTE(B99,"~","~~"),"*","~*"),"?","~?"),Материалы!$T$4:$T$800)/D99) | T99: =R99+S99 | U99: =I99*D99
A100: 12.7.4 | B100: 98. Петля карточная типа Apecs 120*80-F-B4-Steel-CR(хром) | C100: шт. | D100: =IF('Форма'!G98="","",'Форма'!G98) | E100: аналог (12.7.4) | F100: DVR | G100: 690 | H100: 428 | I100: 0.4 | K100: =IF(F100="",0,IFERROR(VLOOKUP(F100,Расходники!$A$4:$B$23,2,FALSE),0)) | L100: =H100*D100 | M100: =L100*K100 | N100: =SUMIF(Материалы!$A$4:$A$800,SUBSTITUTE(SUBSTITUTE(SUBSTITUTE(B100,"~","~~"),"*","~*"),"?","~?"),Материалы!$S$4:$S$800) | O100: =L100+M100+N100 | P100: =IF(SUM($O$4:$O$672)=0,0,Косвенные!$C$9*O100/SUM($O$4:$O$672)) | Q100: =G100*D100+P100 | R100: =IF(D100=0,0,Q100/D100) | S100: =IF(D100=0,0,SUMIF(Материалы!$A$4:$A$800,SUBSTITUTE(SUBSTITUTE(SUBSTITUTE(B100,"~","~~"),"*","~*"),"?","~?"),Материалы!$T$4:$T$800)/D100) | T100: =R100+S100 | U100: =I100*D100
A101: 12.7.4 | B101: 99. Петля под навесной замок | C101: шт. | D101: =IF('Форма'!G99="","",'Форма'!G99) | E101: аналог (12.7.4) | F101: DVR | G101: 690 | H101: 428 | I101: 0.4 | K101: =IF(F101="",0,IFERROR(VLOOKUP(F101,Расходники!$A$4:$B$23,2,FALSE),0)) | L101: =H101*D101 | M101: =L101*K101 | N101: =SUMIF(Материалы!$A$4:$A$800,SUBSTITUTE(SUBSTITUTE(SUBSTITUTE(B101,"~","~~"),"*","~*"),"?","~?"),Материалы!$S$4:$S$800) | O101: =L101+M101+N101 | P101: =IF(SUM($O$4:$O$672)=0,0,Косвенные!$C$9*O101/SUM($O$4:$O$672)) | Q101: =G101*D101+P101 | R101: =IF(D101=0,0,Q101/D101) | S101: =IF(D101=0,0,SUMIF(Материалы!$A$4:$A$800,SUBSTITUTE(SUBSTITUTE(SUBSTITUTE(B101,"~","~~"),"*","~*"),"?","~?"),Материалы!$T$4:$T$800)/D101) | T101: =R101+S101 | U101: =I101*D101
...

Sheet Материалы
A1: Материалы. Жёлтые — ввод. Кол-во = норма на единицу работы × объём этой работы.
A3: К работе | B3: Материал | C3: Категория | D3: Ед. | E3: Норма на ед. | F3: Кол-во | G3: Цена источника | H3: НДС в цене (1/0) | I3: Отходы | J3: Наценка | K3: Розница с НДС | L3: Магазин | M3: Ссылка | N3: Дата | O3: Примечание | P3: Закупка б/НДС | Q3: С/с ед. | R3: Цена КП ед. | S3: С/с итого | T3: КП итого | U3: Выше розницы | V3: Закупка итого б/НДС
A4: 6. Восстановление шарниров: Замена осей крепления, шплинтов, втулок и очистка петель от загрязнений. | B4: Оси, втулки, шплинты доклевеллера, комплект | C4: Металлопрокат и метизы | D4: компл | E4: 1 | F4: =E4*IFERROR(INDEX(Работы!$D$4:$D$672,MATCH(SUBSTITUTE(SUBSTITUTE(SUBSTITUTE(A4,"~","~~"),"*","~*"),"?","~?"),Работы!$B$4:$B$672,0)),0) | G4: 1800 | H4: 1 | I4: 0.05 | J4: 0.1 | L4: оценка | N4: 2026-10-29 | O4: оценка комплекта шарнира, запросить DoorHan В Петрович, Лемана ПРО и Сатурн открытой карточки нет, оставлен прежний источник. | P4: =IF(H4=1,G4/VAT_DIV,G4) | Q4: =P4*(1+I4)*(1+DELIV)*(1+GROWTH+MONEY) | R4: =IF(AND(K4<>"",Q4*(1+J4)>K4/VAT_DIV),K4/VAT_DIV,Q4*(1+J4)) | S4: =Q4*F4 | T4: =R4*F4 | U4: =IF(AND(K4<>"",Q4*(1+J4)>K4/VAT_DIV+0.01),"ДА","") | V4: =P4*F4
A5: 7. Сварочные работы, усиление или замена листов с противоскользящим покрытием. | B5: Лист рифлёный на аппарель, до 0,5 м2 | C5: Металлопрокат и метизы | D5: кг | E5: 8 | F5: =E5*IFERROR(INDEX(Работы!$D$4:$D$672,MATCH(SUBSTITUTE(SUBSTITUTE(SUBSTITUTE(A5,"~","~~"),"*","~*"),"?","~?"),Работы!$B$4:$B$672,0)),0) | G5: 79.76 | H5: 1 | I5: 0.05 | J5: 0.1 | L5: Петрович | M5: https://moscow.petrovich.ru/product/108534/ | N5: 2026-10-29 | O5: Петрович, труба 40х40х2, 587 руб/3 м с НДС, 7,36 кг. Цена кг с НДС 79.76. Карта клуба не учитывалась. | P5: =IF(H5=1,G5/VAT_DIV,G5) | Q5: =P5*(1+I5)*(1+DELIV)*(1+GROWTH+MONEY) | R5: =IF(AND(K5<>"",Q5*(1+J5)>K5/VAT_DIV),K5/VAT_DIV,Q5*(1+J5)) | S5: =Q5*F5 | T5: =R5*F5 | U5: =IF(AND(K5<>"",Q5*(1+J5)>K5/VAT_DIV+0.01),"ДА","") | V5: =P5*F5
A6: 8. Замена пружин для плавного опускания/поднятия. | B6: Пружина доклевеллера | C6: Изделия под заказ (ворота, двери, окна, перегородки) | D6: шт | E6: 1 | F6: =E6*IFERROR(INDEX(Работы!$D$4:$D$672,MATCH(SUBSTITUTE(SUBSTITUTE(SUBSTITUTE(A6,"~","~~"),"*","~*"),"?","~?"),Работы!$B$4:$B$672,0)),0) | G6: 4500 | H6: 1 | I6: 0 | J6: 0.12 | L6: оценка | N6: 2026-10-29 | O6: оценка, запросить DoorHan В Петрович, Лемана ПРО и Сатурн открытой карточки нет, оставлен прежний источник. | P6: =IF(H6=1,G6/VAT_DIV,G6) | Q6: =P6*(1+I6)*(1+DELIV)*(1+GROWTH+MONEY) | R6: =IF(AND(K6<>"",Q6*(1+J6)>K6/VAT_DIV),K6/VAT_DIV,Q6*(1+J6)) | S6: =Q6*F6 | T6: =R6*F6 | U6: =IF(AND(K6<>"",Q6*(1+J6)>K6/VAT_DIV+0.01),"ДА","") | V6: =P6*F6
A7: 10. Замена арматуры сливного бачка типа «Компакт» (включая материалы и з/части) | B7: Арматура бачка компакт | C7: Сантехприборы | D7: шт | E7: 1 | F7: =E7*IFERROR(INDEX(Работы!$D$4:$D$672,MATCH(SUBSTITUTE(SUBSTITUTE(SUBSTITUTE(A7,"~","~~"),"*","~*"),"?","~?"),Работы!$B$4:$B$672,0)),0) | G7: 650 | H7: 1 | I7: 0 | J7: 0.12 | L7: оценка | N7: 2026-10-29 | O7: оценка полки Петрович/Лемана В Петрович, Лемана ПРО и Сатурн открытой карточки нет, оставлен прежний источник. | P7: =IF(H7=1,G7/VAT_DIV,G7) | Q7: =P7*(1+I7)*(1+DELIV)*(1+GROWTH+MONEY) | R7: =IF(AND(K7<>"",Q7*(1+J7)>K7/VAT_DIV),K7/VAT_DIV,Q7*(1+J7)) | S7: =Q7*F7 | T7: =R7*F7 | U7: =IF(AND(K7<>"",Q7*(1+J7)>K7/VAT_DIV+0.01),"ДА","") | V7: =P7*F7
A8: 11. Замена сливного бачка унитаза типа «Компакт» (включая материалы и з/части) | B8: Бачок компакт с арматурой | C8: Сантехприборы | D8: шт | E8: 1 | F8: =E8*IFERROR(INDEX(Работы!$D$4:$D$672,MATCH(SUBSTITUTE(SUBSTITUTE(SUBSTITUTE(A8,"~","~~"),"*","~*"),"?","~?"),Работы!$B$4:$B$672,0)),0) | G8: 1800 | H8: 1 | I8: 0 | J8: 0.12 | L8: оценка | N8: 2026-10-29 | O8: оценка В Петрович, Лемана ПРО и Сатурн открытой карточки нет, оставлен прежний источник. | P8: =IF(H8=1,G8/VAT_DIV,G8) | Q8: =P8*(1+I8)*(1+DELIV)*(1+GROWTH+MONEY) | R8: =IF(AND(K8<>"",Q8*(1+J8)>K8/VAT_DIV),K8/VAT_DIV,Q8*(1+J8)) | S8: =Q8*F8 | T8: =R8*F8 | U8: =IF(AND(K8<>"",Q8*(1+J8)>K8/VAT_DIV+0.01),"ДА","") | V8: =P8*F8
A9: 12. Замена унитаза типа «Компакт» (включая материалы и з/части) | B9: Унитаз-компакт | C9: Сантехприборы | D9: шт | E9: 1 | F9: =E9*IFERROR(INDEX(Работы!$D$4:$D$672,MATCH(SUBSTITUTE(SUBSTITUTE(SUBSTITUTE(A9,"~","~~"),"*","~*"),"?","~?"),Работы!$B$4:$B$672,0)),0) | G9: 4990 | H9: 1 | I9: 0 | J9: 0.12 | L9: Лемана ПРО | M9: https://lemanapro.ru/product/unitaz-kompakt-yauza-82199701/ | N9: 2026-10-29 | O9: Минимум: Лемана ПРО Яуза 4 990 руб. Сатурн Sanita Эталон 5 666, Петрович Cersanit Trento 8 130. | P9: =IF(H9=1,G9/VAT_DIV,G9) | Q9: =P9*(1+I9)*(1+DELIV)*(1+GROWTH+MONEY) | R9: =IF(AND(K9<>"",Q9*(1+J9)>K9/VAT_DIV),K9/VAT_DIV,Q9*(1+J9)) | S9: =Q9*F9 | T9: =R9*F9 | U9: =IF(AND(K9<>"",Q9*(1+J9)>K9/VAT_DIV+0.01),"ДА","") | V9: =P9*F9
A10: 13. Замена гибкой подводки сантехнической до 60 см (включая материалы и з/части) | B10: Подводка гибкая 60 см | C10: Трубы и фитинги ВиК, отопления | D10: шт | E10: 1 | F10: =E10*IFERROR(INDEX(Работы!$D$4:$D$672,MATCH(SUBSTITUTE(SUBSTITUTE(SUBSTITUTE(A10,"~","~~"),"*","~*"),"?","~?"),Работы!$B$4:$B$672,0)),0) | G10: 250 | H10: 1 | I10: 0.04 | J10: 0.12 | L10: оценка | N10: 2026-10-29 | O10: оценка В Петрович, Лемана ПРО и Сатурн открытой карточки нет, оставлен прежний источник. | P10: =IF(H10=1,G10/VAT_DIV,G10) | Q10: =P10*(1+I10)*(1+DELIV)*(1+GROWTH+MONEY) | R10: =IF(AND(K10<>"",Q10*(1+J10)>K10/VAT_DIV),K10/VAT_DIV,Q10*(1+J10)) | S10: =Q10*F10 | T10: =R10*F10 | U10: =IF(AND(K10<>"",Q10*(1+J10)>K10/VAT_DIV+0.01),"ДА","") | V10: =P10*F10
A11: 14. Замена смесителя раковины (включая материалы и з/части) | B11: Смеситель для раковины | C11: Сантехприборы | D11: шт | E11: 1 | F11: =E11*IFERROR(INDEX(Работы!$D$4:$D$672,MATCH(SUBSTITUTE(SUBSTITUTE(SUBSTITUTE(A11,"~","~~"),"*","~*"),"?","~?"),Работы!$B$4:$B$672,0)),0) | G11: 1108 | H11: 1 | I11: 0 | J11: 0.12 | L11: Сатурн | M11: https://msk.saturn.net/product/smesitel-dlya-rakovini-klip-803/ | N11: 2026-10-29 | O11: Минимум: Сатурн Klip 803 = 1 108 руб. Петрович РМС 1 176, Лемана ПРО Fixsen 3 680. | P11: =IF(H11=1,G11/VAT_DIV,G11) | Q11: =P11*(1+I11)*(1+DELIV)*(1+GROWTH+MONEY) | R11: =IF(AND(K11<>"",Q11*(1+J11)>K11/VAT_DIV),K11/VAT_DIV,Q11*(1+J11)) | S11: =Q11*F11 | T11: =R11*F11 | U11: =IF(AND(K11<>"",Q11*(1+J11)>K11/VAT_DIV+0.01),"ДА","") | V11: =P11*F11
A12: 15. Замена раковины керамической с пьедесталом (включая материалы и з/части) | B12: Замена раковины керамической с пьедесталом (включая материалы и з/части) | C12: Сантехприборы | D12: шт | E12: 1 | F12: =E12*IFERROR(INDEX(Работы!$D$4:$D$672,MATCH(SUBSTITUTE(SUBSTITUTE(SUBSTITUTE(A12,"~","~~"),"*","~*"),"?","~?"),Работы!$B$4:$B$672,0)),0) | G12: 3840 | H12: 1 | I12: 0 | J12: 0.12 | L12: Петрович | M12: https://moscow.petrovich.ru/product/1094953/ | N12: 2026-10-29 | O12: Петрович, комплект Sanita Аттика 55 см (раковина и пьедестал) 3 840 руб. Прочие размеры — тот же аналог. | P12: =IF(H12=1,G12/VAT_DIV,G12) | Q12: =P12*(1+I12)*(1+DELIV)*(1+GROWTH+MONEY) | R12: =IF(AND(K12<>"",Q12*(1+J12)>K12/VAT_DIV),K12/VAT_DIV,Q12*(1+J12)) | S12: =Q12*F12 | T12: =R12*F12 | U12: =IF(AND(K12<>"",Q12*(1+J12)>K12/VAT_DIV+0.01),"ДА","") | V12: =P12*F12
A13: 16. Замена раковины металлической (включая материалы и з/части) | B13: Замена раковины металлической (включая материалы и з/части) | C13: Сантехприборы | D13: шт | E13: 1 | F13: =E13*IFERROR(INDEX(Работы!$D$4:$D$672,MATCH(SUBSTITUTE(SUBSTITUTE(SUBSTITUTE(A13,"~","~~"),"*","~*"),"?","~?"),Работы!$B$4:$B$672,0)),0) | G13: 3840 | H13: 1 | I13: 0 | J13: 0.12 | L13: Петрович | M13: https://moscow.petrovich.ru/product/1094953/ | N13: 2026-10-29 | O13: Петрович, комплект Sanita Аттика 55 см (раковина и пьедестал) 3 840 руб. Прочие размеры — тот же аналог. | P13: =IF(H13=1,G13/VAT_DIV,G13) | Q13: =P13*(1+I13)*(1+DELIV)*(1+GROWTH+MONEY) | R13: =IF(AND(K13<>"",Q13*(1+J13)>K13/VAT_DIV),K13/VAT_DIV,Q13*(1+J13)) | S13: =Q13*F13 | T13: =R13*F13 | U13: =IF(AND(K13<>"",Q13*(1+J13)>K13/VAT_DIV+0.01),"ДА","") | V13: =P13*F13
A14: 17. Замена смесителя для ванны с душевой лейкой (включая материалы и з/части) | B14: Смеситель для ванны с лейкой | C14: Сантехприборы | D14: шт | E14: 1 | F14: =E14*IFERROR(INDEX(Работы!$D$4:$D$672,MATCH(SUBSTITUTE(SUBSTITUTE(SUBSTITUTE(A14,"~","~~"),"*","~*"),"?","~?"),Работы!$B$4:$B$672,0)),0) | G14: 3200 | H14: 1 | I14: 0 | J14: 0.12 | L14: оценка | N14: 2026-10-29 | O14: оценка средний сегмент В Петрович, Лемана ПРО и Сатурн открытой карточки нет, оставлен прежний источник. | P14: =IF(H14=1,G14/VAT_DIV,G14) | Q14: =P14*(1+I14)*(1+DELIV)*(1+GROWTH+MONEY) | R14: =IF(AND(K14<>"",Q14*(1+J14)>K14/VAT_DIV),K14/VAT_DIV,Q14*(1+J14)) | S14: =Q14*F14 | T14: =R14*F14 | U14: =IF(AND(K14<>"",Q14*(1+J14)>K14/VAT_DIV+0.01),"ДА","") | V14: =P14*F14
A15: 19. Замена сифона раковины (включая материалы и з/части) | B15: Замена сифона раковины (включая материалы и з/части) | C15: Сантехприборы | D15: шт | E15: 1 | F15: =E15*IFERROR(INDEX(Работы!$D$4:$D$672,MATCH(SUBSTITUTE(SUBSTITUTE(SUBSTITUTE(A15,"~","~~"),"*","~*"),"?","~?"),Работы!$B$4:$B$672,0)),0) | G15: 3840 | H15: 1 | I15: 0 | J15: 0.12 | L15: Петрович | M15: https://moscow.petrovich.ru/product/1094953/ | N15: 2026-10-29 | O15: Петрович, комплект Sanita Аттика 55 см (раковина и пьедестал) 3 840 руб. Прочие размеры — тот же аналог. | P15: =IF(H15=1,G15/VAT_DIV,G15) | Q15: =P15*(1+I15)*(1+DELIV)*(1+GROWTH+MONEY) | R15: =IF(AND(K15<>"",Q15*(1+J15)>K15/VAT_DIV),K15/VAT_DIV,Q15*(1+J15)) | S15: =Q15*F15 | T15: =R15*F15 | U15: =IF(AND(K15<>"",Q15*(1+J15)>K15/VAT_DIV+0.01),"ДА","") | V15: =P15*F15
A16: 20. Замена крана писсуара (включая материалы и з/части) | B16: Кран писсуара | C16: Сантехприборы | D16: шт | E16: 1 | F16: =E16*IFERROR(INDEX(Работы!$D$4:$D$672,MATCH(SUBSTITUTE(SUBSTITUTE(SUBSTITUTE(A16,"~","~~"),"*","~*"),"?","~?"),Работы!$B$4:$B$672,0)),0) | G16: 1400 | H16: 1 | I16: 0 | J16: 0.12 | L16: оценка | N16: 2026-10-29 | O16: оценка В Петрович, Лемана ПРО и Сатурн открытой карточки нет, оставлен прежний источник. | P16: =IF(H16=1,G16/VAT_DIV,G16) | Q16: =P16*(1+I16)*(1+DELIV)*(1+GROWTH+MONEY) | R16: =IF(AND(K16<>"",Q16*(1+J16)>K16/VAT_DIV),K16/VAT_DIV,Q16*(1+J16)) | S16: =Q16*F16 | T16: =R16*F16 | U16: =IF(AND(K16<>"",Q16*(1+J16)>K16/VAT_DIV+0.01),"ДА","") | V16: =P16*F16
A17: 21. Прокладка трубопровода ХВС, ГВС из полипропиленовых труб Ø20-32 мм (включая материалы, комплетующие и з/части) за 1 п.м. | B17: Труба ПП d32 | C17: Трубы и фитинги ВиК, отопления | D17: м | E17: 1 | F17: =E17*IFERROR(INDEX(Работы!$D$4:$D$672,MATCH(SUBSTITUTE(SUBSTITUTE(SUBSTITUTE(A17,"~","~~"),"*","~*"),"?","~?"),Работы!$B$4:$B$672,0)),0) | G17: 120.1 | H17: 1 | I17: 0.04 | J17: 0.12 | L17: Петрович | M17: https://moscow.petrovich.ru/product/1154066/ | N17: 2026-10-29 | O17: Якорь Петрович Lammin PN25 d25 = 85 руб/м (Лемана ПРО 85,5). Остальные диаметры — прежний коэффициент к d25. | P17: =IF(H17=1,G17/VAT_DIV,G17) | Q17: =P17*(1+I17)*(1+DELIV)*(1+GROWTH+MONEY) | R17: =IF(AND(K17<>"",Q17*(1+J17)>K17/VAT_DIV),K17/VAT_DIV,Q17*(1+J17)) | S17: =Q17*F17 | T17: =R17*F17 | U17: =IF(AND(K17<>"",Q17*(1+J17)>K17/VAT_DIV+0.01),"ДА","") | V17: =P17*F17
A18: 22. Прокладка трубопровода внутренней канализации Ø40 мм (включая материалы и з/части) за 1 п.м. | B18: Труба канализация d40 | C18: Трубы и фитинги ВиК, отопления | D18: м | E18: 1 | F18: =E18*IFERROR(INDEX(Работы!$D$4:$D$672,MATCH(SUBSTITUTE(SUBSTITUTE(SUBSTITUTE(A18,"~","~~"),"*","~*"),"?","~?"),Работы!$B$4:$B$672,0)),0) | G18: 85 | H18: 1 | I18: 0.04 | J18: 0.12 | L18: оценка | N18: 2026-10-29 | O18: оценка ПВХ/ПП внутренней канализации В Петрович, Лемана ПРО и Сатурн открытой карточки нет, оставлен прежний источник. | P18: =IF(H18=1,G18/VAT_DIV,G18) | Q18: =P18*(1+I18)*(1+DELIV)*(1+GROWTH+MONEY) | R18: =IF(AND(K18<>"",Q18*(1+J18)>K18/VAT_DIV),K18/VAT_DIV,Q18*(1+J18)) | S18: =Q18*F18 | T18: =R18*F18 | U18: =IF(AND(K18<>"",Q18*(1+J18)>K18/VAT_DIV+0.01),"ДА","") | V18: =P18*F18
A19: 23. Прокладка трубопровода внутренней канализации Ø50 мм (включая материалы и з/части) за 1 п.м. | B19: Труба канализация d50 | C19: Трубы и фитинги ВиК, отопления | D19: м | E19: 1 | F19: =E19*IFERROR(INDEX(Работы!$D$4:$D$672,MATCH(SUBSTITUTE(SUBSTITUTE(SUBSTITUTE(A19,"~","~~"),"*","~*"),"?","~?"),Работы!$B$4:$B$672,0)),0) | G19: 110 | H19: 1 | I19: 0.04 | J19: 0.12 | L19: оценка | N19: 2026-10-29 | O19: оценка ПВХ/ПП внутренней канализации В Петрович, Лемана ПРО и Сатурн открытой карточки нет, оставлен прежний источник. | P19: =IF(H19=1,G19/VAT_DIV,G19) | Q19: =P19*(1+I19)*(1+DELIV)*(1+GROWTH+MONEY) | R19: =IF(AND(K19<>"",Q19*(1+J19)>K19/VAT_DIV),K19/VAT_DIV,Q19*(1+J19)) | S19: =Q19*F19 | T19: =R19*F19 | U19: =IF(AND(K19<>"",Q19*(1+J19)>K19/VAT_DIV+0.01),"ДА","") | V19: =P19*F19
A20: 24. Прокладка трубопровода внутренней канализации Ø100 мм (включая материалы и з/части) за 1 п.м. | B20: Труба канализация d32 | C20: Трубы и фитинги ВиК, отопления | D20: м | E20: 1 | F20: =E20*IFERROR(INDEX(Работы!$D$4:$D$672,MATCH(SUBSTITUTE(SUBSTITUTE(SUBSTITUTE(A20,"~","~~"),"*","~*"),"?","~?"),Работы!$B$4:$B$672,0)),0) | G20: 70 | H20: 1 | I20: 0.04 | J20: 0.12 | L20: оценка | N20: 2026-10-29 | O20: оценка ПВХ/ПП внутренней канализации В Петрович, Лемана ПРО и Сатурн открытой карточки нет, оставлен прежний источник. | P20: =IF(H20=1,G20/VAT_DIV,G20) | Q20: =P20*(1+I20)*(1+DELIV)*(1+GROWTH+MONEY) | R20: =IF(AND(K20<>"",Q20*(1+J20)>K20/VAT_DIV),K20/VAT_DIV,Q20*(1+J20)) | S20: =Q20*F20 | T20: =R20*F20 | U20: =IF(AND(K20<>"",Q20*(1+J20)>K20/VAT_DIV+0.01),"ДА","") | V20: =P20*F20
A21: 25. Устранение протечек в сантехническом оборудовании (включая материалы и з/части) за 1 ед. | B21: Лён, паста, прокладки | C21: Трубы и фитинги ВиК, отопления | D21: компл | E21: 1 | F21: =E21*IFERROR(INDEX(Работы!$D$4:$D$672,MATCH(SUBSTITUTE(SUBSTITUTE(SUBSTITUTE(A21,"~","~~"),"*","~*"),"?","~?"),Работы!$B$4:$B$672,0)),0) | G21: 180 | H21: 1 | I21: 0.04 | J21: 0.12 | L21: оценка | N21: 2026-10-29 | O21: оценка В Петрович, Лемана ПРО и Сатурн открытой карточки нет, оставлен прежний источник. | P21: =IF(H21=1,G21/VAT_DIV,G21) | Q21: =P21*(1+I21)*(1+DELIV)*(1+GROWTH+MONEY) | R21: =IF(AND(K21<>"",Q21*(1+J21)>K21/VAT_DIV),K21/VAT_DIV,Q21*(1+J21)) | S21: =Q21*F21 | T21: =R21*F21 | U21: =IF(AND(K21<>"",Q21*(1+J21)>K21/VAT_DIV+0.01),"ДА","") | V21: =P21*F21
A22: 26. Замена запорной арматуры трубопроводов (включая материалы и з/части) за 1 ед. | B22: Кран шаровой латунь Ду15–25 | C22: Трубы и фитинги ВиК, отопления | D22: шт | E22: 1 | F22: =E22*IFERROR(INDEX(Работы!$D$4:$D$672,MATCH(SUBSTITUTE(SUBSTITUTE(SUBSTITUTE(A22,"~","~~"),"*","~*"),"?","~?"),Работы!$B$4:$B$672,0)),0) | G22: 420 | H22: 1 | I22: 0.04 | J22: 0.12 | L22: оценка | N22: 2026-10-29 | O22: оценка В Петрович, Лемана ПРО и Сатурн открытой карточки нет, оставлен прежний источник. | P22: =IF(H22=1,G22/VAT_DIV,G22) | Q22: =P22*(1+I22)*(1+DELIV)*(1+GROWTH+MONEY) | R22: =IF(AND(K22<>"",Q22*(1+J22)>K22/VAT_DIV),K22/VAT_DIV,Q22*(1+J22)) | S22: =Q22*F22 | T22: =R22*F22 | U22: =IF(AND(K22<>"",Q22*(1+J22)>K22/VAT_DIV+0.01),"ДА","") | V22: =P22*F22
A23: 27. Подключение к системе ХВС, ГВС приборов (водонагреватель, кулер, пурифайр, стиральная машинка и т.д.) (включая материалы, комплектующие, фитинги, з/части и т.д.) за 1 ед. | B23: Кран и подводка для прибора | C23: Трубы и фитинги ВиК, отопления | D23: компл | E23: 1 | F23: =E23*IFERROR(INDEX(Работы!$D$4:$D$672,MATCH(SUBSTITUTE(SUBSTITUTE(SUBSTITUTE(A23,"~","~~"),"*","~*"),"?","~?"),Работы!$B$4:$B$672,0)),0) | G23: 650 | H23: 1 | I23: 0.04 | J23: 0.12 | L23: оценка | N23: 2026-10-29 | O23: оценка В Петрович, Лемана ПРО и Сатурн открытой карточки нет, оставлен прежний источник. | P23: =IF(H23=1,G23/VAT_DIV,G23) | Q23: =P23*(1+I23)*(1+DELIV)*(1+GROWTH+MONEY) | R23: =IF(AND(K23<>"",Q23*(1+J23)>K23/VAT_DIV),K23/VAT_DIV,Q23*(1+J23)) | S23: =Q23*F23 | T23: =R23*F23 | U23: =IF(AND(K23<>"",Q23*(1+J23)>K23/VAT_DIV+0.01),"ДА","") | V23: =P23*F23
A24: 29. Планка примыкания верхняя, нижняя 150 х 250 с полимерным покрытием по RAL по согласованию | B24: Планка 150х250, ~1,6 кг/м | C24: Металлопрокат и метизы | D24: кг | E24: 1.6 | F24: =E24*IFERROR(INDEX(Работы!$D$4:$D$672,MATCH(SUBSTITUTE(SUBSTITUTE(SUBSTITUTE(A24,"~","~~"),"*","~*"),"?","~?"),Работы!$B$4:$B$672,0)),0) | G24: 107.68 | H24: 1 | I24: 0.05 | J24: 0.1 | L24: Петрович | M24: https://moscow.petrovich.ru/product/108534/ | N24: 2026-10-29 | O24: Петрович, труба 40х40х2, 587 руб/3 м с НДС, 7,36 кг. Цена кг с НДС 79.76. Карта клуба не учитывалась. коэффициент 1.35 к чёрному — оценка, запросить КП металлобазы | P24: =IF(H24=1,G24/VAT_DIV,G24) | Q24: =P24*(1+I24)*(1+DELIV)*(1+GROWTH+MONEY) | R24: =IF(AND(K24<>"",Q24*(1+J24)>K24/VAT_DIV),K24/VAT_DIV,Q24*(1+J24)) | S24: =Q24*F24 | T24: =R24*F24 | U24: =IF(AND(K24<>"",Q24*(1+J24)>K24/VAT_DIV+0.01),"ДА","") | V24: =P24*F24
A25: 30. Монтаж профлиста С8-115 - 0,50 окрашенный | B25: Монтаж профлиста С8-115 - 0,50 окрашенный | C25: Кровельные материалы и утеплитель | D25: м2 | E25: 1.08 | F25: =E25*IFERROR(INDEX(Работы!$D$4:$D$672,MATCH(SUBSTITUTE(SUBSTITUTE(SUBSTITUTE(A25,"~","~~"),"*","~*"),"?","~?"),Работы!$B$4:$B$672,0)),0) | G25: 560 | H25: 1 | I25: 0.1 | J25: 0.12 | L25: оценка | N25: 2026-10-29 | O25: оценка профлиста С8 0,45–0,5, запросить металлобазу В Петрович, Лемана ПРО и Сатурн открытой карточки нет, оставлен прежний источник. | P25: =IF(H25=1,G25/VAT_DIV,G25) | Q25: =P25*(1+I25)*(1+DELIV)*(1+GROWTH+MONEY) | R25: =IF(AND(K25<>"",Q25*(1+J25)>K25/VAT_DIV),K25/VAT_DIV,Q25*(1+J25)) | S25: =Q25*F25 | T25: =R25*F25 | U25: =IF(AND(K25<>"",Q25*(1+J25)>K25/VAT_DIV+0.01),"ДА","") | V25: =P25*F25
A26: 31. Монтаж профлиста С8, 0,45мм | B26: Монтаж профлиста С8, 0,45мм | C26: Кровельные материалы и утеплитель | D26: м2 | E26: 1.08 | F26: =E26*IFERROR(INDEX(Работы!$D$4:$D$672,MATCH(SUBSTITUTE(SUBSTITUTE(SUBSTITUTE(A26,"~","~~"),"*","~*"),"?","~?"),Работы!$B$4:$B$672,0)),0) | G26: 560 | H26: 1 | I26: 0.1 | J26: 0.12 | L26: оценка | N26: 2026-10-29 | O26: оценка профлиста С8 0,45–0,5, запросить металлобазу В Петрович, Лемана ПРО и Сатурн открытой карточки нет, оставлен прежний источник. | P26: =IF(H26=1,G26/VAT_DIV,G26) | Q26: =P26*(1+I26)*(1+DELIV)*(1+GROWTH+MONEY) | R26: =IF(AND(K26<>"",Q26*(1+J26)>K26/VAT_DIV),K26/VAT_DIV,Q26*(1+J26)) | S26: =Q26*F26 | T26: =R26*F26 | U26: =IF(AND(K26<>"",Q26*(1+J26)>K26/VAT_DIV+0.01),"ДА","") | V26: =P26*F26
A27: 32. Монтаж профлиста С20, 0,45мм | B27: Монтаж профлиста С20, 0,45мм | C27: Кровельные материалы и утеплитель | D27: м2 | E27: 1.08 | F27: =E27*IFERROR(INDEX(Работы!$D$4:$D$672,MATCH(SUBSTITUTE(SUBSTITUTE(SUBSTITUTE(A27,"~","~~"),"*","~*"),"?","~?"),Работы!$B$4:$B$672,0)),0) | G27: 560 | H27: 1 | I27: 0.1 | J27: 0.12 | L27: оценка | N27: 2026-10-29 | O27: оценка профлиста С8 0,45–0,5, запросить металлобазу В Петрович, Лемана ПРО и Сатурн открытой карточки нет, оставлен прежний источник. | P27: =IF(H27=1,G27/VAT_DIV,G27) | Q27: =P27*(1+I27)*(1+DELIV)*(1+GROWTH+MONEY) | R27: =IF(AND(K27<>"",Q27*(1+J27)>K27/VAT_DIV),K27/VAT_DIV,Q27*(1+J27)) | S27: =Q27*F27 | T27: =R27*F27 | U27: =IF(AND(K27<>"",Q27*(1+J27)>K27/VAT_DIV+0.01),"ДА","") | V27: =P27*F27
A28: 33. Поручни из нержавеющей стали ( с 3 ригелями ) | B28: Поручни из нержавеющей стали ( с 3 ригелями ) | C28: Металлопрокат и метизы | D28: м | E28: 1 | F28: =E28*IFERROR(INDEX(Работы!$D$4:$D$672,MATCH(SUBSTITUTE(SUBSTITUTE(SUBSTITUTE(A28,"~","~~"),"*","~*"),"?","~?"),Работы!$B$4:$B$672,0)),0) | G28: 4500 | H28: 1 | I28: 0.05 | J28: 0.1 | L28: оценка | N28: 2026-10-29 | O28: оценка нержавеющего ограждения, запросить КП В Петрович, Лемана ПРО и Сатурн открытой карточки нет, оставлен прежний источник. | P28: =IF(H28=1,G28/VAT_DIV,G28) | Q28: =P28*(1+I28)*(1+DELIV)*(1+GROWTH+MONEY) | R28: =IF(AND(K28<>"",Q28*(1+J28)>K28/VAT_DIV),K28/VAT_DIV,Q28*(1+J28)) | S28: =Q28*F28 | T28: =R28*F28 | U28: =IF(AND(K28<>"",Q28*(1+J28)>K28/VAT_DIV+0.01),"ДА","") | V28: =P28*F28
A29: 34. Поручни из нержавеющей стали ( с 2 ригелями, с двойным ) | B29: Поручни из нержавеющей стали ( с 2 ригелями, с двойным ) | C29: Металлопрокат и метизы | D29: м | E29: 1 | F29: =E29*IFERROR(INDEX(Работы!$D$4:$D$672,MATCH(SUBSTITUTE(SUBSTITUTE(SUBSTITUTE(A29,"~","~~"),"*","~*"),"?","~?"),Работы!$B$4:$B$672,0)),0) | G29: 4500 | H29: 1 | I29: 0.05 | J29: 0.1 | L29: оценка | N29: 2026-10-29 | O29: оценка нержавеющего ограждения, запросить КП В Петрович, Лемана ПРО и Сатурн открытой карточки нет, оставлен прежний источник. | P29: =IF(H29=1,G29/VAT_DIV,G29) | Q29: =P29*(1+I29)*(1+DELIV)*(1+GROWTH+MONEY) | R29: =IF(AND(K29<>"",Q29*(1+J29)>K29/VAT_DIV),K29/VAT_DIV,Q29*(1+J29)) | S29: =Q29*F29 | T29: =R29*F29 | U29: =IF(AND(K29<>"",Q29*(1+J29)>K29/VAT_DIV+0.01),"ДА","") | V29: =P29*F29
A30: 35. Керамогранит 300х300х8 мм типа "Эстима" (цвет белый )RW-01 (вкл. За основу клей, грунтовку, затирку швов) | B30: Керамогранит 300х300х8 мм типа "Эстима" (цвет белый )RW-01 (вкл. За основу клей, | C30: Плитка, керамогранит | D30: м2 | E30: 1 | F30: =E30*IFERROR(INDEX(Работы!$D$4:$D$672,MATCH(SUBSTITUTE(SUBSTITUTE(SUBSTITUTE(A30,"~","~~"),"*","~*"),"?","~?"),Работы!$B$4:$B$672,0)),0) | G30: 1038.28 | H30: 1 | I30: 0.1 | J30: 0.12 | L30: Лемана ПРО | M30: https://lemanapro.ru/product/keramogranit-grani-taganaya-seryy-600h600-mm-91358213/ | N30: 2026-10-29 | O30: Якорь 600х600: Лемана ПРО 923 руб/м2, Петрович Grasaro 1007 руб/м2. Взят минимум. Прежний коэффициент размера сохранён. Сатурн не использован: цена карточки не сходится с м2. | P30: =IF(H30=1,G30/VAT_DIV,G30) | Q30: =P30*(1+I30)*(1+DELIV)*(1+GROWTH+MONEY) | R30: =IF(AND(K30<>"",Q30*(1+J30)>K30/VAT_DIV),K30/VAT_DIV,Q30*(1+J30)) | S30: =Q30*F30 | T30: =R30*F30 | U30: =IF(AND(K30<>"",Q30*(1+J30)>K30/VAT_DIV+0.01),"ДА","") | V30: =P30*F30
A31: 35. Керамогранит 300х300х8 мм типа "Эстима" (цвет белый )RW-01 (вкл. За основу клей, грунтовку, затирку швов) | B31: Клей плиточный | C31: Сухие смеси, штукатурки, шпаклёвки | D31: кг | E31: 5.5 | F31: =E31*IFERROR(INDEX(Работы!$D$4:$D$672,MATCH(SUBSTITUTE(SUBSTITUTE(SUBSTITUTE(A31,"~","~~"),"*","~*"),"?","~?"),Работы!$B$4:$B$672,0)),0) | G31: 22.68 | H31: 1 | I31: 0.05 | J31: 0.12 | L31: Лемана ПРО | M31: https://lemanapro.ru/product/kley-plitochnyy-ceresit-cm-11-pro-25-kg-89340445/ | N31: 2026-10-29 | O31: Минимум из трёх: Лемана ПРО Ceresit CM 11 PRO 25 кг = 22,68 руб/кг. Петрович 24,76, Сатурн 27. | P31: =IF(H31=1,G31/VAT_DIV,G31) | Q31: =P31*(1+I31)*(1+DELIV)*(1+GROWTH+MONEY) | R31: =IF(AND(K31<>"",Q31*(1+J31)>K31/VAT_DIV),K31/VAT_DIV,Q31*(1+J31)) | S31: =Q31*F31 | T31: =R31*F31 | U31: =IF(AND(K31<>"",Q31*(1+J31)>K31/VAT_DIV+0.01),"ДА","") | V31: =P31*F31
A32: 35. Керамогранит 300х300х8 мм типа "Эстима" (цвет белый )RW-01 (вкл. За основу клей, грунтовку, затирку швов) | B32: Затирка | C32: Сухие смеси, штукатурки, шпаклёвки | D32: кг | E32: 0.4 | F32: =E32*IFERROR(INDEX(Работы!$D$4:$D$672,MATCH(SUBSTITUTE(SUBSTITUTE(SUBSTITUTE(A32,"~","~~"),"*","~*"),"?","~?"),Работы!$B$4:$B$672,0)),0) | G32: 155 | H32: 1 | I32: 0.05 | J32: 0.12 | L32: Петрович | M32: https://moscow.petrovich.ru/product/102834/ | N32: 2026-10-29 | O32: Петрович, Ceresit CE 33, 2 кг = 310 руб (155 руб/кг). Лемана ПРО 173, Сатурн 181,5 руб/кг. | P32: =IF(H32=1,G32/VAT_DIV,G32) | Q32: =P32*(1+I32)*(1+DELIV)*(1+GROWTH+MONEY) | R32: =IF(AND(K32<>"",Q32*(1+J32)>K32/VAT_DIV),K32/VAT_DIV,Q32*(1+J32)) | S32: =Q32*F32 | T32: =R32*F32 | U32: =IF(AND(K32<>"",Q32*(1+J32)>K32/VAT_DIV+0.01),"ДА","") | V32: =P32*F32
A33: 35. Керамогранит 300х300х8 мм типа "Эстима" (цвет белый )RW-01 (вкл. За основу клей, грунтовку, затирку швов) | B33: Грунт | C33: Краски, грунты, ЛКМ | D33: л | E33: 0.15 | F33: =E33*IFERROR(INDEX(Работы!$D$4:$D$672,MATCH(SUBSTITUTE(SUBSTITUTE(SUBSTITUTE(A33,"~","~~"),"*","~*"),"?","~?"),Работы!$B$4:$B$672,0)),0) | G33: 136.7 | H33: 1 | I33: 0.05 | J33: 0.12 | L33: Лемана ПРО | M33: https://lemanapro.ru/product/grunt-ceresit-ct-17-transparent-glubokogo-proniknoveniya-10-l-89398668/ | N33: 2026-10-29 | O33: Минимум из трёх: Лемана ПРО Ceresit CT 17, 10 л = 136,7 руб/л. Петрович CT 17 PRO 143,8, Сатурн 145,9. | P33: =IF(H33=1,G33/VAT_DIV,G33) | Q33: =P33*(1+I33)*(1+DELIV)*(1+GROWTH+MONEY) | R33: =IF(AND(K33<>"",Q33*(1+J33)>K33/VAT_DIV),K33/VAT_DIV,Q33*(1+J33)) | S33: =Q33*F33 | T33: =R33*F33 | U33: =IF(AND(K33<>"",Q33*(1+J33)>K33/VAT_DIV+0.01),"ДА","") | V33: =P33*F33
A34: 36. Керамогранит 400х400х9 мм типа "Эстима" (цвет белый))RW-01 (вкл. За основу клей, грунтовку, затирку швов) | B34: Керамогранит 400х400х9 мм типа "Эстима" (цвет белый))RW-01 (вкл. За основу клей, | C34: Плитка, керамогранит | D34: м2 | E34: 1 | F34: =E34*IFERROR(INDEX(Работы!$D$4:$D$672,MATCH(SUBSTITUTE(SUBSTITUTE(SUBSTITUTE(A34,"~","~~"),"*","~*"),"?","~?"),Работы!$B$4:$B$672,0)),0) | G34: 1153.65 | H34: 1 | I34: 0.1 | J34: 0.12 | L34: Лемана ПРО | M34: https://lemanapro.ru/product/keramogranit-grani-taganaya-seryy-600h600-mm-91358213/ | N34: 2026-10-29 | O34: Якорь 600х600: Лемана ПРО 923 руб/м2, Петрович Grasaro 1007 руб/м2. Взят минимум. Прежний коэффициент размера сохранён. Сатурн не использован: цена карточки не сходится с м2. | P34: =IF(H34=1,G34/VAT_DIV,G34) | Q34: =P34*(1+I34)*(1+DELIV)*(1+GROWTH+MONEY) | R34: =IF(AND(K34<>"",Q34*(1+J34)>K34/VAT_DIV),K34/VAT_DIV,Q34*(1+J34)) | S34: =Q34*F34 | T34: =R34*F34 | U34: =IF(AND(K34<>"",Q34*(1+J34)>K34/VAT_DIV+0.01),"ДА","") | V34: =P34*F34
A35: 36. Керамогранит 400х400х9 мм типа "Эстима" (цвет белый))RW-01 (вкл. За основу клей, грунтовку, затирку швов) | B35: Клей плиточный | C35: Сухие смеси, штукатурки, шпаклёвки | D35: кг | E35: 5.5 | F35: =E35*IFERROR(INDEX(Работы!$D$4:$D$672,MATCH(SUBSTITUTE(SUBSTITUTE(SUBSTITUTE(A35,"~","~~"),"*","~*"),"?","~?"),Работы!$B$4:$B$672,0)),0) | G35: 22.68 | H35: 1 | I35: 0.05 | J35: 0.12 | L35: Лемана ПРО | M35: https://lemanapro.ru/product/kley-plitochnyy-ceresit-cm-11-pro-25-kg-89340445/ | N35: 2026-10-29 | O35: Минимум из трёх: Лемана ПРО Ceresit CM 11 PRO 25 кг = 22,68 руб/кг. Петрович 24,76, Сатурн 27. | P35: =IF(H35=1,G35/VAT_DIV,G35) | Q35: =P35*(1+I35)*(1+DELIV)*(1+GROWTH+MONEY) | R35: =IF(AND(K35<>"",Q35*(1+J35)>K35/VAT_DIV),K35/VAT_DIV,Q35*(1+J35)) | S35: =Q35*F35 | T35: =R35*F35 | U35: =IF(AND(K35<>"",Q35*(1+J35)>K35/VAT_DIV+0.01),"ДА","") | V35: =P35*F35
A36: 36. Керамогранит 400х400х9 мм типа "Эстима" (цвет белый))RW-01 (вкл. За основу клей, грунтовку, затирку швов) | B36: Затирка | C36: Сухие смеси, штукатурки, шпаклёвки | D36: кг | E36: 0.4 | F36: =E36*IFERROR(INDEX(Работы!$D$4:$D$672,MATCH(SUBSTITUTE(SUBSTITUTE(SUBSTITUTE(A36,"~","~~"),"*","~*"),"?","~?"),Работы!$B$4:$B$672,0)),0) | G36: 155 | H36: 1 | I36: 0.05 | J36: 0.12 | L36: Петрович | M36: https://moscow.petrovich.ru/product/102834/ | N36: 2026-10-29 | O36: Петрович, Ceresit CE 33, 2 кг = 310 руб (155 руб/кг). Лемана ПРО 173, Сатурн 181,5 руб/кг. | P36: =IF(H36=1,G36/VAT_DIV,G36) | Q36: =P36*(1+I36)*(1+DELIV)*(1+GROWTH+MONEY) | R36: =IF(AND(K36<>"",Q36*(1+J36)>K36/VAT_DIV),K36/VAT_DIV,Q36*(1+J36)) | S36: =Q36*F36 | T36: =R36*F36 | U36: =IF(AND(K36<>"",Q36*(1+J36)>K36/VAT_DIV+0.01),"ДА","") | V36: =P36*F36
A37: 36. Керамогранит 400х400х9 мм типа "Эстима" (цвет белый))RW-01 (вкл. За основу клей, грунтовку, затирку швов) | B37: Грунт | C37: Краски, грунты, ЛКМ | D37: л | E37: 0.15 | F37: =E37*IFERROR(INDEX(Работы!$D$4:$D$672,MATCH(SUBSTITUTE(SUBSTITUTE(SUBSTITUTE(A37,"~","~~"),"*","~*"),"?","~?"),Работы!$B$4:$B$672,0)),0) | G37: 136.7 | H37: 1 | I37: 0.05 | J37: 0.12 | L37: Лемана ПРО | M37: https://lemanapro.ru/product/grunt-ceresit-ct-17-transparent-glubokogo-proniknoveniya-10-l-89398668/ | N37: 2026-10-29 | O37: Минимум из трёх: Лемана ПРО Ceresit CT 17, 10 л = 136,7 руб/л. Петрович CT 17 PRO 143,8, Сатурн 145,9. | P37: =IF(H37=1,G37/VAT_DIV,G37) | Q37: =P37*(1+I37)*(1+DELIV)*(1+GROWTH+MONEY) | R37: =IF(AND(K37<>"",Q37*(1+J37)>K37/VAT_DIV),K37/VAT_DIV,Q37*(1+J37)) | S37: =Q37*F37 | T37: =R37*F37 | U37: =IF(AND(K37<>"",Q37*(1+J37)>K37/VAT_DIV+0.01),"ДА","") | V37: =P37*F37
A38: 37. Керамогранит 600х600х10 мм типа "Эстима" (цвет белый))RW-01 (вкл. За основу клей, грунтовку, затирку швов) | B38: Керамогранит 600х600х10 мм типа "Эстима" (цвет белый))RW-01 (вкл. За основу клей | C38: Плитка, керамогранит | D38: м2 | E38: 1 | F38: =E38*IFERROR(INDEX(Работы!$D$4:$D$672,MATCH(SUBSTITUTE(SUBSTITUTE(SUBSTITUTE(A38,"~","~~"),"*","~*"),"?","~?"),Работы!$B$4:$B$672,0)),0) | G38: 1326.7 | H38: 1 | I38: 0.1 | J38: 0.12 | L38: Лемана ПРО | M38: https://lemanapro.ru/product/keramogranit-grani-taganaya-seryy-600h600-mm-91358213/ | N38: 2026-10-29 | O38: Якорь 600х600: Лемана ПРО 923 руб/м2, Петрович Grasaro 1007 руб/м2. Взят минимум. Прежний коэффициент размера сохранён. Сатурн не использован: цена карточки не сходится с м2. | P38: =IF(H38=1,G38/VAT_DIV,G38) | Q38: =P38*(1+I38)*(1+DELIV)*(1+GROWTH+MONEY) | R38: =IF(AND(K38<>"",Q38*(1+J38)>K38/VAT_DIV),K38/VAT_DIV,Q38*(1+J38)) | S38: =Q38*F38 | T38: =R38*F38 | U38: =IF(AND(K38<>"",Q38*(1+J38)>K38/VAT_DIV+0.01),"ДА","") | V38: =P38*F38
A39: 37. Керамогранит 600х600х10 мм типа "Эстима" (цвет белый))RW-01 (вкл. За основу клей, грунтовку, затирку швов) | B39: Клей плиточный | C39: Сухие смеси, штукатурки, шпаклёвки | D39: кг | E39: 5.5 | F39: =E39*IFERROR(INDEX(Работы!$D$4:$D$672,MATCH(SUBSTITUTE(SUBSTITUTE(SUBSTITUTE(A39,"~","~~"),"*","~*"),"?","~?"),Работы!$B$4:$B$672,0)),0) | G39: 22.68 | H39: 1 | I39: 0.05 | J39: 0.12 | L39: Лемана ПРО | M39: https://lemanapro.ru/product/kley-plitochnyy-ceresit-cm-11-pro-25-kg-89340445/ | N39: 2026-10-29 | O39: Минимум из трёх: Лемана ПРО Ceresit CM 11 PRO 25 кг = 22,68 руб/кг. Петрович 24,76, Сатурн 27. | P39: =IF(H39=1,G39/VAT_DIV,G39) | Q39: =P39*(1+I39)*(1+DELIV)*(1+GROWTH+MONEY) | R39: =IF(AND(K39<>"",Q39*(1+J39)>K39/VAT_DIV),K39/VAT_DIV,Q39*(1+J39)) | S39: =Q39*F39 | T39: =R39*F39 | U39: =IF(AND(K39<>"",Q39*(1+J39)>K39/VAT_DIV+0.01),"ДА","") | V39: =P39*F39
A40: 37. Керамогранит 600х600х10 мм типа "Эстима" (цвет белый))RW-01 (вкл. За основу клей, грунтовку, затирку швов) | B40: Затирка | C40: Сухие смеси, штукатурки, шпаклёвки | D40: кг | E40: 0.4 | F40: =E40*IFERROR(INDEX(Работы!$D$4:$D$672,MATCH(SUBSTITUTE(SUBSTITUTE(SUBSTITUTE(A40,"~","~~"),"*","~*"),"?","~?"),Работы!$B$4:$B$672,0)),0) | G40: 155 | H40: 1 | I40: 0.05 | J40: 0.12 | L40: Петрович | M40: https://moscow.petrovich.ru/product/102834/ | N40: 2026-10-29 | O40: Петрович, Ceresit CE 33, 2 кг = 310 руб (155 руб/кг). Лемана ПРО 173, Сатурн 181,5 руб/кг. | P40: =IF(H40=1,G40/VAT_DIV,G40) | Q40: =P40*(1+I40)*(1+DELIV)*(1+GROWTH+MONEY) | R40: =IF(AND(K40<>"",Q40*(1+J40)>K40/VAT_DIV),K40/VAT_DIV,Q40*(1+J40)) | S40: =Q40*F40 | T40: =R40*F40 | U40: =IF(AND(K40<>"",Q40*(1+J40)>K40/VAT_DIV+0.01),"ДА","") | V40: =P40*F40
A41: 37. Керамогранит 600х600х10 мм типа "Эстима" (цвет белый))RW-01 (вкл. За основу клей, грунтовку, затирку швов) | B41: Грунт | C41: Краски, грунты, ЛКМ | D41: л | E41: 0.15 | F41: =E41*IFERROR(INDEX(Работы!$D$4:$D$672,MATCH(SUBSTITUTE(SUBSTITUTE(SUBSTITUTE(A41,"~","~~"),"*","~*"),"?","~?"),Работы!$B$4:$B$672,0)),0) | G41: 136.7 | H41: 1 | I41: 0.05 | J41: 0.12 | L41: Лемана ПРО | M41: https://lemanapro.ru/product/grunt-ceresit-ct-17-transparent-glubokogo-proniknoveniya-10-l-89398668/ | N41: 2026-10-29 | O41: Минимум из трёх: Лемана ПРО Ceresit CT 17, 10 л = 136,7 руб/л. Петрович CT 17 PRO 143,8, Сатурн 145,9. | P41: =IF(H41=1,G41/VAT_DIV,G41) | Q41: =P41*(1+I41)*(1+DELIV)*(1+GROWTH+MONEY) | R41: =IF(AND(K41<>"",Q41*(1+J41)>K41/VAT_DIV),K41/VAT_DIV,Q41*(1+J41)) | S41: =Q41*F41 | T41: =R41*F41 | U41: =IF(AND(K41<>"",Q41*(1+J41)>K41/VAT_DIV+0.01),"ДА","") | V41: =P41*F41
... A71: 46. Линолеум коммерческий толщиной не менее 2 мм (типа "Tarket" серии "Optima") | B71: Линолеум коммерческий 2 мм | C71: Напольные покрытия (линолеум, ПВХ, ковролин) | D71: м2 | E71: 1.05 | F71: =E71*IFERROR(INDEX(Работы!$D$4:$D$672,MATCH(SUBSTITUTE(SUBSTITUTE(SUBSTITUTE(A71,"~","~~"),"*","~*"),"?","~?"),Работы!$B$4:$B$672,0)),0) | G71: 399.67 | H71: 1 | I71: 0.08 | J71: 0.15 | L71: Петрович | M71: https://moscow.petrovich.ru/product/1229558/ | N71: 2026-10-29 | O71: Петрович, Tarkett Acczent Mineral, коммерческий, 399,67 руб/м2. Сатурн Polystyl 319 — другой класс. | P71: =IF(H71=1,G71/VAT_DIV,G71) | Q71: =P71*(1+I71)*(1+DELIV)*(1+GROWTH+MONEY) | R71: =IF(AND(K71<>"",Q71*(1+J71)>K71/VAT_DIV),K71/VAT_DIV,Q71*(1+J71)) | S71: =Q71*F71 | T71: =R71*F71 | U71: =IF(AND(K71<>"",Q71*(1+J71)>K71/VAT_DIV+0.01),"ДА","") | V71: =P71*F71
A72: 46. Линолеум коммерческий толщиной не менее 2 мм (типа "Tarket" серии "Optima") | B72: Клей | C72: Напольные покрытия (линолеум, ПВХ, ковролин) | D72: кг | E72: 0.3 | F72: =E72*IFERROR(INDEX(Работы!$D$4:$D$672,MATCH(SUBSTITUTE(SUBSTITUTE(SUBSTITUTE(A72,"~","~~"),"*","~*"),"?","~?"),Работы!$B$4:$B$672,0)),0) | G72: 180 | H72: 1 | I72: 0.08 | J72: 0.15 | L72: оценка | N72: 2026-10-29 | O72: оценка В Петрович, Лемана ПРО и Сатурн открытой карточки нет, оставлен прежний источник. | P72: =IF(H72=1,G72/VAT_DIV,G72) | Q72: =P72*(1+I72)*(1+DELIV)*(1+GROWTH+MONEY) | R72: =IF(AND(K72<>"",Q72*(1+J72)>K72/VAT_DIV),K72/VAT_DIV,Q72*(1+J72)) | S72: =Q72*F72 | T72: =R72*F72 | U72: =IF(AND(K72<>"",Q72*(1+J72)>K72/VAT_DIV+0.01),"ДА","") | V72: =P72*F72
A73: 47. Текстура: гладкая типа Апельсиновая корка. Цвет: RAL 7040 | B73: Краска для пола по бетону | C73: Краски, грунты, ЛКМ | D73: кг | E73: 0.35 | F73: =E73*IFERROR(INDEX(Работы!$D$4:$D$672,MATCH(SUBSTITUTE(SUBSTITUTE(SUBSTITUTE(A73,"~","~~"),"*","~*"),"?","~?"),Работы!$B$4:$B$672,0)),0) | G73: 220 | H73: 1 | I73: 0.05 | J73: 0.12 | L73: оценка | N73: 2026-10-29 | O73: оценка В Петрович, Лемана ПРО и Сатурн открытой карточки нет, оставлен прежний источник. | P73: =IF(H73=1,G73/VAT_DIV,G73) | Q73: =P73*(1+I73)*(1+DELIV)*(1+GROWTH+MONEY) | R73: =IF(AND(K73<>"",Q73*(1+J73)>K73/VAT_DIV),K73/VAT_DIV,Q73*(1+J73)) | S73: =Q73*F73 | T73: =R73*F73 | U73: =IF(AND(K73<>"",Q73*(1+J73)>K73/VAT_DIV+0.01),"ДА","") | V73: =P73*F73
A74: 48. Противоскользящие полосы | B74: Лента противоскользящая | C74: Напольные покрытия (линолеум, ПВХ, ковролин) | D74: м | E74: 1 | F74: =E74*IFERROR(INDEX(Работы!$D$4:$D$672,MATCH(SUBSTITUTE(SUBSTITUTE(SUBSTITUTE(A74,"~","~~"),"*","~*"),"?","~?"),Работы!$B$4:$B$672,0)),0) | G74: 120 | H74: 1 | I74: 0.08 | J74: 0.15 | L74: оценка | N74: 2026-10-29 | O74: оценка В Петрович, Лемана ПРО и Сатурн открытой карточки нет, оставлен прежний источник. | P74: =IF(H74=1,G74/VAT_DIV,G74) | Q74: =P74*(1+I74)*(1+DELIV)*(1+GROWTH+MONEY) | R74: =IF(AND(K74<>"",Q74*(1+J74)>K74/VAT_DIV),K74/VAT_DIV,Q74*(1+J74)) | S74: =Q74*F74 | T74: =R74*F74 | U74: =IF(AND(K74<>"",Q74*(1+J74)>K74/VAT_DIV+0.01),"ДА","") | V74: =P74*F74
A75: 50. Профильный материал для панели ЛГКЛ, направляющие, алюмин. профили ОМЕГА (вкл. крепежные элементы) | B75: Профиль ПН/ПС и крепёж на м2 каркаса | C75: ГКЛ, профиль, комплектующие | D75: м2 | E75: 1 | F75: =E75*IFERROR(INDEX(Работы!$D$4:$D$672,MATCH(SUBSTITUTE(SUBSTITUTE(SUBSTITUTE(A75,"~","~~"),"*","~*"),"?","~?"),Работы!$B$4:$B$672,0)),0) | G75: 180 | H75: 1 | I75: 0.07 | J75: 0.12 | L75: оценка | N75: 2026-10-29 | O75: оценка каркаса под панель В Петрович, Лемана ПРО и Сатурн открытой карточки нет, оставлен прежний источник. | P75: =IF(H75=1,G75/VAT_DIV,G75) | Q75: =P75*(1+I75)*(1+DELIV)*(1+GROWTH+MONEY) | R75: =IF(AND(K75<>"",Q75*(1+J75)>K75/VAT_DIV),K75/VAT_DIV,Q75*(1+J75)) | S75: =Q75*F75 | T75: =R75*F75 | U75: =IF(AND(K75<>"",Q75*(1+J75)>K75/VAT_DIV+0.01),"ДА","") | V75: =P75*F75
A76: 51. Панель ЛГКЛ (цвет RAL 6019, фактура «шагрень» или аналог) типа GYPROC (толщина 12,5 мм) | B76: Панель ЛГКЛ (цвет RAL 6019, фактура «шагрень» или аналог) типа GYPROC (толщина 1 | C76: ГКЛ, профиль, комплектующие | D76: м2 | E76: 1.05 | F76: =E76*IFERROR(INDEX(Работы!$D$4:$D$672,MATCH(SUBSTITUTE(SUBSTITUTE(SUBSTITUTE(A76,"~","~~"),"*","~*"),"?","~?"),Работы!$B$4:$B$672,0)),0) | G76: 900 | H76: 1 | I76: 0.07 | J76: 0.12 | L76: оценка | N76: 2026-10-29 | O76: оценка ламинированной панели, запросить КП В Петрович, Лемана ПРО и Сатурн открытой карточки нет, оставлен прежний источник. | P76: =IF(H76=1,G76/VAT_DIV,G76) | Q76: =P76*(1+I76)*(1+DELIV)*(1+GROWTH+MONEY) | R76: =IF(AND(K76<>"",Q76*(1+J76)>K76/VAT_DIV),K76/VAT_DIV,Q76*(1+J76)) | S76: =Q76*F76 | T76: =R76*F76 | U76: =IF(AND(K76<>"",Q76*(1+J76)>K76/VAT_DIV+0.01),"ДА","") | V76: =P76*F76
A77: 52. Кафельная настенная плитка Kerama Marazzi 200x200 ( цвет-белый) (вкл. За основу клей, грунтовку, затирку швов) | B77: Кафельная настенная плитка Kerama Marazzi 200x200 ( цвет-белый) (вкл. За основу | C77: Плитка, керамогранит | D77: м2 | E77: 1 | F77: =E77*IFERROR(INDEX(Работы!$D$4:$D$672,MATCH(SUBSTITUTE(SUBSTITUTE(SUBSTITUTE(A77,"~","~~"),"*","~*"),"?","~?"),Работы!$B$4:$B$672,0)),0) | G77: 1038.28 | H77: 1 | I77: 0.1 | J77: 0.12 | L77: Лемана ПРО | M77: https://lemanapro.ru/product/keramogranit-grani-taganaya-seryy-600h600-mm-91358213/ | N77: 2026-10-29 | O77: Якорь 600х600: Лемана ПРО 923 руб/м2, Петрович Grasaro 1007 руб/м2. Взят минимум. Прежний коэффициент размера сохранён. Сатурн не использован: цена карточки не сходится с м2. | P77: =IF(H77=1,G77/VAT_DIV,G77) | Q77: =P77*(1+I77)*(1+DELIV)*(1+GROWTH+MONEY) | R77: =IF(AND(K77<>"",Q77*(1+J77)>K77/VAT_DIV),K77/VAT_DIV,Q77*(1+J77)) | S77: =Q77*F77 | T77: =R77*F77 | U77: =IF(AND(K77<>"",Q77*(1+J77)>K77/VAT_DIV+0.01),"ДА","") | V77: =P77*F77
A78: 52. Кафельная настенная плитка Kerama Marazzi 200x200 ( цвет-белый) (вкл. За основу клей, грунтовку, затирку швов) | B78: Клей плиточный | C78: Сухие смеси, штукатурки, шпаклёвки | D78: кг | E78: 5.5 | F78: =E78*IFERROR(INDEX(Работы!$D$4:$D$672,MATCH(SUBSTITUTE(SUBSTITUTE(SUBSTITUTE(A78,"~","~~"),"*","~*"),"?","~?"),Работы!$B$4:$B$672,0)),0) | G78: 22.68 | H78: 1 | I78: 0.05 | J78: 0.12 | L78: Лемана ПРО | M78: https://lemanapro.ru/product/kley-plitochnyy-ceresit-cm-11-pro-25-kg-89340445/ | N78: 2026-10-29 | O78: Минимум из трёх: Лемана ПРО Ceresit CM 11 PRO 25 кг = 22,68 руб/кг. Петрович 24,76, Сатурн 27. | P78: =IF(H78=1,G78/VAT_DIV,G78) | Q78: =P78*(1+I78)*(1+DELIV)*(1+GROWTH+MONEY) | R78: =IF(AND(K78<>"",Q78*(1+J78)>K78/VAT_DIV),K78/VAT_DIV,Q78*(1+J78)) | S78: =Q78*F78 | T78: =R78*F78 | U78: =IF(AND(K78<>"",Q78*(1+J78)>K78/VAT_DIV+0.01),"ДА","") | V78: =P78*F78
A79: 52. Кафельная настенная плитка Kerama Marazzi 200x200 ( цвет-белый) (вкл. За основу клей, грунтовку, затирку швов) | B79: Затирка | C79: Сухие смеси, штукатурки, шпаклёвки | D79: кг | E79: 0.4 | F79: =E79*IFERROR(INDEX(Работы!$D$4:$D$672,MATCH(SUBSTITUTE(SUBSTITUTE(SUBSTITUTE(A79,"~","~~"),"*","~*"),"?","~?"),Работы!$B$4:$B$672,0)),0) | G79: 155 | H79: 1 | I79: 0.05 | J79: 0.12 | L79: Петрович | M79: https://moscow.petrovich.ru/product/102834/ | N79: 2026-10-29 | O79: Петрович, Ceresit CE 33, 2 кг = 310 руб (155 руб/кг). Лемана ПРО 173, Сатурн 181,5 руб/кг. | P79: =IF(H79=1,G79/VAT_DIV,G79) | Q79: =P79*(1+I79)*(1+DELIV)*(1+GROWTH+MONEY) | R79: =IF(AND(K79<>"",Q79*(1+J79)>K79/VAT_DIV),K79/VAT_DIV,Q79*(1+J79)) | S79: =Q79*F79 | T79: =R79*F79 | U79: =IF(AND(K79<>"",Q79*(1+J79)>K79/VAT_DIV+0.01),"ДА","") | V79: =P79*F79
A80: 52. Кафельная настенная плитка Kerama Marazzi 200x200 ( цвет-белый) (вкл. За основу клей, грунтовку, затирку швов) | B80: Грунт | C80: Краски, грунты, ЛКМ | D80: л | E80: 0.15 | F80: =E80*IFERROR(INDEX(Работы!$D$4:$D$672,MATCH(SUBSTITUTE(SUBSTITUTE(SUBSTITUTE(A80,"~","~~"),"*","~*"),"?","~?"),Работы!$B$4:$B$672,0)),0) | G80: 136.7 | H80: 1 | I80: 0.05 | J80: 0.12 | L80: Лемана ПРО | M80: https://lemanapro.ru/product/grunt-ceresit-ct-17-transparent-glubokogo-proniknoveniya-10-l-89398668/ | N80: 2026-10-29 | O80: Минимум из трёх: Лемана ПРО Ceresit CT 17, 10 л = 136,7 руб/л. Петрович CT 17 PRO 143,8, Сатурн 145,9. | P80: =IF(H80=1,G80/VAT_DIV,G80) | Q80: =P80*(1+I80)*(1+DELIV)*(1+GROWTH+MONEY) | R80: =IF(AND(K80<>"",Q80*(1+J80)>K80/VAT_DIV),K80/VAT_DIV,Q80*(1+J80)) | S80: =Q80*F80 | T80: =R80*F80 | U80: =IF(AND(K80<>"",Q80*(1+J80)>K80/VAT_DIV+0.01),"ДА","") | V80: =P80*F80
A81: 53. Кафельная настенная плитка Kerama Marazzi 200x300 ( цвет-белый) (вкл. За основу клей, грунтовку, затирку швов) | B81: Кафельная настенная плитка Kerama Marazzi 200x300 ( цвет-белый) (вкл. За основу | C81: Плитка, керамогранит | D81: м2 | E81: 1 | F81: =E81*IFERROR(INDEX(Работы!$D$4:$D$672,MATCH(SUBSTITUTE(SUBSTITUTE(SUBSTITUTE(A81,"~","~~"),"*","~*"),"?","~?"),Работы!$B$4:$B$672,0)),0) | G81: 1038.28 | H81: 1 | I81: 0.1 | J81: 0.12 | L81: Лемана ПРО | M81: https://lemanapro.ru/product/keramogranit-grani-taganaya-seryy-600h600-mm-91358213/ | N81: 2026-10-29 | O81: Якорь 600х600: Лемана ПРО 923 руб/м2, Петрович Grasaro 1007 руб/м2. Взят минимум. Прежний коэффициент размера сохранён. Сатурн не использован: цена карточки не сходится с м2. | P81: =IF(H81=1,G81/VAT_DIV,G81) | Q81: =P81*(1+I81)*(1+DELIV)*(1+GROWTH+MONEY) | R81: =IF(AND(K81<>"",Q81*(1+J81)>K81/VAT_DIV),K81/VAT_DIV,Q81*(1+J81)) | S81: =Q81*F81 | T81: =R81*F81 | U81: =IF(AND(K81<>"",Q81*(1+J81)>K81/VAT_DIV+0.01),"ДА","") | V81: =P81*F81
A82: 53. Кафельная настенная плитка Kerama Marazzi 200x300 ( цвет-белый) (вкл. За основу клей, грунтовку, затирку швов) | B82: Клей плиточный | C82: Сухие смеси, штукатурки, шпаклёвки | D82: кг | E82: 5.5 | F82: =E82*IFERROR(INDEX(Работы!$D$4:$D$672,MATCH(SUBSTITUTE(SUBSTITUTE(SUBSTITUTE(A82,"~","~~"),"*","~*"),"?","~?"),Работы!$B$4:$B$672,0)),0) | G82: 22.68 | H82: 1 | I82: 0.05 | J82: 0.12 | L82: Лемана ПРО | M82: https://lemanapro.ru/product/kley-plitochnyy-ceresit-cm-11-pro-25-kg-89340445/ | N82: 2026-10-29 | O82: Минимум из трёх: Лемана ПРО Ceresit CM 11 PRO 25 кг = 22,68 руб/кг. Петрович 24,76, Сатурн 27. | P82: =IF(H82=1,G82/VAT_DIV,G82) | Q82: =P82*(1+I82)*(1+DELIV)*(1+GROWTH+MONEY) | R82: =IF(AND(K82<>"",Q82*(1+J82)>K82/VAT_DIV),K82/VAT_DIV,Q82*(1+J82)) | S82: =Q82*F82 | T82: =R82*F82 | U82: =IF(AND(K82<>"",Q82*(1+J82)>K82/VAT_DIV+0.01),"ДА","") | V82: =P82*F82
A83: 53. Кафельная настенная плитка Kerama Marazzi 200x300 ( цвет-белый) (вкл. За основу клей, грунтовку, затирку швов) | B83: Затирка | C83: Сухие смеси, штукатурки, шпаклёвки | D83: кг | E83: 0.4 | F83: =E83*IFERROR(INDEX(Работы!$D$4:$D$672,MATCH(SUBSTITUTE(SUBSTITUTE(SUBSTITUTE(A83,"~","~~"),"*","~*"),"?","~?"),Работы!$B$4:$B$672,0)),0) | G83: 155 | H83: 1 | I83: 0.05 | J83: 0.12 | L83: Петрович | M83: https://moscow.petrovich.ru/product/102834/ | N83: 2026-10-29 | O83: Петрович, Ceresit CE 33, 2 кг = 310 руб (155 руб/кг). Лемана ПРО 173, Сатурн 181,5 руб/кг. | P83: =IF(H83=1,G83/VAT_DIV,G83) | Q83: =P83*(1+I83)*(1+DELIV)*(1+GROWTH+MONEY) | R83: =IF(AND(K83<>"",Q83*(1+J83)>K83/VAT_DIV),K83/VAT_DIV,Q83*(1+J83)) | S83: =Q83*F83 | T83: =R83*F83 | U83: =IF(AND(K83<>"",Q83*(1+J83)>K83/VAT_DIV+0.01),"ДА","") | V83: =P83*F83
A84: 53. Кафельная настенная плитка Kerama Marazzi 200x300 ( цвет-белый) (вкл. За основу клей, грунтовку, затирку швов) | B84: Грунт | C84: Краски, грунты, ЛКМ | D84: л | E84: 0.15 | F84: =E84*IFERROR(INDEX(Работы!$D$4:$D$672,MATCH(SUBSTITUTE(SUBSTITUTE(SUBSTITUTE(A84,"~","~~"),"*","~*"),"?","~?"),Работы!$B$4:$B$672,0)),0) | G84: 136.7 | H84: 1 | I84: 0.05 | J84: 0.12 | L84: Лемана ПРО | M84: https://lemanapro.ru/product/grunt-ceresit-ct-17-transparent-glubokogo-proniknoveniya-10-l-89398668/ | N84: 2026-10-29 | O84: Минимум из трёх: Лемана ПРО Ceresit CT 17, 10 л = 136,7 руб/л. Петрович CT 17 PRO 143,8, Сатурн 145,9. | P84: =IF(H84=1,G84/VAT_DIV,G84) | Q84: =P84*(1+I84)*(1+DELIV)*(1+GROWTH+MONEY) | R84: =IF(AND(K84<>"",Q84*(1+J84)>K84/VAT_DIV),K84/VAT_DIV,Q84*(1+J84)) | S84: =Q84*F84 | T84: =R84*F84 | U84: =IF(AND(K84<>"",Q84*(1+J84)>K84/VAT_DIV+0.01),"ДА","") | V84: =P84*F84
A85: 54. Кафельная настенная плитка Kerama Marazzi 200x200 (оранжевый) (вкл. За основу клей, грунтовку, затирку швов) | B85: Кафельная настенная плитка Kerama Marazzi 200x200 (оранжевый) (вкл. За основу кл | C85: Плитка, керамогранит | D85: м2 | E85: 1 | F85: =E85*IFERROR(INDEX(Работы!$D$4:$D$672,MATCH(SUBSTITUTE(SUBSTITUTE(SUBSTITUTE(A85,"~","~~"),"*","~*"),"?","~?"),Работы!$B$4:$B$672,0)),0) | G85: 830.63 | H85: 1 | I85: 0.1 | J85: 0.12 | L85: Лемана ПРО | M85: https://lemanapro.ru/product/keramogranit-grani-taganaya-seryy-600h600-mm-91358213/ | N85: 2026-10-29 | O85: Якорь 600х600: Лемана ПРО 923 руб/м2, Петрович Grasaro 1007 руб/м2. Взят минимум. Прежний коэффициент размера сохранён. Сатурн не использован: цена карточки не сходится с м2. | P85: =IF(H85=1,G85/VAT_DIV,G85) | Q85: =P85*(1+I85)*(1+DELIV)*(1+GROWTH+MONEY) | R85: =IF(AND(K85<>"",Q85*(1+J85)>K85/VAT_DIV),K85/VAT_DIV,Q85*(1+J85)) | S85: =Q85*F85 | T85: =R85*F85 | U85: =IF(AND(K85<>"",Q85*(1+J85)>K85/VAT_DIV+0.01),"ДА","") | V85: =P85*F85
A86: 54. Кафельная настенная плитка Kerama Marazzi 200x200 (оранжевый) (вкл. За основу клей, грунтовку, затирку швов) | B86: Клей плиточный | C86: Сухие смеси, штукатурки, шпаклёвки | D86: кг | E86: 5.5 | F86: =E86*IFERROR(INDEX(Работы!$D$4:$D$672,MATCH(SUBSTITUTE(SUBSTITUTE(SUBSTITUTE(A86,"~","~~"),"*","~*"),"?","~?"),Работы!$B$4:$B$672,0)),0) | G86: 22.68 | H86: 1 | I86: 0.05 | J86: 0.12 | L86: Лемана ПРО | M86: https://lemanapro.ru/product/kley-plitochnyy-ceresit-cm-11-pro-25-kg-89340445/ | N86: 2026-10-29 | O86: Минимум из трёх: Лемана ПРО Ceresit CM 11 PRO 25 кг = 22,68 руб/кг. Петрович 24,76, Сатурн 27. | P86: =IF(H86=1,G86/VAT_DIV,G86) | Q86: =P86*(1+I86)*(1+DELIV)*(1+GROWTH+MONEY) | R86: =IF(AND(K86<>"",Q86*(1+J86)>K86/VAT_DIV),K86/VAT_DIV,Q86*(1+J86)) | S86: =Q86*F86 | T86: =R86*F86 | U86: =IF(AND(K86<>"",Q86*(1+J86)>K86/VAT_DIV+0.01),"ДА","") | V86: =P86*F86
A87: 54. Кафельная настенная плитка Kerama Marazzi 200x200 (оранжевый) (вкл. За основу клей, грунтовку, затирку швов) | B87: Затирка | C87: Сухие смеси, штукатурки, шпаклёвки | D87: кг | E87: 0.4 | F87: =E87*IFERROR(INDEX(Работы!$D$4:$D$672,MATCH(SUBSTITUTE(SUBSTITUTE(SUBSTITUTE(A87,"~","~~"),"*","~*"),"?","~?"),Работы!$B$4:$B$672,0)),0) | G87: 155 | H87: 1 | I87: 0.05 | J87: 0.12 | L87: Петрович | M87: https://moscow.petrovich.ru/product/102834/ | N87: 2026-10-29 | O87: Петрович, Ceresit CE 33, 2 кг = 310 руб (155 руб/кг). Лемана ПРО 173, Сатурн 181,5 руб/кг. | P87: =IF(H87=1,G87/VAT_DIV,G87) | Q87: =P87*(1+I87)*(1+DELIV)*(1+GROWTH+MONEY) | R87: =IF(AND(K87<>"",Q87*(1+J87)>K87/VAT_DIV),K87/VAT_DIV,Q87*(1+J87)) | S87: =Q87*F87 | T87: =R87*F87 | U87: =IF(AND(K87<>"",Q87*(1+J87)>K87/VAT_DIV+0.01),"ДА","") | V87: =P87*F87
A88: 54. Кафельная настенная плитка Kerama Marazzi 200x200 (оранжевый) (вкл. За основу клей, грунтовку, затирку швов) | B88: Грунт | C88: Краски, грунты, ЛКМ | D88: л | E88: 0.15 | F88: =E88*IFERROR(INDEX(Работы!$D$4:$D$672,MATCH(SUBSTITUTE(SUBSTITUTE(SUBSTITUTE(A88,"~","~~"),"*","~*"),"?","~?"),Работы!$B$4:$B$672,0)),0) | G88: 136.7 | H88: 1 | I88: 0.05 | J88: 0.12 | L88: Лемана ПРО | M88: https://lemanapro.ru/product/grunt-ceresit-ct-17-transparent-glubokogo-proniknoveniya-10-l-89398668/ | N88: 2026-10-29 | O88: Минимум из трёх: Лемана ПРО Ceresit CT 17, 10 л = 136,7 руб/л. Петрович CT 17 PRO 143,8, Сатурн 145,9. | P88: =IF(H88=1,G88/VAT_DIV,G88) | Q88: =P88*(1+I88)*(1+DELIV)*(1+GROWTH+MONEY) | R88: =IF(AND(K88<>"",Q88*(1+J88)>K88/VAT_DIV),K88/VAT_DIV,Q88*(1+J88)) | S88: =Q88*F88 | T88: =R88*F88 | U88: =IF(AND(K88<>"",Q88*(1+J88)>K88/VAT_DIV+0.01),"ДА","") | V88: =P88*F88
... A92: 55. Кафельная настенная плитка 200x200 (цвет серый, RAL ) (вкл. За основу клей, грунтовку, затирку швов белого цвета) | B92: Грунт | C92: Краски, грунты, ЛКМ | D92: л | E92: 0.15 | F92: =E92*IFERROR(INDEX(Работы!$D$4:$D$672,MATCH(SUBSTITUTE(SUBSTITUTE(SUBSTITUTE(A92,"~","~~"),"*","~*"),"?","~?"),Работы!$B$4:$B$672,0)),0) | G92: 136.7 | H92: 1 | I92: 0.05 | J92: 0.12 | L92: Лемана ПРО | M92: https://lemanapro.ru/product/grunt-ceresit-ct-17-transparent-glubokogo-proniknoveniya-10-l-89398668/ | N92: 2026-10-29 | O92: Минимум из трёх: Лемана ПРО Ceresit CT 17, 10 л = 136,7 руб/л. Петрович CT 17 PRO 143,8, Сатурн 145,9. | P92: =IF(H92=1,G92/VAT_DIV,G92) | Q92: =P92*(1+I92)*(1+DELIV)*(1+GROWTH+MONEY) | R92: =IF(AND(K92<>"",Q92*(1+J92)>K92/VAT_DIV),K92/VAT_DIV,Q92*(1+J92)) | S92: =Q92*F92 | T92: =R92*F92 | U92: =IF(AND(K92<>"",Q92*(1+J92)>K92/VAT_DIV+0.01),"ДА","") | V92: =P92*F92
A93: 56. Сэндвич панель толщина 120 мм (ППУ) или аналог | B93: Сэндвич панель толщина 120 мм (ППУ) или аналог | C93: Кровельные материалы и утеплитель | D93: м2 | E93: 1.05 | F93: =E93*IFERROR(INDEX(Работы!$D$4:$D$672,MATCH(SUBSTITUTE(SUBSTITUTE(SUBSTITUTE(A93,"~","~~"),"*","~*"),"?","~?"),Работы!$B$4:$B$672,0)),0) | G93: 3720 | H93: 1 | I93: 0.1 | J93: 0.12 | L93: оценка | N93: 2026-10-29 | O93: оценка сэндвич-панели, запросить КП В Петрович, Лемана ПРО и Сатурн открытой карточки нет, оставлен прежний источник. | P93: =IF(H93=1,G93/VAT_DIV,G93) | Q93: =P93*(1+I93)*(1+DELIV)*(1+GROWTH+MONEY) | R93: =IF(AND(K93<>"",Q93*(1+J93)>K93/VAT_DIV),K93/VAT_DIV,Q93*(1+J93)) | S93: =Q93*F93 | T93: =R93*F93 | U93: =IF(AND(K93<>"",Q93*(1+J93)>K93/VAT_DIV+0.01),"ДА","") | V93: =P93*F93
A94: 57. Сендвич-панель стеновая ППУ (ПИР) 100мм или аналог | B94: Сендвич-панель стеновая ППУ (ПИР) 100мм или аналог | C94: Кровельные материалы и утеплитель | D94: м2 | E94: 1.05 | F94: =E94*IFERROR(INDEX(Работы!$D$4:$D$672,MATCH(SUBSTITUTE(SUBSTITUTE(SUBSTITUTE(A94,"~","~~"),"*","~*"),"?","~?"),Работы!$B$4:$B$672,0)),0) | G94: 3360 | H94: 1 | I94: 0.1 | J94: 0.12 | L94: оценка | N94: 2026-10-29 | O94: оценка сэндвич-панели, запросить КП В Петрович, Лемана ПРО и Сатурн открытой карточки нет, оставлен прежний источник. | P94: =IF(H94=1,G94/VAT_DIV,G94) | Q94: =P94*(1+I94)*(1+DELIV)*(1+GROWTH+MONEY) | R94: =IF(AND(K94<>"",Q94*(1+J94)>K94/VAT_DIV),K94/VAT_DIV,Q94*(1+J94)) | S94: =Q94*F94 | T94: =R94*F94 | U94: =IF(AND(K94<>"",Q94*(1+J94)>K94/VAT_DIV+0.01),"ДА","") | V94: =P94*F94
A95: 58. Сэндвич панели стеновые | толщина 80 мм | базальтовые, трехслойные металлические, негорючие (огнестойкость по ei - 45)/ или аналог | B95: Сэндвич панели стеновые | толщина 80 мм | базальтовые, трехслойные металлические | C95: Кровельные материалы и утеплитель | D95: м2 | E95: 1.05 | F95: =E95*IFERROR(INDEX(Работы!$D$4:$D$672,MATCH(SUBSTITUTE(SUBSTITUTE(SUBSTITUTE(A95,"~","~~"),"*","~*"),"?","~?"),Работы!$B$4:$B$672,0)),0) | G95: 2600 | H95: 1 | I95: 0.1 | J95: 0.12 | L95: оценка | N95: 2026-10-29 | O95: оценка сэндвич-панели, запросить КП В Петрович, Лемана ПРО и Сатурн открытой карточки нет, оставлен прежний источник. | P95: =IF(H95=1,G95/VAT_DIV,G95) | Q95: =P95*(1+I95)*(1+DELIV)*(1+GROWTH+MONEY) | R95: =IF(AND(K95<>"",Q95*(1+J95)>K95/VAT_DIV),K95/VAT_DIV,Q95*(1+J95)) | S95: =Q95*F95 | T95: =R95*F95 | U95: =IF(AND(K95<>"",Q95*(1+J95)>K95/VAT_DIV+0.01),"ДА","") | V95: =P95*F95
A96: 59. Профильный материал для гипсокартона, направляющие (вкл. крепежные элементы) | B96: Профиль ПН/ПС и крепёж на м2 каркаса | C96: ГКЛ, профиль, комплектующие | D96: м2 | E96: 1 | F96: =E96*IFERROR(INDEX(Работы!$D$4:$D$672,MATCH(SUBSTITUTE(SUBSTITUTE(SUBSTITUTE(A96,"~","~~"),"*","~*"),"?","~?"),Работы!$B$4:$B$672,0)),0) | G96: 180 | H96: 1 | I96: 0.07 | J96: 0.12 | L96: оценка | N96: 2026-10-29 | O96: оценка каркаса под панель В Петрович, Лемана ПРО и Сатурн открытой карточки нет, оставлен прежний источник. | P96: =IF(H96=1,G96/VAT_DIV,G96) | Q96: =P96*(1+I96)*(1+DELIV)*(1+GROWTH+MONEY) | R96: =IF(AND(K96<>"",Q96*(1+J96)>K96/VAT_DIV),K96/VAT_DIV,Q96*(1+J96)) | S96: =Q96*F96 | T96: =R96*F96 | U96: =IF(AND(K96<>"",Q96*(1+J96)>K96/VAT_DIV+0.01),"ДА","") | V96: =P96*F96
A97: 60. Гипсокартон ГКЛВ (влагостойкий гипсокартон) типа Knauf (толщина 10мм) | B97: Гипсокартон ГКЛВ (влагостойкий гипсокартон) типа Knauf (толщина 10мм) | C97: ГКЛ, профиль, комплектующие | D97: м2 | E97: 1.05 | F97: =E97*IFERROR(INDEX(Работы!$D$4:$D$672,MATCH(SUBSTITUTE(SUBSTITUTE(SUBSTITUTE(A97,"~","~~"),"*","~*"),"?","~?"),Работы!$B$4:$B$672,0)),0) | G97: 194 | H97: 1 | I97: 0.07 | J97: 0.12 | L97: Петрович | M97: https://moscow.petrovich.ru/product/101932/ | N97: 2026-10-29 | O97: Петрович, Knauf ГКЛВ 12,5 мм 2500х1200 = 582 руб/лист. В форме 10 мм — аналог 12,5. | P97: =IF(H97=1,G97/VAT_DIV,G97) | Q97: =P97*(1+I97)*(1+DELIV)*(1+GROWTH+MONEY) | R97: =IF(AND(K97<>"",Q97*(1+J97)>K97/VAT_DIV),K97/VAT_DIV,Q97*(1+J97)) | S97: =Q97*F97 | T97: =R97*F97 | U97: =IF(AND(K97<>"",Q97*(1+J97)>K97/VAT_DIV+0.01),"ДА","") | V97: =P97*F97
A98: 61. Гипсокартон ГКЛ (обычный гипсокартон) типа Knauf (толщина 10мм) | B98: Гипсокартон ГКЛ (обычный гипсокартон) типа Knauf (толщина 10мм) | C98: ГКЛ, профиль, комплектующие | D98: м2 | E98: 1.05 | F98: =E98*IFERROR(INDEX(Работы!$D$4:$D$672,MATCH(SUBSTITUTE(SUBSTITUTE(SUBSTITUTE(A98,"~","~~"),"*","~*"),"?","~?"),Работы!$B$4:$B$672,0)),0) | G98: 146.67 | H98: 1 | I98: 0.07 | J98: 0.12 | L98: Петрович | M98: https://moscow.petrovich.ru/product/101931/ | N98: 2026-10-29 | O98: Петрович, Knauf ГКЛ 12,5 мм 2500х1200 = 440 руб/лист. В форме 10 мм — аналог 12,5. Лемана ПРО 390 руб/лист. | P98: =IF(H98=1,G98/VAT_DIV,G98) | Q98: =P98*(1+I98)*(1+DELIV)*(1+GROWTH+MONEY) | R98: =IF(AND(K98<>"",Q98*(1+J98)>K98/VAT_DIV),K98/VAT_DIV,Q98*(1+J98)) | S98: =Q98*F98 | T98: =R98*F98 | U98: =IF(AND(K98<>"",Q98*(1+J98)>K98/VAT_DIV+0.01),"ДА","") | V98: =P98*F98
A99: 62. профиль для монтажа гипсокартона ПН 50х40 (вкл. крепежные элементы) | B99: профиль для монтажа гипсокартона ПН 50х40 (вкл. крепежные элементы) | C99: ГКЛ, профиль, комплектующие | D99: м | E99: 1 | F99: =E99*IFERROR(INDEX(Работы!$D$4:$D$672,MATCH(SUBSTITUTE(SUBSTITUTE(SUBSTITUTE(A99,"~","~~"),"*","~*"),"?","~?"),Работы!$B$4:$B$672,0)),0) | G99: 95 | H99: 1 | I99: 0.07 | J99: 0.12 | L99: оценка | N99: 2026-10-29 | O99: оценка профиля Кнауф В Петрович, Лемана ПРО и Сатурн открытой карточки нет, оставлен прежний источник. | P99: =IF(H99=1,G99/VAT_DIV,G99) | Q99: =P99*(1+I99)*(1+DELIV)*(1+GROWTH+MONEY) | R99: =IF(AND(K99<>"",Q99*(1+J99)>K99/VAT_DIV),K99/VAT_DIV,Q99*(1+J99)) | S99: =Q99*F99 | T99: =R99*F99 | U99: =IF(AND(K99<>"",Q99*(1+J99)>K99/VAT_DIV+0.01),"ДА","") | V99: =P99*F99
A100: 63. профиль для монтажа гипсокартона ПС 50х50 (вкл. крепежные элементы) | B100: профиль для монтажа гипсокартона ПС 50х50 (вкл. крепежные элементы) | C100: ГКЛ, профиль, комплектующие | D100: м | E100: 1 | F100: =E100*IFERROR(INDEX(Работы!$D$4:$D$672,MATCH(SUBSTITUTE(SUBSTITUTE(SUBSTITUTE(A100,"~","~~"),"*","~*"),"?","~?"),Работы!$B$4:$B$672,0)),0) | G100: 95 | H100: 1 | I100: 0.07 | J100: 0.12 | L100: оценка | N100: 2026-10-29 | O100: оценка профиля Кнауф В Петрович, Лемана ПРО и Сатурн открытой карточки нет, оставлен прежний источник. | P100: =IF(H100=1,G100/VAT_DIV,G100) | Q100: =P100*(1+I100)*(1+DELIV)*(1+GROWTH+MONEY) | R100: =IF(AND(K100<>"",Q100*(1+J100)>K100/VAT_DIV),K100/VAT_DIV,Q100*(1+J100)) | S100: =Q100*F100 | T100: =R100*F100 | U100: =IF(AND(K100<>"",Q100*(1+J100)>K100/VAT_DIV+0.01),"ДА","") | V100: =P100*F100
A101: 64. Краска-эмаль типа Хамерайт (цвет по выбору) в 2 слоя | B101: Краска | C101: Краски, грунты, ЛКМ | D101: кг | E101: 0.28 | F101: =E101*IFERROR(INDEX(Работы!$D$4:$D$672,MATCH(SUBSTITUTE(SUBSTITUTE(SUBSTITUTE(A101,"~","~~"),"*","~*"),"?","~?"),Работы!$B$4:$B$672,0)),0) | G101: 700 | H101: 1 | I101: 0.05 | J101: 0.12 | L101: оценка | N101: 2026-10-29 | O101: Hammerite оценка 700 руб/кг В Петрович, Лемана ПРО и Сатурн открытой карточки нет, оставлен прежний источник. | P101: =IF(H101=1,G101/VAT_DIV,G101) | Q101: =P101*(1+I101)*(1+DELIV)*(1+GROWTH+MONEY) | R101: =IF(AND(K101<>"",Q101*(1+J101)>K101/VAT_DIV),K101/VAT_DIV,Q101*(1+J101)) | S101: =Q101*F101 | T101: =R101*F101 | U101: =IF(AND(K101<>"",Q101*(1+J101)>K101/VAT_DIV+0.01),"ДА","") | V101: =P101*F101
A102: 65. Краска водоэмульсионная типа Dufa Mattlatex Russia (цвет по выбору) в 2 слоя | B102: Краска | C102: Краски, грунты, ЛКМ | D102: кг | E102: 0.35 | F102: =E102*IFERROR(INDEX(Работы!$D$4:$D$672,MATCH(SUBSTITUTE(SUBSTITUTE(SUBSTITUTE(A102,"~","~~"),"*","~*"),"?","~?"),Работы!$B$4:$B$672,0)),0) | G102: 128.57 | H102: 1 | I102: 0.05 | J102: 0.12 | L102: Петрович | M102: https://moscow.petrovich.ru/product/103990/ | N102: 2026-10-29 | O102: Петрович Москва, Текс влагостойкая 1 800 руб/14 кг | P102: =IF(H102=1,G102/VAT_DIV,G102) | Q102: =P102*(1+I102)*(1+DELIV)*(1+GROWTH+MONEY) | R102: =IF(AND(K102<>"",Q102*(1+J102)>K102/VAT_DIV),K102/VAT_DIV,Q102*(1+J102)) | S102: =Q102*F102 | T102: =R102*F102 | U102: =IF(AND(K102<>"",Q102*(1+J102)>K102/VAT_DIV+0.01),"ДА","") | V102: =P102*F102
A103: 66. Краска водоэмульсионная наружная типа Dufa Fassadenfarbe (цвет по выбору) в 2 слоя. | B103: Краска | C103: Краски, грунты, ЛКМ | D103: кг | E103: 0.35 | F103: =E103*IFERROR(INDEX(Работы!$D$4:$D$672,MATCH(SUBSTITUTE(SUBSTITUTE(SUBSTITUTE(A103,"~","~~"),"*","~*"),"?","~?"),Работы!$B$4:$B$672,0)),0) | G103: 128.57 | H103: 1 | I103: 0.05 | J103: 0.12 | L103: Петрович | M103: https://moscow.petrovich.ru/product/103990/ | N103: 2026-10-29 | O103: Петрович Москва, Текс влагостойкая 1 800 руб/14 кг | P103: =IF(H103=1,G103/VAT_DIV,G103) | Q103: =P103*(1+I103)*(1+DELIV)*(1+GROWTH+MONEY) | R103: =IF(AND(K103<>"",Q103*(1+J103)>K103/VAT_DIV),K103/VAT_DIV,Q103*(1+J103)) | S103: =Q103*F103 | T103: =R103*F103 | U103: =IF(AND(K103<>"",Q103*(1+J103)>K103/VAT_DIV+0.01),"ДА","") | V103: =P103*F103
A104: 67. Штукатурка наружная типа "KNAUF sockelputz" | B104: Штукатурка наружная типа "KNAUF sockelputz" | C104: Сухие смеси, штукатурки, шпаклёвки | D104: кг | E104: 8 | F104: =E104*IFERROR(INDEX(Работы!$D$4:$D$672,MATCH(SUBSTITUTE(SUBSTITUTE(SUBSTITUTE(A104,"~","~~"),"*","~*"),"?","~?"),Работы!$B$4:$B$672,0)),0) | G104: 22 | H104: 1 | I104: 0.05 | J104: 0.12 | L104: оценка | N104: 2026-10-29 | O104: оценка гипсовой/цементной штукатурки В Петрович, Лемана ПРО и Сатурн открытой карточки нет, оставлен прежний источник. | P104: =IF(H104=1,G104/VAT_DIV,G104) | Q104: =P104*(1+I104)*(1+DELIV)*(1+GROWTH+MONEY) | R104: =IF(AND(K104<>"",Q104*(1+J104)>K104/VAT_DIV),K104/VAT_DIV,Q104*(1+J104)) | S104: =Q104*F104 | T104: =R104*F104 | U104: =IF(AND(K104<>"",Q104*(1+J104)>K104/VAT_DIV+0.01),"ДА","") | V104: =P104*F104
A105: 68. Шпаклевка типа UNIS фасадная | B105: Шпаклевка типа UNIS фасадная | C105: Сухие смеси, штукатурки, шпаклёвки | D105: кг | E105: 1.2 | F105: =E105*IFERROR(INDEX(Работы!$D$4:$D$672,MATCH(SUBSTITUTE(SUBSTITUTE(SUBSTITUTE(A105,"~","~~"),"*","~*"),"?","~?"),Работы!$B$4:$B$672,0)),0) | G105: 43.55 | H105: 1 | I105: 0.05 | J105: 0.12 | L105: Сатурн | M105: https://msk.saturn.net/product/shpaklevka-finishnaya-polimernaya-knauf-polymer-finish-20-kg/ | N105: 2026-10-29 | O105: Минимум из трёх: Сатурн Knauf Polymer Finish 20 кг = 43,55 руб/кг. Петрович 45,75, Лемана ПРО Vetonit LR+ 45,6. | P105: =IF(H105=1,G105/VAT_DIV,G105) | Q105: =P105*(1+I105)*(1+DELIV)*(1+GROWTH+MONEY) | R105: =IF(AND(K105<>"",Q105*(1+J105)>K105/VAT_DIV),K105/VAT_DIV,Q105*(1+J105)) | S105: =Q105*F105 | T105: =R105*F105 | U105: =IF(AND(K105<>"",Q105*(1+J105)>K105/VAT_DIV+0.01),"ДА","") | V105: =P105*F105
A106: 69. Грунтовка типа UNIS универсальная в 2 слоя | B106: Грунт | C106: Краски, грунты, ЛКМ | D106: л | E106: 0.2 | F106: =E106*IFERROR(INDEX(Работы!$D$4:$D$672,MATCH(SUBSTITUTE(SUBSTITUTE(SUBSTITUTE(A106,"~","~~"),"*","~*"),"?","~?"),Работы!$B$4:$B$672,0)),0) | G106: 136.7 | H106: 1 | I106: 0.05 | J106: 0.12 | L106: Лемана ПРО | M106: https://lemanapro.ru/product/grunt-ceresit-ct-17-transparent-glubokogo-proniknoveniya-10-l-89398668/ | N106: 2026-10-29 | O106: Минимум из трёх: Лемана ПРО Ceresit CT 17, 10 л = 136,7 руб/л. Петрович CT 17 PRO 143,8, Сатурн 145,9. | P106: =IF(H106=1,G106/VAT_DIV,G106) | Q106: =P106*(1+I106)*(1+DELIV)*(1+GROWTH+MONEY) | R106: =IF(AND(K106<>"",Q106*(1+J106)>K106/VAT_DIV),K106/VAT_DIV,Q106*(1+J106)) | S106: =Q106*F106 | T106: =R106*F106 | U106: =IF(AND(K106<>"",Q106*(1+J106)>K106/VAT_DIV+0.01),"ДА","") | V106: =P106*F106
A107: 70. Штукатурка внутренняя типа "KNAUF MP 75" | B107: Штукатурка внутренняя типа "KNAUF MP 75" | C107: Сухие смеси, штукатурки, шпаклёвки | D107: кг | E107: 8 | F107: =E107*IFERROR(INDEX(Работы!$D$4:$D$672,MATCH(SUBSTITUTE(SUBSTITUTE(SUBSTITUTE(A107,"~","~~"),"*","~*"),"?","~?"),Работы!$B$4:$B$672,0)),0) | G107: 22 | H107: 1 | I107: 0.05 | J107: 0.12 | L107: оценка | N107: 2026-10-29 | O107: оценка гипсовой/цементной штукатурки В Петрович, Лемана ПРО и Сатурн открытой карточки нет, оставлен прежний источник. | P107: =IF(H107=1,G107/VAT_DIV,G107) | Q107: =P107*(1+I107)*(1+DELIV)*(1+GROWTH+MONEY) | R107: =IF(AND(K107<>"",Q107*(1+J107)>K107/VAT_DIV),K107/VAT_DIV,Q107*(1+J107)) | S107: =Q107*F107 | T107: =R107*F107 | U107: =IF(AND(K107<>"",Q107*(1+J107)>K107/VAT_DIV+0.01),"ДА","") | V107: =P107*F107
A108: 71. Шпаклевка гипсовая типа "Unis БЛИК" | B108: Шпаклевка гипсовая типа "Unis БЛИК" | C108: Сухие смеси, штукатурки, шпаклёвки | D108: кг | E108: 1.2 | F108: =E108*IFERROR(INDEX(Работы!$D$4:$D$672,MATCH(SUBSTITUTE(SUBSTITUTE(SUBSTITUTE(A108,"~","~~"),"*","~*"),"?","~?"),Работы!$B$4:$B$672,0)),0) | G108: 43.55 | H108: 1 | I108: 0.05 | J108: 0.12 | L108: Сатурн | M108: https://msk.saturn.net/product/shpaklevka-finishnaya-polimernaya-knauf-polymer-finish-20-kg/ | N108: 2026-10-29 | O108: Минимум из трёх: Сатурн Knauf Polymer Finish 20 кг = 43,55 руб/кг. Петрович 45,75, Лемана ПРО Vetonit LR+ 45,6. | P108: =IF(H108=1,G108/VAT_DIV,G108) | Q108: =P108*(1+I108)*(1+DELIV)*(1+GROWTH+MONEY) | R108: =IF(AND(K108<>"",Q108*(1+J108)>K108/VAT_DIV),K108/VAT_DIV,Q108*(1+J108)) | S108: =Q108*F108 | T108: =R108*F108 | U108: =IF(AND(K108<>"",Q108*(1+J108)>K108/VAT_DIV+0.01),"ДА","") | V108: =P108*F108
A109: 72. Панель Випрок ламинированная 3000х1200х12,5 | B109: Панель Випрок ламинированная 3000х1200х12,5 | C109: ГКЛ, профиль, комплектующие | D109: м2 | E109: 1.05 | F109: =E109*IFERROR(INDEX(Работы!$D$4:$D$672,MATCH(SUBSTITUTE(SUBSTITUTE(SUBSTITUTE(A109,"~","~~"),"*","~*"),"?","~?"),Работы!$B$4:$B$672,0)),0) | G109: 900 | H109: 1 | I109: 0.07 | J109: 0.12 | L109: оценка | N109: 2026-10-29 | O109: оценка ламинированной панели, запросить КП В Петрович, Лемана ПРО и Сатурн открытой карточки нет, оставлен прежний источник. | P109: =IF(H109=1,G109/VAT_DIV,G109) | Q109: =P109*(1+I109)*(1+DELIV)*(1+GROWTH+MONEY) | R109: =IF(AND(K109<>"",Q109*(1+J109)>K109/VAT_DIV),K109/VAT_DIV,Q109*(1+J109)) | S109: =Q109*F109 | T109: =R109*F109 | U109: =IF(AND(K109<>"",Q109*(1+J109)>K109/VAT_DIV+0.01),"ДА","") | V109: =P109*F109
A110: 75. Лента уплотнительная 50 мм | B110: Лента уплотнительная 50 мм | C110: ГКЛ, профиль, комплектующие | D110: м | E110: 1 | F110: =E110*IFERROR(INDEX(Работы!$D$4:$D$672,MATCH(SUBSTITUTE(SUBSTITUTE(SUBSTITUTE(A110,"~","~~"),"*","~*"),"?","~?"),Работы!$B$4:$B$672,0)),0) | G110: 15 | H110: 1 | I110: 0.07 | J110: 0.12 | L110: оценка | N110: 2026-10-29 | O110: оценка В Петрович, Лемана ПРО и Сатурн открытой карточки нет, оставлен прежний источник. | P110: =IF(H110=1,G110/VAT_DIV,G110) | Q110: =P110*(1+I110)*(1+DELIV)*(1+GROWTH+MONEY) | R110: =IF(AND(K110<>"",Q110*(1+J110)>K110/VAT_DIV),K110/VAT_DIV,Q110*(1+J110)) | S110: =Q110*F110 | T110: =R110*F110 | U110: =IF(AND(K110<>"",Q110*(1+J110)>K110/VAT_DIV+0.01),"ДА","") | V110: =P110*F110
A111: 76. Уголок пластиковый 25х25 мм | B111: Уголок пластиковый 25х25 мм | C111: Прочее | D111: м | E111: 1 | F111: =E111*IFERROR(INDEX(Работы!$D$4:$D$672,MATCH(SUBSTITUTE(SUBSTITUTE(SUBSTITUTE(A111,"~","~~"),"*","~*"),"?","~?"),Работы!$B$4:$B$672,0)),0) | G111: 40 | H111: 1 | I111: 0.03 | J111: 0.15 | L111: оценка | N111: 2026-10-29 | O111: оценка ПВХ уголка В Петрович, Лемана ПРО и Сатурн открытой карточки нет, оставлен прежний источник. | P111: =IF(H111=1,G111/VAT_DIV,G111) | Q111: =P111*(1+I111)*(1+DELIV)*(1+GROWTH+MONEY) | R111: =IF(AND(K111<>"",Q111*(1+J111)>K111/VAT_DIV),K111/VAT_DIV,Q111*(1+J111)) | S111: =Q111*F111 | T111: =R111*F111 | U111: =IF(AND(K111<>"",Q111*(1+J111)>K111/VAT_DIV+0.01),"ДА","") | V111: =P111*F111
A112: 77. Полимерная шпатлевка LR для внутренних работ. Рекомендуется для устранения мельчайших дефектов поверхности. CERESIT CT 127 (или аналог) | B112: Полимерная шпатлевка LR для внутренних работ. Рекомендуется | C112: Сухие смеси, штукатурки, шпаклёвки | D112: кг | E112: 1.2 | F112: =E112*IFERROR(INDEX(Работы!$D$4:$D$672,MATCH(SUBSTITUTE(SUBSTITUTE(SUBSTITUTE(A112,"~","~~"),"*","~*"),"?","~?"),Работы!$B$4:$B$672,0)),0) | G112: 45 | H112: 1 | I112: 0.05 | J112: 0.12 | L112: оценка | N112: 2026-10-29 | O112: оценка шпаклёвки ~45 руб/кг В Петрович, Лемана ПРО и Сатурн открытой карточки нет, оставлен прежний источник. | P112: =IF(H112=1,G112/VAT_DIV,G112) | Q112: =P112*(1+I112)*(1+DELIV)*(1+GROWTH+MONEY) | R112: =IF(AND(K112<>"",Q112*(1+J112)>K112/VAT_DIV),K112/VAT_DIV,Q112*(1+J112)) | S112: =Q112*F112 | T112: =R112*F112 | U112: =IF(AND(K112<>"",Q112*(1+J112)>K112/VAT_DIV+0.01),"ДА","") | V112: =P112*F112
A113: 78. Полимерная шпатлевка KR для внутренних работ. Применяется для заделки трещин выбоин и др. дефектов поверхностей. CERESIT CT 127 (или аналог) | B113: Полимерная шпатлевка KR для внутренних работ. Применяется дл | C113: Сухие смеси, штукатурки, шпаклёвки | D113: кг | E113: 1.2 | F113: =E113*IFERROR(INDEX(Работы!$D$4:$D$672,MATCH(SUBSTITUTE(SUBSTITUTE(SUBSTITUTE(A113,"~","~~"),"*","~*"),"?","~?"),Работы!$B$4:$B$672,0)),0) | G113: 45 | H113: 1 | I113: 0.05 | J113: 0.12 | L113: оценка | N113: 2026-10-29 | O113: оценка шпаклёвки ~45 руб/кг В Петрович, Лемана ПРО и Сатурн открытой карточки нет, оставлен прежний источник. | P113: =IF(H113=1,G113/VAT_DIV,G113) | Q113: =P113*(1+I113)*(1+DELIV)*(1+GROWTH+MONEY) | R113: =IF(AND(K113<>"",Q113*(1+J113)>K113/VAT_DIV),K113/VAT_DIV,Q113*(1+J113)) | S113: =Q113*F113 | T113: =R113*F113 | U113: =IF(AND(K113<>"",Q113*(1+J113)>K113/VAT_DIV+0.01),"ДА","") | V113: =P113*F113
A114: 79. Фасадная финишная шпаклевка, серая. Рекомендуется для выравнивания поверхностей фасадов зданий , заделки выбоин , трещин, раковин слоем до 6 мм . CERESIT CT 225 (или аналог) | B114: Фасадная финишная шпаклевка, серая. Рекомендуется для выравнивания поверхностей | C114: Сантехприборы | D114: шт | E114: 1 | F114: =E114*IFERROR(INDEX(Работы!$D$4:$D$672,MATCH(SUBSTITUTE(SUBSTITUTE(SUBSTITUTE(A114,"~","~~"),"*","~*"),"?","~?"),Работы!$B$4:$B$672,0)),0) | G114: 2800 | H114: 1 | I114: 0 | J114: 0.12 | L114: оценка | N114: 2026-10-29 | O114: оценка керамики среднего сегмента В Петрович, Лемана ПРО и Сатурн открытой карточки нет, оставлен прежний источник. | P114: =IF(H114=1,G114/VAT_DIV,G114) | Q114: =P114*(1+I114)*(1+DELIV)*(1+GROWTH+MONEY) | R114: =IF(AND(K114<>"",Q114*(1+J114)>K114/VAT_DIV),K114/VAT_DIV,Q114*(1+J114)) | S114: =Q114*F114 | T114: =R114*F114 | U114: =IF(AND(K114<>"",Q114*(1+J114)>K114/VAT_DIV+0.01),"ДА","") | V114: =P114*F114
A115: 80. Финишная полимерная шпаклевка для внутренних работ.Рекомендуется для шпаклевания штукатурных и бетонных поверхностей стен и потолков перед оклейкой обоев или окраской. CERESIT | B115: Краска | C115: Краски, грунты, ЛКМ | D115: кг | E115: 0.35 | F115: =E115*IFERROR(INDEX(Работы!$D$4:$D$672,MATCH(SUBSTITUTE(SUBSTITUTE(SUBSTITUTE(A115,"~","~~"),"*","~*"),"?","~?"),Работы!$B$4:$B$672,0)),0) | G115: 128.57 | H115: 1 | I115: 0.05 | J115: 0.12 | L115: Петрович | M115: https://moscow.petrovich.ru/product/103990/ | N115: 2026-10-29 | O115: Петрович Москва, Текс влагостойкая 1 800 руб/14 кг | P115: =IF(H115=1,G115/VAT_DIV,G115) | Q115: =P115*(1+I115)*(1+DELIV)*(1+GROWTH+MONEY) | R115: =IF(AND(K115<>"",Q115*(1+J115)>K115/VAT_DIV),K115/VAT_DIV,Q115*(1+J115)) | S115: =Q115*F115 | T115: =R115*F115 | U115: =IF(AND(K115<>"",Q115*(1+J115)>K115/VAT_DIV+0.01),"ДА","") | V115: =P115*F115
A116: 81. Грунтовка для обработки гладких оснований . Рекомендуется для обработки слабо впитывающих Оснований к нанесению различных отделочных материалов перед нанесением гипсовых и цеме | B116: Грунт | C116: Краски, грунты, ЛКМ | D116: л | E116: 0.2 | F116: =E116*IFERROR(INDEX(Работы!$D$4:$D$672,MATCH(SUBSTITUTE(SUBSTITUTE(SUBSTITUTE(A116,"~","~~"),"*","~*"),"?","~?"),Работы!$B$4:$B$672,0)),0) | G116: 136.7 | H116: 1 | I116: 0.05 | J116: 0.12 | L116: Лемана ПРО | M116: https://lemanapro.ru/product/grunt-ceresit-ct-17-transparent-glubokogo-proniknoveniya-10-l-89398668/ | N116: 2026-10-29 | O116: Минимум из трёх: Лемана ПРО Ceresit CT 17, 10 л = 136,7 руб/л. Петрович CT 17 PRO 143,8, Сатурн 145,9. | P116: =IF(H116=1,G116/VAT_DIV,G116) | Q116: =P116*(1+I116)*(1+DELIV)*(1+GROWTH+MONEY) | R116: =IF(AND(K116<>"",Q116*(1+J116)>K116/VAT_DIV),K116/VAT_DIV,Q116*(1+J116)) | S116: =Q116*F116 | T116: =R116*F116 | U116: =IF(AND(K116<>"",Q116*(1+J116)>K116/VAT_DIV+0.01),"ДА","") | V116: =P116*F116
A117: 82. Универсальная самовыравнивающаяся смесь . Финишный ровнитель для тщательного выравнивания и последующей укладки декоративных напольных покрытий, нанесения тонкослойных наливных | B117: Универсальная самовыравнивающаяся смесь . Финишный ровнитель | C117: Сухие смеси, штукатурки, шпаклёвки | D117: кг | E117: 8 | F117: =E117*IFERROR(INDEX(Работы!$D$4:$D$672,MATCH(SUBSTITUTE(SUBSTITUTE(SUBSTITUTE(A117,"~","~~"),"*","~*"),"?","~?"),Работы!$B$4:$B$672,0)),0) | G117: 20.2 | H117: 1 | I117: 0.05 | J117: 0.12 | L117: Петрович | M117: https://moscow.petrovich.ru/product/998145/ | N117: 2026-10-29 | O117: Петрович, Volma Nivelir Express 25 кг = 20,2 руб/кг. Лемана ПРО 19,76, Сатурн 19,04 — соседние SKU. | P117: =IF(H117=1,G117/VAT_DIV,G117) | Q117: =P117*(1+I117)*(1+DELIV)*(1+GROWTH+MONEY) | R117: =IF(AND(K117<>"",Q117*(1+J117)>K117/VAT_DIV),K117/VAT_DIV,Q117*(1+J117)) | S117: =Q117*F117 | T117: =R117*F117 | U117: =IF(AND(K117<>"",Q117*(1+J117)>K117/VAT_DIV+0.01),"ДА","") | V117: =P117*F117
A118: 83. Уголок пластиковый 25х25 мм | B118: Уголок пластиковый 25х25 мм | C118: Прочее | D118: м | E118: 1 | F118: =E118*IFERROR(INDEX(Работы!$D$4:$D$672,MATCH(SUBSTITUTE(SUBSTITUTE(SUBSTITUTE(A118,"~","~~"),"*","~*"),"?","~?"),Работы!$B$4:$B$672,0)),0) | G118: 40 | H118: 1 | I118: 0.03 | J118: 0.15 | L118: оценка | N118: 2026-10-29 | O118: оценка ПВХ уголка В Петрович, Лемана ПРО и Сатурн открытой карточки нет, оставлен прежний источник. | P118: =IF(H118=1,G118/VAT_DIV,G118) | Q118: =P118*(1+I118)*(1+DELIV)*(1+GROWTH+MONEY) | R118: =IF(AND(K118<>"",Q118*(1+J118)>K118/VAT_DIV),K118/VAT_DIV,Q118*(1+J118)) | S118: =Q118*F118 | T118: =R118*F118 | U118: =IF(AND(K118<>"",Q118*(1+J118)>K118/VAT_DIV+0.01),"ДА","") | V118: =P118*F118
A119: 84. Уголок пластиковый 40х40 мм | B119: Уголок пластиковый 40х40 мм | C119: Прочее | D119: м | E119: 1 | F119: =E119*IFERROR(INDEX(Работы!$D$4:$D$672,MATCH(SUBSTITUTE(SUBSTITUTE(SUBSTITUTE(A119,"~","~~"),"*","~*"),"?","~?"),Работы!$B$4:$B$672,0)),0) | G119: 40 | H119: 1 | I119: 0.03 | J119: 0.15 | L119: оценка | N119: 2026-10-29 | O119: оценка ПВХ уголка В Петрович, Лемана ПРО и Сатурн открытой карточки нет, оставлен прежний источник. | P119: =IF(H119=1,G119/VAT_DIV,G119) | Q119: =P119*(1+I119)*(1+DELIV)*(1+GROWTH+MONEY) | R119: =IF(AND(K119<>"",Q119*(1+J119)>K119/VAT_DIV),K119/VAT_DIV,Q119*(1+J119)) | S119: =Q119*F119 | T119: =R119*F119 | U119: =IF(AND(K119<>"",Q119*(1+J119)>K119/VAT_DIV+0.01),"ДА","") | V119: =P119*F119
A120: 85. Уголок пластиковый 60х60 мм | B120: Уголок пластиковый 60х60 мм | C120: Прочее | D120: м | E120: 1 | F120: =E120*IFERROR(INDEX(Работы!$D$4:$D$672,MATCH(SUBSTITUTE(SUBSTITUTE(SUBSTITUTE(A120,"~","~~"),"*","~*"),"?","~?"),Работы!$B$4:$B$672,0)),0) | G120: 40 | H120: 1 | I120: 0.03 | J120: 0.15 | L120: оценка | N120: 2026-10-29 | O120: оценка ПВХ уголка В Петрович, Лемана ПРО и Сатурн открытой карточки нет, оставлен прежний источник. | P120: =IF(H120=1,G120/VAT_DIV,G120) | Q120: =P120*(1+I120)*(1+DELIV)*(1+GROWTH+MONEY) | R120: =IF(AND(K120<>"",Q120*(1+J120)>K120/VAT_DIV),K120/VAT_DIV,Q120*(1+J120)) | S120: =Q120*F120 | T120: =R120*F120 | U120: =IF(AND(K120<>"",Q120*(1+J120)>K120/VAT_DIV+0.01),"ДА","") | V120: =P120*F120
A121: 87. Стопор дверной типа Amig 103 | B121: Стопор дверной типа Amig 103 | C121: Прочее | D121: шт | E121: 1 | F121: =E121*IFERROR(INDEX(Работы!$D$4:$D$672,MATCH(SUBSTITUTE(SUBSTITUTE(SUBSTITUTE(A121,"~","~~"),"*","~*"),"?","~?"),Работы!$B$4:$B$672,0)),0) | G121: 250 | H121: 1 | I121: 0.03 | J121: 0.15 | L121: оценка | N121: 2026-10-29 | O121: оценка фурнитуры В Петрович, Лемана ПРО и Сатурн открытой карточки нет, оставлен прежний источник. | P121: =IF(H121=1,G121/VAT_DIV,G121) | Q121: =P121*(1+I121)*(1+DELIV)*(1+GROWTH+MONEY) | R121: =IF(AND(K121<>"",Q121*(1+J121)>K121/VAT_DIV),K121/VAT_DIV,Q121*(1+J121)) | S121: =Q121*F121 | T121: =R121*F121 | U121: =IF(AND(K121<>"",Q121*(1+J121)>K121/VAT_DIV+0.01),"ДА","") | V121: =P121*F121
A122: 88. Шпингалет APEX 100 мм. | B122: Шпингалет APEX 100 мм. | C122: Прочее | D122: шт | E122: 1 | F122: =E122*IFERROR(INDEX(Работы!$D$4:$D$672,MATCH(SUBSTITUTE(SUBSTITUTE(SUBSTITUTE(A122,"~","~~"),"*","~*"),"?","~?"),Работы!$B$4:$B$672,0)),0) | G122: 250 | H122: 1 | I122: 0.03 | J122: 0.15 | L122: оценка | N122: 2026-10-29 | O122: оценка фурнитуры В Петрович, Лемана ПРО и Сатурн открытой карточки нет, оставлен прежний источник. | P122: =IF(H122=1,G122/VAT_DIV,G122) | Q122: =P122*(1+I122)*(1+DELIV)*(1+GROWTH+MONEY) | R122: =IF(AND(K122<>"",Q122*(1+J122)>K122/VAT_DIV),K122/VAT_DIV,Q122*(1+J122)) | S122: =Q122*F122 | T122: =R122*F122 | U122: =IF(AND(K122<>"",Q122*(1+J122)>K122/VAT_DIV+0.01),"ДА","") | V122: =P122*F122
A123: 89. Наличники дверные пвх | B123: Наличники дверные пвх | C123: Прочее | D123: м | E123: 1 | F123: =E123*IFERROR(INDEX(Работы!$D$4:$D$672,MATCH(SUBSTITUTE(SUBSTITUTE(SUBSTITUTE(A123,"~","~~"),"*","~*"),"?","~?"),Работы!$B$4:$B$672,0)),0) | G123: 180 | H123: 1 | I123: 0.03 | J123: 0.15 | L123: оценка | N123: 2026-10-29 | O123: оценка фурнитуры В Петрович, Лемана ПРО и Сатурн открытой карточки нет, оставлен прежний источник. | P123: =IF(H123=1,G123/VAT_DIV,G123) | Q123: =P123*(1+I123)*(1+DELIV)*(1+GROWTH+MONEY) | R123: =IF(AND(K123<>"",Q123*(1+J123)>K123/VAT_DIV),K123/VAT_DIV,Q123*(1+J123)) | S123: =Q123*F123 | T123: =R123*F123 | U123: =IF(AND(K123<>"",Q123*(1+J123)>K123/VAT_DIV+0.01),"ДА","") | V123: =P123*F123
A124: 90. Засов дверной (Москва-№6) | B124: Засов дверной (Москва-№6) | C124: Прочее | D124: шт | E124: 1 | F124: =E124*IFERROR(INDEX(Работы!$D$4:$D$672,MATCH(SUBSTITUTE(SUBSTITUTE(SUBSTITUTE(A124,"~","~~"),"*","~*"),"?","~?"),Работы!$B$4:$B$672,0)),0) | G124: 250 | H124: 1 | I124: 0.03 | J124: 0.15 | L124: оценка | N124: 2026-10-29 | O124: оценка фурнитуры В Петрович, Лемана ПРО и Сатурн открытой карточки нет, оставлен прежний источник. | P124: =IF(H124=1,G124/VAT_DIV,G124) | Q124: =P124*(1+I124)*(1+DELIV)*(1+GROWTH+MONEY) | R124: =IF(AND(K124<>"",Q124*(1+J124)>K124/VAT_DIV),K124/VAT_DIV,Q124*(1+J124)) | S124: =Q124*F124 | T124: =R124*F124 | U124: =IF(AND(K124<>"",Q124*(1+J124)>K124/VAT_DIV+0.01),"ДА","") | V124: =P124*F124
A125: 91. Упор дверной напольный "Крит" УД-П60/50-Цн | B125: Упор дверной напольный "Крит" УД-П60/50-Цн | C125: Прочее | D125: шт | E125: 1 | F125: =E125*IFERROR(INDEX(Работы!$D$4:$D$672,MATCH(SUBSTITUTE(SUBSTITUTE(SUBSTITUTE(A125,"~","~~"),"*","~*"),"?","~?"),Работы!$B$4:$B$672,0)),0) | G125: 250 | H125: 1 | I125: 0.03 | J125: 0.15 | L125: оценка | N125: 2026-10-29 | O125: оценка фурнитуры В Петрович, Лемана ПРО и Сатурн открытой карточки нет, оставлен прежний источник. | P125: =IF(H125=1,G125/VAT_DIV,G125) | Q125: =P125*(1+I125)*(1+DELIV)*(1+GROWTH+MONEY) | R125: =IF(AND(K125<>"",Q125*(1+J125)>K125/VAT_DIV),K125/VAT_DIV,Q125*(1+J125)) | S125: =Q125*F125 | T125: =R125*F125 | U125: =IF(AND(K125<>"",Q125*(1+J125)>K125/VAT_DIV+0.01),"ДА","") | V125: =P125*F125
A126: 92. Фиксатор (стопор) открытого положения двери типа Palladium "КН" (любой цвет по RAL) | B126: Фиксатор (стопор) открытого положения двери типа Palladium "КН" (любой | C126: Прочее | D126: шт | E126: 1 | F126: =E126*IFERROR(INDEX(Работы!$D$4:$D$672,MATCH(SUBSTITUTE(SUBSTITUTE(SUBSTITUTE(A126,"~","~~"),"*","~*"),"?","~?"),Работы!$B$4:$B$672,0)),0) | G126: 250 | H126: 1 | I126: 0.03 | J126: 0.15 | L126: оценка | N126: 2026-10-29 | O126: оценка фурнитуры В Петрович, Лемана ПРО и Сатурн открытой карточки нет, оставлен прежний источник. | P126: =IF(H126=1,G126/VAT_DIV,G126) | Q126: =P126*(1+I126)*(1+DELIV)*(1+GROWTH+MONEY) | R126: =IF(AND(K126<>"",Q126*(1+J126)>K126/VAT_DIV),K126/VAT_DIV,Q126*(1+J126)) | S126: =Q126*F126 | T126: =R126*F126 | U126: =IF(AND(K126<>"",Q126*(1+J126)>K126/VAT_DIV+0.01),"ДА","") | V126: =P126*F126
A127: 93. Концевой выключатель кнопочного типа "Elfin limit switch 050f02" | B127: Концевой выключатель кнопочного типа "Elfin limit switch 050f02" | C127: Электроустановочные изделия, щиты, автоматы | D127: шт | E127: 1 | F127: =E127*IFERROR(INDEX(Работы!$D$4:$D$672,MATCH(SUBSTITUTE(SUBSTITUTE(SUBSTITUTE(A127,"~","~~"),"*","~*"),"?","~?"),Работы!$B$4:$B$672,0)),0) | G127: 160 | H127: 1 | I127: 0.01 | J127: 0.12 | L127: оценка | N127: 2026-10-29 | O127: оценка В Петрович, Лемана ПРО и Сатурн открытой карточки нет, оставлен прежний источник. | P127: =IF(H127=1,G127/VAT_DIV,G127) | Q127: =P127*(1+I127)*(1+DELIV)*(1+GROWTH+MONEY) | R127: =IF(AND(K127<>"",Q127*(1+J127)>K127/VAT_DIV),K127/VAT_DIV,Q127*(1+J127)) | S127: =Q127*F127 | T127: =R127*F127 | U127: =IF(AND(K127<>"",Q127*(1+J127)>K127/VAT_DIV+0.01),"ДА","") | V127: =P127*F127
A128: 94. Петля СТН (белая) "Сатурн" | B128: Петля СТН (белая) "Сатурн" | C128: Изделия под заказ (ворота, двери, окна, перегородки) | D128: шт | E128: 1 | F128: =E128*IFERROR(INDEX(Работы!$D$4:$D$672,MATCH(SUBSTITUTE(SUBSTITUTE(SUBSTITUTE(A128,"~","~~"),"*","~*"),"?","~?"),Работы!$B$4:$B$672,0)),0) | G128: 180 | H128: 1 | I128: 0 | J128: 0.12 | L128: оценка | N128: 2026-10-29 | O128: оценка петли В Петрович, Лемана ПРО и Сатурн открытой карточки нет, оставлен прежний источник. | P128: =IF(H128=1,G128/VAT_DIV,G128) | Q128: =P128*(1+I128)*(1+DELIV)*(1+GROWTH+MONEY) | R128: =IF(AND(K128<>"",Q128*(1+J128)>K128/VAT_DIV),K128/VAT_DIV,Q128*(1+J128)) | S128: =Q128*F128 | T128: =R128*F128 | U128: =IF(AND(K128<>"",Q128*(1+J128)>K128/VAT_DIV+0.01),"ДА","") | V128: =P128*F128
A129: 95. Петля дверная трёхсекционная с крепежом | B129: Петля дверная трёхсекционная с крепежом | C129: Изделия под заказ (ворота, двери, окна, перегородки) | D129: шт | E129: 1 | F129: =E129*IFERROR(INDEX(Работы!$D$4:$D$672,MATCH(SUBSTITUTE(SUBSTITUTE(SUBSTITUTE(A129,"~","~~"),"*","~*"),"?","~?"),Работы!$B$4:$B$672,0)),0) | G129: 180 | H129: 1 | I129: 0 | J129: 0.12 | L129: оценка | N129: 2026-10-29 | O129: оценка петли В Петрович, Лемана ПРО и Сатурн открытой карточки нет, оставлен прежний источник. | P129: =IF(H129=1,G129/VAT_DIV,G129) | Q129: =P129*(1+I129)*(1+DELIV)*(1+GROWTH+MONEY) | R129: =IF(AND(K129<>"",Q129*(1+J129)>K129/VAT_DIV),K129/VAT_DIV,Q129*(1+J129)) | S129: =Q129*F129 | T129: =R129*F129 | U129: =IF(AND(K129<>"",Q129*(1+J129)>K129/VAT_DIV+0.01),"ДА","") | V129: =P129*F129
... A134: 100. Металлическая петля под металоконструкцию d16 | B134: Металлическая петля под металоконструкцию d16 | C134: Изделия под заказ (ворота, двери, окна, перегородки) | D134: шт | E134: 1 | F134: =E134*IFERROR(INDEX(Работы!$D$4:$D$672,MATCH(SUBSTITUTE(SUBSTITUTE(SUBSTITUTE(A134,"~","~~"),"*","~*"),"?","~?"),Работы!$B$4:$B$672,0)),0) | G134: 350 | H134: 1 | I134: 0 | J134: 0.12 | L134: оценка | N134: 2026-10-29 | O134: оценка петли В Петрович, Лемана ПРО и Сатурн открытой карточки нет, оставлен прежний источник. | P134: =IF(H134=1,G134/VAT_DIV,G134) | Q134: =P134*(1+I134)*(1+DELIV)*(1+GROWTH+MONEY) | R134: =IF(AND(K134<>"",Q134*(1+J134)>K134/VAT_DIV),K134/VAT_DIV,Q134*(1+J134)) | S134: =Q134*F134 | T134: =R134*F134 | U134: =IF(AND(K134<>"",Q134*(1+J134)>K134/VAT_DIV+0.01),"ДА","") | V134: =P134*F134
A135: 101. Дверь глухая пластиковая "Капелли", 900х2000, белая, комплект наличников и доборов на две стороны | B135: Дверь глухая пластиковая "Капелли", 900х2000, белая, комплект наличников и добор | C135: Изделия под заказ (ворота, двери, окна, перегородки) | D135: шт | E135: 1 | F135: =E135*IFERROR(INDEX(Работы!$D$4:$D$672,MATCH(SUBSTITUTE(SUBSTITUTE(SUBSTITUTE(A135,"~","~~"),"*","~*"),"?","~?"),Работы!$B$4:$B$672,0)),0) | G135: 15624 | H135: 1 | I135: 0 | J135: 0.12 | L135: Петрович | M135: https://moscow.petrovich.ru/product/1138646/ | N135: 2026-10-29 | O135: Петрович, Kapelli Classic ПВХ 800х2000 глухая с коробкой, 15 624 руб. Лемана ПРО комплект ПВХ 16 400. | P135: =IF(H135=1,G135/VAT_DIV,G135) | Q135: =P135*(1+I135)*(1+DELIV)*(1+GROWTH+MONEY) | R135: =IF(AND(K135<>"",Q135*(1+J135)>K135/VAT_DIV),K135/VAT_DIV,Q135*(1+J135)) | S135: =Q135*F135 | T135: =R135*F135 | U135: =IF(AND(K135<>"",Q135*(1+J135)>K135/VAT_DIV+0.01),"ДА","") | V135: =P135*F135
A136: 102. Дверей металлопластиковая одностворчатая глухая 900х2000, комплект наличников и доборов на две стороны | B136: Дверей металлопластиковая одностворчатая глухая 900х2000, комплект наличников и доборов на | C136: Трубы и фитинги ВиК, отопления | D136: шт | E136: 1 | F136: =E136*IFERROR(INDEX(Работы!$D$4:$D$672,MATCH(SUBSTITUTE(SUBSTITUTE(SUBSTITUTE(A136,"~","~~"),"*","~*"),"?","~?"),Работы!$B$4:$B$672,0)),0) | G136: 15624 | H136: 1 | I136: 0.04 | J136: 0.12 | L136: Петрович | M136: https://moscow.petrovich.ru/product/1138646/ | N136: 2026-10-29 | O136: Петрович, Kapelli Classic ПВХ 800х2000 глухая с коробкой, 15 624 руб. Лемана ПРО комплект ПВХ 16 400. | P136: =IF(H136=1,G136/VAT_DIV,G136) | Q136: =P136*(1+I136)*(1+DELIV)*(1+GROWTH+MONEY) | R136: =IF(AND(K136<>"",Q136*(1+J136)>K136/VAT_DIV),K136/VAT_DIV,Q136*(1+J136)) | S136: =Q136*F136 | T136: =R136*F136 | U136: =IF(AND(K136<>"",Q136*(1+J136)>K136/VAT_DIV+0.01),"ДА","") | V136: =P136*F136
A137: 103. Двери однопольные деревянные гладкие (типа Alavus, mod 200) размер полотна: 725х2040 мм Цвет - белый, RAL-9016. 9010 Дверные стопоры (ограничители)- настенные. | B137: Двери однопольные деревянные гладкие (типа Alavus, mod 200) размер полотна: 725 | C137: Изделия под заказ (ворота, двери, окна, перегородки) | D137: шт | E137: 1 | F137: =E137*IFERROR(INDEX(Работы!$D$4:$D$672,MATCH(SUBSTITUTE(SUBSTITUTE(SUBSTITUTE(A137,"~","~~"),"*","~*"),"?","~?"),Работы!$B$4:$B$672,0)),0) | G137: 6671 | H137: 1 | I137: 0 | J137: 0.12 | L137: Лемана ПРО | M137: https://lemanapro.ru/set/komplekt-dveri-artens-dukato-gluhaya-80x200-sm-hardflex-cvet-bora-s-doborom-200-mm-89428747/ | N137: 2026-10-29 | O137: Минимум: Лемана ПРО Artens глухая 80х200 = 6 671 руб. Петрович Мона эмаль 8 246. | P137: =IF(H137=1,G137/VAT_DIV,G137) | Q137: =P137*(1+I137)*(1+DELIV)*(1+GROWTH+MONEY) | R137: =IF(AND(K137<>"",Q137*(1+J137)>K137/VAT_DIV),K137/VAT_DIV,Q137*(1+J137)) | S137: =Q137*F137 | T137: =R137*F137 | U137: =IF(AND(K137<>"",Q137*(1+J137)>K137/VAT_DIV+0.01),"ДА","") | V137: =P137*F137
...

Sheet Косвенные
A1: Косвенные считаются от листов «Работы» и «Материалы» и от процентов на «Параметрах».
A3: Статья | B3: Расчёт | C3: Сумма
A4: Разъезды и мобилизация по площадкам Москвы и МО | B4: P_LOG * оплата бригадам | C4: =P_LOG*SUM(Работы!L4:L800)
A5: Мастер на заявках | B5: P_ITR * оплата бригадам. Диспетчер 24/7 сюда не входит | C5: =P_ITR*SUM(Работы!L4:L800)
A6: Резерв удержания цены 2 года | B6: P_HOLD * закупка материалов без НДС | C6: =P_HOLD*SUM(Материалы!V4:V800)
A7: Резерв на гарантию | B7: P_WAR * (бригада + закупка) | C7: =P_WAR*(SUM(Работы!L4:L800)+SUM(Материалы!V4:V800))
A8: Резерв на риски действующего склада | B8: P_RISK * (бригада + закупка) | C8: =P_RISK*(SUM(Работы!L4:L800)+SUM(Материалы!V4:V800))
A9: Итого | C9: =SUM(C4:C8)

Sheet Форма
A1: Раздел | B1: Подраздел | C1: Тип работ | D1: Наименование материалов используемых в РСР | E1: Стоимость услуги за еденицу RUB без НДС | F1: Ед.изм | G1: 1.Ozon Москва, Москва, ул Гренадерская, д. 1 стр. 6. | H1: 2. Московская область, городской округ Подольск, деревня Гривно, территория промышленного парка Гривно, д. 1, к. 13 | I1: 3. Московская область городской округ Домодедово, дер. Кучино, стр. 52. | J1: 4. Московская область Жуковский, район Замоскворечье, 457, стр. 5 | K1: 5. Московская область, Раменский городской округ, территория Логистический технопарк Софьино, 2/1 | L1: 6. Московская область, Троицкий муниципальный округ . Квартал номер 80 | M1: 7.Московская область, село Петровское территория МПСК ориентир запад здание 2 | N1: Стоимость материалов без НДС | O1: Стоимость монтажных работ без НДС | P1: 8. Московская область го Красногорск, поселок Ильинское-Усово , территория СмартПарк Новая Рига | Q1: 9 обл. Московская, Никольское, МО Дмитровский р-он п. Никольское 205 стр 1 | R1: 10. Московская область район Замоскворечье, 866, Жуковский, Московская область(склад шин) | S1: 11. Московская область район Замоскворечье, 92, Жуковский, Московская область | T1: 12. Московская область Промышленная улица, 10, микрорайон Центральный, Домодедово, | U1: 13 Московская область территория МПСК Ориентир-Запад, 1Б, муниципальный округ Истра, Московская область | V1: 14 Московская область территория МПСК Ориентир-Запад, 2, муниципальный округ Истра, Московская область | W1: 15 Московская область Дачная улица, 3, деревня Давыдовское, муниципальный округ Истра, Московская область | X1: 16 Московская область территория ПромТехАльянс, 1с2, городской округ Подольск, Московская область, 142143 | Y1: 17 г. Москва, Россия, Москва, Проектируемый проезд № 727, 22с1 | Z1: 18 Московская Область, город Химки, деревня Черная Грязь, Чёрная Грязь | AA1: 19.Россия, обл. Московская, г. Истра, с. Павловская Слобода, промышленная зона квартала 0050343, д. 2
A2: Аварийные работы | B2: Прочистка канализации | C2: Очистка | D2: Гидродинамическим спосбом включая вызов спец.техники | E2: =N2+O2 | F2: м.п. | G2: =IFERROR('[1]Лист1'!G2,2) | H2: 2 | I2: 2 | J2: 2 | K2: 2 | L2: 2 | M2: 2 | N2: =Работы!S4 | O2: =Работы!R4 | P2: 2 | Q2: 2 | R2: 2 | S2: 2 | T2: 2 | U2: 2 | V2: 2 | W2: 2 | X2: 2 | Y2: 2 | Z2: 2 | AA2: 2
A3: Аварийные работы | B3: Прочистка канализации | C3: Очистка | D3: Ручным способом с применением спец.инструмента | E3: =N3+O3 | F3: м.п. | G3: =IFERROR('[1]Лист1'!G3,2) | H3: 2 | I3: 2 | J3: 2 | K3: 2 | L3: 2 | M3: 2 | N3: =Работы!S5 | O3: =Работы!R5 | P3: 2 | Q3: 2 | R3: 2 | S3: 2 | T3: 2 | U3: 2 | V3: 2 | W3: 2 | X3: 2 | Y3: 2 | Z3: 2 | AA3: 2
A4: Аварийные работы | B4: Чистка пескоуловителей | C4: Очистка | D4: Ручная очистка пескоуловителя объемом до 1м3 включая разбоку и сборку,утилизацию мусора | E4: =N4+O4 | F4: шт. | G4: =IFERROR('[1]Лист1'!G4,2) | H4: 2 | I4: 2 | J4: 2 | K4: 2 | L4: 2 | M4: 2 | N4: =Работы!S6 | O4: =Работы!R6 | P4: 2 | Q4: 2 | R4: 2 | S4: 2 | T4: 2 | U4: 2 | V4: 2 | W4: 2 | X4: 2 | Y4: 2 | Z4: 2 | AA4: 2
A5: Аварийные работы | B5: Ремонт откидных, перегрузочных мостов тип DoorHan или аналоги | C5: Диагностика | D5: Диагностика и дефектовка: Проверка механизма подъема (пружин или гидравлики), состояния аппарели и шарнирных соединений. | E5: =N5+O5 | F5: шт. | G5: =IFERROR('[1]Лист1'!G5,2) | H5: 2 | I5: 2 | J5: 2 | K5: 2 | L5: 2 | M5: 2 | N5: =Работы!S7 | O5: =Работы!R7 | P5: 2 | Q5: 2 | R5: 2 | S5: 2 | T5: 2 | U5: 2 | V5: 2 | W5: 2 | X5: 2 | Y5: 2 | Z5: 2 | AA5: 2
A6: Аварийные работы | B6: Ремонт откидных, перегрузочных мостов тип DoorHan или аналоги | C6: Восстановительные работы | D6: Восстановление шарниров: Замена осей крепления, шплинтов, втулок и очистка петель от загрязнений. | E6: =N6+O6 | F6: шт. | G6: =IFERROR('[1]Лист1'!G6,20) | H6: 20 | I6: 20 | J6: 20 | K6: 20 | L6: 20 | M6: 20 | N6: =Работы!S8 | O6: =Работы!R8 | P6: 20 | Q6: 20 | R6: 20 | S6: 20 | T6: 20 | U6: 20 | V6: 20 | W6: 20 | X6: 20 | Y6: 20 | Z6: 20 | AA6: 20
A7: Аварийные работы | B7: Ремонт откидных, перегрузочных мостов тип DoorHan или аналоги | C7: Сварочные работы | D7: Сварочные работы, усиление или замена листов с противоскользящим покрытием. | E7: =N7+O7 | F7: шт. | G7: =IFERROR('[1]Лист1'!G7,20) | H7: 20 | I7: 20 | J7: 20 | K7: 20 | L7: 20 | M7: 20 | N7: =Работы!S9 | O7: =Работы!R9 | P7: 20 | Q7: 20 | R7: 20 | S7: 20 | T7: 20 | U7: 20 | V7: 20 | W7: 20 | X7: 20 | Y7: 20 | Z7: 20 | AA7: 20
A8: Аварийные работы | B8: Ремонт откидных, перегрузочных мостов тип DoorHan или аналоги | C8: Замена | D8: Замена пружин для плавного опускания/поднятия. | E8: =N8+O8 | F8: шт. | G8: =IFERROR('[1]Лист1'!G8,20) | H8: 20 | I8: 20 | J8: 20 | K8: 20 | L8: 20 | M8: 20 | N8: =Работы!S10 | O8: =Работы!R10 | P8: 20 | Q8: 20 | R8: 20 | S8: 20 | T8: 20 | U8: 20 | V8: 20 | W8: 20 | X8: 20 | Y8: 20 | Z8: 20 | AA8: 20
A9: Аварийные работы | B9: Ремонт откидных, перегрузочных мостов тип DoorHan или аналоги | C9: Демонтажные работы | D9: Демонтажные работы, включая резку. | E9: =N9+O9 | F9: шт. | G9: =IFERROR('[1]Лист1'!G9,20) | H9: 20 | I9: 20 | J9: 20 | K9: 20 | L9: 20 | M9: 20 | N9: =Работы!S11 | O9: =Работы!R11 | P9: 20 | Q9: 20 | R9: 20 | S9: 20 | T9: 20 | U9: 20 | V9: 20 | W9: 20 | X9: 20 | Y9: 20 | Z9: 20 | AA9: 20
A10: Аварийные работы | B10: Ремонт сантехнического оборудования | C10: Замена | D10: Замена арматуры сливного бачка типа «Компакт» (включая материалы и з/части) | E10: =N10+O10 | F10: шт. | G10: =IFERROR('[1]Лист1'!G10,20) | H10: 20 | I10: 20 | J10: 20 | K10: 20 | L10: 20 | M10: 20 | N10: =Работы!S12 | O10: =Работы!R12 | P10: 20 | Q10: 20 | R10: 20 | S10: 20 | T10: 20 | U10: 20 | V10: 20 | W10: 20 | X10: 20 | Y10: 20 | Z10: 20 | AA10: 20
A11: Аварийные работы | B11: Ремонт сантехнического оборудования | C11: Замена | D11: Замена сливного бачка унитаза типа «Компакт» (включая материалы и з/части) | E11: =N11+O11 | F11: шт. | G11: =IFERROR('[1]Лист1'!G11,20) | H11: 20 | I11: 20 | J11: 20 | K11: 20 | L11: 20 | M11: 20 | N11: =Работы!S13 | O11: =Работы!R13 | P11: 20 | Q11: 20 | R11: 20 | S11: 20 | T11: 20 | U11: 20 | V11: 20 | W11: 20 | X11: 20 | Y11: 20 | Z11: 20 | AA11: 20
A12: Аварийные работы | B12: Ремонт сантехнического оборудования | C12: Замена | D12: Замена унитаза типа «Компакт» (включая материалы и з/части) | E12: =N12+O12 | F12: шт. | G12: =IFERROR('[1]Лист1'!G12,20) | H12: 20 | I12: 20 | J12: 20 | K12: 20 | L12: 20 | M12: 20 | N12: =Работы!S14 | O12: =Работы!R14 | P12: 20 | Q12: 20 | R12: 20 | S12: 20 | T12: 20 | U12: 20 | V12: 20 | W12: 20 | X12: 20 | Y12: 20 | Z12: 20 | AA12: 20
A13: Аварийные работы | B13: Ремонт сантехнического оборудования | C13: Замена | D13: Замена гибкой подводки сантехнической до 60 см (включая материалы и з/части) | E13: =N13+O13 | F13: шт. | G13: =IFERROR('[1]Лист1'!G13,20) | H13: 20 | I13: 20 | J13: 20 | K13: 20 | L13: 20 | M13: 20 | N13: =Работы!S15 | O13: =Работы!R15 | P13: 20 | Q13: 20 | R13: 20 | S13: 20 | T13: 20 | U13: 20 | V13: 20 | W13: 20 | X13: 20 | Y13: 20 | Z13: 20 | AA13: 20
A14: Аварийные работы | B14: Ремонт сантехнического оборудования | C14: Замена | D14: Замена смесителя раковины (включая материалы и з/части) | E14: =N14+O14 | F14: шт. | G14: =IFERROR('[1]Лист1'!G14,20) | H14: 20 | I14: 20 | J14: 20 | K14: 20 | L14: 20 | M14: 20 | N14: =Работы!S16 | O14: =Работы!R16 | P14: 20 | Q14: 20 | R14: 20 | S14: 20 | T14: 20 | U14: 20 | V14: 20 | W14: 20 | X14: 20 | Y14: 20 | Z14: 20 | AA14: 20
A15: Аварийные работы | B15: Ремонт сантехнического оборудования | C15: Замена | D15: Замена раковины керамической с пьедесталом (включая материалы и з/части) | E15: =N15+O15 | F15: шт. | G15: =IFERROR('[1]Лист1'!G15,20) | H15: 20 | I15: 20 | J15: 20 | K15: 20 | L15: 20 | M15: 20 | N15: =Работы!S17 | O15: =Работы!R17 | P15: 20 | Q15: 20 | R15: 20 | S15: 20 | T15: 20 | U15: 20 | V15: 20 | W15: 20 | X15: 20 | Y15: 20 | Z15: 20 | AA15: 20
A16: Аварийные работы | B16: Ремонт сантехнического оборудования | C16: Замена | D16: Замена раковины металлической (включая материалы и з/части) | E16: =N16+O16 | F16: шт. | G16: =IFERROR('[1]Лист1'!G16,20) | H16: 20 | I16: 20 | J16: 20 | K16: 20 | L16: 20 | M16: 20 | N16: =Работы!S18 | O16: =Работы!R18 | P16: 20 | Q16: 20 | R16: 20 | S16: 20 | T16: 20 | U16: 20 | V16: 20 | W16: 20 | X16: 20 | Y16: 20 | Z16: 20 | AA16: 20
A17: Аварийные работы | B17: Ремонт сантехнического оборудования | C17: Замена | D17: Замена смесителя для ванны с душевой лейкой (включая материалы и з/части) | E17: =N17+O17 | F17: шт. | G17: =IFERROR('[1]Лист1'!G17,20) | H17: 20 | I17: 20 | J17: 20 | K17: 20 | L17: 20 | M17: 20 | N17: =Работы!S19 | O17: =Работы!R19 | P17: 20 | Q17: 20 | R17: 20 | S17: 20 | T17: 20 | U17: 20 | V17: 20 | W17: 20 | X17: 20 | Y17: 20 | Z17: 20 | AA17: 20
... A27: Аварийные работы | B27: Ремонт сантехнического оборудования | C27: Монтажные работы | D27: Подключение к системе ХВС, ГВС приборов (водонагреватель, кулер, пурифайр, стиральная машинка и т.д.) (включая материалы, комплектующие, фитинги, з/части и т.д.) за 1 ед. | E27: =N27+O27 | F27: шт. | G27: =IFERROR('[1]Лист1'!G27,20) | H27: 20 | I27: 20 | J27: 20 | K27: 20 | L27: 20 | M27: 20 | N27: =Работы!S29 | O27: =Работы!R29 | P27: 20 | Q27: 20 | R27: 20 | S27: 20 | T27: 20 | U27: 20 | V27: 20 | W27: 20 | X27: 20 | Y27: 20 | Z27: 20 | AA27: 20
A28: Аварийные работы | B28: Ремонт сантехнического оборудования | C28: Восстановительные работы | D28: Стоимость нормо-часа для работ, не вошедших в основной перечень | E28: =N28+O28 | F28: н/час | G28: =IFERROR('[1]Лист1'!G28,1) | H28: 1 | I28: 1 | J28: 1 | K28: 1 | L28: 1 | M28: 1 | N28: =Работы!S30 | O28: =Работы!R30 | P28: 1 | Q28: 1 | R28: 1 | S28: 1 | T28: 1 | U28: 1 | V28: 1 | W28: 1 | X28: 1 | Y28: 1 | Z28: 1 | AA28: 1
A29: Фасад | B29: Доборные и Фасонные элементы Кровли и Фасада | C29: Монтажные работы | D29: Планка примыкания верхняя, нижняя 150 х 250 с полимерным покрытием по RAL по согласованию | E29: =N29+O29 | F29: п.м | G29: =IFERROR('[1]Лист1'!G29,50) | H29: 50 | I29: 50 | J29: 50 | K29: 50 | L29: 50 | M29: 50 | N29: =Работы!S31 | O29: =Работы!R31 | P29: 50 | Q29: 50 | R29: 50 | S29: 50 | T29: 50 | U29: 50 | V29: 50 | W29: 50 | X29: 50 | Y29: 50 | Z29: 50 | AA29: 50
A30: Фасад | B30: Профлист окрашенный | C30: Монтажные работы | D30: Монтаж профлиста С8-115 - 0,50 окрашенный | E30: =N30+O30 | F30: м2 | G30: =IFERROR('[1]Лист1'!G30,50) | H30: 50 | I30: 50 | J30: 50 | K30: 50 | L30: 50 | M30: 50 | N30: =Работы!S32 | O30: =Работы!R32 | P30: 50 | Q30: 50 | R30: 50 | S30: 50 | T30: 50 | U30: 50 | V30: 50 | W30: 50 | X30: 50 | Y30: 50 | Z30: 50 | AA30: 50
A31: Фасад | B31: Профлист неокрашенный | C31: Монтажные работы | D31: Монтаж профлиста С8, 0,45мм | E31: =N31+O31 | F31: м2 | G31: =IFERROR('[1]Лист1'!G31,50) | H31: 50 | I31: 50 | J31: 50 | K31: 50 | L31: 50 | M31: 50 | N31: =Работы!S33 | O31: =Работы!R33 | P31: 50 | Q31: 50 | R31: 50 | S31: 50 | T31: 50 | U31: 50 | V31: 50 | W31: 50 | X31: 50 | Y31: 50 | Z31: 50 | AA31: 50
A32: Фасад | B32: Профлист неокрашенный | C32: Монтажные работы | D32: Монтаж профлиста С20, 0,45мм | E32: =N32+O32 | F32: м2 | G32: =IFERROR('[1]Лист1'!G32,50) | H32: 50 | I32: 50 | J32: 50 | K32: 50 | L32: 50 | M32: 50 | N32: =Работы!S34 | O32: =Работы!R34 | P32: 50 | Q32: 50 | R32: 50 | S32: 50 | T32: 50 | U32: 50 | V32: 50 | W32: 50 | X32: 50 | Y32: 50 | Z32: 50 | AA32: 50
A33: Главный вход | B33: Поручни | C33: Монтажные работы | D33: Поручни из нержавеющей стали ( с 3 ригелями ) | E33: =N33+O33 | F33: м.п. | G33: =IFERROR('[1]Лист1'!G33,50) | H33: 50 | I33: 50 | J33: 50 | K33: 50 | L33: 50 | M33: 50 | N33: =Работы!S35 | O33: =Работы!R35 | P33: 50 | Q33: 50 | R33: 50 | S33: 50 | T33: 50 | U33: 50 | V33: 50 | W33: 50 | X33: 50 | Y33: 50 | Z33: 50 | AA33: 50
A34: Главный вход | B34: Поручни | C34: Монтажные работы | D34: Поручни из нержавеющей стали ( с 2 ригелями, с двойным ) | E34: =N34+O34 | F34: м.п. | G34: =IFERROR('[1]Лист1'!G34,50) | H34: 50 | I34: 50 | J34: 50 | K34: 50 | L34: 50 | M34: 50 | N34: =Работы!S36 | O34: =Работы!R36 | P34: 50 | Q34: 50 | R34: 50 | S34: 50 | T34: 50 | U34: 50 | V34: 50 | W34: 50 | X34: 50 | Y34: 50 | Z34: 50 | AA34: 50
A35: Пол | B35: Плитка Керамогранит | C35: Монтажные работы | D35: Керамогранит 300х300х8 мм типа "Эстима" (цвет белый )RW-01 (вкл. За основу клей, грунтовку, затирку швов) | E35: =N35+O35 | F35: м2 | G35: =IFERROR('[1]Лист1'!G35,150) | H35: 150 | I35: 150 | J35: 150 | K35: 150 | L35: 150 | M35: 150 | N35: =Работы!S37 | O35: =Работы!R37 | P35: 150 | Q35: 150 | R35: 150 | S35: 150 | T35: 150 | U35: 150 | V35: 150 | W35: 150 | X35: 150 | Y35: 150 | Z35: 150 | AA35: 150
A36: Пол | B36: Плитка Керамогранит | C36: Монтажные работы | D36: Керамогранит 400х400х9 мм типа "Эстима" (цвет белый))RW-01 (вкл. За основу клей, грунтовку, затирку швов) | E36: =N36+O36 | F36: м2 | G36: =IFERROR('[1]Лист1'!G36,150) | H36: 150 | I36: 150 | J36: 150 | K36: 150 | L36: 150 | M36: 150 | N36: =Работы!S38 | O36: =Работы!R38 | P36: 150 | Q36: 150 | R36: 150 | S36: 150 | T36: 150 | U36: 150 | V36: 150 | W36: 150 | X36: 150 | Y36: 150 | Z36: 150 | AA36: 150
A37: Пол | B37: Плитка Керамогранит | C37: Монтажные работы | D37: Керамогранит 600х600х10 мм типа "Эстима" (цвет белый))RW-01 (вкл. За основу клей, грунтовку, затирку швов) | E37: =N37+O37 | F37: м2 | G37: =IFERROR('[1]Лист1'!G37,150) | H37: 150 | I37: 150 | J37: 150 | K37: 150 | L37: 150 | M37: 150 | N37: =Работы!S39 | O37: =Работы!R39 | P37: 150 | Q37: 150 | R37: 150 | S37: 150 | T37: 150 | U37: 150 | V37: 150 | W37: 150 | X37: 150 | Y37: 150 | Z37: 150 | AA37: 150
A38: Пол | B38: Плитка Керамогранит | C38: Монтажные работы | D38: Плитка керамогранита 200*200*12 мм типа "Эстима" (цвет-серый ) ST-101 (вкл. За основу клей, грунтовку, затирку швов) | E38: =N38+O38 | F38: м2 | G38: =IFERROR('[1]Лист1'!G38,150) | H38: 150 | I38: 150 | J38: 150 | K38: 150 | L38: 150 | M38: 150 | N38: =Работы!S40 | O38: =Работы!R40 | P38: 150 | Q38: 150 | R38: 150 | S38: 150 | T38: 150 | U38: 150 | V38: 150 | W38: 150 | X38: 150 | Y38: 150 | Z38: 150 | AA38: 150
A39: Пол | B39: Плитка Керамогранит | C39: Монтажные работы | D39: Плитка керамогранита 300*300*12 мм типа "Эстима" (цвет-серый ) ST-101 (вкл. За основу клей, грунтовку, затирку швов) | E39: =N39+O39 | F39: м2 | G39: =IFERROR('[1]Лист1'!G39,150) | H39: 150 | I39: 150 | J39: 150 | K39: 150 | L39: 150 | M39: 150 | N39: =Работы!S41 | O39: =Работы!R41 | P39: 150 | Q39: 150 | R39: 150 | S39: 150 | T39: 150 | U39: 150 | V39: 150 | W39: 150 | X39: 150 | Y39: 150 | Z39: 150 | AA39: 150
A40: Пол | B40: Плитка Керамогранит | C40: Монтажные работы | D40: Плитка керамогранита 300*300*8 мм типа "Эстима"(цвет-серый ) ST-03 (вкл. За основу клей, грунтовку, затирку швов) | E40: =N40+O40 | F40: м2 | G40: =IFERROR('[1]Лист1'!G40,150) | H40: 150 | I40: 150 | J40: 150 | K40: 150 | L40: 150 | M40: 150 | N40: =Работы!S42 | O40: =Работы!R42 | P40: 150 | Q40: 150 | R40: 150 | S40: 150 | T40: 150 | U40: 150 | V40: 150 | W40: 150 | X40: 150 | Y40: 150 | Z40: 150 | AA40: 150
A41: Пол | B41: Плитка Керамогранит | C41: Монтажные работы | D41: Плитка Керамогранит 400х400х9 мм типа "Эстима"(цвет-серый ) ST-03 (вкл. За основу клей, грунтовку, затирку швов) | E41: =N41+O41 | F41: м2 | G41: =IFERROR('[1]Лист1'!G41,150) | H41: 150 | I41: 150 | J41: 150 | K41: 150 | L41: 150 | M41: 150 | N41: =Работы!S43 | O41: =Работы!R43 | P41: 150 | Q41: 150 | R41: 150 | S41: 150 | T41: 150 | U41: 150 | V41: 150 | W41: 150 | X41: 150 | Y41: 150 | Z41: 150 | AA41: 150
A42: Пол | B42: Плитка Керамогранит | C42: Монтажные работы | D42: Плитка керамогранита 600*600*10 мм типа "Эстима"(цвет-серый ) ST-03 (вкл. За основу клей, грунтовку, затирку швов) | E42: =N42+O42 | F42: м2 | G42: =IFERROR('[1]Лист1'!G42,150) | H42: 150 | I42: 150 | J42: 150 | K42: 150 | L42: 150 | M42: 150 | N42: =Работы!S44 | O42: =Работы!R44 | P42: 150 | Q42: 150 | R42: 150 | S42: 150 | T42: 150 | U42: 150 | V42: 150 | W42: 150 | X42: 150 | Y42: 150 | Z42: 150 | AA42: 150
A43: Пол | B43: Плитка Керамогранит | C43: Монтажные работы | D43: Керамогранит для пола 200х200х12 мм (полосы, PEI 4) глазурованный (полосатая) (вкл. За основу клей, грунтовку, затирку швов) | E43: =N43+O43 | F43: м2 | G43: =IFERROR('[1]Лист1'!G43,150) | H43: 150 | I43: 150 | J43: 150 | K43: 150 | L43: 150 | M43: 150 | N43: =Работы!S45 | O43: =Работы!R45 | P43: 150 | Q43: 150 | R43: 150 | S43: 150 | T43: 150 | U43: 150 | V43: 150 | W43: 150 | X43: 150 | Y43: 150 | Z43: 150 | AA43: 150
A44: Пол | B44: Плитка | C44: Монтажные работы | D44: Керамогранит Техногрес 300х300х12мм соль-перец | E44: =N44+O44 | F44: м2 | G44: =IFERROR('[1]Лист1'!G44,150) | H44: 150 | I44: 150 | J44: 150 | K44: 150 | L44: 150 | M44: 150 | N44: =Работы!S46 | O44: =Работы!R46 | P44: 150 | Q44: 150 | R44: 150 | S44: 150 | T44: 150 | U44: 150 | V44: 150 | W44: 150 | X44: 150 | Y44: 150 | Z44: 150 | AA44: 150
A45: Пол | B45: Прочее | C45: Монтажные работы | D45: Плинтус напольный пластиковый 55 x 22 мм типа "Идеал" с кабель каналом | E45: =N45+O45 | F45: м.п. | G45: =IFERROR('[1]Лист1'!G45,300) | H45: 300 | I45: 300 | J45: 300 | K45: 300 | L45: 300 | M45: 300 | N45: =Работы!S47 | O45: =Работы!R47 | P45: 300 | Q45: 300 | R45: 300 | S45: 300 | T45: 300 | U45: 300 | V45: 300 | W45: 300 | X45: 300 | Y45: 300 | Z45: 300 | AA45: 300
A46: Пол | B46: Прочее | C46: Монтажные работы | D46: Линолеум коммерческий толщиной не менее 2 мм (типа "Tarket" серии "Optima") | E46: =N46+O46 | F46: м2 | G46: =IFERROR('[1]Лист1'!G46,500) | H46: 500 | I46: 500 | J46: 500 | K46: 500 | L46: 500 | M46: 500 | N46: =Работы!S48 | O46: =Работы!R48 | P46: 500 | Q46: 500 | R46: 500 | S46: 500 | T46: 500 | U46: 500 | V46: 500 | W46: 500 | X46: 500 | Y46: 500 | Z46: 500 | AA46: 500
A47: Пол | B47: Прочее | C47: Монтажные работы | D47: Текстура: гладкая типа Апельсиновая корка. Цвет: RAL 7040 | E47: =N47+O47 | F47: м2 | G47: =IFERROR('[1]Лист1'!G47,500) | H47: 500 | I47: 500 | J47: 500 | K47: 500 | L47: 500 | M47: 500 | N47: =Работы!S49 | O47: =Работы!R49 | P47: 500 | Q47: 500 | R47: 500 | S47: 500 | T47: 500 | U47: 500 | V47: 500 | W47: 500 | X47: 500 | Y47: 500 | Z47: 500 | AA47: 500
A48: Пол | B48: Прочее | C48: Монтажные работы | D48: Противоскользящие полосы | E48: =N48+O48 | F48: м.п. | G48: =IFERROR('[1]Лист1'!G48,500) | H48: 500 | I48: 500 | J48: 500 | K48: 500 | L48: 500 | M48: 500 | N48: =Работы!S50 | O48: =Работы!R50 | P48: 500 | Q48: 500 | R48: 500 | S48: 500 | T48: 500 | U48: 500 | V48: 500 | W48: 500 | X48: 500 | Y48: 500 | Z48: 500 | AA48: 500
A49: Потолок | B49: Подвесные потолки | C49: Монтажные работы | D49: Подвесной потолок типа "ARMSTRONG"(комплект) | E49: =N49+O49 | F49: м2 | G49: =IFERROR('[1]Лист1'!G49,500) | H49: 500 | I49: 500 | J49: 500 | K49: 500 | L49: 500 | M49: 500 | N49: =Работы!S51 | O49: =Работы!R51 | P49: 500 | Q49: 500 | R49: 500 | S49: 500 | T49: 500 | U49: 500 | V49: 500 | W49: 500 | X49: 500 | Y49: 500 | Z49: 500 | AA49: 500
A50: Стена | B50: Покрытие стен | C50: Монтажные работы | D50: Профильный материал для панели ЛГКЛ, направляющие, алюмин. профили ОМЕГА (вкл. крепежные элементы) | E50: =N50+O50 | F50: м2 | G50: =IFERROR('[1]Лист1'!G50,500) | H50: 500 | I50: 500 | J50: 500 | K50: 500 | L50: 500 | M50: 500 | N50: =Работы!S52 | O50: =Работы!R52 | P50: 500 | Q50: 500 | R50: 500 | S50: 500 | T50: 500 | U50: 500 | V50: 500 | W50: 500 | X50: 500 | Y50: 500 | Z50: 500 | AA50: 500
A51: Стена | B51: Покрытие стен | C51: Монтажные работы | D51: Панель ЛГКЛ (цвет RAL 6019, фактура «шагрень» или аналог) типа GYPROC (толщина 12,5 мм) | E51: =N51+O51 | F51: м2 | G51: =IFERROR('[1]Лист1'!G51,200) | H51: 200 | I51: 200 | J51: 200 | K51: 200 | L51: 200 | M51: 200 | N51: =Работы!S53 | O51: =Работы!R53 | P51: 200 | Q51: 200 | R51: 200 | S51: 200 | T51: 200 | U51: 200 | V51: 200 | W51: 200 | X51: 200 | Y51: 200 | Z51: 200 | AA51: 200
A52: Стена | B52: Покрытие стен | C52: Монтажные работы | D52: Кафельная настенная плитка Kerama Marazzi 200x200 ( цвет-белый) (вкл. За основу клей, грунтовку, затирку швов) | E52: =N52+O52 | F52: м2 | G52: =IFERROR('[1]Лист1'!G52,50) | H52: 50 | I52: 50 | J52: 50 | K52: 50 | L52: 50 | M52: 50 | N52: =Работы!S54 | O52: =Работы!R54 | P52: 50 | Q52: 50 | R52: 50 | S52: 50 | T52: 50 | U52: 50 | V52: 50 | W52: 50 | X52: 50 | Y52: 50 | Z52: 50 | AA52: 50
A53: Стена | B53: Кафельная плитка | C53: Монтажные работы | D53: Кафельная настенная плитка Kerama Marazzi 200x300 ( цвет-белый) (вкл. За основу клей, грунтовку, затирку швов) | E53: =N53+O53 | F53: м2 | G53: =IFERROR('[1]Лист1'!G53,50) | H53: 50 | I53: 50 | J53: 50 | K53: 50 | L53: 50 | M53: 50 | N53: =Работы!S55 | O53: =Работы!R55 | P53: 50 | Q53: 50 | R53: 50 | S53: 50 | T53: 50 | U53: 50 | V53: 50 | W53: 50 | X53: 50 | Y53: 50 | Z53: 50 | AA53: 50
A54: Стена | B54: Кафельная плитка | C54: Монтажные работы | D54: Кафельная настенная плитка Kerama Marazzi 200x200 (оранжевый) (вкл. За основу клей, грунтовку, затирку швов) | E54: =N54+O54 | F54: м2 | G54: =IFERROR('[1]Лист1'!G54,50) | H54: 50 | I54: 50 | J54: 50 | K54: 50 | L54: 50 | M54: 50 | N54: =Работы!S56 | O54: =Работы!R56 | P54: 50 | Q54: 50 | R54: 50 | S54: 50 | T54: 50 | U54: 50 | V54: 50 | W54: 50 | X54: 50 | Y54: 50 | Z54: 50 | AA54: 50
A55: Стена | B55: Кафельная плитка | C55: Монтажные работы | D55: Кафельная настенная плитка 200x200 (цвет серый, RAL ) (вкл. За основу клей, грунтовку, затирку швов белого цвета) | E55: =N55+O55 | F55: м2 | G55: =IFERROR('[1]Лист1'!G55,50) | H55: 50 | I55: 50 | J55: 50 | K55: 50 | L55: 50 | M55: 50 | N55: =Работы!S57 | O55: =Работы!R57 | P55: 50 | Q55: 50 | R55: 50 | S55: 50 | T55: 50 | U55: 50 | V55: 50 | W55: 50 | X55: 50 | Y55: 50 | Z55: 50 | AA55: 50
A56: Стена | B56: Сэндвич панель | C56: Монтажные работы | D56: Сэндвич панель толщина 120 мм (ППУ) или аналог | E56: =N56+O56 | F56: м2 | G56: =IFERROR('[1]Лист1'!G56,100) | H56: 100 | I56: 100 | J56: 100 | K56: 100 | L56: 100 | M56: 100 | N56: =Работы!S58 | O56: =Работы!R58 | P56: 100 | Q56: 100 | R56: 100 | S56: 100 | T56: 100 | U56: 100 | V56: 100 | W56: 100 | X56: 100 | Y56: 100 | Z56: 100 | AA56: 100
A57: Стена | B57: Сэндвич панель | C57: Монтажные работы | D57: Сендвич-панель стеновая ППУ (ПИР) 100мм или аналог | E57: =N57+O57 | F57: м2 | G57: =IFERROR('[1]Лист1'!G57,100) | H57: 100 | I57: 100 | J57: 100 | K57: 100 | L57: 100 | M57: 100 | N57: =Работы!S59 | O57: =Работы!R59 | P57: 100 | Q57: 100 | R57: 100 | S57: 100 | T57: 100 | U57: 100 | V57: 100 | W57: 100 | X57: 100 | Y57: 100 | Z57: 100 | AA57: 100
A58: Стена | B58: Сэндвич панель | C58: Монтажные работы | D58: Сэндвич панели стеновые | толщина 80 мм | базальтовые, трехслойные металлические, негорючие (огнестойкость по ei - 45)/ или аналог | E58: =N58+O58 | F58: м2 | G58: =IFERROR('[1]Лист1'!G58,100) | H58: 100 | I58: 100 | J58: 100 | K58: 100 | L58: 100 | M58: 100 | N58: =Работы!S60 | O58: =Работы!R60 | P58: 100 | Q58: 100 | R58: 100 | S58: 100 | T58: 100 | U58: 100 | V58: 100 | W58: 100 | X58: 100 | Y58: 100 | Z58: 100 | AA58: 100
A59: Стена | B59: Гипсокартон | C59: Монтажные работы | D59: Профильный материал для гипсокартона, направляющие (вкл. крепежные элементы) | E59: =N59+O59 | F59: м2 | G59: =IFERROR('[1]Лист1'!G59,100) | H59: 100 | I59: 100 | J59: 100 | K59: 100 | L59: 100 | M59: 100 | N59: =Работы!S61 | O59: =Работы!R61 | P59: 100 | Q59: 100 | R59: 100 | S59: 100 | T59: 100 | U59: 100 | V59: 100 | W59: 100 | X59: 100 | Y59: 100 | Z59: 100 | AA59: 100
A60: Стена | B60: Гипсокартон | C60: Монтажные работы | D60: Гипсокартон ГКЛВ (влагостойкий гипсокартон) типа Knauf (толщина 10мм) | E60: =N60+O60 | F60: м2 | G60: =IFERROR('[1]Лист1'!G60,100) | H60: 100 | I60: 100 | J60: 100 | K60: 100 | L60: 100 | M60: 100 | N60: =Работы!S62 | O60: =Работы!R62 | P60: 100 | Q60: 100 | R60: 100 | S60: 100 | T60: 100 | U60: 100 | V60: 100 | W60: 100 | X60: 100 | Y60: 100 | Z60: 100 | AA60: 100
A61: Стена | B61: Гипсокартон | C61: Монтажные работы | D61: Гипсокартон ГКЛ (обычный гипсокартон) типа Knauf (толщина 10мм) | E61: =N61+O61 | F61: м2 | G61: =IFERROR('[1]Лист1'!G61,100) | H61: 100 | I61: 100 | J61: 100 | K61: 100 | L61: 100 | M61: 100 | N61: =Работы!S63 | O61: =Работы!R63 | P61: 100 | Q61: 100 | R61: 100 | S61: 100 | T61: 100 | U61: 100 | V61: 100 | W61: 100 | X61: 100 | Y61: 100 | Z61: 100 | AA61: 100
A62: Стена | B62: Гипсокартон | C62: Монтажные работы | D62: профиль для монтажа гипсокартона ПН 50х40 (вкл. крепежные элементы) | E62: =N62+O62 | F62: м.п. | G62: =IFERROR('[1]Лист1'!G62,100) | H62: 100 | I62: 100 | J62: 100 | K62: 100 | L62: 100 | M62: 100 | N62: =Работы!S64 | O62: =Работы!R64 | P62: 100 | Q62: 100 | R62: 100 | S62: 100 | T62: 100 | U62: 100 | V62: 100 | W62: 100 | X62: 100 | Y62: 100 | Z62: 100 | AA62: 100
A63: Стена | B63: Гипсокартон | C63: Монтажные работы | D63: профиль для монтажа гипсокартона ПС 50х50 (вкл. крепежные элементы) | E63: =N63+O63 | F63: м.п. | G63: =IFERROR('[1]Лист1'!G63,100) | H63: 100 | I63: 100 | J63: 100 | K63: 100 | L63: 100 | M63: 100 | N63: =Работы!S65 | O63: =Работы!R65 | P63: 100 | Q63: 100 | R63: 100 | S63: 100 | T63: 100 | U63: 100 | V63: 100 | W63: 100 | X63: 100 | Y63: 100 | Z63: 100 | AA63: 100
A64: Стена | B64: Краска | C64: Малярные работы | D64: Краска-эмаль типа Хамерайт (цвет по выбору) в 2 слоя | E64: =N64+O64 | F64: м2 | G64: =IFERROR('[1]Лист1'!G64,100) | H64: 100 | I64: 100 | J64: 100 | K64: 100 | L64: 100 | M64: 100 | N64: =Работы!S66 | O64: =Работы!R66 | P64: 100 | Q64: 100 | R64: 100 | S64: 100 | T64: 100 | U64: 100 | V64: 100 | W64: 100 | X64: 100 | Y64: 100 | Z64: 100 | AA64: 100
A65: Стена | B65: Краска | C65: Малярные работы | D65: Краска водоэмульсионная типа Dufa Mattlatex Russia (цвет по выбору) в 2 слоя | E65: =N65+O65 | F65: м2 | G65: =IFERROR('[1]Лист1'!G65,100) | H65: 100 | I65: 100 | J65: 100 | K65: 100 | L65: 100 | M65: 100 | N65: =Работы!S67 | O65: =Работы!R67 | P65: 100 | Q65: 100 | R65: 100 | S65: 100 | T65: 100 | U65: 100 | V65: 100 | W65: 100 | X65: 100 | Y65: 100 | Z65: 100 | AA65: 100
A66: Стена | B66: Краска | C66: Малярные работы | D66: Краска водоэмульсионная наружная типа Dufa Fassadenfarbe (цвет по выбору) в 2 слоя. | E66: =N66+O66 | F66: м2 | G66: =IFERROR('[1]Лист1'!G66,100) | H66: 100 | I66: 100 | J66: 100 | K66: 100 | L66: 100 | M66: 100 | N66: =Работы!S68 | O66: =Работы!R68 | P66: 100 | Q66: 100 | R66: 100 | S66: 100 | T66: 100 | U66: 100 | V66: 100 | W66: 100 | X66: 100 | Y66: 100 | Z66: 100 | AA66: 100
A67: Стена | B67: Отделочные материалы | C67: Штукатурные работы | D67: Штукатурка наружная типа "KNAUF sockelputz" | E67: =N67+O67 | F67: м2 | G67: =IFERROR('[1]Лист1'!G67,100) | H67: 100 | I67: 100 | J67: 100 | K67: 100 | L67: 100 | M67: 100 | N67: =Работы!S69 | O67: =Работы!R69 | P67: 100 | Q67: 100 | R67: 100 | S67: 100 | T67: 100 | U67: 100 | V67: 100 | W67: 100 | X67: 100 | Y67: 100 | Z67: 100 | AA67: 100
... A185: Металлоконструкци и | B185: 3D ограждения металлического сетчатого | C185: Монтажные работы | D185: Столб 60х40х1,4х2500 RAL 6005 5 отверстийМ6 (1,53/1,73/2,03) или аналог. | E185: =N185+O185 | F185: шт | G185: =IFERROR('[1]Лист1'!G185,100) | H185: 100 | I185: 100 | J185: 100 | K185: 100 | L185: 100 | M185: 100 | N185: =Работы!S187 | O185: =Работы!R187 | P185: 100 | Q185: 100 | R185: 100 | S185: 100 | T185: 100 | U185: 100 | V185: 100 | W185: 100 | X185: 100 | Y185: 100 | Z185: 100 | AA185: 100
A186: Электрика | B186: Кабель ВВГнг | C186: Электромонтажные работы | D186: Кабель ВВГ нг(А) LS 5x6 мм.кв. | E186: =N186+O186 | F186: м.п. | G186: =IFERROR('[1]Лист1'!G186,200) | H186: 200 | I186: 200 | J186: 200 | K186: 200 | L186: 200 | M186: 200 | N186: =Работы!S188 | O186: =Работы!R188 | P186: 200 | Q186: 200 | R186: 200 | S186: 200 | T186: 200 | U186: 200 | V186: 200 | W186: 200 | X186: 200 | Y186: 200 | Z186: 200 | AA186: 200
A187: Электрика | B187: Кабель ВВГнг | C187: Электромонтажные работы | D187: Кабель КВВГ нг(А) LS 5x2,5 мм.кв. | E187: =N187+O187 | F187: м.п. | G187: =IFERROR('[1]Лист1'!G187,200) | H187: 200 | I187: 200 | J187: 200 | K187: 200 | L187: 200 | M187: 200 | N187: =Работы!S189 | O187: =Работы!R189 | P187: 200 | Q187: 200 | R187: 200 | S187: 200 | T187: 200 | U187: 200 | V187: 200 | W187: 200 | X187: 200 | Y187: 200 | Z187: 200 | AA187: 200
A188: Электрика | B188: Кабель ВВГнг | C188: Электромонтажные работы | D188: Кабель нагревательный саморегулирующийся 30КСТМ2-Т | E188: =N188+O188 | F188: м.п. | G188: =IFERROR('[1]Лист1'!G188,200) | H188: 200 | I188: 200 | J188: 200 | K188: 200 | L188: 200 | M188: 200 | N188: =Работы!S190 | O188: =Работы!R190 | P188: 200 | Q188: 200 | R188: 200 | S188: 200 | T188: 200 | U188: 200 | V188: 200 | W188: 200 | X188: 200 | Y188: 200 | Z188: 200 | AA188: 200
A189: Электрика | B189: Кабель АВВГ | C189: Электромонтажные работы | D189: СИП-2 -0,6/1 3х 16 + 1х25 кабель | E189: =N189+O189 | F189: м.п. | G189: =IFERROR('[1]Лист1'!G189,200) | H189: 200 | I189: 200 | J189: 200 | K189: 200 | L189: 200 | M189: 200 | N189: =Работы!S191 | O189: =Работы!R191 | P189: 200 | Q189: 200 | R189: 200 | S189: 200 | T189: 200 | U189: 200 | V189: 200 | W189: 200 | X189: 200 | Y189: 200 | Z189: 200 | AA189: 200
A190: Электрика | B190: Кабель АВВГ | C190: Электромонтажные работы | D190: СИП-2 -0,6/1 3х 25 + 1х35 кабель | E190: =N190+O190 | F190: м.п. | G190: =IFERROR('[1]Лист1'!G190,200) | H190: 200 | I190: 200 | J190: 200 | K190: 200 | L190: 200 | M190: 200 | N190: =Работы!S192 | O190: =Работы!R192 | P190: 200 | Q190: 200 | R190: 200 | S190: 200 | T190: 200 | U190: 200 | V190: 200 | W190: 200 | X190: 200 | Y190: 200 | Z190: 200 | AA190: 200
A191: Электрика | B191: Кабель АВВГ | C191: Электромонтажные работы | D191: СИП-2 -0,6/1 3х 35 + 1х54,6 кабель | E191: =N191+O191 | F191: м.п. | G191: =IFERROR('[1]Лист1'!G191,200) | H191: 200 | I191: 200 | J191: 200 | K191: 200 | L191: 200 | M191: 200 | N191: =Работы!S193 | O191: =Работы!R193 | P191: 200 | Q191: 200 | R191: 200 | S191: 200 | T191: 200 | U191: 200 | V191: 200 | W191: 200 | X191: 200 | Y191: 200 | Z191: 200 | AA191: 200
A192: Электрика | B192: Кабель АВВГ | C192: Электромонтажные работы | D192: СИП-2 -0,6/1 3х 50 + 1х54,6 кабель | E192: =N192+O192 | F192: м.п. | G192: =IFERROR('[1]Лист1'!G192,200) | H192: 200 | I192: 200 | J192: 200 | K192: 200 | L192: 200 | M192: 200 | N192: =Работы!S194 | O192: =Работы!R194 | P192: 200 | Q192: 200 | R192: 200 | S192: 200 | T192: 200 | U192: 200 | V192: 200 | W192: 200 | X192: 200 | Y192: 200 | Z192: 200 | AA192: 200
A193: Электрика | B193: Кабель АВВГ | C193: Электромонтажные работы | D193: СИП-2 -0,6/1 3х 70 + 1х54,6 кабель | E193: =N193+O193 | F193: м.п. | G193: =IFERROR('[1]Лист1'!G193,200) | H193: 200 | I193: 200 | J193: 200 | K193: 200 | L193: 200 | M193: 200 | N193: =Работы!S195 | O193: =Работы!R195 | P193: 200 | Q193: 200 | R193: 200 | S193: 200 | T193: 200 | U193: 200 | V193: 200 | W193: 200 | X193: 200 | Y193: 200 | Z193: 200 | AA193: 200
A194: Электрика | B194: Розетки | C194: Электромонтажные работы | D194: Розетка одинарная наружная 220В 16А | E194: =N194+O194 | F194: шт. | G194: =IFERROR('[1]Лист1'!G194,200) | H194: 200 | I194: 200 | J194: 200 | K194: 200 | L194: 200 | M194: 200 | N194: =Работы!S196 | O194: =Работы!R196 | P194: 200 | Q194: 200 | R194: 200 | S194: 200 | T194: 200 | U194: 200 | V194: 200 | W194: 200 | X194: 200 | Y194: 200 | Z194: 200 | AA194: 200
A195: Электрика | B195: Розетки | C195: Электромонтажные работы | D195: Розетка одинарная внутренняя 220В 16А | E195: =N195+O195 | F195: шт. | G195: =IFERROR('[1]Лист1'!G195,200) | H195: 200 | I195: 200 | J195: 200 | K195: 200 | L195: 200 | M195: 200 | N195: =Работы!S197 | O195: =Работы!R197 | P195: 200 | Q195: 200 | R195: 200 | S195: 200 | T195: 200 | U195: 200 | V195: 200 | W195: 200 | X195: 200 | Y195: 200 | Z195: 200 | AA195: 200
A196: Электрика | B196: Розетки | C196: Электромонтажные работы | D196: Розетка двойная наружная 220В 16А | E196: =N196+O196 | F196: шт. | G196: =IFERROR('[1]Лист1'!G196,200) | H196: 200 | I196: 200 | J196: 200 | K196: 200 | L196: 200 | M196: 200 | N196: =Работы!S198 | O196: =Работы!R198 | P196: 200 | Q196: 200 | R196: 200 | S196: 200 | T196: 200 | U196: 200 | V196: 200 | W196: 200 | X196: 200 | Y196: 200 | Z196: 200 | AA196: 200
A197: Электрика | B197: Розетки | C197: Электромонтажные работы | D197: Розетка двойная внутренняя 220В 16А | E197: =N197+O197 | F197: шт. | G197: =IFERROR('[1]Лист1'!G197,200) | H197: 200 | I197: 200 | J197: 200 | K197: 200 | L197: 200 | M197: 200 | N197: =Работы!S199 | O197: =Работы!R199 | P197: 200 | Q197: 200 | R197: 200 | S197: 200 | T197: 200 | U197: 200 | V197: 200 | W197: 200 | X197: 200 | Y197: 200 | Z197: 200 | AA197: 200
... A294: Электрика | B294: Труба ПНД | C294: Электромонтажные работы | D294: Труба ПНД Д-32 | E294: =N294+O294 | F294: м.п. | G294: =IFERROR('[1]Лист1'!G294,200) | H294: 200 | I294: 200 | J294: 200 | K294: 200 | L294: 200 | M294: 200 | N294: =Работы!S296 | O294: =Работы!R296 | P294: 200 | Q294: 200 | R294: 200 | S294: 200 | T294: 200 | U294: 200 | V294: 200 | W294: 200 | X294: 200 | Y294: 200 | Z294: 200 | AA294: 200
A295: Электрика | B295: Прочее | C295: Электромонтажные работы | D295: Нулевая шина медная/Шина Заземления | E295: =N295+O295 | F295: шт. | G295: =IFERROR('[1]Лист1'!G295,30) | H295: 30 | I295: 30 | J295: 30 | K295: 30 | L295: 30 | M295: 30 | N295: =Работы!S297 | O295: =Работы!R297 | P295: 30 | Q295: 30 | R295: 30 | S295: 30 | T295: 30 | U295: 30 | V295: 30 | W295: 30 | X295: 30 | Y295: 30 | Z295: 30 | AA295: 30
A296: Электрика | B296: Прочее | C296: Электромонтажные работы | D296: Держатели плавких вставок габарит 00 | E296: =N296+O296 | F296: шт. | G296: =IFERROR('[1]Лист1'!G296,30) | H296: 30 | I296: 30 | J296: 30 | K296: 30 | L296: 30 | M296: 30 | N296: =Работы!S298 | O296: =Работы!R298 | P296: 30 | Q296: 30 | R296: 30 | S296: 30 | T296: 30 | U296: 30 | V296: 30 | W296: 30 | X296: 30 | Y296: 30 | Z296: 30 | AA296: 30
A297: Электрика | B297: Прочее | C297: Электромонтажные работы | D297: Коробка распределительная 100х100х50 IP55 6 -вводов | E297: =N297+O297 | F297: шт. | G297: =IFERROR('[1]Лист1'!G297,30) | H297: 30 | I297: 30 | J297: 30 | K297: 30 | L297: 30 | M297: 30 | N297: =Работы!S299 | O297: =Работы!R299 | P297: 30 | Q297: 30 | R297: 30 | S297: 30 | T297: 30 | U297: 30 | V297: 30 | W297: 30 | X297: 30 | Y297: 30 | Z297: 30 | AA297: 30
A298: Электрика | B298: Прочее | C298: Электромонтажные работы | D298: Датчики движения н/в установки Steinel или аналог | E298: =N298+O298 | F298: шт. | G298: =IFERROR('[1]Лист1'!G298,30) | H298: 30 | I298: 30 | J298: 30 | K298: 30 | L298: 30 | M298: 30 | N298: =Работы!S300 | O298: =Работы!R300 | P298: 30 | Q298: 30 | R298: 30 | S298: 30 | T298: 30 | U298: 30 | V298: 30 | W298: 30 | X298: 30 | Y298: 30 | Z298: 30 | AA298: 30
A299: Электрика | B299: Прочее | C299: Электромонтажные работы | D299: Проведение приёмо-сдаточных испытаний (Технический отчёт о проведении испытаний электроустановки помещения) / услуга | E299: =N299+O299 | F299: шт. | G299: =IFERROR('[1]Лист1'!G299,30) | H299: 30 | I299: 30 | J299: 30 | K299: 30 | L299: 30 | M299: 30 | N299: =Работы!S301 | O299: =Работы!R301 | P299: 30 | Q299: 30 | R299: 30 | S299: 30 | T299: 30 | U299: 30 | V299: 30 | W299: 30 | X299: 30 | Y299: 30 | Z299: 30 | AA299: 30
A300: Электрика | B300: Прочее | C300: Электромонтажные работы | D300: Ламподержатель для Светильника 4*18 | E300: =N300+O300 | F300: шт. | G300: =IFERROR('[1]Лист1'!G300,30) | H300: 30 | I300: 30 | J300: 30 | K300: 30 | L300: 30 | M300: 30 | N300: =Работы!S302 | O300: =Работы!R302 | P300: 30 | Q300: 30 | R300: 30 | S300: 30 | T300: 30 | U300: 30 | V300: 30 | W300: 30 | X300: 30 | Y300: 30 | Z300: 30 | AA300: 30
A301: Электрика | B301: Прочее | C301: Электромонтажные работы | D301: TYCO/IEK Коробка распределительная 100х100х50мм откидная крышка 8 вводов IP54 | E301: =N301+O301 | F301: шт. | G301: =IFERROR('[1]Лист1'!G301,30) | H301: 30 | I301: 30 | J301: 30 | K301: 30 | L301: 30 | M301: 30 | N301: =Работы!S303 | O301: =Работы!R303 | P301: 30 | Q301: 30 | R301: 30 | S301: 30 | T301: 30 | U301: 30 | V301: 30 | W301: 30 | X301: 30 | Y301: 30 | Z301: 30 | AA301: 30
A302: Электрика | B302: Прочее | C302: Электромонтажные работы | D302: TYCO/IEK Коробка распределительная 85х85х50мм откидная крышка 8 вводов IP54 | E302: =N302+O302 | F302: шт. | G302: =IFERROR('[1]Лист1'!G302,30) | H302: 30 | I302: 30 | J302: 30 | K302: 30 | L302: 30 | M302: 30 | N302: =Работы!S304 | O302: =Работы!R304 | P302: 30 | Q302: 30 | R302: 30 | S302: 30 | T302: 30 | U302: 30 | V302: 30 | W302: 30 | X302: 30 | Y302: 30 | Z302: 30 | AA302: 30
A303: Электрика | B303: Прочее | C303: Электромонтажные работы | D303: TYCO|IEK Коробка распределительная 50х50х50мм откидная крышка IP54 | E303: =N303+O303 | F303: шт. | G303: =IFERROR('[1]Лист1'!G303,30) | H303: 30 | I303: 30 | J303: 30 | K303: 30 | L303: 30 | M303: 30 | N303: =Работы!S305 | O303: =Работы!R305 | P303: 30 | Q303: 30 | R303: 30 | S303: 30 | T303: 30 | U303: 30 | V303: 30 | W303: 30 | X303: 30 | Y303: 30 | Z303: 30 | AA303: 30
A304: Электрика | B304: Прочее | C304: Электромонтажные работы | D304: Патрон G13 для лампы освещения | E304: =N304+O304 | F304: шт. | G304: =IFERROR('[1]Лист1'!G304,30) | H304: 30 | I304: 30 | J304: 30 | K304: 30 | L304: 30 | M304: 30 | N304: =Работы!S306 | O304: =Работы!R306 | P304: 30 | Q304: 30 | R304: 30 | S304: 30 | T304: 30 | U304: 30 | V304: 30 | W304: 30 | X304: 30 | Y304: 30 | Z304: 30 | AA304: 30
A305: Электрика | B305: Прочее | C305: Электромонтажные работы | D305: Патрон E27 для лампы освещения | E305: =N305+O305 | F305: шт. | G305: =IFERROR('[1]Лист1'!G305,30) | H305: 30 | I305: 30 | J305: 30 | K305: 30 | L305: 30 | M305: 30 | N305: =Работы!S307 | O305: =Работы!R307 | P305: 30 | Q305: 30 | R305: 30 | S305: 30 | T305: 30 | U305: 30 | V305: 30 | W305: 30 | X305: 30 | Y305: 30 | Z305: 30 | AA305: 30
A306: Электрика | B306: Прочее | C306: Электромонтажные работы | D306: Муфта соединительная, тип Стп-10-150/240 | E306: =N306+O306 | F306: шт. | G306: =IFERROR('[1]Лист1'!G306,30) | H306: 30 | I306: 30 | J306: 30 | K306: 30 | L306: 30 | M306: 30 | N306: =Работы!S308 | O306: =Работы!R308 | P306: 30 | Q306: 30 | R306: 30 | S306: 30 | T306: 30 | U306: 30 | V306: 30 | W306: 30 | X306: 30 | Y306: 30 | Z306: 30 | AA306: 30
... A467: Водосток | B467: Услуги по кровли | C467: Монтажные работы | D467: Устройство подогрева воронок водосточных с ручных режимом включения (с учетом материалов) | E467: =N467+O467 | F467: шт. | G467: =IFERROR('[1]Лист1'!G467,30) | H467: 30 | I467: 30 | J467: 30 | K467: 30 | L467: 30 | M467: 30 | N467: =Работы!S469 | O467: =Работы!R469 | P467: 30 | Q467: 30 | R467: 30 | S467: 30 | T467: 30 | U467: 30 | V467: 30 | W467: 30 | X467: 30 | Y467: 30 | Z467: 30 | AA467: 30
A468: Услуги ассенизации | B468: Услуги ассенизации | C468: Монтажные работы | D468: Услуга по откачке ЖБО от 8 до 10 м3 (предоставление техники; сбор, вывоз и утилизация, в т.ч. ГСМ) | E468: =N468+O468 | F468: шт. | G468: =IFERROR('[1]Лист1'!G468,2) | H468: 2 | I468: 2 | J468: 2 | K468: 2 | L468: 2 | M468: 2 | N468: =Работы!S470 | O468: =Работы!R470 | P468: 2 | Q468: 2 | R468: 2 | S468: 2 | T468: 2 | U468: 2 | V468: 2 | W468: 2 | X468: 2 | Y468: 2 | Z468: 2 | AA468: 2
A469: Аренда спецтехники | B469: Аренда строительных лесов | C469: Аренда | D469: Строительные леса ЛРСП/ЛШ (вкл. сборку/разборку) применение при реконструкции фасада здания и в помещениях с высотой потолка более 5 м. | E469: =N469+O469 | F469: шт. | G469: =IFERROR('[1]Лист1'!G469,2) | H469: 2 | I469: 2 | J469: 2 | K469: 2 | L469: 2 | M469: 2 | N469: =Работы!S471 | O469: =Работы!R471 | P469: 2 | Q469: 2 | R469: 2 | S469: 2 | T469: 2 | U469: 2 | V469: 2 | W469: 2 | X469: 2 | Y469: 2 | Z469: 2 | AA469: 2
