Workbook

Sheet Как пользоваться
B1: РАСЦЕНКИ НЕОСТРОЙ — ПРАВИЛА РАБОТЫ ДЛЯ СОТРУДНИКОВ
B2: Версия от 23.10.2026. Все цены — только работа (без материалов и оборудования), руб. без НДС. Документ внутренний, заказчикам и бригадам не передаётся.
B3: 1. СМЕТЧИКИ И МЕНЕДЖЕРЫ: ЦЕНЫ В КП
B4: • В КП ставим «Цену в КП» с листа «Расценки» (голубые колонки) — СПб или Мск по месту объекта. Это наша базовая цена; ниже — только с согласования руководителя.
B5: • Материалы считаются отдельно, по счетам поставщиков.
B6: • Если заказчик просит ставку нормо-часа (ТО, аварийные и нерегламентные работы) — берём «Нормо-час для заказчика» с листа «Почасовка — ставки и план».
B7: • Позиции, подсвеченные оранжевым/красным в колонке «Цена в КП», стоят выше рынка (на 10–30 % и больше 30 %): мы их подняли, потому что на почасовке они убыточны. Если заказчик торгуется именно по ним — снижать можно только при условии, что работу берёт бригада в сделку по целевой цене.
B8: • Работы, которой нет в списке, — не придумывать цену: запрос сметчику.
B9: 2. ПРОРАБЫ И РУКОВОДИТЕЛИ ПРОЕКТОВ: СДЕЛКА С БРИГАДОЙ
B10: • «Сделка — цель» — цена за единицу, которую предлагаем бригаде (ИП или самозанятый), уже включая их налог 6 %. С неё начинаем переговоры.
B11: • «Сделка — потолок» (цель +15 %) — максимум, который можно согласовать самостоятельно. Выше потолка — только с письменного согласования руководителя.
B12: • Платим за принятый объём по акту (м², м, шт, т…), а не за выходы. Мусор, уборка и вынос в пределах рабочей зоны входят в цену.
... B29: Периодичность выплат бригадам/почасовикам: ____________________ · Форма договора: ИП / самозанятый, договор подряда · Кто подписывает акты: ____________________

Sheet Расценки
A1: РАСЦЕНКИ НЕОСТРОЙ: ЦЕНА В КП, СДЕЛКА С БРИГАДОЙ, ПОЧАСОВАЯ ОПЛАТА И ПЛАН
A2: Только работа, руб. без НДС. Колонки F, G, H, J, L — исходные данные из основного тарификатора (цена КП, цель сделки, норма); остальное считается формулами (подсказка формулы — в заголовке), параметры — лист «Параметры», ставки часа — лист «Почасовка — ставки и план».
F3: ЦЕНА В КП | H3: СДЕЛКА С БРИГАДОЙ (за единицу) | L3: ПОЧАСОВАЯ ОПЛАТА И ПЛАН (1 человек)
A4: Артикул | B4: Вид работ | C4: Ед. изм. | D4: Код | E4: Специальность (по коду) | F4: Цена в КП СПб (тарификатор) | G4: Цена в КП Мск (тарификатор) | H4: Сделка — цель СПб (тарификатор) | I4: Сделка — потолок СПб = цель × 1,15, не выше цены КП × 0,75 | J4: Сделка — цель Мск (тарификатор) | K4: Сделка — потолок Мск = цель × 1,15, не выше цены КП × 0,75 | L4: Норма, чел.-ч на ед. (тарификатор) | M4: План за 1 час, ед. = 1 ÷ норма | N4: План на смену, ед. = часы смены ÷ норма | O4: Ставка часа СПб, руб/ч (лист «Почасовка») | P4: Ставка часа Мск, руб/ч (лист «Почасовка») | Q4: Оплата за ед. по часам СПб = норма × ставка | R4: Как выгоднее отдать (СПб) оплата по часам vs цель сделки, ±10 %
A5: 1.1 Демонтаж зданий, строений, сооружений
A6: 1.1.1 | B6: Разборка покрытий и оснований асфальтобетонных | C6: м3 | D6: BLG | E6: =IFERROR(INDEX('Почасовка — ставки и план'!$B$5:$B$24,MATCH(D6,'Почасовка — ставки и план'!$A$5:$A$24,0)),"Аренда техники / механизмы") -> Дорожный рабочий / благоустройство | F6: 3500 | G6: 4025 | H6: 2100 | I6: =IF(OR(H6="",F6=""),"",MAX(H6,MIN(ROUND(H6*(1+Параметры!$B$5),IF(H6*(1+Параметры!$B$5)>=1000,-1,0)),ROUND(F6*Параметры!$B$6,IF(F6*Параметры!$B$6>=1000,-1,0))))) -> 2420 | J6: 2415 | K6: =IF(OR(J6="",G6=""),"",MAX(J6,MIN(ROUND(J6*(1+Параметры!$B$5),IF(J6*(1+Параметры!$B$5)>=1000,-1,0)),ROUND(G6*Параметры!$B$6,IF(G6*Параметры!$B$6>=1000,-1,0))))) -> 2780 | L6: 3.5 | M6: =IF(OR(L6="",L6=0),"",1/L6) -> 0.28571429 | N6: =IF(OR(L6="",L6=0),"",Параметры!$B$3/L6) -> 2.2857143 | O6: =IF(L6="","",IFERROR(INDEX('Почасовка — ставки и план'!$D$5:$D$24,MATCH($D6,'Почасовка — ставки и план'!$A$5:$A$24,0)),"")) -> 650 | P6: =IF(L6="","",IFERROR(INDEX('Почасовка — ставки и план'!$E$5:$E$24,MATCH($D6,'Почасовка — ставки и план'!$A$5:$A$24,0)),"")) -> 780 | Q6: =IF(OR(L6="",O6=""),"",ROUND(L6*O6,0)) -> 2275 | R6: =IF(D6="TEX","аренда техники — сделка/счёт",IF(OR(Q6="",H6="",H6=0),"—",IF(Q6<H6*(1-Параметры!$B$7),"почасовка",IF(Q6>H6*(1+Параметры!$B$7),"сделка","любой способ")))) -> любой способ | S6: 0 | T6: 0
A7: 1.1.2 | B7: Демонтаж деревянных зданий и строений без сохранения годного материала | C7: м3 здания | D7: RAZ | E7: =IFERROR(INDEX('Почасовка — ставки и план'!$B$5:$B$24,MATCH(D7,'Почасовка — ставки и план'!$A$5:$A$24,0)),"Аренда техники / механизмы") -> Разнорабочий / демонтажник | F7: 1000 | G7: 1300 | H7: 600 | I7: =IF(OR(H7="",F7=""),"",MAX(H7,MIN(ROUND(H7*(1+Параметры!$B$5),IF(H7*(1+Параметры!$B$5)>=1000,-1,0)),ROUND(F7*Параметры!$B$6,IF(F7*Параметры!$B$6>=1000,-1,0))))) -> 690 | J7: 768 | K7: =IF(OR(J7="",G7=""),"",MAX(J7,MIN(ROUND(J7*(1+Параметры!$B$5),IF(J7*(1+Параметры!$B$5)>=1000,-1,0)),ROUND(G7*Параметры!$B$6,IF(G7*Параметры!$B$6>=1000,-1,0))))) -> 883 | L7: 1.2 | M7: =IF(OR(L7="",L7=0),"",1/L7) -> 0.83333333 | N7: =IF(OR(L7="",L7=0),"",Параметры!$B$3/L7) -> 6.6666667 | O7: =IF(L7="","",IFERROR(INDEX('Почасовка — ставки и план'!$D$5:$D$24,MATCH($D7,'Почасовка — ставки и план'!$A$5:$A$24,0)),"")) -> 550 | P7: =IF(L7="","",IFERROR(INDEX('Почасовка — ставки и план'!$E$5:$E$24,MATCH($D7,'Почасовка — ставки и план'!$A$5:$A$24,0)),"")) -> 660 | Q7: =IF(OR(L7="",O7=""),"",ROUND(L7*O7,0)) -> 660 | R7: =IF(D7="TEX","аренда техники — сделка/счёт",IF(OR(Q7="",H7="",H7=0),"—",IF(Q7<H7*(1-Параметры!$B$7),"почасовка",IF(Q7>H7*(1+Параметры!$B$7),"сделка","любой способ")))) -> любой способ | S7: 0 | T7: 0
A8: 1.1.3 | B8: Демонтаж зданий и строений из металлоконструкций без сохранения годного материала | C8: т | D8: SVA | E8: =IFERROR(INDEX('Почасовка — ставки и план'!$B$5:$B$24,MATCH(D8,'Почасовка — ставки и план'!$A$5:$A$24,0)),"Аренда техники / механизмы") -> Сварщик / монтажник МК | F8: 12000 | G8: 14400 | H8: 3900 | I8: =IF(OR(H8="",F8=""),"",MAX(H8,MIN(ROUND(H8*(1+Параметры!$B$5),IF(H8*(1+Параметры!$B$5)>=1000,-1,0)),ROUND(F8*Параметры!$B$6,IF(F8*Параметры!$B$6>=1000,-1,0))))) -> 4490 | J8: 4485 | K8: =IF(OR(J8="",G8=""),"",MAX(J8,MIN(ROUND(J8*(1+Параметры!$B$5),IF(J8*(1+Параметры!$B$5)>=1000,-1,0)),ROUND(G8*Параметры!$B$6,IF(G8*Параметры!$B$6>=1000,-1,0))))) -> 5160 | L8: 10 | M8: =IF(OR(L8="",L8=0),"",1/L8) -> 0.1 | N8: =IF(OR(L8="",L8=0),"",Параметры!$B$3/L8) -> 0.8 | O8: =IF(L8="","",IFERROR(INDEX('Почасовка — ставки и план'!$D$5:$D$24,MATCH($D8,'Почасовка — ставки и план'!$A$5:$A$24,0)),"")) -> 900 | P8: =IF(L8="","",IFERROR(INDEX('Почасовка — ставки и план'!$E$5:$E$24,MATCH($D8,'Почасовка — ставки и план'!$A$5:$A$24,0)),"")) -> 1080 | Q8: =IF(OR(L8="",O8=""),"",ROUND(L8*O8,0)) -> 9000 | R8: =IF(D8="TEX","аренда техники — сделка/счёт",IF(OR(Q8="",H8="",H8=0),"—",IF(Q8<H8*(1-Параметры!$B$7),"почасовка",IF(Q8>H8*(1+Параметры!$B$7),"сделка","любой способ")))) -> сделка | S8: 0.84615385 | T8: 0.9264214
A9: 1.1.4 | B9: Демонтаж каменных зданий и строений (кирпич, бетон, железобетон) комплексная работа с сохранением годного материала | C9: м3 | D9: RAZ | E9: =IFERROR(INDEX('Почасовка — ставки и план'!$B$5:$B$24,MATCH(D9,'Почасовка — ставки и план'!$A$5:$A$24,0)),"Аренда техники / механизмы") -> Разнорабочий / демонтажник | F9: 4767 | G9: 5720 | H9: 2500 | I9: =IF(OR(H9="",F9=""),"",MAX(H9,MIN(ROUND(H9*(1+Параметры!$B$5),IF(H9*(1+Параметры!$B$5)>=1000,-1,0)),ROUND(F9*Параметры!$B$6,IF(F9*Параметры!$B$6>=1000,-1,0))))) -> 2880 | J9: 2875 | K9: =IF(OR(J9="",G9=""),"",MAX(J9,MIN(ROUND(J9*(1+Параметры!$B$5),IF(J9*(1+Параметры!$B$5)>=1000,-1,0)),ROUND(G9*Параметры!$B$6,IF(G9*Параметры!$B$6>=1000,-1,0))))) -> 3310 | L9: 6.5 | M9: =IF(OR(L9="",L9=0),"",1/L9) -> 0.15384615 | N9: =IF(OR(L9="",L9=0),"",Параметры!$B$3/L9) -> 1.2307692 | O9: =IF(L9="","",IFERROR(INDEX('Почасовка — ставки и план'!$D$5:$D$24,MATCH($D9,'Почасовка — ставки и план'!$A$5:$A$24,0)),"")) -> 550 | P9: =IF(L9="","",IFERROR(INDEX('Почасовка — ставки и план'!$E$5:$E$24,MATCH($D9,'Почасовка — ставки и план'!$A$5:$A$24,0)),"")) -> 660 | Q9: =IF(OR(L9="",O9=""),"",ROUND(L9*O9,0)) -> 3575 | R9: =IF(D9="TEX","аренда техники — сделка/счёт",IF(OR(Q9="",H9="",H9=0),"—",IF(Q9<H9*(1-Параметры!$B$7),"почасовка",IF(Q9>H9*(1+Параметры!$B$7),"сделка","любой способ")))) -> сделка | S9: 0.135 | T9: 0.18426501
A10: 1.1.5 | B10: Разборка бортовых камней с сохранением камня пригодного для дальнейшего использования | C10: мп | D10: BLG | E10: =IFERROR(INDEX('Почасовка — ставки и план'!$B$5:$B$24,MATCH(D10,'Почасовка — ставки и план'!$A$5:$A$24,0)),"Аренда техники / механизмы") -> Дорожный рабочий / благоустройство | F10: 350 | G10: 402 | H10: 200 | I10: =IF(OR(H10="",F10=""),"",MAX(H10,MIN(ROUND(H10*(1+Параметры!$B$5),IF(H10*(1+Параметры!$B$5)>=1000,-1,0)),ROUND(F10*Параметры!$B$6,IF(F10*Параметры!$B$6>=1000,-1,0))))) -> 230 | J10: 230 | K10: =IF(OR(J10="",G10=""),"",MAX(J10,MIN(ROUND(J10*(1+Параметры!$B$5),IF(J10*(1+Параметры!$B$5)>=1000,-1,0)),ROUND(G10*Параметры!$B$6,IF(G10*Параметры!$B$6>=1000,-1,0))))) -> 265 | L10: 0.35 | M10: =IF(OR(L10="",L10=0),"",1/L10) -> 2.8571429 | N10: =IF(OR(L10="",L10=0),"",Параметры!$B$3/L10) -> 22.857143 | O10: =IF(L10="","",IFERROR(INDEX('Почасовка — ставки и план'!$D$5:$D$24,MATCH($D10,'Почасовка — ставки и план'!$A$5:$A$24,0)),"")) -> 650 | P10: =IF(L10="","",IFERROR(INDEX('Почасовка — ставки и план'!$E$5:$E$24,MATCH($D10,'Почасовка — ставки и план'!$A$5:$A$24,0)),"")) -> 780 | Q10: =IF(OR(L10="",O10=""),"",ROUND(L10*O10,0)) -> 228 | R10: =IF(D10="TEX","аренда техники — сделка/счёт",IF(OR(Q10="",H10="",H10=0),"—",IF(Q10<H10*(1-Параметры!$B$7),"почасовка",IF(Q10>H10*(1+Параметры!$B$7),"сделка","любой способ")))) -> сделка | S10: 0 | T10: 0
A11: 1.1.6 | B11: Разборка тротуаров и дорожек из плит бетонных, брусчатки с сохранением пригодных для дальнейшего использования | C11: м2 | D11: BLG | E11: =IFERROR(INDEX('Почасовка — ставки и план'!$B$5:$B$24,MATCH(D11,'Почасовка — ставки и план'!$A$5:$A$24,0)),"Аренда техники / механизмы") -> Дорожный рабочий / благоустройство | F11: 260 | G11: 312 | H11: 150 | I11: =IF(OR(H11="",F11=""),"",MAX(H11,MIN(ROUND(H11*(1+Параметры!$B$5),IF(H11*(1+Параметры!$B$5)>=1000,-1,0)),ROUND(F11*Параметры!$B$6,IF(F11*Параметры!$B$6>=1000,-1,0))))) -> 173 | J11: 172 | K11: =IF(OR(J11="",G11=""),"",MAX(J11,MIN(ROUND(J11*(1+Параметры!$B$5),IF(J11*(1+Параметры!$B$5)>=1000,-1,0)),ROUND(G11*Параметры!$B$6,IF(G11*Параметры!$B$6>=1000,-1,0))))) -> 198 | L11: 0.3 | M11: =IF(OR(L11="",L11=0),"",1/L11) -> 3.3333333 | N11: =IF(OR(L11="",L11=0),"",Параметры!$B$3/L11) -> 26.666667 | O11: =IF(L11="","",IFERROR(INDEX('Почасовка — ставки и план'!$D$5:$D$24,MATCH($D11,'Почасовка — ставки и план'!$A$5:$A$24,0)),"")) -> 650 | P11: =IF(L11="","",IFERROR(INDEX('Почасовка — ставки и план'!$E$5:$E$24,MATCH($D11,'Почасовка — ставки и план'!$A$5:$A$24,0)),"")) -> 780 | Q11: =IF(OR(L11="",O11=""),"",ROUND(L11*O11,0)) -> 195 | R11: =IF(D11="TEX","аренда техники — сделка/счёт",IF(OR(Q11="",H11="",H11=0),"—",IF(Q11<H11*(1-Параметры!$B$7),"почасовка",IF(Q11>H11*(1+Параметры!$B$7),"сделка","любой способ")))) -> сделка | S11: 0.04 | T11: 0.083333333
A12: 1.1.N1 | B12: Разборка асфальтобетонного покрытия толщиной до 5 см отбойными молотками | C12: м2 | D12: BLG | E12: =IFERROR(INDEX('Почасовка — ставки и план'!$B$5:$B$24,MATCH(D12,'Почасовка — ставки и план'!$A$5:$A$24,0)),"Аренда техники / механизмы") -> Дорожный рабочий / благоустройство | F12: 200 | G12: 230 | H12: 120 | I12: =IF(OR(H12="",F12=""),"",MAX(H12,MIN(ROUND(H12*(1+Параметры!$B$5),IF(H12*(1+Параметры!$B$5)>=1000,-1,0)),ROUND(F12*Параметры!$B$6,IF(F12*Параметры!$B$6>=1000,-1,0))))) -> 138 | J12: 138 | K12: =IF(OR(J12="",G12=""),"",MAX(J12,MIN(ROUND(J12*(1+Параметры!$B$5),IF(J12*(1+Параметры!$B$5)>=1000,-1,0)),ROUND(G12*Параметры!$B$6,IF(G12*Параметры!$B$6>=1000,-1,0))))) -> 159 | L12: 0.2 | M12: =IF(OR(L12="",L12=0),"",1/L12) -> 5 | N12: =IF(OR(L12="",L12=0),"",Параметры!$B$3/L12) -> 40 | O12: =IF(L12="","",IFERROR(INDEX('Почасовка — ставки и план'!$D$5:$D$24,MATCH($D12,'Почасовка — ставки и план'!$A$5:$A$24,0)),"")) -> 650 | P12: =IF(L12="","",IFERROR(INDEX('Почасовка — ставки и план'!$E$5:$E$24,MATCH($D12,'Почасовка — ставки и план'!$A$5:$A$24,0)),"")) -> 780 | Q12: =IF(OR(L12="",O12=""),"",ROUND(L12*O12,0)) -> 130 | R12: =IF(D12="TEX","аренда техники — сделка/счёт",IF(OR(Q12="",H12="",H12=0),"—",IF(Q12<H12*(1-Параметры!$B$7),"почасовка",IF(Q12>H12*(1+Параметры!$B$7),"сделка","любой способ")))) -> любой способ | S12: 0 | T12: 0
A13: 1.1.N2 | B13: Демонтаж бетонных дорожных плит (ПАГ, 2П) с погрузкой | C13: м2 | D13: BLG | E13: =IFERROR(INDEX('Почасовка — ставки и план'!$B$5:$B$24,MATCH(D13,'Почасовка — ставки и план'!$A$5:$A$24,0)),"Аренда техники / механизмы") -> Дорожный рабочий / благоустройство | F13: 460 | G13: 529 | H13: 280 | I13: =IF(OR(H13="",F13=""),"",MAX(H13,MIN(ROUND(H13*(1+Параметры!$B$5),IF(H13*(1+Параметры!$B$5)>=1000,-1,0)),ROUND(F13*Параметры!$B$6,IF(F13*Параметры!$B$6>=1000,-1,0))))) -> 322 | J13: 322 | K13: =IF(OR(J13="",G13=""),"",MAX(J13,MIN(ROUND(J13*(1+Параметры!$B$5),IF(J13*(1+Параметры!$B$5)>=1000,-1,0)),ROUND(G13*Параметры!$B$6,IF(G13*Параметры!$B$6>=1000,-1,0))))) -> 370 | L13: 0.25 | M13: =IF(OR(L13="",L13=0),"",1/L13) -> 4 | N13: =IF(OR(L13="",L13=0),"",Параметры!$B$3/L13) -> 32 | O13: =IF(L13="","",IFERROR(INDEX('Почасовка — ставки и план'!$D$5:$D$24,MATCH($D13,'Почасовка — ставки и план'!$A$5:$A$24,0)),"")) -> 650 | P13: =IF(L13="","",IFERROR(INDEX('Почасовка — ставки и план'!$E$5:$E$24,MATCH($D13,'Почасовка — ставки и план'!$A$5:$A$24,0)),"")) -> 780 | Q13: =IF(OR(L13="",O13=""),"",ROUND(L13*O13,0)) -> 163 | R13: =IF(D13="TEX","аренда техники — сделка/счёт",IF(OR(Q13="",H13="",H13=0),"—",IF(Q13<H13*(1-Параметры!$B$7),"почасовка",IF(Q13>H13*(1+Параметры!$B$7),"сделка","любой способ")))) -> почасовка | S13: 0 | T13: 0
A14: 1.1.N3 | B14: Демонтаж ограждения из сетки/профлиста со стойками | C14: мп | D14: SVA | E14: =IFERROR(INDEX('Почасовка — ставки и план'!$B$5:$B$24,MATCH(D14,'Почасовка — ставки и план'!$A$5:$A$24,0)),"Аренда техники / механизмы") -> Сварщик / монтажник МК | F14: 480 | G14: 576 | H14: 180 | I14: =IF(OR(H14="",F14=""),"",MAX(H14,MIN(ROUND(H14*(1+Параметры!$B$5),IF(H14*(1+Параметры!$B$5)>=1000,-1,0)),ROUND(F14*Параметры!$B$6,IF(F14*Параметры!$B$6>=1000,-1,0))))) -> 207 | J14: 207 | K14: =IF(OR(J14="",G14=""),"",MAX(J14,MIN(ROUND(J14*(1+Параметры!$B$5),IF(J14*(1+Параметры!$B$5)>=1000,-1,0)),ROUND(G14*Параметры!$B$6,IF(G14*Параметры!$B$6>=1000,-1,0))))) -> 238 | L14: 0.4 | M14: =IF(OR(L14="",L14=0),"",1/L14) -> 2.5 | N14: =IF(OR(L14="",L14=0),"",Параметры!$B$3/L14) -> 20 | O14: =IF(L14="","",IFERROR(INDEX('Почасовка — ставки и план'!$D$5:$D$24,MATCH($D14,'Почасовка — ставки и план'!$A$5:$A$24,0)),"")) -> 900 | P14: =IF(L14="","",IFERROR(INDEX('Почасовка — ставки и план'!$E$5:$E$24,MATCH($D14,'Почасовка — ставки и план'!$A$5:$A$24,0)),"")) -> 1080 | Q14: =IF(OR(L14="",O14=""),"",ROUND(L14*O14,0)) -> 360 | R14: =IF(D14="TEX","аренда техники — сделка/счёт",IF(OR(Q14="",H14="",H14=0),"—",IF(Q14<H14*(1-Параметры!$B$7),"почасовка",IF(Q14>H14*(1+Параметры!$B$7),"сделка","любой способ")))) -> сделка | S14: 0.6 | T14: 0.66956522
A15: 1.2 Демонтажные работы по фасаду
A16: 1.2.1 | B16: Отбивка штукатурки с поверхностей стен | C16: м2 | D16: RAZ | E16: =IFERROR(INDEX('Почасовка — ставки и план'!$B$5:$B$24,MATCH(D16,'Почасовка — ставки и план'!$A$5:$A$24,0)),"Аренда техники / механизмы") -> Разнорабочий / демонтажник | F16: 300 | G16: 345 | H16: 180 | I16: =IF(OR(H16="",F16=""),"",MAX(H16,MIN(ROUND(H16*(1+Параметры!$B$5),IF(H16*(1+Параметры!$B$5)>=1000,-1,0)),ROUND(F16*Параметры!$B$6,IF(F16*Параметры!$B$6>=1000,-1,0))))) -> 207 | J16: 207 | K16: =IF(OR(J16="",G16=""),"",MAX(J16,MIN(ROUND(J16*(1+Параметры!$B$5),IF(J16*(1+Параметры!$B$5)>=1000,-1,0)),ROUND(G16*Параметры!$B$6,IF(G16*Параметры!$B$6>=1000,-1,0))))) -> 238 | L16: 0.35 | M16: =IF(OR(L16="",L16=0),"",1/L16) -> 2.8571429 | N16: =IF(OR(L16="",L16=0),"",Параметры!$B$3/L16) -> 22.857143 | O16: =IF(L16="","",IFERROR(INDEX('Почасовка — ставки и план'!$D$5:$D$24,MATCH($D16,'Почасовка — ставки и план'!$A$5:$A$24,0)),"")) -> 550 | P16: =IF(L16="","",IFERROR(INDEX('Почасовка — ставки и план'!$E$5:$E$24,MATCH($D16,'Почасовка — ставки и план'!$A$5:$A$24,0)),"")) -> 660 | Q16: =IF(OR(L16="",O16=""),"",ROUND(L16*O16,0)) -> 193 | R16: =IF(D16="TEX","аренда техники — сделка/счёт",IF(OR(Q16="",H16="",H16=0),"—",IF(Q16<H16*(1-Параметры!$B$7),"почасовка",IF(Q16>H16*(1+Параметры!$B$7),"сделка","любой способ")))) -> любой способ | S16: 0 | T16: 0
A17: 1.2.2 | B17: Демонтаж облицовки из профилированного листа без разборки каркаса | C17: м2 | D17: RAZ | E17: =IFERROR(INDEX('Почасовка — ставки и план'!$B$5:$B$24,MATCH(D17,'Почасовка — ставки и план'!$A$5:$A$24,0)),"Аренда техники / механизмы") -> Разнорабочий / демонтажник | F17: 250 | G17: 288 | H17: 150 | I17: =IF(OR(H17="",F17=""),"",MAX(H17,MIN(ROUND(H17*(1+Параметры!$B$5),IF(H17*(1+Параметры!$B$5)>=1000,-1,0)),ROUND(F17*Параметры!$B$6,IF(F17*Параметры!$B$6>=1000,-1,0))))) -> 173 | J17: 172 | K17: =IF(OR(J17="",G17=""),"",MAX(J17,MIN(ROUND(J17*(1+Параметры!$B$5),IF(J17*(1+Параметры!$B$5)>=1000,-1,0)),ROUND(G17*Параметры!$B$6,IF(G17*Параметры!$B$6>=1000,-1,0))))) -> 198 | L17: 0.25 | M17: =IF(OR(L17="",L17=0),"",1/L17) -> 4 | N17: =IF(OR(L17="",L17=0),"",Параметры!$B$3/L17) -> 32 | O17: =IF(L17="","",IFERROR(INDEX('Почасовка — ставки и план'!$D$5:$D$24,MATCH($D17,'Почасовка — ставки и план'!$A$5:$A$24,0)),"")) -> 550 | P17: =IF(L17="","",IFERROR(INDEX('Почасовка — ставки и план'!$E$5:$E$24,MATCH($D17,'Почасовка — ставки и план'!$A$5:$A$24,0)),"")) -> 660 | Q17: =IF(OR(L17="",O17=""),"",ROUND(L17*O17,0)) -> 138 | R17: =IF(D17="TEX","аренда техники — сделка/счёт",IF(OR(Q17="",H17="",H17=0),"—",IF(Q17<H17*(1-Параметры!$B$7),"почасовка",IF(Q17>H17*(1+Параметры!$B$7),"сделка","любой способ")))) -> любой способ | S17: 0 | T17: 0
A18: 1.2.3 | B18: Демонтаж облицовки из профилированного листа с разборкой каркаса | C18: м2 | D18: RAZ | E18: =IFERROR(INDEX('Почасовка — ставки и план'!$B$5:$B$24,MATCH(D18,'Почасовка — ставки и план'!$A$5:$A$24,0)),"Аренда техники / механизмы") -> Разнорабочий / демонтажник | F18: 380 | G18: 437 | H18: 230 | I18: =IF(OR(H18="",F18=""),"",MAX(H18,MIN(ROUND(H18*(1+Параметры!$B$5),IF(H18*(1+Параметры!$B$5)>=1000,-1,0)),ROUND(F18*Параметры!$B$6,IF(F18*Параметры!$B$6>=1000,-1,0))))) -> 265 | J18: 264 | K18: =IF(OR(J18="",G18=""),"",MAX(J18,MIN(ROUND(J18*(1+Параметры!$B$5),IF(J18*(1+Параметры!$B$5)>=1000,-1,0)),ROUND(G18*Параметры!$B$6,IF(G18*Параметры!$B$6>=1000,-1,0))))) -> 304 | L18: 0.4 | M18: =IF(OR(L18="",L18=0),"",1/L18) -> 2.5 | N18: =IF(OR(L18="",L18=0),"",Параметры!$B$3/L18) -> 20 | O18: =IF(L18="","",IFERROR(INDEX('Почасовка — ставки и план'!$D$5:$D$24,MATCH($D18,'Почасовка — ставки и план'!$A$5:$A$24,0)),"")) -> 550 | P18: =IF(L18="","",IFERROR(INDEX('Почасовка — ставки и план'!$E$5:$E$24,MATCH($D18,'Почасовка — ставки и план'!$A$5:$A$24,0)),"")) -> 660 | Q18: =IF(OR(L18="",O18=""),"",ROUND(L18*O18,0)) -> 220 | R18: =IF(D18="TEX","аренда техники — сделка/счёт",IF(OR(Q18="",H18="",H18=0),"—",IF(Q18<H18*(1-Параметры!$B$7),"почасовка",IF(Q18>H18*(1+Параметры!$B$7),"сделка","любой способ")))) -> любой способ | S18: 0 | T18: 0
A19: 1.2.4 | B19: Демонтаж ограждающих конструкций стен из многослойных панелей (сэндвич-панели) | C19: м2 | D19: KRO | E19: =IFERROR(INDEX('Почасовка — ставки и план'!$B$5:$B$24,MATCH(D19,'Почасовка — ставки и план'!$A$5:$A$24,0)),"Аренда техники / механизмы") -> Кровельщик | F19: 480 | G19: 571 | H19: 230 | I19: =IF(OR(H19="",F19=""),"",MAX(H19,MIN(ROUND(H19*(1+Параметры!$B$5),IF(H19*(1+Параметры!$B$5)>=1000,-1,0)),ROUND(F19*Параметры!$B$6,IF(F19*Параметры!$B$6>=1000,-1,0))))) -> 265 | J19: 264 | K19: =IF(OR(J19="",G19=""),"",MAX(J19,MIN(ROUND(J19*(1+Параметры!$B$5),IF(J19*(1+Параметры!$B$5)>=1000,-1,0)),ROUND(G19*Параметры!$B$6,IF(G19*Параметры!$B$6>=1000,-1,0))))) -> 304 | L19: 0.45 | M19: =IF(OR(L19="",L19=0),"",1/L19) -> 2.2222222 | N19: =IF(OR(L19="",L19=0),"",Параметры!$B$3/L19) -> 17.777778 | O19: =IF(L19="","",IFERROR(INDEX('Почасовка — ставки и план'!$D$5:$D$24,MATCH($D19,'Почасовка — ставки и план'!$A$5:$A$24,0)),"")) -> 800 | P19: =IF(L19="","",IFERROR(INDEX('Почасовка — ставки и план'!$E$5:$E$24,MATCH($D19,'Почасовка — ставки и план'!$A$5:$A$24,0)),"")) -> 950 | Q19: =IF(OR(L19="",O19=""),"",ROUND(L19*O19,0)) -> 360 | R19: =IF(D19="TEX","аренда техники — сделка/счёт",IF(OR(Q19="",H19="",H19=0),"—",IF(Q19<H19*(1-Параметры!$B$7),"почасовка",IF(Q19>H19*(1+Параметры!$B$7),"сделка","любой способ")))) -> сделка | S19: 0.26315789 | T19: 0.30663616
A20: 1.2.5 | B20: Демонтаж ограждающих конструкций стен из панелей "Алюкобонд" и металлического каркаса | C20: м2 | D20: FAS | E20: =IFERROR(INDEX('Почасовка — ставки и план'!$B$5:$B$24,MATCH(D20,'Почасовка — ставки и план'!$A$5:$A$24,0)),"Аренда техники / механизмы") -> Фасадчик / промальпинист | F20: 1320 | G20: 1560 | H20: 650 | I20: =IF(OR(H20="",F20=""),"",MAX(H20,MIN(ROUND(H20*(1+Параметры!$B$5),IF(H20*(1+Параметры!$B$5)>=1000,-1,0)),ROUND(F20*Параметры!$B$6,IF(F20*Параметры!$B$6>=1000,-1,0))))) -> 748 | J20: 747 | K20: =IF(OR(J20="",G20=""),"",MAX(J20,MIN(ROUND(J20*(1+Параметры!$B$5),IF(J20*(1+Параметры!$B$5)>=1000,-1,0)),ROUND(G20*Параметры!$B$6,IF(G20*Параметры!$B$6>=1000,-1,0))))) -> 859 | L20: 0.9 | M20: =IF(OR(L20="",L20=0),"",1/L20) -> 1.1111111 | N20: =IF(OR(L20="",L20=0),"",Параметры!$B$3/L20) -> 8.8888889 | O20: =IF(L20="","",IFERROR(INDEX('Почасовка — ставки и план'!$D$5:$D$24,MATCH($D20,'Почасовка — ставки и план'!$A$5:$A$24,0)),"")) -> 1100 | P20: =IF(L20="","",IFERROR(INDEX('Почасовка — ставки и план'!$E$5:$E$24,MATCH($D20,'Почасовка — ставки и план'!$A$5:$A$24,0)),"")) -> 1300 | Q20: =IF(OR(L20="",O20=""),"",ROUND(L20*O20,0)) -> 990 | R20: =IF(D20="TEX","аренда техники — сделка/счёт",IF(OR(Q20="",H20="",H20=0),"—",IF(Q20<H20*(1-Параметры!$B$7),"почасовка",IF(Q20>H20*(1+Параметры!$B$7),"сделка","любой способ")))) -> сделка | S20: 0.2 | T20: 0.23320158
A21: 1.2.6 | B21: Демонтаж теплоизоляционного слоя стен | C21: м2 | D21: RAZ | E21: =IFERROR(INDEX('Почасовка — ставки и план'!$B$5:$B$24,MATCH(D21,'Почасовка — ставки и план'!$A$5:$A$24,0)),"Аренда техники / механизмы") -> Разнорабочий / демонтажник | F21: 200 | G21: 230 | H21: 120 | I21: =IF(OR(H21="",F21=""),"",MAX(H21,MIN(ROUND(H21*(1+Параметры!$B$5),IF(H21*(1+Параметры!$B$5)>=1000,-1,0)),ROUND(F21*Параметры!$B$6,IF(F21*Параметры!$B$6>=1000,-1,0))))) -> 138 | J21: 138 | K21: =IF(OR(J21="",G21=""),"",MAX(J21,MIN(ROUND(J21*(1+Параметры!$B$5),IF(J21*(1+Параметры!$B$5)>=1000,-1,0)),ROUND(G21*Параметры!$B$6,IF(G21*Параметры!$B$6>=1000,-1,0))))) -> 159 | L21: 0.2 | M21: =IF(OR(L21="",L21=0),"",1/L21) -> 5 | N21: =IF(OR(L21="",L21=0),"",Параметры!$B$3/L21) -> 40 | O21: =IF(L21="","",IFERROR(INDEX('Почасовка — ставки и план'!$D$5:$D$24,MATCH($D21,'Почасовка — ставки и план'!$A$5:$A$24,0)),"")) -> 550 | P21: =IF(L21="","",IFERROR(INDEX('Почасовка — ставки и план'!$E$5:$E$24,MATCH($D21,'Почасовка — ставки и план'!$A$5:$A$24,0)),"")) -> 660 | Q21: =IF(OR(L21="",O21=""),"",ROUND(L21*O21,0)) -> 110 | R21: =IF(D21="TEX","аренда техники — сделка/счёт",IF(OR(Q21="",H21="",H21=0),"—",IF(Q21<H21*(1-Параметры!$B$7),"почасовка",IF(Q21>H21*(1+Параметры!$B$7),"сделка","любой способ")))) -> любой способ | S21: 0 | T21: 0
A22: 1.2.7 | B22: Разборка систем вентилируемых фасадов из плит "Керамогранит" с сохранением каркаса | C22: м2 | D22: FAS | E22: =IFERROR(INDEX('Почасовка — ставки и план'!$B$5:$B$24,MATCH(D22,'Почасовка — ставки и план'!$A$5:$A$24,0)),"Аренда техники / механизмы") -> Фасадчик / промальпинист | F22: 880 | G22: 1040 | H22: 400 | I22: =IF(OR(H22="",F22=""),"",MAX(H22,MIN(ROUND(H22*(1+Параметры!$B$5),IF(H22*(1+Параметры!$B$5)>=1000,-1,0)),ROUND(F22*Параметры!$B$6,IF(F22*Параметры!$B$6>=1000,-1,0))))) -> 460 | J22: 460 | K22: =IF(OR(J22="",G22=""),"",MAX(J22,MIN(ROUND(J22*(1+Параметры!$B$5),IF(J22*(1+Параметры!$B$5)>=1000,-1,0)),ROUND(G22*Параметры!$B$6,IF(G22*Параметры!$B$6>=1000,-1,0))))) -> 529 | L22: 0.6 | M22: =IF(OR(L22="",L22=0),"",1/L22) -> 1.6666667 | N22: =IF(OR(L22="",L22=0),"",Параметры!$B$3/L22) -> 13.333333 | O22: =IF(L22="","",IFERROR(INDEX('Почасовка — ставки и план'!$D$5:$D$24,MATCH($D22,'Почасовка — ставки и план'!$A$5:$A$24,0)),"")) -> 1100 | P22: =IF(L22="","",IFERROR(INDEX('Почасовка — ставки и план'!$E$5:$E$24,MATCH($D22,'Почасовка — ставки и план'!$A$5:$A$24,0)),"")) -> 1300 | Q22: =IF(OR(L22="",O22=""),"",ROUND(L22*O22,0)) -> 660 | R22: =IF(D22="TEX","аренда техники — сделка/счёт",IF(OR(Q22="",H22="",H22=0),"—",IF(Q22<H22*(1-Параметры!$B$7),"почасовка",IF(Q22>H22*(1+Параметры!$B$7),"сделка","любой способ")))) -> сделка | S22: 0.35384615 | T22: 0.39223561
A23: 1.2.8 | B23: Разборка систем вентилируемых фасадов из плит "Керамогранит" с учетом каркаса | C23: м2 | D23: FAS | E23: =IFERROR(INDEX('Почасовка — ставки и план'!$B$5:$B$24,MATCH(D23,'Почасовка — ставки и план'!$A$5:$A$24,0)),"Аренда техники / механизмы") -> Фасадчик / промальпинист | F23: 1467 | G23: 1734 | H23: 650 | I23: =IF(OR(H23="",F23=""),"",MAX(H23,MIN(ROUND(H23*(1+Параметры!$B$5),IF(H23*(1+Параметры!$B$5)>=1000,-1,0)),ROUND(F23*Параметры!$B$6,IF(F23*Параметры!$B$6>=1000,-1,0))))) -> 748 | J23: 747 | K23: =IF(OR(J23="",G23=""),"",MAX(J23,MIN(ROUND(J23*(1+Параметры!$B$5),IF(J23*(1+Параметры!$B$5)>=1000,-1,0)),ROUND(G23*Параметры!$B$6,IF(G23*Параметры!$B$6>=1000,-1,0))))) -> 859 | L23: 1 | M23: =IF(OR(L23="",L23=0),"",1/L23) -> 1 | N23: =IF(OR(L23="",L23=0),"",Параметры!$B$3/L23) -> 8 | O23: =IF(L23="","",IFERROR(INDEX('Почасовка — ставки и план'!$D$5:$D$24,MATCH($D23,'Почасовка — ставки и план'!$A$5:$A$24,0)),"")) -> 1100 | P23: =IF(L23="","",IFERROR(INDEX('Почасовка — ставки и план'!$E$5:$E$24,MATCH($D23,'Почасовка — ставки и план'!$A$5:$A$24,0)),"")) -> 1300 | Q23: =IF(OR(L23="",O23=""),"",ROUND(L23*O23,0)) -> 1100 | R23: =IF(D23="TEX","аренда техники — сделка/счёт",IF(OR(Q23="",H23="",H23=0),"—",IF(Q23<H23*(1-Параметры!$B$7),"почасовка",IF(Q23>H23*(1+Параметры!$B$7),"сделка","любой способ")))) -> сделка | S23: 0.33363636 | T23: 0.37075099
A24: 1.2.N1 | B24: Демонтаж металлического козырька/навеса над входом | C24: м2 | D24: SVA | E24: =IFERROR(INDEX('Почасовка — ставки и план'!$B$5:$B$24,MATCH(D24,'Почасовка — ставки и план'!$A$5:$A$24,0)),"Аренда техники / механизмы") -> Сварщик / монтажник МК | F24: 1200 | G24: 1440 | H24: 720 | I24: =IF(OR(H24="",F24=""),"",MAX(H24,MIN(ROUND(H24*(1+Параметры!$B$5),IF(H24*(1+Параметры!$B$5)>=1000,-1,0)),ROUND(F24*Параметры!$B$6,IF(F24*Параметры!$B$6>=1000,-1,0))))) -> 828 | J24: 828 | K24: =IF(OR(J24="",G24=""),"",MAX(J24,MIN(ROUND(J24*(1+Параметры!$B$5),IF(J24*(1+Параметры!$B$5)>=1000,-1,0)),ROUND(G24*Параметры!$B$6,IF(G24*Параметры!$B$6>=1000,-1,0))))) -> 952 | L24: 1 | M24: =IF(OR(L24="",L24=0),"",1/L24) -> 1 | N24: =IF(OR(L24="",L24=0),"",Параметры!$B$3/L24) -> 8 | O24: =IF(L24="","",IFERROR(INDEX('Почасовка — ставки и план'!$D$5:$D$24,MATCH($D24,'Почасовка — ставки и план'!$A$5:$A$24,0)),"")) -> 900 | P24: =IF(L24="","",IFERROR(INDEX('Почасовка — ставки и план'!$E$5:$E$24,MATCH($D24,'Почасовка — ставки и план'!$A$5:$A$24,0)),"")) -> 1080 | Q24: =IF(OR(L24="",O24=""),"",ROUND(L24*O24,0)) -> 900 | R24: =IF(D24="TEX","аренда техники — сделка/счёт",IF(OR(Q24="",H24="",H24=0),"—",IF(Q24<H24*(1-Параметры!$B$7),"почасовка",IF(Q24>H24*(1+Параметры!$B$7),"сделка","любой способ")))) -> сделка | S24: 0 | T24: 0.043478261
A25: 1.3 Демонтажные работы по фундаменту
A26: 1.3.1 | B26: Разборка бутовых фундаментов | C26: м3 | D26: RAZ | E26: =IFERROR(INDEX('Почасовка — ставки и план'!$B$5:$B$24,MATCH(D26,'Почасовка — ставки и план'!$A$5:$A$24,0)),"Аренда техники / механизмы") -> Разнорабочий / демонтажник | F26: 5500 | G26: 6600 | H26: 2400 | I26: =IF(OR(H26="",F26=""),"",MAX(H26,MIN(ROUND(H26*(1+Параметры!$B$5),IF(H26*(1+Параметры!$B$5)>=1000,-1,0)),ROUND(F26*Параметры!$B$6,IF(F26*Параметры!$B$6>=1000,-1,0))))) -> 2760 | J26: 2760 | K26: =IF(OR(J26="",G26=""),"",MAX(J26,MIN(ROUND(J26*(1+Параметры!$B$5),IF(J26*(1+Параметры!$B$5)>=1000,-1,0)),ROUND(G26*Параметры!$B$6,IF(G26*Параметры!$B$6>=1000,-1,0))))) -> 3170 | L26: 7.5 | M26: =IF(OR(L26="",L26=0),"",1/L26) -> 0.13333333 | N26: =IF(OR(L26="",L26=0),"",Параметры!$B$3/L26) -> 1.0666667 | O26: =IF(L26="","",IFERROR(INDEX('Почасовка — ставки и план'!$D$5:$D$24,MATCH($D26,'Почасовка — ставки и план'!$A$5:$A$24,0)),"")) -> 550 | P26: =IF(L26="","",IFERROR(INDEX('Почасовка — ставки и план'!$E$5:$E$24,MATCH($D26,'Почасовка — ставки и план'!$A$5:$A$24,0)),"")) -> 660 | Q26: =IF(OR(L26="",O26=""),"",ROUND(L26*O26,0)) -> 4125 | R26: =IF(D26="TEX","аренда техники — сделка/счёт",IF(OR(Q26="",H26="",H26=0),"—",IF(Q26<H26*(1-Параметры!$B$7),"почасовка",IF(Q26>H26*(1+Параметры!$B$7),"сделка","любой способ")))) -> сделка | S26: 0.375 | T26: 0.43478261
A27: 1.3.2 | B27: Разборка бетонных фундаментов | C27: м3 | D27: RAZ | E27: =IFERROR(INDEX('Почасовка — ставки и план'!$B$5:$B$24,MATCH(D27,'Почасовка — ставки и план'!$A$5:$A$24,0)),"Аренда техники / механизмы") -> Разнорабочий / демонтажник | F27: 8067 | G27: 9680 | H27: 4500 | I27: =IF(OR(H27="",F27=""),"",MAX(H27,MIN(ROUND(H27*(1+Параметры!$B$5),IF(H27*(1+Параметры!$B$5)>=1000,-1,0)),ROUND(F27*Параметры!$B$6,IF(F27*Параметры!$B$6>=1000,-1,0))))) -> 5180 | J27: 5310 | K27: =IF(OR(J27="",G27=""),"",MAX(J27,MIN(ROUND(J27*(1+Параметры!$B$5),IF(J27*(1+Параметры!$B$5)>=1000,-1,0)),ROUND(G27*Параметры!$B$6,IF(G27*Параметры!$B$6>=1000,-1,0))))) -> 6110 | L27: 11 | M27: =IF(OR(L27="",L27=0),"",1/L27) -> 0.090909091 | N27: =IF(OR(L27="",L27=0),"",Параметры!$B$3/L27) -> 0.72727273 | O27: =IF(L27="","",IFERROR(INDEX('Почасовка — ставки и план'!$D$5:$D$24,MATCH($D27,'Почасовка — ставки и план'!$A$5:$A$24,0)),"")) -> 550 | P27: =IF(L27="","",IFERROR(INDEX('Почасовка — ставки и план'!$E$5:$E$24,MATCH($D27,'Почасовка — ставки и план'!$A$5:$A$24,0)),"")) -> 660 | Q27: =IF(OR(L27="",O27=""),"",ROUND(L27*O27,0)) -> 6050 | R27: =IF(D27="TEX","аренда техники — сделка/счёт",IF(OR(Q27="",H27="",H27=0),"—",IF(Q27<H27*(1-Параметры!$B$7),"почасовка",IF(Q27>H27*(1+Параметры!$B$7),"сделка","любой способ")))) -> сделка | S27: 0.0756 | T27: 0.075555556
A28: 1.3.3 | B28: Разборка железобетонных фундаментов | C28: м3 | D28: RAZ | E28: =IFERROR(INDEX('Почасовка — ставки и план'!$B$5:$B$24,MATCH(D28,'Почасовка — ставки и план'!$A$5:$A$24,0)),"Аренда техники / механизмы") -> Разнорабочий / демонтажник | F28: 11000 | G28: 13200 | H28: 6000 | I28: =IF(OR(H28="",F28=""),"",MAX(H28,MIN(ROUND(H28*(1+Параметры!$B$5),IF(H28*(1+Параметры!$B$5)>=1000,-1,0)),ROUND(F28*Параметры!$B$6,IF(F28*Параметры!$B$6>=1000,-1,0))))) -> 6900 | J28: 7080 | K28: =IF(OR(J28="",G28=""),"",MAX(J28,MIN(ROUND(J28*(1+Параметры!$B$5),IF(J28*(1+Параметры!$B$5)>=1000,-1,0)),ROUND(G28*Параметры!$B$6,IF(G28*Параметры!$B$6>=1000,-1,0))))) -> 8140 | L28: 15 | M28: =IF(OR(L28="",L28=0),"",1/L28) -> 0.066666667 | N28: =IF(OR(L28="",L28=0),"",Параметры!$B$3/L28) -> 0.53333333 | O28: =IF(L28="","",IFERROR(INDEX('Почасовка — ставки и план'!$D$5:$D$24,MATCH($D28,'Почасовка — ставки и план'!$A$5:$A$24,0)),"")) -> 550 | P28: =IF(L28="","",IFERROR(INDEX('Почасовка — ставки и план'!$E$5:$E$24,MATCH($D28,'Почасовка — ставки и план'!$A$5:$A$24,0)),"")) -> 660 | Q28: =IF(OR(L28="",O28=""),"",ROUND(L28*O28,0)) -> 8250 | R28: =IF(D28="TEX","аренда техники — сделка/счёт",IF(OR(Q28="",H28="",H28=0),"—",IF(Q28<H28*(1-Параметры!$B$7),"почасовка",IF(Q28>H28*(1+Параметры!$B$7),"сделка","любой способ")))) -> сделка | S28: 0.1 | T28: 0.1
A29: 1.4 Демонтажные работы кровли
A30: 1.4.1 | B30: Очистка кровли от листвы и мусора | C30: м2 | D30: RAZ | E30: =IFERROR(INDEX('Почасовка — ставки и план'!$B$5:$B$24,MATCH(D30,'Почасовка — ставки и план'!$A$5:$A$24,0)),"Аренда техники / механизмы") -> Разнорабочий / демонтажник | F30: 35 | G30: 40 | H30: 20 | I30: =IF(OR(H30="",F30=""),"",MAX(H30,MIN(ROUND(H30*(1+Параметры!$B$5),IF(H30*(1+Параметры!$B$5)>=1000,-1,0)),ROUND(F30*Параметры!$B$6,IF(F30*Параметры!$B$6>=1000,-1,0))))) -> 23 | J30: 23 | K30: =IF(OR(J30="",G30=""),"",MAX(J30,MIN(ROUND(J30*(1+Параметры!$B$5),IF(J30*(1+Параметры!$B$5)>=1000,-1,0)),ROUND(G30*Параметры!$B$6,IF(G30*Параметры!$B$6>=1000,-1,0))))) -> 26 | L30: 0.04 | M30: =IF(OR(L30="",L30=0),"",1/L30) -> 25 | N30: =IF(OR(L30="",L30=0),"",Параметры!$B$3/L30) -> 200 | O30: =IF(L30="","",IFERROR(INDEX('Почасовка — ставки и план'!$D$5:$D$24,MATCH($D30,'Почасовка — ставки и план'!$A$5:$A$24,0)),"")) -> 550 | P30: =IF(L30="","",IFERROR(INDEX('Почасовка — ставки и план'!$E$5:$E$24,MATCH($D30,'Почасовка — ставки и план'!$A$5:$A$24,0)),"")) -> 660 | Q30: =IF(OR(L30="",O30=""),"",ROUND(L30*O30,0)) -> 22 | R30: =IF(D30="TEX","аренда техники — сделка/счёт",IF(OR(Q30="",H30="",H30=0),"—",IF(Q30<H30*(1-Параметры!$B$7),"почасовка",IF(Q30>H30*(1+Параметры!$B$7),"сделка","любой способ")))) -> любой способ | S30: 0 | T30: 0
A31: 1.4.2 | B31: Очистка снега с крыш при толщине слоя до 20 см | C31: м2 | D31: RAZ | E31: =IFERROR(INDEX('Почасовка — ставки и план'!$B$5:$B$24,MATCH(D31,'Почасовка — ставки и план'!$A$5:$A$24,0)),"Аренда техники / механизмы") -> Разнорабочий / демонтажник | F31: 30 | G31: 35 | H31: 18 | I31: =IF(OR(H31="",F31=""),"",MAX(H31,MIN(ROUND(H31*(1+Параметры!$B$5),IF(H31*(1+Параметры!$B$5)>=1000,-1,0)),ROUND(F31*Параметры!$B$6,IF(F31*Параметры!$B$6>=1000,-1,0))))) -> 21 | J31: 20.5 | K31: =IF(OR(J31="",G31=""),"",MAX(J31,MIN(ROUND(J31*(1+Параметры!$B$5),IF(J31*(1+Параметры!$B$5)>=1000,-1,0)),ROUND(G31*Параметры!$B$6,IF(G31*Параметры!$B$6>=1000,-1,0))))) -> 24 | L31: 0.04 | M31: =IF(OR(L31="",L31=0),"",1/L31) -> 25 | N31: =IF(OR(L31="",L31=0),"",Параметры!$B$3/L31) -> 200 | O31: =IF(L31="","",IFERROR(INDEX('Почасовка — ставки и план'!$D$5:$D$24,MATCH($D31,'Почасовка — ставки и план'!$A$5:$A$24,0)),"")) -> 550 | P31: =IF(L31="","",IFERROR(INDEX('Почасовка — ставки и план'!$E$5:$E$24,MATCH($D31,'Почасовка — ставки и план'!$A$5:$A$24,0)),"")) -> 660 | Q31: =IF(OR(L31="",O31=""),"",ROUND(L31*O31,0)) -> 22 | R31: =IF(D31="TEX","аренда техники — сделка/счёт",IF(OR(Q31="",H31="",H31=0),"—",IF(Q31<H31*(1-Параметры!$B$7),"почасовка",IF(Q31>H31*(1+Параметры!$B$7),"сделка","любой способ")))) -> сделка | S31: 0 | T31: 0.014492754
A32: 1.4.3 | B32: Очистка снега с крыш, добавлять на каждые следующие 10 см увеличения толщины слоя | C32: м2 | D32: RAZ | E32: =IFERROR(INDEX('Почасовка — ставки и план'!$B$5:$B$24,MATCH(D32,'Почасовка — ставки и план'!$A$5:$A$24,0)),"Аренда техники / механизмы") -> Разнорабочий / демонтажник | F32: 10 | G32: 11 | H32: 5 | I32: =IF(OR(H32="",F32=""),"",MAX(H32,MIN(ROUND(H32*(1+Параметры!$B$5),IF(H32*(1+Параметры!$B$5)>=1000,-1,0)),ROUND(F32*Параметры!$B$6,IF(F32*Параметры!$B$6>=1000,-1,0))))) -> 6 | J32: 6 | K32: =IF(OR(J32="",G32=""),"",MAX(J32,MIN(ROUND(J32*(1+Параметры!$B$5),IF(J32*(1+Параметры!$B$5)>=1000,-1,0)),ROUND(G32*Параметры!$B$6,IF(G32*Параметры!$B$6>=1000,-1,0))))) -> 7 | L32: 0.012 | M32: =IF(OR(L32="",L32=0),"",1/L32) -> 83.333333 | N32: =IF(OR(L32="",L32=0),"",Параметры!$B$3/L32) -> 666.66667 | O32: =IF(L32="","",IFERROR(INDEX('Почасовка — ставки и план'!$D$5:$D$24,MATCH($D32,'Почасовка — ставки и план'!$A$5:$A$24,0)),"")) -> 550 | P32: =IF(L32="","",IFERROR(INDEX('Почасовка — ставки и план'!$E$5:$E$24,MATCH($D32,'Почасовка — ставки и план'!$A$5:$A$24,0)),"")) -> 660 | Q32: =IF(OR(L32="",O32=""),"",ROUND(L32*O32,0)) -> 7 | R32: =IF(D32="TEX","аренда техники — сделка/счёт",IF(OR(Q32="",H32="",H32=0),"—",IF(Q32<H32*(1-Параметры!$B$7),"почасовка",IF(Q32>H32*(1+Параметры!$B$7),"сделка","любой способ")))) -> сделка | S32: 0.25 | T32: 0.22222222
A33: 1.4.4 | B33: Разборка водосточных ПВХ труб | C33: мп | D33: KRO | E33: =IFERROR(INDEX('Почасовка — ставки и план'!$B$5:$B$24,MATCH(D33,'Почасовка — ставки и план'!$A$5:$A$24,0)),"Аренда техники / механизмы") -> Кровельщик | F33: 160 | G33: 191 | H33: 70 | I33: =IF(OR(H33="",F33=""),"",MAX(H33,MIN(ROUND(H33*(1+Параметры!$B$5),IF(H33*(1+Параметры!$B$5)>=1000,-1,0)),ROUND(F33*Параметры!$B$6,IF(F33*Параметры!$B$6>=1000,-1,0))))) -> 81 | J33: 80.5 | K33: =IF(OR(J33="",G33=""),"",MAX(J33,MIN(ROUND(J33*(1+Параметры!$B$5),IF(J33*(1+Параметры!$B$5)>=1000,-1,0)),ROUND(G33*Параметры!$B$6,IF(G33*Параметры!$B$6>=1000,-1,0))))) -> 93 | L33: 0.15 | M33: =IF(OR(L33="",L33=0),"",1/L33) -> 6.6666667 | N33: =IF(OR(L33="",L33=0),"",Параметры!$B$3/L33) -> 53.333333 | O33: =IF(L33="","",IFERROR(INDEX('Почасовка — ставки и план'!$D$5:$D$24,MATCH($D33,'Почасовка — ставки и план'!$A$5:$A$24,0)),"")) -> 800 | P33: =IF(L33="","",IFERROR(INDEX('Почасовка — ставки и план'!$E$5:$E$24,MATCH($D33,'Почасовка — ставки и план'!$A$5:$A$24,0)),"")) -> 950 | Q33: =IF(OR(L33="",O33=""),"",ROUND(L33*O33,0)) -> 120 | R33: =IF(D33="TEX","аренда техники — сделка/счёт",IF(OR(Q33="",H33="",H33=0),"—",IF(Q33<H33*(1-Параметры!$B$7),"почасовка",IF(Q33>H33*(1+Параметры!$B$7),"сделка","любой способ")))) -> сделка | S33: 0.33333333 | T33: 0.38405797
A34: 1.4.5 | B34: Разборка водосточных труб металлических | C34: мп | D34: KRO | E34: =IFERROR(INDEX('Почасовка — ставки и план'!$B$5:$B$24,MATCH(D34,'Почасовка — ставки и план'!$A$5:$A$24,0)),"Аренда техники / механизмы") -> Кровельщик | F34: 214 | G34: 254 | H34: 90 | I34: =IF(OR(H34="",F34=""),"",MAX(H34,MIN(ROUND(H34*(1+Параметры!$B$5),IF(H34*(1+Параметры!$B$5)>=1000,-1,0)),ROUND(F34*Параметры!$B$6,IF(F34*Параметры!$B$6>=1000,-1,0))))) -> 104 | J34: 103 | K34: =IF(OR(J34="",G34=""),"",MAX(J34,MIN(ROUND(J34*(1+Параметры!$B$5),IF(J34*(1+Параметры!$B$5)>=1000,-1,0)),ROUND(G34*Параметры!$B$6,IF(G34*Параметры!$B$6>=1000,-1,0))))) -> 118 | L34: 0.2 | M34: =IF(OR(L34="",L34=0),"",1/L34) -> 5 | N34: =IF(OR(L34="",L34=0),"",Параметры!$B$3/L34) -> 40 | O34: =IF(L34="","",IFERROR(INDEX('Почасовка — ставки и план'!$D$5:$D$24,MATCH($D34,'Почасовка — ставки и план'!$A$5:$A$24,0)),"")) -> 800 | P34: =IF(L34="","",IFERROR(INDEX('Почасовка — ставки и план'!$E$5:$E$24,MATCH($D34,'Почасовка — ставки и план'!$A$5:$A$24,0)),"")) -> 950 | Q34: =IF(OR(L34="",O34=""),"",ROUND(L34*O34,0)) -> 160 | R34: =IF(D34="TEX","аренда техники — сделка/счёт",IF(OR(Q34="",H34="",H34=0),"—",IF(Q34<H34*(1-Параметры!$B$7),"почасовка",IF(Q34>H34*(1+Параметры!$B$7),"сделка","любой способ")))) -> сделка | S34: 0.42666667 | T34: 0.47674419
A35: 1.4.6 | B35: Разборка выравнивающих стяжек цементно-песчаных на кровле | C35: м3 | D35: KRO | E35: =IFERROR(INDEX('Почасовка — ставки и план'!$B$5:$B$24,MATCH(D35,'Почасовка — ставки и план'!$A$5:$A$24,0)),"Аренда техники / механизмы") -> Кровельщик | F35: 10134 | G35: 12034 | H35: 3600 | I35: =IF(OR(H35="",F35=""),"",MAX(H35,MIN(ROUND(H35*(1+Параметры!$B$5),IF(H35*(1+Параметры!$B$5)>=1000,-1,0)),ROUND(F35*Параметры!$B$6,IF(F35*Параметры!$B$6>=1000,-1,0))))) -> 4140 | J35: 4140 | K35: =IF(OR(J35="",G35=""),"",MAX(J35,MIN(ROUND(J35*(1+Параметры!$B$5),IF(J35*(1+Параметры!$B$5)>=1000,-1,0)),ROUND(G35*Параметры!$B$6,IF(G35*Параметры!$B$6>=1000,-1,0))))) -> 4760 | L35: 9.5 | M35: =IF(OR(L35="",L35=0),"",1/L35) -> 0.10526316 | N35: =IF(OR(L35="",L35=0),"",Параметры!$B$3/L35) -> 0.84210526 | O35: =IF(L35="","",IFERROR(INDEX('Почасовка — ставки и план'!$D$5:$D$24,MATCH($D35,'Почасовка — ставки и план'!$A$5:$A$24,0)),"")) -> 800 | P35: =IF(L35="","",IFERROR(INDEX('Почасовка — ставки и план'!$E$5:$E$24,MATCH($D35,'Почасовка — ставки и план'!$A$5:$A$24,0)),"")) -> 950 | Q35: =IF(OR(L35="",O35=""),"",ROUND(L35*O35,0)) -> 7600 | R35: =IF(D35="TEX","аренда техники — сделка/счёт",IF(OR(Q35="",H35="",H35=0),"—",IF(Q35<H35*(1-Параметры!$B$7),"почасовка",IF(Q35>H35*(1+Параметры!$B$7),"сделка","любой способ")))) -> сделка | S35: 0.689 | T35: 0.74405797
A36: 1.4.7 | B36: Разборка монолитных перекрытий бетонных | C36: м3 | D36: RAZ | E36: =IFERROR(INDEX('Почасовка — ставки и план'!$B$5:$B$24,MATCH(D36,'Почасовка — ставки и план'!$A$5:$A$24,0)),"Аренда техники / механизмы") -> Разнорабочий / демонтажник | F36: 9534 | G36: 11440 | H36: 5100 | I36: =IF(OR(H36="",F36=""),"",MAX(H36,MIN(ROUND(H36*(1+Параметры!$B$5),IF(H36*(1+Параметры!$B$5)>=1000,-1,0)),ROUND(F36*Параметры!$B$6,IF(F36*Параметры!$B$6>=1000,-1,0))))) -> 5870 | J36: 5865 | K36: =IF(OR(J36="",G36=""),"",MAX(J36,MIN(ROUND(J36*(1+Параметры!$B$5),IF(J36*(1+Параметры!$B$5)>=1000,-1,0)),ROUND(G36*Параметры!$B$6,IF(G36*Параметры!$B$6>=1000,-1,0))))) -> 6740 | L36: 13 | M36: =IF(OR(L36="",L36=0),"",1/L36) -> 0.076923077 | N36: =IF(OR(L36="",L36=0),"",Параметры!$B$3/L36) -> 0.61538462 | O36: =IF(L36="","",IFERROR(INDEX('Почасовка — ставки и план'!$D$5:$D$24,MATCH($D36,'Почасовка — ставки и план'!$A$5:$A$24,0)),"")) -> 550 | P36: =IF(L36="","",IFERROR(INDEX('Почасовка — ставки и план'!$E$5:$E$24,MATCH($D36,'Почасовка — ставки и план'!$A$5:$A$24,0)),"")) -> 660 | Q36: =IF(OR(L36="",O36=""),"",ROUND(L36*O36,0)) -> 7150 | R36: =IF(D36="TEX","аренда техники — сделка/счёт",IF(OR(Q36="",H36="",H36=0),"—",IF(Q36<H36*(1-Параметры!$B$7),"почасовка",IF(Q36>H36*(1+Параметры!$B$7),"сделка","любой способ")))) -> сделка | S36: 0.12164706 | T36: 0.17033248
A37: 1.4.8 | B37: Разборка монолитных перекрытий железобетонных | C37: м3 | D37: RAZ | E37: =IFERROR(INDEX('Почасовка — ставки и план'!$B$5:$B$24,MATCH(D37,'Почасовка — ставки и план'!$A$5:$A$24,0)),"Аренда техники / механизмы") -> Разнорабочий / демонтажник | F37: 12467 | G37: 14960 | H37: 6600 | I37: =IF(OR(H37="",F37=""),"",MAX(H37,MIN(ROUND(H37*(1+Параметры!$B$5),IF(H37*(1+Параметры!$B$5)>=1000,-1,0)),ROUND(F37*Параметры!$B$6,IF(F37*Параметры!$B$6>=1000,-1,0))))) -> 7590 | J37: 7788 | K37: =IF(OR(J37="",G37=""),"",MAX(J37,MIN(ROUND(J37*(1+Параметры!$B$5),IF(J37*(1+Параметры!$B$5)>=1000,-1,0)),ROUND(G37*Параметры!$B$6,IF(G37*Параметры!$B$6>=1000,-1,0))))) -> 8960 | L37: 17 | M37: =IF(OR(L37="",L37=0),"",1/L37) -> 0.058823529 | N37: =IF(OR(L37="",L37=0),"",Параметры!$B$3/L37) -> 0.47058824 | O37: =IF(L37="","",IFERROR(INDEX('Почасовка — ставки и план'!$D$5:$D$24,MATCH($D37,'Почасовка — ставки и план'!$A$5:$A$24,0)),"")) -> 550 | P37: =IF(L37="","",IFERROR(INDEX('Почасовка — ставки и план'!$E$5:$E$24,MATCH($D37,'Почасовка — ставки и план'!$A$5:$A$24,0)),"")) -> 660 | Q37: =IF(OR(L37="",O37=""),"",ROUND(L37*O37,0)) -> 9350 | R37: =IF(D37="TEX","аренда техники — сделка/счёт",IF(OR(Q37="",H37="",H37=0),"—",IF(Q37<H37*(1-Параметры!$B$7),"почасовка",IF(Q37>H37*(1+Параметры!$B$7),"сделка","любой способ")))) -> сделка | S37: 0.13336364 | T37: 0.13333333
A38: 1.4.9 | B38: Разборка парапетных решеток | C38: мп | D38: KRO | E38: =IFERROR(INDEX('Почасовка — ставки и план'!$B$5:$B$24,MATCH(D38,'Почасовка — ставки и план'!$A$5:$A$24,0)),"Аренда техники / механизмы") -> Кровельщик | F38: 427 | G38: 507 | H38: 150 | I38: =IF(OR(H38="",F38=""),"",MAX(H38,MIN(ROUND(H38*(1+Параметры!$B$5),IF(H38*(1+Параметры!$B$5)>=1000,-1,0)),ROUND(F38*Параметры!$B$6,IF(F38*Параметры!$B$6>=1000,-1,0))))) -> 173 | J38: 172 | K38: =IF(OR(J38="",G38=""),"",MAX(J38,MIN(ROUND(J38*(1+Параметры!$B$5),IF(J38*(1+Параметры!$B$5)>=1000,-1,0)),ROUND(G38*Параметры!$B$6,IF(G38*Параметры!$B$6>=1000,-1,0))))) -> 198 | L38: 0.4 | M38: =IF(OR(L38="",L38=0),"",1/L38) -> 2.5 | N38: =IF(OR(L38="",L38=0),"",Параметры!$B$3/L38) -> 20 | O38: =IF(L38="","",IFERROR(INDEX('Почасовка — ставки и план'!$D$5:$D$24,MATCH($D38,'Почасовка — ставки и план'!$A$5:$A$24,0)),"")) -> 800 | P38: =IF(L38="","",IFERROR(INDEX('Почасовка — ставки и план'!$E$5:$E$24,MATCH($D38,'Почасовка — ставки и план'!$A$5:$A$24,0)),"")) -> 950 | Q38: =IF(OR(L38="",O38=""),"",ROUND(L38*O38,0)) -> 320 | R38: =IF(D38="TEX","аренда техники — сделка/счёт",IF(OR(Q38="",H38="",H38=0),"—",IF(Q38<H38*(1-Параметры!$B$7),"почасовка",IF(Q38>H38*(1+Параметры!$B$7),"сделка","любой способ")))) -> сделка | S38: 0.708 | T38: 0.76041667
A39: 1.4.10 | B39: Разборка покрытий кровель из волнистых и полуволнистых асбестоцементных листов | C39: м2 | D39: KRO | E39: =IFERROR(INDEX('Почасовка — ставки и план'!$B$5:$B$24,MATCH(D39,'Почасовка — ставки и план'!$A$5:$A$24,0)),"Аренда техники / механизмы") -> Кровельщик | F39: 267 | G39: 318 | H39: 130 | I39: =IF(OR(H39="",F39=""),"",MAX(H39,MIN(ROUND(H39*(1+Параметры!$B$5),IF(H39*(1+Параметры!$B$5)>=1000,-1,0)),ROUND(F39*Параметры!$B$6,IF(F39*Параметры!$B$6>=1000,-1,0))))) -> 150 | J39: 150 | K39: =IF(OR(J39="",G39=""),"",MAX(J39,MIN(ROUND(J39*(1+Параметры!$B$5),IF(J39*(1+Параметры!$B$5)>=1000,-1,0)),ROUND(G39*Параметры!$B$6,IF(G39*Параметры!$B$6>=1000,-1,0))))) -> 173 | L39: 0.25 | M39: =IF(OR(L39="",L39=0),"",1/L39) -> 4 | N39: =IF(OR(L39="",L39=0),"",Параметры!$B$3/L39) -> 32 | O39: =IF(L39="","",IFERROR(INDEX('Почасовка — ставки и план'!$D$5:$D$24,MATCH($D39,'Почасовка — ставки и план'!$A$5:$A$24,0)),"")) -> 800 | P39: =IF(L39="","",IFERROR(INDEX('Почасовка — ставки и план'!$E$5:$E$24,MATCH($D39,'Почасовка — ставки и план'!$A$5:$A$24,0)),"")) -> 950 | Q39: =IF(OR(L39="",O39=""),"",ROUND(L39*O39,0)) -> 200 | R39: =IF(D39="TEX","аренда техники — сделка/счёт",IF(OR(Q39="",H39="",H39=0),"—",IF(Q39<H39*(1-Параметры!$B$7),"почасовка",IF(Q39>H39*(1+Параметры!$B$7),"сделка","любой способ")))) -> сделка | S39: 0.21363636 | T39: 0.256917
A40: 1.4.11 | B40: Разборка покрытий кровель из листовой стали | C40: м2 | D40: KRO | E40: =IFERROR(INDEX('Почасовка — ставки и план'!$B$5:$B$24,MATCH(D40,'Почасовка — ставки и план'!$A$5:$A$24,0)),"Аренда техники / механизмы") -> Кровельщик | F40: 192 | G40: 228 | H40: 90 | I40: =IF(OR(H40="",F40=""),"",MAX(H40,MIN(ROUND(H40*(1+Параметры!$B$5),IF(H40*(1+Параметры!$B$5)>=1000,-1,0)),ROUND(F40*Параметры!$B$6,IF(F40*Параметры!$B$6>=1000,-1,0))))) -> 104 | J40: 103 | K40: =IF(OR(J40="",G40=""),"",MAX(J40,MIN(ROUND(J40*(1+Параметры!$B$5),IF(J40*(1+Параметры!$B$5)>=1000,-1,0)),ROUND(G40*Параметры!$B$6,IF(G40*Параметры!$B$6>=1000,-1,0))))) -> 118 | L40: 0.18 | M40: =IF(OR(L40="",L40=0),"",1/L40) -> 5.5555556 | N40: =IF(OR(L40="",L40=0),"",Параметры!$B$3/L40) -> 44.444444 | O40: =IF(L40="","",IFERROR(INDEX('Почасовка — ставки и план'!$D$5:$D$24,MATCH($D40,'Почасовка — ставки и план'!$A$5:$A$24,0)),"")) -> 800 | P40: =IF(L40="","",IFERROR(INDEX('Почасовка — ставки и план'!$E$5:$E$24,MATCH($D40,'Почасовка — ставки и план'!$A$5:$A$24,0)),"")) -> 950 | Q40: =IF(OR(L40="",O40=""),"",ROUND(L40*O40,0)) -> 144 | R40: =IF(D40="TEX","аренда техники — сделка/счёт",IF(OR(Q40="",H40="",H40=0),"—",IF(Q40<H40*(1-Параметры!$B$7),"почасовка",IF(Q40>H40*(1+Параметры!$B$7),"сделка","любой способ")))) -> сделка | S40: 0.28 | T40: 0.3255814
A41: 1.4.12 | B41: Разборка покрытий кровель из рулонных материалов (добавляется на каждый последующий слой сверх 4х слоев) | C41: м2 | D41: KRO | E41: =IFERROR(INDEX('Почасовка — ставки и план'!$B$5:$B$24,MATCH(D41,'Почасовка — ставки и план'!$A$5:$A$24,0)),"Аренда техники / механизмы") -> Кровельщик | F41: 54 | G41: 64 | H41: 25 | I41: =IF(OR(H41="",F41=""),"",MAX(H41,MIN(ROUND(H41*(1+Параметры!$B$5),IF(H41*(1+Параметры!$B$5)>=1000,-1,0)),ROUND(F41*Параметры!$B$6,IF(F41*Параметры!$B$6>=1000,-1,0))))) -> 29 | J41: 28.5 | K41: =IF(OR(J41="",G41=""),"",MAX(J41,MIN(ROUND(J41*(1+Параметры!$B$5),IF(J41*(1+Параметры!$B$5)>=1000,-1,0)),ROUND(G41*Параметры!$B$6,IF(G41*Параметры!$B$6>=1000,-1,0))))) -> 33 | L41: 0.05 | M41: =IF(OR(L41="",L41=0),"",1/L41) -> 20 | N41: =IF(OR(L41="",L41=0),"",Параметры!$B$3/L41) -> 160 | O41: =IF(L41="","",IFERROR(INDEX('Почасовка — ставки и план'!$D$5:$D$24,MATCH($D41,'Почасовка — ставки и план'!$A$5:$A$24,0)),"")) -> 800 | P41: =IF(L41="","",IFERROR(INDEX('Почасовка — ставки и план'!$E$5:$E$24,MATCH($D41,'Почасовка — ставки и план'!$A$5:$A$24,0)),"")) -> 950 | Q41: =IF(OR(L41="",O41=""),"",ROUND(L41*O41,0)) -> 40 | R41: =IF(D41="TEX","аренда техники — сделка/счёт",IF(OR(Q41="",H41="",H41=0),"—",IF(Q41<H41*(1-Параметры!$B$7),"почасовка",IF(Q41>H41*(1+Параметры!$B$7),"сделка","любой способ")))) -> сделка | S41: 0.35 | T41: 0.39130435
... A49: 1.4.N5 | B49: Демонтаж зенитного фонаря / люка дымоудаления | C49: шт | D49: KRO | E49: =IFERROR(INDEX('Почасовка — ставки и план'!$B$5:$B$24,MATCH(D49,'Почасовка — ставки и план'!$A$5:$A$24,0)),"Аренда техники / механизмы") -> Кровельщик | F49: 6000 | G49: 6900 | H49: 3600 | I49: =IF(OR(H49="",F49=""),"",MAX(H49,MIN(ROUND(H49*(1+Параметры!$B$5),IF(H49*(1+Параметры!$B$5)>=1000,-1,0)),ROUND(F49*Параметры!$B$6,IF(F49*Параметры!$B$6>=1000,-1,0))))) -> 4140 | J49: 4140 | K49: =IF(OR(J49="",G49=""),"",MAX(J49,MIN(ROUND(J49*(1+Параметры!$B$5),IF(J49*(1+Параметры!$B$5)>=1000,-1,0)),ROUND(G49*Параметры!$B$6,IF(G49*Параметры!$B$6>=1000,-1,0))))) -> 4760 | L49: 4 | M49: =IF(OR(L49="",L49=0),"",1/L49) -> 0.25 | N49: =IF(OR(L49="",L49=0),"",Параметры!$B$3/L49) -> 2 | O49: =IF(L49="","",IFERROR(INDEX('Почасовка — ставки и план'!$D$5:$D$24,MATCH($D49,'Почасовка — ставки и план'!$A$5:$A$24,0)),"")) -> 800 | P49: =IF(L49="","",IFERROR(INDEX('Почасовка — ставки и план'!$E$5:$E$24,MATCH($D49,'Почасовка — ставки и план'!$A$5:$A$24,0)),"")) -> 950 | Q49: =IF(OR(L49="",O49=""),"",ROUND(L49*O49,0)) -> 3200 | R49: =IF(D49="TEX","аренда техники — сделка/счёт",IF(OR(Q49="",H49="",H49=0),"—",IF(Q49<H49*(1-Параметры!$B$7),"почасовка",IF(Q49>H49*(1+Параметры!$B$7),"сделка","любой способ")))) -> почасовка | S49: 0 | T49: 0
A50: 1.5 Демонтажные работы в здании
A51: 1.5.1 | B51: Демонтаж металлических балок, ригелей перекрытия, покрытия | C51: тн | D51: SVA | E51: =IFERROR(INDEX('Почасовка — ставки и план'!$B$5:$B$24,MATCH(D51,'Почасовка — ставки и план'!$A$5:$A$24,0)),"Аренда техники / механизмы") -> Сварщик / монтажник МК | F51: 24000 | G51: 28800 | H51: 7200 | I51: =IF(OR(H51="",F51=""),"",MAX(H51,MIN(ROUND(H51*(1+Параметры!$B$5),IF(H51*(1+Параметры!$B$5)>=1000,-1,0)),ROUND(F51*Параметры!$B$6,IF(F51*Параметры!$B$6>=1000,-1,0))))) -> 8280 | J51: 8280 | K51: =IF(OR(J51="",G51=""),"",MAX(J51,MIN(ROUND(J51*(1+Параметры!$B$5),IF(J51*(1+Параметры!$B$5)>=1000,-1,0)),ROUND(G51*Параметры!$B$6,IF(G51*Параметры!$B$6>=1000,-1,0))))) -> 9520 | L51: 20 | M51: =IF(OR(L51="",L51=0),"",1/L51) -> 0.05 | N51: =IF(OR(L51="",L51=0),"",Параметры!$B$3/L51) -> 0.4 | O51: =IF(L51="","",IFERROR(INDEX('Почасовка — ставки и план'!$D$5:$D$24,MATCH($D51,'Почасовка — ставки и план'!$A$5:$A$24,0)),"")) -> 900 | P51: =IF(L51="","",IFERROR(INDEX('Почасовка — ставки и план'!$E$5:$E$24,MATCH($D51,'Почасовка — ставки и план'!$A$5:$A$24,0)),"")) -> 1080 | Q51: =IF(OR(L51="",O51=""),"",ROUND(L51*O51,0)) -> 18000 | R51: =IF(D51="TEX","аренда техники — сделка/счёт",IF(OR(Q51="",H51="",H51=0),"—",IF(Q51<H51*(1-Параметры!$B$7),"почасовка",IF(Q51>H51*(1+Параметры!$B$7),"сделка","любой способ")))) -> сделка | S51: 1 | T51: 1.0869565
A52: 1.5.2 | B52: Демонтаж железобетонных конструкций. При объеме более 1 м3 - при помощи отбойных молотков | C52: м3 | D52: RAZ | E52: =IFERROR(INDEX('Почасовка — ставки и план'!$B$5:$B$24,MATCH(D52,'Почасовка — ставки и план'!$A$5:$A$24,0)),"Аренда техники / механизмы") -> Разнорабочий / демонтажник | F52: 12467 | G52: 14960 | H52: 6600 | I52: =IF(OR(H52="",F52=""),"",MAX(H52,MIN(ROUND(H52*(1+Параметры!$B$5),IF(H52*(1+Параметры!$B$5)>=1000,-1,0)),ROUND(F52*Параметры!$B$6,IF(F52*Параметры!$B$6>=1000,-1,0))))) -> 7590 | J52: 7788 | K52: =IF(OR(J52="",G52=""),"",MAX(J52,MIN(ROUND(J52*(1+Параметры!$B$5),IF(J52*(1+Параметры!$B$5)>=1000,-1,0)),ROUND(G52*Параметры!$B$6,IF(G52*Параметры!$B$6>=1000,-1,0))))) -> 8960 | L52: 17 | M52: =IF(OR(L52="",L52=0),"",1/L52) -> 0.058823529 | N52: =IF(OR(L52="",L52=0),"",Параметры!$B$3/L52) -> 0.47058824 | O52: =IF(L52="","",IFERROR(INDEX('Почасовка — ставки и план'!$D$5:$D$24,MATCH($D52,'Почасовка — ставки и план'!$A$5:$A$24,0)),"")) -> 550 | P52: =IF(L52="","",IFERROR(INDEX('Почасовка — ставки и план'!$E$5:$E$24,MATCH($D52,'Почасовка — ставки и план'!$A$5:$A$24,0)),"")) -> 660 | Q52: =IF(OR(L52="",O52=""),"",ROUND(L52*O52,0)) -> 9350 | R52: =IF(D52="TEX","аренда техники — сделка/счёт",IF(OR(Q52="",H52="",H52=0),"—",IF(Q52<H52*(1-Параметры!$B$7),"почасовка",IF(Q52>H52*(1+Параметры!$B$7),"сделка","любой способ")))) -> сделка | S52: 0.13336364 | T52: 0.13333333
A53: 1.5.3 | B53: Демонтаж бетонных конструкций | C53: м3 | D53: RAZ | E53: =IFERROR(INDEX('Почасовка — ставки и план'!$B$5:$B$24,MATCH(D53,'Почасовка — ставки и план'!$A$5:$A$24,0)),"Аренда техники / механизмы") -> Разнорабочий / демонтажник | F53: 9534 | G53: 11440 | H53: 5100 | I53: =IF(OR(H53="",F53=""),"",MAX(H53,MIN(ROUND(H53*(1+Параметры!$B$5),IF(H53*(1+Параметры!$B$5)>=1000,-1,0)),ROUND(F53*Параметры!$B$6,IF(F53*Параметры!$B$6>=1000,-1,0))))) -> 5870 | J53: 6018 | K53: =IF(OR(J53="",G53=""),"",MAX(J53,MIN(ROUND(J53*(1+Параметры!$B$5),IF(J53*(1+Параметры!$B$5)>=1000,-1,0)),ROUND(G53*Параметры!$B$6,IF(G53*Параметры!$B$6>=1000,-1,0))))) -> 6920 | L53: 13 | M53: =IF(OR(L53="",L53=0),"",1/L53) -> 0.076923077 | N53: =IF(OR(L53="",L53=0),"",Параметры!$B$3/L53) -> 0.61538462 | O53: =IF(L53="","",IFERROR(INDEX('Почасовка — ставки и план'!$D$5:$D$24,MATCH($D53,'Почасовка — ставки и план'!$A$5:$A$24,0)),"")) -> 550 | P53: =IF(L53="","",IFERROR(INDEX('Почасовка — ставки и план'!$E$5:$E$24,MATCH($D53,'Почасовка — ставки и план'!$A$5:$A$24,0)),"")) -> 660 | Q53: =IF(OR(L53="",O53=""),"",ROUND(L53*O53,0)) -> 7150 | R53: =IF(D53="TEX","аренда техники — сделка/счёт",IF(OR(Q53="",H53="",H53=0),"—",IF(Q53<H53*(1-Параметры!$B$7),"почасовка",IF(Q53>H53*(1+Параметры!$B$7),"сделка","любой способ")))) -> сделка | S53: 0.12164706 | T53: 0.12156863
A54: 1.5.4 | B54: Демонтаж металлоконструкций | C54: тн | D54: SVA | E54: =IFERROR(INDEX('Почасовка — ставки и план'!$B$5:$B$24,MATCH(D54,'Почасовка — ставки и план'!$A$5:$A$24,0)),"Аренда техники / механизмы") -> Сварщик / монтажник МК | F54: 14400 | G54: 17280 | H54: 4500 | I54: =IF(OR(H54="",F54=""),"",MAX(H54,MIN(ROUND(H54*(1+Параметры!$B$5),IF(H54*(1+Параметры!$B$5)>=1000,-1,0)),ROUND(F54*Параметры!$B$6,IF(F54*Параметры!$B$6>=1000,-1,0))))) -> 5180 | J54: 5175 | K54: =IF(OR(J54="",G54=""),"",MAX(J54,MIN(ROUND(J54*(1+Параметры!$B$5),IF(J54*(1+Параметры!$B$5)>=1000,-1,0)),ROUND(G54*Параметры!$B$6,IF(G54*Параметры!$B$6>=1000,-1,0))))) -> 5950 | L54: 12 | M54: =IF(OR(L54="",L54=0),"",1/L54) -> 0.083333333 | N54: =IF(OR(L54="",L54=0),"",Параметры!$B$3/L54) -> 0.66666667 | O54: =IF(L54="","",IFERROR(INDEX('Почасовка — ставки и план'!$D$5:$D$24,MATCH($D54,'Почасовка — ставки и план'!$A$5:$A$24,0)),"")) -> 900 | P54: =IF(L54="","",IFERROR(INDEX('Почасовка — ставки и план'!$E$5:$E$24,MATCH($D54,'Почасовка — ставки и план'!$A$5:$A$24,0)),"")) -> 1080 | Q54: =IF(OR(L54="",O54=""),"",ROUND(L54*O54,0)) -> 10800 | R54: =IF(D54="TEX","аренда техники — сделка/счёт",IF(OR(Q54="",H54="",H54=0),"—",IF(Q54<H54*(1-Параметры!$B$7),"почасовка",IF(Q54>H54*(1+Параметры!$B$7),"сделка","любой способ")))) -> сделка | S54: 0.92 | T54: 1.0034783
A55: 1.5.5 | B55: Алмазная резка железобетонных конструкций глубиной 230 мм | C55: м реза | D55: BET | E55: =IFERROR(INDEX('Почасовка — ставки и план'!$B$5:$B$24,MATCH(D55,'Почасовка — ставки и план'!$A$5:$A$24,0)),"Аренда техники / механизмы") -> Бетонщик / арматурщик | F55: 2000 | G55: 2300 | H55: 1200 | I55: =IF(OR(H55="",F55=""),"",MAX(H55,MIN(ROUND(H55*(1+Параметры!$B$5),IF(H55*(1+Параметры!$B$5)>=1000,-1,0)),ROUND(F55*Параметры!$B$6,IF(F55*Параметры!$B$6>=1000,-1,0))))) -> 1380 | J55: 1380 | K55: =IF(OR(J55="",G55=""),"",MAX(J55,MIN(ROUND(J55*(1+Параметры!$B$5),IF(J55*(1+Параметры!$B$5)>=1000,-1,0)),ROUND(G55*Параметры!$B$6,IF(G55*Параметры!$B$6>=1000,-1,0))))) -> 1590 | L55: 1 | M55: =IF(OR(L55="",L55=0),"",1/L55) -> 1 | N55: =IF(OR(L55="",L55=0),"",Параметры!$B$3/L55) -> 8 | O55: =IF(L55="","",IFERROR(INDEX('Почасовка — ставки и план'!$D$5:$D$24,MATCH($D55,'Почасовка — ставки и план'!$A$5:$A$24,0)),"")) -> 800 | P55: =IF(L55="","",IFERROR(INDEX('Почасовка — ставки и план'!$E$5:$E$24,MATCH($D55,'Почасовка — ставки и план'!$A$5:$A$24,0)),"")) -> 950 | Q55: =IF(OR(L55="",O55=""),"",ROUND(L55*O55,0)) -> 800 | R55: =IF(D55="TEX","аренда техники — сделка/счёт",IF(OR(Q55="",H55="",H55=0),"—",IF(Q55<H55*(1-Параметры!$B$7),"почасовка",IF(Q55>H55*(1+Параметры!$B$7),"сделка","любой способ")))) -> почасовка | S55: 0 | T55: 0
A56: 1.5.6 | B56: На каждые 100 мм увеличения глубины реза добавлять к расценке по алмазной резке ж/б конструкций | C56: м реза | D56: BET | E56: =IFERROR(INDEX('Почасовка — ставки и план'!$B$5:$B$24,MATCH(D56,'Почасовка — ставки и план'!$A$5:$A$24,0)),"Аренда техники / механизмы") -> Бетонщик / арматурщик | F56: 800 | G56: 920 | H56: 480 | I56: =IF(OR(H56="",F56=""),"",MAX(H56,MIN(ROUND(H56*(1+Параметры!$B$5),IF(H56*(1+Параметры!$B$5)>=1000,-1,0)),ROUND(F56*Параметры!$B$6,IF(F56*Параметры!$B$6>=1000,-1,0))))) -> 552 | J56: 552 | K56: =IF(OR(J56="",G56=""),"",MAX(J56,MIN(ROUND(J56*(1+Параметры!$B$5),IF(J56*(1+Параметры!$B$5)>=1000,-1,0)),ROUND(G56*Параметры!$B$6,IF(G56*Параметры!$B$6>=1000,-1,0))))) -> 635 | L56: 0.4 | M56: =IF(OR(L56="",L56=0),"",1/L56) -> 2.5 | N56: =IF(OR(L56="",L56=0),"",Параметры!$B$3/L56) -> 20 | O56: =IF(L56="","",IFERROR(INDEX('Почасовка — ставки и план'!$D$5:$D$24,MATCH($D56,'Почасовка — ставки и план'!$A$5:$A$24,0)),"")) -> 800 | P56: =IF(L56="","",IFERROR(INDEX('Почасовка — ставки и план'!$E$5:$E$24,MATCH($D56,'Почасовка — ставки и план'!$A$5:$A$24,0)),"")) -> 950 | Q56: =IF(OR(L56="",O56=""),"",ROUND(L56*O56,0)) -> 320 | R56: =IF(D56="TEX","аренда техники — сделка/счёт",IF(OR(Q56="",H56="",H56=0),"—",IF(Q56<H56*(1-Параметры!$B$7),"почасовка",IF(Q56>H56*(1+Параметры!$B$7),"сделка","любой способ")))) -> почасовка | S56: 0 | T56: 0
A57: 1.5.N1 | B57: Алмазное бурение отверстия в ж/б Ø до 100 мм глубиной до 200 мм | C57: шт | D57: BET | E57: =IFERROR(INDEX('Почасовка — ставки и план'!$B$5:$B$24,MATCH(D57,'Почасовка — ставки и план'!$A$5:$A$24,0)),"Аренда техники / механизмы") -> Бетонщик / арматурщик | F57: 1200 | G57: 1380 | H57: 720 | I57: =IF(OR(H57="",F57=""),"",MAX(H57,MIN(ROUND(H57*(1+Параметры!$B$5),IF(H57*(1+Параметры!$B$5)>=1000,-1,0)),ROUND(F57*Параметры!$B$6,IF(F57*Параметры!$B$6>=1000,-1,0))))) -> 828 | J57: 828 | K57: =IF(OR(J57="",G57=""),"",MAX(J57,MIN(ROUND(J57*(1+Параметры!$B$5),IF(J57*(1+Параметры!$B$5)>=1000,-1,0)),ROUND(G57*Параметры!$B$6,IF(G57*Параметры!$B$6>=1000,-1,0))))) -> 952 | L57: 0.6 | M57: =IF(OR(L57="",L57=0),"",1/L57) -> 1.6666667 | N57: =IF(OR(L57="",L57=0),"",Параметры!$B$3/L57) -> 13.333333 | O57: =IF(L57="","",IFERROR(INDEX('Почасовка — ставки и план'!$D$5:$D$24,MATCH($D57,'Почасовка — ставки и план'!$A$5:$A$24,0)),"")) -> 800 | P57: =IF(L57="","",IFERROR(INDEX('Почасовка — ставки и план'!$E$5:$E$24,MATCH($D57,'Почасовка — ставки и план'!$A$5:$A$24,0)),"")) -> 950 | Q57: =IF(OR(L57="",O57=""),"",ROUND(L57*O57,0)) -> 480 | R57: =IF(D57="TEX","аренда техники — сделка/счёт",IF(OR(Q57="",H57="",H57=0),"—",IF(Q57<H57*(1-Параметры!$B$7),"почасовка",IF(Q57>H57*(1+Параметры!$B$7),"сделка","любой способ")))) -> почасовка | S57: 0 | T57: 0
A58: 1.5.N2 | B58: Демонтаж металлических лестниц, площадок, антресолей | C58: т | D58: SVA | E58: =IFERROR(INDEX('Почасовка — ставки и план'!$B$5:$B$24,MATCH(D58,'Почасовка — ставки и план'!$A$5:$A$24,0)),"Аренда техники / механизмы") -> Сварщик / монтажник МК | F58: 21600 | G58: 25920 | H58: 7200 | I58: =IF(OR(H58="",F58=""),"",MAX(H58,MIN(ROUND(H58*(1+Параметры!$B$5),IF(H58*(1+Параметры!$B$5)>=1000,-1,0)),ROUND(F58*Параметры!$B$6,IF(F58*Параметры!$B$6>=1000,-1,0))))) -> 8280 | J58: 8280 | K58: =IF(OR(J58="",G58=""),"",MAX(J58,MIN(ROUND(J58*(1+Параметры!$B$5),IF(J58*(1+Параметры!$B$5)>=1000,-1,0)),ROUND(G58*Параметры!$B$6,IF(G58*Параметры!$B$6>=1000,-1,0))))) -> 9520 | L58: 18 | M58: =IF(OR(L58="",L58=0),"",1/L58) -> 0.055555556 | N58: =IF(OR(L58="",L58=0),"",Параметры!$B$3/L58) -> 0.44444444 | O58: =IF(L58="","",IFERROR(INDEX('Почасовка — ставки и план'!$D$5:$D$24,MATCH($D58,'Почасовка — ставки и план'!$A$5:$A$24,0)),"")) -> 900 | P58: =IF(L58="","",IFERROR(INDEX('Почасовка — ставки и план'!$E$5:$E$24,MATCH($D58,'Почасовка — ставки и план'!$A$5:$A$24,0)),"")) -> 1080 | Q58: =IF(OR(L58="",O58=""),"",ROUND(L58*O58,0)) -> 16200 | R58: =IF(D58="TEX","аренда техники — сделка/счёт",IF(OR(Q58="",H58="",H58=0),"—",IF(Q58<H58*(1-Параметры!$B$7),"почасовка",IF(Q58>H58*(1+Параметры!$B$7),"сделка","любой способ")))) -> сделка | S58: 0.8 | T58: 0.87826087
A59: 1.6 Демонтажные работы полов
A60: 1.6.1 | B60: Демонтаж стяжек полов до основания | C60: м3 | D60: RAZ | E60: =IFERROR(INDEX('Почасовка — ставки и план'!$B$5:$B$24,MATCH(D60,'Почасовка — ставки и план'!$A$5:$A$24,0)),"Аренда техники / механизмы") -> Разнорабочий / демонтажник | F60: 6600 | G60: 7920 | H60: 3900 | I60: =IF(OR(H60="",F60=""),"",MAX(H60,MIN(ROUND(H60*(1+Параметры!$B$5),IF(H60*(1+Параметры!$B$5)>=1000,-1,0)),ROUND(F60*Параметры!$B$6,IF(F60*Параметры!$B$6>=1000,-1,0))))) -> 4490 | J60: 4485 | K60: =IF(OR(J60="",G60=""),"",MAX(J60,MIN(ROUND(J60*(1+Параметры!$B$5),IF(J60*(1+Параметры!$B$5)>=1000,-1,0)),ROUND(G60*Параметры!$B$6,IF(G60*Параметры!$B$6>=1000,-1,0))))) -> 5160 | L60: 9 | M60: =IF(OR(L60="",L60=0),"",1/L60) -> 0.11111111 | N60: =IF(OR(L60="",L60=0),"",Параметры!$B$3/L60) -> 0.88888889 | O60: =IF(L60="","",IFERROR(INDEX('Почасовка — ставки и план'!$D$5:$D$24,MATCH($D60,'Почасовка — ставки и план'!$A$5:$A$24,0)),"")) -> 550 | P60: =IF(L60="","",IFERROR(INDEX('Почасовка — ставки и план'!$E$5:$E$24,MATCH($D60,'Почасовка — ставки и план'!$A$5:$A$24,0)),"")) -> 660 | Q60: =IF(OR(L60="",O60=""),"",ROUND(L60*O60,0)) -> 4950 | R60: =IF(D60="TEX","аренда техники — сделка/счёт",IF(OR(Q60="",H60="",H60=0),"—",IF(Q60<H60*(1-Параметры!$B$7),"почасовка",IF(Q60>H60*(1+Параметры!$B$7),"сделка","любой способ")))) -> сделка | S60: 0.015384615 | T60: 0.059531773
A61: 1.6.2 | B61: Разборка бетонных оснований под полы | C61: м3 | D61: RAZ | E61: =IFERROR(INDEX('Почасовка — ставки и план'!$B$5:$B$24,MATCH(D61,'Почасовка — ставки и план'!$A$5:$A$24,0)),"Аренда техники / механизмы") -> Разнорабочий / демонтажник | F61: 8800 | G61: 10560 | H61: 4800 | I61: =IF(OR(H61="",F61=""),"",MAX(H61,MIN(ROUND(H61*(1+Параметры!$B$5),IF(H61*(1+Параметры!$B$5)>=1000,-1,0)),ROUND(F61*Параметры!$B$6,IF(F61*Параметры!$B$6>=1000,-1,0))))) -> 5520 | J61: 5520 | K61: =IF(OR(J61="",G61=""),"",MAX(J61,MIN(ROUND(J61*(1+Параметры!$B$5),IF(J61*(1+Параметры!$B$5)>=1000,-1,0)),ROUND(G61*Параметры!$B$6,IF(G61*Параметры!$B$6>=1000,-1,0))))) -> 6350 | L61: 12 | M61: =IF(OR(L61="",L61=0),"",1/L61) -> 0.083333333 | N61: =IF(OR(L61="",L61=0),"",Параметры!$B$3/L61) -> 0.66666667 | O61: =IF(L61="","",IFERROR(INDEX('Почасовка — ставки и план'!$D$5:$D$24,MATCH($D61,'Почасовка — ставки и план'!$A$5:$A$24,0)),"")) -> 550 | P61: =IF(L61="","",IFERROR(INDEX('Почасовка — ставки и план'!$E$5:$E$24,MATCH($D61,'Почасовка — ставки и план'!$A$5:$A$24,0)),"")) -> 660 | Q61: =IF(OR(L61="",O61=""),"",ROUND(L61*O61,0)) -> 6600 | R61: =IF(D61="TEX","аренда техники — сделка/счёт",IF(OR(Q61="",H61="",H61=0),"—",IF(Q61<H61*(1-Параметры!$B$7),"почасовка",IF(Q61>H61*(1+Параметры!$B$7),"сделка","любой способ")))) -> сделка | S61: 0.1 | T61: 0.14782609
A62: 1.6.3 | B62: Разборка плинтусов деревянных и из пластмассовых материалов | C62: мп | D62: RAZ | E62: =IFERROR(INDEX('Почасовка — ставки и план'!$B$5:$B$24,MATCH(D62,'Почасовка — ставки и план'!$A$5:$A$24,0)),"Аренда техники / механизмы") -> Разнорабочий / демонтажник | F62: 50 | G62: 57.5 | H62: 30 | I62: =IF(OR(H62="",F62=""),"",MAX(H62,MIN(ROUND(H62*(1+Параметры!$B$5),IF(H62*(1+Параметры!$B$5)>=1000,-1,0)),ROUND(F62*Параметры!$B$6,IF(F62*Параметры!$B$6>=1000,-1,0))))) -> 35 | J62: 34.5 | K62: =IF(OR(J62="",G62=""),"",MAX(J62,MIN(ROUND(J62*(1+Параметры!$B$5),IF(J62*(1+Параметры!$B$5)>=1000,-1,0)),ROUND(G62*Параметры!$B$6,IF(G62*Параметры!$B$6>=1000,-1,0))))) -> 40 | L62: 0.05 | M62: =IF(OR(L62="",L62=0),"",1/L62) -> 20 | N62: =IF(OR(L62="",L62=0),"",Параметры!$B$3/L62) -> 160 | O62: =IF(L62="","",IFERROR(INDEX('Почасовка — ставки и план'!$D$5:$D$24,MATCH($D62,'Почасовка — ставки и план'!$A$5:$A$24,0)),"")) -> 550 | P62: =IF(L62="","",IFERROR(INDEX('Почасовка — ставки и план'!$E$5:$E$24,MATCH($D62,'Почасовка — ставки и план'!$A$5:$A$24,0)),"")) -> 660 | Q62: =IF(OR(L62="",O62=""),"",ROUND(L62*O62,0)) -> 28 | R62: =IF(D62="TEX","аренда техники — сделка/счёт",IF(OR(Q62="",H62="",H62=0),"—",IF(Q62<H62*(1-Параметры!$B$7),"почасовка",IF(Q62>H62*(1+Параметры!$B$7),"сделка","любой способ")))) -> любой способ | S62: 0 | T62: 0
A63: 1.6.4 | B63: Разборка плинтусов цементных и из керамогранита | C63: мп | D63: RAZ | E63: =IFERROR(INDEX('Почасовка — ставки и план'!$B$5:$B$24,MATCH(D63,'Почасовка — ставки и план'!$A$5:$A$24,0)),"Аренда техники / механизмы") -> Разнорабочий / демонтажник | F63: 120 | G63: 138 | H63: 70 | I63: =IF(OR(H63="",F63=""),"",MAX(H63,MIN(ROUND(H63*(1+Параметры!$B$5),IF(H63*(1+Параметры!$B$5)>=1000,-1,0)),ROUND(F63*Параметры!$B$6,IF(F63*Параметры!$B$6>=1000,-1,0))))) -> 81 | J63: 80.5 | K63: =IF(OR(J63="",G63=""),"",MAX(J63,MIN(ROUND(J63*(1+Параметры!$B$5),IF(J63*(1+Параметры!$B$5)>=1000,-1,0)),ROUND(G63*Параметры!$B$6,IF(G63*Параметры!$B$6>=1000,-1,0))))) -> 93 | L63: 0.12 | M63: =IF(OR(L63="",L63=0),"",1/L63) -> 8.3333333 | N63: =IF(OR(L63="",L63=0),"",Параметры!$B$3/L63) -> 66.666667 | O63: =IF(L63="","",IFERROR(INDEX('Почасовка — ставки и план'!$D$5:$D$24,MATCH($D63,'Почасовка — ставки и план'!$A$5:$A$24,0)),"")) -> 550 | P63: =IF(L63="","",IFERROR(INDEX('Почасовка — ставки и план'!$E$5:$E$24,MATCH($D63,'Почасовка — ставки и план'!$A$5:$A$24,0)),"")) -> 660 | Q63: =IF(OR(L63="",O63=""),"",ROUND(L63*O63,0)) -> 66 | R63: =IF(D63="TEX","аренда техники — сделка/счёт",IF(OR(Q63="",H63="",H63=0),"—",IF(Q63<H63*(1-Параметры!$B$7),"почасовка",IF(Q63>H63*(1+Параметры!$B$7),"сделка","любой способ")))) -> любой способ | S63: 0 | T63: 0
A64: 1.6.5 | B64: Разборка покрытий полов из древесностружечных плит в один слой | C64: м2 | D64: RAZ | E64: =IFERROR(INDEX('Почасовка — ставки и план'!$B$5:$B$24,MATCH(D64,'Почасовка — ставки и план'!$A$5:$A$24,0)),"Аренда техники / механизмы") -> Разнорабочий / демонтажник | F64: 100 | G64: 115 | H64: 60 | I64: =IF(OR(H64="",F64=""),"",MAX(H64,MIN(ROUND(H64*(1+Параметры!$B$5),IF(H64*(1+Параметры!$B$5)>=1000,-1,0)),ROUND(F64*Параметры!$B$6,IF(F64*Параметры!$B$6>=1000,-1,0))))) -> 69 | J64: 69 | K64: =IF(OR(J64="",G64=""),"",MAX(J64,MIN(ROUND(J64*(1+Параметры!$B$5),IF(J64*(1+Параметры!$B$5)>=1000,-1,0)),ROUND(G64*Параметры!$B$6,IF(G64*Параметры!$B$6>=1000,-1,0))))) -> 79 | L64: 0.12 | M64: =IF(OR(L64="",L64=0),"",1/L64) -> 8.3333333 | N64: =IF(OR(L64="",L64=0),"",Параметры!$B$3/L64) -> 66.666667 | O64: =IF(L64="","",IFERROR(INDEX('Почасовка — ставки и план'!$D$5:$D$24,MATCH($D64,'Почасовка — ставки и план'!$A$5:$A$24,0)),"")) -> 550 | P64: =IF(L64="","",IFERROR(INDEX('Почасовка — ставки и план'!$E$5:$E$24,MATCH($D64,'Почасовка — ставки и план'!$A$5:$A$24,0)),"")) -> 660 | Q64: =IF(OR(L64="",O64=""),"",ROUND(L64*O64,0)) -> 66 | R64: =IF(D64="TEX","аренда техники — сделка/счёт",IF(OR(Q64="",H64="",H64=0),"—",IF(Q64<H64*(1-Параметры!$B$7),"почасовка",IF(Q64>H64*(1+Параметры!$B$7),"сделка","любой способ")))) -> любой способ | S64: 0 | T64: 0
A65: 1.6.6 | B65: Разборка покрытий полов из керамических плиток | C65: м2 | D65: RAZ | E65: =IFERROR(INDEX('Почасовка — ставки и план'!$B$5:$B$24,MATCH(D65,'Почасовка — ставки и план'!$A$5:$A$24,0)),"Аренда техники / механизмы") -> Разнорабочий / демонтажник | F65: 300 | G65: 345 | H65: 180 | I65: =IF(OR(H65="",F65=""),"",MAX(H65,MIN(ROUND(H65*(1+Параметры!$B$5),IF(H65*(1+Параметры!$B$5)>=1000,-1,0)),ROUND(F65*Параметры!$B$6,IF(F65*Параметры!$B$6>=1000,-1,0))))) -> 207 | J65: 207 | K65: =IF(OR(J65="",G65=""),"",MAX(J65,MIN(ROUND(J65*(1+Параметры!$B$5),IF(J65*(1+Параметры!$B$5)>=1000,-1,0)),ROUND(G65*Параметры!$B$6,IF(G65*Параметры!$B$6>=1000,-1,0))))) -> 238 | L65: 0.35 | M65: =IF(OR(L65="",L65=0),"",1/L65) -> 2.8571429 | N65: =IF(OR(L65="",L65=0),"",Параметры!$B$3/L65) -> 22.857143 | O65: =IF(L65="","",IFERROR(INDEX('Почасовка — ставки и план'!$D$5:$D$24,MATCH($D65,'Почасовка — ставки и план'!$A$5:$A$24,0)),"")) -> 550 | P65: =IF(L65="","",IFERROR(INDEX('Почасовка — ставки и план'!$E$5:$E$24,MATCH($D65,'Почасовка — ставки и план'!$A$5:$A$24,0)),"")) -> 660 | Q65: =IF(OR(L65="",O65=""),"",ROUND(L65*O65,0)) -> 193 | R65: =IF(D65="TEX","аренда техники — сделка/счёт",IF(OR(Q65="",H65="",H65=0),"—",IF(Q65<H65*(1-Параметры!$B$7),"почасовка",IF(Q65>H65*(1+Параметры!$B$7),"сделка","любой способ")))) -> любой способ | S65: 0 | T65: 0
A66: 1.6.7 | B66: Разборка покрытий полов из керамогранитных плит толщиной более 15 мм с расчисткой основания от клея | C66: м2 | D66: RAZ | E66: =IFERROR(INDEX('Почасовка — ставки и план'!$B$5:$B$24,MATCH(D66,'Почасовка — ставки и план'!$A$5:$A$24,0)),"Аренда техники / механизмы") -> Разнорабочий / демонтажник | F66: 650 | G66: 747 | H66: 400 | I66: =IF(OR(H66="",F66=""),"",MAX(H66,MIN(ROUND(H66*(1+Параметры!$B$5),IF(H66*(1+Параметры!$B$5)>=1000,-1,0)),ROUND(F66*Параметры!$B$6,IF(F66*Параметры!$B$6>=1000,-1,0))))) -> 460 | J66: 460 | K66: =IF(OR(J66="",G66=""),"",MAX(J66,MIN(ROUND(J66*(1+Параметры!$B$5),IF(J66*(1+Параметры!$B$5)>=1000,-1,0)),ROUND(G66*Параметры!$B$6,IF(G66*Параметры!$B$6>=1000,-1,0))))) -> 529 | L66: 0.8 | M66: =IF(OR(L66="",L66=0),"",1/L66) -> 1.25 | N66: =IF(OR(L66="",L66=0),"",Параметры!$B$3/L66) -> 10 | O66: =IF(L66="","",IFERROR(INDEX('Почасовка — ставки и план'!$D$5:$D$24,MATCH($D66,'Почасовка — ставки и план'!$A$5:$A$24,0)),"")) -> 550 | P66: =IF(L66="","",IFERROR(INDEX('Почасовка — ставки и план'!$E$5:$E$24,MATCH($D66,'Почасовка — ставки и план'!$A$5:$A$24,0)),"")) -> 660 | Q66: =IF(OR(L66="",O66=""),"",ROUND(L66*O66,0)) -> 440 | R66: =IF(D66="TEX","аренда техники — сделка/счёт",IF(OR(Q66="",H66="",H66=0),"—",IF(Q66<H66*(1-Параметры!$B$7),"почасовка",IF(Q66>H66*(1+Параметры!$B$7),"сделка","любой способ")))) -> любой способ | S66: 0 | T66: 0
A67: 1.6.8 | B67: Разборка покрытий полов из линолеума и релина | C67: м2 | D67: RAZ | E67: =IFERROR(INDEX('Почасовка — ставки и план'!$B$5:$B$24,MATCH(D67,'Почасовка — ставки и план'!$A$5:$A$24,0)),"Аренда техники / механизмы") -> Разнорабочий / демонтажник | F67: 80 | G67: 92 | H67: 50 | I67: =IF(OR(H67="",F67=""),"",MAX(H67,MIN(ROUND(H67*(1+Параметры!$B$5),IF(H67*(1+Параметры!$B$5)>=1000,-1,0)),ROUND(F67*Параметры!$B$6,IF(F67*Параметры!$B$6>=1000,-1,0))))) -> 58 | J67: 57.5 | K67: =IF(OR(J67="",G67=""),"",MAX(J67,MIN(ROUND(J67*(1+Параметры!$B$5),IF(J67*(1+Параметры!$B$5)>=1000,-1,0)),ROUND(G67*Параметры!$B$6,IF(G67*Параметры!$B$6>=1000,-1,0))))) -> 66 | L67: 0.07 | M67: =IF(OR(L67="",L67=0),"",1/L67) -> 14.285714 | N67: =IF(OR(L67="",L67=0),"",Параметры!$B$3/L67) -> 114.28571 | O67: =IF(L67="","",IFERROR(INDEX('Почасовка — ставки и план'!$D$5:$D$24,MATCH($D67,'Почасовка — ставки и план'!$A$5:$A$24,0)),"")) -> 550 | P67: =IF(L67="","",IFERROR(INDEX('Почасовка — ставки и план'!$E$5:$E$24,MATCH($D67,'Почасовка — ставки и план'!$A$5:$A$24,0)),"")) -> 660 | Q67: =IF(OR(L67="",O67=""),"",ROUND(L67*O67,0)) -> 39 | R67: =IF(D67="TEX","аренда техники — сделка/счёт",IF(OR(Q67="",H67="",H67=0),"—",IF(Q67<H67*(1-Параметры!$B$7),"почасовка",IF(Q67>H67*(1+Параметры!$B$7),"сделка","любой способ")))) -> почасовка | S67: 0 | T67: 0
A68: 1.6.9 | B68: Снятие алюминиевого порога | C68: мп | D68: RAZ | E68: =IFERROR(INDEX('Почасовка — ставки и план'!$B$5:$B$24,MATCH(D68,'Почасовка — ставки и план'!$A$5:$A$24,0)),"Аренда техники / механизмы") -> Разнорабочий / демонтажник | F68: 120 | G68: 138 | H68: 70 | I68: =IF(OR(H68="",F68=""),"",MAX(H68,MIN(ROUND(H68*(1+Параметры!$B$5),IF(H68*(1+Параметры!$B$5)>=1000,-1,0)),ROUND(F68*Параметры!$B$6,IF(F68*Параметры!$B$6>=1000,-1,0))))) -> 81 | J68: 80.5 | K68: =IF(OR(J68="",G68=""),"",MAX(J68,MIN(ROUND(J68*(1+Параметры!$B$5),IF(J68*(1+Параметры!$B$5)>=1000,-1,0)),ROUND(G68*Параметры!$B$6,IF(G68*Параметры!$B$6>=1000,-1,0))))) -> 93 | L68: 0.15 | M68: =IF(OR(L68="",L68=0),"",1/L68) -> 6.6666667 | N68: =IF(OR(L68="",L68=0),"",Параметры!$B$3/L68) -> 53.333333 | O68: =IF(L68="","",IFERROR(INDEX('Почасовка — ставки и план'!$D$5:$D$24,MATCH($D68,'Почасовка — ставки и план'!$A$5:$A$24,0)),"")) -> 550 | P68: =IF(L68="","",IFERROR(INDEX('Почасовка — ставки и план'!$E$5:$E$24,MATCH($D68,'Почасовка — ставки и план'!$A$5:$A$24,0)),"")) -> 660 | Q68: =IF(OR(L68="",O68=""),"",ROUND(L68*O68,0)) -> 83 | R68: =IF(D68="TEX","аренда техники — сделка/счёт",IF(OR(Q68="",H68="",H68=0),"—",IF(Q68<H68*(1-Параметры!$B$7),"почасовка",IF(Q68>H68*(1+Параметры!$B$7),"сделка","любой способ")))) -> сделка | S68: 0 | T68: 0
A69: 1.6.10 | B69: Разборка покрытий полов из плиток поливинилхлоридных | C69: м2 | D69: RAZ | E69: =IFERROR(INDEX('Почасовка — ставки и план'!$B$5:$B$24,MATCH(D69,'Почасовка — ставки и план'!$A$5:$A$24,0)),"Аренда техники / механизмы") -> Разнорабочий / демонтажник | F69: 150 | G69: 172 | H69: 90 | I69: =IF(OR(H69="",F69=""),"",MAX(H69,MIN(ROUND(H69*(1+Параметры!$B$5),IF(H69*(1+Параметры!$B$5)>=1000,-1,0)),ROUND(F69*Параметры!$B$6,IF(F69*Параметры!$B$6>=1000,-1,0))))) -> 104 | J69: 103 | K69: =IF(OR(J69="",G69=""),"",MAX(J69,MIN(ROUND(J69*(1+Параметры!$B$5),IF(J69*(1+Параметры!$B$5)>=1000,-1,0)),ROUND(G69*Параметры!$B$6,IF(G69*Параметры!$B$6>=1000,-1,0))))) -> 118 | L69: 0.18 | M69: =IF(OR(L69="",L69=0),"",1/L69) -> 5.5555556 | N69: =IF(OR(L69="",L69=0),"",Параметры!$B$3/L69) -> 44.444444 | O69: =IF(L69="","",IFERROR(INDEX('Почасовка — ставки и план'!$D$5:$D$24,MATCH($D69,'Почасовка — ставки и план'!$A$5:$A$24,0)),"")) -> 550 | P69: =IF(L69="","",IFERROR(INDEX('Почасовка — ставки и план'!$E$5:$E$24,MATCH($D69,'Почасовка — ставки и план'!$A$5:$A$24,0)),"")) -> 660 | Q69: =IF(OR(L69="",O69=""),"",ROUND(L69*O69,0)) -> 99 | R69: =IF(D69="TEX","аренда техники — сделка/счёт",IF(OR(Q69="",H69="",H69=0),"—",IF(Q69<H69*(1-Параметры!$B$7),"почасовка",IF(Q69>H69*(1+Параметры!$B$7),"сделка","любой способ")))) -> любой способ | S69: 0 | T69: 0
A70: 1.6.11 | B70: Разборка покрытий полов цементных толщиной до 150 мм | C70: м2 | D70: RAZ | E70: =IFERROR(INDEX('Почасовка — ставки и план'!$B$5:$B$24,MATCH(D70,'Почасовка — ставки и план'!$A$5:$A$24,0)),"Аренда техники / механизмы") -> Разнорабочий / демонтажник | F70: 1027 | G70: 1232 | H70: 600 | I70: =IF(OR(H70="",F70=""),"",MAX(H70,MIN(ROUND(H70*(1+Параметры!$B$5),IF(H70*(1+Параметры!$B$5)>=1000,-1,0)),ROUND(F70*Параметры!$B$6,IF(F70*Параметры!$B$6>=1000,-1,0))))) -> 690 | J70: 690 | K70: =IF(OR(J70="",G70=""),"",MAX(J70,MIN(ROUND(J70*(1+Параметры!$B$5),IF(J70*(1+Параметры!$B$5)>=1000,-1,0)),ROUND(G70*Параметры!$B$6,IF(G70*Параметры!$B$6>=1000,-1,0))))) -> 794 | L70: 1.4 | M70: =IF(OR(L70="",L70=0),"",1/L70) -> 0.71428571 | N70: =IF(OR(L70="",L70=0),"",Параметры!$B$3/L70) -> 5.7142857 | O70: =IF(L70="","",IFERROR(INDEX('Почасовка — ставки и план'!$D$5:$D$24,MATCH($D70,'Почасовка — ставки и план'!$A$5:$A$24,0)),"")) -> 550 | P70: =IF(L70="","",IFERROR(INDEX('Почасовка — ставки и план'!$E$5:$E$24,MATCH($D70,'Почасовка — ставки и план'!$A$5:$A$24,0)),"")) -> 660 | Q70: =IF(OR(L70="",O70=""),"",ROUND(L70*O70,0)) -> 770 | R70: =IF(D70="TEX","аренда техники — сделка/счёт",IF(OR(Q70="",H70="",H70=0),"—",IF(Q70<H70*(1-Параметры!$B$7),"почасовка",IF(Q70>H70*(1+Параметры!$B$7),"сделка","любой способ")))) -> сделка | S70: 0.027 | T70: 0.071304348
A71: 1.6.12 | B71: Разборка покрытий полов из керамогранитных плит толщиной до 15 мм с расчисткой основания от клея | C71: м2 | D71: RAZ | E71: =IFERROR(INDEX('Почасовка — ставки и план'!$B$5:$B$24,MATCH(D71,'Почасовка — ставки и план'!$A$5:$A$24,0)),"Аренда техники / механизмы") -> Разнорабочий / демонтажник | F71: 450 | G71: 518 | H71: 270 | I71: =IF(OR(H71="",F71=""),"",MAX(H71,MIN(ROUND(H71*(1+Параметры!$B$5),IF(H71*(1+Параметры!$B$5)>=1000,-1,0)),ROUND(F71*Параметры!$B$6,IF(F71*Параметры!$B$6>=1000,-1,0))))) -> 311 | J71: 310 | K71: =IF(OR(J71="",G71=""),"",MAX(J71,MIN(ROUND(J71*(1+Параметры!$B$5),IF(J71*(1+Параметры!$B$5)>=1000,-1,0)),ROUND(G71*Параметры!$B$6,IF(G71*Параметры!$B$6>=1000,-1,0))))) -> 357 | L71: 0.55 | M71: =IF(OR(L71="",L71=0),"",1/L71) -> 1.8181818 | N71: =IF(OR(L71="",L71=0),"",Параметры!$B$3/L71) -> 14.545455 | O71: =IF(L71="","",IFERROR(INDEX('Почасовка — ставки и план'!$D$5:$D$24,MATCH($D71,'Почасовка — ставки и план'!$A$5:$A$24,0)),"")) -> 550 | P71: =IF(L71="","",IFERROR(INDEX('Почасовка — ставки и план'!$E$5:$E$24,MATCH($D71,'Почасовка — ставки и план'!$A$5:$A$24,0)),"")) -> 660 | Q71: =IF(OR(L71="",O71=""),"",ROUND(L71*O71,0)) -> 303 | R71: =IF(D71="TEX","аренда техники — сделка/счёт",IF(OR(Q71="",H71="",H71=0),"—",IF(Q71<H71*(1-Параметры!$B$7),"почасовка",IF(Q71>H71*(1+Параметры!$B$7),"сделка","любой способ")))) -> сделка | S71: 0 | T71: 0
... A75: 1.6.N4 | B75: Демонтаж фальшпола (съёмного) с опорами | C75: м2 | D75: RAZ | E75: =IFERROR(INDEX('Почасовка — ставки и план'!$B$5:$B$24,MATCH(D75,'Почасовка — ставки и план'!$A$5:$A$24,0)),"Аренда техники / механизмы") -> Разнорабочий / демонтажник | F75: 300 | G75: 345 | H75: 180 | I75: =IF(OR(H75="",F75=""),"",MAX(H75,MIN(ROUND(H75*(1+Параметры!$B$5),IF(H75*(1+Параметры!$B$5)>=1000,-1,0)),ROUND(F75*Параметры!$B$6,IF(F75*Параметры!$B$6>=1000,-1,0))))) -> 207 | J75: 207 | K75: =IF(OR(J75="",G75=""),"",MAX(J75,MIN(ROUND(J75*(1+Параметры!$B$5),IF(J75*(1+Параметры!$B$5)>=1000,-1,0)),ROUND(G75*Параметры!$B$6,IF(G75*Параметры!$B$6>=1000,-1,0))))) -> 238 | L75: 0.3 | M75: =IF(OR(L75="",L75=0),"",1/L75) -> 3.3333333 | N75: =IF(OR(L75="",L75=0),"",Параметры!$B$3/L75) -> 26.666667 | O75: =IF(L75="","",IFERROR(INDEX('Почасовка — ставки и план'!$D$5:$D$24,MATCH($D75,'Почасовка — ставки и план'!$A$5:$A$24,0)),"")) -> 550 | P75: =IF(L75="","",IFERROR(INDEX('Почасовка — ставки и план'!$E$5:$E$24,MATCH($D75,'Почасовка — ставки и план'!$A$5:$A$24,0)),"")) -> 660 | Q75: =IF(OR(L75="",O75=""),"",ROUND(L75*O75,0)) -> 165 | R75: =IF(D75="TEX","аренда техники — сделка/счёт",IF(OR(Q75="",H75="",H75=0),"—",IF(Q75<H75*(1-Параметры!$B$7),"почасовка",IF(Q75>H75*(1+Параметры!$B$7),"сделка","любой способ")))) -> любой способ | S75: 0 | T75: 0
A76: 1.7 Демонтажные работы потолка
A77: 1.7.1 | B77: Демонтаж утеплителя потолков | C77: м2 | D77: RAZ | E77: =IFERROR(INDEX('Почасовка — ставки и план'!$B$5:$B$24,MATCH(D77,'Почасовка — ставки и план'!$A$5:$A$24,0)),"Аренда техники / механизмы") -> Разнорабочий / демонтажник | F77: 120 | G77: 138 | H77: 70 | I77: =IF(OR(H77="",F77=""),"",MAX(H77,MIN(ROUND(H77*(1+Параметры!$B$5),IF(H77*(1+Параметры!$B$5)>=1000,-1,0)),ROUND(F77*Параметры!$B$6,IF(F77*Параметры!$B$6>=1000,-1,0))))) -> 81 | J77: 80.5 | K77: =IF(OR(J77="",G77=""),"",MAX(J77,MIN(ROUND(J77*(1+Параметры!$B$5),IF(J77*(1+Параметры!$B$5)>=1000,-1,0)),ROUND(G77*Параметры!$B$6,IF(G77*Параметры!$B$6>=1000,-1,0))))) -> 93 | L77: 0.15 | M77: =IF(OR(L77="",L77=0),"",1/L77) -> 6.6666667 | N77: =IF(OR(L77="",L77=0),"",Параметры!$B$3/L77) -> 53.333333 | O77: =IF(L77="","",IFERROR(INDEX('Почасовка — ставки и план'!$D$5:$D$24,MATCH($D77,'Почасовка — ставки и план'!$A$5:$A$24,0)),"")) -> 550 | P77: =IF(L77="","",IFERROR(INDEX('Почасовка — ставки и план'!$E$5:$E$24,MATCH($D77,'Почасовка — ставки и план'!$A$5:$A$24,0)),"")) -> 660 | Q77: =IF(OR(L77="",O77=""),"",ROUND(L77*O77,0)) -> 83 | R77: =IF(D77="TEX","аренда техники — сделка/счёт",IF(OR(Q77="",H77="",H77=0),"—",IF(Q77<H77*(1-Параметры!$B$7),"почасовка",IF(Q77>H77*(1+Параметры!$B$7),"сделка","любой способ")))) -> сделка | S77: 0 | T77: 0
A78: 1.7.2 | B78: Отбивка штукатурки с поверхности потолка | C78: м2 | D78: OTD | E78: =IFERROR(INDEX('Почасовка — ставки и план'!$B$5:$B$24,MATCH(D78,'Почасовка — ставки и план'!$A$5:$A$24,0)),"Аренда техники / механизмы") -> Отделочник (штукатур, маляр, ГКЛ) | F78: 500 | G78: 600 | H78: 210 | I78: =IF(OR(H78="",F78=""),"",MAX(H78,MIN(ROUND(H78*(1+Параметры!$B$5),IF(H78*(1+Параметры!$B$5)>=1000,-1,0)),ROUND(F78*Параметры!$B$6,IF(F78*Параметры!$B$6>=1000,-1,0))))) -> 242 | J78: 241 | K78: =IF(OR(J78="",G78=""),"",MAX(J78,MIN(ROUND(J78*(1+Параметры!$B$5),IF(J78*(1+Параметры!$B$5)>=1000,-1,0)),ROUND(G78*Параметры!$B$6,IF(G78*Параметры!$B$6>=1000,-1,0))))) -> 277 | L78: 0.5 | M78: =IF(OR(L78="",L78=0),"",1/L78) -> 2 | N78: =IF(OR(L78="",L78=0),"",Параметры!$B$3/L78) -> 16 | O78: =IF(L78="","",IFERROR(INDEX('Почасовка — ставки и план'!$D$5:$D$24,MATCH($D78,'Почасовка — ставки и план'!$A$5:$A$24,0)),"")) -> 750 | P78: =IF(L78="","",IFERROR(INDEX('Почасовка — ставки и план'!$E$5:$E$24,MATCH($D78,'Почасовка — ставки и план'!$A$5:$A$24,0)),"")) -> 900 | Q78: =IF(OR(L78="",O78=""),"",ROUND(L78*O78,0)) -> 375 | R78: =IF(D78="TEX","аренда техники — сделка/счёт",IF(OR(Q78="",H78="",H78=0),"—",IF(Q78<H78*(1-Параметры!$B$7),"почасовка",IF(Q78>H78*(1+Параметры!$B$7),"сделка","любой способ")))) -> сделка | S78: 0.42857143 | T78: 0.49253731
A79: 1.7.3 | B79: Разборка облицовки потолков из гипсокартонных листов с каркасом | C79: м2 | D79: OTD | E79: =IFERROR(INDEX('Почасовка — ставки и план'!$B$5:$B$24,MATCH(D79,'Почасовка — ставки и план'!$A$5:$A$24,0)),"Аренда техники / механизмы") -> Отделочник (штукатур, маляр, ГКЛ) | F79: 251 | G79: 300 | H79: 130 | I79: =IF(OR(H79="",F79=""),"",MAX(H79,MIN(ROUND(H79*(1+Параметры!$B$5),IF(H79*(1+Параметры!$B$5)>=1000,-1,0)),ROUND(F79*Параметры!$B$6,IF(F79*Параметры!$B$6>=1000,-1,0))))) -> 150 | J79: 150 | K79: =IF(OR(J79="",G79=""),"",MAX(J79,MIN(ROUND(J79*(1+Параметры!$B$5),IF(J79*(1+Параметры!$B$5)>=1000,-1,0)),ROUND(G79*Параметры!$B$6,IF(G79*Параметры!$B$6>=1000,-1,0))))) -> 173 | L79: 0.25 | M79: =IF(OR(L79="",L79=0),"",1/L79) -> 4 | N79: =IF(OR(L79="",L79=0),"",Параметры!$B$3/L79) -> 32 | O79: =IF(L79="","",IFERROR(INDEX('Почасовка — ставки и план'!$D$5:$D$24,MATCH($D79,'Почасовка — ставки и план'!$A$5:$A$24,0)),"")) -> 750 | P79: =IF(L79="","",IFERROR(INDEX('Почасовка — ставки и план'!$E$5:$E$24,MATCH($D79,'Почасовка — ставки и план'!$A$5:$A$24,0)),"")) -> 900 | Q79: =IF(OR(L79="",O79=""),"",ROUND(L79*O79,0)) -> 188 | R79: =IF(D79="TEX","аренда техники — сделка/счёт",IF(OR(Q79="",H79="",H79=0),"—",IF(Q79<H79*(1-Параметры!$B$7),"почасовка",IF(Q79>H79*(1+Параметры!$B$7),"сделка","любой способ")))) -> сделка | S79: 0.14090909 | T79: 0.18577075
A80: 1.7.4 | B80: Разборка подвесного потолка Грильято включая направляющие | C80: м2 | D80: OTD | E80: =IFERROR(INDEX('Почасовка — ставки и план'!$B$5:$B$24,MATCH(D80,'Почасовка — ставки и план'!$A$5:$A$24,0)),"Аренда техники / механизмы") -> Отделочник (штукатур, маляр, ГКЛ) | F80: 200 | G80: 240 | H80: 110 | I80: =IF(OR(H80="",F80=""),"",MAX(H80,MIN(ROUND(H80*(1+Параметры!$B$5),IF(H80*(1+Параметры!$B$5)>=1000,-1,0)),ROUND(F80*Параметры!$B$6,IF(F80*Параметры!$B$6>=1000,-1,0))))) -> 127 | J80: 126 | K80: =IF(OR(J80="",G80=""),"",MAX(J80,MIN(ROUND(J80*(1+Параметры!$B$5),IF(J80*(1+Параметры!$B$5)>=1000,-1,0)),ROUND(G80*Параметры!$B$6,IF(G80*Параметры!$B$6>=1000,-1,0))))) -> 145 | L80: 0.2 | M80: =IF(OR(L80="",L80=0),"",1/L80) -> 5 | N80: =IF(OR(L80="",L80=0),"",Параметры!$B$3/L80) -> 40 | O80: =IF(L80="","",IFERROR(INDEX('Почасовка — ставки и план'!$D$5:$D$24,MATCH($D80,'Почасовка — ставки и план'!$A$5:$A$24,0)),"")) -> 750 | P80: =IF(L80="","",IFERROR(INDEX('Почасовка — ставки и план'!$E$5:$E$24,MATCH($D80,'Почасовка — ставки и план'!$A$5:$A$24,0)),"")) -> 900 | Q80: =IF(OR(L80="",O80=""),"",ROUND(L80*O80,0)) -> 150 | R80: =IF(D80="TEX","аренда техники — сделка/счёт",IF(OR(Q80="",H80="",H80=0),"—",IF(Q80<H80*(1-Параметры!$B$7),"почасовка",IF(Q80>H80*(1+Параметры!$B$7),"сделка","любой способ")))) -> сделка | S80: 0.11111111 | T80: 0.15942029
A81: 1.7.5 | B81: Разборка подвесной системы потолка | C81: м2 | D81: OTD | E81: =IFERROR(INDEX('Почасовка — ставки и план'!$B$5:$B$24,MATCH(D81,'Почасовка — ставки и план'!$A$5:$A$24,0)),"Аренда техники / механизмы") -> Отделочник (штукатур, маляр, ГКЛ) | F81: 120 | G81: 144 | H81: 70 | I81: =IF(OR(H81="",F81=""),"",MAX(H81,MIN(ROUND(H81*(1+Параметры!$B$5),IF(H81*(1+Параметры!$B$5)>=1000,-1,0)),ROUND(F81*Параметры!$B$6,IF(F81*Параметры!$B$6>=1000,-1,0))))) -> 81 | J81: 80.5 | K81: =IF(OR(J81="",G81=""),"",MAX(J81,MIN(ROUND(J81*(1+Параметры!$B$5),IF(J81*(1+Параметры!$B$5)>=1000,-1,0)),ROUND(G81*Параметры!$B$6,IF(G81*Параметры!$B$6>=1000,-1,0))))) -> 93 | L81: 0.12 | M81: =IF(OR(L81="",L81=0),"",1/L81) -> 8.3333333 | N81: =IF(OR(L81="",L81=0),"",Параметры!$B$3/L81) -> 66.666667 | O81: =IF(L81="","",IFERROR(INDEX('Почасовка — ставки и план'!$D$5:$D$24,MATCH($D81,'Почасовка — ставки и план'!$A$5:$A$24,0)),"")) -> 750 | P81: =IF(L81="","",IFERROR(INDEX('Почасовка — ставки и план'!$E$5:$E$24,MATCH($D81,'Почасовка — ставки и план'!$A$5:$A$24,0)),"")) -> 900 | Q81: =IF(OR(L81="",O81=""),"",ROUND(L81*O81,0)) -> 90 | R81: =IF(D81="TEX","аренда техники — сделка/счёт",IF(OR(Q81="",H81="",H81=0),"—",IF(Q81<H81*(1-Параметры!$B$7),"почасовка",IF(Q81>H81*(1+Параметры!$B$7),"сделка","любой способ")))) -> сделка | S81: 0 | T81: 0.043478261
A82: 1.7.6 | B82: Разборка подвесных каркасов, подшивных потолков из металлических уголков (не применимо для направляющих) | C82: м2 | D82: OTD | E82: =IFERROR(INDEX('Почасовка — ставки и план'!$B$5:$B$24,MATCH(D82,'Почасовка — ставки и план'!$A$5:$A$24,0)),"Аренда техники / механизмы") -> Отделочник (штукатур, маляр, ГКЛ) | F82: 180 | G82: 216 | H82: 90 | I82: =IF(OR(H82="",F82=""),"",MAX(H82,MIN(ROUND(H82*(1+Параметры!$B$5),IF(H82*(1+Параметры!$B$5)>=1000,-1,0)),ROUND(F82*Параметры!$B$6,IF(F82*Параметры!$B$6>=1000,-1,0))))) -> 104 | J82: 103 | K82: =IF(OR(J82="",G82=""),"",MAX(J82,MIN(ROUND(J82*(1+Параметры!$B$5),IF(J82*(1+Параметры!$B$5)>=1000,-1,0)),ROUND(G82*Параметры!$B$6,IF(G82*Параметры!$B$6>=1000,-1,0))))) -> 118 | L82: 0.18 | M82: =IF(OR(L82="",L82=0),"",1/L82) -> 5.5555556 | N82: =IF(OR(L82="",L82=0),"",Параметры!$B$3/L82) -> 44.444444 | O82: =IF(L82="","",IFERROR(INDEX('Почасовка — ставки и план'!$D$5:$D$24,MATCH($D82,'Почасовка — ставки и план'!$A$5:$A$24,0)),"")) -> 750 | P82: =IF(L82="","",IFERROR(INDEX('Почасовка — ставки и план'!$E$5:$E$24,MATCH($D82,'Почасовка — ставки и план'!$A$5:$A$24,0)),"")) -> 900 | Q82: =IF(OR(L82="",O82=""),"",ROUND(L82*O82,0)) -> 135 | R82: =IF(D82="TEX","аренда техники — сделка/счёт",IF(OR(Q82="",H82="",H82=0),"—",IF(Q82<H82*(1-Параметры!$B$7),"почасовка",IF(Q82>H82*(1+Параметры!$B$7),"сделка","любой способ")))) -> сделка | S82: 0.2 | T82: 0.25581395
A83: 1.7.7 | B83: Разборка подвесных потолков из металлических кассет, включая направляющие | C83: м2 | D83: OTD | E83: =IFERROR(INDEX('Почасовка — ставки и план'!$B$5:$B$24,MATCH(D83,'Почасовка — ставки и план'!$A$5:$A$24,0)),"Аренда техники / механизмы") -> Отделочник (штукатур, маляр, ГКЛ) | F83: 220 | G83: 264 | H83: 120 | I83: =IF(OR(H83="",F83=""),"",MAX(H83,MIN(ROUND(H83*(1+Параметры!$B$5),IF(H83*(1+Параметры!$B$5)>=1000,-1,0)),ROUND(F83*Параметры!$B$6,IF(F83*Параметры!$B$6>=1000,-1,0))))) -> 138 | J83: 138 | K83: =IF(OR(J83="",G83=""),"",MAX(J83,MIN(ROUND(J83*(1+Параметры!$B$5),IF(J83*(1+Параметры!$B$5)>=1000,-1,0)),ROUND(G83*Параметры!$B$6,IF(G83*Параметры!$B$6>=1000,-1,0))))) -> 159 | L83: 0.22 | M83: =IF(OR(L83="",L83=0),"",1/L83) -> 4.5454545 | N83: =IF(OR(L83="",L83=0),"",Параметры!$B$3/L83) -> 36.363636 | O83: =IF(L83="","",IFERROR(INDEX('Почасовка — ставки и план'!$D$5:$D$24,MATCH($D83,'Почасовка — ставки и план'!$A$5:$A$24,0)),"")) -> 750 | P83: =IF(L83="","",IFERROR(INDEX('Почасовка — ставки и план'!$E$5:$E$24,MATCH($D83,'Почасовка — ставки и план'!$A$5:$A$24,0)),"")) -> 900 | Q83: =IF(OR(L83="",O83=""),"",ROUND(L83*O83,0)) -> 165 | R83: =IF(D83="TEX","аренда техники — сделка/счёт",IF(OR(Q83="",H83="",H83=0),"—",IF(Q83<H83*(1-Параметры!$B$7),"почасовка",IF(Q83>H83*(1+Параметры!$B$7),"сделка","любой способ")))) -> сделка | S83: 0.1 | T83: 0.14782609
A84: 1.7.8 | B84: Разборка подвесных потолков типа <Армстронг> включая направляющие | C84: м2 | D84: OTD | E84: =IFERROR(INDEX('Почасовка — ставки и план'!$B$5:$B$24,MATCH(D84,'Почасовка — ставки и план'!$A$5:$A$24,0)),"Аренда техники / механизмы") -> Отделочник (штукатур, маляр, ГКЛ) | F84: 180 | G84: 216 | H84: 110 | I84: =IF(OR(H84="",F84=""),"",MAX(H84,MIN(ROUND(H84*(1+Параметры!$B$5),IF(H84*(1+Параметры!$B$5)>=1000,-1,0)),ROUND(F84*Параметры!$B$6,IF(F84*Параметры!$B$6>=1000,-1,0))))) -> 127 | J84: 126 | K84: =IF(OR(J84="",G84=""),"",MAX(J84,MIN(ROUND(J84*(1+Параметры!$B$5),IF(J84*(1+Параметры!$B$5)>=1000,-1,0)),ROUND(G84*Параметры!$B$6,IF(G84*Параметры!$B$6>=1000,-1,0))))) -> 145 | L84: 0.18 | M84: =IF(OR(L84="",L84=0),"",1/L84) -> 5.5555556 | N84: =IF(OR(L84="",L84=0),"",Параметры!$B$3/L84) -> 44.444444 | O84: =IF(L84="","",IFERROR(INDEX('Почасовка — ставки и план'!$D$5:$D$24,MATCH($D84,'Почасовка — ставки и план'!$A$5:$A$24,0)),"")) -> 750 | P84: =IF(L84="","",IFERROR(INDEX('Почасовка — ставки и план'!$E$5:$E$24,MATCH($D84,'Почасовка — ставки и план'!$A$5:$A$24,0)),"")) -> 900 | Q84: =IF(OR(L84="",O84=""),"",ROUND(L84*O84,0)) -> 135 | R84: =IF(D84="TEX","аренда техники — сделка/счёт",IF(OR(Q84="",H84="",H84=0),"—",IF(Q84<H84*(1-Параметры!$B$7),"почасовка",IF(Q84>H84*(1+Параметры!$B$7),"сделка","любой способ")))) -> сделка | S84: 0 | T84: 0.043478261
A85: 1.7.9 | B85: Разборка потолков реечных алюминиевых включая направляющие | C85: м2 | D85: OTD | E85: =IFERROR(INDEX('Почасовка — ставки и план'!$B$5:$B$24,MATCH(D85,'Почасовка — ставки и план'!$A$5:$A$24,0)),"Аренда техники / механизмы") -> Отделочник (штукатур, маляр, ГКЛ) | F85: 220 | G85: 264 | H85: 120 | I85: =IF(OR(H85="",F85=""),"",MAX(H85,MIN(ROUND(H85*(1+Параметры!$B$5),IF(H85*(1+Параметры!$B$5)>=1000,-1,0)),ROUND(F85*Параметры!$B$6,IF(F85*Параметры!$B$6>=1000,-1,0))))) -> 138 | J85: 138 | K85: =IF(OR(J85="",G85=""),"",MAX(J85,MIN(ROUND(J85*(1+Параметры!$B$5),IF(J85*(1+Параметры!$B$5)>=1000,-1,0)),ROUND(G85*Параметры!$B$6,IF(G85*Параметры!$B$6>=1000,-1,0))))) -> 159 | L85: 0.22 | M85: =IF(OR(L85="",L85=0),"",1/L85) -> 4.5454545 | N85: =IF(OR(L85="",L85=0),"",Параметры!$B$3/L85) -> 36.363636 | O85: =IF(L85="","",IFERROR(INDEX('Почасовка — ставки и план'!$D$5:$D$24,MATCH($D85,'Почасовка — ставки и план'!$A$5:$A$24,0)),"")) -> 750 | P85: =IF(L85="","",IFERROR(INDEX('Почасовка — ставки и план'!$E$5:$E$24,MATCH($D85,'Почасовка — ставки и план'!$A$5:$A$24,0)),"")) -> 900 | Q85: =IF(OR(L85="",O85=""),"",ROUND(L85*O85,0)) -> 165 | R85: =IF(D85="TEX","аренда техники — сделка/счёт",IF(OR(Q85="",H85="",H85=0),"—",IF(Q85<H85*(1-Параметры!$B$7),"почасовка",IF(Q85>H85*(1+Параметры!$B$7),"сделка","любой способ")))) -> сделка | S85: 0.1 | T85: 0.14782609
A86: 1.7.10 | B86: Разборка реечного потолка из ламелей (потолок Кубота) | C86: м2 | D86: OTD | E86: =IFERROR(INDEX('Почасовка — ставки и план'!$B$5:$B$24,MATCH(D86,'Почасовка — ставки и план'!$A$5:$A$24,0)),"Аренда техники / механизмы") -> Отделочник (штукатур, маляр, ГКЛ) | F86: 251 | G86: 300 | H86: 140 | I86: =IF(OR(H86="",F86=""),"",MAX(H86,MIN(ROUND(H86*(1+Параметры!$B$5),IF(H86*(1+Параметры!$B$5)>=1000,-1,0)),ROUND(F86*Параметры!$B$6,IF(F86*Параметры!$B$6>=1000,-1,0))))) -> 161 | J86: 161 | K86: =IF(OR(J86="",G86=""),"",MAX(J86,MIN(ROUND(J86*(1+Параметры!$B$5),IF(J86*(1+Параметры!$B$5)>=1000,-1,0)),ROUND(G86*Параметры!$B$6,IF(G86*Параметры!$B$6>=1000,-1,0))))) -> 185 | L86: 0.25 | M86: =IF(OR(L86="",L86=0),"",1/L86) -> 4 | N86: =IF(OR(L86="",L86=0),"",Параметры!$B$3/L86) -> 32 | O86: =IF(L86="","",IFERROR(INDEX('Почасовка — ставки и план'!$D$5:$D$24,MATCH($D86,'Почасовка — ставки и план'!$A$5:$A$24,0)),"")) -> 750 | P86: =IF(L86="","",IFERROR(INDEX('Почасовка — ставки и план'!$E$5:$E$24,MATCH($D86,'Почасовка — ставки и план'!$A$5:$A$24,0)),"")) -> 900 | Q86: =IF(OR(L86="",O86=""),"",ROUND(L86*O86,0)) -> 188 | R86: =IF(D86="TEX","аренда техники — сделка/счёт",IF(OR(Q86="",H86="",H86=0),"—",IF(Q86<H86*(1-Параметры!$B$7),"почасовка",IF(Q86>H86*(1+Параметры!$B$7),"сделка","любой способ")))) -> сделка | S86: 0.091304348 | T86: 0.13636364
A87: 1.7.11 | B87: Снятие акустических плит, металлокассет подвесного потолка без направляющих | C87: шт | D87: OTD | E87: =IFERROR(INDEX('Почасовка — ставки и план'!$B$5:$B$24,MATCH(D87,'Почасовка — ставки и план'!$A$5:$A$24,0)),"Аренда техники / механизмы") -> Отделочник (штукатур, маляр, ГКЛ) | F87: 40 | G87: 48 | H87: 25 | I87: =IF(OR(H87="",F87=""),"",MAX(H87,MIN(ROUND(H87*(1+Параметры!$B$5),IF(H87*(1+Параметры!$B$5)>=1000,-1,0)),ROUND(F87*Параметры!$B$6,IF(F87*Параметры!$B$6>=1000,-1,0))))) -> 29 | J87: 28.5 | K87: =IF(OR(J87="",G87=""),"",MAX(J87,MIN(ROUND(J87*(1+Параметры!$B$5),IF(J87*(1+Параметры!$B$5)>=1000,-1,0)),ROUND(G87*Параметры!$B$6,IF(G87*Параметры!$B$6>=1000,-1,0))))) -> 33 | L87: 0.04 | M87: =IF(OR(L87="",L87=0),"",1/L87) -> 25 | N87: =IF(OR(L87="",L87=0),"",Параметры!$B$3/L87) -> 200 | O87: =IF(L87="","",IFERROR(INDEX('Почасовка — ставки и план'!$D$5:$D$24,MATCH($D87,'Почасовка — ставки и план'!$A$5:$A$24,0)),"")) -> 750 | P87: =IF(L87="","",IFERROR(INDEX('Почасовка — ставки и план'!$E$5:$E$24,MATCH($D87,'Почасовка — ставки и план'!$A$5:$A$24,0)),"")) -> 900 | Q87: =IF(OR(L87="",O87=""),"",ROUND(L87*O87,0)) -> 30 | R87: =IF(D87="TEX","аренда техники — сделка/счёт",IF(OR(Q87="",H87="",H87=0),"—",IF(Q87<H87*(1-Параметры!$B$7),"почасовка",IF(Q87>H87*(1+Параметры!$B$7),"сделка","любой способ")))) -> сделка | S87: 0 | T87: 0.043478261
A88: 1.7.12 | B88: Снятие облицовки ГКЛ без каркаса | C88: м2 | D88: OTD | E88: =IFERROR(INDEX('Почасовка — ставки и план'!$B$5:$B$24,MATCH(D88,'Почасовка — ставки и план'!$A$5:$A$24,0)),"Аренда техники / механизмы") -> Отделочник (штукатур, маляр, ГКЛ) | F88: 151 | G88: 180 | H88: 70 | I88: =IF(OR(H88="",F88=""),"",MAX(H88,MIN(ROUND(H88*(1+Параметры!$B$5),IF(H88*(1+Параметры!$B$5)>=1000,-1,0)),ROUND(F88*Параметры!$B$6,IF(F88*Параметры!$B$6>=1000,-1,0))))) -> 81 | J88: 80.5 | K88: =IF(OR(J88="",G88=""),"",MAX(J88,MIN(ROUND(J88*(1+Параметры!$B$5),IF(J88*(1+Параметры!$B$5)>=1000,-1,0)),ROUND(G88*Параметры!$B$6,IF(G88*Параметры!$B$6>=1000,-1,0))))) -> 93 | L88: 0.15 | M88: =IF(OR(L88="",L88=0),"",1/L88) -> 6.6666667 | N88: =IF(OR(L88="",L88=0),"",Параметры!$B$3/L88) -> 53.333333 | O88: =IF(L88="","",IFERROR(INDEX('Почасовка — ставки и план'!$D$5:$D$24,MATCH($D88,'Почасовка — ставки и план'!$A$5:$A$24,0)),"")) -> 750 | P88: =IF(L88="","",IFERROR(INDEX('Почасовка — ставки и план'!$E$5:$E$24,MATCH($D88,'Почасовка — ставки и план'!$A$5:$A$24,0)),"")) -> 900 | Q88: =IF(OR(L88="",O88=""),"",ROUND(L88*O88,0)) -> 113 | R88: =IF(D88="TEX","аренда техники — сделка/счёт",IF(OR(Q88="",H88="",H88=0),"—",IF(Q88<H88*(1-Параметры!$B$7),"почасовка",IF(Q88>H88*(1+Параметры!$B$7),"сделка","любой способ")))) -> сделка | S88: 0.25833333 | T88: 0.30434783
A89: 1.7.N1 | B89: Демонтаж натяжного потолка | C89: м2 | D89: OTD | E89: =IFERROR(INDEX('Почасовка — ставки и план'!$B$5:$B$24,MATCH(D89,'Почасовка — ставки и план'!$A$5:$A$24,0)),"Аренда техники / механизмы") -> Отделочник (штукатур, маляр, ГКЛ) | F89: 100 | G89: 115 | H89: 60 | I89: =IF(OR(H89="",F89=""),"",MAX(H89,MIN(ROUND(H89*(1+Параметры!$B$5),IF(H89*(1+Параметры!$B$5)>=1000,-1,0)),ROUND(F89*Параметры!$B$6,IF(F89*Параметры!$B$6>=1000,-1,0))))) -> 69 | J89: 69 | K89: =IF(OR(J89="",G89=""),"",MAX(J89,MIN(ROUND(J89*(1+Параметры!$B$5),IF(J89*(1+Параметры!$B$5)>=1000,-1,0)),ROUND(G89*Параметры!$B$6,IF(G89*Параметры!$B$6>=1000,-1,0))))) -> 79 | L89: 0.08 | M89: =IF(OR(L89="",L89=0),"",1/L89) -> 12.5 | N89: =IF(OR(L89="",L89=0),"",Параметры!$B$3/L89) -> 100 | O89: =IF(L89="","",IFERROR(INDEX('Почасовка — ставки и план'!$D$5:$D$24,MATCH($D89,'Почасовка — ставки и план'!$A$5:$A$24,0)),"")) -> 750 | P89: =IF(L89="","",IFERROR(INDEX('Почасовка — ставки и план'!$E$5:$E$24,MATCH($D89,'Почасовка — ставки и план'!$A$5:$A$24,0)),"")) -> 900 | Q89: =IF(OR(L89="",O89=""),"",ROUND(L89*O89,0)) -> 60 | R89: =IF(D89="TEX","аренда техники — сделка/счёт",IF(OR(Q89="",H89="",H89=0),"—",IF(Q89<H89*(1-Параметры!$B$7),"почасовка",IF(Q89>H89*(1+Параметры!$B$7),"сделка","любой способ")))) -> любой способ | S89: 0 | T89: 0
A90: 1.8 Демонтажные работы стен и перегородок
A91: 1.8.1 | B91: Алмазная резка стены железобетонной глубиной до 10 см | C91: мп | D91: BET | E91: =IFERROR(INDEX('Почасовка — ставки и план'!$B$5:$B$24,MATCH(D91,'Почасовка — ставки и план'!$A$5:$A$24,0)),"Аренда техники / механизмы") -> Бетонщик / арматурщик | F91: 800 | G91: 920 | H91: 480 | I91: =IF(OR(H91="",F91=""),"",MAX(H91,MIN(ROUND(H91*(1+Параметры!$B$5),IF(H91*(1+Параметры!$B$5)>=1000,-1,0)),ROUND(F91*Параметры!$B$6,IF(F91*Параметры!$B$6>=1000,-1,0))))) -> 552 | J91: 552 | K91: =IF(OR(J91="",G91=""),"",MAX(J91,MIN(ROUND(J91*(1+Параметры!$B$5),IF(J91*(1+Параметры!$B$5)>=1000,-1,0)),ROUND(G91*Параметры!$B$6,IF(G91*Параметры!$B$6>=1000,-1,0))))) -> 635 | L91: 0.4 | M91: =IF(OR(L91="",L91=0),"",1/L91) -> 2.5 | N91: =IF(OR(L91="",L91=0),"",Параметры!$B$3/L91) -> 20 | O91: =IF(L91="","",IFERROR(INDEX('Почасовка — ставки и план'!$D$5:$D$24,MATCH($D91,'Почасовка — ставки и план'!$A$5:$A$24,0)),"")) -> 800 | P91: =IF(L91="","",IFERROR(INDEX('Почасовка — ставки и план'!$E$5:$E$24,MATCH($D91,'Почасовка — ставки и план'!$A$5:$A$24,0)),"")) -> 950 | Q91: =IF(OR(L91="",O91=""),"",ROUND(L91*O91,0)) -> 320 | R91: =IF(D91="TEX","аренда техники — сделка/счёт",IF(OR(Q91="",H91="",H91=0),"—",IF(Q91<H91*(1-Параметры!$B$7),"почасовка",IF(Q91>H91*(1+Параметры!$B$7),"сделка","любой способ")))) -> почасовка | S91: 0 | T91: 0
A92: 1.8.2 | B92: Алмазная резка стены железобетонной глубиной от 10 см до 40 см | C92: мп | D92: BET | E92: =IFERROR(INDEX('Почасовка — ставки и план'!$B$5:$B$24,MATCH(D92,'Почасовка — ставки и план'!$A$5:$A$24,0)),"Аренда техники / механизмы") -> Бетонщик / арматурщик | F92: 2000 | G92: 2300 | H92: 1200 | I92: =IF(OR(H92="",F92=""),"",MAX(H92,MIN(ROUND(H92*(1+Параметры!$B$5),IF(H92*(1+Параметры!$B$5)>=1000,-1,0)),ROUND(F92*Параметры!$B$6,IF(F92*Параметры!$B$6>=1000,-1,0))))) -> 1380 | J92: 1380 | K92: =IF(OR(J92="",G92=""),"",MAX(J92,MIN(ROUND(J92*(1+Параметры!$B$5),IF(J92*(1+Параметры!$B$5)>=1000,-1,0)),ROUND(G92*Параметры!$B$6,IF(G92*Параметры!$B$6>=1000,-1,0))))) -> 1590 | L92: 1 | M92: =IF(OR(L92="",L92=0),"",1/L92) -> 1 | N92: =IF(OR(L92="",L92=0),"",Параметры!$B$3/L92) -> 8 | O92: =IF(L92="","",IFERROR(INDEX('Почасовка — ставки и план'!$D$5:$D$24,MATCH($D92,'Почасовка — ставки и план'!$A$5:$A$24,0)),"")) -> 800 | P92: =IF(L92="","",IFERROR(INDEX('Почасовка — ставки и план'!$E$5:$E$24,MATCH($D92,'Почасовка — ставки и план'!$A$5:$A$24,0)),"")) -> 950 | Q92: =IF(OR(L92="",O92=""),"",ROUND(L92*O92,0)) -> 800 | R92: =IF(D92="TEX","аренда техники — сделка/счёт",IF(OR(Q92="",H92="",H92=0),"—",IF(Q92<H92*(1-Параметры!$B$7),"почасовка",IF(Q92>H92*(1+Параметры!$B$7),"сделка","любой способ")))) -> почасовка | S92: 0 | T92: 0
A93: 1.8.3 | B93: Демонтаж каркаса под облицовку (только для ГКЛ, ГВЛ,ДСП) | C93: м2 | D93: OTD | E93: =IFERROR(INDEX('Почасовка — ставки и план'!$B$5:$B$24,MATCH(D93,'Почасовка — ставки и план'!$A$5:$A$24,0)),"Аренда техники / механизмы") -> Отделочник (штукатур, маляр, ГКЛ) | F93: 151 | G93: 180 | H93: 70 | I93: =IF(OR(H93="",F93=""),"",MAX(H93,MIN(ROUND(H93*(1+Параметры!$B$5),IF(H93*(1+Параметры!$B$5)>=1000,-1,0)),ROUND(F93*Параметры!$B$6,IF(F93*Параметры!$B$6>=1000,-1,0))))) -> 81 | J93: 80.5 | K93: =IF(OR(J93="",G93=""),"",MAX(J93,MIN(ROUND(J93*(1+Параметры!$B$5),IF(J93*(1+Параметры!$B$5)>=1000,-1,0)),ROUND(G93*Параметры!$B$6,IF(G93*Параметры!$B$6>=1000,-1,0))))) -> 93 | L93: 0.15 | M93: =IF(OR(L93="",L93=0),"",1/L93) -> 6.6666667 | N93: =IF(OR(L93="",L93=0),"",Параметры!$B$3/L93) -> 53.333333 | O93: =IF(L93="","",IFERROR(INDEX('Почасовка — ставки и план'!$D$5:$D$24,MATCH($D93,'Почасовка — ставки и план'!$A$5:$A$24,0)),"")) -> 750 | P93: =IF(L93="","",IFERROR(INDEX('Почасовка — ставки и план'!$E$5:$E$24,MATCH($D93,'Почасовка — ставки и план'!$A$5:$A$24,0)),"")) -> 900 | Q93: =IF(OR(L93="",O93=""),"",ROUND(L93*O93,0)) -> 113 | R93: =IF(D93="TEX","аренда техники — сделка/счёт",IF(OR(Q93="",H93="",H93=0),"—",IF(Q93<H93*(1-Параметры!$B$7),"почасовка",IF(Q93>H93*(1+Параметры!$B$7),"сделка","любой способ")))) -> сделка | S93: 0.25833333 | T93: 0.30434783
A94: 1.8.4 | B94: Демонтаж облицовки стен из ГКЛ, ГВЛ, панелей ПВХ, ДСП (с сохранением каркаса) | C94: м2 | D94: OTD | E94: =IFERROR(INDEX('Почасовка — ставки и план'!$B$5:$B$24,MATCH(D94,'Почасовка — ставки и план'!$A$5:$A$24,0)),"Аренда техники / механизмы") -> Отделочник (штукатур, маляр, ГКЛ) | F94: 180 | G94: 216 | H94: 90 | I94: =IF(OR(H94="",F94=""),"",MAX(H94,MIN(ROUND(H94*(1+Параметры!$B$5),IF(H94*(1+Параметры!$B$5)>=1000,-1,0)),ROUND(F94*Параметры!$B$6,IF(F94*Параметры!$B$6>=1000,-1,0))))) -> 104 | J94: 103 | K94: =IF(OR(J94="",G94=""),"",MAX(J94,MIN(ROUND(J94*(1+Параметры!$B$5),IF(J94*(1+Параметры!$B$5)>=1000,-1,0)),ROUND(G94*Параметры!$B$6,IF(G94*Параметры!$B$6>=1000,-1,0))))) -> 118 | L94: 0.18 | M94: =IF(OR(L94="",L94=0),"",1/L94) -> 5.5555556 | N94: =IF(OR(L94="",L94=0),"",Параметры!$B$3/L94) -> 44.444444 | O94: =IF(L94="","",IFERROR(INDEX('Почасовка — ставки и план'!$D$5:$D$24,MATCH($D94,'Почасовка — ставки и план'!$A$5:$A$24,0)),"")) -> 750 | P94: =IF(L94="","",IFERROR(INDEX('Почасовка — ставки и план'!$E$5:$E$24,MATCH($D94,'Почасовка — ставки и план'!$A$5:$A$24,0)),"")) -> 900 | Q94: =IF(OR(L94="",O94=""),"",ROUND(L94*O94,0)) -> 135 | R94: =IF(D94="TEX","аренда техники — сделка/счёт",IF(OR(Q94="",H94="",H94=0),"—",IF(Q94<H94*(1-Параметры!$B$7),"почасовка",IF(Q94>H94*(1+Параметры!$B$7),"сделка","любой способ")))) -> сделка | S94: 0.2 | T94: 0.25581395
A95: 1.8.5 | B95: Демонтаж облицовки стен из керамической плитки | C95: м2 | D95: OTD | E95: =IFERROR(INDEX('Почасовка — ставки и план'!$B$5:$B$24,MATCH(D95,'Почасовка — ставки и план'!$A$5:$A$24,0)),"Аренда техники / механизмы") -> Отделочник (штукатур, маляр, ГКЛ) | F95: 400 | G95: 480 | H95: 180 | I95: =IF(OR(H95="",F95=""),"",MAX(H95,MIN(ROUND(H95*(1+Параметры!$B$5),IF(H95*(1+Параметры!$B$5)>=1000,-1,0)),ROUND(F95*Параметры!$B$6,IF(F95*Параметры!$B$6>=1000,-1,0))))) -> 207 | J95: 207 | K95: =IF(OR(J95="",G95=""),"",MAX(J95,MIN(ROUND(J95*(1+Параметры!$B$5),IF(J95*(1+Параметры!$B$5)>=1000,-1,0)),ROUND(G95*Параметры!$B$6,IF(G95*Параметры!$B$6>=1000,-1,0))))) -> 238 | L95: 0.4 | M95: =IF(OR(L95="",L95=0),"",1/L95) -> 2.5 | N95: =IF(OR(L95="",L95=0),"",Параметры!$B$3/L95) -> 20 | O95: =IF(L95="","",IFERROR(INDEX('Почасовка — ставки и план'!$D$5:$D$24,MATCH($D95,'Почасовка — ставки и план'!$A$5:$A$24,0)),"")) -> 750 | P95: =IF(L95="","",IFERROR(INDEX('Почасовка — ставки и план'!$E$5:$E$24,MATCH($D95,'Почасовка — ставки и план'!$A$5:$A$24,0)),"")) -> 900 | Q95: =IF(OR(L95="",O95=""),"",ROUND(L95*O95,0)) -> 300 | R95: =IF(D95="TEX","аренда техники — сделка/счёт",IF(OR(Q95="",H95="",H95=0),"—",IF(Q95<H95*(1-Параметры!$B$7),"почасовка",IF(Q95>H95*(1+Параметры!$B$7),"сделка","любой способ")))) -> сделка | S95: 0.33333333 | T95: 0.39130435
A96: 1.8.6 | B96: Демонтаж облицовки стен из металлических листов/оцинковки | C96: м2 | D96: OTD | E96: =IFERROR(INDEX('Почасовка — ставки и план'!$B$5:$B$24,MATCH(D96,'Почасовка — ставки и план'!$A$5:$A$24,0)),"Аренда техники / механизмы") -> Отделочник (штукатур, маляр, ГКЛ) | F96: 220 | G96: 264 | H96: 110 | I96: =IF(OR(H96="",F96=""),"",MAX(H96,MIN(ROUND(H96*(1+Параметры!$B$5),IF(H96*(1+Параметры!$B$5)>=1000,-1,0)),ROUND(F96*Параметры!$B$6,IF(F96*Параметры!$B$6>=1000,-1,0))))) -> 127 | J96: 126 | K96: =IF(OR(J96="",G96=""),"",MAX(J96,MIN(ROUND(J96*(1+Параметры!$B$5),IF(J96*(1+Параметры!$B$5)>=1000,-1,0)),ROUND(G96*Параметры!$B$6,IF(G96*Параметры!$B$6>=1000,-1,0))))) -> 145 | L96: 0.22 | M96: =IF(OR(L96="",L96=0),"",1/L96) -> 4.5454545 | N96: =IF(OR(L96="",L96=0),"",Параметры!$B$3/L96) -> 36.363636 | O96: =IF(L96="","",IFERROR(INDEX('Почасовка — ставки и план'!$D$5:$D$24,MATCH($D96,'Почасовка — ставки и план'!$A$5:$A$24,0)),"")) -> 750 | P96: =IF(L96="","",IFERROR(INDEX('Почасовка — ставки и план'!$E$5:$E$24,MATCH($D96,'Почасовка — ставки и план'!$A$5:$A$24,0)),"")) -> 900 | Q96: =IF(OR(L96="",O96=""),"",ROUND(L96*O96,0)) -> 165 | R96: =IF(D96="TEX","аренда техники — сделка/счёт",IF(OR(Q96="",H96="",H96=0),"—",IF(Q96<H96*(1-Параметры!$B$7),"почасовка",IF(Q96>H96*(1+Параметры!$B$7),"сделка","любой способ")))) -> сделка | S96: 0.22222222 | T96: 0.27536232
A97: 1.8.7 | B97: Демонтаж утеплителя стен | C97: м2 | D97: RAZ | E97: =IFERROR(INDEX('Почасовка — ставки и план'!$B$5:$B$24,MATCH(D97,'Почасовка — ставки и план'!$A$5:$A$24,0)),"Аренда техники / механизмы") -> Разнорабочий / демонтажник | F97: 120 | G97: 138 | H97: 70 | I97: =IF(OR(H97="",F97=""),"",MAX(H97,MIN(ROUND(H97*(1+Параметры!$B$5),IF(H97*(1+Параметры!$B$5)>=1000,-1,0)),ROUND(F97*Параметры!$B$6,IF(F97*Параметры!$B$6>=1000,-1,0))))) -> 81 | J97: 80.5 | K97: =IF(OR(J97="",G97=""),"",MAX(J97,MIN(ROUND(J97*(1+Параметры!$B$5),IF(J97*(1+Параметры!$B$5)>=1000,-1,0)),ROUND(G97*Параметры!$B$6,IF(G97*Параметры!$B$6>=1000,-1,0))))) -> 93 | L97: 0.15 | M97: =IF(OR(L97="",L97=0),"",1/L97) -> 6.6666667 | N97: =IF(OR(L97="",L97=0),"",Параметры!$B$3/L97) -> 53.333333 | O97: =IF(L97="","",IFERROR(INDEX('Почасовка — ставки и план'!$D$5:$D$24,MATCH($D97,'Почасовка — ставки и план'!$A$5:$A$24,0)),"")) -> 550 | P97: =IF(L97="","",IFERROR(INDEX('Почасовка — ставки и план'!$E$5:$E$24,MATCH($D97,'Почасовка — ставки и план'!$A$5:$A$24,0)),"")) -> 660 | Q97: =IF(OR(L97="",O97=""),"",ROUND(L97*O97,0)) -> 83 | R97: =IF(D97="TEX","аренда техники — сделка/счёт",IF(OR(Q97="",H97="",H97=0),"—",IF(Q97<H97*(1-Параметры!$B$7),"почасовка",IF(Q97>H97*(1+Параметры!$B$7),"сделка","любой способ")))) -> сделка | S97: 0 | T97: 0
A98: 1.8.8 | B98: Отбивка штукатурки с поверхностей стен, столбов, колонн, пилястр | C98: м2 | D98: OTD | E98: =IFERROR(INDEX('Почасовка — ставки и план'!$B$5:$B$24,MATCH(D98,'Почасовка — ставки и план'!$A$5:$A$24,0)),"Аренда техники / механизмы") -> Отделочник (штукатур, маляр, ГКЛ) | F98: 451 | G98: 540 | H98: 210 | I98: =IF(OR(H98="",F98=""),"",MAX(H98,MIN(ROUND(H98*(1+Параметры!$B$5),IF(H98*(1+Параметры!$B$5)>=1000,-1,0)),ROUND(F98*Параметры!$B$6,IF(F98*Параметры!$B$6>=1000,-1,0))))) -> 242 | J98: 241 | K98: =IF(OR(J98="",G98=""),"",MAX(J98,MIN(ROUND(J98*(1+Параметры!$B$5),IF(J98*(1+Параметры!$B$5)>=1000,-1,0)),ROUND(G98*Параметры!$B$6,IF(G98*Параметры!$B$6>=1000,-1,0))))) -> 277 | L98: 0.45 | M98: =IF(OR(L98="",L98=0),"",1/L98) -> 2.2222222 | N98: =IF(OR(L98="",L98=0),"",Параметры!$B$3/L98) -> 17.777778 | O98: =IF(L98="","",IFERROR(INDEX('Почасовка — ставки и план'!$D$5:$D$24,MATCH($D98,'Почасовка — ставки и план'!$A$5:$A$24,0)),"")) -> 750 | P98: =IF(L98="","",IFERROR(INDEX('Почасовка — ставки и план'!$E$5:$E$24,MATCH($D98,'Почасовка — ставки и план'!$A$5:$A$24,0)),"")) -> 900 | Q98: =IF(OR(L98="",O98=""),"",ROUND(L98*O98,0)) -> 338 | R98: =IF(D98="TEX","аренда техники — сделка/счёт",IF(OR(Q98="",H98="",H98=0),"—",IF(Q98<H98*(1-Параметры!$B$7),"почасовка",IF(Q98>H98*(1+Параметры!$B$7),"сделка","любой способ")))) -> сделка | S98: 0.28857143 | T98: 0.34328358
A99: 1.8.9 | B99: Пробивка проема в конструкциях из бетона | C99: м3 | D99: RAZ | E99: =IFERROR(INDEX('Почасовка — ставки и план'!$B$5:$B$24,MATCH(D99,'Почасовка — ставки и план'!$A$5:$A$24,0)),"Аренда техники / механизмы") -> Разнорабочий / демонтажник | F99: 14667 | G99: 17600 | H99: 8400 | I99: =IF(OR(H99="",F99=""),"",MAX(H99,MIN(ROUND(H99*(1+Параметры!$B$5),IF(H99*(1+Параметры!$B$5)>=1000,-1,0)),ROUND(F99*Параметры!$B$6,IF(F99*Параметры!$B$6>=1000,-1,0))))) -> 9660 | J99: 9912 | K99: =IF(OR(J99="",G99=""),"",MAX(J99,MIN(ROUND(J99*(1+Параметры!$B$5),IF(J99*(1+Параметры!$B$5)>=1000,-1,0)),ROUND(G99*Параметры!$B$6,IF(G99*Параметры!$B$6>=1000,-1,0))))) -> 11400 | L99: 20 | M99: =IF(OR(L99="",L99=0),"",1/L99) -> 0.05 | N99: =IF(OR(L99="",L99=0),"",Параметры!$B$3/L99) -> 0.4 | O99: =IF(L99="","",IFERROR(INDEX('Почасовка — ставки и план'!$D$5:$D$24,MATCH($D99,'Почасовка — ставки и план'!$A$5:$A$24,0)),"")) -> 550 | P99: =IF(L99="","",IFERROR(INDEX('Почасовка — ставки и план'!$E$5:$E$24,MATCH($D99,'Почасовка — ставки и план'!$A$5:$A$24,0)),"")) -> 660 | Q99: =IF(OR(L99="",O99=""),"",ROUND(L99*O99,0)) -> 11000 | R99: =IF(D99="TEX","аренда техники — сделка/счёт",IF(OR(Q99="",H99="",H99=0),"—",IF(Q99<H99*(1-Параметры!$B$7),"почасовка",IF(Q99>H99*(1+Параметры!$B$7),"сделка","любой способ")))) -> сделка | S99: 0.047642857 | T99: 0.047619048
A100: 1.8.10 | B100: Пробивка проема в конструкциях из кирпича | C100: м3 | D100: KAM | E100: =IFERROR(INDEX('Почасовка — ставки и план'!$B$5:$B$24,MATCH(D100,'Почасовка — ставки и план'!$A$5:$A$24,0)),"Аренда техники / механизмы") -> Каменщик | F100: 9600 | G100: 11400 | H100: 3600 | I100: =IF(OR(H100="",F100=""),"",MAX(H100,MIN(ROUND(H100*(1+Параметры!$B$5),IF(H100*(1+Параметры!$B$5)>=1000,-1,0)),ROUND(F100*Параметры!$B$6,IF(F100*Параметры!$B$6>=1000,-1,0))))) -> 4140 | J100: 4140 | K100: =IF(OR(J100="",G100=""),"",MAX(J100,MIN(ROUND(J100*(1+Параметры!$B$5),IF(J100*(1+Параметры!$B$5)>=1000,-1,0)),ROUND(G100*Параметры!$B$6,IF(G100*Параметры!$B$6>=1000,-1,0))))) -> 4760 | L100: 9 | M100: =IF(OR(L100="",L100=0),"",1/L100) -> 0.11111111 | N100: =IF(OR(L100="",L100=0),"",Параметры!$B$3/L100) -> 0.88888889 | O100: =IF(L100="","",IFERROR(INDEX('Почасовка — ставки и план'!$D$5:$D$24,MATCH($D100,'Почасовка — ставки и план'!$A$5:$A$24,0)),"")) -> 800 | P100: =IF(L100="","",IFERROR(INDEX('Почасовка — ставки и план'!$E$5:$E$24,MATCH($D100,'Почасовка — ставки и план'!$A$5:$A$24,0)),"")) -> 950 | Q100: =IF(OR(L100="",O100=""),"",ROUND(L100*O100,0)) -> 7200 | R100: =IF(D100="TEX","аренда техники — сделка/счёт",IF(OR(Q100="",H100="",H100=0),"—",IF(Q100<H100*(1-Параметры!$B$7),"почасовка",IF(Q100>H100*(1+Параметры!$B$7),"сделка","любой способ")))) -> сделка | S100: 0.6 | T100: 0.65217391
A101: 1.8.11 | B101: Пробивка проема со сплошным выравниванием откосов в перегородках бетонных | C101: м2 | D101: RAZ | E101: =IFERROR(INDEX('Почасовка — ставки и план'!$B$5:$B$24,MATCH(D101,'Почасовка — ставки и план'!$A$5:$A$24,0)),"Аренда техники / механизмы") -> Разнорабочий / демонтажник | F101: 4000 | G101: 4600 | H101: 2400 | I101: =IF(OR(H101="",F101=""),"",MAX(H101,MIN(ROUND(H101*(1+Параметры!$B$5),IF(H101*(1+Параметры!$B$5)>=1000,-1,0)),ROUND(F101*Параметры!$B$6,IF(F101*Параметры!$B$6>=1000,-1,0))))) -> 2760 | J101: 2760 | K101: =IF(OR(J101="",G101=""),"",MAX(J101,MIN(ROUND(J101*(1+Параметры!$B$5),IF(J101*(1+Параметры!$B$5)>=1000,-1,0)),ROUND(G101*Параметры!$B$6,IF(G101*Параметры!$B$6>=1000,-1,0))))) -> 3170 | L101: 5 | M101: =IF(OR(L101="",L101=0),"",1/L101) -> 0.2 | N101: =IF(OR(L101="",L101=0),"",Параметры!$B$3/L101) -> 1.6 | O101: =IF(L101="","",IFERROR(INDEX('Почасовка — ставки и план'!$D$5:$D$24,MATCH($D101,'Почасовка — ставки и план'!$A$5:$A$24,0)),"")) -> 550 | P101: =IF(L101="","",IFERROR(INDEX('Почасовка — ставки и план'!$E$5:$E$24,MATCH($D101,'Почасовка — ставки и план'!$A$5:$A$24,0)),"")) -> 660 | Q101: =IF(OR(L101="",O101=""),"",ROUND(L101*O101,0)) -> 2750 | R101: =IF(D101="TEX","аренда техники — сделка/счёт",IF(OR(Q101="",H101="",H101=0),"—",IF(Q101<H101*(1-Параметры!$B$7),"почасовка",IF(Q101>H101*(1+Параметры!$B$7),"сделка","любой способ")))) -> сделка | S101: 0 | T101: 0
A102: 1.8.12 | B102: Пробивка проема со сплошным выравниванием откосов в перегородках кирпичных | C102: м2 | D102: KAM | E102: =IFERROR(INDEX('Почасовка — ставки и план'!$B$5:$B$24,MATCH(D102,'Почасовка — ставки и план'!$A$5:$A$24,0)),"Аренда техники / механизмы") -> Каменщик | F102: 4267 | G102: 5067 | H102: 1800 | I102: =IF(OR(H102="",F102=""),"",MAX(H102,MIN(ROUND(H102*(1+Параметры!$B$5),IF(H102*(1+Параметры!$B$5)>=1000,-1,0)),ROUND(F102*Параметры!$B$6,IF(F102*Параметры!$B$6>=1000,-1,0))))) -> 2070 | J102: 2070 | K102: =IF(OR(J102="",G102=""),"",MAX(J102,MIN(ROUND(J102*(1+Параметры!$B$5),IF(J102*(1+Параметры!$B$5)>=1000,-1,0)),ROUND(G102*Параметры!$B$6,IF(G102*Параметры!$B$6>=1000,-1,0))))) -> 2380 | L102: 4 | M102: =IF(OR(L102="",L102=0),"",1/L102) -> 0.25 | N102: =IF(OR(L102="",L102=0),"",Параметры!$B$3/L102) -> 2 | O102: =IF(L102="","",IFERROR(INDEX('Почасовка — ставки и план'!$D$5:$D$24,MATCH($D102,'Почасовка — ставки и план'!$A$5:$A$24,0)),"")) -> 800 | P102: =IF(L102="","",IFERROR(INDEX('Почасовка — ставки и план'!$E$5:$E$24,MATCH($D102,'Почасовка — ставки и план'!$A$5:$A$24,0)),"")) -> 950 | Q102: =IF(OR(L102="",O102=""),"",ROUND(L102*O102,0)) -> 3200 | R102: =IF(D102="TEX","аренда техники — сделка/счёт",IF(OR(Q102="",H102="",H102=0),"—",IF(Q102<H102*(1-Параметры!$B$7),"почасовка",IF(Q102>H102*(1+Параметры!$B$7),"сделка","любой способ")))) -> сделка | S102: 0.42233333 | T102: 0.46869565
... A112: 1.8.N4 | B112: Удаление масляной краски со стен механически | C112: м2 | D112: OTD | E112: =IFERROR(INDEX('Почасовка — ставки и план'!$B$5:$B$24,MATCH(D112,'Почасовка — ставки и план'!$A$5:$A$24,0)),"Аренда техники / механизмы") -> Отделочник (штукатур, маляр, ГКЛ) | F112: 351 | G112: 420 | H112: 150 | I112: =IF(OR(H112="",F112=""),"",MAX(H112,MIN(ROUND(H112*(1+Параметры!$B$5),IF(H112*(1+Параметры!$B$5)>=1000,-1,0)),ROUND(F112*Параметры!$B$6,IF(F112*Параметры!$B$6>=1000,-1,0))))) -> 173 | J112: 172 | K112: =IF(OR(J112="",G112=""),"",MAX(J112,MIN(ROUND(J112*(1+Параметры!$B$5),IF(J112*(1+Параметры!$B$5)>=1000,-1,0)),ROUND(G112*Параметры!$B$6,IF(G112*Параметры!$B$6>=1000,-1,0))))) -> 198 | L112: 0.35 | M112: =IF(OR(L112="",L112=0),"",1/L112) -> 2.8571429 | N112: =IF(OR(L112="",L112=0),"",Параметры!$B$3/L112) -> 22.857143 | O112: =IF(L112="","",IFERROR(INDEX('Почасовка — ставки и план'!$D$5:$D$24,MATCH($D112,'Почасовка — ставки и план'!$A$5:$A$24,0)),"")) -> 750 | P112: =IF(L112="","",IFERROR(INDEX('Почасовка — ставки и план'!$E$5:$E$24,MATCH($D112,'Почасовка — ставки и план'!$A$5:$A$24,0)),"")) -> 900 | Q112: =IF(OR(L112="",O112=""),"",ROUND(L112*O112,0)) -> 263 | R112: =IF(D112="TEX","аренда техники — сделка/счёт",IF(OR(Q112="",H112="",H112=0),"—",IF(Q112<H112*(1-Параметры!$B$7),"почасовка",IF(Q112>H112*(1+Параметры!$B$7),"сделка","любой способ")))) -> сделка | S112: 0.404 | T112: 0.45833333
A113: 1.9 Демонтажные работы вентиляция/кондиционирование
A114: 1.9.1 | B114: Демонтаж антивандальной решетки №1 1000х500х 600 | C114: шт | D114: SVA | E114: =IFERROR(INDEX('Почасовка — ставки и план'!$B$5:$B$24,MATCH(D114,'Почасовка — ставки и план'!$A$5:$A$24,0)),"Аренда техники / механизмы") -> Сварщик / монтажник МК | F114: 1800 | G114: 2160 | H114: 720 | I114: =IF(OR(H114="",F114=""),"",MAX(H114,MIN(ROUND(H114*(1+Параметры!$B$5),IF(H114*(1+Параметры!$B$5)>=1000,-1,0)),ROUND(F114*Параметры!$B$6,IF(F114*Параметры!$B$6>=1000,-1,0))))) -> 828 | J114: 828 | K114: =IF(OR(J114="",G114=""),"",MAX(J114,MIN(ROUND(J114*(1+Параметры!$B$5),IF(J114*(1+Параметры!$B$5)>=1000,-1,0)),ROUND(G114*Параметры!$B$6,IF(G114*Параметры!$B$6>=1000,-1,0))))) -> 952 | L114: 1.5 | M114: =IF(OR(L114="",L114=0),"",1/L114) -> 0.66666667 | N114: =IF(OR(L114="",L114=0),"",Параметры!$B$3/L114) -> 5.3333333 | O114: =IF(L114="","",IFERROR(INDEX('Почасовка — ставки и план'!$D$5:$D$24,MATCH($D114,'Почасовка — ставки и план'!$A$5:$A$24,0)),"")) -> 900 | P114: =IF(L114="","",IFERROR(INDEX('Почасовка — ставки и план'!$E$5:$E$24,MATCH($D114,'Почасовка — ставки и план'!$A$5:$A$24,0)),"")) -> 1080 | Q114: =IF(OR(L114="",O114=""),"",ROUND(L114*O114,0)) -> 1350 | R114: =IF(D114="TEX","аренда техники — сделка/счёт",IF(OR(Q114="",H114="",H114=0),"—",IF(Q114<H114*(1-Параметры!$B$7),"почасовка",IF(Q114>H114*(1+Параметры!$B$7),"сделка","любой способ")))) -> сделка | S114: 0.5 | T114: 0.56521739
A115: 1.9.2 | B115: Демонтаж антивандальной решетки №2 1200х700х1000 | C115: шт | D115: SVA | E115: =IFERROR(INDEX('Почасовка — ставки и план'!$B$5:$B$24,MATCH(D115,'Почасовка — ставки и план'!$A$5:$A$24,0)),"Аренда техники / механизмы") -> Сварщик / монтажник МК | F115: 2400 | G115: 2880 | H115: 960 | I115: =IF(OR(H115="",F115=""),"",MAX(H115,MIN(ROUND(H115*(1+Параметры!$B$5),IF(H115*(1+Параметры!$B$5)>=1000,-1,0)),ROUND(F115*Параметры!$B$6,IF(F115*Параметры!$B$6>=1000,-1,0))))) -> 1100 | J115: 1104 | K115: =IF(OR(J115="",G115=""),"",MAX(J115,MIN(ROUND(J115*(1+Параметры!$B$5),IF(J115*(1+Параметры!$B$5)>=1000,-1,0)),ROUND(G115*Параметры!$B$6,IF(G115*Параметры!$B$6>=1000,-1,0))))) -> 1270 | L115: 2 | M115: =IF(OR(L115="",L115=0),"",1/L115) -> 0.5 | N115: =IF(OR(L115="",L115=0),"",Параметры!$B$3/L115) -> 4 | O115: =IF(L115="","",IFERROR(INDEX('Почасовка — ставки и план'!$D$5:$D$24,MATCH($D115,'Почасовка — ставки и план'!$A$5:$A$24,0)),"")) -> 900 | P115: =IF(L115="","",IFERROR(INDEX('Почасовка — ставки и план'!$E$5:$E$24,MATCH($D115,'Почасовка — ставки и план'!$A$5:$A$24,0)),"")) -> 1080 | Q115: =IF(OR(L115="",O115=""),"",ROUND(L115*O115,0)) -> 1800 | R115: =IF(D115="TEX","аренда техники — сделка/счёт",IF(OR(Q115="",H115="",H115=0),"—",IF(Q115<H115*(1-Параметры!$B$7),"почасовка",IF(Q115>H115*(1+Параметры!$B$7),"сделка","любой способ")))) -> сделка | S115: 0.5 | T115: 0.56521739
A116: 1.9.3 | B116: Демонтаж антивандальной решетки №3 1300х900х1500 | C116: шт | D116: SVA | E116: =IFERROR(INDEX('Почасовка — ставки и план'!$B$5:$B$24,MATCH(D116,'Почасовка — ставки и план'!$A$5:$A$24,0)),"Аренда техники / механизмы") -> Сварщик / монтажник МК | F116: 3000 | G116: 3600 | H116: 1200 | I116: =IF(OR(H116="",F116=""),"",MAX(H116,MIN(ROUND(H116*(1+Параметры!$B$5),IF(H116*(1+Параметры!$B$5)>=1000,-1,0)),ROUND(F116*Параметры!$B$6,IF(F116*Параметры!$B$6>=1000,-1,0))))) -> 1380 | J116: 1380 | K116: =IF(OR(J116="",G116=""),"",MAX(J116,MIN(ROUND(J116*(1+Параметры!$B$5),IF(J116*(1+Параметры!$B$5)>=1000,-1,0)),ROUND(G116*Параметры!$B$6,IF(G116*Параметры!$B$6>=1000,-1,0))))) -> 1590 | L116: 2.5 | M116: =IF(OR(L116="",L116=0),"",1/L116) -> 0.4 | N116: =IF(OR(L116="",L116=0),"",Параметры!$B$3/L116) -> 3.2 | O116: =IF(L116="","",IFERROR(INDEX('Почасовка — ставки и план'!$D$5:$D$24,MATCH($D116,'Почасовка — ставки и план'!$A$5:$A$24,0)),"")) -> 900 | P116: =IF(L116="","",IFERROR(INDEX('Почасовка — ставки и план'!$E$5:$E$24,MATCH($D116,'Почасовка — ставки и план'!$A$5:$A$24,0)),"")) -> 1080 | Q116: =IF(OR(L116="",O116=""),"",ROUND(L116*O116,0)) -> 2250 | R116: =IF(D116="TEX","аренда техники — сделка/счёт",IF(OR(Q116="",H116="",H116=0),"—",IF(Q116<H116*(1-Параметры!$B$7),"почасовка",IF(Q116>H116*(1+Параметры!$B$7),"сделка","любой способ")))) -> сделка | S116: 0.5 | T116: 0.56521739
A117: 1.9.4 | B117: Демонтаж вент.оборудования весом от 025 тн до 0.5 тн (вентилятор) | C117: шт | D117: VEN | E117: =IFERROR(INDEX('Почасовка — ставки и план'!$B$5:$B$24,MATCH(D117,'Почасовка — ставки и план'!$A$5:$A$24,0)),"Аренда техники / механизмы") -> Монтажник вентиляции | F117: 22000 | G117: 25300 | H117: 13000 | I117: =IF(OR(H117="",F117=""),"",MAX(H117,MIN(ROUND(H117*(1+Параметры!$B$5),IF(H117*(1+Параметры!$B$5)>=1000,-1,0)),ROUND(F117*Параметры!$B$6,IF(F117*Параметры!$B$6>=1000,-1,0))))) -> 14950 | J117: 14950 | K117: =IF(OR(J117="",G117=""),"",MAX(J117,MIN(ROUND(J117*(1+Параметры!$B$5),IF(J117*(1+Параметры!$B$5)>=1000,-1,0)),ROUND(G117*Параметры!$B$6,IF(G117*Параметры!$B$6>=1000,-1,0))))) -> 17190 | L117: 16 | M117: =IF(OR(L117="",L117=0),"",1/L117) -> 0.0625 | N117: =IF(OR(L117="",L117=0),"",Параметры!$B$3/L117) -> 0.5 | O117: =IF(L117="","",IFERROR(INDEX('Почасовка — ставки и план'!$D$5:$D$24,MATCH($D117,'Почасовка — ставки и план'!$A$5:$A$24,0)),"")) -> 850 | P117: =IF(L117="","",IFERROR(INDEX('Почасовка — ставки и план'!$E$5:$E$24,MATCH($D117,'Почасовка — ставки и план'!$A$5:$A$24,0)),"")) -> 1020 | Q117: =IF(OR(L117="",O117=""),"",ROUND(L117*O117,0)) -> 13600 | R117: =IF(D117="TEX","аренда техники — сделка/счёт",IF(OR(Q117="",H117="",H117=0),"—",IF(Q117<H117*(1-Параметры!$B$7),"почасовка",IF(Q117>H117*(1+Параметры!$B$7),"сделка","любой способ")))) -> любой способ | S117: 0 | T117: 0
A118: 1.9.5 | B118: Демонтаж вент.оборудования весом до 0.1 тн (вентилятор) | C118: шт | D118: VEN | E118: =IFERROR(INDEX('Почасовка — ставки и план'!$B$5:$B$24,MATCH(D118,'Почасовка — ставки и план'!$A$5:$A$24,0)),"Аренда техники / механизмы") -> Монтажник вентиляции | F118: 6000 | G118: 6900 | H118: 3600 | I118: =IF(OR(H118="",F118=""),"",MAX(H118,MIN(ROUND(H118*(1+Параметры!$B$5),IF(H118*(1+Параметры!$B$5)>=1000,-1,0)),ROUND(F118*Параметры!$B$6,IF(F118*Параметры!$B$6>=1000,-1,0))))) -> 4140 | J118: 4140 | K118: =IF(OR(J118="",G118=""),"",MAX(J118,MIN(ROUND(J118*(1+Параметры!$B$5),IF(J118*(1+Параметры!$B$5)>=1000,-1,0)),ROUND(G118*Параметры!$B$6,IF(G118*Параметры!$B$6>=1000,-1,0))))) -> 4760 | L118: 5 | M118: =IF(OR(L118="",L118=0),"",1/L118) -> 0.2 | N118: =IF(OR(L118="",L118=0),"",Параметры!$B$3/L118) -> 1.6 | O118: =IF(L118="","",IFERROR(INDEX('Почасовка — ставки и план'!$D$5:$D$24,MATCH($D118,'Почасовка — ставки и план'!$A$5:$A$24,0)),"")) -> 850 | P118: =IF(L118="","",IFERROR(INDEX('Почасовка — ставки и план'!$E$5:$E$24,MATCH($D118,'Почасовка — ставки и план'!$A$5:$A$24,0)),"")) -> 1020 | Q118: =IF(OR(L118="",O118=""),"",ROUND(L118*O118,0)) -> 4250 | R118: =IF(D118="TEX","аренда техники — сделка/счёт",IF(OR(Q118="",H118="",H118=0),"—",IF(Q118<H118*(1-Параметры!$B$7),"почасовка",IF(Q118>H118*(1+Параметры!$B$7),"сделка","любой способ")))) -> сделка | S118: 0 | T118: 0
A119: 1.9.6 | B119: Демонтаж вент.оборудования весом от 01 тн до 0.25 тн (вентилятор) | C119: шт | D119: VEN | E119: =IFERROR(INDEX('Почасовка — ставки и план'!$B$5:$B$24,MATCH(D119,'Почасовка — ставки и план'!$A$5:$A$24,0)),"Аренда техники / механизмы") -> Монтажник вентиляции | F119: 11000 | G119: 12650 | H119: 6600 | I119: =IF(OR(H119="",F119=""),"",MAX(H119,MIN(ROUND(H119*(1+Параметры!$B$5),IF(H119*(1+Параметры!$B$5)>=1000,-1,0)),ROUND(F119*Параметры!$B$6,IF(F119*Параметры!$B$6>=1000,-1,0))))) -> 7590 | J119: 7590 | K119: =IF(OR(J119="",G119=""),"",MAX(J119,MIN(ROUND(J119*(1+Параметры!$B$5),IF(J119*(1+Параметры!$B$5)>=1000,-1,0)),ROUND(G119*Параметры!$B$6,IF(G119*Параметры!$B$6>=1000,-1,0))))) -> 8730 | L119: 9 | M119: =IF(OR(L119="",L119=0),"",1/L119) -> 0.11111111 | N119: =IF(OR(L119="",L119=0),"",Параметры!$B$3/L119) -> 0.88888889 | O119: =IF(L119="","",IFERROR(INDEX('Почасовка — ставки и план'!$D$5:$D$24,MATCH($D119,'Почасовка — ставки и план'!$A$5:$A$24,0)),"")) -> 850 | P119: =IF(L119="","",IFERROR(INDEX('Почасовка — ставки и план'!$E$5:$E$24,MATCH($D119,'Почасовка — ставки и план'!$A$5:$A$24,0)),"")) -> 1020 | Q119: =IF(OR(L119="",O119=""),"",ROUND(L119*O119,0)) -> 7650 | R119: =IF(D119="TEX","аренда техники — сделка/счёт",IF(OR(Q119="",H119="",H119=0),"—",IF(Q119<H119*(1-Параметры!$B$7),"почасовка",IF(Q119>H119*(1+Параметры!$B$7),"сделка","любой способ")))) -> сделка | S119: 0 | T119: 0
...

Sheet Почасовка — ставки и план
A1: ПОЧАСОВАЯ ОПЛАТА ПО СПЕЦИАЛЬНОСТЯМ
A2: Жёлтые ячейки — вводные (ставка бригаде ИП/СЗ вкл. налог 6 % и рынок нормо-часа подрядчика): при изменении пересчитываются листы «Расценки» и «Для HR». Цена в КП на листе «Расценки» не пересчитывается — она из основного тарификатора.
A4: Код | B4: Специальность | C4: Что делает | D4: Ставка часа СПб, руб/ч (вводная) | E4: Ставка часа Мск, руб/ч (вводная) | F4: Смена СПб, руб = ставка × часы смены | G4: Смена Мск, руб = ставка × часы смены | H4: Месяц СПб, руб = смена × смен в месяц | I4: Месяц Мск, руб = смена × смен в месяц | J4: Рынок нормо-часа подрядчика СПб, б/НДС (вводная) | K4: Рынок нормо-часа Мск (вводная) | L4: Нормо-час для заказчика СПб, б/НДС = ставка × 1,25 × 1,35, не ниже 95 % рынка | M4: Нормо-час для заказчика Мск, б/НДС = то же | N4: Работ в тарификаторе
A5: RAZ | B5: Разнорабочий / демонтажник | C5: Демонтаж, разборка, вынос мусора, такелаж вручную, уборка | D5: 550 | E5: 660 | F5: =D5*Параметры!$B$3 -> 4400 | G5: =E5*Параметры!$B$3 -> 5280 | H5: =F5*Параметры!$B$4 -> 92400 | I5: =G5*Параметры!$B$4 -> 110880 | J5: 1000 | K5: 1200 | L5: =IF(J5=0,ROUND(ROUND(D5*(1+Параметры!$B$9),0)*(1+Параметры!$B$10),-1),IF(ROUND(ROUND(D5*(1+Параметры!$B$9),0)*(1+Параметры!$B$10),-1)<=J5,ROUND(MAX(ROUND(ROUND(D5*(1+Параметры!$B$9),0)*(1+Параметры!$B$10),-1),J5*Параметры!$B$11),-1),ROUND(ROUND(D5*(1+Параметры!$B$9),0)*(1+Параметры!$B$10),-1))) -> 950 | M5: =IF(K5=0,ROUND(ROUND(E5*(1+Параметры!$B$9),0)*(1+Параметры!$B$10),-1),IF(ROUND(ROUND(E5*(1+Параметры!$B$9),0)*(1+Параметры!$B$10),-1)<=K5,ROUND(MAX(ROUND(ROUND(E5*(1+Параметры!$B$9),0)*(1+Параметры!$B$10),-1),K5*Параметры!$B$11),-1),ROUND(ROUND(E5*(1+Параметры!$B$9),0)*(1+Параметры!$B$10),-1))) -> 1140 | N5: =COUNTIF(Расценки!$D$5:$D$2419,A5) -> 111
A6: ZEM | B6: Землекоп / рабочий земляных работ | C6: Ручная разработка и обратная засыпка грунта, планировка | D6: 550 | E6: 660 | F6: =D6*Параметры!$B$3 -> 4400 | G6: =E6*Параметры!$B$3 -> 5280 | H6: =F6*Параметры!$B$4 -> 92400 | I6: =G6*Параметры!$B$4 -> 110880 | J6: 1000 | K6: 1200 | L6: =IF(J6=0,ROUND(ROUND(D6*(1+Параметры!$B$9),0)*(1+Параметры!$B$10),-1),IF(ROUND(ROUND(D6*(1+Параметры!$B$9),0)*(1+Параметры!$B$10),-1)<=J6,ROUND(MAX(ROUND(ROUND(D6*(1+Параметры!$B$9),0)*(1+Параметры!$B$10),-1),J6*Параметры!$B$11),-1),ROUND(ROUND(D6*(1+Параметры!$B$9),0)*(1+Параметры!$B$10),-1))) -> 950 | M6: =IF(K6=0,ROUND(ROUND(E6*(1+Параметры!$B$9),0)*(1+Параметры!$B$10),-1),IF(ROUND(ROUND(E6*(1+Параметры!$B$9),0)*(1+Параметры!$B$10),-1)<=K6,ROUND(MAX(ROUND(ROUND(E6*(1+Параметры!$B$9),0)*(1+Параметры!$B$10),-1),K6*Параметры!$B$11),-1),ROUND(ROUND(E6*(1+Параметры!$B$9),0)*(1+Параметры!$B$10),-1))) -> 1140 | N6: =COUNTIF(Расценки!$D$5:$D$2419,A6) -> 18
A7: BLG | B7: Дорожный рабочий / благоустройство | C7: Бортовой камень, плитка, газоны, ограждения, ручные дорожные работы | D7: 650 | E7: 780 | F7: =D7*Параметры!$B$3 -> 5200 | G7: =E7*Параметры!$B$3 -> 6240 | H7: =F7*Параметры!$B$4 -> 109200 | I7: =G7*Параметры!$B$4 -> 131040 | J7: 1300 | K7: 1500 | L7: =IF(J7=0,ROUND(ROUND(D7*(1+Параметры!$B$9),0)*(1+Параметры!$B$10),-1),IF(ROUND(ROUND(D7*(1+Параметры!$B$9),0)*(1+Параметры!$B$10),-1)<=J7,ROUND(MAX(ROUND(ROUND(D7*(1+Параметры!$B$9),0)*(1+Параметры!$B$10),-1),J7*Параметры!$B$11),-1),ROUND(ROUND(D7*(1+Параметры!$B$9),0)*(1+Параметры!$B$10),-1))) -> 1240 | M7: =IF(K7=0,ROUND(ROUND(E7*(1+Параметры!$B$9),0)*(1+Параметры!$B$10),-1),IF(ROUND(ROUND(E7*(1+Параметры!$B$9),0)*(1+Параметры!$B$10),-1)<=K7,ROUND(MAX(ROUND(ROUND(E7*(1+Параметры!$B$9),0)*(1+Параметры!$B$10),-1),K7*Параметры!$B$11),-1),ROUND(ROUND(E7*(1+Параметры!$B$9),0)*(1+Параметры!$B$10),-1))) -> 1430 | N7: =COUNTIF(Расценки!$D$5:$D$2419,A7) -> 84
A8: BET | B8: Бетонщик / арматурщик | C8: Опалубка, армирование, бетонирование, стяжки, основания | D8: 800 | E8: 950 | F8: =D8*Параметры!$B$3 -> 6400 | G8: =E8*Параметры!$B$3 -> 7600 | H8: =F8*Параметры!$B$4 -> 134400 | I8: =G8*Параметры!$B$4 -> 159600 | J8: 1500 | K8: 1800 | L8: =IF(J8=0,ROUND(ROUND(D8*(1+Параметры!$B$9),0)*(1+Параметры!$B$10),-1),IF(ROUND(ROUND(D8*(1+Параметры!$B$9),0)*(1+Параметры!$B$10),-1)<=J8,ROUND(MAX(ROUND(ROUND(D8*(1+Параметры!$B$9),0)*(1+Параметры!$B$10),-1),J8*Параметры!$B$11),-1),ROUND(ROUND(D8*(1+Параметры!$B$9),0)*(1+Параметры!$B$10),-1))) -> 1430 | M8: =IF(K8=0,ROUND(ROUND(E8*(1+Параметры!$B$9),0)*(1+Параметры!$B$10),-1),IF(ROUND(ROUND(E8*(1+Параметры!$B$9),0)*(1+Параметры!$B$10),-1)<=K8,ROUND(MAX(ROUND(ROUND(E8*(1+Параметры!$B$9),0)*(1+Параметры!$B$10),-1),K8*Параметры!$B$11),-1),ROUND(ROUND(E8*(1+Параметры!$B$9),0)*(1+Параметры!$B$10),-1))) -> 1710 | N8: =COUNTIF(Расценки!$D$5:$D$2419,A8) -> 61
A9: KAM | B9: Каменщик | C9: Кладка кирпича и блоков, перегородки, ремонт кладки | D9: 800 | E9: 950 | F9: =D9*Параметры!$B$3 -> 6400 | G9: =E9*Параметры!$B$3 -> 7600 | H9: =F9*Параметры!$B$4 -> 134400 | I9: =G9*Параметры!$B$4 -> 159600 | J9: 1600 | K9: 1900 | L9: =IF(J9=0,ROUND(ROUND(D9*(1+Параметры!$B$9),0)*(1+Параметры!$B$10),-1),IF(ROUND(ROUND(D9*(1+Параметры!$B$9),0)*(1+Параметры!$B$10),-1)<=J9,ROUND(MAX(ROUND(ROUND(D9*(1+Параметры!$B$9),0)*(1+Параметры!$B$10),-1),J9*Параметры!$B$11),-1),ROUND(ROUND(D9*(1+Параметры!$B$9),0)*(1+Параметры!$B$10),-1))) -> 1520 | M9: =IF(K9=0,ROUND(ROUND(E9*(1+Параметры!$B$9),0)*(1+Параметры!$B$10),-1),IF(ROUND(ROUND(E9*(1+Параметры!$B$9),0)*(1+Параметры!$B$10),-1)<=K9,ROUND(MAX(ROUND(ROUND(E9*(1+Параметры!$B$9),0)*(1+Параметры!$B$10),-1),K9*Параметры!$B$11),-1),ROUND(ROUND(E9*(1+Параметры!$B$9),0)*(1+Параметры!$B$10),-1))) -> 1810 | N9: =COUNTIF(Расценки!$D$5:$D$2419,A9) -> 29
A10: OTD | B10: Отделочник (штукатур, маляр, ГКЛ) | C10: Штукатурка, шпаклёвка, окраска, перегородки и потолки ГКЛ, подвесные потолки | D10: 750 | E10: 900 | F10: =D10*Параметры!$B$3 -> 6000 | G10: =E10*Параметры!$B$3 -> 7200 | H10: =F10*Параметры!$B$4 -> 126000 | I10: =G10*Параметры!$B$4 -> 151200 | J10: 1500 | K10: 1800 | L10: =IF(J10=0,ROUND(ROUND(D10*(1+Параметры!$B$9),0)*(1+Параметры!$B$10),-1),IF(ROUND(ROUND(D10*(1+Параметры!$B$9),0)*(1+Параметры!$B$10),-1)<=J10,ROUND(MAX(ROUND(ROUND(D10*(1+Параметры!$B$9),0)*(1+Параметры!$B$10),-1),J10*Параметры!$B$11),-1),ROUND(ROUND(D10*(1+Параметры!$B$9),0)*(1+Параметры!$B$10),-1))) -> 1430 | M10: =IF(K10=0,ROUND(ROUND(E10*(1+Параметры!$B$9),0)*(1+Параметры!$B$10),-1),IF(ROUND(ROUND(E10*(1+Параметры!$B$9),0)*(1+Параметры!$B$10),-1)<=K10,ROUND(MAX(ROUND(ROUND(E10*(1+Параметры!$B$9),0)*(1+Параметры!$B$10),-1),K10*Параметры!$B$11),-1),ROUND(ROUND(E10*(1+Параметры!$B$9),0)*(1+Параметры!$B$10),-1))) -> 1710 | N10: =COUNTIF(Расценки!$D$5:$D$2419,A10) -> 141
A11: PLI | B11: Плиточник / укладчик полов | C11: Плитка, керамогранит, наливные полы, линолеум, ПВХ, плинтус | D11: 900 | E11: 1080 | F11: =D11*Параметры!$B$3 -> 7200 | G11: =E11*Параметры!$B$3 -> 8640 | H11: =F11*Параметры!$B$4 -> 151200 | I11: =G11*Параметры!$B$4 -> 181440 | J11: 1700 | K11: 2000 | L11: =IF(J11=0,ROUND(ROUND(D11*(1+Параметры!$B$9),0)*(1+Параметры!$B$10),-1),IF(ROUND(ROUND(D11*(1+Параметры!$B$9),0)*(1+Параметры!$B$10),-1)<=J11,ROUND(MAX(ROUND(ROUND(D11*(1+Параметры!$B$9),0)*(1+Параметры!$B$10),-1),J11*Параметры!$B$11),-1),ROUND(ROUND(D11*(1+Параметры!$B$9),0)*(1+Параметры!$B$10),-1))) -> 1620 | M11: =IF(K11=0,ROUND(ROUND(E11*(1+Параметры!$B$9),0)*(1+Параметры!$B$10),-1),IF(ROUND(ROUND(E11*(1+Параметры!$B$9),0)*(1+Параметры!$B$10),-1)<=K11,ROUND(MAX(ROUND(ROUND(E11*(1+Параметры!$B$9),0)*(1+Параметры!$B$10),-1),K11*Параметры!$B$11),-1),ROUND(ROUND(E11*(1+Параметры!$B$9),0)*(1+Параметры!$B$10),-1))) -> 1900 | N11: =COUNTIF(Расценки!$D$5:$D$2419,A11) -> 62
A12: KRO | B12: Кровельщик | C12: Наплавляемые и мембранные кровли, металлокровля, водосток, примыкания | D12: 800 | E12: 950 | F12: =D12*Параметры!$B$3 -> 6400 | G12: =E12*Параметры!$B$3 -> 7600 | H12: =F12*Параметры!$B$4 -> 134400 | I12: =G12*Параметры!$B$4 -> 159600 | J12: 1600 | K12: 1900 | L12: =IF(J12=0,ROUND(ROUND(D12*(1+Параметры!$B$9),0)*(1+Параметры!$B$10),-1),IF(ROUND(ROUND(D12*(1+Параметры!$B$9),0)*(1+Параметры!$B$10),-1)<=J12,ROUND(MAX(ROUND(ROUND(D12*(1+Параметры!$B$9),0)*(1+Параметры!$B$10),-1),J12*Параметры!$B$11),-1),ROUND(ROUND(D12*(1+Параметры!$B$9),0)*(1+Параметры!$B$10),-1))) -> 1520 | M12: =IF(K12=0,ROUND(ROUND(E12*(1+Параметры!$B$9),0)*(1+Параметры!$B$10),-1),IF(ROUND(ROUND(E12*(1+Параметры!$B$9),0)*(1+Параметры!$B$10),-1)<=K12,ROUND(MAX(ROUND(ROUND(E12*(1+Параметры!$B$9),0)*(1+Параметры!$B$10),-1),K12*Параметры!$B$11),-1),ROUND(ROUND(E12*(1+Параметры!$B$9),0)*(1+Параметры!$B$10),-1))) -> 1810 | N12: =COUNTIF(Расценки!$D$5:$D$2419,A12) -> 66
A13: FAS | B13: Фасадчик / промальпинист | C13: Вентфасады, сэндвич-панели, работы на высоте с люльки и верёвки | D13: 1100 | E13: 1300 | F13: =D13*Параметры!$B$3 -> 8800 | G13: =E13*Параметры!$B$3 -> 10400 | H13: =F13*Параметры!$B$4 -> 184800 | I13: =G13*Параметры!$B$4 -> 218400 | J13: 2400 | K13: 2800 | L13: =IF(J13=0,ROUND(ROUND(D13*(1+Параметры!$B$9),0)*(1+Параметры!$B$10),-1),IF(ROUND(ROUND(D13*(1+Параметры!$B$9),0)*(1+Параметры!$B$10),-1)<=J13,ROUND(MAX(ROUND(ROUND(D13*(1+Параметры!$B$9),0)*(1+Параметры!$B$10),-1),J13*Параметры!$B$11),-1),ROUND(ROUND(D13*(1+Параметры!$B$9),0)*(1+Параметры!$B$10),-1))) -> 2280 | M13: =IF(K13=0,ROUND(ROUND(E13*(1+Параметры!$B$9),0)*(1+Параметры!$B$10),-1),IF(ROUND(ROUND(E13*(1+Параметры!$B$9),0)*(1+Параметры!$B$10),-1)<=K13,ROUND(MAX(ROUND(ROUND(E13*(1+Параметры!$B$9),0)*(1+Параметры!$B$10),-1),K13*Параметры!$B$11),-1),ROUND(ROUND(E13*(1+Параметры!$B$9),0)*(1+Параметры!$B$10),-1))) -> 2660 | N13: =COUNTIF(Расценки!$D$5:$D$2419,A13) -> 32
A14: SVA | B14: Сварщик / монтажник МК | C14: Сварка, монтаж и ремонт металлоконструкций, ограждений, ворот | D14: 900 | E14: 1080 | F14: =D14*Параметры!$B$3 -> 7200 | G14: =E14*Параметры!$B$3 -> 8640 | H14: =F14*Параметры!$B$4 -> 151200 | I14: =G14*Параметры!$B$4 -> 181440 | J14: 2000 | K14: 2400 | L14: =IF(J14=0,ROUND(ROUND(D14*(1+Параметры!$B$9),0)*(1+Параметры!$B$10),-1),IF(ROUND(ROUND(D14*(1+Параметры!$B$9),0)*(1+Параметры!$B$10),-1)<=J14,ROUND(MAX(ROUND(ROUND(D14*(1+Параметры!$B$9),0)*(1+Параметры!$B$10),-1),J14*Параметры!$B$11),-1),ROUND(ROUND(D14*(1+Параметры!$B$9),0)*(1+Параметры!$B$10),-1))) -> 1900 | M14: =IF(K14=0,ROUND(ROUND(E14*(1+Параметры!$B$9),0)*(1+Параметры!$B$10),-1),IF(ROUND(ROUND(E14*(1+Параметры!$B$9),0)*(1+Параметры!$B$10),-1)<=K14,ROUND(MAX(ROUND(ROUND(E14*(1+Параметры!$B$9),0)*(1+Параметры!$B$10),-1),K14*Параметры!$B$11),-1),ROUND(ROUND(E14*(1+Параметры!$B$9),0)*(1+Параметры!$B$10),-1))) -> 2280 | N14: =COUNTIF(Расценки!$D$5:$D$2419,A14) -> 132
A15: SAN | B15: Сантехник | C15: Водопровод, канализация, отопление, сантехприборы, насосы | D15: 850 | E15: 1020 | F15: =D15*Параметры!$B$3 -> 6800 | G15: =E15*Параметры!$B$3 -> 8160 | H15: =F15*Параметры!$B$4 -> 142800 | I15: =G15*Параметры!$B$4 -> 171360 | J15: 1900 | K15: 2200 | L15: =IF(J15=0,ROUND(ROUND(D15*(1+Параметры!$B$9),0)*(1+Параметры!$B$10),-1),IF(ROUND(ROUND(D15*(1+Параметры!$B$9),0)*(1+Параметры!$B$10),-1)<=J15,ROUND(MAX(ROUND(ROUND(D15*(1+Параметры!$B$9),0)*(1+Параметры!$B$10),-1),J15*Параметры!$B$11),-1),ROUND(ROUND(D15*(1+Параметры!$B$9),0)*(1+Параметры!$B$10),-1))) -> 1810 | M15: =IF(K15=0,ROUND(ROUND(E15*(1+Параметры!$B$9),0)*(1+Параметры!$B$10),-1),IF(ROUND(ROUND(E15*(1+Параметры!$B$9),0)*(1+Параметры!$B$10),-1)<=K15,ROUND(MAX(ROUND(ROUND(E15*(1+Параметры!$B$9),0)*(1+Параметры!$B$10),-1),K15*Параметры!$B$11),-1),ROUND(ROUND(E15*(1+Параметры!$B$9),0)*(1+Параметры!$B$10),-1))) -> 2090 | N15: =COUNTIF(Расценки!$D$5:$D$2419,A15) -> 342
A16: VEN | B16: Монтажник вентиляции | C16: Воздуховоды, вентиляторы, решётки, клапаны, ТО вентустановок | D16: 850 | E16: 1020 | F16: =D16*Параметры!$B$3 -> 6800 | G16: =E16*Параметры!$B$3 -> 8160 | H16: =F16*Параметры!$B$4 -> 142800 | I16: =G16*Параметры!$B$4 -> 171360 | J16: 2200 | K16: 2600 | L16: =IF(J16=0,ROUND(ROUND(D16*(1+Параметры!$B$9),0)*(1+Параметры!$B$10),-1),IF(ROUND(ROUND(D16*(1+Параметры!$B$9),0)*(1+Параметры!$B$10),-1)<=J16,ROUND(MAX(ROUND(ROUND(D16*(1+Параметры!$B$9),0)*(1+Параметры!$B$10),-1),J16*Параметры!$B$11),-1),ROUND(ROUND(D16*(1+Параметры!$B$9),0)*(1+Параметры!$B$10),-1))) -> 2090 | M16: =IF(K16=0,ROUND(ROUND(E16*(1+Параметры!$B$9),0)*(1+Параметры!$B$10),-1),IF(ROUND(ROUND(E16*(1+Параметры!$B$9),0)*(1+Параметры!$B$10),-1)<=K16,ROUND(MAX(ROUND(ROUND(E16*(1+Параметры!$B$9),0)*(1+Параметры!$B$10),-1),K16*Параметры!$B$11),-1),ROUND(ROUND(E16*(1+Параметры!$B$9),0)*(1+Параметры!$B$10),-1))) -> 2470 | N16: =COUNTIF(Расценки!$D$5:$D$2419,A16) -> 124
... A24: DER | B24: Дезинфектор (ОЗДС) | C24: Дератизация, дезинсекция, обслуживание ОЗДС — лицензируемая | D24: 850 | E24: 1020 | F24: =D24*Параметры!$B$3 -> 6800 | G24: =E24*Параметры!$B$3 -> 8160 | H24: =F24*Параметры!$B$4 -> 142800 | I24: =G24*Параметры!$B$4 -> 171360 | J24: 1800 | K24: 2100 | L24: =IF(J24=0,ROUND(ROUND(D24*(1+Параметры!$B$9),0)*(1+Параметры!$B$10),-1),IF(ROUND(ROUND(D24*(1+Параметры!$B$9),0)*(1+Параметры!$B$10),-1)<=J24,ROUND(MAX(ROUND(ROUND(D24*(1+Параметры!$B$9),0)*(1+Параметры!$B$10),-1),J24*Параметры!$B$11),-1),ROUND(ROUND(D24*(1+Параметры!$B$9),0)*(1+Параметры!$B$10),-1))) -> 1710 | M24: =IF(K24=0,ROUND(ROUND(E24*(1+Параметры!$B$9),0)*(1+Параметры!$B$10),-1),IF(ROUND(ROUND(E24*(1+Параметры!$B$9),0)*(1+Параметры!$B$10),-1)<=K24,ROUND(MAX(ROUND(ROUND(E24*(1+Параметры!$B$9),0)*(1+Параметры!$B$10),-1),K24*Параметры!$B$11),-1),ROUND(ROUND(E24*(1+Параметры!$B$9),0)*(1+Параметры!$B$10),-1))) -> 2000 | N24: =COUNTIF(Расценки!$D$5:$D$2419,A24) -> 6
A26: Как ставить план строителю:
A27: 1. Найдите работу на листе «Расценки» → колонка «План на смену» — это объём для ОДНОГО человека за смену. Для звена умножьте на число людей.
A28: 2. Если за смену несколько видов работ: время на каждую = объём × норма (колонка L). Сумма по всем работам должна быть не меньше 8 ч на человека.
A29: 3. Пример: монтажник должен уложить 40 м кабеля при норме 0,05 чел.-ч/м = 2 ч и поставить 12 розеток при норме 0,25 = 3 ч → загрузка 5 ч, добавьте работ ещё на 3 ч.
A30: 4. В конце смены прораб фиксирует сделанный объём. Выполнение < 85 % плана два дня подряд — разговор; не выправляется — сделка или замена исполнителя.

Sheet Для HR
A1: ДЛЯ HR: КОГО ИЩЕМ И ЧТО ОБЕЩАЕМ
A2: Вилка ставки — для вакансии и собеседования (ИП/самозанятый, налог платит исполнитель). Нижняя граница — для новичка без своего инструмента, верхняя — опыт от 3 лет, свой инструмент, допуски. Ставки берутся с листа «Почасовка — ставки и план», доход — смена × смен в месяц (лист «Параметры»).
A4: Код | B4: Специальность | C4: Что должен уметь / допуски | D4: Ставка в вакансии СПб: от, руб/ч = ставка × 0,85 | E4: до, руб/ч = ставка | F4: Доход в месяц СПб: от, руб = от × часы × смены | G4: до, руб | H4: Ставка в вакансии Мск: от, руб/ч = ставка × 0,85 | I4: до, руб/ч = ставка | J4: Доход в месяц Мск: от, руб | K4: до, руб | L4: Найм в штат СПб, на руки, руб/ч (ориентир рынка вакансий)
A5: RAZ | B5: ='Почасовка — ставки и план'!B5 -> Разнорабочий / демонтажник | C5: Физически вынослив, без вредных привычек; опыт демонтажа — плюс | D5: =ROUND('Почасовка — ставки и план'!D5*Параметры!$B$8,-1) -> 470 | E5: ='Почасовка — ставки и план'!D5 -> 550 | F5: =D5*Параметры!$B$3*Параметры!$B$4 -> 78960 | G5: =E5*Параметры!$B$3*Параметры!$B$4 -> 92400 | H5: =ROUND('Почасовка — ставки и план'!E5*Параметры!$B$8,-1) -> 560 | I5: ='Почасовка — ставки и план'!E5 -> 660 | J5: =H5*Параметры!$B$3*Параметры!$B$4 -> 94080 | K5: =I5*Параметры!$B$3*Параметры!$B$4 -> 110880 | L5: 450–560
A6: ZEM | B6: ='Почасовка — ставки и план'!B6 -> Землекоп / рабочий земляных работ | C6: Опыт земляных работ, работа на улице в любую погоду | D6: =ROUND('Почасовка — ставки и план'!D6*Параметры!$B$8,-1) -> 470 | E6: ='Почасовка — ставки и план'!D6 -> 550 | F6: =D6*Параметры!$B$3*Параметры!$B$4 -> 78960 | G6: =E6*Параметры!$B$3*Параметры!$B$4 -> 92400 | H6: =ROUND('Почасовка — ставки и план'!E6*Параметры!$B$8,-1) -> 560 | I6: ='Почасовка — ставки и план'!E6 -> 660 | J6: =H6*Параметры!$B$3*Параметры!$B$4 -> 94080 | K6: =I6*Параметры!$B$3*Параметры!$B$4 -> 110880 | L6: 450–560
A7: BLG | B7: ='Почасовка — ставки и план'!B7 -> Дорожный рабочий / благоустройство | C7: Опыт укладки бортового камня и плитки | D7: =ROUND('Почасовка — ставки и план'!D7*Параметры!$B$8,-1) -> 550 | E7: ='Почасовка — ставки и план'!D7 -> 650 | F7: =D7*Параметры!$B$3*Параметры!$B$4 -> 92400 | G7: =E7*Параметры!$B$3*Параметры!$B$4 -> 109200 | H7: =ROUND('Почасовка — ставки и план'!E7*Параметры!$B$8,-1) -> 660 | I7: ='Почасовка — ставки и план'!E7 -> 780 | J7: =H7*Параметры!$B$3*Параметры!$B$4 -> 110880 | K7: =I7*Параметры!$B$3*Параметры!$B$4 -> 131040 | L7: 500–650
A8: BET | B8: ='Почасовка — ставки и план'!B8 -> Бетонщик / арматурщик | C8: Опыт опалубки, вязки арматуры, бетонирования; читать простые чертежи | D8: =ROUND('Почасовка — ставки и план'!D8*Параметры!$B$8,-1) -> 680 | E8: ='Почасовка — ставки и план'!D8 -> 800 | F8: =D8*Параметры!$B$3*Параметры!$B$4 -> 114240 | G8: =E8*Параметры!$B$3*Параметры!$B$4 -> 134400 | H8: =ROUND('Почасовка — ставки и план'!E8*Параметры!$B$8,-1) -> 810 | I8: ='Почасовка — ставки и план'!E8 -> 950 | J8: =H8*Параметры!$B$3*Параметры!$B$4 -> 136080 | K8: =I8*Параметры!$B$3*Параметры!$B$4 -> 159600 | L8: 550–700
A9: KAM | B9: ='Почасовка — ставки и план'!B9 -> Каменщик | C9: Опыт кладки кирпича и блоков от 2 лет | D9: =ROUND('Почасовка — ставки и план'!D9*Параметры!$B$8,-1) -> 680 | E9: ='Почасовка — ставки и план'!D9 -> 800 | F9: =D9*Параметры!$B$3*Параметры!$B$4 -> 114240 | G9: =E9*Параметры!$B$3*Параметры!$B$4 -> 134400 | H9: =ROUND('Почасовка — ставки и план'!E9*Параметры!$B$8,-1) -> 810 | I9: ='Почасовка — ставки и план'!E9 -> 950 | J9: =H9*Параметры!$B$3*Параметры!$B$4 -> 136080 | K9: =I9*Параметры!$B$3*Параметры!$B$4 -> 159600 | L9: 600–750
A10: OTD | B10: ='Почасовка — ставки и план'!B10 -> Отделочник (штукатур, маляр, ГКЛ) | C10: Штукатурка/шпаклёвка/окраска/ГКЛ, свой ручной инструмент | D10: =ROUND('Почасовка — ставки и план'!D10*Параметры!$B$8,-1) -> 640 | E10: ='Почасовка — ставки и план'!D10 -> 750 | F10: =D10*Параметры!$B$3*Параметры!$B$4 -> 107520 | G10: =E10*Параметры!$B$3*Параметры!$B$4 -> 126000 | H10: =ROUND('Почасовка — ставки и план'!E10*Параметры!$B$8,-1) -> 770 | I10: ='Почасовка — ставки и план'!E10 -> 900 | J10: =H10*Параметры!$B$3*Параметры!$B$4 -> 129360 | K10: =I10*Параметры!$B$3*Параметры!$B$4 -> 151200 | L10: 550–800
A11: PLI | B11: ='Почасовка — ставки и план'!B11 -> Плиточник / укладчик полов | C11: Плитка и керамогранит, наливные полы; портфолио работ | D11: =ROUND('Почасовка — ставки и план'!D11*Параметры!$B$8,-1) -> 770 | E11: ='Почасовка — ставки и план'!D11 -> 900 | F11: =D11*Параметры!$B$3*Параметры!$B$4 -> 129360 | G11: =E11*Параметры!$B$3*Параметры!$B$4 -> 151200 | H11: =ROUND('Почасовка — ставки и план'!E11*Параметры!$B$8,-1) -> 920 | I11: ='Почасовка — ставки и план'!E11 -> 1080 | J11: =H11*Параметры!$B$3*Параметры!$B$4 -> 154560 | K11: =I11*Параметры!$B$3*Параметры!$B$4 -> 181440 | L11: 650–900
A12: KRO | B12: ='Почасовка — ставки и план'!B12 -> Кровельщик | C12: Наплавляемые и мембранные кровли; допуск к работам на высоте | D12: =ROUND('Почасовка — ставки и план'!D12*Параметры!$B$8,-1) -> 680 | E12: ='Почасовка — ставки и план'!D12 -> 800 | F12: =D12*Параметры!$B$3*Параметры!$B$4 -> 114240 | G12: =E12*Параметры!$B$3*Параметры!$B$4 -> 134400 | H12: =ROUND('Почасовка — ставки и план'!E12*Параметры!$B$8,-1) -> 810 | I12: ='Почасовка — ставки и план'!E12 -> 950 | J12: =H12*Параметры!$B$3*Параметры!$B$4 -> 136080 | K12: =I12*Параметры!$B$3*Параметры!$B$4 -> 159600 | L12: 600–800
A13: FAS | B13: ='Почасовка — ставки и план'!B13 -> Фасадчик / промальпинист | C13: Допуск к работам на высоте (группа 2–3), опыт вентфасадов; для промальпа — удостоверение | D13: =ROUND('Почасовка — ставки и план'!D13*Параметры!$B$8,-1) -> 940 | E13: ='Почасовка — ставки и план'!D13 -> 1100 | F13: =D13*Параметры!$B$3*Параметры!$B$4 -> 157920 | G13: =E13*Параметры!$B$3*Параметры!$B$4 -> 184800 | H13: =ROUND('Почасовка — ставки и план'!E13*Параметры!$B$8,-1) -> 1110 | I13: ='Почасовка — ставки и план'!E13 -> 1300 | J13: =H13*Параметры!$B$3*Параметры!$B$4 -> 186480 | K13: =I13*Параметры!$B$3*Параметры!$B$4 -> 218400 | L13: 800–1 000
A14: SVA | B14: ='Почасовка — ставки и план'!B14 -> Сварщик / монтажник МК | C14: Удостоверение сварщика (НАКС — плюс), монтаж МК, допуск на высоту | D14: =ROUND('Почасовка — ставки и план'!D14*Параметры!$B$8,-1) -> 770 | E14: ='Почасовка — ставки и план'!D14 -> 900 | F14: =D14*Параметры!$B$3*Параметры!$B$4 -> 129360 | G14: =E14*Параметры!$B$3*Параметры!$B$4 -> 151200 | H14: =ROUND('Почасовка — ставки и план'!E14*Параметры!$B$8,-1) -> 920 | I14: ='Почасовка — ставки и план'!E14 -> 1080 | J14: =H14*Параметры!$B$3*Параметры!$B$4 -> 154560 | K14: =I14*Параметры!$B$3*Параметры!$B$4 -> 181440 | L14: 600–850
A15: SAN | B15: ='Почасовка — ставки и план'!B15 -> Сантехник | C15: Монтаж ВиК и отопления (ПП, металл, чугун), опыт на коммерческих объектах | D15: =ROUND('Почасовка — ставки и план'!D15*Параметры!$B$8,-1) -> 720 | E15: ='Почасовка — ставки и план'!D15 -> 850 | F15: =D15*Параметры!$B$3*Параметры!$B$4 -> 120960 | G15: =E15*Параметры!$B$3*Параметры!$B$4 -> 142800 | H15: =ROUND('Почасовка — ставки и план'!E15*Параметры!$B$8,-1) -> 870 | I15: ='Почасовка — ставки и план'!E15 -> 1020 | J15: =H15*Параметры!$B$3*Параметры!$B$4 -> 146160 | K15: =I15*Параметры!$B$3*Параметры!$B$4 -> 171360 | L15: 600–800
A16: VEN | B16: ='Почасовка — ставки и план'!B16 -> Монтажник вентиляции | C16: Монтаж воздуховодов и вентоборудования, допуск на высоту | D16: =ROUND('Почасовка — ставки и план'!D16*Параметры!$B$8,-1) -> 720 | E16: ='Почасовка — ставки и план'!D16 -> 850 | F16: =D16*Параметры!$B$3*Параметры!$B$4 -> 120960 | G16: =E16*Параметры!$B$3*Параметры!$B$4 -> 142800 | H16: =ROUND('Почасовка — ставки и план'!E16*Параметры!$B$8,-1) -> 870 | I16: ='Почасовка — ставки и план'!E16 -> 1020 | J16: =H16*Параметры!$B$3*Параметры!$B$4 -> 146160 | K16: =I16*Параметры!$B$3*Параметры!$B$4 -> 171360 | L16: 650–900
... A24: DER | B24: ='Почасовка — ставки и план'!B24 -> Дезинфектор (ОЗДС) | C24: Обучение по дезинфекции/дератизации, работа по СанПиН | D24: =ROUND('Почасовка — ставки и план'!D24*Параметры!$B$8,-1) -> 720 | E24: ='Почасовка — ставки и план'!D24 -> 850 | F24: =D24*Параметры!$B$3*Параметры!$B$4 -> 120960 | G24: =E24*Параметры!$B$3*Параметры!$B$4 -> 142800 | H24: =ROUND('Почасовка — ставки и план'!E24*Параметры!$B$8,-1) -> 870 | I24: ='Почасовка — ставки и план'!E24 -> 1020 | J24: =H24*Параметры!$B$3*Параметры!$B$4 -> 146160 | K24: =I24*Параметры!$B$3*Параметры!$B$4 -> 171360 | L24: 550–700
A26: Что обещать на собеседовании:
A27: • Оплата за отработанные часы по ставке (почасовка) или за принятый объём по расценке (сделка) — по выбору прораба для конкретного объекта.
A28: • Объекты — коммерческая недвижимость СПб и Москвы: гипермаркеты, склады и РЦ, ТЦ, офисы; часто работа на действующем объекте, возможны ночные смены.
A29: • При почасовке — понятный план на смену; кто стабильно выполняет план, получает верх вилки и приоритет на сделку (там заработок выше).
A30: • Работа как ИП или самозанятый, налог 6 % исполнитель платит сам (он уже учтён в ставке).
A31: • Сроки выплат и документы — по условиям на листе «Как пользоваться» (раздел «Порядок выплат»).
A32: Чего НЕ обещать: ставку выше верхней границы вилки, оплату простоев по вине исполнителя, оплату работ без акта приёмки.

Sheet Параметры
A1: ПАРАМЕТРЫ РАСЧЁТА (жёлтые ячейки можно менять — формулы во всём файле пересчитаются)
A2: Параметр | B2: Значение | C2: Как используется
A3: Оплачиваемых часов в смене | B3: 8 | C3: План на смену = часы ÷ норма; оплата смены = ставка × часы
A4: Рабочих смен в месяц | B4: 21 | C4: Доход в месяц = оплата смены × смены
A5: Потолок сделки: надбавка к цели | B5: 0.15 | C5: Потолок = цель × (1 + надбавка)…
A6: Потолок сделки: не выше доли цены КП | B6: 0.75 | C6: …но не больше цены КП × эта доля (оставляем ≥ 25 % на накладные и прибыль)
A7: Порог «любой способ», ± | B7: 0.1 | C7: Почасовая оплата за ед. дешевле цели сделки больше чем на порог → «почасовка», дороже → «сделка»
A8: Нижняя граница вилки HR, доля ставки | B8: 0.85 | C8: Вилка в вакансии: от ставка × доля до ставка
A9: Накладные НЕОСТРОЙ к ставке бригады | B9: 0.25 | C9: ИТР/прораб, транспорт, СИЗ, инструмент, гарантия
A10: Наценка НЕОСТРОЙ | B10: 0.35 | C10: Нормо-час заказчику = ставка × (1 + накладные) × (1 + наценка)
A11: Нормо-час заказчику не ниже доли рынка | B11: 0.95 | C11: Если формула ниже рынка — ставим рынок × доля
A12: Порог выполнения плана для разбора | B12: 0.85 | C12: Справочно: ниже два дня подряд — разговор с исполнителем
