Workbook

Sheet Реестр
A1: РЕЕСТР ТЕНДЕРОВ НЕОСТРОЙ
A2: Синие колонки — расчёт (заполнено по расчётам с июля 2026). Жёлтые колонки — РЕЗУЛЬТАТ, заполняет отдел тендеров после подведения итогов. Наценка и маржа считаются формулами из с/с и КП. Цифры — руб. без НДС за период из колонки «Период». Аналитика — на листе «Аналитика».
A3: РАСЧЁТ | U3: ИТОГИ ТЕНДЕРА (заполнять)
A4: № | B4: Дата расчёта | C4: Заказчик | D4: Объект | E4: Предмет | F4: Регион | G4: Вид работ | H4: Тип тендера | I4: Период цены | J4: НМЦК б/НДС | K4: С/с б/НДС | L4: КП б/НДС | M4: КП с НДС | N4: Наценка = КП ÷ с/с − 1 | O4: Маржа = 1 − с/с ÷ КП | P4: КП к НМЦК | Q4: Наценка мат. | R4: Наценка раб. | S4: Решение по расчёту | T4: Переторжки (история) | U4: Подано, дата | V4: Наша финальная цена б/НДС | W4: РЕЗУЛЬТАТ | X4: Место | Y4: Цена победителя б/НДС | Z4: Наша цена к победителю = наша ÷ победитель − 1 | AA4: Участников | AB4: Причина / комментарий по итогам | AC4: Папка | AD4: Источник расчёта (память) | AE4: Примечания
A5: 1 | B5: 46212 | C5: ООО «Пулково Аэропорт Отель СПб» | D5: СПб, Пулковское ш. 41 лит. ЗД, 109 ед. оборудования | E5: ТО кухонного и холодильного оборудования точек питания | F5: СПб | G5: КТО / ТО | H5: ТО и абонентское обслуживание | I5: в месяц | K5: 241132 | L5: 361698 | M5: 441263 | N5: =IF(AND(ISNUMBER(K5),ISNUMBER(L5),K5>0),L5/K5-1,0.5) -> 0.5 | O5: =IF(AND(ISNUMBER(K5),ISNUMBER(L5),L5>0),1-K5/L5,0.3333) -> 0.33333333 | P5: =IF(AND(ISNUMBER(J5),ISNUMBER(L5),J5>0),L5/J5-1,"") | S5: рассчитано | Z5: =IF(AND(ISNUMBER(V5),ISNUMBER(Y5),Y5>0),V5/Y5-1,"") | AD5: project_pulkovo_hotel.md | AE5: Форма с НДС 5 %, по решению пользователя НДС 22 %. Кол-во ед. 109 vs 103 в ТЗ.
A6: 2 | B6: 46213 | C6: ООО «Лента» | D6: ТК-6 | E6: Ремонт асфальтовой парковки ТК-6 | F6: СПб | G6: СМР / ремонт | H6: Крупные сети и девелоперы — конкурентный тендер | I6: разово | K6: 2710000 | L6: 4073770.5 | M6: 4970000 | N6: =IF(AND(ISNUMBER(K6),ISNUMBER(L6),K6>0),L6/K6-1,0.5) -> 0.50323634 | O6: =IF(AND(ISNUMBER(K6),ISNUMBER(L6),L6>0),1-K6/L6,0.3348) -> 0.33476861 | P6: =IF(AND(ISNUMBER(J6),ISNUMBER(L6),J6>0),L6/J6-1,"") | S6: рассчитано | Z6: =IF(AND(ISNUMBER(V6),ISNUMBER(Y6),Y6>0),V6/Y6-1,"") | AD6: project_lenta_parkovki.md | AE6: Портфель 3 ТК: с/с 10,08 млн, КП 18,46 млн с НДС. ТЗ ТК-6 путаница (объём 85 vs 985 м²).
A7: 3 | B7: 46213 | C7: ООО «Лента» | D7: ТК-48, Кудрово | E7: Ремонт асфальтовой парковки ТК-48 | F7: ЛО | G7: СМР / ремонт | H7: Крупные сети и девелоперы — конкурентный тендер | I7: разово | K7: 3870000 | L7: 5811475.4 | M7: 7090000 | N7: =IF(AND(ISNUMBER(K7),ISNUMBER(L7),K7>0),L7/K7-1,0.5) -> 0.50167323 | O7: =IF(AND(ISNUMBER(K7),ISNUMBER(L7),L7>0),1-K7/L7,0.3341) -> 0.33407616 | P7: =IF(AND(ISNUMBER(J7),ISNUMBER(L7),J7>0),L7/J7-1,"") | S7: рассчитано | Z7: =IF(AND(ISNUMBER(V7),ISNUMBER(Y7),Y7>0),V7/Y7-1,"") | AD7: project_lenta_parkovki.md | AE7: Портфель 3 ТК: с/с 10,08 млн, КП 18,46 млн с НДС.
A8: 4 | B8: 46213 | C8: ООО «Лента» | D8: ТК-270, Сосновый Бор | E8: Ремонт асфальтовой парковки ТК-270 | F8: ЛО | G8: СМР / ремонт | H8: Крупные сети и девелоперы — конкурентный тендер | I8: разово | K8: 3500000 | L8: 5245901.6 | M8: 6400000 | N8: =IF(AND(ISNUMBER(K8),ISNUMBER(L8),K8>0),L8/K8-1,0.5) -> 0.49882904 | O8: =IF(AND(ISNUMBER(K8),ISNUMBER(L8),L8>0),1-K8/L8,0.3328) -> 0.3328125 | P8: =IF(AND(ISNUMBER(J8),ISNUMBER(L8),J8>0),L8/J8-1,"") | S8: рассчитано | Z8: =IF(AND(ISNUMBER(V8),ISNUMBER(Y8),Y8>0),V8/Y8-1,"") | AD8: project_lenta_parkovki.md | AE8: Портфель 3 ТК: с/с 10,08 млн, КП 18,46 млн с НДС.
A9: 5 | B9: 46216 | C9: ООО «Лента» | D9: Столовая Центрального офиса Ленты | E9: ТОиР кухонного/пекарного оборудования столовой ЦО, 63 ед., 2026 г. | F9: СПб | G9: КТО / ТО | H9: ТО и абонентское обслуживание | I9: в месяц | K9: 63242 | L9: 94795.08 | M9: 115650 | N9: =IF(AND(ISNUMBER(K9),ISNUMBER(L9),K9>0),L9/K9-1,0.5) -> 0.49892603 | O9: =IF(AND(ISNUMBER(K9),ISNUMBER(L9),L9>0),1-K9/L9,0.3329) -> 0.33285567 | P9: =IF(AND(ISNUMBER(J9),ISNUMBER(L9),J9>0),L9/J9-1,"") | S9: рассчитано | Z9: =IF(AND(ISNUMBER(V9),ISNUMBER(Y9),Y9>0),V9/Y9-1,"") | AD9: project_lenta_stolovaya_co.md | AE9: КП 115 650/мес с НДС (б/НДС = /1,22); нерегламент 3 100 руб/ч с НДС; запчасти отдельно; SL ≥ 96 %
A10: 6 | B10: 46220 | C10: ОАО «КАРАВАЙ» | D10: ПП2 СПб, Политехническая 11 + ПП3 СПб, пр. Стачек 39 | E10: Ремонт асфальтобетонного покрытия двух площадок | F10: СПб | G10: СМР / ремонт | H10: Крупные сети и девелоперы — конкурентный тендер | I10: разово | K10: 3909760 | L10: 7504410 | M10: 9155380.2 | N10: =IF(AND(ISNUMBER(K10),ISNUMBER(L10),K10>0),L10/K10-1,0.9194) -> 0.91940426 | O10: =IF(AND(ISNUMBER(K10),ISNUMBER(L10),L10>0),1-K10/L10,0.479) -> 0.47900501 | P10: =IF(AND(ISNUMBER(J10),ISNUMBER(L10),J10>0),L10/J10-1,"") | S10: рассчитано | Z10: =IF(AND(ISNUMBER(V10),ISNUMBER(Y10),Y10>0),V10/Y10-1,"") | AD10: project_karavay_asfalt.md | AE10: B2B №4518138; ПП2 с/с 2 999 790 / КП 5 758 080, ПП3 909 970 / 1 746 330; первоначально КП 6 253 745 (+60 %), поднято +20 % до подачи
A11: 7 | B11: 46223 | C11: ООО «ФЕНИКС-ОТЕЛЬ» | D11: Cosmos SPb Nevsky, Гончарная 4А, конференц-зал 115,6 м² | E11: Реновация конференц-зала с оснащением (мебель, АВ) | F11: СПб | G11: Fit-out | H11: Fit-out, частный бизнес, малые объёмы | I11: разово | K11: 6966150 | L11: 10125740 | N11: =IF(AND(ISNUMBER(K11),ISNUMBER(L11),K11>0),L11/K11-1,0.4536) -> 0.4535633 | O11: =IF(AND(ISNUMBER(K11),ISNUMBER(L11),L11>0),1-K11/L11,0.312) -> 0.31203547 | P11: =IF(AND(ISNUMBER(J11),ISNUMBER(L11),J11>0),L11/J11-1,"") | Q11: 0.2 | R11: 1 | S11: рассчитано | Z11: =IF(AND(ISNUMBER(V11),ISNUMBER(Y11),Y11>0),V11/Y11-1,"") | AC11: Космос. Невский | AD11: project_cosmos_nevsky.md | AE11: Расхождения формы КП и РД: панели 36 vs 107 м² (~330К), ковролин, рейка. Срок до 01.09.2026.
A12: 8 | B12: 46225 | C12: ООО «ГИПЕРГЛОБУС» (Глобус) | D12: ГМ «Глобус» Тверь, Октябрьский пр-т 101 | E12: Полное ТО ГМ: электро, ОВиК, мех., холод, дежурство 24/7, Купава | F12: Тверь | G12: КТО / ТО | H12: ТО и абонентское обслуживание | I12: в год | K12: 22965000 | L12: 27999000 | N12: =IF(AND(ISNUMBER(K12),ISNUMBER(L12),K12>0),L12/K12-1,0.2192) -> 0.21920314 | O12: =IF(AND(ISNUMBER(K12),ISNUMBER(L12),L12>0),1-K12/L12,0.1798) -> 0.17979214 | P12: =IF(AND(ISNUMBER(J12),ISNUMBER(L12),J12>0),L12/J12-1,"") | S12: рассчитано | Z12: =IF(AND(ISNUMBER(V12),ISNUMBER(Y12),Y12>0),V12/Y12-1,"") | AC12: Сметы (корень, подпапки Встройка, ЦХМ) | AD12: project_globus_to.md | AE12: Финал v2 по ценам Митино; первый вариант 33,54 млн. Р1–Р3 по уровню Митино, Р4–Р6 с/с×1,3. Ремонты до 200 тыс/мес в цене, фиксация цены 1–3 года
A13: 9 | B13: 46225 | C13: ООО «ГИПЕРГЛОБУС» (Глобус) | D13: ГМ «Глобус» Тула 2, ул. Октябрьская 215 | E13: Полное ТО ГМ: электро, ОВиК, механические системы | F13: Тула | G13: КТО / ТО | H13: ТО и абонентское обслуживание | I13: в год | K13: 11765000 | L13: 13673000 | N13: =IF(AND(ISNUMBER(K13),ISNUMBER(L13),K13>0),L13/K13-1,0.1622) -> 0.16217595 | O13: =IF(AND(ISNUMBER(K13),ISNUMBER(L13),L13>0),1-K13/L13,0.1395) -> 0.13954509 | P13: =IF(AND(ISNUMBER(J13),ISNUMBER(L13),J13>0),L13/J13-1,"") | S13: рассчитано | Z13: =IF(AND(ISNUMBER(V13),ISNUMBER(Y13),Y13>0),V13/Y13-1,"") | AC13: Сметы (корень) | AD13: project_globus_to.md | AE13: Финал v2 по ценам Митино; первый вариант 17,34 млн. По файлу итог двух ГМ 41,67 млн, «маржа 20,0 %» = фактически наценка (маржа 16,7 %)
A14: 10 | B14: 46226 | C14: X5 (Агроторг) | D14: РЦ Калининград | E14: КТО РЦ, оптимизированный штат 8 чел. (вар. А) | F14: Калининград | G14: КТО / ТО | H14: ТО и абонентское обслуживание | I14: в месяц | J14: 2600000 | K14: 2111750 | L14: 2600000 | N14: =IF(AND(ISNUMBER(K14),ISNUMBER(L14),K14>0),L14/K14-1,0.231) -> 0.23120635 | O14: =IF(AND(ISNUMBER(K14),ISNUMBER(L14),L14>0),1-K14/L14,0.188) -> 0.18778846 | P14: =IF(AND(ISNUMBER(J14),ISNUMBER(L14),J14>0),L14/J14-1,"") -> 0 | S14: рассчитано | Z14: =IF(AND(ISNUMBER(V14),ISNUMBER(Y14),Y14>0),V14/Y14-1,"") | AC14: РЦ Калининград | AD14: project_kaliningrad_budget.md | AE14: Полный штат 17 чел. — с/с 4,74 млн/мес (убыток). Фикс 70 % (1,82 млн) с/с не покрывает; вар. Б 7 чел. маржа 24,2 %. Штраф 100 % мес.
A15: 11 | B15: 46226 | C15: X5 / Агроторг («Пятёрочка») | D15: РЦ «Пятёрочка» Ярославль | E15: Комплексное ТО распределительного центра, 24 мес (B2B 4507641) | F15: Ярославль | G15: КТО / ТО | H15: ТО и абонентское обслуживание | I15: в месяц | L15: 1300000 | N15: =IF(AND(ISNUMBER(K15),ISNUMBER(L15),K15>0),L15/K15-1,"") | O15: =IF(AND(ISNUMBER(K15),ISNUMBER(L15),L15>0),1-K15/L15,"") | P15: =IF(AND(ISNUMBER(J15),ISNUMBER(L15),J15>0),L15/J15-1,"") | S15: подано | V15: 1300000 | W15: проиграли | Z15: =IF(AND(ISNUMBER(V15),ISNUMBER(Y15),Y15>0),V15/Y15-1,"") | AB15: По цене 1-е место в 5 лотах из 9; проиграли на квалификации (оборот 20–50 млн в анкете). Итог 12.08.2026. | AC15: РЦ … (9 подпапок) | AD15: project_pyaterochka_rc.md | AE15: Итог 12.08.2026: проиграли все 9 лотов (по 5 лотам были 1-ми по цене). Слабая квал. анкета (оборот 20–50 млн). Плюс нормочасы РСР отдельно
A16: 12 | B16: 46226 | C16: X5 / Агроторг («Пятёрочка») | D16: РЦ «Пятёрочка» Вятка | E16: Комплексное ТО распределительного центра, 24 мес (B2B 4507641) | F16: Киров | G16: КТО / ТО | H16: ТО и абонентское обслуживание | I16: в месяц | L16: 1200000 | N16: =IF(AND(ISNUMBER(K16),ISNUMBER(L16),K16>0),L16/K16-1,"") | O16: =IF(AND(ISNUMBER(K16),ISNUMBER(L16),L16>0),1-K16/L16,"") | P16: =IF(AND(ISNUMBER(J16),ISNUMBER(L16),J16>0),L16/J16-1,"") | S16: подано | V16: 1200000 | W16: проиграли | Z16: =IF(AND(ISNUMBER(V16),ISNUMBER(Y16),Y16>0),V16/Y16-1,"") | AB16: По цене 1-е место в 5 лотах из 9; проиграли на квалификации (оборот 20–50 млн в анкете). Итог 12.08.2026. | AC16: РЦ … (9 подпапок) | AD16: project_pyaterochka_rc.md | AE16: Итог 12.08.2026: проиграли все 9 лотов (по 5 лотам были 1-ми по цене). Слабая квал. анкета (оборот 20–50 млн). Плюс нормочасы РСР отдельно
A17: 13 | B17: 46226 | C17: X5 / Агроторг («Пятёрочка») | D17: РЦ «Пятёрочка» В.Новгород | E17: Комплексное ТО распределительного центра, 24 мес (B2B 4507641) | F17: Новгородская обл. | G17: КТО / ТО | H17: ТО и абонентское обслуживание | I17: в месяц | L17: 1200000 | N17: =IF(AND(ISNUMBER(K17),ISNUMBER(L17),K17>0),L17/K17-1,"") | O17: =IF(AND(ISNUMBER(K17),ISNUMBER(L17),L17>0),1-K17/L17,"") | P17: =IF(AND(ISNUMBER(J17),ISNUMBER(L17),J17>0),L17/J17-1,"") | S17: подано | V17: 1200000 | W17: проиграли | Z17: =IF(AND(ISNUMBER(V17),ISNUMBER(Y17),Y17>0),V17/Y17-1,"") | AB17: По цене 1-е место в 5 лотах из 9; проиграли на квалификации (оборот 20–50 млн в анкете). Итог 12.08.2026. | AC17: РЦ … (9 подпапок) | AD17: project_pyaterochka_rc.md | AE17: Итог 12.08.2026: проиграли все 9 лотов (по 5 лотам были 1-ми по цене). Слабая квал. анкета (оборот 20–50 млн). Плюс нормочасы РСР отдельно
A18: 14 | B18: 46226 | C18: X5 / Агроторг («Пятёрочка») | D18: РЦ «Пятёрочка» Калининград | E18: Комплексное ТО распределительного центра, 24 мес (B2B 4507641) | F18: Калининград | G18: КТО / ТО | H18: ТО и абонентское обслуживание | I18: в месяц | L18: 2600000 | N18: =IF(AND(ISNUMBER(K18),ISNUMBER(L18),K18>0),L18/K18-1,"") | O18: =IF(AND(ISNUMBER(K18),ISNUMBER(L18),L18>0),1-K18/L18,"") | P18: =IF(AND(ISNUMBER(J18),ISNUMBER(L18),J18>0),L18/J18-1,"") | S18: подано | V18: 2600000 | W18: проиграли | Z18: =IF(AND(ISNUMBER(V18),ISNUMBER(Y18),Y18>0),V18/Y18-1,"") | AB18: По цене 1-е место в 5 лотах из 9; проиграли на квалификации (оборот 20–50 млн в анкете). Итог 12.08.2026. | AC18: РЦ … (9 подпапок) | AD18: project_pyaterochka_rc.md | AE18: Итог 12.08.2026: проиграли все 9 лотов (по 5 лотам были 1-ми по цене). Слабая квал. анкета (оборот 20–50 млн). Плюс нормочасы РСР отдельно
A19: 15 | B19: 46226 | C19: X5 / Агроторг («Пятёрочка») | D19: РЦ «Пятёрочка» Адамант | E19: Комплексное ТО распределительного центра, 24 мес (B2B 4507641) | G19: КТО / ТО | H19: ТО и абонентское обслуживание | I19: в месяц | L19: 1550000 | N19: =IF(AND(ISNUMBER(K19),ISNUMBER(L19),K19>0),L19/K19-1,"") | O19: =IF(AND(ISNUMBER(K19),ISNUMBER(L19),L19>0),1-K19/L19,"") | P19: =IF(AND(ISNUMBER(J19),ISNUMBER(L19),J19>0),L19/J19-1,"") | S19: подано | V19: 1550000 | W19: проиграли | Z19: =IF(AND(ISNUMBER(V19),ISNUMBER(Y19),Y19>0),V19/Y19-1,"") | AB19: По цене 1-е место в 5 лотах из 9; проиграли на квалификации (оборот 20–50 млн в анкете). Итог 12.08.2026. | AC19: РЦ … (9 подпапок) | AD19: project_pyaterochka_rc.md | AE19: Итог 12.08.2026: проиграли все 9 лотов (по 5 лотам были 1-ми по цене). Слабая квал. анкета (оборот 20–50 млн). Плюс нормочасы РСР отдельно
A20: 16 | B20: 46226 | C20: X5 / Агроторг («Пятёрочка») | D20: РЦ «Пятёрочка» ЗТЛ лот 1 | E20: Комплексное ТО распределительного центра, 24 мес (B2B 4507641) | G20: КТО / ТО | H20: ТО и абонентское обслуживание | I20: в месяц | L20: 1050000 | N20: =IF(AND(ISNUMBER(K20),ISNUMBER(L20),K20>0),L20/K20-1,"") | O20: =IF(AND(ISNUMBER(K20),ISNUMBER(L20),L20>0),1-K20/L20,"") | P20: =IF(AND(ISNUMBER(J20),ISNUMBER(L20),J20>0),L20/J20-1,"") | S20: подано | V20: 1050000 | W20: проиграли | Z20: =IF(AND(ISNUMBER(V20),ISNUMBER(Y20),Y20>0),V20/Y20-1,"") | AB20: По цене 1-е место в 5 лотах из 9; проиграли на квалификации (оборот 20–50 млн в анкете). Итог 12.08.2026. | AC20: РЦ … (9 подпапок) | AD20: project_pyaterochka_rc.md | AE20: Итог 12.08.2026: проиграли все 9 лотов (по 5 лотам были 1-ми по цене). Слабая квал. анкета (оборот 20–50 млн). Плюс нормочасы РСР отдельно
A21: 17 | B21: 46226 | C21: X5 / Агроторг («Пятёрочка») | D21: РЦ «Пятёрочка» ЗТЛ лот 2 | E21: Комплексное ТО распределительного центра, 24 мес (B2B 4507641) | G21: КТО / ТО | H21: ТО и абонентское обслуживание | I21: в месяц | L21: 1235000 | N21: =IF(AND(ISNUMBER(K21),ISNUMBER(L21),K21>0),L21/K21-1,"") | O21: =IF(AND(ISNUMBER(K21),ISNUMBER(L21),L21>0),1-K21/L21,"") | P21: =IF(AND(ISNUMBER(J21),ISNUMBER(L21),J21>0),L21/J21-1,"") | S21: подано | V21: 1235000 | W21: проиграли | Z21: =IF(AND(ISNUMBER(V21),ISNUMBER(Y21),Y21>0),V21/Y21-1,"") | AB21: По цене 1-е место в 5 лотах из 9; проиграли на квалификации (оборот 20–50 млн в анкете). Итог 12.08.2026. | AC21: РЦ … (9 подпапок) | AD21: project_pyaterochka_rc.md | AE21: Итог 12.08.2026: проиграли все 9 лотов (по 5 лотам были 1-ми по цене). Слабая квал. анкета (оборот 20–50 млн). Плюс нормочасы РСР отдельно
A22: 18 | B22: 46226 | C22: X5 / Агроторг («Пятёрочка») | D22: РЦ «Пятёрочка» Уткина Заводь (УТЗ) | E22: Комплексное ТО распределительного центра, 24 мес (B2B 4507641) | F22: ЛО | G22: КТО / ТО | H22: ТО и абонентское обслуживание | I22: в месяц | L22: 1100000 | N22: =IF(AND(ISNUMBER(K22),ISNUMBER(L22),K22>0),L22/K22-1,"") | O22: =IF(AND(ISNUMBER(K22),ISNUMBER(L22),L22>0),1-K22/L22,"") | P22: =IF(AND(ISNUMBER(J22),ISNUMBER(L22),J22>0),L22/J22-1,"") | S22: переторжка | T22: 1 150 000 → 1 100 000/мес (повторная переторжка 23.07.2026) | V22: 1100000 | W22: проиграли | Z22: =IF(AND(ISNUMBER(V22),ISNUMBER(Y22),Y22>0),V22/Y22-1,"") | AB22: По цене 1-е место в 5 лотах из 9; проиграли на квалификации (оборот 20–50 млн в анкете). Итог 12.08.2026. | AC22: РЦ … (9 подпапок) | AD22: project_pyaterochka_rc.md | AE22: Итог 12.08.2026: проиграли все 9 лотов (по 5 лотам были 1-ми по цене). Слабая квал. анкета (оборот 20–50 млн). Плюс нормочасы РСР отдельно
A23: 19 | B23: 46226 | C23: X5 / Агроторг («Пятёрочка») | D23: РЦ «Пятёрочка» Петрозаводск | E23: Комплексное ТО распределительного центра, 24 мес (B2B 4507641) | F23: Карелия | G23: КТО / ТО | H23: ТО и абонентское обслуживание | I23: в месяц | L23: 1140000 | N23: =IF(AND(ISNUMBER(K23),ISNUMBER(L23),K23>0),L23/K23-1,"") | O23: =IF(AND(ISNUMBER(K23),ISNUMBER(L23),L23>0),1-K23/L23,"") | P23: =IF(AND(ISNUMBER(J23),ISNUMBER(L23),J23>0),L23/J23-1,"") | S23: переторжка | T23: 1 200 000 → 1 140 000/мес (повторная переторжка 23.07.2026) | V23: 1140000 | W23: проиграли | Z23: =IF(AND(ISNUMBER(V23),ISNUMBER(Y23),Y23>0),V23/Y23-1,"") | AB23: По цене 1-е место в 5 лотах из 9; проиграли на квалификации (оборот 20–50 млн в анкете). Итог 12.08.2026. | AC23: РЦ … (9 подпапок) | AD23: project_pyaterochka_rc.md | AE23: Итог 12.08.2026: проиграли все 9 лотов (по 5 лотам были 1-ми по цене). Слабая квал. анкета (оборот 20–50 млн). Плюс нормочасы РСР отдельно
A24: 20 | B24: 46227 | C24: X5 Group | D24: РЦ «Троицкий», СПб, пр. Обуховской Обороны 295БД, 16 742 м² | E24: КТОиР инж. сетей, зданий и РСР, 1 200 н-ч/мес (B2B-Center 4491892) | F24: СПб | G24: КТО / ТО | H24: ТО и абонентское обслуживание | I24: в месяц | K24: 1876875 | L24: 2436000 | N24: =IF(AND(ISNUMBER(K24),ISNUMBER(L24),K24>0),L24/K24-1,0.2979) -> 0.2979021 | O24: =IF(AND(ISNUMBER(K24),ISNUMBER(L24),L24>0),1-K24/L24,0.2295) -> 0.22952586 | P24: =IF(AND(ISNUMBER(J24),ISNUMBER(L24),J24>0),L24/J24-1,"") | S24: рассчитано | Z24: =IF(AND(ISNUMBER(V24),ISNUMBER(Y24),Y24>0),V24/Y24-1,"") | AC24: РЦ БЕ ОКОЛО | AD24: project_x5_troitsky.md | AE24: Цена 2 030 руб/н-ч × 14 400 = 29 232 000/год; наценка 30 %. Пост 24/7, реакция 60 мин. Материалы по тарификатору ×1,3.
A25: 21 | B25: 46227 | C25: АО «Балтийский берег» | D25: ЛО, Ломоносовский р-н, д. Пеники, Центральная 2Г — 3 цеха | E25: Ремонтно-отделочные работы 3 объектов (полы, лотки, трапы, покраска, освещение) | F25: ЛО | G25: СМР / ремонт | H25: Крупные сети и девелоперы — конкурентный тендер | I25: разово | K25: 13010000 | L25: 19524000 | N25: =IF(AND(ISNUMBER(K25),ISNUMBER(L25),K25>0),L25/K25-1,0.5) -> 0.50069178 | O25: =IF(AND(ISNUMBER(K25),ISNUMBER(L25),L25>0),1-K25/L25,0.3336) -> 0.33364065 | P25: =IF(AND(ISNUMBER(J25),ISNUMBER(L25),J25>0),L25/J25-1,"") | S25: рассчитано | Z25: =IF(AND(ISNUMBER(V25),ISNUMBER(Y25),Y25>0),V25/Y25-1,"") | AC25: Балтийский берег | AD25: project_baltbereg_remont.md | AE25: Объекты: КП 7,167 / 7,777 / 4,58 млн. Действующее производство; площади уточнить обмером
A26: 22 | B26: 46230 | C26: X5 (АО «ТД «ПЕРЕКРЕСТОК») | D26: РЦ «Троицкий», СПб, пр. Обуховской Обороны 295БД | E26: Лот 1: ТО и ремонт ХО/КО/ВО, full service | F26: СПб | G26: КТО / ТО | H26: ТО и абонентское обслуживание | I26: в год | K26: 8520600 | L26: 11159000 | N26: =IF(AND(ISNUMBER(K26),ISNUMBER(L26),K26>0),L26/K26-1,0.3096) -> 0.30964956 | O26: =IF(AND(ISNUMBER(K26),ISNUMBER(L26),L26>0),1-K26/L26,0.2364) -> 0.23643696 | P26: =IF(AND(ISNUMBER(J26),ISNUMBER(L26),J26>0),L26/J26-1,"") | S26: рассчитано | Z26: =IF(AND(ISNUMBER(V26),ISNUMBER(Y26),Y26>0),V26/Y26-1,"") | AC26: РЦ БЕ ОКОЛО ХО | AD26: project_x5_ho_troitsky_ufa.md | AE26: с/с 710 050/мес ×12; ТО ХО 900 000/мес, н-ч 2 300; тарификатор ЗИП 3 174 поз. рынок ×1,30 (модельные цены); оффер на ЭТП заполнен
A27: 23 | B27: 46230 | C27: X5 (АО «ТД «ПЕРЕКРЕСТОК») | D27: РЦ Уфа, ул. Цветочная 36 | E27: Лот 2: ТО и ремонт ХО/КО/ВО, full service | F27: Башкортостан (Уфа) | G27: КТО / ТО | H27: ТО и абонентское обслуживание | I27: в год | K27: 4167900 | L27: 5465500 | N27: =IF(AND(ISNUMBER(K27),ISNUMBER(L27),K27>0),L27/K27-1,0.3113) -> 0.31133185 | O27: =IF(AND(ISNUMBER(K27),ISNUMBER(L27),L27>0),1-K27/L27,0.2374) -> 0.23741652 | P27: =IF(AND(ISNUMBER(J27),ISNUMBER(L27),J27>0),L27/J27-1,"") | S27: рассчитано | Z27: =IF(AND(ISNUMBER(V27),ISNUMBER(Y27),Y27>0),V27/Y27-1,"") | AC27: РЦ БЕ ОКОЛО ХО | AD27: project_x5_ho_troitsky_ufa.md | AE27: с/с 347 325/мес ×12; уфимская ставка — допущение (альтернатива субподряд 350–400К/мес); риск неоплаты месяца при потере товара
A28: 24 | B28: 46230 | C28: ООО «Гротекс» (Solopharm) | D28: Завод ЖЛФ, СПб, Индустриальный пр. 71 к.2 лит. А | E28: Ремонт плоской кровли ~350 м² (ПВХ-мембрана), Bidzaar 352-421 | F28: СПб | G28: СМР / ремонт | H28: Fit-out, частный бизнес, малые объёмы | I28: разово | K28: 914947 | N28: =IF(AND(ISNUMBER(K28),ISNUMBER(L28),K28>0),L28/K28-1,"") | O28: =IF(AND(ISNUMBER(K28),ISNUMBER(L28),L28>0),1-K28/L28,"") | P28: =IF(AND(ISNUMBER(J28),ISNUMBER(L28),J28>0),L28/J28-1,"") | S28: рассчитано | Z28: =IF(AND(ISNUMBER(V28),ISNUMBER(Y28),Y28>0),V28/Y28-1,"") | AC28: Сметы (корень) | AD28: project_grotex_krovlya.md | AE28: С/с 1 116 235 с НДС /1,22. ВОР нет — объёмы по 2 фото; КП не делали. Демонтаж старого ковра не заложен
A29: 25 | B29: 46230 | C29: ООО «Ладожская Форель» | D29: Склад-навес 18×24 м, пос. Хийденсельга, Питкярантский р-н | E29: Строительство склада-навеса (МК ~15 т, профнастил, фундаменты) с ПИР | F29: Карелия | G29: ПИР+СМР | H29: Fit-out, частный бизнес, малые объёмы | I29: разово | K29: 7541230 | L29: 15081967 | M29: 18400000 | N29: =IF(AND(ISNUMBER(K29),ISNUMBER(L29),K29>0),L29/K29-1,1) -> 0.99993465 | O29: =IF(AND(ISNUMBER(K29),ISNUMBER(L29),L29>0),1-K29/L29,0.5) -> 0.49998366 | P29: =IF(AND(ISNUMBER(J29),ISNUMBER(L29),J29>0),L29/J29-1,"") | S29: рассчитано | Z29: =IF(AND(ISNUMBER(V29),ISNUMBER(Y29),Y29>0),V29/Y29-1,"") | AC29: Сметы (корень) | AD29: project_ladoga_sklad.md | AE29: С/с 9 200 300 с НДС /1,22. КП б/НДС = 18,4 млн − НДС 3 318 032,79. Расхождения ТЗ/чертежей; полы, сети, электрика не включены
A30: 26 | B30: 46231 | C30: SUNLIGHT / ООО «МЦЗ-Ритейл» | D30: Магазин МЦЗ, СПб, Балканская пл. 5, ТРК «Балканский-3», пом. 21-16 (153,2 м²) | E30: СМР магазина ювелирных украшений + монтаж ТО | F30: СПб | G30: Fit-out | H30: Fit-out, частный бизнес, малые объёмы | I30: разово | K30: 4376359 | L30: 5224768 | M30: 6374217 | N30: =IF(AND(ISNUMBER(K30),ISNUMBER(L30),K30>0),L30/K30-1,"") -> 0.19386184 | O30: =IF(AND(ISNUMBER(K30),ISNUMBER(L30),L30>0),1-K30/L30,"") -> 0.16238214 | P30: =IF(AND(ISNUMBER(J30),ISNUMBER(L30),J30>0),L30/J30-1,"") | Q30: 0.2 | R30: 0.7 | S30: рассчитано | Z30: =IF(AND(ISNUMBER(V30),ISNUMBER(Y30),Y30>0),V30/Y30-1,"") | AC30: СанЛайт | AD30: project_sunlight_balkansky.md | AE30: КП 6 374 217 в т.ч. НДС (б/НДС = /1,22); с/с смешанная (работы без НДС, материалы с НДС) — наценка не считалась
A31: 27 | B31: 46232 | C31: СПбГИКиТ | D31: Съёмочный павильон УЛК №3, СПб, Бухарестская 22 лит. А | E31: Текущий ремонт съёмочного павильона (ЛСР 02-17-01, 138 позиций) | F31: СПб | G31: СМР / ремонт | H31: Госзакупки 44-ФЗ / 223-ФЗ | I31: разово | J31: 2146695.5 | K31: 1332034 | N31: =IF(AND(ISNUMBER(K31),ISNUMBER(L31),K31>0),L31/K31-1,"") | O31: =IF(AND(ISNUMBER(K31),ISNUMBER(L31),L31>0),1-K31/L31,"") | P31: =IF(AND(ISNUMBER(J31),ISNUMBER(L31),J31>0),L31/J31-1,"") | S31: рассчитано | Z31: =IF(AND(ISNUMBER(V31),ISNUMBER(Y31),Y31>0),V31/Y31-1,"") | AD31: project_gikit_pavilion.md | AE31: НМЦ 2 618 968,53 с НДС; рыночный бюджет на 37,9 % ниже сметы
A32: 28 | B32: 46232 | C32: СПбГУ | D32: СПб шоссе 109 (Петергоф) | E32: Ремонт ограждений: сварка, антикор, окраска 1 227 м² | F32: СПб | G32: СМР / ремонт | H32: Госзакупки 44-ФЗ / 223-ФЗ | I32: разово | J32: 944874.04 | K32: 641998 | N32: =IF(AND(ISNUMBER(K32),ISNUMBER(L32),K32>0),L32/K32-1,"") | O32: =IF(AND(ISNUMBER(K32),ISNUMBER(L32),L32>0),1-K32/L32,"") | P32: =IF(AND(ISNUMBER(J32),ISNUMBER(L32),J32>0),L32/J32-1,"") | S32: рассчитано | Z32: =IF(AND(ISNUMBER(V32),ISNUMBER(Y32),Y32>0),V32/Y32-1,"") | AC32: Сметы (корень) | AD32: project_spbgu_ograzhdeniya.md | AE32: Книга проекта по ЛСР 480-26/03-06-10; рыночный бюджет на 32,1 % ниже НМЦ. Доска для настила моста без стоимости
A33: 29 | B33: 46233 | C33: АО «СЗ Ланселот» | D33: ОКН «Мастеровой двор» (CHEVAL COURT), СПб, Конюшенная пл. 2 | E33: Отделочные и инженерные работы МОП, полная ВОР (463 поз.) | F33: СПб | G33: СМР / ремонт | H33: Крупные сети и девелоперы — конкурентный тендер | I33: разово | K33: 25900000 | L33: 48331148 | M33: 58964000 | N33: =IF(AND(ISNUMBER(K33),ISNUMBER(L33),K33>0),L33/K33-1,0.8661) -> 0.86606749 | O33: =IF(AND(ISNUMBER(K33),ISNUMBER(L33),L33>0),1-K33/L33,0.465) -> 0.4641137 | P33: =IF(AND(ISNUMBER(J33),ISNUMBER(L33),J33>0),L33/J33-1,"") | S33: рассчитано | Z33: =IF(AND(ISNUMBER(V33),ISNUMBER(Y33),Y33>0),V33/Y33-1,"") | AC33: Конюшня 2 | AD33: project_cheval_court_mop.md | AE33: На 2,2 % ниже конкурента (60,26 млн с НДС). Первый вариант 54 560 000. Люкс-отделка, много давальческих, ГУ 5 %.
A34: 30 | B34: 46233 | C34: ООО «СТД «Петрович» | D34: СПб, Южное ш. 39, лит. П, пом. 3.7 ~100 м² | E34: Косметический ремонт видеостудии (ЗА-523) | F34: СПб | G34: Fit-out | H34: Fit-out, частный бизнес, малые объёмы | I34: разово | K34: 1258232 | N34: =IF(AND(ISNUMBER(K34),ISNUMBER(L34),K34>0),L34/K34-1,"") | O34: =IF(AND(ISNUMBER(K34),ISNUMBER(L34),L34>0),1-K34/L34,"") | P34: =IF(AND(ISNUMBER(J34),ISNUMBER(L34),J34>0),L34/J34-1,"") | S34: рассчитано | Z34: =IF(AND(ISNUMBER(V34),ISNUMBER(Y34),Y34>0),V34/Y34-1,"") | AD34: project_petrovich_videostudia.md | AE34: КП не сделано. Без аванса, оплата 15 к.д. после КС с ИД; выезд обязателен. НДС в с/с не уточнён.
A35: 31 | B35: 46233 | C35: ООО «СТРОЙКОМПЛЕКС» | D35: Москва, ЦЗ №169, 1 и 4 этажи | E35: Отделка помещений 1 и 4 этажей (~133 поз.) | F35: Москва | G35: СМР / ремонт | H35: Крупные сети и девелоперы — конкурентный тендер | I35: разово | K35: 86803279 | L35: 1.7364619e+08 | M35: 211848347 | N35: =IF(AND(ISNUMBER(K35),ISNUMBER(L35),K35>0),L35/K35-1,1) -> 1.0004565 | O35: =IF(AND(ISNUMBER(K35),ISNUMBER(L35),L35>0),1-K35/L35,0.5001) -> 0.50011411 | P35: =IF(AND(ISNUMBER(J35),ISNUMBER(L35),J35>0),L35/J35-1,"") | S35: рассчитано | Z35: =IF(AND(ISNUMBER(V35),ISNUMBER(Y35),Y35>0),V35/Y35-1,"") | AD35: project_stroykompleks_otdelka_14.md | AE35: С/с 105,9 млн принята с НДС (маржа = КП − с/с), ÷1,22. Km 1,37 / Kw 3,50. В заметке противоречие «КП не сделано».
A36: 32 | B36: 46233 | C36: ООО «СТРОЙКОМПЛЕКС» | D36: Объект ЦЗ №165, Москва, 2–3 этаж (фарма, ЧПП) | E36: Отделка помещений 2–3 этажа с ЧПП, ~150 позиций | F36: Москва | G36: СМР / ремонт | H36: Крупные сети и девелоперы — конкурентный тендер | I36: разово | K36: 125100000 | M36: 250261091 | N36: =IF(AND(ISNUMBER(K36),ISNUMBER(L36),K36>0),L36/K36-1,1) -> 1 | O36: =IF(AND(ISNUMBER(K36),ISNUMBER(L36),L36>0),1-K36/L36,0.5) -> 0.5 | P36: =IF(AND(ISNUMBER(J36),ISNUMBER(L36),J36>0),L36/J36-1,"") | Q36: 0.36 | R36: 2.43 | S36: рассчитано | Z36: =IF(AND(ISNUMBER(V36),ISNUMBER(Y36),Y36>0),V36/Y36-1,"") | AD36: project_stroykompleks_otdelka.md | AE36: КП 250,26 млн указан «с НДС», но = с/с×2 (мат 94,5 + раб 155,8) — вероятно без НДС; уточнить. Давальческие материалы, аванс 30 %, 240 к.д.
A37: 33 | B37: 46233 | C37: ФСО (44-ФЗ) | D37: 11 режимных объектов ФСО в СПб, 462 ед. | E37: ТОиР кухонного оборудования, 12 мес | F37: СПб | G37: КТО / ТО | H37: Госзакупки 44-ФЗ / 223-ФЗ | I37: в год | J37: 4657400 | K37: 5214744 | N37: =IF(AND(ISNUMBER(K37),ISNUMBER(L37),K37>0),L37/K37-1,"") | O37: =IF(AND(ISNUMBER(K37),ISNUMBER(L37),L37>0),1-K37/L37,-0.12) -> -0.12 | P37: =IF(AND(ISNUMBER(J37),ISNUMBER(L37),J37>0),L37/J37-1,"") | S37: не участвовать | W37: не подавали | Z37: =IF(AND(ISNUMBER(V37),ISNUMBER(Y37),Y37>0),V37/Y37-1,"") | AD37: project_to_fso.md | AE37: С/с — сценарий Б (434 562/мес ×12); сценарий А −52,8 %. НМЦК под действующего исполнителя; участие только по НМЦК как вход.
A38: 34 | B38: 46234 | D38: 3 площадки: СПб Софийская 8; Сестрорецк, Воскова 2; Пушкин, Тиньков пер. 7 | E38: Абонентский хендимен-сервис офисных и производственных помещений (355-604 Bidzaar) | F38: СПб | G38: КТО / ТО | H38: ТО и абонентское обслуживание | I38: в месяц | K38: 93000 | L38: 195000 | M38: 237900 | N38: =IF(AND(ISNUMBER(K38),ISNUMBER(L38),K38>0),L38/K38-1,1.0968) -> 1.0967742 | O38: =IF(AND(ISNUMBER(K38),ISNUMBER(L38),L38>0),1-K38/L38,0.5231) -> 0.52307692 | P38: =IF(AND(ISNUMBER(J38),ISNUMBER(L38),J38>0),L38/J38-1,"") | S38: рассчитано | Z38: =IF(AND(ISNUMBER(V38),ISNUMBER(Y38),Y38>0),V38/Y38-1,"") | AC38: Сметы (корень) | AD38: project_handyman_3ploshchadki.md | AE38: С/с ≈93К при присоединении к бригадам (отдельным мастером ≈143К). Пол торга 150К. Лимит 60 н-ч/мес, сверх 3 000/н-ч
A39: 35 | B39: 46234 | C39: modi | D39: ТЦ «Экопарк», Мурино, Охтинская аллея 9, 112,5 м² | E39: Fit-out магазина modi | F39: ЛО | G39: Fit-out | H39: Fit-out, частный бизнес, малые объёмы | I39: разово | K39: 2230201 | L39: 3345301 | M39: 4081267 | N39: =IF(AND(ISNUMBER(K39),ISNUMBER(L39),K39>0),L39/K39-1,0.5) -> 0.49999978 | O39: =IF(AND(ISNUMBER(K39),ISNUMBER(L39),L39>0),1-K39/L39,0.3333) -> 0.33333323 | P39: =IF(AND(ISNUMBER(J39),ISNUMBER(L39),J39>0),L39/J39-1,"") | S39: рассчитано | Z39: =IF(AND(ISNUMBER(V39),ISNUMBER(Y39),Y39>0),V39/Y39-1,"") | AC39: Моди | AD39: project_modi_ekopark.md | AE39: Опция вывеска +330К; минус за сохранение треков −787 894 б/НДС. Вопросы: треки, готовый щит, вывеска.
A40: 36 | B40: 46234 | C40: Отель Sofitel 5* | D40: Отель Sofitel, СПб, 16 сплит-систем | E40: Абонентское ТО 16 кондиционеров (Bidzaar 351-654) | F40: СПб | G40: КТО / ТО | H40: ТО и абонентское обслуживание | I40: в месяц | K40: 55272 | L40: 98000 | M40: 119560 | N40: =IF(AND(ISNUMBER(K40),ISNUMBER(L40),K40>0),L40/K40-1,0.773) -> 0.77304965 | O40: =IF(AND(ISNUMBER(K40),ISNUMBER(L40),L40>0),1-K40/L40,0.436) -> 0.436 | P40: =IF(AND(ISNUMBER(J40),ISNUMBER(L40),J40>0),L40/J40-1,"") | S40: рассчитано | Z40: =IF(AND(ISNUMBER(V40),ISNUMBER(Y40),Y40>0),V40/Y40-1,"") | AC40: Софитель | AD40: project_sofitel_kondicionery.md | AE40: В форме: 96 000 за цикл раз в 2 мес (576К/год), выезд 6 000, н-ч 3 500. Пол торга ~80К/мес.
A41: 37 | B41: 46239 | D41: Банный комплекс «Жар-Птица», ТЦ «Лапино Коллекшн», МО, Одинцовский г.о., д. Новодарьино | E41: Генподряд: реконструкция 1–2 эт. ТЦ под банный комплекс, 2 222 м² | F41: МО | G41: Fit-out | H41: Fit-out, частный бизнес, малые объёмы | I41: разово | K41: 113114754 | L41: 2.1553159e+08 | M41: 262948537 | N41: =IF(AND(ISNUMBER(K41),ISNUMBER(L41),K41>0),L41/K41-1,0.9054) -> 0.90542418 | O41: =IF(AND(ISNUMBER(K41),ISNUMBER(L41),L41>0),1-K41/L41,0.475) -> 0.47518248 | P41: =IF(AND(ISNUMBER(J41),ISNUMBER(L41),J41>0),L41/J41-1,"") | Q41: 0.3 | R41: 2.5 | S41: рассчитано | Z41: =IF(AND(ISNUMBER(V41),ISNUMBER(Y41),Y41>0),V41/Y41-1,"") | AC41: Лапино Баня | AD41: project_lapino_banya.md | AE41: с/с в тексте 138,0 млн С НДС (/1,22); КП = форма 244,92 + дополнение 18,03 млн с НДС; нет РД вентиляции, чистовые материалы — заказчика
A42: 38 | B42: 46240 | C42: АО «АльфаСтрахование» | D42: Офис, МО, Сергиев Посад, пр-т Красной Армии 12 | E42: Косметический ремонт клиентской зоны офиса (~110 м²) | F42: МО | G42: Fit-out | H42: Fit-out, частный бизнес, малые объёмы | I42: разово | K42: 498365 | N42: =IF(AND(ISNUMBER(K42),ISNUMBER(L42),K42>0),L42/K42-1,"") | O42: =IF(AND(ISNUMBER(K42),ISNUMBER(L42),L42>0),1-K42/L42,"") | P42: =IF(AND(ISNUMBER(J42),ISNUMBER(L42),J42>0),L42/J42-1,"") | S42: рассчитано | Z42: =IF(AND(ISNUMBER(V42),ISNUMBER(Y42),Y42>0),V42/Y42-1,"") | AC42: Альфа Сергиево | AD42: project_alfa_sergiev.md | AE42: с/с 608 005 с НДС /1,22; КП не считалось; командировка 160 тыс; смысл только с местным субподрядом
A43: 39 | B43: 46240 | C43: АО «Дороги и Мосты» (ГП; заказчик ДКРС ОАО «РЖД») | D43: Полигон №4 ПК2419 ВСМ СПб–Москва, Валдай | E43: Завод балок: 4 пакета ВОР (СМУ, ИТИС, СПИ, ГПСМ), укрупнённо ±20 % | F43: Новгородская обл. | G43: СМР / ремонт | H43: Переторжка / 2 тур / вход к новому заказчику | I43: разово | K43: 1.5286885e+09 | N43: =IF(AND(ISNUMBER(K43),ISNUMBER(L43),K43>0),L43/K43-1,"") | O43: =IF(AND(ISNUMBER(K43),ISNUMBER(L43),L43>0),1-K43/L43,"") | P43: =IF(AND(ISNUMBER(J43),ISNUMBER(L43),J43>0),L43/J43-1,"") | S43: рассчитано | Z43: =IF(AND(ISNUMBER(V43),ISNUMBER(Y43),Y43>0),V43/Y43-1,"") | AC43: П4 | AD43: project_polygon4_vsm.md | AE43: С/с 1 865 млн с НДС ÷1,22. Песок 502 тыс. м³ принят давальческим (иначе +250–400 млн). Полный объект ~3,5–5 млрд, ВОР по остальным разделам не переданы.
A44: 40 | B44: 46240 | C44: ООО «ЕвроХим Северо-Запад-2» | D44: Кингисепп, промзона «Фосфорит», Аммиак-2/Карбамид | E44: Монтаж наружных сетей, тендер NW2-0AUP-1746 | F44: ЛО | G44: СМР / ремонт | H44: Переторжка / 2 тур / вход к новому заказчику | I44: разово | K44: 11862660 | L44: 20968499 | M44: 25580000 | N44: =IF(AND(ISNUMBER(K44),ISNUMBER(L44),K44>0),L44/K44-1,0.7676) -> 0.76760516 | O44: =IF(AND(ISNUMBER(K44),ISNUMBER(L44),L44>0),1-K44/L44,0.434) -> 0.4342628 | P44: =IF(AND(ISNUMBER(J44),ISNUMBER(L44),J44>0),L44/J44-1,"") | Q44: 0.35 | R44: 1 | S44: рассчитано | Z44: =IF(AND(ISNUMBER(V44),ISNUMBER(Y44),Y44>0),V44/Y44-1,"") | AC44: ЕвроХим | AD44: project_evrohim_seti.md | AE44: Вход в пул подрядчиков «Фосфорита». Действующий ОПО, НАКС, лаборатория НК; аванс 30 % с БГ. КП с НДС ≈25,58 млн.
A45: 41 | B45: 46240 | C45: ТД «ЦУМ» (Mercury) | D45: ЦУМ Outlet, ТЦ «Гранд Марина», Сочи, Несебрская 1А, 805 м² | E45: Fit-out магазина 805 м² | F45: Краснодарский край | G45: Fit-out | H45: Fit-out, частный бизнес, малые объёмы | I45: разово | K45: 21262178 | L45: 32373269 | N45: =IF(AND(ISNUMBER(K45),ISNUMBER(L45),K45>0),L45/K45-1,0.5226) -> 0.52257539 | O45: =IF(AND(ISNUMBER(K45),ISNUMBER(L45),L45>0),1-K45/L45,0.343) -> 0.34321807 | P45: =IF(AND(ISNUMBER(J45),ISNUMBER(L45),J45>0),L45/J45-1,"") | Q45: 0.3 | R45: 2 | S45: рассчитано | Z45: =IF(AND(ISNUMBER(V45),ISNUMBER(Y45),Y45>0),V45/Y45-1,"") | AC45: Сочи ЦУМ | AD45: project_sochi_tsum.md | AE45: Командировка, ночные работы в действующем ТЦ; неустойка 0,3 %/день; гарантийное удержание; аванс 30 %
A46: 42 | B46: 46241 | C46: ОАО «МЗ «Арсенал» | D46: СПб, Комсомола 1-3, здание 20 (КИЦ), h 21,6 м | E46: Поставка и монтаж освещения: 72 светильника PromLed, щит, кабели | F46: СПб | G46: Поставка и монтаж | H46: Госзакупки 44-ФЗ / 223-ФЗ | I46: разово | K46: 3561885.2 | L46: 5102459 | M46: 6225000 | N46: =IF(AND(ISNUMBER(K46),ISNUMBER(L46),K46>0),L46/K46-1,0.4325) -> 0.4325164 | O46: =IF(AND(ISNUMBER(K46),ISNUMBER(L46),L46>0),1-K46/L46,0.302) -> 0.30192771 | P46: =IF(AND(ISNUMBER(J46),ISNUMBER(L46),J46>0),L46/J46-1,"") | Q46: 0.3 | R46: 0.7 | S46: рассчитано | Z46: =IF(AND(ISNUMBER(V46),ISNUMBER(Y46),Y46>0),V46/Y46-1,"") | AC46: Арсенал | AD46: project_arsenal_osveshenie.md | AE46: С/с 4,35 млн с НДС ÷1,22. Режимный объект; подъёмник 22–26 м; светорасчёт DIALux обязателен в ТКП.
A47: 43 | B47: 46241 | C47: ООО «Рыбстандарт» (ГК «Балтийский берег») | D47: РВУ №2, ЛО, Выборгский р-н, Каменногорское ГП (~380 м²) | E47: Проектирование и строительство общежития 32 чел из СИП-панелей, 30 дней | F47: ЛО | G47: ПИР+СМР | H47: Fit-out, частный бизнес, малые объёмы | I47: разово | K47: 15166557 | N47: =IF(AND(ISNUMBER(K47),ISNUMBER(L47),K47>0),L47/K47-1,"") | O47: =IF(AND(ISNUMBER(K47),ISNUMBER(L47),L47>0),1-K47/L47,"") | P47: =IF(AND(ISNUMBER(J47),ISNUMBER(L47),J47>0),L47/J47-1,"") | S47: рассчитано | Z47: =IF(AND(ISNUMBER(V47),ISNUMBER(Y47),Y47>0),V47/Y47-1,"") | AC47: ББ Каменогорск | AD47: project_bb_kamenogorsk.md | AE47: с/с 18 503 200 с НДС /1,22; КП не считалось; нет геологии (гранит); аванса нет; срок 30 дней
A48: 44 | B48: 46245 | C48: Генподрядчик Лота 19 АГМ (реквизиты не заполнены) | D48: АБК Р7.1 автозавода АГМ, СПб, Шушары | E48: Субподряд: бригады монолит + МК + наружные сети без материалов (Сценарий А) | F48: СПб | G48: СМР / ремонт | H48: Переторжка / 2 тур / вход к новому заказчику | I48: разово | K48: 8350000 | L48: 11048979 | M48: 13479754 | N48: =IF(AND(ISNUMBER(K48),ISNUMBER(L48),K48>0),L48/K48-1,0.3232) -> 0.32323102 | O48: =IF(AND(ISNUMBER(K48),ISNUMBER(L48),L48>0),1-K48/L48,0.2443) -> 0.24427406 | P48: =IF(AND(ISNUMBER(J48),ISNUMBER(L48),J48>0),L48/J48-1,"") | S48: рассчитано | Z48: =IF(AND(ISNUMBER(V48),ISNUMBER(Y48),Y48>0),V48/Y48-1,"") | AC48: АГМ АБК (Desktop\АГМ АБК) | AD48: project_agm_abk.md | AE48: Сценарий Б (всё наше): с/с 13,90 млн, цена 18,54 млн б/НДС; сети ±100 % (РД НВК нет); чел.-смена ~18 тыс. vs 9–12 у неоформленных бригад
A49: 45 | B49: 46246 | C49: X5 Import (АО «АРВИАЙ») | D49: ХАБ «Богородск», Ногинск — Лот 1 | E49: КТО логистического ХАБа, 01.10.2026–30.09.2027 | F49: МО | G49: КТО / ТО | H49: ТО и абонентское обслуживание | I49: в месяц | K49: 851675 | L49: 850000 | N49: =IF(AND(ISNUMBER(K49),ISNUMBER(L49),K49>0),L49/K49-1,-0.002) -> -0.0019667127 | O49: =IF(AND(ISNUMBER(K49),ISNUMBER(L49),L49>0),1-K49/L49,-0.002) -> -0.0019705882 | P49: =IF(AND(ISNUMBER(J49),ISNUMBER(L49),J49>0),L49/J49-1,"") | S49: рассчитано | Z49: =IF(AND(ISNUMBER(V49),ISNUMBER(Y49),Y49>0),V49/Y49-1,"") | AC49: Перекресток РЦ | AD49: project_x5_arviay.md | AE49: Цены — решение руководства; в сумме по 3 лотам −3 200/мес. Нормо-час 1 200 ниже с/с. Сценарий Б: с/с 1,70 млн, маржа 19,2 %
A50: 46 | B50: 46246 | C50: X5 Import (АО «АРВИАЙ») | D50: ХАБ «Богородск», Ногинск — Лот 2 | E50: КТО логистического ХАБа, 01.10.2026–30.09.2027 | F50: МО | G50: КТО / ТО | H50: ТО и абонентское обслуживание | I50: в месяц | K50: 253550 | L50: 400000 | N50: =IF(AND(ISNUMBER(K50),ISNUMBER(L50),K50>0),L50/K50-1,0.5776) -> 0.57759811 | O50: =IF(AND(ISNUMBER(K50),ISNUMBER(L50),L50>0),1-K50/L50,0.3661) -> 0.366125 | P50: =IF(AND(ISNUMBER(J50),ISNUMBER(L50),J50>0),L50/J50-1,"") | S50: рассчитано | Z50: =IF(AND(ISNUMBER(V50),ISNUMBER(Y50),Y50>0),V50/Y50-1,"") | AC50: Перекресток РЦ | AD50: project_x5_arviay.md | AE50: Цены — решение руководства; в сумме по 3 лотам −3 200/мес. Нормо-час 1 200 ниже с/с. Сценарий Б: с/с 1,70 млн, маржа 19,2 %
A51: 47 | B51: 46246 | C51: X5 Import (АО «АРВИАЙ») | D51: ХАБ «Пулково», Виллози — Лот 3 | E51: КТО логистического ХАБа, 01.10.2026–30.09.2027 | F51: ЛО | G51: КТО / ТО | H51: ТО и абонентское обслуживание | I51: в месяц | K51: 997975 | L51: 850000 | N51: =IF(AND(ISNUMBER(K51),ISNUMBER(L51),K51>0),L51/K51-1,-0.1483) -> -0.14827526 | O51: =IF(AND(ISNUMBER(K51),ISNUMBER(L51),L51>0),1-K51/L51,-0.1741) -> -0.17408824 | P51: =IF(AND(ISNUMBER(J51),ISNUMBER(L51),J51>0),L51/J51-1,"") | S51: рассчитано | Z51: =IF(AND(ISNUMBER(V51),ISNUMBER(Y51),Y51>0),V51/Y51-1,"") | AC51: Перекресток РЦ | AD51: project_x5_arviay.md | AE51: Цены — решение руководства; в сумме по 3 лотам −3 200/мес. Нормо-час 1 200 ниже с/с. Сценарий Б: с/с 1,70 млн, маржа 19,2 %
A52: 48 | B52: 46247 | C52: АО «Дороги и Мосты» (ГП; заказчик ДКРС ОАО «РЖД») | D52: Полигон №4 ПК2419 ВСМ СПб–Москва, Валдай | E52: Только бригада: монолит, МК 717,8 т, наружные сети (материалы ГП), вар. А | F52: Новгородская обл. | G52: СМР / ремонт | H52: Переторжка / 2 тур / вход к новому заказчику | I52: разово | K52: 166470000 | L52: 198100000 | M52: 241700000 | N52: =IF(AND(ISNUMBER(K52),ISNUMBER(L52),K52>0),L52/K52-1,0.19) -> 0.1900042 | O52: =IF(AND(ISNUMBER(K52),ISNUMBER(L52),L52>0),1-K52/L52,0.19) -> 0.15966683 | P52: =IF(AND(ISNUMBER(J52),ISNUMBER(L52),J52>0),L52/J52-1,"") | S52: рассчитано | Z52: =IF(AND(ISNUMBER(V52),ISNUMBER(Y52),Y52>0),V52/Y52-1,"") | AC52: П4 | AD52: project_polygon4_vsm.md | AE52: КП — ориентир при марже 19 %, не подано. Вар. Б (механизация ГП) с/с 122,45 / КП 145,7 млн. Риск: 43,9 км трубы ССД на 4,5 км трассы.
A53: 49 | B53: 46248 | D53: ДОУ на 103 места, Папушево (5 608 м²) | E53: Строительство ДОУ, монолит, 107 позиций ВОР | G53: СМР / ремонт | H53: Крупные сети и девелоперы — конкурентный тендер | I53: разово | K53: 299810658 | L53: 449715987 | M53: 548653504 | N53: =IF(AND(ISNUMBER(K53),ISNUMBER(L53),K53>0),L53/K53-1,0.5) -> 0.5 | O53: =IF(AND(ISNUMBER(K53),ISNUMBER(L53),L53>0),1-K53/L53,0.333) -> 0.33333333 | P53: =IF(AND(ISNUMBER(J53),ISNUMBER(L53),J53>0),L53/J53-1,"") | S53: рассчитано | Z53: =IF(AND(ISNUMBER(V53),ISNUMBER(Y53),Y53>0),V53/Y53-1,"") | AC53: Папушево | AD53: project_tendery_avgust_2026.md | AE53: КП выпущено 14.08 на текстовой шапке (нужен бланк); фасад 1 925 vs 2 750 м², нет внутренних инженерных систем в ВОР
A54: 50 | B54: 46248 | C54: ГК ФСК СЗ | D54: Пушкинец: ПМК + пункт полиции | E54: Лоты 141/142: отделка ПМК + пункт полиции (ресурсная ФКП 1 179 строк) | G54: СМР / ремонт | H54: Крупные сети и девелоперы — конкурентный тендер | I54: разово | K54: 5829971 | L54: 7847760 | N54: =IF(AND(ISNUMBER(K54),ISNUMBER(L54),K54>0),L54/K54-1,0.3461) -> 0.34610618 | O54: =IF(AND(ISNUMBER(K54),ISNUMBER(L54),L54>0),1-K54/L54,0.2571) -> 0.25711655 | P54: =IF(AND(ISNUMBER(J54),ISNUMBER(L54),J54>0),L54/J54-1,"") | S54: рассчитано | Z54: =IF(AND(ISNUMBER(V54),ISNUMBER(Y54),Y54>0),V54/Y54-1,"") | AC54: Пушкинец | AD54: project_tendery_avgust_2026.md | AE54: Цена — расчётная (мат +20 %/раб +50 %), факт подачи не указан
A55: 51 | B55: 46248 | C55: ЛЕМАНА ПРО | D55: 12 ТЦ ЛЕМАНА ПРО | E55: Предквалификация: замена освещения 12 ТЦ | G55: Поставка и монтаж | H55: Крупные сети и девелоперы — конкурентный тендер | I55: разово | K55: 307742346 | L55: 386818000 | N55: =IF(AND(ISNUMBER(K55),ISNUMBER(L55),K55>0),L55/K55-1,0.257) -> 0.25695409 | O55: =IF(AND(ISNUMBER(K55),ISNUMBER(L55),L55>0),1-K55/L55,0.2044) -> 0.20442599 | P55: =IF(AND(ISNUMBER(J55),ISNUMBER(L55),J55>0),L55/J55-1,"") | S55: рассчитано | Z55: =IF(AND(ISNUMBER(V55),ISNUMBER(Y55),Y55>0),V55/Y55-1,"") | AC55: Лемана светильники | AD55: project_tendery_avgust_2026.md | AE55: Цена — расчётная (мат +20 %/раб +50 %), факт подачи не указан; РД нет, оценка ±25 %; выгодно брать только 4 объекта в СПб (с/с 75,2 млн)
A56: 52 | B56: 46248 | C56: МБМ Девел | D56: Офис «Копирка», 14 эт. БЦ «Линкор», Москва | E56: Отделка офиса (субподряд) | F56: Москва | G56: Fit-out | H56: Fit-out, частный бизнес, малые объёмы | I56: разово | K56: 3765163 | L56: 5181908 | N56: =IF(AND(ISNUMBER(K56),ISNUMBER(L56),K56>0),L56/K56-1,0.3763) -> 0.3762772 | O56: =IF(AND(ISNUMBER(K56),ISNUMBER(L56),L56>0),1-K56/L56,0.2734) -> 0.27340219 | P56: =IF(AND(ISNUMBER(J56),ISNUMBER(L56),J56>0),L56/J56-1,"") | S56: рассчитано | Z56: =IF(AND(ISNUMBER(V56),ISNUMBER(Y56),Y56>0),V56/Y56-1,"") | AC56: МБМ Девел | AD56: project_tendery_avgust_2026.md | AE56: Цена — расчётная (мат +20 %/раб +50 %), факт подачи не указан; в ЛСР нет перегородок ГКЛ и дверей из РД (+1,45 млн); командировочные 719 тыс
A57: 53 | B57: 46248 | C57: ОАО «КАРАВАЙ» | D57: ПП1, СПб, Херсонская 22 (башня ~30 м) | E57: Кровля 45 м² над баками воды | F57: СПб | G57: СМР / ремонт | H57: Крупные сети и девелоперы — конкурентный тендер | I57: разово | K57: 866935 | L57: 1127000 | N57: =IF(AND(ISNUMBER(K57),ISNUMBER(L57),K57>0),L57/K57-1,0.3) -> 0.29998212 | O57: =IF(AND(ISNUMBER(K57),ISNUMBER(L57),L57>0),1-K57/L57,0.2308) -> 0.23075865 | P57: =IF(AND(ISNUMBER(J57),ISNUMBER(L57),J57>0),L57/J57-1,"") | S57: рассчитано | Z57: =IF(AND(ISNUMBER(V57),ISNUMBER(Y57),Y57>0),V57/Y57-1,"") | AC57: Каравай кровля | AD57: project_tendery_avgust_2026.md | AE57: B2B № 4561866, до 20.08; цена с наценкой 30 %
A58: 54 | B58: 46251 | C58: АО «Балтийский берег» | D58: ОП «Пеники», ЛО, Ломоносовский р-н, 3 участка 837 м² | E58: Кислотоупорные полы, лотки AISI, окраска, освещение склада | F58: ЛО | G58: СМР / ремонт | H58: Крупные сети и девелоперы — конкурентный тендер | I58: разово | K58: 16338060 | L58: 22056388 | M58: 26908793 | N58: =IF(AND(ISNUMBER(K58),ISNUMBER(L58),K58>0),L58/K58-1,0.35) -> 0.35000043 | O58: =IF(AND(ISNUMBER(K58),ISNUMBER(L58),L58>0),1-K58/L58,0.2593) -> 0.25925949 | P58: =IF(AND(ISNUMBER(J58),ISNUMBER(L58),J58>0),L58/J58-1,"") | S58: рассчитано | Z58: =IF(AND(ISNUMBER(V58),ISNUMBER(Y58),Y58>0),V58/Y58-1,"") | AC58: Пеники СМР | AD58: project_peniki_smr.md | AE58: Единый коэф. 1,6009 на работы и материалы. Гарантия 5 лет. Лоток AISI 304 2,8 млн — подтвердить КП поставщика. Аванс не оговорён.
A59: 55 | B59: 46251 | C59: АО «Балтийский берег» | D59: Корпус №3 ОП «Пеники», ЛО, д. Пеники, Центральная 2Г | E59: ПИР, поставка, монтаж, ПНР вентиляции и кондиционирования 5 зон (~1280 м²) | F59: ЛО | G59: ПИР+СМР | H59: Крупные сети и девелоперы — конкурентный тендер | I59: разово | K59: 34553224 | L59: 49670000 | M59: 60597400 | N59: =IF(AND(ISNUMBER(K59),ISNUMBER(L59),K59>0),L59/K59-1,0.4375) -> 0.43749249 | O59: =IF(AND(ISNUMBER(K59),ISNUMBER(L59),L59>0),1-K59/L59,0.3043) -> 0.30434419 | P59: =IF(AND(ISNUMBER(J59),ISNUMBER(L59),J59>0),L59/J59-1,"") | Q59: 0.35 | R59: 1 | S59: рассчитано | Z59: =IF(AND(ISNUMBER(V59),ISNUMBER(Y59),Y59>0),V59/Y59-1,"") | AC59: ББ. Пеники. Вентиляция | AD59: project_peniki_ventilation.md | AE59: Ред.1 48,70 млн б/НДС → ред.2 49,67 млн. Оборуд. ×1,25. Холод 399 vs 481 кВт по РД; срок цены завода истёк; аванс 40 % при 100 % предоплате поставщику
A60: 56 | B60: 46251 | C60: ООО «Русский Стандарт Водка» | D60: СПб, Пулковское ш. 46 к2, АБК и Котельная | E60: Ремонт ПВХ-кровли АБК и Котельной | F60: СПб | G60: СМР / ремонт | H60: Fit-out, частный бизнес, малые объёмы | I60: разово | K60: 427747 | L60: 933850 | M60: 1139297 | N60: =IF(AND(ISNUMBER(K60),ISNUMBER(L60),K60>0),L60/K60-1,1.1832) -> 1.183183 | O60: =IF(AND(ISNUMBER(K60),ISNUMBER(L60),L60>0),1-K60/L60,0.542) -> 0.5419532 | P60: =IF(AND(ISNUMBER(J60),ISNUMBER(L60),J60>0),L60/J60-1,"") | Q60: 0.3 | R60: 1.5 | S60: рассчитано | Z60: =IF(AND(ISNUMBER(V60),ISNUMBER(Y60),Y60>0),V60/Y60-1,"") | AC60: РС Водка | AD60: project_rsv_krovlya.md | AE60: Промальпинисты, Leister, Технониколь; отсрочка ≥45 к.д., аванса нет. Ошибки формы заказчика исправлены.
A61: 57 | B61: 46251 | C61: ООО «Система ПБО» («Вкусно — и точка») | D61: ПБО 21055, СПб, Индустриальный пр. 22А | E61: Полная замена кровельного пирога 980 м² | F61: СПб | G61: СМР / ремонт | H61: Крупные сети и девелоперы — конкурентный тендер | I61: разово | K61: 10469802 | L61: 14500000 | M61: 17690000 | N61: =IF(AND(ISNUMBER(K61),ISNUMBER(L61),K61>0),L61/K61-1,0.3849) -> 0.38493546 | O61: =IF(AND(ISNUMBER(K61),ISNUMBER(L61),L61>0),1-K61/L61,0.278) -> 0.27794469 | P61: =IF(AND(ISNUMBER(J61),ISNUMBER(L61),J61>0),L61/J61-1,"") | S61: рассчитано | Z61: =IF(AND(ISNUMBER(V61),ISNUMBER(Y61),Y61>0),V61/Y61-1,"") | AC61: Мак на индустриальном | AD61: project_vit_industrialny.md | AE61: Bidzaar, переторжка назначена 20.08 (итог не описан); ночной коэф. 1,20; рамочный договор 3 года с фиксацией цен
A62: 58 | B62: 46252 | C62: ООО «ТТЦ Чапыгина 6» (орг. ООО «Медиа Бизнес Солюшенс») | D62: КПП, СПб, ул. Чапыгина 6 лит. Х | E62: Ремонт КПП (46 позиций ВОР) | F62: СПб | G62: СМР / ремонт | H62: Fit-out, частный бизнес, малые объёмы | I62: разово | K62: 1821221 | L62: 2731832 | M62: 3332835 | N62: =IF(AND(ISNUMBER(K62),ISNUMBER(L62),K62>0),L62/K62-1,0.5) -> 0.50000027 | O62: =IF(AND(ISNUMBER(K62),ISNUMBER(L62),L62>0),1-K62/L62,0.33) -> 0.33333346 | P62: =IF(AND(ISNUMBER(J62),ISNUMBER(L62),J62>0),L62/J62-1,"") | S62: подано | W62: ждём итогов | Z62: =IF(AND(ISNUMBER(V62),ISNUMBER(Y62),Y62>0),V62/Y62-1,"") | AD62: project_mbs_chapygina.md | AE62: Bidzaar 360-142, 2 этапа (финальное КП после выбора материалов); 40 к.д.; нет решения по усилению проёма
A63: 59 | B63: 46253 | C63: Ozon (ООО «Интернет Решения») | D63: ЛЦ «Горское», СПб, Парголово, Горское ш. 6 стр. 16 | E63: СМР: отделка 14 санузлов и 4 комнат приёма пищи | F63: СПб | G63: СМР / ремонт | H63: Крупные сети и девелоперы — конкурентный тендер | I63: разово | K63: 4055407 | L63: 5474799 | M63: 6679255 | N63: =IF(AND(ISNUMBER(K63),ISNUMBER(L63),K63>0),L63/K63-1,0.35) -> 0.34999989 | O63: =IF(AND(ISNUMBER(K63),ISNUMBER(L63),L63>0),1-K63/L63,0.259) -> 0.2592592 | P63: =IF(AND(ISNUMBER(J63),ISNUMBER(L63),J63>0),L63/J63-1,"") | Q63: 0.25 | R63: 1.7528 | S63: подано | W63: ждём итогов | Z63: =IF(AND(ISNUMBER(V63),ISNUMBER(Y63),Y63>0),V63/Y63-1,"") | AD63: project_ozon_gorskoe.md | AE63: Постоплата 45 к.д.; санфаянса нет в ВОР (ставим демонтированный, иначе +400–450 тыс)
A64: 60 | B64: 46253 | C64: X5 Group / ООО «Найс Айс» | D64: Производственно-складское здание, ЛО, Всеволожский р-н, Порошкино, зд. 1734 | E64: Реконструкция участка «ХотХит» 2 эт. (~600 м²): ПИР, узаконивание, СМР, инженерия | F64: ЛО | G64: ПИР+СМР | H64: Крупные сети и девелоперы — конкурентный тендер | I64: разово | K64: 32646810 | L64: 41630000 | M64: 50788600 | N64: =IF(AND(ISNUMBER(K64),ISNUMBER(L64),K64>0),L64/K64-1,0.275) -> 0.27516287 | O64: =IF(AND(ISNUMBER(K64),ISNUMBER(L64),L64>0),1-K64/L64,0.216) -> 0.21578645 | P64: =IF(AND(ISNUMBER(J64),ISNUMBER(L64),J64>0),L64/J64-1,"") | S64: рассчитано | Z64: =IF(AND(ISNUMBER(V64),ISNUMBER(Y64),Y64>0),V64/Y64-1,"") | AC64: Перек ТУ РЦ 20.08 | AD64: project_niceice_hothit.md | AE64: ВОР не передана, объёмы ±20–25 %; 100 % постоплата 15 р.д., финансирование не в с/с; проектирование без наценки
A65: 61 | B65: 46253 | C65: ООО «Компания БКС» | D65: Офис 419,7 м², Москва, пр-т Мира 69 стр. 1 | E65: Ремонт офиса (РСР), закупка 26107, форма КОРР | F65: Москва | G65: Fit-out | H65: Fit-out, частный бизнес, малые объёмы | I65: разово | K65: 18483607 | L65: 68814902 | M65: 83954181 | N65: =IF(AND(ISNUMBER(K65),ISNUMBER(L65),K65>0),L65/K65-1,2.723) -> 2.7230235 | O65: =IF(AND(ISNUMBER(K65),ISNUMBER(L65),L65>0),1-K65/L65,0.731) -> 0.73140111 | P65: =IF(AND(ISNUMBER(J65),ISNUMBER(L65),J65>0),L65/J65-1,"") | Q65: 1.9 | R65: 5 | S65: рассчитано | Z65: =IF(AND(ISNUMBER(V65),ISNUMBER(Y65),Y65>0),V65/Y65-1,"") | AC65: БКС | AD65: project_bks_ofis.md | AE65: С/с 22,55 млн с НДС ÷1,22. Версия 05.08 — 75 031 986 с НДС, 19.08 пересчёт по форме КОРР. В форме заказчика минус-формулы (~4,7 млн).
A66: 62 | B66: 46253 | C66: ООО «ОПХ» филиал «Бочкарев» | D66: Пивзавод, СПб, Тельмана 24А | E66: Замена колодца К3 Ду1000, коллектора Ду250 3 м, ремонт асфальта | F66: СПб | G66: СМР / ремонт | H66: Fit-out, частный бизнес, малые объёмы | I66: разово | K66: 2650838 | N66: =IF(AND(ISNUMBER(K66),ISNUMBER(L66),K66>0),L66/K66-1,"") | O66: =IF(AND(ISNUMBER(K66),ISNUMBER(L66),L66>0),1-K66/L66,"") | P66: =IF(AND(ISNUMBER(J66),ISNUMBER(L66),J66>0),L66/J66-1,"") | S66: рассчитано | Z66: =IF(AND(ISNUMBER(V66),ISNUMBER(Y66),Y66>0),V66/Y66-1,"") | AC66: Бочкарев | AD66: project_opkh_bochkarev_k3.md | AE66: Исследование рынка; ориентир КП 3,45/3,71/3,98 млн; постоплата 120 к.д., гарантия 5 лет, штраф 20 %
A67: 63 | B67: 46253 | C67: ООО «Ультрамар» | D67: Северные парки 1 и 2, ЛО, Кингисеппский р-н, д. Вистино (порт Усть-Луга) | E67: ТО освещения ж/д парков: 596 светильников, 64 шкафа, 4 щита, СИП 4,5 км | F67: ЛО | G67: КТО / ТО | H67: ТО и абонентское обслуживание | I67: в год | K67: 5449320 | L67: 8069900 | M67: 9845278 | N67: =IF(AND(ISNUMBER(K67),ISNUMBER(L67),K67>0),L67/K67-1,0.4809) -> 0.48090037 | O67: =IF(AND(ISNUMBER(K67),ISNUMBER(L67),L67>0),1-K67/L67,0.325) -> 0.32473513 | P67: =IF(AND(ISNUMBER(J67),ISNUMBER(L67),J67>0),L67/J67-1,"") | S67: рассчитано | Z67: =IF(AND(ISNUMBER(V67),ISNUMBER(Y67),Y67>0),V67/Y67-1,"") | AC67: Кингисепп Северный парк | AD67: project_ultramar_osveshenie.md | AE67: Вариант 2 (ТО 1 раз/год) 6 222 300. Пол переторжки 6,81 млн. Периодичность и срок не заданы, режимный объект, штрафы до 5 млн
A68: 64 | B68: 46254 | C68: АО «Балтийский Балкерный Терминал» | D68: ПС-6, СПб, Элеваторная пл. 28 | E68: Ремонт ПС-6: АКЗ, профлист, МК, огнезащитные перегородки | F68: СПб | G68: СМР / ремонт | H68: Крупные сети и девелоперы — конкурентный тендер | I68: разово | J68: 50000000 | K68: 26840000 | N68: =IF(AND(ISNUMBER(K68),ISNUMBER(L68),K68>0),L68/K68-1,"") | O68: =IF(AND(ISNUMBER(K68),ISNUMBER(L68),L68>0),1-K68/L68,"") | P68: =IF(AND(ISNUMBER(J68),ISNUMBER(L68),J68>0),L68/J68-1,"") | S68: рассчитано | Z68: =IF(AND(ISNUMBER(V68),ISNUMBER(Y68),Y68>0),V68/Y68-1,"") | AD68: project_bbt_ps6_kg.md | AE68: КП не указано; маржа к бюджету 46,3 %; нужна лицензия МЧС и согласование огнезащиты; доп. работы в счёт твёрдой цены
A69: 65 | B69: 46254 | C69: АО «Балтийский Балкерный Терминал» | D69: Конвейерные галереи КГ-3/4/17, СПб, Элеваторная пл. 28 | E69: Ремонт галерей: АКЗ, профлист, поручни | F69: СПб | G69: СМР / ремонт | H69: Крупные сети и девелоперы — конкурентный тендер | I69: разово | J69: 38770000 | K69: 26250000 | N69: =IF(AND(ISNUMBER(K69),ISNUMBER(L69),K69>0),L69/K69-1,"") | O69: =IF(AND(ISNUMBER(K69),ISNUMBER(L69),L69>0),1-K69/L69,"") | P69: =IF(AND(ISNUMBER(J69),ISNUMBER(L69),J69>0),L69/J69-1,"") | S69: рассчитано | Z69: =IF(AND(ISNUMBER(V69),ISNUMBER(Y69),Y69>0),V69/Y69-1,"") | AD69: project_bbt_ps6_kg.md | AE69: КП не указано; маржа к бюджету 32,3 %; промальп + АГП вместо лесов
A70: 66 | B70: 46255 | C70: X5 (АО «ТД «ПЕРЕКРЕСТОК») | D70: 696 супермаркетов, 11 лотов по дивизионам | E70: ТО систем канализации, жироуловителей, КНС (16 704 услуги/год) | F70: несколько регионов | G70: КТО / ТО | H70: ТО и абонентское обслуживание | I70: в год | K70: 366400000 | N70: =IF(AND(ISNUMBER(K70),ISNUMBER(L70),K70>0),L70/K70-1,"") | O70: =IF(AND(ISNUMBER(K70),ISNUMBER(L70),L70>0),1-K70/L70,"") | P70: =IF(AND(ISNUMBER(J70),ISNUMBER(L70),J70>0),L70/J70-1,"") | S70: рассчитано | Z70: =IF(AND(ISNUMBER(V70),ISNUMBER(Y70),Y70>0),V70/Y70-1,"") | AC70: Канализация Х5 | AD70: project_x5_kanalizaciya.md | AE70: КП нет; 21 936 руб за услугу; состав оборудования не передан; SLA 2 ч в договоре vs 3–4 ч в ТЗ
A71: 67 | B71: 46255 | C71: АО «Раменский ГОК» (ГК ФСК) | D71: Центральный склад и склад АТН, МО, Раменский, ул. Карьерная | E71: Ремонт мягкой кровли 928,5 м² | F71: МО | G71: СМР / ремонт | H71: Крупные сети и девелоперы — конкурентный тендер | I71: разово | K71: 2643130 | L71: 3395281 | M71: 4142243 | N71: =IF(AND(ISNUMBER(K71),ISNUMBER(L71),K71>0),L71/K71-1,0.2846) -> 0.2845683 | O71: =IF(AND(ISNUMBER(K71),ISNUMBER(L71),L71>0),1-K71/L71,0.222) -> 0.22152835 | P71: =IF(AND(ISNUMBER(J71),ISNUMBER(L71),J71>0),L71/J71-1,"") | Q71: 0.15 | R71: 0.35 | S71: рассчитано | Z71: =IF(AND(ISNUMBER(V71),ISNUMBER(Y71),Y71>0),V71/Y71-1,"") | AC71: ФСК кровля | AD71: project_ramgok_krovlya.md | AE71: КП — ориентир; пол торга 3 174 204. Объём замены утеплителя не определён (до +1,7 млн), оплачивать по факту
A72: 68 | B72: 46255 | C72: ФГБОУ ВО ПГУПС | D72: СПб, Московский пр. 9 лит. В (Фонтанки 115; Садовая 50-а) | E72: Текущий ремонт 14 металлических ворот (7 в границах ОКН) | F72: СПб | G72: СМР / ремонт | H72: Госзакупки 44-ФЗ / 223-ФЗ | I72: разово | J72: 3964220.4 | K72: 2251740 | N72: =IF(AND(ISNUMBER(K72),ISNUMBER(L72),K72>0),L72/K72-1,"") | O72: =IF(AND(ISNUMBER(K72),ISNUMBER(L72),L72>0),1-K72/L72,"") | P72: =IF(AND(ISNUMBER(J72),ISNUMBER(L72),J72>0),L72/J72-1,"") | S72: рассчитано | Z72: =IF(AND(ISNUMBER(V72),ISNUMBER(Y72),Y72>0),V72/Y72-1,"") | AC72: ПГУПС Ворота | AD72: project_pgups_vorota.md | AE72: Аукцион 223-ФЗ 03.09.2026; с/с — рыночный бюджет; маржа при НМЦ 43,2 %. Аванса нет, обеспечение 5 %, гарантия 3 года
A73: 69 | B73: 46258 | C73: ООО «АГМ» | D73: Корпус Р100, автозавод АГМ, СПб, Шушары | E73: Лот 26: кухонная зона корпуса Р100 (столовая 68 мест) | F73: СПб | G73: СМР / ремонт | H73: Крупные сети и девелоперы — конкурентный тендер | I73: разово | K73: 5200462 | L73: 7800694 | M73: 9516847 | N73: =IF(AND(ISNUMBER(K73),ISNUMBER(L73),K73>0),L73/K73-1,0.5) -> 0.50000019 | O73: =IF(AND(ISNUMBER(K73),ISNUMBER(L73),L73>0),1-K73/L73,0.333) -> 0.33333342 | P73: =IF(AND(ISNUMBER(J73),ISNUMBER(L73),J73>0),L73/J73-1,"") | Q73: 0.45 | R73: 2.3533 | S73: подано | W73: ждём итогов | Z73: =IF(AND(ISNUMBER(V73),ISNUMBER(Y73),Y73>0),V73/Y73-1,"") | AC73: АГМ кухня | AD73: project_agm_kuhnya_paneli.md | AE73: Раздела ОВ нет (вентиляция 35 % бюджета); аванса нет, неустойка 0,1 %/день без потолка; расчёты через ГПБ
A74: 70 | B74: 46258 | C74: ООО «АГМ» | D74: Корпус Р60.1 (цех Сборки), автозавод АГМ, СПб, Шушары | E74: Замена 5 стеновых сэндвич-панелей (25 м²) | F74: СПб | G74: СМР / ремонт | H74: Крупные сети и девелоперы — конкурентный тендер | I74: разово | K74: 803609 | L74: 1205413 | M74: 1470604 | N74: =IF(AND(ISNUMBER(K74),ISNUMBER(L74),K74>0),L74/K74-1,0.5) -> 0.49999938 | O74: =IF(AND(ISNUMBER(K74),ISNUMBER(L74),L74>0),1-K74/L74,0.333) -> 0.33333306 | P74: =IF(AND(ISNUMBER(J74),ISNUMBER(L74),J74>0),L74/J74-1,"") | Q74: 0.3 | R74: 0.7548 | S74: подано | W74: ждём итогов | Z74: =IF(AND(ISNUMBER(V74),ISNUMBER(Y74),Y74>0),V74/Y74-1,"") | AC74: АГМ стеновые панели | AD74: project_agm_kuhnya_paneli.md | AE74: Механизация 57 % с/с; ТЗ 4 панели vs форма 5; гарантия 6 мес в договоре vs 3 года в ТЗ
A75: 71 | B75: 46258 | C75: ООО «АГС» (Автозавод АГР) | D75: Сестрорецк, Левашовское ш. 20 стр. 1, 4 958,55 м² | E75: Восстановление дорожной разметки 28 560 м.п. | F75: СПб | G75: СМР / ремонт | H75: Крупные сети и девелоперы — конкурентный тендер | I75: разово | K75: 3053665 | N75: =IF(AND(ISNUMBER(K75),ISNUMBER(L75),K75>0),L75/K75-1,"") | O75: =IF(AND(ISNUMBER(K75),ISNUMBER(L75),L75>0),1-K75/L75,"") | P75: =IF(AND(ISNUMBER(J75),ISNUMBER(L75),J75>0),L75/J75-1,"") | S75: рассчитано | Z75: =IF(AND(ISNUMBER(V75),ISNUMBER(Y75),Y75>0),V75/Y75-1,"") | AC75: АГР разметка | AD75: project_agr_razmetka.md | AE75: КП не сделано. Аванса нет, оплата 30 дн.; гарантия 6 мес на зиму; объём очистки от ГСМ не задан.
A76: 72 | B76: 46261 | C76: ООО «ЛЕ МОНЛИД» (Лемана ПРО) | D76: Магазин №137, СПб, Таллинское ш. 163 | E76: Благоустройство парковки: ямочный ремонт 240 м², островки, ИДН, знаки, разметка | F76: СПб | G76: СМР / ремонт | H76: Крупные сети и девелоперы — конкурентный тендер | I76: разово | K76: 3089414 | L76: 4325000 | M76: 5276500 | N76: =IF(AND(ISNUMBER(K76),ISNUMBER(L76),K76>0),L76/K76-1,0.4) -> 0.39994187 | O76: =IF(AND(ISNUMBER(K76),ISNUMBER(L76),L76>0),1-K76/L76,0.286) -> 0.28568462 | P76: =IF(AND(ISNUMBER(J76),ISNUMBER(L76),J76>0),L76/J76-1,"") | Q76: 0.2 | R76: 0.544 | S76: рассчитано | Z76: =IF(AND(ISNUMBER(V76),ISNUMBER(Y76),Y76>0),V76/Y76-1,"") | AC76: ЛеМана парковка | AD76: project_lemana_parkovka.md | AE76: Ночные работы; гарантийное удержание 10 % в форме vs договор без удержания; толщина а/б не задана (70 мм +210 тыс.)
A77: 73 | B77: 46261 | C77: ООО «Лента» | D77: ТК «Лента» ТК-1, СПб (адрес в ТЗ не указан) | E77: Капремонт асфальта парковки ~1 000 м² | F77: СПб | G77: СМР / ремонт | H77: Крупные сети и девелоперы — конкурентный тендер | I77: разово | K77: 2830715 | L77: 3680000 | M77: 4489600 | N77: =IF(AND(ISNUMBER(K77),ISNUMBER(L77),K77>0),L77/K77-1,0.3) -> 0.30002491 | O77: =IF(AND(ISNUMBER(K77),ISNUMBER(L77),L77>0),1-K77/L77,0.231) -> 0.23078397 | P77: =IF(AND(ISNUMBER(J77),ISNUMBER(L77),J77>0),L77/J77-1,"") | S77: рассчитано | Z77: =IF(AND(ISNUMBER(V77),ISNUMBER(Y77),Y77>0),V77/Y77-1,"") | AC77: Лента ТК-1 | AD77: project_lenta_tk1_parkovka.md | AE77: Объёмы в ТЗ не заданы — пиксельный обмер ±15 %; пол торга 3 114–3 397 тыс.
A78: 74 | B78: 46262 | C78: АО «ПНТ-Сервис» | D78: Трасса 11, СПб, Элеваторная пл. 32А | E78: Ремонт трубопроводов, МК, ж/б колонн, АКЗ (ДВ Ав-04/26, Ав-09/26) | F78: СПб | G78: СМР / ремонт | H78: Крупные сети и девелоперы — конкурентный тендер | I78: разово | K78: 291441193 | L78: 378873551 | M78: 462225732 | N78: =IF(AND(ISNUMBER(K78),ISNUMBER(L78),K78>0),L78/K78-1,0.3) -> 0.3 | O78: =IF(AND(ISNUMBER(K78),ISNUMBER(L78),L78>0),1-K78/L78,0.2308) -> 0.23076923 | P78: =IF(AND(ISNUMBER(J78),ISNUMBER(L78),J78>0),L78/J78-1,"") | S78: рассчитано | Z78: =IF(AND(ISNUMBER(V78),ISNUMBER(Y78),Y78>0),V78/Y78-1,"") | AC78: Металл Дудко | AD78: project_pnt_trassa11.md | AE78: ОПО, СРО+НАКС, 240 к.д. круглосуточно; нет теплоизоляции в ДВ (+15–18 млн); краны DN800 120–150 дн.
A79: 75 | B79: 46262 | C79: АО «ПНТ-Сервис» | D79: Вышки внутреннего контура H=55 м, 15 шт. | E79: Монтаж 15 вышек 55 м (МК давальческие) | F79: СПб | G79: СМР / ремонт | H79: Крупные сети и девелоперы — конкурентный тендер | I79: разово | K79: 86175796 | L79: 141808989 | N79: =IF(AND(ISNUMBER(K79),ISNUMBER(L79),K79>0),L79/K79-1,0.6456) -> 0.64557794 | O79: =IF(AND(ISNUMBER(K79),ISNUMBER(L79),L79>0),1-K79/L79,0.3923) -> 0.39231077 | P79: =IF(AND(ISNUMBER(J79),ISNUMBER(L79),J79>0),L79/J79-1,"") | S79: рассчитано | Z79: =IF(AND(ISNUMBER(V79),ISNUMBER(Y79),Y79>0),V79/Y79-1,"") | AC79: Металл Дудко | AD79: project_pnt_trassa11.md | AE79: Цена = с/с ×1,3 / 0,79 (услуги ГП 21 % от цены); с НДС ~173,0 млн
A80: 76 | B80: 46262 | C80: ООО «СК АЛЬЯНС» (ТКП на ООО «СТРОЙ АЛЬЯНС») | D80: ПСК ИндастриалСити «Есипово-5», МО, г.о. Солнечногорск | E80: Отделка АББ + внутренние ОВ, ВК, ЭОМ, вентиляция, АУПТ (лот неделим) | F80: МО | G80: СМР / ремонт | H80: Крупные сети и девелоперы — конкурентный тендер | I80: разово | K80: 429170059 | L80: 557920900 | M80: 680663498 | N80: =IF(AND(ISNUMBER(K80),ISNUMBER(L80),K80>0),L80/K80-1,0.3) -> 0.29999959 | O80: =IF(AND(ISNUMBER(K80),ISNUMBER(L80),L80>0),1-K80/L80,0.231) -> 0.23076899 | P80: =IF(AND(ISNUMBER(J80),ISNUMBER(L80),J80>0),L80/J80-1,"") | S80: рассчитано | Z80: =IF(AND(ISNUMBER(V80),ISNUMBER(Y80),Y80>0),V80/Y80-1,"") | AC80: парк Есипово 5 | AD80: project_esipovo5_otdelka.md | AE80: В Форме 4 ошибки объёмов (430 строк исправлено); удержания 7,74 % цены; РД только по внешней ссылке, цена твёрдая; переторжки не ограничены
A81: 77 | B81: 46265 | C81: АО «СЗ Ланселот» | D81: ОКН «Мастеровой двор» (CHEVAL COURT), СПб, Конюшенная пл. 2 | E81: Отделка МОП по урезанной ВОР (95 поз., срок 6 мес) | F81: СПб | G81: СМР / ремонт | H81: Переторжка / 2 тур / вход к новому заказчику | I81: разово | L81: 22131148 | M81: 27000000 | N81: =IF(AND(ISNUMBER(K81),ISNUMBER(L81),K81>0),L81/K81-1,"") | O81: =IF(AND(ISNUMBER(K81),ISNUMBER(L81),L81>0),1-K81/L81,"") | P81: =IF(AND(ISNUMBER(J81),ISNUMBER(L81),J81>0),L81/J81-1,"") | S81: рассчитано | T81: 30.07 58 964 000 с НДС (полная ВОР) → 31.08 27 000 000 с НДС (урезанная ВОР) | Z81: =IF(AND(ISNUMBER(V81),ISNUMBER(Y81),Y81>0),V81/Y81-1,"") | AC81: Конюшня 2 | AD81: project_cheval_court_mop.md | AE81: С/с по урезанной ВОР не посчитана; расценки из КП 30.07. ±1 мес срока = ±1,13 млн с НДС. Часть материалов стала давальческой.
A82: 78 | B82: 46265 | C82: ООО «ЛЕ МОНЛИД» (Лемана ПРО) | D82: Даркстор ЛЕМАНА ПРО, СПб, Парнас (~12 000 м²) | E82: Заявка 139/2.2.1: КТО инженерных систем даркстора | F82: СПб | G82: КТО / ТО | H82: ТО и абонентское обслуживание | I82: в месяц | K82: 989789 | L82: 1386000 | M82: 1690920 | N82: =IF(AND(ISNUMBER(K82),ISNUMBER(L82),K82>0),L82/K82-1,0.4) -> 0.40029845 | O82: =IF(AND(ISNUMBER(K82),ISNUMBER(L82),L82>0),1-K82/L82,0.2859) -> 0.28586652 | P82: =IF(AND(ISNUMBER(J82),ISNUMBER(L82),J82>0),L82/J82-1,"") | S82: рассчитано | Z82: =IF(AND(ISNUMBER(V82),ISNUMBER(Y82),Y82>0),V82/Y82-1,"") | AC82: Лемана Парнас КТО | AD82: project_lemana_parnas_kto.md | AE82: Площадь и генплан не переданы; при max штрафе SLA −15 % маржа 16 %; прайс Прил. 2 (627 поз.) не заполнен
A83: 79 | B83: 46265 | C83: ООО «ЛЕ МОНЛИД» (Лемана ПРО) | D83: ТЦ Екатеринбург Базовый 025 (~20 000 м²) | E83: КТО инженерных систем гипермаркета | F83: Екатеринбург | G83: КТО / ТО | H83: ТО и абонентское обслуживание | I83: в месяц | K83: 1842131 | L83: 2211000 | N83: =IF(AND(ISNUMBER(K83),ISNUMBER(L83),K83>0),L83/K83-1,0.2) -> 0.20024037 | O83: =IF(AND(ISNUMBER(K83),ISNUMBER(L83),L83>0),1-K83/L83,0.1668) -> 0.16683356 | P83: =IF(AND(ISNUMBER(J83),ISNUMBER(L83),J83>0),L83/J83-1,"") | S83: рассчитано | Z83: =IF(AND(ISNUMBER(V83),ISNUMBER(Y83),Y83>0),V83/Y83-1,"") | AC83: Лемана ЕКБ | AD83: project_lemana_4_gipermarketa.md | AE83: Решение к подаче: наценка 20 % (5 лотов = 10,0 млн/мес). Варианты: 50 %, по лотам 30–45 %, по с/с. При штрафе SLA −15 % маржа 2 %. Площади оценочные
A84: 80 | B84: 46265 | C84: ООО «ЛЕ МОНЛИД» (Лемана ПРО) | D84: Магазин Кемерово, Карболитовская 16б (~16 000 м²) | E84: КТО инженерных систем гипермаркета | F84: Кемерово | G84: КТО / ТО | H84: ТО и абонентское обслуживание | I84: в месяц | K84: 1749724 | L84: 2100000 | N84: =IF(AND(ISNUMBER(K84),ISNUMBER(L84),K84>0),L84/K84-1,0.2) -> 0.20018929 | O84: =IF(AND(ISNUMBER(K84),ISNUMBER(L84),L84>0),1-K84/L84,0.1668) -> 0.1667981 | P84: =IF(AND(ISNUMBER(J84),ISNUMBER(L84),J84>0),L84/J84-1,"") | S84: рассчитано | Z84: =IF(AND(ISNUMBER(V84),ISNUMBER(Y84),Y84>0),V84/Y84-1,"") | AC84: Лемана Кемерово | AD84: project_lemana_4_gipermarketa.md | AE84: Решение к подаче: наценка 20 % (5 лотов = 10,0 млн/мес). Варианты: 50 %, по лотам 30–45 %, по с/с. При штрафе SLA −15 % маржа 2 %. Площади оценочные
A85: 81 | B85: 46265 | C85: ООО «ЛЕ МОНЛИД» (Лемана ПРО) | D85: ТЦ Краснодар СБС (~14 000 м²) | E85: КТО инженерных систем гипермаркета | F85: Краснодар | G85: КТО / ТО | H85: ТО и абонентское обслуживание | I85: в месяц | K85: 1409990 | L85: 1692000 | N85: =IF(AND(ISNUMBER(K85),ISNUMBER(L85),K85>0),L85/K85-1,0.2) -> 0.20000851 | O85: =IF(AND(ISNUMBER(K85),ISNUMBER(L85),L85>0),1-K85/L85,0.1667) -> 0.16667258 | P85: =IF(AND(ISNUMBER(J85),ISNUMBER(L85),J85>0),L85/J85-1,"") | S85: рассчитано | Z85: =IF(AND(ISNUMBER(V85),ISNUMBER(Y85),Y85>0),V85/Y85-1,"") | AC85: Лемана краснодар КТО | AD85: project_lemana_4_gipermarketa.md | AE85: Решение к подаче: наценка 20 % (5 лотов = 10,0 млн/мес). Варианты: 50 %, по лотам 30–45 %, по с/с. При штрафе SLA −15 % маржа 2 %. Площади оценочные
A86: 82 | B86: 46265 | C86: ООО «ЛЕ МОНЛИД» (Лемана ПРО) | D86: ТЦ Челябинск, Копейское ш. 64 (~17 000 м²) | E86: КТО инженерных систем гипермаркета | F86: Челябинск | G86: КТО / ТО | H86: ТО и абонентское обслуживание | I86: в месяц | K86: 1695949 | L86: 2035000 | N86: =IF(AND(ISNUMBER(K86),ISNUMBER(L86),K86>0),L86/K86-1,0.2) -> 0.19991816 | O86: =IF(AND(ISNUMBER(K86),ISNUMBER(L86),L86>0),1-K86/L86,0.1666) -> 0.16660983 | P86: =IF(AND(ISNUMBER(J86),ISNUMBER(L86),J86>0),L86/J86-1,"") | S86: рассчитано | Z86: =IF(AND(ISNUMBER(V86),ISNUMBER(Y86),Y86>0),V86/Y86-1,"") | AC86: Лемана ЧЛБ | AD86: project_lemana_4_gipermarketa.md | AE86: Решение к подаче: наценка 20 % (5 лотов = 10,0 млн/мес). Варианты: 50 %, по лотам 30–45 %, по с/с. При штрафе SLA −15 % маржа 2 %. Площади оценочные
A87: 83 | B87: 46265 | C87: ООО «ЛЕ МОНЛИД» (Лемана ПРО) | D87: Гипермаркет Липецк (Заявка 155) | E87: КТО инженерных систем гипермаркета | F87: Липецк | G87: КТО / ТО | H87: ТО и абонентское обслуживание | I87: в месяц | K87: 1635088 | L87: 1962000 | N87: =IF(AND(ISNUMBER(K87),ISNUMBER(L87),K87>0),L87/K87-1,0.2) -> 0.19993542 | O87: =IF(AND(ISNUMBER(K87),ISNUMBER(L87),L87>0),1-K87/L87,0.1666) -> 0.16662181 | P87: =IF(AND(ISNUMBER(J87),ISNUMBER(L87),J87>0),L87/J87-1,"") | S87: рассчитано | Z87: =IF(AND(ISNUMBER(V87),ISNUMBER(Y87),Y87>0),V87/Y87-1,"") | AC87: Лемана Липецк КТО | AD87: project_lemana_4_gipermarketa.md | AE87: Решение к подаче: наценка 20 % (5 лотов = 10,0 млн/мес). Варианты: 50 %, по лотам 30–45 %, по с/с. При штрафе SLA −15 % маржа 2 %. Площади оценочные
A88: 84 | B88: 46265 | C88: ООО «СПАР Миддл Волга» (EUROSPAR) | D88: 8 супермаркетов СПб, 15 016 м² | E88: ТОиР 8 супермаркетов (инж. системы, конструктив, электрика), 8 лотов | F88: СПб | G88: КТО / ТО | H88: ТО и абонентское обслуживание | I88: в месяц | K88: 127134 | L88: 200000 | M88: 244000 | N88: =IF(AND(ISNUMBER(K88),ISNUMBER(L88),K88>0),L88/K88-1,0.573) -> 0.5731433 | O88: =IF(AND(ISNUMBER(K88),ISNUMBER(L88),L88>0),1-K88/L88,0.364) -> 0.36433 | P88: =IF(AND(ISNUMBER(J88),ISNUMBER(L88),J88>0),L88/J88-1,"") | S88: рассчитано | Z88: =IF(AND(ISNUMBER(V88),ISNUMBER(Y88),Y88>0),V88/Y88-1,"") | AC88: Евроспар КТО | AD88: project_spar_spb_toir.md | AE88: Решение к подаче 25 000/мес за магазин (как Перекрёсток), н-ч 1 650, выезд 3 500. Вариант 165 200/мес при наценке 30 %. Кассовый разрыв ~2,5 мес.
A89: 85 | B89: 46266 | C89: ООО «ЛЕ МОНЛИД» (Лемана ПРО) | D89: Лемана ПРО Парнас (139) | E89: КТО гипермаркета, разделы 1–12, Open Book | F89: СПб | G89: КТО / ТО | H89: ТО и абонентское обслуживание | I89: в месяц | L89: 738000 | N89: =IF(AND(ISNUMBER(K89),ISNUMBER(L89),K89>0),L89/K89-1,"") | O89: =IF(AND(ISNUMBER(K89),ISNUMBER(L89),L89>0),1-K89/L89,"") | P89: =IF(AND(ISNUMBER(J89),ISNUMBER(L89),J89>0),L89/J89-1,"") | S89: переторжка | T89: КП-1 (с/с пакета 9,32 млн/мес) → КП-2 после раскрытия цен конкурента, ~−2 % к конкуренту; пакет 5 725 000/мес | W89: ждём итогов | Z89: =IF(AND(ISNUMBER(V89),ISNUMBER(Y89),Y89>0),V89/Y89-1,"") | AC89: Леруа\КП-2 ниже конкурента | AD89: project_lemana_6_objektov_kp2.md | AE89: Пакет: с/с 5,23 млн/мес, маржа 10,3 %; по 4 лотам маржа 0,3–1,9 % (вход под ремонтный поток).
A90: 86 | B90: 46266 | C90: ООО «ЛЕ МОНЛИД» (Лемана ПРО) | D90: Лемана ПРО Екатеринбург (025) | E90: КТО гипермаркета, разделы 1–12, Open Book | F90: Екатеринбург | G90: КТО / ТО | H90: ТО и абонентское обслуживание | I90: в месяц | L90: 957000 | N90: =IF(AND(ISNUMBER(K90),ISNUMBER(L90),K90>0),L90/K90-1,"") | O90: =IF(AND(ISNUMBER(K90),ISNUMBER(L90),L90>0),1-K90/L90,"") | P90: =IF(AND(ISNUMBER(J90),ISNUMBER(L90),J90>0),L90/J90-1,"") | S90: переторжка | T90: КП-1 (с/с пакета 9,32 млн/мес) → КП-2 после раскрытия цен конкурента, ~−2 % к конкуренту; пакет 5 725 000/мес | W90: ждём итогов | Z90: =IF(AND(ISNUMBER(V90),ISNUMBER(Y90),Y90>0),V90/Y90-1,"") | AC90: Леруа\КП-2 ниже конкурента | AD90: project_lemana_6_objektov_kp2.md | AE90: Пакет: с/с 5,23 млн/мес, маржа 10,3 %; по 4 лотам маржа 0,3–1,9 % (вход под ремонтный поток). Раздел 13 (газовая котельная) отдельно 46 200/мес.
A91: 87 | B91: 46266 | C91: ООО «ЛЕ МОНЛИД» (Лемана ПРО) | D91: Лемана ПРО Кемерово (128) | E91: КТО гипермаркета, разделы 1–12, Open Book | F91: Кемерово | G91: КТО / ТО | H91: ТО и абонентское обслуживание | I91: в месяц | L91: 834000 | N91: =IF(AND(ISNUMBER(K91),ISNUMBER(L91),K91>0),L91/K91-1,"") | O91: =IF(AND(ISNUMBER(K91),ISNUMBER(L91),L91>0),1-K91/L91,"") | P91: =IF(AND(ISNUMBER(J91),ISNUMBER(L91),J91>0),L91/J91-1,"") | S91: переторжка | T91: КП-1 (с/с пакета 9,32 млн/мес) → КП-2 после раскрытия цен конкурента, ~−2 % к конкуренту; пакет 5 725 000/мес | W91: ждём итогов | Z91: =IF(AND(ISNUMBER(V91),ISNUMBER(Y91),Y91>0),V91/Y91-1,"") | AC91: Леруа\КП-2 ниже конкурента | AD91: project_lemana_6_objektov_kp2.md | AE91: Пакет: с/с 5,23 млн/мес, маржа 10,3 %; по 4 лотам маржа 0,3–1,9 % (вход под ремонтный поток). Раздел 13 (газовая котельная) отдельно 60 500/мес.
A92: 88 | B92: 46266 | C92: ООО «ЛЕ МОНЛИД» (Лемана ПРО) | D92: Лемана ПРО Краснодар (008) | E92: КТО гипермаркета, разделы 1–12, Open Book | F92: Краснодар | G92: КТО / ТО | H92: ТО и абонентское обслуживание | I92: в месяц | L92: 828000 | N92: =IF(AND(ISNUMBER(K92),ISNUMBER(L92),K92>0),L92/K92-1,"") | O92: =IF(AND(ISNUMBER(K92),ISNUMBER(L92),L92>0),1-K92/L92,"") | P92: =IF(AND(ISNUMBER(J92),ISNUMBER(L92),J92>0),L92/J92-1,"") | S92: переторжка | T92: КП-1 (с/с пакета 9,32 млн/мес) → КП-2 после раскрытия цен конкурента, ~−2 % к конкуренту; пакет 5 725 000/мес | W92: ждём итогов | Z92: =IF(AND(ISNUMBER(V92),ISNUMBER(Y92),Y92>0),V92/Y92-1,"") | AC92: Леруа\КП-2 ниже конкурента | AD92: project_lemana_6_objektov_kp2.md | AE92: Пакет: с/с 5,23 млн/мес, маржа 10,3 %; по 4 лотам маржа 0,3–1,9 % (вход под ремонтный поток).
A93: 89 | B93: 46266 | C93: ООО «ЛЕ МОНЛИД» (Лемана ПРО) | D93: Лемана ПРО Липецк (155) | E93: КТО гипермаркета, разделы 1–12, Open Book | F93: Липецк | G93: КТО / ТО | H93: ТО и абонентское обслуживание | I93: в месяц | L93: 903000 | N93: =IF(AND(ISNUMBER(K93),ISNUMBER(L93),K93>0),L93/K93-1,"") | O93: =IF(AND(ISNUMBER(K93),ISNUMBER(L93),L93>0),1-K93/L93,"") | P93: =IF(AND(ISNUMBER(J93),ISNUMBER(L93),J93>0),L93/J93-1,"") | S93: переторжка | T93: КП-1 (с/с пакета 9,32 млн/мес) → КП-2 после раскрытия цен конкурента, ~−2 % к конкуренту; пакет 5 725 000/мес | W93: ждём итогов | Z93: =IF(AND(ISNUMBER(V93),ISNUMBER(Y93),Y93>0),V93/Y93-1,"") | AC93: Леруа\КП-2 ниже конкурента | AD93: project_lemana_6_objektov_kp2.md | AE93: Пакет: с/с 5,23 млн/мес, маржа 10,3 %; по 4 лотам маржа 0,3–1,9 % (вход под ремонтный поток).
A94: 90 | B94: 46266 | C94: ООО «ЛЕ МОНЛИД» (Лемана ПРО) | D94: Лемана ПРО Челябинск (038) | E94: КТО гипермаркета, разделы 1–12, Open Book | F94: Челябинск | G94: КТО / ТО | H94: ТО и абонентское обслуживание | I94: в месяц | L94: 1465000 | N94: =IF(AND(ISNUMBER(K94),ISNUMBER(L94),K94>0),L94/K94-1,"") | O94: =IF(AND(ISNUMBER(K94),ISNUMBER(L94),L94>0),1-K94/L94,0.346) -> 0.346 | P94: =IF(AND(ISNUMBER(J94),ISNUMBER(L94),J94>0),L94/J94-1,"") | S94: переторжка | T94: КП-1 (с/с пакета 9,32 млн/мес) → КП-2 после раскрытия цен конкурента, ~−2 % к конкуренту; пакет 5 725 000/мес | W94: ждём итогов | Z94: =IF(AND(ISNUMBER(V94),ISNUMBER(Y94),Y94>0),V94/Y94-1,"") | AC94: Леруа\КП-2 ниже конкурента | AD94: project_lemana_6_objektov_kp2.md | AE94: Пакет: с/с 5,23 млн/мес, маржа 10,3 %; по 4 лотам маржа 0,3–1,9 % (вход под ремонтный поток). КП-1 было 2 035 000 б/НДС; конкурент здесь дорогой.
A95: 91 | B95: 46267 | C95: Lamoda (ООО «Купишуз») | D95: 793 объекта в 72 субъектах РФ (ПВЗ, магазины, ТВХ) | E95: ТОиР систем противопожарной защиты | F95: РФ (72 субъекта) | G95: КТО / ТО | H95: ТО и абонентское обслуживание | I95: в год | K95: 32523780 | N95: =IF(AND(ISNUMBER(K95),ISNUMBER(L95),K95>0),L95/K95-1,"") | O95: =IF(AND(ISNUMBER(K95),ISNUMBER(L95),L95>0),1-K95/L95,"") | P95: =IF(AND(ISNUMBER(J95),ISNUMBER(L95),J95>0),L95/J95-1,"") | S95: рассчитано | Z95: =IF(AND(ISNUMBER(V95),ISNUMBER(Y95),Y95>0),V95/Y95-1,"") | AC95: Ламода КТО | AD95: project_lamoda_spz.md | AE95: Рынок ~26,3 млн/год — на 19 % ниже с/с; мин. цена при марже 12 % 36,4 млн. 1-й год с/с 37,37 млн. Штраф 10 %/день без лимита.
A96: 92 | B96: 46267 | C96: ГК ФСК Северо-Запад | D96: ЖК Московское шоссе уч. 179, 3 этап, корпуса 4/5/6 | E96: ЛОТ 126: электроснабжение ЖК, 572 позиции | F96: СПб | G96: СМР / ремонт | H96: Крупные сети и девелоперы — конкурентный тендер | I96: разово | K96: 162847922 | N96: =IF(AND(ISNUMBER(K96),ISNUMBER(L96),K96>0),L96/K96-1,"") | O96: =IF(AND(ISNUMBER(K96),ISNUMBER(L96),L96>0),1-K96/L96,"") | P96: =IF(AND(ISNUMBER(J96),ISNUMBER(L96),J96>0),L96/J96-1,"") | S96: рассчитано | Z96: =IF(AND(ISNUMBER(V96),ISNUMBER(Y96),Y96>0),V96/Y96-1,"") | AC96: ФСК электросети | AD96: project_budgets_sept2026_3folders.md | AE96: Только бюджет с/с (КП — в project_fsk_lot126_kp). Риск двойного счёта работ в форме ФСК (+51 млн без поправки)
A97: 93 | B97: 46267 | C97: ООО «АГМ» | D97: Автозавод, СПб, пос. Шушары, Автозаводская 2 | E97: ТО, диагностика и ремонт 65 ворот и 6 перегрузочных мостов | F97: СПб | G97: КТО / ТО | H97: ТО и абонентское обслуживание | I97: в год | K97: 3234097 | L97: 4204750 | M97: 5129795 | N97: =IF(AND(ISNUMBER(K97),ISNUMBER(L97),K97>0),L97/K97-1,0.3) -> 0.30013107 | O97: =IF(AND(ISNUMBER(K97),ISNUMBER(L97),L97>0),1-K97/L97,0.231) -> 0.23084678 | P97: =IF(AND(ISNUMBER(J97),ISNUMBER(L97),J97>0),L97/J97-1,"") | S97: рассчитано | Z97: =IF(AND(ISNUMBER(V97),ISNUMBER(Y97),Y97>0),V97/Y97-1,"") | AC97: АГМ Ворота | AD97: project_agm_vorota.md | AE97: Оплата по заявкам; периодичность ТО не задана; неустойка 0,1 % от цены договора без предела; бригадо-час 5 900; первый год 4 745 750
A98: 94 | B98: 46267 | C98: ООО «АГС» (Автозавод АГР) | D98: Сестрорецк, Левашовское ш. 20 стр.1, серверная UPS | E98: Замена компрессоров 2 кондиционеров LG + ПНР | F98: СПб | G98: СМР / ремонт | H98: Fit-out, частный бизнес, малые объёмы | I98: разово | K98: 403978 | N98: =IF(AND(ISNUMBER(K98),ISNUMBER(L98),K98>0),L98/K98-1,"") | O98: =IF(AND(ISNUMBER(K98),ISNUMBER(L98),L98>0),1-K98/L98,"") | P98: =IF(AND(ISNUMBER(J98),ISNUMBER(L98),J98>0),L98/J98-1,"") | S98: рассчитано | Z98: =IF(AND(ISNUMBER(V98),ISNUMBER(Y98),Y98>0),V98/Y98-1,"") | AC98: АГМ кондеи | AD98: project_budgets_sept2026_3folders.md | AE98: Только бюджет с/с. Хладагент не указан (принят R22), оригинальных компрессоров LG нет, причина отказа не установлена
A99: 95 | B99: 46268 | C99: АО «Тандер» (Магнит) | D99: ГМ «Магнит», Тосно (4 240 м²) | E99: Капремонт кровли | F99: ЛО | G99: СМР / ремонт | H99: Крупные сети и девелоперы — конкурентный тендер | I99: разово | K99: 13523846 | L99: 19875899 | M99: 24248597 | N99: =IF(AND(ISNUMBER(K99),ISNUMBER(L99),K99>0),L99/K99-1,0.47) -> 0.46969282 | O99: =IF(AND(ISNUMBER(K99),ISNUMBER(L99),L99>0),1-K99/L99,0.32) -> 0.31958571 | P99: =IF(AND(ISNUMBER(J99),ISNUMBER(L99),J99>0),L99/J99-1,"") | Q99: 0.3 | R99: 0.7 | S99: рассчитано | Z99: =IF(AND(ISNUMBER(V99),ISNUMBER(Y99),Y99>0),V99/Y99-1,"") | AC99: Тосно Кровля | AD99: project_tosno_krovlya_kp.md | AE99: Критерий — мин. цена, маржа высокая: при переторжке снижать трудовую часть; толщина утеплителя не задана
A100: 96 | B100: 46268 | C100: ГК ФСК СЗ (ГП ООО «Генеральный Подряд СПб», СЗ «Славянка») | D100: ЖК СЗ «Славянка», корп. 4/5/6 | E100: ЛОТ 126: электроснабжение ЖК по форме ФКП | F100: СПб | G100: СМР / ремонт | H100: Крупные сети и девелоперы — конкурентный тендер | I100: разово | K100: 1.6284792e+08 | L100: 191126171 | M100: 2.3317393e+08 | N100: =IF(AND(ISNUMBER(K100),ISNUMBER(L100),K100>0),L100/K100-1,0.174) -> 0.1736482 | O100: =IF(AND(ISNUMBER(K100),ISNUMBER(L100),L100>0),1-K100/L100,0.148) -> 0.14795592 | P100: =IF(AND(ISNUMBER(J100),ISNUMBER(L100),J100>0),L100/J100-1,"") | Q100: 0.2 | R100: 0.35 | S100: рассчитано | Z100: =IF(AND(ISNUMBER(V100),ISNUMBER(Y100),Y100>0),V100/Y100-1,"") | AC100: ФСК электросети | AD100: project_fsk_lot126_kp.md | AE100: Наценка только на прямые, косвенные 47,3 млн по с/с; срок 01.09–31.12.2026 очень плотный; без аванса, гарантия 5 лет
...

Sheet Аналитика
A1: АНАЛИТИКА: ПРИ КАКОЙ НАЦЕНКЕ МЫ ВЫИГРЫВАЕМ
A2: Считается формулами по листу «Реестр». Колонки результата заполнятся, когда в реестре будут проставлены итоги (РЕЗУЛЬТАТ, цена победителя). Цель — через 15–20 закрытых тендеров откалибровать диапазоны наценки на листе «Тип тендера» файла материалов.
A4: По типу тендера
A5: Тип тендера | B5: Расчётов | C5: Не участвовали | D5: Средняя наценка (все) | E5: Средняя маржа (все) | F5: Ждём итогов | G5: Выиграли | H5: Проиграли | I5: Доля побед | J5: Средняя наценка — выигранные | K5: Средняя наценка — проигранные | L5: Наша цена к победителю (проигранные), среднее
A6: Крупные сети и девелоперы — конкурентный тендер | B6: =COUNTIF(Реестр!$H$5:$H$318,$A6) -> 130 | C6: =COUNTIFS(Реестр!$H$5:$H$318,$A6,Реестр!$S$5:$S$318,"не участвовать") -> 1 | D6: =IFERROR(AVERAGEIFS(Реестр!$N$5:$N$318,Реестр!$H$5:$H$318,$A6,Реестр!$S$5:$S$318,"<>не участвовать"),"") -> 0.39120221 | E6: =IFERROR(AVERAGEIFS(Реестр!$O$5:$O$318,Реестр!$H$5:$H$318,$A6,Реестр!$S$5:$S$318,"<>не участвовать"),"") -> 0.22722002 | F6: =COUNTIFS(Реестр!$H$5:$H$318,$A6,Реестр!$W$5:$W$318,"ждём итогов") -> 5 | G6: =COUNTIFS(Реестр!$H$5:$H$318,$A6,Реестр!$W$5:$W$318,"выиграли") -> 0 | H6: =COUNTIFS(Реестр!$H$5:$H$318,$A6,Реестр!$W$5:$W$318,"проиграли") -> 0 | I6: =IF(G6+H6=0,"",G6/(G6+H6)) | J6: =IFERROR(AVERAGEIFS(Реестр!$N$5:$N$318,Реестр!$H$5:$H$318,$A6,Реестр!$W$5:$W$318,"выиграли"),"") | K6: =IFERROR(AVERAGEIFS(Реестр!$N$5:$N$318,Реестр!$H$5:$H$318,$A6,Реестр!$W$5:$W$318,"проиграли"),"") | L6: =IFERROR(AVERAGEIFS(Реестр!$Z$5:$Z$318,Реестр!$H$5:$H$318,$A6,Реестр!$W$5:$W$318,"проиграли"),"")
A7: Переторжка / 2 тур / вход к новому заказчику | B7: =COUNTIF(Реестр!$H$5:$H$318,$A7) -> 8 | C7: =COUNTIFS(Реестр!$H$5:$H$318,$A7,Реестр!$S$5:$S$318,"не участвовать") -> 0 | D7: =IFERROR(AVERAGEIFS(Реестр!$N$5:$N$318,Реестр!$H$5:$H$318,$A7,Реестр!$S$5:$S$318,"<>не участвовать"),"") -> 0.31983688 | E7: =IFERROR(AVERAGEIFS(Реестр!$O$5:$O$318,Реестр!$H$5:$H$318,$A7,Реестр!$S$5:$S$318,"<>не участвовать"),"") -> 0.22243298 | F7: =COUNTIFS(Реестр!$H$5:$H$318,$A7,Реестр!$W$5:$W$318,"ждём итогов") -> 2 | G7: =COUNTIFS(Реестр!$H$5:$H$318,$A7,Реестр!$W$5:$W$318,"выиграли") -> 0 | H7: =COUNTIFS(Реестр!$H$5:$H$318,$A7,Реестр!$W$5:$W$318,"проиграли") -> 0 | I7: =IF(G7+H7=0,"",G7/(G7+H7)) | J7: =IFERROR(AVERAGEIFS(Реестр!$N$5:$N$318,Реестр!$H$5:$H$318,$A7,Реестр!$W$5:$W$318,"выиграли"),"") | K7: =IFERROR(AVERAGEIFS(Реестр!$N$5:$N$318,Реестр!$H$5:$H$318,$A7,Реестр!$W$5:$W$318,"проиграли"),"") | L7: =IFERROR(AVERAGEIFS(Реестр!$Z$5:$Z$318,Реестр!$H$5:$H$318,$A7,Реестр!$W$5:$W$318,"проиграли"),"")
A8: Fit-out, частный бизнес, малые объёмы | B8: =COUNTIF(Реестр!$H$5:$H$318,$A8) -> 25 | C8: =COUNTIFS(Реестр!$H$5:$H$318,$A8,Реестр!$S$5:$S$318,"не участвовать") -> 0 | D8: =IFERROR(AVERAGEIFS(Реестр!$N$5:$N$318,Реестр!$H$5:$H$318,$A8,Реестр!$S$5:$S$318,"<>не участвовать"),"") -> 0.65207654 | E8: =IFERROR(AVERAGEIFS(Реестр!$O$5:$O$318,Реестр!$H$5:$H$318,$A8,Реестр!$S$5:$S$318,"<>не участвовать"),"") -> 0.35423362 | F8: =COUNTIFS(Реестр!$H$5:$H$318,$A8,Реестр!$W$5:$W$318,"ждём итогов") -> 1 | G8: =COUNTIFS(Реестр!$H$5:$H$318,$A8,Реестр!$W$5:$W$318,"выиграли") -> 0 | H8: =COUNTIFS(Реестр!$H$5:$H$318,$A8,Реестр!$W$5:$W$318,"проиграли") -> 0 | I8: =IF(G8+H8=0,"",G8/(G8+H8)) | J8: =IFERROR(AVERAGEIFS(Реестр!$N$5:$N$318,Реестр!$H$5:$H$318,$A8,Реестр!$W$5:$W$318,"выиграли"),"") | K8: =IFERROR(AVERAGEIFS(Реестр!$N$5:$N$318,Реестр!$H$5:$H$318,$A8,Реестр!$W$5:$W$318,"проиграли"),"") | L8: =IFERROR(AVERAGEIFS(Реестр!$Z$5:$Z$318,Реестр!$H$5:$H$318,$A8,Реестр!$W$5:$W$318,"проиграли"),"")
A9: ТО и абонентское обслуживание | B9: =COUNTIF(Реестр!$H$5:$H$318,$A9) -> 75 | C9: =COUNTIFS(Реестр!$H$5:$H$318,$A9,Реестр!$S$5:$S$318,"не участвовать") -> 1 | D9: =IFERROR(AVERAGEIFS(Реестр!$N$5:$N$318,Реестр!$H$5:$H$318,$A9,Реестр!$S$5:$S$318,"<>не участвовать"),"") -> 0.35019268 | E9: =IFERROR(AVERAGEIFS(Реестр!$O$5:$O$318,Реестр!$H$5:$H$318,$A9,Реестр!$S$5:$S$318,"<>не участвовать"),"") -> 0.2251106 | F9: =COUNTIFS(Реестр!$H$5:$H$318,$A9,Реестр!$W$5:$W$318,"ждём итогов") -> 10 | G9: =COUNTIFS(Реестр!$H$5:$H$318,$A9,Реестр!$W$5:$W$318,"выиграли") -> 0 | H9: =COUNTIFS(Реестр!$H$5:$H$318,$A9,Реестр!$W$5:$W$318,"проиграли") -> 9 | I9: =IF(G9+H9=0,"",G9/(G9+H9)) -> 0 | J9: =IFERROR(AVERAGEIFS(Реестр!$N$5:$N$318,Реестр!$H$5:$H$318,$A9,Реестр!$W$5:$W$318,"выиграли"),"") | K9: =IFERROR(AVERAGEIFS(Реестр!$N$5:$N$318,Реестр!$H$5:$H$318,$A9,Реестр!$W$5:$W$318,"проиграли"),"") | L9: =IFERROR(AVERAGEIFS(Реестр!$Z$5:$Z$318,Реестр!$H$5:$H$318,$A9,Реестр!$W$5:$W$318,"проиграли"),"")
A10: Госзакупки 44-ФЗ / 223-ФЗ | B10: =COUNTIF(Реестр!$H$5:$H$318,$A10) -> 62 | C10: =COUNTIFS(Реестр!$H$5:$H$318,$A10,Реестр!$S$5:$S$318,"не участвовать") -> 17 | D10: =IFERROR(AVERAGEIFS(Реестр!$N$5:$N$318,Реестр!$H$5:$H$318,$A10,Реестр!$S$5:$S$318,"<>не участвовать"),"") -> 0.32657362 | E10: =IFERROR(AVERAGEIFS(Реестр!$O$5:$O$318,Реестр!$H$5:$H$318,$A10,Реестр!$S$5:$S$318,"<>не участвовать"),"") -> 0.23911797 | F10: =COUNTIFS(Реестр!$H$5:$H$318,$A10,Реестр!$W$5:$W$318,"ждём итогов") -> 0 | G10: =COUNTIFS(Реестр!$H$5:$H$318,$A10,Реестр!$W$5:$W$318,"выиграли") -> 0 | H10: =COUNTIFS(Реестр!$H$5:$H$318,$A10,Реестр!$W$5:$W$318,"проиграли") -> 0 | I10: =IF(G10+H10=0,"",G10/(G10+H10)) | J10: =IFERROR(AVERAGEIFS(Реестр!$N$5:$N$318,Реестр!$H$5:$H$318,$A10,Реестр!$W$5:$W$318,"выиграли"),"") | K10: =IFERROR(AVERAGEIFS(Реестр!$N$5:$N$318,Реестр!$H$5:$H$318,$A10,Реестр!$W$5:$W$318,"проиграли"),"") | L10: =IFERROR(AVERAGEIFS(Реестр!$Z$5:$Z$318,Реестр!$H$5:$H$318,$A10,Реестр!$W$5:$W$318,"проиграли"),"")
A11: ИТОГО | B11: =SUM(B6:B10) -> 300 | C11: =SUM(C6:C10) -> 19 | F11: =SUM(F6:F10) -> 18 | G11: =SUM(G6:G10) -> 0 | H11: =SUM(H6:H10) -> 9
A14: По виду работ
A15: Вид работ | B15: Расчётов | C15: Не участвовали | D15: Средняя наценка (все) | E15: Средняя маржа (все) | F15: Ждём итогов | G15: Выиграли | H15: Проиграли | I15: Доля побед | J15: Средняя наценка — выигранные | K15: Средняя наценка — проигранные | L15: Наша цена к победителю (проигранные), среднее
A16: СМР / ремонт | B16: =COUNTIF(Реестр!$G$5:$G$318,$A16) -> 131 | C16: =COUNTIFS(Реестр!$G$5:$G$318,$A16,Реестр!$S$5:$S$318,"не участвовать") -> 6 | D16: =IFERROR(AVERAGEIFS(Реестр!$N$5:$N$318,Реестр!$G$5:$G$318,$A16,Реестр!$S$5:$S$318,"<>не участвовать"),"") -> 0.41650876 | E16: =IFERROR(AVERAGEIFS(Реестр!$O$5:$O$318,Реестр!$G$5:$G$318,$A16,Реестр!$S$5:$S$318,"<>не участвовать"),"") -> 0.28370905 | F16: =COUNTIFS(Реестр!$G$5:$G$318,$A16,Реестр!$W$5:$W$318,"ждём итогов") -> 6 | G16: =COUNTIFS(Реестр!$G$5:$G$318,$A16,Реестр!$W$5:$W$318,"выиграли") -> 0 | H16: =COUNTIFS(Реестр!$G$5:$G$318,$A16,Реестр!$W$5:$W$318,"проиграли") -> 0 | I16: =IF(G16+H16=0,"",G16/(G16+H16)) | J16: =IFERROR(AVERAGEIFS(Реестр!$N$5:$N$318,Реестр!$G$5:$G$318,$A16,Реестр!$W$5:$W$318,"выиграли"),"") | K16: =IFERROR(AVERAGEIFS(Реестр!$N$5:$N$318,Реестр!$G$5:$G$318,$A16,Реестр!$W$5:$W$318,"проиграли"),"") | L16: =IFERROR(AVERAGEIFS(Реестр!$Z$5:$Z$318,Реестр!$G$5:$G$318,$A16,Реестр!$W$5:$W$318,"проиграли"),"")
A17: Fit-out | B17: =COUNTIF(Реестр!$G$5:$G$318,$A17) -> 12 | C17: =COUNTIFS(Реестр!$G$5:$G$318,$A17,Реестр!$S$5:$S$318,"не участвовать") -> 0 | D17: =IFERROR(AVERAGEIFS(Реестр!$N$5:$N$318,Реестр!$G$5:$G$318,$A17,Реестр!$S$5:$S$318,"<>не участвовать"),"") -> 0.6740113 | E17: =IFERROR(AVERAGEIFS(Реестр!$O$5:$O$318,Реестр!$G$5:$G$318,$A17,Реестр!$S$5:$S$318,"<>не участвовать"),"") -> 0.34156961 | F17: =COUNTIFS(Реестр!$G$5:$G$318,$A17,Реестр!$W$5:$W$318,"ждём итогов") -> 0 | G17: =COUNTIFS(Реестр!$G$5:$G$318,$A17,Реестр!$W$5:$W$318,"выиграли") -> 0 | H17: =COUNTIFS(Реестр!$G$5:$G$318,$A17,Реестр!$W$5:$W$318,"проиграли") -> 0 | I17: =IF(G17+H17=0,"",G17/(G17+H17)) | J17: =IFERROR(AVERAGEIFS(Реестр!$N$5:$N$318,Реестр!$G$5:$G$318,$A17,Реестр!$W$5:$W$318,"выиграли"),"") | K17: =IFERROR(AVERAGEIFS(Реестр!$N$5:$N$318,Реестр!$G$5:$G$318,$A17,Реестр!$W$5:$W$318,"проиграли"),"") | L17: =IFERROR(AVERAGEIFS(Реестр!$Z$5:$Z$318,Реестр!$G$5:$G$318,$A17,Реестр!$W$5:$W$318,"проиграли"),"")
A18: КТО / ТО | B18: =COUNTIF(Реестр!$G$5:$G$318,$A18) -> 107 | C18: =COUNTIFS(Реестр!$G$5:$G$318,$A18,Реестр!$S$5:$S$318,"не участвовать") -> 11 | D18: =IFERROR(AVERAGEIFS(Реестр!$N$5:$N$318,Реестр!$G$5:$G$318,$A18,Реестр!$S$5:$S$318,"<>не участвовать"),"") -> 0.34870728 | E18: =IFERROR(AVERAGEIFS(Реестр!$O$5:$O$318,Реестр!$G$5:$G$318,$A18,Реестр!$S$5:$S$318,"<>не участвовать"),"") -> 0.1611856 | F18: =COUNTIFS(Реестр!$G$5:$G$318,$A18,Реестр!$W$5:$W$318,"ждём итогов") -> 10 | G18: =COUNTIFS(Реестр!$G$5:$G$318,$A18,Реестр!$W$5:$W$318,"выиграли") -> 0 | H18: =COUNTIFS(Реестр!$G$5:$G$318,$A18,Реестр!$W$5:$W$318,"проиграли") -> 9 | I18: =IF(G18+H18=0,"",G18/(G18+H18)) -> 0 | J18: =IFERROR(AVERAGEIFS(Реестр!$N$5:$N$318,Реестр!$G$5:$G$318,$A18,Реестр!$W$5:$W$318,"выиграли"),"") | K18: =IFERROR(AVERAGEIFS(Реестр!$N$5:$N$318,Реестр!$G$5:$G$318,$A18,Реестр!$W$5:$W$318,"проиграли"),"") | L18: =IFERROR(AVERAGEIFS(Реестр!$Z$5:$Z$318,Реестр!$G$5:$G$318,$A18,Реестр!$W$5:$W$318,"проиграли"),"")
A19: Рамочные расценки | B19: =COUNTIF(Реестр!$G$5:$G$318,$A19) -> 11 | C19: =COUNTIFS(Реестр!$G$5:$G$318,$A19,Реестр!$S$5:$S$318,"не участвовать") -> 0 | D19: =IFERROR(AVERAGEIFS(Реестр!$N$5:$N$318,Реестр!$G$5:$G$318,$A19,Реестр!$S$5:$S$318,"<>не участвовать"),"") -> 0.35819824 | E19: =IFERROR(AVERAGEIFS(Реестр!$O$5:$O$318,Реестр!$G$5:$G$318,$A19,Реестр!$S$5:$S$318,"<>не участвовать"),"") -> 0.24813785 | F19: =COUNTIFS(Реестр!$G$5:$G$318,$A19,Реестр!$W$5:$W$318,"ждём итогов") -> 1 | G19: =COUNTIFS(Реестр!$G$5:$G$318,$A19,Реестр!$W$5:$W$318,"выиграли") -> 0 | H19: =COUNTIFS(Реестр!$G$5:$G$318,$A19,Реестр!$W$5:$W$318,"проиграли") -> 0 | I19: =IF(G19+H19=0,"",G19/(G19+H19)) | J19: =IFERROR(AVERAGEIFS(Реестр!$N$5:$N$318,Реестр!$G$5:$G$318,$A19,Реестр!$W$5:$W$318,"выиграли"),"") | K19: =IFERROR(AVERAGEIFS(Реестр!$N$5:$N$318,Реестр!$G$5:$G$318,$A19,Реестр!$W$5:$W$318,"проиграли"),"") | L19: =IFERROR(AVERAGEIFS(Реестр!$Z$5:$Z$318,Реестр!$G$5:$G$318,$A19,Реестр!$W$5:$W$318,"проиграли"),"")
A20: Поставка и монтаж | B20: =COUNTIF(Реестр!$G$5:$G$318,$A20) -> 13 | C20: =COUNTIFS(Реестр!$G$5:$G$318,$A20,Реестр!$S$5:$S$318,"не участвовать") -> 0 | D20: =IFERROR(AVERAGEIFS(Реестр!$N$5:$N$318,Реестр!$G$5:$G$318,$A20,Реестр!$S$5:$S$318,"<>не участвовать"),"") -> 0.36143126 | E20: =IFERROR(AVERAGEIFS(Реестр!$O$5:$O$318,Реестр!$G$5:$G$318,$A20,Реестр!$S$5:$S$318,"<>не участвовать"),"") -> 0.26381181 | F20: =COUNTIFS(Реестр!$G$5:$G$318,$A20,Реестр!$W$5:$W$318,"ждём итогов") -> 1 | G20: =COUNTIFS(Реестр!$G$5:$G$318,$A20,Реестр!$W$5:$W$318,"выиграли") -> 0 | H20: =COUNTIFS(Реестр!$G$5:$G$318,$A20,Реестр!$W$5:$W$318,"проиграли") -> 0 | I20: =IF(G20+H20=0,"",G20/(G20+H20)) | J20: =IFERROR(AVERAGEIFS(Реестр!$N$5:$N$318,Реестр!$G$5:$G$318,$A20,Реестр!$W$5:$W$318,"выиграли"),"") | K20: =IFERROR(AVERAGEIFS(Реестр!$N$5:$N$318,Реестр!$G$5:$G$318,$A20,Реестр!$W$5:$W$318,"проиграли"),"") | L20: =IFERROR(AVERAGEIFS(Реестр!$Z$5:$Z$318,Реестр!$G$5:$G$318,$A20,Реестр!$W$5:$W$318,"проиграли"),"")
A21: ПИР+СМР | B21: =COUNTIF(Реестр!$G$5:$G$318,$A21) -> 11 | C21: =COUNTIFS(Реестр!$G$5:$G$318,$A21,Реестр!$S$5:$S$318,"не участвовать") -> 0 | D21: =IFERROR(AVERAGEIFS(Реестр!$N$5:$N$318,Реестр!$G$5:$G$318,$A21,Реестр!$S$5:$S$318,"<>не участвовать"),"") -> 0.41889296 | E21: =IFERROR(AVERAGEIFS(Реестр!$O$5:$O$318,Реестр!$G$5:$G$318,$A21,Реестр!$S$5:$S$318,"<>не участвовать"),"") -> 0.28410036 | F21: =COUNTIFS(Реестр!$G$5:$G$318,$A21,Реестр!$W$5:$W$318,"ждём итогов") -> 0 | G21: =COUNTIFS(Реестр!$G$5:$G$318,$A21,Реестр!$W$5:$W$318,"выиграли") -> 0 | H21: =COUNTIFS(Реестр!$G$5:$G$318,$A21,Реестр!$W$5:$W$318,"проиграли") -> 0 | I21: =IF(G21+H21=0,"",G21/(G21+H21)) | J21: =IFERROR(AVERAGEIFS(Реестр!$N$5:$N$318,Реестр!$G$5:$G$318,$A21,Реестр!$W$5:$W$318,"выиграли"),"") | K21: =IFERROR(AVERAGEIFS(Реестр!$N$5:$N$318,Реестр!$G$5:$G$318,$A21,Реестр!$W$5:$W$318,"проиграли"),"") | L21: =IFERROR(AVERAGEIFS(Реестр!$Z$5:$Z$318,Реестр!$G$5:$G$318,$A21,Реестр!$W$5:$W$318,"проиграли"),"")
A22: Другое | B22: =COUNTIF(Реестр!$G$5:$G$318,$A22) -> 4 | C22: =COUNTIFS(Реестр!$G$5:$G$318,$A22,Реестр!$S$5:$S$318,"не участвовать") -> 0 | D22: =IFERROR(AVERAGEIFS(Реестр!$N$5:$N$318,Реестр!$G$5:$G$318,$A22,Реестр!$S$5:$S$318,"<>не участвовать"),"") -> 0.36910972 | E22: =IFERROR(AVERAGEIFS(Реестр!$O$5:$O$318,Реестр!$G$5:$G$318,$A22,Реестр!$S$5:$S$318,"<>не участвовать"),"") -> 0.28582623 | F22: =COUNTIFS(Реестр!$G$5:$G$318,$A22,Реестр!$W$5:$W$318,"ждём итогов") -> 0 | G22: =COUNTIFS(Реестр!$G$5:$G$318,$A22,Реестр!$W$5:$W$318,"выиграли") -> 0 | H22: =COUNTIFS(Реестр!$G$5:$G$318,$A22,Реестр!$W$5:$W$318,"проиграли") -> 0 | I22: =IF(G22+H22=0,"",G22/(G22+H22)) | J22: =IFERROR(AVERAGEIFS(Реестр!$N$5:$N$318,Реестр!$G$5:$G$318,$A22,Реестр!$W$5:$W$318,"выиграли"),"") | K22: =IFERROR(AVERAGEIFS(Реестр!$N$5:$N$318,Реестр!$G$5:$G$318,$A22,Реестр!$W$5:$W$318,"проиграли"),"") | L22: =IFERROR(AVERAGEIFS(Реестр!$Z$5:$Z$318,Реестр!$G$5:$G$318,$A22,Реестр!$W$5:$W$318,"проиграли"),"")
A23: ИТОГО | B23: =SUM(B16:B22) -> 289 | C23: =SUM(C16:C22) -> 17 | F23: =SUM(F16:F22) -> 18 | G23: =SUM(G16:G22) -> 0 | H23: =SUM(H16:H22) -> 9
A26: Как читать: если «средняя наценка — выигранные» стабильно ниже целевого диапазона — диапазон завышен; если проигрываем с ценой выше победителя на 5–10 % — снижать наценку на работы в этом типе тендеров.

Sheet Как вести
A1: КАК ВЕСТИ РЕЕСТР
A2: 1. Новый тендер добавляется в реестр после каждого расчёта (шаг 12 промта «Расчёт тендера и КП»): дата, заказчик, объект, тип, с/с, КП, наценка, решение.
A3: 2. После подачи — отдел тендеров ставит дату подачи и нашу финальную цену (после переторжки — последнюю).
A4: 3. После итогов — РЕЗУЛЬТАТ (выиграли / проиграли / отменён), место, цену победителя и число участников, причину проигрыша (цена, квалификация, сроки, отказ заказчика).
A5: 4. Цену победителя спрашивать у организатора или смотреть в протоколе (на ЭТП она обычно публикуется). Без неё нельзя понять, насколько мы дороже рынка.
A6: 5. Раз в месяц смотреть лист «Аналитика»: доля побед и наценка выигранных тендеров по типам — по ним корректируем целевые диапазоны наценки.
A7: Синие колонки заполнены по расчётам в памяти Claude (июль–октябрь 2026). Решение «подано» стоит только там, где подача была явно зафиксирована; РЕЗУЛЬТАТ пуст, если неизвестно, подавали ли; по остальным «рассчитано» — проверьте и поправьте статус.
A8: Наценка/маржа: формула из с/с и КП; если какой-то из сумм нет — подставлено значение из расчёта. Периоды разные (разово / в месяц / в год) — суммы между строками не складывать.

Sheet Списки
A1: Крупные сети и девелоперы — конкурентный тендер
A2: Переторжка / 2 тур / вход к новому заказчику
A3: Fit-out, частный бизнес, малые объёмы
A4: ТО и абонентское обслуживание
A5: Госзакупки 44-ФЗ / 223-ФЗ
