Workbook

Sheet Расценки
A1: ТАРИФИКАТОР НЕОСТРОЙ v2 — рыночные расценки, оплата бригадам и маржа
A2: Только работа, без материалов и оборудования · руб. без НДС · октябрь 2026. Бригада = выплата ИП/самозанятому за единицу, включая их налог 6 %. Цена НЕОСТРОЙ = рыночная цена; если при оплате бригаде по нормо-часам (норма × ставка часа) маржа ниже порога в F3 — цена поднята выше рынка до этого порога (подсвечено: светло — до +10 % к рынку, оранжевый — +10…30 %, красный — больше +30 %). Маржа = (цена НЕОСТРОЙ − оплата бригаде) ÷ цена НЕОСТРОЙ. Зелёные артикулы — новые работы.
B3: Минимальная маржа при оплате бригаде по нормо-часам (ниже — цена НЕОСТРОЙ поднимается над рынком): | F3: 0.25
A4: Артикул | B4: Вид работ | C4: Ед. изм. | D4: Новая | E4: Специальность (код) | F4: Рынок СПб, руб/ед. | G4: Рынок Мск, руб/ед. | H4: ЦЕНА НЕОСТРОЙ СПб, руб/ед. | I4: ЦЕНА НЕОСТРОЙ Мск, руб/ед. | J4: Цена НЕОСТРОЙ выше рынка СПб, % | K4: Цена НЕОСТРОЙ выше рынка Мск, % | L4: Оплата бригаде СПб (ИП/СЗ, вкл. 6 %) | M4: Оплата бригаде Мск (ИП/СЗ, вкл. 6 %) | N4: Маржа СПб, % | O4: Маржа Мск, % | P4: Маржа СПб, руб/ед. | Q4: Маржа Мск, руб/ед. | R4: Старый тарификатор: оплата бригаде | S4: Старый тарификатор: цена (+35 %) | T4: Старая цена ÷ рынок СПб | U4: Источник цены | V4: Примечание
A5: 1.1 Демонтаж зданий, строений, сооружений
A6: 1.1.1 | B6: Разборка покрытий и оснований асфальтобетонных | C6: м3 | E6: BLG | F6: 3500 | G6: 4025 | H6: =IF(OR(F6="",F6=0),"",MAX(F6,IF(ISNUMBER('Нормы и нормо-часы'!K7),ROUNDUP('Нормы и нормо-часы'!K7/(1-$F$3),0),0))) -> 3500 | I6: =IF(OR(G6="",G6=0),"",MAX(G6,IF(ISNUMBER('Нормы и нормо-часы'!L7),ROUNDUP('Нормы и нормо-часы'!L7/(1-$F$3),0),0))) -> 4025 | J6: =IF(OR(F6="",F6=0),"",H6/F6-1) -> 0 | K6: =IF(OR(G6="",G6=0),"",I6/G6-1) -> 0 | L6: 2100 | M6: 2415 | N6: =IF(OR(H6="",H6=0),"",(H6-L6)/H6) -> 0.4 | O6: =IF(OR(I6="",I6=0),"",(I6-M6)/I6) -> 0.4 | P6: =IF(H6="","",H6-L6) -> 1400 | Q6: =IF(I6="","",I6-M6) -> 1610 | R6: 5162.06 | S6: 6968.78 | T6: =IF(OR(S6="",F6="",F6=0),"",S6/F6) -> 1.99108 | U6: аналог zakazstroy.ru 120 руб/м2 при 5 см (мех.), ручная ×1,4 | V6: Наш тариф ~2× рынка; при площадях >100 м2 выгоднее фрезерование/экскаватор с гидромолотом (100–200 руб/м2)
A7: 1.1.2 | B7: Демонтаж деревянных зданий и строений без сохранения годного материала | C7: м3 здания | E7: RAZ | F7: 1000 | G7: 1300 | H7: =IF(OR(F7="",F7=0),"",MAX(F7,IF(ISNUMBER('Нормы и нормо-часы'!K8),ROUNDUP('Нормы и нормо-часы'!K8/(1-$F$3),0),0))) -> 1000 | I7: =IF(OR(G7="",G7=0),"",MAX(G7,IF(ISNUMBER('Нормы и нормо-часы'!L8),ROUNDUP('Нормы и нормо-часы'!L8/(1-$F$3),0),0))) -> 1300 | J7: =IF(OR(F7="",F7=0),"",H7/F7-1) -> 0 | K7: =IF(OR(G7="",G7=0),"",I7/G7-1) -> 0 | L7: 600 | M7: 768 | N7: =IF(OR(H7="",H7=0),"",(H7-L7)/H7) -> 0.4 | O7: =IF(OR(I7="",I7=0),"",(I7-M7)/I7) -> 0.40923077 | P7: =IF(H7="","",H7-L7) -> 400 | Q7: =IF(I7="","",I7-M7) -> 532 | R7: 1479.19 | S7: 1996.91 | T7: =IF(OR(S7="",F7="",F7=0),"",S7/F7) -> 1.99691 | U7: прайс moskva-demontazh.ru (дер. дом от 1300/м3, МСК) | V7: Ед. — м3 строительного объёма здания; вывоз не входит
A8: 1.1.3 | B8: Демонтаж зданий и строений из металлоконструкций без сохранения годного материала | C8: т | E8: SVA | F8: 6500 | G8: 7475 | H8: =IF(OR(F8="",F8=0),"",MAX(F8,IF(ISNUMBER('Нормы и нормо-часы'!K9),ROUNDUP('Нормы и нормо-часы'!K9/(1-$F$3),0),0))) -> 12000 | I8: =IF(OR(G8="",G8=0),"",MAX(G8,IF(ISNUMBER('Нормы и нормо-часы'!L9),ROUNDUP('Нормы и нормо-часы'!L9/(1-$F$3),0),0))) -> 14400 | J8: =IF(OR(F8="",F8=0),"",H8/F8-1) -> 0.84615385 | K8: =IF(OR(G8="",G8=0),"",I8/G8-1) -> 0.9264214 | L8: 3900 | M8: 4485 | N8: =IF(OR(H8="",H8=0),"",(H8-L8)/H8) -> 0.675 | O8: =IF(OR(I8="",I8=0),"",(I8-M8)/I8) -> 0.68854167 | P8: =IF(H8="","",H8-L8) -> 8100 | Q8: =IF(I8="","",I8-M8) -> 9915 | R8: 8588.95 | S8: 11595.08 | T8: =IF(OR(S8="",F8="",F8=0),"",S8/F8) -> 1.7838585 | U8: аналог moskva-demontazh.ru (МК от 4000 руб/т МСК, мех.) | V8: Газорезка без сохранения; кран/автовышка оплачиваются отдельно
A9: 1.1.4 | B9: Демонтаж каменных зданий и строений (кирпич, бетон, железобетон) комплексная работа с сохранением годного материала | C9: м3 | E9: RAZ | F9: 4200 | G9: 4830 | H9: =IF(OR(F9="",F9=0),"",MAX(F9,IF(ISNUMBER('Нормы и нормо-часы'!K10),ROUNDUP('Нормы и нормо-часы'!K10/(1-$F$3),0),0))) -> 4767 | I9: =IF(OR(G9="",G9=0),"",MAX(G9,IF(ISNUMBER('Нормы и нормо-часы'!L10),ROUNDUP('Нормы и нормо-часы'!L10/(1-$F$3),0),0))) -> 5720 | J9: =IF(OR(F9="",F9=0),"",H9/F9-1) -> 0.135 | K9: =IF(OR(G9="",G9=0),"",I9/G9-1) -> 0.18426501 | L9: 2500 | M9: 2875 | N9: =IF(OR(H9="",H9=0),"",(H9-L9)/H9) -> 0.47556115 | O9: =IF(OR(I9="",I9=0),"",(I9-M9)/I9) -> 0.49737762 | P9: =IF(H9="","",H9-L9) -> 2267 | Q9: =IF(I9="","",I9-M9) -> 2845 | R9: 2294.25 | S9: 3097.24 | T9: =IF(OR(S9="",F9="",F9=0),"",S9/F9) -> 0.7374381 | U9: аналог zakazstroy.ru (кирп. стены от 1800/м3 мех.), ручная с сохранением ×2,3 | V9: Неясно м3 конструкций или строит. объёма; цена дана на м3 кладки/конструкций
A10: 1.1.5 | B10: Разборка бортовых камней с сохранением камня пригодного для дальнейшего использования | C10: мп | E10: BLG | F10: 350 | G10: 402 | H10: =IF(OR(F10="",F10=0),"",MAX(F10,IF(ISNUMBER('Нормы и нормо-часы'!K11),ROUNDUP('Нормы и нормо-часы'!K11/(1-$F$3),0),0))) -> 350 | I10: =IF(OR(G10="",G10=0),"",MAX(G10,IF(ISNUMBER('Нормы и нормо-часы'!L11),ROUNDUP('Нормы и нормо-часы'!L11/(1-$F$3),0),0))) -> 402 | J10: =IF(OR(F10="",F10=0),"",H10/F10-1) -> 0 | K10: =IF(OR(G10="",G10=0),"",I10/G10-1) -> 0 | L10: 200 | M10: 230 | N10: =IF(OR(H10="",H10=0),"",(H10-L10)/H10) -> 0.42857143 | O10: =IF(OR(I10="",I10=0),"",(I10-M10)/I10) -> 0.4278607 | P10: =IF(H10="","",H10-L10) -> 150 | Q10: =IF(I10="","",I10-M10) -> 172 | R10: 543.38 | S10: 733.56 | T10: =IF(OR(S10="",F10="",F10=0),"",S10/F10) -> 2.0958857 | U10: аналог zakazstroy.ru 160–200 руб/мп с вывозом (крупные объёмы)
A11: 1.1.6 | B11: Разборка тротуаров и дорожек из плит бетонных, брусчатки с сохранением пригодных для дальнейшего использования | C11: м2 | E11: BLG | F11: 250 | G11: 288 | H11: =IF(OR(F11="",F11=0),"",MAX(F11,IF(ISNUMBER('Нормы и нормо-часы'!K12),ROUNDUP('Нормы и нормо-часы'!K12/(1-$F$3),0),0))) -> 260 | I11: =IF(OR(G11="",G11=0),"",MAX(G11,IF(ISNUMBER('Нормы и нормо-часы'!L12),ROUNDUP('Нормы и нормо-часы'!L12/(1-$F$3),0),0))) -> 312 | J11: =IF(OR(F11="",F11=0),"",H11/F11-1) -> 0.04 | K11: =IF(OR(G11="",G11=0),"",I11/G11-1) -> 0.083333333 | L11: 150 | M11: 172 | N11: =IF(OR(H11="",H11=0),"",(H11-L11)/H11) -> 0.42307692 | O11: =IF(OR(I11="",I11=0),"",(I11-M11)/I11) -> 0.44871795 | P11: =IF(H11="","",H11-L11) -> 110 | Q11: =IF(I11="","",I11-M11) -> 140 | R11: 256.8 | S11: 346.68 | T11: =IF(OR(S11="",F11="",F11=0),"",S11/F11) -> 1.38672 | U11: аналог zakazstroy.ru 100 руб/м2 (без сохранения)
A12: 1.1.N1 | B12: Разборка асфальтобетонного покрытия толщиной до 5 см отбойными молотками | C12: м2 | D12: да | E12: BLG | F12: 200 | G12: 230 | H12: =IF(OR(F12="",F12=0),"",MAX(F12,IF(ISNUMBER('Нормы и нормо-часы'!K13),ROUNDUP('Нормы и нормо-часы'!K13/(1-$F$3),0),0))) -> 200 | I12: =IF(OR(G12="",G12=0),"",MAX(G12,IF(ISNUMBER('Нормы и нормо-часы'!L13),ROUNDUP('Нормы и нормо-часы'!L13/(1-$F$3),0),0))) -> 230 | J12: =IF(OR(F12="",F12=0),"",H12/F12-1) -> 0 | K12: =IF(OR(G12="",G12=0),"",I12/G12-1) -> 0 | L12: 120 | M12: 138 | N12: =IF(OR(H12="",H12=0),"",(H12-L12)/H12) -> 0.4 | O12: =IF(OR(I12="",I12=0),"",(I12-M12)/I12) -> 0.4 | P12: =IF(H12="","",H12-L12) -> 80 | Q12: =IF(I12="","",I12-M12) -> 92 | T12: =IF(OR(S12="",F12="",F12=0),"",S12/F12) | U12: аналог zakazstroy.ru 120 руб/м2 (мех.)
A13: 1.1.N2 | B13: Демонтаж бетонных дорожных плит (ПАГ, 2П) с погрузкой | C13: м2 | D13: да | E13: BLG | F13: 460 | G13: 529 | H13: =IF(OR(F13="",F13=0),"",MAX(F13,IF(ISNUMBER('Нормы и нормо-часы'!K14),ROUNDUP('Нормы и нормо-часы'!K14/(1-$F$3),0),0))) -> 460 | I13: =IF(OR(G13="",G13=0),"",MAX(G13,IF(ISNUMBER('Нормы и нормо-часы'!L14),ROUNDUP('Нормы и нормо-часы'!L14/(1-$F$3),0),0))) -> 529 | J13: =IF(OR(F13="",F13=0),"",H13/F13-1) -> 0 | K13: =IF(OR(G13="",G13=0),"",I13/G13-1) -> 0 | L13: 280 | M13: 322 | N13: =IF(OR(H13="",H13=0),"",(H13-L13)/H13) -> 0.39130435 | O13: =IF(OR(I13="",I13=0),"",(I13-M13)/I13) -> 0.39130435 | P13: =IF(H13="","",H13-L13) -> 180 | Q13: =IF(I13="","",I13-M13) -> 207 | T13: =IF(OR(S13="",F13="",F13=0),"",S13/F13) | U13: прайс zakazstroy.ru 460 руб/м2 | V13: Кран/манипулятор отдельно
A14: 1.1.N3 | B14: Демонтаж ограждения из сетки/профлиста со стойками | C14: мп | D14: да | E14: SVA | F14: 300 | G14: 345 | H14: =IF(OR(F14="",F14=0),"",MAX(F14,IF(ISNUMBER('Нормы и нормо-часы'!K15),ROUNDUP('Нормы и нормо-часы'!K15/(1-$F$3),0),0))) -> 480 | I14: =IF(OR(G14="",G14=0),"",MAX(G14,IF(ISNUMBER('Нормы и нормо-часы'!L15),ROUNDUP('Нормы и нормо-часы'!L15/(1-$F$3),0),0))) -> 576 | J14: =IF(OR(F14="",F14=0),"",H14/F14-1) -> 0.6 | K14: =IF(OR(G14="",G14=0),"",I14/G14-1) -> 0.66956522 | L14: 180 | M14: 207 | N14: =IF(OR(H14="",H14=0),"",(H14-L14)/H14) -> 0.625 | O14: =IF(OR(I14="",I14=0),"",(I14-M14)/I14) -> 0.640625 | P14: =IF(H14="","",H14-L14) -> 300 | Q14: =IF(I14="","",I14-M14) -> 369 | T14: =IF(OR(S14="",F14="",F14=0),"",S14/F14) | U14: аналог zakazstroy.ru (ж/б заборы 800 руб/мп)
A15: 1.2 Демонтажные работы по фасаду
A16: 1.2.1 | B16: Отбивка штукатурки с поверхностей стен | C16: м2 | E16: RAZ | F16: 300 | G16: 345 | H16: =IF(OR(F16="",F16=0),"",MAX(F16,IF(ISNUMBER('Нормы и нормо-часы'!K17),ROUNDUP('Нормы и нормо-часы'!K17/(1-$F$3),0),0))) -> 300 | I16: =IF(OR(G16="",G16=0),"",MAX(G16,IF(ISNUMBER('Нормы и нормо-часы'!L17),ROUNDUP('Нормы и нормо-часы'!L17/(1-$F$3),0),0))) -> 345 | J16: =IF(OR(F16="",F16=0),"",H16/F16-1) -> 0 | K16: =IF(OR(G16="",G16=0),"",I16/G16-1) -> 0 | L16: 180 | M16: 207 | N16: =IF(OR(H16="",H16=0),"",(H16-L16)/H16) -> 0.4 | O16: =IF(OR(I16="",I16=0),"",(I16-M16)/I16) -> 0.4 | P16: =IF(H16="","",H16-L16) -> 120 | Q16: =IF(I16="","",I16-M16) -> 138 | R16: 217.35 | S16: 293.42 | T16: =IF(OR(S16="",F16="",F16=0),"",S16/F16) -> 0.97806667 | U16: прайс remontvspb.ru 200–500, stroygarant78.ru 220 руб/м2
A17: 1.2.2 | B17: Демонтаж облицовки из профилированного листа без разборки каркаса | C17: м2 | E17: RAZ | F17: 250 | G17: 288 | H17: =IF(OR(F17="",F17=0),"",MAX(F17,IF(ISNUMBER('Нормы и нормо-часы'!K18),ROUNDUP('Нормы и нормо-часы'!K18/(1-$F$3),0),0))) -> 250 | I17: =IF(OR(G17="",G17=0),"",MAX(G17,IF(ISNUMBER('Нормы и нормо-часы'!L18),ROUNDUP('Нормы и нормо-часы'!L18/(1-$F$3),0),0))) -> 288 | J17: =IF(OR(F17="",F17=0),"",H17/F17-1) -> 0 | K17: =IF(OR(G17="",G17=0),"",I17/G17-1) -> 0 | L17: 150 | M17: 172 | N17: =IF(OR(H17="",H17=0),"",(H17-L17)/H17) -> 0.4 | O17: =IF(OR(I17="",I17=0),"",(I17-M17)/I17) -> 0.40277778 | P17: =IF(H17="","",H17-L17) -> 100 | Q17: =IF(I17="","",I17-M17) -> 116 | R17: 244.52 | S17: 330.1 | T17: =IF(OR(S17="",F17="",F17=0),"",S17/F17) -> 1.3204 | U17: аналог spb.rsk-uteplitel.ru (профлист кровли 60–240 руб/м2) | V17: Работа с вышки/подъёмника — техника отдельно
A18: 1.2.3 | B18: Демонтаж облицовки из профилированного листа с разборкой каркаса | C18: м2 | E18: RAZ | F18: 380 | G18: 437 | H18: =IF(OR(F18="",F18=0),"",MAX(F18,IF(ISNUMBER('Нормы и нормо-часы'!K19),ROUNDUP('Нормы и нормо-часы'!K19/(1-$F$3),0),0))) -> 380 | I18: =IF(OR(G18="",G18=0),"",MAX(G18,IF(ISNUMBER('Нормы и нормо-часы'!L19),ROUNDUP('Нормы и нормо-часы'!L19/(1-$F$3),0),0))) -> 437 | J18: =IF(OR(F18="",F18=0),"",H18/F18-1) -> 0 | K18: =IF(OR(G18="",G18=0),"",I18/G18-1) -> 0 | L18: 230 | M18: 264 | N18: =IF(OR(H18="",H18=0),"",(H18-L18)/H18) -> 0.39473684 | O18: =IF(OR(I18="",I18=0),"",(I18-M18)/I18) -> 0.39588101 | P18: =IF(H18="","",H18-L18) -> 150 | Q18: =IF(I18="","",I18-M18) -> 173 | R18: 304.83 | S18: 411.52 | T18: =IF(OR(S18="",F18="",F18=0),"",S18/F18) -> 1.0829474 | U18: аналог 1.2.2 + разборка каркаса (spb.innstroy.ru подсистема 632)
A19: 1.2.4 | B19: Демонтаж ограждающих конструкций стен из многослойных панелей (сэндвич-панели) | C19: м2 | E19: KRO | F19: 380 | G19: 437 | H19: =IF(OR(F19="",F19=0),"",MAX(F19,IF(ISNUMBER('Нормы и нормо-часы'!K20),ROUNDUP('Нормы и нормо-часы'!K20/(1-$F$3),0),0))) -> 480 | I19: =IF(OR(G19="",G19=0),"",MAX(G19,IF(ISNUMBER('Нормы и нормо-часы'!L20),ROUNDUP('Нормы и нормо-часы'!L20/(1-$F$3),0),0))) -> 571 | J19: =IF(OR(F19="",F19=0),"",H19/F19-1) -> 0.26315789 | K19: =IF(OR(G19="",G19=0),"",I19/G19-1) -> 0.30663616 | L19: 230 | M19: 264 | N19: =IF(OR(H19="",H19=0),"",(H19-L19)/H19) -> 0.52083333 | O19: =IF(OR(I19="",I19=0),"",(I19-M19)/I19) -> 0.53765324 | P19: =IF(H19="","",H19-L19) -> 250 | Q19: =IF(I19="","",I19-M19) -> 307 | R19: 547.3 | S19: 738.86 | T19: =IF(OR(S19="",F19="",F19=0),"",S19/F19) -> 1.9443684 | U19: прайс spb.rsk-uteplitel.ru 316–380 руб/м2 (СПб, 50–100 мм) | V19: Наш тариф ~1,9× рынка; техника (вышка/кран) отдельно
A20: 1.2.5 | B20: Демонтаж ограждающих конструкций стен из панелей "Алюкобонд" и металлического каркаса | C20: м2 | E20: FAS | F20: 1100 | G20: 1265 | H20: =IF(OR(F20="",F20=0),"",MAX(F20,IF(ISNUMBER('Нормы и нормо-часы'!K21),ROUNDUP('Нормы и нормо-часы'!K21/(1-$F$3),0),0))) -> 1320 | I20: =IF(OR(G20="",G20=0),"",MAX(G20,IF(ISNUMBER('Нормы и нормо-часы'!L21),ROUNDUP('Нормы и нормо-часы'!L21/(1-$F$3),0),0))) -> 1560 | J20: =IF(OR(F20="",F20=0),"",H20/F20-1) -> 0.2 | K20: =IF(OR(G20="",G20=0),"",I20/G20-1) -> 0.23320158 | L20: 650 | M20: 747 | N20: =IF(OR(H20="",H20=0),"",(H20-L20)/H20) -> 0.50757576 | O20: =IF(OR(I20="",I20=0),"",(I20-M20)/I20) -> 0.52115385 | P20: =IF(H20="","",H20-L20) -> 670 | Q20: =IF(I20="","",I20-M20) -> 813 | R20: 962.99 | S20: 1300.04 | T20: =IF(OR(S20="",F20="",F20=0),"",S20/F20) -> 1.1818545 | U20: прайс spb.innstroy.ru облицовка 738 + подсистема 632 руб/м2
A21: 1.2.6 | B21: Демонтаж теплоизоляционного слоя стен | C21: м2 | E21: RAZ | F21: 200 | G21: 230 | H21: =IF(OR(F21="",F21=0),"",MAX(F21,IF(ISNUMBER('Нормы и нормо-часы'!K22),ROUNDUP('Нормы и нормо-часы'!K22/(1-$F$3),0),0))) -> 200 | I21: =IF(OR(G21="",G21=0),"",MAX(G21,IF(ISNUMBER('Нормы и нормо-часы'!L22),ROUNDUP('Нормы и нормо-часы'!L22/(1-$F$3),0),0))) -> 230 | J21: =IF(OR(F21="",F21=0),"",H21/F21-1) -> 0 | K21: =IF(OR(G21="",G21=0),"",I21/G21-1) -> 0 | L21: 120 | M21: 138 | N21: =IF(OR(H21="",H21=0),"",(H21-L21)/H21) -> 0.4 | O21: =IF(OR(I21="",I21=0),"",(I21-M21)/I21) -> 0.4 | P21: =IF(H21="","",H21-L21) -> 80 | Q21: =IF(I21="","",I21-M21) -> 92 | R21: 171.47 | S21: 231.48 | T21: =IF(OR(S21="",F21="",F21=0),"",S21/F21) -> 1.1574 | U21: аналог spb.innstroy.ru (утеплитель фасада 527, внутри помещений 120–150)
A22: 1.2.7 | B22: Разборка систем вентилируемых фасадов из плит "Керамогранит" с сохранением каркаса | C22: м2 | E22: FAS | F22: 650 | G22: 747 | H22: =IF(OR(F22="",F22=0),"",MAX(F22,IF(ISNUMBER('Нормы и нормо-часы'!K23),ROUNDUP('Нормы и нормо-часы'!K23/(1-$F$3),0),0))) -> 880 | I22: =IF(OR(G22="",G22=0),"",MAX(G22,IF(ISNUMBER('Нормы и нормо-часы'!L23),ROUNDUP('Нормы и нормо-часы'!L23/(1-$F$3),0),0))) -> 1040 | J22: =IF(OR(F22="",F22=0),"",H22/F22-1) -> 0.35384615 | K22: =IF(OR(G22="",G22=0),"",I22/G22-1) -> 0.39223561 | L22: 400 | M22: 460 | N22: =IF(OR(H22="",H22=0),"",(H22-L22)/H22) -> 0.54545455 | O22: =IF(OR(I22="",I22=0),"",(I22-M22)/I22) -> 0.55769231 | P22: =IF(H22="","",H22-L22) -> 480 | Q22: =IF(I22="","",I22-M22) -> 580 | R22: 929.78 | S22: 1255.2 | T22: =IF(OR(S22="",F22="",F22=0),"",S22/F22) -> 1.9310769 | U22: прайс spb.innstroy.ru снятие облицовки 738 руб/м2 | V22: С сохранением каркаса — только снятие плит
A23: 1.2.8 | B23: Разборка систем вентилируемых фасадов из плит "Керамогранит" с учетом каркаса | C23: м2 | E23: FAS | F23: 1100 | G23: 1265 | H23: =IF(OR(F23="",F23=0),"",MAX(F23,IF(ISNUMBER('Нормы и нормо-часы'!K24),ROUNDUP('Нормы и нормо-часы'!K24/(1-$F$3),0),0))) -> 1467 | I23: =IF(OR(G23="",G23=0),"",MAX(G23,IF(ISNUMBER('Нормы и нормо-часы'!L24),ROUNDUP('Нормы и нормо-часы'!L24/(1-$F$3),0),0))) -> 1734 | J23: =IF(OR(F23="",F23=0),"",H23/F23-1) -> 0.33363636 | K23: =IF(OR(G23="",G23=0),"",I23/G23-1) -> 0.37075099 | L23: 650 | M23: 747 | N23: =IF(OR(H23="",H23=0),"",(H23-L23)/H23) -> 0.55691888 | O23: =IF(OR(I23="",I23=0),"",(I23-M23)/I23) -> 0.56920415 | P23: =IF(H23="","",H23-L23) -> 817 | Q23: =IF(I23="","",I23-M23) -> 987 | R23: 914.69 | S23: 1234.83 | T23: =IF(OR(S23="",F23="",F23=0),"",S23/F23) -> 1.1225727 | U23: прайс spb.innstroy.ru облицовка+подсистема 738+632 | V23: В нашем тарифе «с каркасом» дешевле, чем «без» (1.2.7) — нелогично
A24: 1.2.N1 | B24: Демонтаж металлического козырька/навеса над входом | C24: м2 | D24: да | E24: SVA | F24: 1200 | G24: 1380 | H24: =IF(OR(F24="",F24=0),"",MAX(F24,IF(ISNUMBER('Нормы и нормо-часы'!K25),ROUNDUP('Нормы и нормо-часы'!K25/(1-$F$3),0),0))) -> 1200 | I24: =IF(OR(G24="",G24=0),"",MAX(G24,IF(ISNUMBER('Нормы и нормо-часы'!L25),ROUNDUP('Нормы и нормо-часы'!L25/(1-$F$3),0),0))) -> 1440 | J24: =IF(OR(F24="",F24=0),"",H24/F24-1) -> 0 | K24: =IF(OR(G24="",G24=0),"",I24/G24-1) -> 0.043478261 | L24: 720 | M24: 828 | N24: =IF(OR(H24="",H24=0),"",(H24-L24)/H24) -> 0.4 | O24: =IF(OR(I24="",I24=0),"",(I24-M24)/I24) -> 0.425 | P24: =IF(H24="","",H24-L24) -> 480 | Q24: =IF(I24="","",I24-M24) -> 612 | T24: =IF(OR(S24="",F24="",F24=0),"",S24/F24) | U24: расчёт | V24: Техника отдельно
A25: 1.3 Демонтажные работы по фундаменту
A26: 1.3.1 | B26: Разборка бутовых фундаментов | C26: м3 | E26: RAZ | F26: 4000 | G26: 4600 | H26: =IF(OR(F26="",F26=0),"",MAX(F26,IF(ISNUMBER('Нормы и нормо-часы'!K27),ROUNDUP('Нормы и нормо-часы'!K27/(1-$F$3),0),0))) -> 5500 | I26: =IF(OR(G26="",G26=0),"",MAX(G26,IF(ISNUMBER('Нормы и нормо-часы'!L27),ROUNDUP('Нормы и нормо-часы'!L27/(1-$F$3),0),0))) -> 6600 | J26: =IF(OR(F26="",F26=0),"",H26/F26-1) -> 0.375 | K26: =IF(OR(G26="",G26=0),"",I26/G26-1) -> 0.43478261 | L26: 2400 | M26: 2760 | N26: =IF(OR(H26="",H26=0),"",(H26-L26)/H26) -> 0.56363636 | O26: =IF(OR(I26="",I26=0),"",(I26-M26)/I26) -> 0.58181818 | P26: =IF(H26="","",H26-L26) -> 3100 | Q26: =IF(I26="","",I26-M26) -> 3840 | R26: 10022.25 | S26: 13530.04 | T26: =IF(OR(S26="",F26="",F26=0),"",S26/F26) -> 3.38251 | U26: аналог rezka-prof.ru (гидроклин кирпич/бут 3000), moskva-demontazh.ru фундамент от 1900 | V26: Наш тариф 13,5 тыс. — ×3,4 к рынку
A27: 1.3.2 | B27: Разборка бетонных фундаментов | C27: м3 | E27: RAZ | F27: 7500 | G27: 9000 | H27: =IF(OR(F27="",F27=0),"",MAX(F27,IF(ISNUMBER('Нормы и нормо-часы'!K28),ROUNDUP('Нормы и нормо-часы'!K28/(1-$F$3),0),0))) -> 8067 | I27: =IF(OR(G27="",G27=0),"",MAX(G27,IF(ISNUMBER('Нормы и нормо-часы'!L28),ROUNDUP('Нормы и нормо-часы'!L28/(1-$F$3),0),0))) -> 9680 | J27: =IF(OR(F27="",F27=0),"",H27/F27-1) -> 0.0756 | K27: =IF(OR(G27="",G27=0),"",I27/G27-1) -> 0.075555556 | L27: 4500 | M27: 5310 | N27: =IF(OR(H27="",H27=0),"",(H27-L27)/H27) -> 0.44217181 | O27: =IF(OR(I27="",I27=0),"",(I27-M27)/I27) -> 0.45144628 | P27: =IF(H27="","",H27-L27) -> 3567 | Q27: =IF(I27="","",I27-M27) -> 4370 | R27: 14490 | S27: 19561.5 | T27: =IF(OR(S27="",F27="",F27=0),"",S27/F27) -> 2.6082 | U27: прайс rezka-prof.ru гидроклин бетон от 7000; moskva-demontazh.ru ручной от 9200 (МСК) | V27: Наш тариф 19,6 тыс. — ×2,6 к рынку
A28: 1.3.3 | B28: Разборка железобетонных фундаментов | C28: м3 | E28: RAZ | F28: 10000 | G28: 12000 | H28: =IF(OR(F28="",F28=0),"",MAX(F28,IF(ISNUMBER('Нормы и нормо-часы'!K29),ROUNDUP('Нормы и нормо-часы'!K29/(1-$F$3),0),0))) -> 11000 | I28: =IF(OR(G28="",G28=0),"",MAX(G28,IF(ISNUMBER('Нормы и нормо-часы'!L29),ROUNDUP('Нормы и нормо-часы'!L29/(1-$F$3),0),0))) -> 13200 | J28: =IF(OR(F28="",F28=0),"",H28/F28-1) -> 0.1 | K28: =IF(OR(G28="",G28=0),"",I28/G28-1) -> 0.1 | L28: 6000 | M28: 7080 | N28: =IF(OR(H28="",H28=0),"",(H28-L28)/H28) -> 0.45454545 | O28: =IF(OR(I28="",I28=0),"",(I28-M28)/I28) -> 0.46363636 | P28: =IF(H28="","",H28-L28) -> 5000 | Q28: =IF(I28="","",I28-M28) -> 6120 | R28: 16703.75 | S28: 22550.06 | T28: =IF(OR(S28="",F28="",F28=0),"",S28/F28) -> 2.255006 | U28: прайс rezka-prof.ru гидроклин ж/б от 13500; zakazstroy.ru ж/б от 8500 | V28: Наш тариф 22,6 тыс. — ×2,3 к рынку
A29: 1.4 Демонтажные работы кровли
A30: 1.4.1 | B30: Очистка кровли от листвы и мусора | C30: м2 | E30: RAZ | F30: 35 | G30: 40 | H30: =IF(OR(F30="",F30=0),"",MAX(F30,IF(ISNUMBER('Нормы и нормо-часы'!K31),ROUNDUP('Нормы и нормо-часы'!K31/(1-$F$3),0),0))) -> 35 | I30: =IF(OR(G30="",G30=0),"",MAX(G30,IF(ISNUMBER('Нормы и нормо-часы'!L31),ROUNDUP('Нормы и нормо-часы'!L31/(1-$F$3),0),0))) -> 40 | J30: =IF(OR(F30="",F30=0),"",H30/F30-1) -> 0 | K30: =IF(OR(G30="",G30=0),"",I30/G30-1) -> 0 | L30: 20 | M30: 23 | N30: =IF(OR(H30="",H30=0),"",(H30-L30)/H30) -> 0.42857143 | O30: =IF(OR(I30="",I30=0),"",(I30-M30)/I30) -> 0.425 | P30: =IF(H30="","",H30-L30) -> 15 | Q30: =IF(I30="","",I30-M30) -> 17 | R30: 64.96 | S30: 87.7 | T30: =IF(OR(S30="",F30="",F30=0),"",S30/F30) -> 2.5057143 | U30: аналог spb-dvigenie.ru/h2oclean.ru (снег 20–35 руб/м2) | V30: Наш тариф 88 руб — ×2,5 к рынку
A31: 1.4.2 | B31: Очистка снега с крыш при толщине слоя до 20 см | C31: м2 | E31: RAZ | F31: 30 | G31: 34.5 | H31: =IF(OR(F31="",F31=0),"",MAX(F31,IF(ISNUMBER('Нормы и нормо-часы'!K32),ROUNDUP('Нормы и нормо-часы'!K32/(1-$F$3),0),0))) -> 30 | I31: =IF(OR(G31="",G31=0),"",MAX(G31,IF(ISNUMBER('Нормы и нормо-часы'!L32),ROUNDUP('Нормы и нормо-часы'!L32/(1-$F$3),0),0))) -> 35 | J31: =IF(OR(F31="",F31=0),"",H31/F31-1) -> 0 | K31: =IF(OR(G31="",G31=0),"",I31/G31-1) -> 0.014492754 | L31: 18 | M31: 20.5 | N31: =IF(OR(H31="",H31=0),"",(H31-L31)/H31) -> 0.4 | O31: =IF(OR(I31="",I31=0),"",(I31-M31)/I31) -> 0.41428571 | P31: =IF(H31="","",H31-L31) -> 12 | Q31: =IF(I31="","",I31-M31) -> 14.5 | R31: 50.32 | S31: 67.93 | T31: =IF(OR(S31="",F31="",F31=0),"",S31/F31) -> 2.2643333 | U31: прайс spb-dvigenie.ru/h2oclean.ru юрлица 18–35 руб/м2 | V31: Наш тариф 68 руб — ×2,3 к рынку; при >1000 м2 рынок 20 руб
A32: 1.4.3 | B32: Очистка снега с крыш, добавлять на каждые следующие 10 см увеличения толщины слоя | C32: м2 | E32: RAZ | F32: 8 | G32: 9 | H32: =IF(OR(F32="",F32=0),"",MAX(F32,IF(ISNUMBER('Нормы и нормо-часы'!K33),ROUNDUP('Нормы и нормо-часы'!K33/(1-$F$3),0),0))) -> 10 | I32: =IF(OR(G32="",G32=0),"",MAX(G32,IF(ISNUMBER('Нормы и нормо-часы'!L33),ROUNDUP('Нормы и нормо-часы'!L33/(1-$F$3),0),0))) -> 11 | J32: =IF(OR(F32="",F32=0),"",H32/F32-1) -> 0.25 | K32: =IF(OR(G32="",G32=0),"",I32/G32-1) -> 0.22222222 | L32: 5 | M32: 6 | N32: =IF(OR(H32="",H32=0),"",(H32-L32)/H32) -> 0.5 | O32: =IF(OR(I32="",I32=0),"",(I32-M32)/I32) -> 0.45454545 | P32: =IF(H32="","",H32-L32) -> 5 | Q32: =IF(I32="","",I32-M32) -> 5 | R32: 11.27 | S32: 15.21 | T32: =IF(OR(S32="",F32="",F32=0),"",S32/F32) -> 1.90125 | U32: аналог 1.4.2 (+30 %/10 см)
A33: 1.4.4 | B33: Разборка водосточных ПВХ труб | C33: мп | E33: KRO | F33: 120 | G33: 138 | H33: =IF(OR(F33="",F33=0),"",MAX(F33,IF(ISNUMBER('Нормы и нормо-часы'!K34),ROUNDUP('Нормы и нормо-часы'!K34/(1-$F$3),0),0))) -> 160 | I33: =IF(OR(G33="",G33=0),"",MAX(G33,IF(ISNUMBER('Нормы и нормо-часы'!L34),ROUNDUP('Нормы и нормо-часы'!L34/(1-$F$3),0),0))) -> 191 | J33: =IF(OR(F33="",F33=0),"",H33/F33-1) -> 0.33333333 | K33: =IF(OR(G33="",G33=0),"",I33/G33-1) -> 0.38405797 | L33: 70 | M33: 80.5 | N33: =IF(OR(H33="",H33=0),"",(H33-L33)/H33) -> 0.5625 | O33: =IF(OR(I33="",I33=0),"",(I33-M33)/I33) -> 0.57853403 | P33: =IF(H33="","",H33-L33) -> 90 | Q33: =IF(I33="","",I33-M33) -> 110.5 | R33: 181.13 | S33: 244.53 | T33: =IF(OR(S33="",F33="",F33=0),"",S33/F33) -> 2.03775 | U33: аналог demontazh.spb.ru (ПВХ трубы 50 руб/мп) с учётом высоты | V33: Работа с вышки/альпинистами — отдельно
A34: 1.4.5 | B34: Разборка водосточных труб металлических | C34: мп | E34: KRO | F34: 150 | G34: 172 | H34: =IF(OR(F34="",F34=0),"",MAX(F34,IF(ISNUMBER('Нормы и нормо-часы'!K35),ROUNDUP('Нормы и нормо-часы'!K35/(1-$F$3),0),0))) -> 214 | I34: =IF(OR(G34="",G34=0),"",MAX(G34,IF(ISNUMBER('Нормы и нормо-часы'!L35),ROUNDUP('Нормы и нормо-часы'!L35/(1-$F$3),0),0))) -> 254 | J34: =IF(OR(F34="",F34=0),"",H34/F34-1) -> 0.42666667 | K34: =IF(OR(G34="",G34=0),"",I34/G34-1) -> 0.47674419 | L34: 90 | M34: 103 | N34: =IF(OR(H34="",H34=0),"",(H34-L34)/H34) -> 0.57943925 | O34: =IF(OR(I34="",I34=0),"",(I34-M34)/I34) -> 0.59448819 | P34: =IF(H34="","",H34-L34) -> 124 | Q34: =IF(I34="","",I34-M34) -> 151 | R34: 301.88 | S34: 407.54 | T34: =IF(OR(S34="",F34="",F34=0),"",S34/F34) -> 2.7169333 | U34: аналог 1.4.4
A35: 1.4.6 | B35: Разборка выравнивающих стяжек цементно-песчаных на кровле | C35: м3 | E35: KRO | F35: 6000 | G35: 6900 | H35: =IF(OR(F35="",F35=0),"",MAX(F35,IF(ISNUMBER('Нормы и нормо-часы'!K36),ROUNDUP('Нормы и нормо-часы'!K36/(1-$F$3),0),0))) -> 10134 | I35: =IF(OR(G35="",G35=0),"",MAX(G35,IF(ISNUMBER('Нормы и нормо-часы'!L36),ROUNDUP('Нормы и нормо-часы'!L36/(1-$F$3),0),0))) -> 12034 | J35: =IF(OR(F35="",F35=0),"",H35/F35-1) -> 0.689 | K35: =IF(OR(G35="",G35=0),"",I35/G35-1) -> 0.74405797 | L35: 3600 | M35: 4140 | N35: =IF(OR(H35="",H35=0),"",(H35-L35)/H35) -> 0.64476021 | O35: =IF(OR(I35="",I35=0),"",(I35-M35)/I35) -> 0.65597474 | P35: =IF(H35="","",H35-L35) -> 6534 | Q35: =IF(I35="","",I35-M35) -> 7894 | R35: 4612.65 | S35: 6227.08 | T35: =IF(OR(S35="",F35="",F35=0),"",S35/F35) -> 1.0378467 | U35: аналог stroygarant78.ru стяжка 50 мм 350 руб/м2 = 7000/м3 | V35: Включён спуск мусора с кровли вручную до 1 этажа
A36: 1.4.7 | B36: Разборка монолитных перекрытий бетонных | C36: м3 | E36: RAZ | F36: 8500 | G36: 9775 | H36: =IF(OR(F36="",F36=0),"",MAX(F36,IF(ISNUMBER('Нормы и нормо-часы'!K37),ROUNDUP('Нормы и нормо-часы'!K37/(1-$F$3),0),0))) -> 9534 | I36: =IF(OR(G36="",G36=0),"",MAX(G36,IF(ISNUMBER('Нормы и нормо-часы'!L37),ROUNDUP('Нормы и нормо-часы'!L37/(1-$F$3),0),0))) -> 11440 | J36: =IF(OR(F36="",F36=0),"",H36/F36-1) -> 0.12164706 | K36: =IF(OR(G36="",G36=0),"",I36/G36-1) -> 0.17033248 | L36: 5100 | M36: 5865 | N36: =IF(OR(H36="",H36=0),"",(H36-L36)/H36) -> 0.46507237 | O36: =IF(OR(I36="",I36=0),"",(I36-M36)/I36) -> 0.48732517 | P36: =IF(H36="","",H36-L36) -> 4434 | Q36: =IF(I36="","",I36-M36) -> 5575 | R36: 9750.56 | S36: 13163.26 | T36: =IF(OR(S36="",F36="",F36=0),"",S36/F36) -> 1.5486188 | U36: аналог zakazstroy.ru перекрытия от 1500 руб/м2; rezka-prof.ru гидроклин бетон 7000 | V36: Перекрытия в подразделе «кровля» — место позиции некорректно; ед. м3
A37: 1.4.8 | B37: Разборка монолитных перекрытий железобетонных | C37: м3 | E37: RAZ | F37: 11000 | G37: 13200 | H37: =IF(OR(F37="",F37=0),"",MAX(F37,IF(ISNUMBER('Нормы и нормо-часы'!K38),ROUNDUP('Нормы и нормо-часы'!K38/(1-$F$3),0),0))) -> 12467 | I37: =IF(OR(G37="",G37=0),"",MAX(G37,IF(ISNUMBER('Нормы и нормо-часы'!L38),ROUNDUP('Нормы и нормо-часы'!L38/(1-$F$3),0),0))) -> 14960 | J37: =IF(OR(F37="",F37=0),"",H37/F37-1) -> 0.13336364 | K37: =IF(OR(G37="",G37=0),"",I37/G37-1) -> 0.13333333 | L37: 6600 | M37: 7788 | N37: =IF(OR(H37="",H37=0),"",(H37-L37)/H37) -> 0.47060239 | O37: =IF(OR(I37="",I37=0),"",(I37-M37)/I37) -> 0.47941176 | P37: =IF(H37="","",H37-L37) -> 5867 | Q37: =IF(I37="","",I37-M37) -> 7172 | R37: 10958.06 | S37: 14793.38 | T37: =IF(OR(S37="",F37="",F37=0),"",S37/F37) -> 1.3448527 | U37: аналог rezka-prof.ru гидроклин ж/б от 13500; zakazstroy.ru ж/б 8500
A38: 1.4.9 | B38: Разборка парапетных решеток | C38: мп | E38: KRO | F38: 250 | G38: 288 | H38: =IF(OR(F38="",F38=0),"",MAX(F38,IF(ISNUMBER('Нормы и нормо-часы'!K39),ROUNDUP('Нормы и нормо-часы'!K39/(1-$F$3),0),0))) -> 427 | I38: =IF(OR(G38="",G38=0),"",MAX(G38,IF(ISNUMBER('Нормы и нормо-часы'!L39),ROUNDUP('Нормы и нормо-часы'!L39/(1-$F$3),0),0))) -> 507 | J38: =IF(OR(F38="",F38=0),"",H38/F38-1) -> 0.708 | K38: =IF(OR(G38="",G38=0),"",I38/G38-1) -> 0.76041667 | L38: 150 | M38: 172 | N38: =IF(OR(H38="",H38=0),"",(H38-L38)/H38) -> 0.64871194 | O38: =IF(OR(I38="",I38=0),"",(I38-M38)/I38) -> 0.66074951 | P38: =IF(H38="","",H38-L38) -> 277 | Q38: =IF(I38="","",I38-M38) -> 335 | R38: 181.13 | S38: 244.53 | T38: =IF(OR(S38="",F38="",F38=0),"",S38/F38) -> 0.97812 | U38: аналог (ограждения кровли)
A39: 1.4.10 | B39: Разборка покрытий кровель из волнистых и полуволнистых асбестоцементных листов | C39: м2 | E39: KRO | F39: 220 | G39: 253 | H39: =IF(OR(F39="",F39=0),"",MAX(F39,IF(ISNUMBER('Нормы и нормо-часы'!K40),ROUNDUP('Нормы и нормо-часы'!K40/(1-$F$3),0),0))) -> 267 | I39: =IF(OR(G39="",G39=0),"",MAX(G39,IF(ISNUMBER('Нормы и нормо-часы'!L40),ROUNDUP('Нормы и нормо-часы'!L40/(1-$F$3),0),0))) -> 318 | J39: =IF(OR(F39="",F39=0),"",H39/F39-1) -> 0.21363636 | K39: =IF(OR(G39="",G39=0),"",I39/G39-1) -> 0.256917 | L39: 130 | M39: 150 | N39: =IF(OR(H39="",H39=0),"",(H39-L39)/H39) -> 0.51310861 | O39: =IF(OR(I39="",I39=0),"",(I39-M39)/I39) -> 0.52830189 | P39: =IF(H39="","",H39-L39) -> 137 | Q39: =IF(I39="","",I39-M39) -> 168 | R39: 206 | S39: 278.1 | T39: =IF(OR(S39="",F39="",F39=0),"",S39/F39) -> 1.2640909 | U39: аналог profi.ru (демонтаж шифера СПб), zakazstroy.ru | V39: Асбестосодержащие отходы — утилизация с паспортом отходов отдельно
A40: 1.4.11 | B40: Разборка покрытий кровель из листовой стали | C40: м2 | E40: KRO | F40: 150 | G40: 172 | H40: =IF(OR(F40="",F40=0),"",MAX(F40,IF(ISNUMBER('Нормы и нормо-часы'!K41),ROUNDUP('Нормы и нормо-часы'!K41/(1-$F$3),0),0))) -> 192 | I40: =IF(OR(G40="",G40=0),"",MAX(G40,IF(ISNUMBER('Нормы и нормо-часы'!L41),ROUNDUP('Нормы и нормо-часы'!L41/(1-$F$3),0),0))) -> 228 | J40: =IF(OR(F40="",F40=0),"",H40/F40-1) -> 0.28 | K40: =IF(OR(G40="",G40=0),"",I40/G40-1) -> 0.3255814 | L40: 90 | M40: 103 | N40: =IF(OR(H40="",H40=0),"",(H40-L40)/H40) -> 0.53125 | O40: =IF(OR(I40="",I40=0),"",(I40-M40)/I40) -> 0.54824561 | P40: =IF(H40="","",H40-L40) -> 102 | Q40: =IF(I40="","",I40-M40) -> 125 | R40: 123.47 | S40: 166.68 | T40: =IF(OR(S40="",F40="",F40=0),"",S40/F40) -> 1.1112 | U40: аналог прайсов кровли МСК (профлист 60–240)
A41: 1.4.12 | B41: Разборка покрытий кровель из рулонных материалов (добавляется на каждый последующий слой сверх 4х слоев) | C41: м2 | E41: KRO | F41: 40 | G41: 46 | H41: =IF(OR(F41="",F41=0),"",MAX(F41,IF(ISNUMBER('Нормы и нормо-часы'!K42),ROUNDUP('Нормы и нормо-часы'!K42/(1-$F$3),0),0))) -> 54 | I41: =IF(OR(G41="",G41=0),"",MAX(G41,IF(ISNUMBER('Нормы и нормо-часы'!L42),ROUNDUP('Нормы и нормо-часы'!L42/(1-$F$3),0),0))) -> 64 | J41: =IF(OR(F41="",F41=0),"",H41/F41-1) -> 0.35 | K41: =IF(OR(G41="",G41=0),"",I41/G41-1) -> 0.39130435 | L41: 25 | M41: 28.5 | N41: =IF(OR(H41="",H41=0),"",(H41-L41)/H41) -> 0.53703704 | O41: =IF(OR(I41="",I41=0),"",(I41-M41)/I41) -> 0.5546875 | P41: =IF(H41="","",H41-L41) -> 29 | Q41: =IF(I41="","",I41-M41) -> 35.5 | R41: 34.11 | S41: 46.05 | T41: =IF(OR(S41="",F41="",F41=0),"",S41/F41) -> 1.15125 | U41: аналог 1.4.13
A42: 1.4.13 | B42: Разборка покрытий кровель из рулонных материалов ковер до 4х слоев | C42: м2 | E42: KRO | F42: 200 | G42: 230 | H42: =IF(OR(F42="",F42=0),"",MAX(F42,IF(ISNUMBER('Нормы и нормо-часы'!K43),ROUNDUP('Нормы и нормо-часы'!K43/(1-$F$3),0),0))) -> 235 | I42: =IF(OR(G42="",G42=0),"",MAX(G42,IF(ISNUMBER('Нормы и нормо-часы'!L43),ROUNDUP('Нормы и нормо-часы'!L43/(1-$F$3),0),0))) -> 279 | J42: =IF(OR(F42="",F42=0),"",H42/F42-1) -> 0.175 | K42: =IF(OR(G42="",G42=0),"",I42/G42-1) -> 0.21304348 | L42: 120 | M42: 138 | N42: =IF(OR(H42="",H42=0),"",(H42-L42)/H42) -> 0.4893617 | O42: =IF(OR(I42="",I42=0),"",(I42-M42)/I42) -> 0.50537634 | P42: =IF(H42="","",H42-L42) -> 115 | Q42: =IF(I42="","",I42-M42) -> 141 | R42: 96.6 | S42: 130.41 | T42: =IF(OR(S42="",F42="",F42=0),"",S42/F42) -> 0.65205 | U42: прайс spec-krovlya/mos-stroi-alians (рулонная 150–420 руб/м2)
A43: 1.4.14 | B43: Разборка поясков, сандриков, желобов, отливов, свесов и т.п. из листовой стали | C43: мп | E43: KRO | F43: 120 | G43: 138 | H43: =IF(OR(F43="",F43=0),"",MAX(F43,IF(ISNUMBER('Нормы и нормо-часы'!K44),ROUNDUP('Нормы и нормо-часы'!K44/(1-$F$3),0),0))) -> 160 | I43: =IF(OR(G43="",G43=0),"",MAX(G43,IF(ISNUMBER('Нормы и нормо-часы'!L44),ROUNDUP('Нормы и нормо-часы'!L44/(1-$F$3),0),0))) -> 191 | J43: =IF(OR(F43="",F43=0),"",H43/F43-1) -> 0.33333333 | K43: =IF(OR(G43="",G43=0),"",I43/G43-1) -> 0.38405797 | L43: 70 | M43: 80.5 | N43: =IF(OR(H43="",H43=0),"",(H43-L43)/H43) -> 0.5625 | O43: =IF(OR(I43="",I43=0),"",(I43-M43)/I43) -> 0.57853403 | P43: =IF(H43="","",H43-L43) -> 90 | Q43: =IF(I43="","",I43-M43) -> 110.5 | R43: 122.26 | S43: 165.05 | T43: =IF(OR(S43="",F43="",F43=0),"",S43/F43) -> 1.3754167 | U43: аналог 1.4.11
A44: 1.4.15 | B44: Разборка теплоизоляции на кровле из листовых материалов | C44: м2 | E44: KRO | F44: 90 | G44: 103 | H44: =IF(OR(F44="",F44=0),"",MAX(F44,IF(ISNUMBER('Нормы и нормо-часы'!K45),ROUNDUP('Нормы и нормо-часы'!K45/(1-$F$3),0),0))) -> 107 | I44: =IF(OR(G44="",G44=0),"",MAX(G44,IF(ISNUMBER('Нормы и нормо-часы'!L45),ROUNDUP('Нормы и нормо-часы'!L45/(1-$F$3),0),0))) -> 127 | J44: =IF(OR(F44="",F44=0),"",H44/F44-1) -> 0.18888889 | K44: =IF(OR(G44="",G44=0),"",I44/G44-1) -> 0.23300971 | L44: 55 | M44: 63 | N44: =IF(OR(H44="",H44=0),"",(H44-L44)/H44) -> 0.48598131 | O44: =IF(OR(I44="",I44=0),"",(I44-M44)/I44) -> 0.50393701 | P44: =IF(H44="","",H44-L44) -> 52 | Q44: =IF(I44="","",I44-M44) -> 64 | R44: 159.09 | S44: 214.77 | T44: =IF(OR(S44="",F44="",F44=0),"",S44/F44) -> 2.3863333 | U44: аналог spb.innstroy.ru (утеплитель) с учётом простоты плит | V44: Наш тариф 215 руб — ×2,4 к рынку
A45: 1.4.N1 | B45: Демонтаж кровельных сэндвич-панелей | C45: м2 | D45: да | E45: KRO | F45: 450 | G45: 518 | H45: =IF(OR(F45="",F45=0),"",MAX(F45,IF(ISNUMBER('Нормы и нормо-часы'!K46),ROUNDUP('Нормы и нормо-часы'!K46/(1-$F$3),0),0))) -> 534 | I45: =IF(OR(G45="",G45=0),"",MAX(G45,IF(ISNUMBER('Нормы и нормо-часы'!L46),ROUNDUP('Нормы и нормо-часы'!L46/(1-$F$3),0),0))) -> 634 | J45: =IF(OR(F45="",F45=0),"",H45/F45-1) -> 0.18666667 | K45: =IF(OR(G45="",G45=0),"",I45/G45-1) -> 0.22393822 | L45: 270 | M45: 310 | N45: =IF(OR(H45="",H45=0),"",(H45-L45)/H45) -> 0.49438202 | O45: =IF(OR(I45="",I45=0),"",(I45-M45)/I45) -> 0.51104101 | P45: =IF(H45="","",H45-L45) -> 264 | Q45: =IF(I45="","",I45-M45) -> 324 | T45: =IF(OR(S45="",F45="",F45=0),"",S45/F45) | U45: аналог spb.rsk-uteplitel.ru (стеновые 316–380) | V45: Кран отдельно
A46: 1.4.N2 | B46: Демонтаж кровельного профлиста | C46: м2 | D46: да | E46: KRO | F46: 200 | G46: 230 | H46: =IF(OR(F46="",F46=0),"",MAX(F46,IF(ISNUMBER('Нормы и нормо-часы'!K47),ROUNDUP('Нормы и нормо-часы'!K47/(1-$F$3),0),0))) -> 214 | I46: =IF(OR(G46="",G46=0),"",MAX(G46,IF(ISNUMBER('Нормы и нормо-часы'!L47),ROUNDUP('Нормы и нормо-часы'!L47/(1-$F$3),0),0))) -> 254 | J46: =IF(OR(F46="",F46=0),"",H46/F46-1) -> 0.07 | K46: =IF(OR(G46="",G46=0),"",I46/G46-1) -> 0.10434783 | L46: 120 | M46: 138 | N46: =IF(OR(H46="",H46=0),"",(H46-L46)/H46) -> 0.43925234 | O46: =IF(OR(I46="",I46=0),"",(I46-M46)/I46) -> 0.45669291 | P46: =IF(H46="","",H46-L46) -> 94 | Q46: =IF(I46="","",I46-M46) -> 116 | T46: =IF(OR(S46="",F46="",F46=0),"",S46/F46) | U46: прайс МСК (профлист 60–240 руб/м2)
A47: 1.4.N3 | B47: Демонтаж кровельной воронки | C47: шт | D47: да | E47: KRO | F47: 900 | G47: 1035 | H47: =IF(OR(F47="",F47=0),"",MAX(F47,IF(ISNUMBER('Нормы и нормо-часы'!K48),ROUNDUP('Нормы и нормо-часы'!K48/(1-$F$3),0),0))) -> 900 | I47: =IF(OR(G47="",G47=0),"",MAX(G47,IF(ISNUMBER('Нормы и нормо-часы'!L48),ROUNDUP('Нормы и нормо-часы'!L48/(1-$F$3),0),0))) -> 1035 | J47: =IF(OR(F47="",F47=0),"",H47/F47-1) -> 0 | K47: =IF(OR(G47="",G47=0),"",I47/G47-1) -> 0 | L47: 540 | M47: 621 | N47: =IF(OR(H47="",H47=0),"",(H47-L47)/H47) -> 0.4 | O47: =IF(OR(I47="",I47=0),"",(I47-M47)/I47) -> 0.4 | P47: =IF(H47="","",H47-L47) -> 360 | Q47: =IF(I47="","",I47-M47) -> 414 | T47: =IF(OR(S47="",F47="",F47=0),"",S47/F47) | U47: расчёт
A48: 1.4.N4 | B48: Сбивание сосулек и наледи с карнизов (промальп) | C48: мп | D48: да | E48: FAS | F48: 120 | G48: 138 | H48: =IF(OR(F48="",F48=0),"",MAX(F48,IF(ISNUMBER('Нормы и нормо-часы'!K49),ROUNDUP('Нормы и нормо-часы'!K49/(1-$F$3),0),0))) -> 220 | I48: =IF(OR(G48="",G48=0),"",MAX(G48,IF(ISNUMBER('Нормы и нормо-часы'!L49),ROUNDUP('Нормы и нормо-часы'!L49/(1-$F$3),0),0))) -> 260 | J48: =IF(OR(F48="",F48=0),"",H48/F48-1) -> 0.83333333 | K48: =IF(OR(G48="",G48=0),"",I48/G48-1) -> 0.88405797 | L48: 70 | M48: 80.5 | N48: =IF(OR(H48="",H48=0),"",(H48-L48)/H48) -> 0.68181818 | O48: =IF(OR(I48="",I48=0),"",(I48-M48)/I48) -> 0.69038462 | P48: =IF(H48="","",H48-L48) -> 150 | Q48: =IF(I48="","",I48-M48) -> 179.5 | T48: =IF(OR(S48="",F48="",F48=0),"",S48/F48) | U48: аналог spb-dvigenie.ru/h2oclean.ru (периметр 40 руб/мп) + альпинизм
A49: 1.4.N5 | B49: Демонтаж зенитного фонаря / люка дымоудаления | C49: шт | D49: да | E49: KRO | F49: 6000 | G49: 6900 | H49: =IF(OR(F49="",F49=0),"",MAX(F49,IF(ISNUMBER('Нормы и нормо-часы'!K50),ROUNDUP('Нормы и нормо-часы'!K50/(1-$F$3),0),0))) -> 6000 | I49: =IF(OR(G49="",G49=0),"",MAX(G49,IF(ISNUMBER('Нормы и нормо-часы'!L50),ROUNDUP('Нормы и нормо-часы'!L50/(1-$F$3),0),0))) -> 6900 | J49: =IF(OR(F49="",F49=0),"",H49/F49-1) -> 0 | K49: =IF(OR(G49="",G49=0),"",I49/G49-1) -> 0 | L49: 3600 | M49: 4140 | N49: =IF(OR(H49="",H49=0),"",(H49-L49)/H49) -> 0.4 | O49: =IF(OR(I49="",I49=0),"",(I49-M49)/I49) -> 0.4 | P49: =IF(H49="","",H49-L49) -> 2400 | Q49: =IF(I49="","",I49-M49) -> 2760 | T49: =IF(OR(S49="",F49="",F49=0),"",S49/F49) | U49: расчёт
A50: 1.5 Демонтажные работы в здании
A51: 1.5.1 | B51: Демонтаж металлических балок, ригелей перекрытия, покрытия | C51: тн | E51: SVA | F51: 12000 | G51: 13800 | H51: =IF(OR(F51="",F51=0),"",MAX(F51,IF(ISNUMBER('Нормы и нормо-часы'!K52),ROUNDUP('Нормы и нормо-часы'!K52/(1-$F$3),0),0))) -> 24000 | I51: =IF(OR(G51="",G51=0),"",MAX(G51,IF(ISNUMBER('Нормы и нормо-часы'!L52),ROUNDUP('Нормы и нормо-часы'!L52/(1-$F$3),0),0))) -> 28800 | J51: =IF(OR(F51="",F51=0),"",H51/F51-1) -> 1 | K51: =IF(OR(G51="",G51=0),"",I51/G51-1) -> 1.0869565 | L51: 7200 | M51: 8280 | N51: =IF(OR(H51="",H51=0),"",(H51-L51)/H51) -> 0.7 | O51: =IF(OR(I51="",I51=0),"",(I51-M51)/I51) -> 0.7125 | P51: =IF(H51="","",H51-L51) -> 16800 | Q51: =IF(I51="","",I51-M51) -> 20520 | R51: 23995.44 | S51: 32393.84 | T51: =IF(OR(S51="",F51="",F51=0),"",S51/F51) -> 2.6994867 | U51: аналог moskva-demontazh.ru (МК от 4000/т) ×3 для балок внутри здания | V51: Наш тариф 32,4 тыс./т — ×2,7 к рынку; кран/лебёдки отдельно
A52: 1.5.2 | B52: Демонтаж железобетонных конструкций. При объеме более 1 м3 - при помощи отбойных молотков | C52: м3 | E52: RAZ | F52: 11000 | G52: 13200 | H52: =IF(OR(F52="",F52=0),"",MAX(F52,IF(ISNUMBER('Нормы и нормо-часы'!K53),ROUNDUP('Нормы и нормо-часы'!K53/(1-$F$3),0),0))) -> 12467 | I52: =IF(OR(G52="",G52=0),"",MAX(G52,IF(ISNUMBER('Нормы и нормо-часы'!L53),ROUNDUP('Нормы и нормо-часы'!L53/(1-$F$3),0),0))) -> 14960 | J52: =IF(OR(F52="",F52=0),"",H52/F52-1) -> 0.13336364 | K52: =IF(OR(G52="",G52=0),"",I52/G52-1) -> 0.13333333 | L52: 6600 | M52: 7788 | N52: =IF(OR(H52="",H52=0),"",(H52-L52)/H52) -> 0.47060239 | O52: =IF(OR(I52="",I52=0),"",(I52-M52)/I52) -> 0.47941176 | P52: =IF(H52="","",H52-L52) -> 5867 | Q52: =IF(I52="","",I52-M52) -> 7172 | R52: 15386.36 | S52: 20771.59 | T52: =IF(OR(S52="",F52="",F52=0),"",S52/F52) -> 1.8883264 | U52: прайс rezka-prof.ru гидроклин ж/б 13500; zakazstroy.ru ж/б 8500 | V52: Наш тариф ×1,9 к рынку
A53: 1.5.3 | B53: Демонтаж бетонных конструкций | C53: м3 | E53: RAZ | F53: 8500 | G53: 10200 | H53: =IF(OR(F53="",F53=0),"",MAX(F53,IF(ISNUMBER('Нормы и нормо-часы'!K54),ROUNDUP('Нормы и нормо-часы'!K54/(1-$F$3),0),0))) -> 9534 | I53: =IF(OR(G53="",G53=0),"",MAX(G53,IF(ISNUMBER('Нормы и нормо-часы'!L54),ROUNDUP('Нормы и нормо-часы'!L54/(1-$F$3),0),0))) -> 11440 | J53: =IF(OR(F53="",F53=0),"",H53/F53-1) -> 0.12164706 | K53: =IF(OR(G53="",G53=0),"",I53/G53-1) -> 0.12156863 | L53: 5100 | M53: 6018 | N53: =IF(OR(H53="",H53=0),"",(H53-L53)/H53) -> 0.46507237 | O53: =IF(OR(I53="",I53=0),"",(I53-M53)/I53) -> 0.47395105 | P53: =IF(H53="","",H53-L53) -> 4434 | Q53: =IF(I53="","",I53-M53) -> 5422 | R53: 12427.18 | S53: 16776.69 | T53: =IF(OR(S53="",F53="",F53=0),"",S53/F53) -> 1.9737282 | U53: прайс rezka-prof.ru гидроклин бетон 7000; moskva-demontazh.ru ручной 9200
A54: 1.5.4 | B54: Демонтаж металлоконструкций | C54: тн | E54: SVA | F54: 7500 | G54: 8625 | H54: =IF(OR(F54="",F54=0),"",MAX(F54,IF(ISNUMBER('Нормы и нормо-часы'!K55),ROUNDUP('Нормы и нормо-часы'!K55/(1-$F$3),0),0))) -> 14400 | I54: =IF(OR(G54="",G54=0),"",MAX(G54,IF(ISNUMBER('Нормы и нормо-часы'!L55),ROUNDUP('Нормы и нормо-часы'!L55/(1-$F$3),0),0))) -> 17280 | J54: =IF(OR(F54="",F54=0),"",H54/F54-1) -> 0.92 | K54: =IF(OR(G54="",G54=0),"",I54/G54-1) -> 1.0034783 | L54: 4500 | M54: 5175 | N54: =IF(OR(H54="",H54=0),"",(H54-L54)/H54) -> 0.6875 | O54: =IF(OR(I54="",I54=0),"",(I54-M54)/I54) -> 0.70052083 | P54: =IF(H54="","",H54-L54) -> 9900 | Q54: =IF(I54="","",I54-M54) -> 12105 | R54: 15031.22 | S54: 20292.15 | T54: =IF(OR(S54="",F54="",F54=0),"",S54/F54) -> 2.70562 | U54: аналог moskva-demontazh.ru МК от 4000/т (мех., МСК) | V54: Наш тариф 20,3 тыс./т — ×2,7 к рынку
A55: 1.5.5 | B55: Алмазная резка железобетонных конструкций глубиной 230 мм | C55: м реза | E55: BET | F55: 2000 | G55: 2300 | H55: =IF(OR(F55="",F55=0),"",MAX(F55,IF(ISNUMBER('Нормы и нормо-часы'!K56),ROUNDUP('Нормы и нормо-часы'!K56/(1-$F$3),0),0))) -> 2000 | I55: =IF(OR(G55="",G55=0),"",MAX(G55,IF(ISNUMBER('Нормы и нормо-часы'!L56),ROUNDUP('Нормы и нормо-часы'!L56/(1-$F$3),0),0))) -> 2300 | J55: =IF(OR(F55="",F55=0),"",H55/F55-1) -> 0 | K55: =IF(OR(G55="",G55=0),"",I55/G55-1) -> 0 | L55: 1200 | M55: 1380 | N55: =IF(OR(H55="",H55=0),"",(H55-L55)/H55) -> 0.4 | O55: =IF(OR(I55="",I55=0),"",(I55-M55)/I55) -> 0.4 | P55: =IF(H55="","",H55-L55) -> 800 | Q55: =IF(I55="","",I55-M55) -> 920 | R55: 7593.97 | S55: 10251.86 | T55: =IF(OR(S55="",F55="",F55=0),"",S55/F55) -> 5.12593 | U55: прайс rezka-prof.ru 1125 (23–25 см), demont.spb 1600–3200, profi.ru 1500–10000 | V55: Наш тариф 10 252 руб/м — ×5 к рынку; износ сегментов включён
A56: 1.5.6 | B56: На каждые 100 мм увеличения глубины реза добавлять к расценке по алмазной резке ж/б конструкций | C56: м реза | E56: BET | F56: 800 | G56: 920 | H56: =IF(OR(F56="",F56=0),"",MAX(F56,IF(ISNUMBER('Нормы и нормо-часы'!K57),ROUNDUP('Нормы и нормо-часы'!K57/(1-$F$3),0),0))) -> 800 | I56: =IF(OR(G56="",G56=0),"",MAX(G56,IF(ISNUMBER('Нормы и нормо-часы'!L57),ROUNDUP('Нормы и нормо-часы'!L57/(1-$F$3),0),0))) -> 920 | J56: =IF(OR(F56="",F56=0),"",H56/F56-1) -> 0 | K56: =IF(OR(G56="",G56=0),"",I56/G56-1) -> 0 | L56: 480 | M56: 552 | N56: =IF(OR(H56="",H56=0),"",(H56-L56)/H56) -> 0.4 | O56: =IF(OR(I56="",I56=0),"",(I56-M56)/I56) -> 0.4 | P56: =IF(H56="","",H56-L56) -> 320 | Q56: =IF(I56="","",I56-M56) -> 368 | R56: 1872.83 | S56: 2528.32 | T56: =IF(OR(S56="",F56="",F56=0),"",S56/F56) -> 3.1604 | U56: аналог rezka-prof.ru (26–40 см 1800 против 1125) | V56: Наш тариф 2528 — ×3 к рынку
A57: 1.5.N1 | B57: Алмазное бурение отверстия в ж/б Ø до 100 мм глубиной до 200 мм | C57: шт | D57: да | E57: BET | F57: 1200 | G57: 1380 | H57: =IF(OR(F57="",F57=0),"",MAX(F57,IF(ISNUMBER('Нормы и нормо-часы'!K58),ROUNDUP('Нормы и нормо-часы'!K58/(1-$F$3),0),0))) -> 1200 | I57: =IF(OR(G57="",G57=0),"",MAX(G57,IF(ISNUMBER('Нормы и нормо-часы'!L58),ROUNDUP('Нормы и нормо-часы'!L58/(1-$F$3),0),0))) -> 1380 | J57: =IF(OR(F57="",F57=0),"",H57/F57-1) -> 0 | K57: =IF(OR(G57="",G57=0),"",I57/G57-1) -> 0 | L57: 720 | M57: 828 | N57: =IF(OR(H57="",H57=0),"",(H57-L57)/H57) -> 0.4 | O57: =IF(OR(I57="",I57=0),"",(I57-M57)/I57) -> 0.4 | P57: =IF(H57="","",H57-L57) -> 480 | Q57: =IF(I57="","",I57-M57) -> 552 | T57: =IF(OR(S57="",F57="",F57=0),"",S57/F57) | U57: аналог rezka-prof.ru / bnk-servis.ru | V57: Глубже — пропорционально
A58: 1.5.N2 | B58: Демонтаж металлических лестниц, площадок, антресолей | C58: т | D58: да | E58: SVA | F58: 12000 | G58: 13800 | H58: =IF(OR(F58="",F58=0),"",MAX(F58,IF(ISNUMBER('Нормы и нормо-часы'!K59),ROUNDUP('Нормы и нормо-часы'!K59/(1-$F$3),0),0))) -> 21600 | I58: =IF(OR(G58="",G58=0),"",MAX(G58,IF(ISNUMBER('Нормы и нормо-часы'!L59),ROUNDUP('Нормы и нормо-часы'!L59/(1-$F$3),0),0))) -> 25920 | J58: =IF(OR(F58="",F58=0),"",H58/F58-1) -> 0.8 | K58: =IF(OR(G58="",G58=0),"",I58/G58-1) -> 0.87826087 | L58: 7200 | M58: 8280 | N58: =IF(OR(H58="",H58=0),"",(H58-L58)/H58) -> 0.66666667 | O58: =IF(OR(I58="",I58=0),"",(I58-M58)/I58) -> 0.68055556 | P58: =IF(H58="","",H58-L58) -> 14400 | Q58: =IF(I58="","",I58-M58) -> 17640 | T58: =IF(OR(S58="",F58="",F58=0),"",S58/F58) | U58: аналог 1.5.1
A59: 1.6 Демонтажные работы полов
A60: 1.6.1 | B60: Демонтаж стяжек полов до основания | C60: м3 | E60: RAZ | F60: 6500 | G60: 7475 | H60: =IF(OR(F60="",F60=0),"",MAX(F60,IF(ISNUMBER('Нормы и нормо-часы'!K61),ROUNDUP('Нормы и нормо-часы'!K61/(1-$F$3),0),0))) -> 6600 | I60: =IF(OR(G60="",G60=0),"",MAX(G60,IF(ISNUMBER('Нормы и нормо-часы'!L61),ROUNDUP('Нормы и нормо-часы'!L61/(1-$F$3),0),0))) -> 7920 | J60: =IF(OR(F60="",F60=0),"",H60/F60-1) -> 0.015384615 | K60: =IF(OR(G60="",G60=0),"",I60/G60-1) -> 0.059531773 | L60: 3900 | M60: 4485 | N60: =IF(OR(H60="",H60=0),"",(H60-L60)/H60) -> 0.40909091 | O60: =IF(OR(I60="",I60=0),"",(I60-M60)/I60) -> 0.43371212 | P60: =IF(H60="","",H60-L60) -> 2700 | Q60: =IF(I60="","",I60-M60) -> 3435 | R60: 4018.49 | S60: 5424.96 | T60: =IF(OR(S60="",F60="",F60=0),"",S60/F60) -> 0.83460923 | U60: прайс remontvspb.ru 380/м2 (3 см), stroygarant78.ru 350/м2 (5 см) → 6500–9000/м3
A61: 1.6.2 | B61: Разборка бетонных оснований под полы | C61: м3 | E61: RAZ | F61: 8000 | G61: 9200 | H61: =IF(OR(F61="",F61=0),"",MAX(F61,IF(ISNUMBER('Нормы и нормо-часы'!K62),ROUNDUP('Нормы и нормо-часы'!K62/(1-$F$3),0),0))) -> 8800 | I61: =IF(OR(G61="",G61=0),"",MAX(G61,IF(ISNUMBER('Нормы и нормо-часы'!L62),ROUNDUP('Нормы и нормо-часы'!L62/(1-$F$3),0),0))) -> 10560 | J61: =IF(OR(F61="",F61=0),"",H61/F61-1) -> 0.1 | K61: =IF(OR(G61="",G61=0),"",I61/G61-1) -> 0.14782609 | L61: 4800 | M61: 5520 | N61: =IF(OR(H61="",H61=0),"",(H61-L61)/H61) -> 0.45454545 | O61: =IF(OR(I61="",I61=0),"",(I61-M61)/I61) -> 0.47727273 | P61: =IF(H61="","",H61-L61) -> 4000 | Q61: =IF(I61="","",I61-M61) -> 5040 | R61: 10172.51 | S61: 13732.89 | T61: =IF(OR(S61="",F61="",F61=0),"",S61/F61) -> 1.7166112 | U61: аналог remontvspb.ru монолитный пол 1100 руб/м2 (~12 см) | V61: Наш тариф 13,7 тыс. — ×1,7
A62: 1.6.3 | B62: Разборка плинтусов деревянных и из пластмассовых материалов | C62: мп | E62: RAZ | F62: 50 | G62: 57.5 | H62: =IF(OR(F62="",F62=0),"",MAX(F62,IF(ISNUMBER('Нормы и нормо-часы'!K63),ROUNDUP('Нормы и нормо-часы'!K63/(1-$F$3),0),0))) -> 50 | I62: =IF(OR(G62="",G62=0),"",MAX(G62,IF(ISNUMBER('Нормы и нормо-часы'!L63),ROUNDUP('Нормы и нормо-часы'!L63/(1-$F$3),0),0))) -> 57.5 | J62: =IF(OR(F62="",F62=0),"",H62/F62-1) -> 0 | K62: =IF(OR(G62="",G62=0),"",I62/G62-1) -> 0 | L62: 30 | M62: 34.5 | N62: =IF(OR(H62="",H62=0),"",(H62-L62)/H62) -> 0.4 | O62: =IF(OR(I62="",I62=0),"",(I62-M62)/I62) -> 0.4 | P62: =IF(H62="","",H62-L62) -> 20 | Q62: =IF(I62="","",I62-M62) -> 23 | R62: 37.19 | S62: 50.21 | T62: =IF(OR(S62="",F62="",F62=0),"",S62/F62) -> 1.0042 | U62: прайс demontazh.spb.ru 30, stroygarant78.ru 40 руб/мп
A63: 1.6.4 | B63: Разборка плинтусов цементных и из керамогранита | C63: мп | E63: RAZ | F63: 120 | G63: 138 | H63: =IF(OR(F63="",F63=0),"",MAX(F63,IF(ISNUMBER('Нормы и нормо-часы'!K64),ROUNDUP('Нормы и нормо-часы'!K64/(1-$F$3),0),0))) -> 120 | I63: =IF(OR(G63="",G63=0),"",MAX(G63,IF(ISNUMBER('Нормы и нормо-часы'!L64),ROUNDUP('Нормы и нормо-часы'!L64/(1-$F$3),0),0))) -> 138 | J63: =IF(OR(F63="",F63=0),"",H63/F63-1) -> 0 | K63: =IF(OR(G63="",G63=0),"",I63/G63-1) -> 0 | L63: 70 | M63: 80.5 | N63: =IF(OR(H63="",H63=0),"",(H63-L63)/H63) -> 0.41666667 | O63: =IF(OR(I63="",I63=0),"",(I63-M63)/I63) -> 0.41666667 | P63: =IF(H63="","",H63-L63) -> 50 | Q63: =IF(I63="","",I63-M63) -> 57.5 | R63: 140.6 | S63: 189.81 | T63: =IF(OR(S63="",F63="",F63=0),"",S63/F63) -> 1.58175 | U63: аналог (керамический плинтус на клею)
A64: 1.6.5 | B64: Разборка покрытий полов из древесностружечных плит в один слой | C64: м2 | E64: RAZ | F64: 100 | G64: 115 | H64: =IF(OR(F64="",F64=0),"",MAX(F64,IF(ISNUMBER('Нормы и нормо-часы'!K65),ROUNDUP('Нормы и нормо-часы'!K65/(1-$F$3),0),0))) -> 100 | I64: =IF(OR(G64="",G64=0),"",MAX(G64,IF(ISNUMBER('Нормы и нормо-часы'!L65),ROUNDUP('Нормы и нормо-часы'!L65/(1-$F$3),0),0))) -> 115 | J64: =IF(OR(F64="",F64=0),"",H64/F64-1) -> 0 | K64: =IF(OR(G64="",G64=0),"",I64/G64-1) -> 0 | L64: 60 | M64: 69 | N64: =IF(OR(H64="",H64=0),"",(H64-L64)/H64) -> 0.4 | O64: =IF(OR(I64="",I64=0),"",(I64-M64)/I64) -> 0.4 | P64: =IF(H64="","",H64-L64) -> 40 | Q64: =IF(I64="","",I64-M64) -> 46 | R64: 164.36 | S64: 221.89 | T64: =IF(OR(S64="",F64="",F64=0),"",S64/F64) -> 2.2189 | U64: аналог remontvspb.ru фанера/оргалит 80 руб/м2 | V64: Наш тариф ×2,2
A65: 1.6.6 | B65: Разборка покрытий полов из керамических плиток | C65: м2 | E65: RAZ | F65: 300 | G65: 345 | H65: =IF(OR(F65="",F65=0),"",MAX(F65,IF(ISNUMBER('Нормы и нормо-часы'!K66),ROUNDUP('Нормы и нормо-часы'!K66/(1-$F$3),0),0))) -> 300 | I65: =IF(OR(G65="",G65=0),"",MAX(G65,IF(ISNUMBER('Нормы и нормо-часы'!L66),ROUNDUP('Нормы и нормо-часы'!L66/(1-$F$3),0),0))) -> 345 | J65: =IF(OR(F65="",F65=0),"",H65/F65-1) -> 0 | K65: =IF(OR(G65="",G65=0),"",I65/G65-1) -> 0 | L65: 180 | M65: 207 | N65: =IF(OR(H65="",H65=0),"",(H65-L65)/H65) -> 0.4 | O65: =IF(OR(I65="",I65=0),"",(I65-M65)/I65) -> 0.4 | P65: =IF(H65="","",H65-L65) -> 120 | Q65: =IF(I65="","",I65-M65) -> 138 | R65: 513.19 | S65: 692.81 | T65: =IF(OR(S65="",F65="",F65=0),"",S65/F65) -> 2.3093667 | U65: прайс stroygarant78.ru 300, remontvspb.ru 300, demontazh.spb.ru 150 | V65: Наш тариф 693 — ×2,3
A66: 1.6.7 | B66: Разборка покрытий полов из керамогранитных плит толщиной более 15 мм с расчисткой основания от клея | C66: м2 | E66: RAZ | F66: 650 | G66: 747 | H66: =IF(OR(F66="",F66=0),"",MAX(F66,IF(ISNUMBER('Нормы и нормо-часы'!K67),ROUNDUP('Нормы и нормо-часы'!K67/(1-$F$3),0),0))) -> 650 | I66: =IF(OR(G66="",G66=0),"",MAX(G66,IF(ISNUMBER('Нормы и нормо-часы'!L67),ROUNDUP('Нормы и нормо-часы'!L67/(1-$F$3),0),0))) -> 747 | J66: =IF(OR(F66="",F66=0),"",H66/F66-1) -> 0 | K66: =IF(OR(G66="",G66=0),"",I66/G66-1) -> 0 | L66: 400 | M66: 460 | N66: =IF(OR(H66="",H66=0),"",(H66-L66)/H66) -> 0.38461538 | O66: =IF(OR(I66="",I66=0),"",(I66-M66)/I66) -> 0.38420348 | P66: =IF(H66="","",H66-L66) -> 250 | Q66: =IF(I66="","",I66-M66) -> 287 | R66: 1691.47 | S66: 2283.48 | T66: =IF(OR(S66="",F66="",F66=0),"",S66/F66) -> 3.5130462 | U66: аналог 1.6.6 ×2 (толстый керамогранит + зачистка клея) | V66: Наш тариф 2283 — ×3,5
A67: 1.6.8 | B67: Разборка покрытий полов из линолеума и релина | C67: м2 | E67: RAZ | F67: 80 | G67: 92 | H67: =IF(OR(F67="",F67=0),"",MAX(F67,IF(ISNUMBER('Нормы и нормо-часы'!K68),ROUNDUP('Нормы и нормо-часы'!K68/(1-$F$3),0),0))) -> 80 | I67: =IF(OR(G67="",G67=0),"",MAX(G67,IF(ISNUMBER('Нормы и нормо-часы'!L68),ROUNDUP('Нормы и нормо-часы'!L68/(1-$F$3),0),0))) -> 92 | J67: =IF(OR(F67="",F67=0),"",H67/F67-1) -> 0 | K67: =IF(OR(G67="",G67=0),"",I67/G67-1) -> 0 | L67: 50 | M67: 57.5 | N67: =IF(OR(H67="",H67=0),"",(H67-L67)/H67) -> 0.375 | O67: =IF(OR(I67="",I67=0),"",(I67-M67)/I67) -> 0.375 | P67: =IF(H67="","",H67-L67) -> 30 | Q67: =IF(I67="","",I67-M67) -> 34.5 | R67: 117.05 | S67: 158.02 | T67: =IF(OR(S67="",F67="",F67=0),"",S67/F67) -> 1.97525 | U67: прайс remontvspb.ru 100, stroygarant78.ru 90, demontazh.spb.ru 50 | V67: Наш тариф ×2
A68: 1.6.9 | B68: Снятие алюминиевого порога | C68: мп | E68: RAZ | F68: 120 | G68: 138 | H68: =IF(OR(F68="",F68=0),"",MAX(F68,IF(ISNUMBER('Нормы и нормо-часы'!K69),ROUNDUP('Нормы и нормо-часы'!K69/(1-$F$3),0),0))) -> 120 | I68: =IF(OR(G68="",G68=0),"",MAX(G68,IF(ISNUMBER('Нормы и нормо-часы'!L69),ROUNDUP('Нормы и нормо-часы'!L69/(1-$F$3),0),0))) -> 138 | J68: =IF(OR(F68="",F68=0),"",H68/F68-1) -> 0 | K68: =IF(OR(G68="",G68=0),"",I68/G68-1) -> 0 | L68: 70 | M68: 80.5 | N68: =IF(OR(H68="",H68=0),"",(H68-L68)/H68) -> 0.41666667 | O68: =IF(OR(I68="",I68=0),"",(I68-M68)/I68) -> 0.41666667 | P68: =IF(H68="","",H68-L68) -> 50 | Q68: =IF(I68="","",I68-M68) -> 57.5 | R68: 207.69 | S68: 280.38 | T68: =IF(OR(S68="",F68="",F68=0),"",S68/F68) -> 2.3365 | U68: аналог 1.6.4
A69: 1.6.10 | B69: Разборка покрытий полов из плиток поливинилхлоридных | C69: м2 | E69: RAZ | F69: 150 | G69: 172 | H69: =IF(OR(F69="",F69=0),"",MAX(F69,IF(ISNUMBER('Нормы и нормо-часы'!K70),ROUNDUP('Нормы и нормо-часы'!K70/(1-$F$3),0),0))) -> 150 | I69: =IF(OR(G69="",G69=0),"",MAX(G69,IF(ISNUMBER('Нормы и нормо-часы'!L70),ROUNDUP('Нормы и нормо-часы'!L70/(1-$F$3),0),0))) -> 172 | J69: =IF(OR(F69="",F69=0),"",H69/F69-1) -> 0 | K69: =IF(OR(G69="",G69=0),"",I69/G69-1) -> 0 | L69: 90 | M69: 103 | N69: =IF(OR(H69="",H69=0),"",(H69-L69)/H69) -> 0.4 | O69: =IF(OR(I69="",I69=0),"",(I69-M69)/I69) -> 0.40116279 | P69: =IF(H69="","",H69-L69) -> 60 | Q69: =IF(I69="","",I69-M69) -> 69 | R69: 368.29 | S69: 497.19 | T69: =IF(OR(S69="",F69="",F69=0),"",S69/F69) -> 3.3146 | U69: прайс remontvspb.ru 100 (1 слой) + зачистка клея | V69: Наш тариф 497 — ×3,3
A70: 1.6.11 | B70: Разборка покрытий полов цементных толщиной до 150 мм | C70: м2 | E70: RAZ | F70: 1000 | G70: 1150 | H70: =IF(OR(F70="",F70=0),"",MAX(F70,IF(ISNUMBER('Нормы и нормо-часы'!K71),ROUNDUP('Нормы и нормо-часы'!K71/(1-$F$3),0),0))) -> 1027 | I70: =IF(OR(G70="",G70=0),"",MAX(G70,IF(ISNUMBER('Нормы и нормо-часы'!L71),ROUNDUP('Нормы и нормо-часы'!L71/(1-$F$3),0),0))) -> 1232 | J70: =IF(OR(F70="",F70=0),"",H70/F70-1) -> 0.027 | K70: =IF(OR(G70="",G70=0),"",I70/G70-1) -> 0.071304348 | L70: 600 | M70: 690 | N70: =IF(OR(H70="",H70=0),"",(H70-L70)/H70) -> 0.4157741 | O70: =IF(OR(I70="",I70=0),"",(I70-M70)/I70) -> 0.43993506 | P70: =IF(H70="","",H70-L70) -> 427 | Q70: =IF(I70="","",I70-M70) -> 542 | R70: 1321.01 | S70: 1783.36 | T70: =IF(OR(S70="",F70="",F70=0),"",S70/F70) -> 1.78336 | U70: прайс remontvspb.ru монолитный пол 1100 руб/м2
A71: 1.6.12 | B71: Разборка покрытий полов из керамогранитных плит толщиной до 15 мм с расчисткой основания от клея | C71: м2 | E71: RAZ | F71: 450 | G71: 518 | H71: =IF(OR(F71="",F71=0),"",MAX(F71,IF(ISNUMBER('Нормы и нормо-часы'!K72),ROUNDUP('Нормы и нормо-часы'!K72/(1-$F$3),0),0))) -> 450 | I71: =IF(OR(G71="",G71=0),"",MAX(G71,IF(ISNUMBER('Нормы и нормо-часы'!L72),ROUNDUP('Нормы и нормо-часы'!L72/(1-$F$3),0),0))) -> 518 | J71: =IF(OR(F71="",F71=0),"",H71/F71-1) -> 0 | K71: =IF(OR(G71="",G71=0),"",I71/G71-1) -> 0 | L71: 270 | M71: 310 | N71: =IF(OR(H71="",H71=0),"",(H71-L71)/H71) -> 0.4 | O71: =IF(OR(I71="",I71=0),"",(I71-M71)/I71) -> 0.4015444 | P71: =IF(H71="","",H71-L71) -> 180 | Q71: =IF(I71="","",I71-M71) -> 208 | R71: 979.6 | S71: 1322.46 | T71: =IF(OR(S71="",F71="",F71=0),"",S71/F71) -> 2.9388 | U71: аналог 1.6.6 + зачистка клея | V71: Наш тариф 1322 — ×2,9
A72: 1.6.N1 | B72: Разборка покрытия из ламината / паркетной доски | C72: м2 | D72: да | E72: RAZ | F72: 90 | G72: 103 | H72: =IF(OR(F72="",F72=0),"",MAX(F72,IF(ISNUMBER('Нормы и нормо-часы'!K73),ROUNDUP('Нормы и нормо-часы'!K73/(1-$F$3),0),0))) -> 90 | I72: =IF(OR(G72="",G72=0),"",MAX(G72,IF(ISNUMBER('Нормы и нормо-часы'!L73),ROUNDUP('Нормы и нормо-часы'!L73/(1-$F$3),0),0))) -> 103 | J72: =IF(OR(F72="",F72=0),"",H72/F72-1) -> 0 | K72: =IF(OR(G72="",G72=0),"",I72/G72-1) -> 0 | L72: 55 | M72: 63 | N72: =IF(OR(H72="",H72=0),"",(H72-L72)/H72) -> 0.38888889 | O72: =IF(OR(I72="",I72=0),"",(I72-M72)/I72) -> 0.38834951 | P72: =IF(H72="","",H72-L72) -> 35 | Q72: =IF(I72="","",I72-M72) -> 40 | T72: =IF(OR(S72="",F72="",F72=0),"",S72/F72) | U72: прайс demontazh.spb.ru 80 руб/м2
A73: 1.6.N2 | B73: Демонтаж ковролина / ковровой плитки с зачисткой клея | C73: м2 | D73: да | E73: RAZ | F73: 150 | G73: 172 | H73: =IF(OR(F73="",F73=0),"",MAX(F73,IF(ISNUMBER('Нормы и нормо-часы'!K74),ROUNDUP('Нормы и нормо-часы'!K74/(1-$F$3),0),0))) -> 150 | I73: =IF(OR(G73="",G73=0),"",MAX(G73,IF(ISNUMBER('Нормы и нормо-часы'!L74),ROUNDUP('Нормы и нормо-часы'!L74/(1-$F$3),0),0))) -> 172 | J73: =IF(OR(F73="",F73=0),"",H73/F73-1) -> 0 | K73: =IF(OR(G73="",G73=0),"",I73/G73-1) -> 0 | L73: 90 | M73: 103 | N73: =IF(OR(H73="",H73=0),"",(H73-L73)/H73) -> 0.4 | O73: =IF(OR(I73="",I73=0),"",(I73-M73)/I73) -> 0.40116279 | P73: =IF(H73="","",H73-L73) -> 60 | Q73: =IF(I73="","",I73-M73) -> 69 | T73: =IF(OR(S73="",F73="",F73=0),"",S73/F73) | U73: аналог stroygarant78.ru линолеум/ковролин 90 + зачистка
A74: 1.6.N3 | B74: Удаление полимерного (эпоксидного/ПУ) покрытия пола фрезерованием | C74: м2 | D74: да | E74: PLI | F74: 450 | G74: 518 | H74: =IF(OR(F74="",F74=0),"",MAX(F74,IF(ISNUMBER('Нормы и нормо-часы'!K75),ROUNDUP('Нормы и нормо-часы'!K75/(1-$F$3),0),0))) -> 450 | I74: =IF(OR(G74="",G74=0),"",MAX(G74,IF(ISNUMBER('Нормы и нормо-часы'!L75),ROUNDUP('Нормы и нормо-часы'!L75/(1-$F$3),0),0))) -> 518 | J74: =IF(OR(F74="",F74=0),"",H74/F74-1) -> 0 | K74: =IF(OR(G74="",G74=0),"",I74/G74-1) -> 0 | L74: 270 | M74: 310 | N74: =IF(OR(H74="",H74=0),"",(H74-L74)/H74) -> 0.4 | O74: =IF(OR(I74="",I74=0),"",(I74-M74)/I74) -> 0.4015444 | P74: =IF(H74="","",H74-L74) -> 180 | Q74: =IF(I74="","",I74-M74) -> 208 | T74: =IF(OR(S74="",F74="",F74=0),"",S74/F74) | U74: расчёт | V74: Фрезеровальная машина и пылесос — в цене подрядчика
A75: 1.6.N4 | B75: Демонтаж фальшпола (съёмного) с опорами | C75: м2 | D75: да | E75: RAZ | F75: 300 | G75: 345 | H75: =IF(OR(F75="",F75=0),"",MAX(F75,IF(ISNUMBER('Нормы и нормо-часы'!K76),ROUNDUP('Нормы и нормо-часы'!K76/(1-$F$3),0),0))) -> 300 | I75: =IF(OR(G75="",G75=0),"",MAX(G75,IF(ISNUMBER('Нормы и нормо-часы'!L76),ROUNDUP('Нормы и нормо-часы'!L76/(1-$F$3),0),0))) -> 345 | J75: =IF(OR(F75="",F75=0),"",H75/F75-1) -> 0 | K75: =IF(OR(G75="",G75=0),"",I75/G75-1) -> 0 | L75: 180 | M75: 207 | N75: =IF(OR(H75="",H75=0),"",(H75-L75)/H75) -> 0.4 | O75: =IF(OR(I75="",I75=0),"",(I75-M75)/I75) -> 0.4 | P75: =IF(H75="","",H75-L75) -> 120 | Q75: =IF(I75="","",I75-M75) -> 138 | T75: =IF(OR(S75="",F75="",F75=0),"",S75/F75) | U75: расчёт
A76: 1.7 Демонтажные работы потолка
A77: 1.7.1 | B77: Демонтаж утеплителя потолков | C77: м2 | E77: RAZ | F77: 120 | G77: 138 | H77: =IF(OR(F77="",F77=0),"",MAX(F77,IF(ISNUMBER('Нормы и нормо-часы'!K78),ROUNDUP('Нормы и нормо-часы'!K78/(1-$F$3),0),0))) -> 120 | I77: =IF(OR(G77="",G77=0),"",MAX(G77,IF(ISNUMBER('Нормы и нормо-часы'!L78),ROUNDUP('Нормы и нормо-часы'!L78/(1-$F$3),0),0))) -> 138 | J77: =IF(OR(F77="",F77=0),"",H77/F77-1) -> 0 | K77: =IF(OR(G77="",G77=0),"",I77/G77-1) -> 0 | L77: 70 | M77: 80.5 | N77: =IF(OR(H77="",H77=0),"",(H77-L77)/H77) -> 0.41666667 | O77: =IF(OR(I77="",I77=0),"",(I77-M77)/I77) -> 0.41666667 | P77: =IF(H77="","",H77-L77) -> 50 | Q77: =IF(I77="","",I77-M77) -> 57.5 | R77: 208.73 | S77: 281.79 | T77: =IF(OR(S77="",F77="",F77=0),"",S77/F77) -> 2.34825 | U77: аналог 1.8.7
A78: 1.7.2 | B78: Отбивка штукатурки с поверхности потолка | C78: м2 | E78: OTD | F78: 350 | G78: 402 | H78: =IF(OR(F78="",F78=0),"",MAX(F78,IF(ISNUMBER('Нормы и нормо-часы'!K79),ROUNDUP('Нормы и нормо-часы'!K79/(1-$F$3),0),0))) -> 500 | I78: =IF(OR(G78="",G78=0),"",MAX(G78,IF(ISNUMBER('Нормы и нормо-часы'!L79),ROUNDUP('Нормы и нормо-часы'!L79/(1-$F$3),0),0))) -> 600 | J78: =IF(OR(F78="",F78=0),"",H78/F78-1) -> 0.42857143 | K78: =IF(OR(G78="",G78=0),"",I78/G78-1) -> 0.49253731 | L78: 210 | M78: 241 | N78: =IF(OR(H78="",H78=0),"",(H78-L78)/H78) -> 0.58 | O78: =IF(OR(I78="",I78=0),"",(I78-M78)/I78) -> 0.59833333 | P78: =IF(H78="","",H78-L78) -> 290 | Q78: =IF(I78="","",I78-M78) -> 359 | R78: 265.65 | S78: 358.63 | T78: =IF(OR(S78="",F78="",F78=0),"",S78/F78) -> 1.0246571 | U78: аналог remontvspb.ru штукатурка 200–500 ×1,3 за потолок
A79: 1.7.3 | B79: Разборка облицовки потолков из гипсокартонных листов с каркасом | C79: м2 | E79: OTD | F79: 220 | G79: 253 | H79: =IF(OR(F79="",F79=0),"",MAX(F79,IF(ISNUMBER('Нормы и нормо-часы'!K80),ROUNDUP('Нормы и нормо-часы'!K80/(1-$F$3),0),0))) -> 251 | I79: =IF(OR(G79="",G79=0),"",MAX(G79,IF(ISNUMBER('Нормы и нормо-часы'!L80),ROUNDUP('Нормы и нормо-часы'!L80/(1-$F$3),0),0))) -> 300 | J79: =IF(OR(F79="",F79=0),"",H79/F79-1) -> 0.14090909 | K79: =IF(OR(G79="",G79=0),"",I79/G79-1) -> 0.18577075 | L79: 130 | M79: 150 | N79: =IF(OR(H79="",H79=0),"",(H79-L79)/H79) -> 0.48207171 | O79: =IF(OR(I79="",I79=0),"",(I79-M79)/I79) -> 0.5 | P79: =IF(H79="","",H79-L79) -> 121 | Q79: =IF(I79="","",I79-M79) -> 150 | R79: 111.09 | S79: 149.97 | T79: =IF(OR(S79="",F79="",F79=0),"",S79/F79) -> 0.68168182 | U79: прайс stroygarant78.ru ГКЛ потолок 200, moskva-demontazh.ru от 100
A80: 1.7.4 | B80: Разборка подвесного потолка Грильято включая направляющие | C80: м2 | E80: OTD | F80: 180 | G80: 207 | H80: =IF(OR(F80="",F80=0),"",MAX(F80,IF(ISNUMBER('Нормы и нормо-часы'!K81),ROUNDUP('Нормы и нормо-часы'!K81/(1-$F$3),0),0))) -> 200 | I80: =IF(OR(G80="",G80=0),"",MAX(G80,IF(ISNUMBER('Нормы и нормо-часы'!L81),ROUNDUP('Нормы и нормо-часы'!L81/(1-$F$3),0),0))) -> 240 | J80: =IF(OR(F80="",F80=0),"",H80/F80-1) -> 0.11111111 | K80: =IF(OR(G80="",G80=0),"",I80/G80-1) -> 0.15942029 | L80: 110 | M80: 126 | N80: =IF(OR(H80="",H80=0),"",(H80-L80)/H80) -> 0.45 | O80: =IF(OR(I80="",I80=0),"",(I80-M80)/I80) -> 0.475 | P80: =IF(H80="","",H80-L80) -> 90 | Q80: =IF(I80="","",I80-M80) -> 114 | R80: 399.26 | S80: 539 | T80: =IF(OR(S80="",F80="",F80=0),"",S80/F80) -> 2.9944444 | U80: аналог demontazh.spb.ru подвесные 200 руб/м2 | V80: Наш тариф 539 — ×3
A81: 1.7.5 | B81: Разборка подвесной системы потолка | C81: м2 | E81: OTD | F81: 120 | G81: 138 | H81: =IF(OR(F81="",F81=0),"",MAX(F81,IF(ISNUMBER('Нормы и нормо-часы'!K82),ROUNDUP('Нормы и нормо-часы'!K82/(1-$F$3),0),0))) -> 120 | I81: =IF(OR(G81="",G81=0),"",MAX(G81,IF(ISNUMBER('Нормы и нормо-часы'!L82),ROUNDUP('Нормы и нормо-часы'!L82/(1-$F$3),0),0))) -> 144 | J81: =IF(OR(F81="",F81=0),"",H81/F81-1) -> 0 | K81: =IF(OR(G81="",G81=0),"",I81/G81-1) -> 0.043478261 | L81: 70 | M81: 80.5 | N81: =IF(OR(H81="",H81=0),"",(H81-L81)/H81) -> 0.41666667 | O81: =IF(OR(I81="",I81=0),"",(I81-M81)/I81) -> 0.44097222 | P81: =IF(H81="","",H81-L81) -> 50 | Q81: =IF(I81="","",I81-M81) -> 63.5 | R81: 402.19 | S81: 542.96 | T81: =IF(OR(S81="",F81="",F81=0),"",S81/F81) -> 4.5246667 | U81: аналог demontazh.spb.ru подвесные 200 | V81: Неясно, что входит (только подвесы/каркас?); наш тариф ×4,5
A82: 1.7.6 | B82: Разборка подвесных каркасов, подшивных потолков из металлических уголков (не применимо для направляющих) | C82: м2 | E82: OTD | F82: 150 | G82: 172 | H82: =IF(OR(F82="",F82=0),"",MAX(F82,IF(ISNUMBER('Нормы и нормо-часы'!K83),ROUNDUP('Нормы и нормо-часы'!K83/(1-$F$3),0),0))) -> 180 | I82: =IF(OR(G82="",G82=0),"",MAX(G82,IF(ISNUMBER('Нормы и нормо-часы'!L83),ROUNDUP('Нормы и нормо-часы'!L83/(1-$F$3),0),0))) -> 216 | J82: =IF(OR(F82="",F82=0),"",H82/F82-1) -> 0.2 | K82: =IF(OR(G82="",G82=0),"",I82/G82-1) -> 0.25581395 | L82: 90 | M82: 103 | N82: =IF(OR(H82="",H82=0),"",(H82-L82)/H82) -> 0.5 | O82: =IF(OR(I82="",I82=0),"",(I82-M82)/I82) -> 0.52314815 | P82: =IF(H82="","",H82-L82) -> 90 | Q82: =IF(I82="","",I82-M82) -> 113 | R82: 125.1 | S82: 168.89 | T82: =IF(OR(S82="",F82="",F82=0),"",S82/F82) -> 1.1259333 | U82: аналог 1.7.3
A83: 1.7.7 | B83: Разборка подвесных потолков из металлических кассет, включая направляющие | C83: м2 | E83: OTD | F83: 200 | G83: 230 | H83: =IF(OR(F83="",F83=0),"",MAX(F83,IF(ISNUMBER('Нормы и нормо-часы'!K84),ROUNDUP('Нормы и нормо-часы'!K84/(1-$F$3),0),0))) -> 220 | I83: =IF(OR(G83="",G83=0),"",MAX(G83,IF(ISNUMBER('Нормы и нормо-часы'!L84),ROUNDUP('Нормы и нормо-часы'!L84/(1-$F$3),0),0))) -> 264 | J83: =IF(OR(F83="",F83=0),"",H83/F83-1) -> 0.1 | K83: =IF(OR(G83="",G83=0),"",I83/G83-1) -> 0.14782609 | L83: 120 | M83: 138 | N83: =IF(OR(H83="",H83=0),"",(H83-L83)/H83) -> 0.45454545 | O83: =IF(OR(I83="",I83=0),"",(I83-M83)/I83) -> 0.47727273 | P83: =IF(H83="","",H83-L83) -> 100 | Q83: =IF(I83="","",I83-M83) -> 126 | R83: 402.19 | S83: 542.96 | T83: =IF(OR(S83="",F83="",F83=0),"",S83/F83) -> 2.7148 | U83: аналог demontazh.spb.ru 200 руб/м2 | V83: Наш тариф ×2,7
A84: 1.7.8 | B84: Разборка подвесных потолков типа <Армстронг> включая направляющие | C84: м2 | E84: OTD | F84: 180 | G84: 207 | H84: =IF(OR(F84="",F84=0),"",MAX(F84,IF(ISNUMBER('Нормы и нормо-часы'!K85),ROUNDUP('Нормы и нормо-часы'!K85/(1-$F$3),0),0))) -> 180 | I84: =IF(OR(G84="",G84=0),"",MAX(G84,IF(ISNUMBER('Нормы и нормо-часы'!L85),ROUNDUP('Нормы и нормо-часы'!L85/(1-$F$3),0),0))) -> 216 | J84: =IF(OR(F84="",F84=0),"",H84/F84-1) -> 0 | K84: =IF(OR(G84="",G84=0),"",I84/G84-1) -> 0.043478261 | L84: 110 | M84: 126 | N84: =IF(OR(H84="",H84=0),"",(H84-L84)/H84) -> 0.38888889 | O84: =IF(OR(I84="",I84=0),"",(I84-M84)/I84) -> 0.41666667 | P84: =IF(H84="","",H84-L84) -> 70 | Q84: =IF(I84="","",I84-M84) -> 90 | R84: 404.96 | S84: 546.7 | T84: =IF(OR(S84="",F84="",F84=0),"",S84/F84) -> 3.0372222 | U84: прайс demontazh.spb.ru 200, zoon.ru (СПб) 250 руб/м2 | V84: Наш тариф 547 — ×3
A85: 1.7.9 | B85: Разборка потолков реечных алюминиевых включая направляющие | C85: м2 | E85: OTD | F85: 200 | G85: 230 | H85: =IF(OR(F85="",F85=0),"",MAX(F85,IF(ISNUMBER('Нормы и нормо-часы'!K86),ROUNDUP('Нормы и нормо-часы'!K86/(1-$F$3),0),0))) -> 220 | I85: =IF(OR(G85="",G85=0),"",MAX(G85,IF(ISNUMBER('Нормы и нормо-часы'!L86),ROUNDUP('Нормы и нормо-часы'!L86/(1-$F$3),0),0))) -> 264 | J85: =IF(OR(F85="",F85=0),"",H85/F85-1) -> 0.1 | K85: =IF(OR(G85="",G85=0),"",I85/G85-1) -> 0.14782609 | L85: 120 | M85: 138 | N85: =IF(OR(H85="",H85=0),"",(H85-L85)/H85) -> 0.45454545 | O85: =IF(OR(I85="",I85=0),"",(I85-M85)/I85) -> 0.47727273 | P85: =IF(H85="","",H85-L85) -> 100 | Q85: =IF(I85="","",I85-M85) -> 126 | R85: 403.7 | S85: 545 | T85: =IF(OR(S85="",F85="",F85=0),"",S85/F85) -> 2.725 | U85: прайс stroygarant78.ru реечный 200 руб/м2 | V85: Наш тариф ×2,7
A86: 1.7.10 | B86: Разборка реечного потолка из ламелей (потолок Кубота) | C86: м2 | E86: OTD | F86: 230 | G86: 264 | H86: =IF(OR(F86="",F86=0),"",MAX(F86,IF(ISNUMBER('Нормы и нормо-часы'!K87),ROUNDUP('Нормы и нормо-часы'!K87/(1-$F$3),0),0))) -> 251 | I86: =IF(OR(G86="",G86=0),"",MAX(G86,IF(ISNUMBER('Нормы и нормо-часы'!L87),ROUNDUP('Нормы и нормо-часы'!L87/(1-$F$3),0),0))) -> 300 | J86: =IF(OR(F86="",F86=0),"",H86/F86-1) -> 0.091304348 | K86: =IF(OR(G86="",G86=0),"",I86/G86-1) -> 0.13636364 | L86: 140 | M86: 161 | N86: =IF(OR(H86="",H86=0),"",(H86-L86)/H86) -> 0.44223108 | O86: =IF(OR(I86="",I86=0),"",(I86-M86)/I86) -> 0.46333333 | P86: =IF(H86="","",H86-L86) -> 111 | Q86: =IF(I86="","",I86-M86) -> 139 | R86: 414.03 | S86: 558.94 | T86: =IF(OR(S86="",F86="",F86=0),"",S86/F86) -> 2.4301739 | U86: аналог 1.7.9
A87: 1.7.11 | B87: Снятие акустических плит, металлокассет подвесного потолка без направляющих | C87: шт | E87: OTD | F87: 40 | G87: 46 | H87: =IF(OR(F87="",F87=0),"",MAX(F87,IF(ISNUMBER('Нормы и нормо-часы'!K88),ROUNDUP('Нормы и нормо-часы'!K88/(1-$F$3),0),0))) -> 40 | I87: =IF(OR(G87="",G87=0),"",MAX(G87,IF(ISNUMBER('Нормы и нормо-часы'!L88),ROUNDUP('Нормы и нормо-часы'!L88/(1-$F$3),0),0))) -> 48 | J87: =IF(OR(F87="",F87=0),"",H87/F87-1) -> 0 | K87: =IF(OR(G87="",G87=0),"",I87/G87-1) -> 0.043478261 | L87: 25 | M87: 28.5 | N87: =IF(OR(H87="",H87=0),"",(H87-L87)/H87) -> 0.375 | O87: =IF(OR(I87="",I87=0),"",(I87-M87)/I87) -> 0.40625 | P87: =IF(H87="","",H87-L87) -> 15 | Q87: =IF(I87="","",I87-M87) -> 19.5 | R87: 111.57 | S87: 150.62 | T87: =IF(OR(S87="",F87="",F87=0),"",S87/F87) -> 3.7655 | U87: аналог 1.7.8 (на 1 плиту 0,36 м2) | V87: Наш тариф 151 руб/шт — ×3,8; если это разовый доступ к коммуникациям — оправдано только с выездом
A88: 1.7.12 | B88: Снятие облицовки ГКЛ без каркаса | C88: м2 | E88: OTD | F88: 120 | G88: 138 | H88: =IF(OR(F88="",F88=0),"",MAX(F88,IF(ISNUMBER('Нормы и нормо-часы'!K89),ROUNDUP('Нормы и нормо-часы'!K89/(1-$F$3),0),0))) -> 151 | I88: =IF(OR(G88="",G88=0),"",MAX(G88,IF(ISNUMBER('Нормы и нормо-часы'!L89),ROUNDUP('Нормы и нормо-часы'!L89/(1-$F$3),0),0))) -> 180 | J88: =IF(OR(F88="",F88=0),"",H88/F88-1) -> 0.25833333 | K88: =IF(OR(G88="",G88=0),"",I88/G88-1) -> 0.30434783 | L88: 70 | M88: 80.5 | N88: =IF(OR(H88="",H88=0),"",(H88-L88)/H88) -> 0.53642384 | O88: =IF(OR(I88="",I88=0),"",(I88-M88)/I88) -> 0.55277778 | P88: =IF(H88="","",H88-L88) -> 81 | Q88: =IF(I88="","",I88-M88) -> 99.5 | R88: 85.73 | S88: 115.74 | T88: =IF(OR(S88="",F88="",F88=0),"",S88/F88) -> 0.9645 | U88: аналог 1.7.3 без каркаса
A89: 1.7.N1 | B89: Демонтаж натяжного потолка | C89: м2 | D89: да | E89: OTD | F89: 100 | G89: 115 | H89: =IF(OR(F89="",F89=0),"",MAX(F89,IF(ISNUMBER('Нормы и нормо-часы'!K90),ROUNDUP('Нормы и нормо-часы'!K90/(1-$F$3),0),0))) -> 100 | I89: =IF(OR(G89="",G89=0),"",MAX(G89,IF(ISNUMBER('Нормы и нормо-часы'!L90),ROUNDUP('Нормы и нормо-часы'!L90/(1-$F$3),0),0))) -> 115 | J89: =IF(OR(F89="",F89=0),"",H89/F89-1) -> 0 | K89: =IF(OR(G89="",G89=0),"",I89/G89-1) -> 0 | L89: 60 | M89: 69 | N89: =IF(OR(H89="",H89=0),"",(H89-L89)/H89) -> 0.4 | O89: =IF(OR(I89="",I89=0),"",(I89-M89)/I89) -> 0.4 | P89: =IF(H89="","",H89-L89) -> 40 | Q89: =IF(I89="","",I89-M89) -> 46 | T89: =IF(OR(S89="",F89="",F89=0),"",S89/F89) | U89: аналог moskva-demontazh.ru от 25, stroygarant78.ru 200
A90: 1.8 Демонтажные работы стен и перегородок
A91: 1.8.1 | B91: Алмазная резка стены железобетонной глубиной до 10 см | C91: мп | E91: BET | F91: 800 | G91: 920 | H91: =IF(OR(F91="",F91=0),"",MAX(F91,IF(ISNUMBER('Нормы и нормо-часы'!K92),ROUNDUP('Нормы и нормо-часы'!K92/(1-$F$3),0),0))) -> 800 | I91: =IF(OR(G91="",G91=0),"",MAX(G91,IF(ISNUMBER('Нормы и нормо-часы'!L92),ROUNDUP('Нормы и нормо-часы'!L92/(1-$F$3),0),0))) -> 920 | J91: =IF(OR(F91="",F91=0),"",H91/F91-1) -> 0 | K91: =IF(OR(G91="",G91=0),"",I91/G91-1) -> 0 | L91: 480 | M91: 552 | N91: =IF(OR(H91="",H91=0),"",(H91-L91)/H91) -> 0.4 | O91: =IF(OR(I91="",I91=0),"",(I91-M91)/I91) -> 0.4 | P91: =IF(H91="","",H91-L91) -> 320 | Q91: =IF(I91="","",I91-M91) -> 368 | R91: 1175.61 | S91: 1587.07 | T91: =IF(OR(S91="",F91="",F91=0),"",S91/F91) -> 1.9838375 | U91: прайс rezka-prof.ru 450, demont.spb 800 (до 12 см), reg-spb 900 | V91: Наш тариф 1587 — ×2
A92: 1.8.2 | B92: Алмазная резка стены железобетонной глубиной от 10 см до 40 см | C92: мп | E92: BET | F92: 2000 | G92: 2300 | H92: =IF(OR(F92="",F92=0),"",MAX(F92,IF(ISNUMBER('Нормы и нормо-часы'!K93),ROUNDUP('Нормы и нормо-часы'!K93/(1-$F$3),0),0))) -> 2000 | I92: =IF(OR(G92="",G92=0),"",MAX(G92,IF(ISNUMBER('Нормы и нормо-часы'!L93),ROUNDUP('Нормы и нормо-часы'!L93/(1-$F$3),0),0))) -> 2300 | J92: =IF(OR(F92="",F92=0),"",H92/F92-1) -> 0 | K92: =IF(OR(G92="",G92=0),"",I92/G92-1) -> 0 | L92: 1200 | M92: 1380 | N92: =IF(OR(H92="",H92=0),"",(H92-L92)/H92) -> 0.4 | O92: =IF(OR(I92="",I92=0),"",(I92-M92)/I92) -> 0.4 | P92: =IF(H92="","",H92-L92) -> 800 | Q92: =IF(I92="","",I92-M92) -> 920 | R92: 3279.91 | S92: 4427.88 | T92: =IF(OR(S92="",F92="",F92=0),"",S92/F92) -> 2.21394 | U92: прайс rezka-prof.ru 900–1800, demont.spb 1600–3200, reg-spb 2800 (30 см) | V92: Диапазон 10–40 см слишком широк — разбить на 10–20 / 20–30 / 30–40 см; наш тариф ×2,2
A93: 1.8.3 | B93: Демонтаж каркаса под облицовку (только для ГКЛ, ГВЛ,ДСП) | C93: м2 | E93: OTD | F93: 120 | G93: 138 | H93: =IF(OR(F93="",F93=0),"",MAX(F93,IF(ISNUMBER('Нормы и нормо-часы'!K94),ROUNDUP('Нормы и нормо-часы'!K94/(1-$F$3),0),0))) -> 151 | I93: =IF(OR(G93="",G93=0),"",MAX(G93,IF(ISNUMBER('Нормы и нормо-часы'!L94),ROUNDUP('Нормы и нормо-часы'!L94/(1-$F$3),0),0))) -> 180 | J93: =IF(OR(F93="",F93=0),"",H93/F93-1) -> 0.25833333 | K93: =IF(OR(G93="",G93=0),"",I93/G93-1) -> 0.30434783 | L93: 70 | M93: 80.5 | N93: =IF(OR(H93="",H93=0),"",(H93-L93)/H93) -> 0.53642384 | O93: =IF(OR(I93="",I93=0),"",(I93-M93)/I93) -> 0.55277778 | P93: =IF(H93="","",H93-L93) -> 81 | Q93: =IF(I93="","",I93-M93) -> 99.5 | R93: 299.92 | S93: 404.89 | T93: =IF(OR(S93="",F93="",F93=0),"",S93/F93) -> 3.3740833 | U93: аналог moskva-demontazh.ru каркасные перегородки от 100 | V93: Наш тариф 405 — ×3,4
A94: 1.8.4 | B94: Демонтаж облицовки стен из ГКЛ, ГВЛ, панелей ПВХ, ДСП (с сохранением каркаса) | C94: м2 | E94: OTD | F94: 150 | G94: 172 | H94: =IF(OR(F94="",F94=0),"",MAX(F94,IF(ISNUMBER('Нормы и нормо-часы'!K95),ROUNDUP('Нормы и нормо-часы'!K95/(1-$F$3),0),0))) -> 180 | I94: =IF(OR(G94="",G94=0),"",MAX(G94,IF(ISNUMBER('Нормы и нормо-часы'!L95),ROUNDUP('Нормы и нормо-часы'!L95/(1-$F$3),0),0))) -> 216 | J94: =IF(OR(F94="",F94=0),"",H94/F94-1) -> 0.2 | K94: =IF(OR(G94="",G94=0),"",I94/G94-1) -> 0.25581395 | L94: 90 | M94: 103 | N94: =IF(OR(H94="",H94=0),"",(H94-L94)/H94) -> 0.5 | O94: =IF(OR(I94="",I94=0),"",(I94-M94)/I94) -> 0.52314815 | P94: =IF(H94="","",H94-L94) -> 90 | Q94: =IF(I94="","",I94-M94) -> 113 | R94: 267.98 | S94: 361.77 | T94: =IF(OR(S94="",F94="",F94=0),"",S94/F94) -> 2.4118 | U94: прайс stroygarant78.ru ГКЛ 240, ПВХ панели 230; demontazh.spb.ru 150 | V94: Наш тариф ×2,4
A95: 1.8.5 | B95: Демонтаж облицовки стен из керамической плитки | C95: м2 | E95: OTD | F95: 300 | G95: 345 | H95: =IF(OR(F95="",F95=0),"",MAX(F95,IF(ISNUMBER('Нормы и нормо-часы'!K96),ROUNDUP('Нормы и нормо-часы'!K96/(1-$F$3),0),0))) -> 400 | I95: =IF(OR(G95="",G95=0),"",MAX(G95,IF(ISNUMBER('Нормы и нормо-часы'!L96),ROUNDUP('Нормы и нормо-часы'!L96/(1-$F$3),0),0))) -> 480 | J95: =IF(OR(F95="",F95=0),"",H95/F95-1) -> 0.33333333 | K95: =IF(OR(G95="",G95=0),"",I95/G95-1) -> 0.39130435 | L95: 180 | M95: 207 | N95: =IF(OR(H95="",H95=0),"",(H95-L95)/H95) -> 0.55 | O95: =IF(OR(I95="",I95=0),"",(I95-M95)/I95) -> 0.56875 | P95: =IF(H95="","",H95-L95) -> 220 | Q95: =IF(I95="","",I95-M95) -> 273 | R95: 750.9 | S95: 1013.72 | T95: =IF(OR(S95="",F95="",F95=0),"",S95/F95) -> 3.3790667 | U95: прайс stroygarant78.ru 260, remontvspb.ru 300 руб/м2 | V95: Наш тариф 1014 — ×3,4
A96: 1.8.6 | B96: Демонтаж облицовки стен из металлических листов/оцинковки | C96: м2 | E96: OTD | F96: 180 | G96: 207 | H96: =IF(OR(F96="",F96=0),"",MAX(F96,IF(ISNUMBER('Нормы и нормо-часы'!K97),ROUNDUP('Нормы и нормо-часы'!K97/(1-$F$3),0),0))) -> 220 | I96: =IF(OR(G96="",G96=0),"",MAX(G96,IF(ISNUMBER('Нормы и нормо-часы'!L97),ROUNDUP('Нормы и нормо-часы'!L97/(1-$F$3),0),0))) -> 264 | J96: =IF(OR(F96="",F96=0),"",H96/F96-1) -> 0.22222222 | K96: =IF(OR(G96="",G96=0),"",I96/G96-1) -> 0.27536232 | L96: 110 | M96: 126 | N96: =IF(OR(H96="",H96=0),"",(H96-L96)/H96) -> 0.5 | O96: =IF(OR(I96="",I96=0),"",(I96-M96)/I96) -> 0.52272727 | P96: =IF(H96="","",H96-L96) -> 110 | Q96: =IF(I96="","",I96-M96) -> 138 | R96: 414.97 | S96: 560.21 | T96: =IF(OR(S96="",F96="",F96=0),"",S96/F96) -> 3.1122778 | U96: аналог demontazh.spb.ru листовые 150
A97: 1.8.7 | B97: Демонтаж утеплителя стен | C97: м2 | E97: RAZ | F97: 120 | G97: 138 | H97: =IF(OR(F97="",F97=0),"",MAX(F97,IF(ISNUMBER('Нормы и нормо-часы'!K98),ROUNDUP('Нормы и нормо-часы'!K98/(1-$F$3),0),0))) -> 120 | I97: =IF(OR(G97="",G97=0),"",MAX(G97,IF(ISNUMBER('Нормы и нормо-часы'!L98),ROUNDUP('Нормы и нормо-часы'!L98/(1-$F$3),0),0))) -> 138 | J97: =IF(OR(F97="",F97=0),"",H97/F97-1) -> 0 | K97: =IF(OR(G97="",G97=0),"",I97/G97-1) -> 0 | L97: 70 | M97: 80.5 | N97: =IF(OR(H97="",H97=0),"",(H97-L97)/H97) -> 0.41666667 | O97: =IF(OR(I97="",I97=0),"",(I97-M97)/I97) -> 0.41666667 | P97: =IF(H97="","",H97-L97) -> 50 | Q97: =IF(I97="","",I97-M97) -> 57.5 | R97: 201.25 | S97: 271.69 | T97: =IF(OR(S97="",F97="",F97=0),"",S97/F97) -> 2.2640833 | U97: аналог (снятие минваты без крепежа)
A98: 1.8.8 | B98: Отбивка штукатурки с поверхностей стен, столбов, колонн, пилястр | C98: м2 | E98: OTD | F98: 350 | G98: 402 | H98: =IF(OR(F98="",F98=0),"",MAX(F98,IF(ISNUMBER('Нормы и нормо-часы'!K99),ROUNDUP('Нормы и нормо-часы'!K99/(1-$F$3),0),0))) -> 451 | I98: =IF(OR(G98="",G98=0),"",MAX(G98,IF(ISNUMBER('Нормы и нормо-часы'!L99),ROUNDUP('Нормы и нормо-часы'!L99/(1-$F$3),0),0))) -> 540 | J98: =IF(OR(F98="",F98=0),"",H98/F98-1) -> 0.28857143 | K98: =IF(OR(G98="",G98=0),"",I98/G98-1) -> 0.34328358 | L98: 210 | M98: 241 | N98: =IF(OR(H98="",H98=0),"",(H98-L98)/H98) -> 0.53436807 | O98: =IF(OR(I98="",I98=0),"",(I98-M98)/I98) -> 0.5537037 | P98: =IF(H98="","",H98-L98) -> 241 | Q98: =IF(I98="","",I98-M98) -> 299 | R98: 377.51 | S98: 509.64 | T98: =IF(OR(S98="",F98="",F98=0),"",S98/F98) -> 1.4561143 | U98: прайс remontvspb.ru 200–500, stroygarant78.ru 220 | V98: Частично дублирует 1.2.1 (те же стены); колонны/пилястры дороже
A99: 1.8.9 | B99: Пробивка проема в конструкциях из бетона | C99: м3 | E99: RAZ | F99: 14000 | G99: 16800 | H99: =IF(OR(F99="",F99=0),"",MAX(F99,IF(ISNUMBER('Нормы и нормо-часы'!K100),ROUNDUP('Нормы и нормо-часы'!K100/(1-$F$3),0),0))) -> 14667 | I99: =IF(OR(G99="",G99=0),"",MAX(G99,IF(ISNUMBER('Нормы и нормо-часы'!L100),ROUNDUP('Нормы и нормо-часы'!L100/(1-$F$3),0),0))) -> 17600 | J99: =IF(OR(F99="",F99=0),"",H99/F99-1) -> 0.047642857 | K99: =IF(OR(G99="",G99=0),"",I99/G99-1) -> 0.047619048 | L99: 8400 | M99: 9912 | N99: =IF(OR(H99="",H99=0),"",(H99-L99)/H99) -> 0.42728574 | O99: =IF(OR(I99="",I99=0),"",(I99-M99)/I99) -> 0.43681818 | P99: =IF(H99="","",H99-L99) -> 6267 | Q99: =IF(I99="","",I99-M99) -> 7688 | R99: 16797.33 | S99: 22676.4 | T99: =IF(OR(S99="",F99="",F99=0),"",S99/F99) -> 1.6197429 | U99: аналог rezka-prof.ru гидроклин ж/б 13500 + аккуратная граница проёма
A100: 1.8.10 | B100: Пробивка проема в конструкциях из кирпича | C100: м3 | E100: KAM | F100: 6000 | G100: 6900 | H100: =IF(OR(F100="",F100=0),"",MAX(F100,IF(ISNUMBER('Нормы и нормо-часы'!K101),ROUNDUP('Нормы и нормо-часы'!K101/(1-$F$3),0),0))) -> 9600 | I100: =IF(OR(G100="",G100=0),"",MAX(G100,IF(ISNUMBER('Нормы и нормо-часы'!L101),ROUNDUP('Нормы и нормо-часы'!L101/(1-$F$3),0),0))) -> 11400 | J100: =IF(OR(F100="",F100=0),"",H100/F100-1) -> 0.6 | K100: =IF(OR(G100="",G100=0),"",I100/G100-1) -> 0.65217391 | L100: 3600 | M100: 4140 | N100: =IF(OR(H100="",H100=0),"",(H100-L100)/H100) -> 0.625 | O100: =IF(OR(I100="",I100=0),"",(I100-M100)/I100) -> 0.63684211 | P100: =IF(H100="","",H100-L100) -> 6000 | Q100: =IF(I100="","",I100-M100) -> 7260 | R100: 10082.63 | S100: 13611.55 | T100: =IF(OR(S100="",F100="",F100=0),"",S100/F100) -> 2.2685917 | U100: аналог rezka-prof.ru гидроклин кирпич 3000 ×2 (проём, выборка) | V100: Наш тариф 13,6 тыс. — ×2,3
...

Sheet Нормы и нормо-часы
A1: НОРМЫ ВРЕМЕНИ И СРАВНЕНИЕ: СДЕЛЬНАЯ РАСЦЕНКА vs ОПЛАТА ПО НОРМО-ЧАСАМ
A2: Норма = трудоёмкость, чел.-ч на единицу (ЕНиР / ВНиР / ГЭСН ×0,85 / нормы ТО / экспертно). Почасовая расценка = норма × ставка нормо-часа бригады нужной специальности (лист «Нормо-час по специальностям», жёлтые ячейки). Разница = (почасовая − сдельная) ÷ сдельная: минус — по нормо-часам дешевле, плюс — дешевле отдавать в расценку.
A3: Порог «равно», ± | C3: 0.1 | D3: Часов чистой работы в смене | G3: 7
A5: Артикул | B5: Вид работ | C5: Ед. изм. | D5: Код | E5: Специальность | F5: Норма, чел.-ч на ед. | G5: Основание нормы | H5: Выработка 1 чел. за смену, ед. | I5: Ставка бригады СПб, руб/нормо-ч | J5: Ставка бригады Мск, руб/нормо-ч | K5: Расценка по нормо-часам СПб | L5: Расценка по нормо-часам Мск | M5: Сдельная расценка бригады СПб (лист 1) | N5: Сдельная расценка бригады Мск (лист 1) | O5: Разница СПб, % | P5: Разница Мск, % | Q5: Выгоднее СПб | R5: Выгоднее Мск | S5: Сдельно бригада получает за нормо-час СПб | T5: Сдельно за нормо-час Мск | U5: Рынок СПб, руб/ед. | V5: Рынок Мск, руб/ед. | W5: Маржа по нормо-часам при РЫНОЧНОЙ цене СПб, % | X5: Маржа по нормо-часам при рыночной цене Мск, % | Y5: ЦЕНА НЕОСТРОЙ СПб (после подтяжки), руб/ед. | Z5: ЦЕНА НЕОСТРОЙ Мск (после подтяжки), руб/ед. | AA5: Цена НЕОСТРОЙ выше рынка СПб, % | AB5: Цена НЕОСТРОЙ выше рынка Мск, % | AC5: МАРЖА при оплате бригаде по нормо-часам СПб, % | AD5: МАРЖА при оплате по нормо-часам Мск, % | AE5: Маржа при сдельной оплате СПб, % | AF5: Маржа при сдельной оплате Мск, % | AG5: Маржа по нормо-часам СПб, руб/ед. | AH5: Маржа по нормо-часам Мск, руб/ед.
A6: 1.1 Демонтаж зданий, строений, сооружений
A7: 1.1.1 | B7: Разборка покрытий и оснований асфальтобетонных | C7: м3 | D7: BLG | E7: =INDEX('Нормо-час по специальностям'!$B$6:$B$26,MATCH(D7,'Нормо-час по специальностям'!$A$6:$A$26,0)) -> Дорожный рабочий / благоустройство | F7: 3.5 | G7: ЕНиР Е20-1 / Е27 (разборка асф. покрытия отбойными молотками) | H7: =IF(OR(F7="",F7=0),"",ROUND($G$3/F7,2)) -> 2 | I7: =INDEX('Нормо-час по специальностям'!$D$6:$D$26,MATCH(D7,'Нормо-час по специальностям'!$A$6:$A$26,0)) -> 650 | J7: =INDEX('Нормо-час по специальностям'!$E$6:$E$26,MATCH(D7,'Нормо-час по специальностям'!$A$6:$A$26,0)) -> 780 | K7: =IF(OR(F7="",F7=0,I7=0),"",ROUND(F7*I7,0)) -> 2275 | L7: =IF(OR(F7="",F7=0,J7=0),"",ROUND(F7*J7,0)) -> 2730 | M7: =Расценки!L6 -> 2100 | N7: =Расценки!M6 -> 2415 | O7: =IF(OR(K7="",M7="",M7=0),"",K7/M7-1) -> 0.083333333 | P7: =IF(OR(L7="",N7="",N7=0),"",L7/N7-1) -> 0.13043478 | Q7: =IF(O7="","—",IF(O7<-$C$3,"нормо-часы",IF(O7>$C$3,"расценка","равно"))) -> равно | R7: =IF(P7="","—",IF(P7<-$C$3,"нормо-часы",IF(P7>$C$3,"расценка","равно"))) -> расценка | S7: =IF(OR(F7="",F7=0,M7=""),"",ROUND(M7/F7,0)) -> 600 | T7: =IF(OR(F7="",F7=0,N7=""),"",ROUND(N7/F7,0)) -> 690 | U7: =Расценки!F6 -> 3500 | V7: =Расценки!G6 -> 4025 | W7: =IF(OR(K7="",U7="",U7=0),"",(U7-K7)/U7) -> 0.35 | X7: =IF(OR(L7="",V7="",V7=0),"",(V7-L7)/V7) -> 0.32173913 | Y7: =Расценки!H6 -> 3500 | Z7: =Расценки!I6 -> 4025 | AA7: =Расценки!J6 -> 0 | AB7: =Расценки!K6 -> 0 | AC7: =IF(OR(K7="",Y7="",Y7=0),"",(Y7-K7)/Y7) -> 0.35 | AD7: =IF(OR(L7="",Z7="",Z7=0),"",(Z7-L7)/Z7) -> 0.32173913 | AE7: =IF(OR(Y7="",Y7=0),"",(Y7-M7)/Y7) -> 0.4 | AF7: =IF(OR(Z7="",Z7=0),"",(Z7-N7)/Z7) -> 0.4 | AG7: =IF(OR(K7="",Y7=""),"",Y7-K7) -> 1225 | AH7: =IF(OR(L7="",Z7=""),"",Z7-L7) -> 1295
A8: 1.1.2 | B8: Демонтаж деревянных зданий и строений без сохранения годного материала | C8: м3 здания | D8: RAZ | E8: =INDEX('Нормо-час по специальностям'!$B$6:$B$26,MATCH(D8,'Нормо-час по специальностям'!$A$6:$A$26,0)) -> Разнорабочий / демонтажник | F8: 1.2 | G8: ГЭСНр 46-04 (разборка конструкций) ×0,85 | H8: =IF(OR(F8="",F8=0),"",ROUND($G$3/F8,2)) -> 5.83 | I8: =INDEX('Нормо-час по специальностям'!$D$6:$D$26,MATCH(D8,'Нормо-час по специальностям'!$A$6:$A$26,0)) -> 550 | J8: =INDEX('Нормо-час по специальностям'!$E$6:$E$26,MATCH(D8,'Нормо-час по специальностям'!$A$6:$A$26,0)) -> 660 | K8: =IF(OR(F8="",F8=0,I8=0),"",ROUND(F8*I8,0)) -> 660 | L8: =IF(OR(F8="",F8=0,J8=0),"",ROUND(F8*J8,0)) -> 792 | M8: =Расценки!L7 -> 600 | N8: =Расценки!M7 -> 768 | O8: =IF(OR(K8="",M8="",M8=0),"",K8/M8-1) -> 0.1 | P8: =IF(OR(L8="",N8="",N8=0),"",L8/N8-1) -> 0.03125 | Q8: =IF(O8="","—",IF(O8<-$C$3,"нормо-часы",IF(O8>$C$3,"расценка","равно"))) -> равно | R8: =IF(P8="","—",IF(P8<-$C$3,"нормо-часы",IF(P8>$C$3,"расценка","равно"))) -> равно | S8: =IF(OR(F8="",F8=0,M8=""),"",ROUND(M8/F8,0)) -> 500 | T8: =IF(OR(F8="",F8=0,N8=""),"",ROUND(N8/F8,0)) -> 640 | U8: =Расценки!F7 -> 1000 | V8: =Расценки!G7 -> 1300 | W8: =IF(OR(K8="",U8="",U8=0),"",(U8-K8)/U8) -> 0.34 | X8: =IF(OR(L8="",V8="",V8=0),"",(V8-L8)/V8) -> 0.39076923 | Y8: =Расценки!H7 -> 1000 | Z8: =Расценки!I7 -> 1300 | AA8: =Расценки!J7 -> 0 | AB8: =Расценки!K7 -> 0 | AC8: =IF(OR(K8="",Y8="",Y8=0),"",(Y8-K8)/Y8) -> 0.34 | AD8: =IF(OR(L8="",Z8="",Z8=0),"",(Z8-L8)/Z8) -> 0.39076923 | AE8: =IF(OR(Y8="",Y8=0),"",(Y8-M8)/Y8) -> 0.4 | AF8: =IF(OR(Z8="",Z8=0),"",(Z8-N8)/Z8) -> 0.40923077 | AG8: =IF(OR(K8="",Y8=""),"",Y8-K8) -> 340 | AH8: =IF(OR(L8="",Z8=""),"",Z8-L8) -> 508
A9: 1.1.3 | B9: Демонтаж зданий и строений из металлоконструкций без сохранения годного материала | C9: т | D9: SVA | E9: =INDEX('Нормо-час по специальностям'!$B$6:$B$26,MATCH(D9,'Нормо-час по специальностям'!$A$6:$A$26,0)) -> Сварщик / монтажник МК | F9: 10 | G9: ЕНиР Е5 (демонтаж МК ≈0,6–0,7 от монтажа) | H9: =IF(OR(F9="",F9=0),"",ROUND($G$3/F9,2)) -> 0.7 | I9: =INDEX('Нормо-час по специальностям'!$D$6:$D$26,MATCH(D9,'Нормо-час по специальностям'!$A$6:$A$26,0)) -> 900 | J9: =INDEX('Нормо-час по специальностям'!$E$6:$E$26,MATCH(D9,'Нормо-час по специальностям'!$A$6:$A$26,0)) -> 1080 | K9: =IF(OR(F9="",F9=0,I9=0),"",ROUND(F9*I9,0)) -> 9000 | L9: =IF(OR(F9="",F9=0,J9=0),"",ROUND(F9*J9,0)) -> 10800 | M9: =Расценки!L8 -> 3900 | N9: =Расценки!M8 -> 4485 | O9: =IF(OR(K9="",M9="",M9=0),"",K9/M9-1) -> 1.3076923 | P9: =IF(OR(L9="",N9="",N9=0),"",L9/N9-1) -> 1.4080268 | Q9: =IF(O9="","—",IF(O9<-$C$3,"нормо-часы",IF(O9>$C$3,"расценка","равно"))) -> расценка | R9: =IF(P9="","—",IF(P9<-$C$3,"нормо-часы",IF(P9>$C$3,"расценка","равно"))) -> расценка | S9: =IF(OR(F9="",F9=0,M9=""),"",ROUND(M9/F9,0)) -> 390 | T9: =IF(OR(F9="",F9=0,N9=""),"",ROUND(N9/F9,0)) -> 449 | U9: =Расценки!F8 -> 6500 | V9: =Расценки!G8 -> 7475 | W9: =IF(OR(K9="",U9="",U9=0),"",(U9-K9)/U9) -> -0.38461538 | X9: =IF(OR(L9="",V9="",V9=0),"",(V9-L9)/V9) -> -0.44481605 | Y9: =Расценки!H8 -> 12000 | Z9: =Расценки!I8 -> 14400 | AA9: =Расценки!J8 -> 0.84615385 | AB9: =Расценки!K8 -> 0.9264214 | AC9: =IF(OR(K9="",Y9="",Y9=0),"",(Y9-K9)/Y9) -> 0.25 | AD9: =IF(OR(L9="",Z9="",Z9=0),"",(Z9-L9)/Z9) -> 0.25 | AE9: =IF(OR(Y9="",Y9=0),"",(Y9-M9)/Y9) -> 0.675 | AF9: =IF(OR(Z9="",Z9=0),"",(Z9-N9)/Z9) -> 0.68854167 | AG9: =IF(OR(K9="",Y9=""),"",Y9-K9) -> 3000 | AH9: =IF(OR(L9="",Z9=""),"",Z9-L9) -> 3600
A10: 1.1.4 | B10: Демонтаж каменных зданий и строений (кирпич, бетон, железобетон) комплексная работа с сохранением годного материала | C10: м3 | D10: RAZ | E10: =INDEX('Нормо-час по специальностям'!$B$6:$B$26,MATCH(D10,'Нормо-час по специальностям'!$A$6:$A$26,0)) -> Разнорабочий / демонтажник | F10: 6.5 | G10: ГЭСНр 46-04 (разборка конструкций) ×0,85 | H10: =IF(OR(F10="",F10=0),"",ROUND($G$3/F10,2)) -> 1.08 | I10: =INDEX('Нормо-час по специальностям'!$D$6:$D$26,MATCH(D10,'Нормо-час по специальностям'!$A$6:$A$26,0)) -> 550 | J10: =INDEX('Нормо-час по специальностям'!$E$6:$E$26,MATCH(D10,'Нормо-час по специальностям'!$A$6:$A$26,0)) -> 660 | K10: =IF(OR(F10="",F10=0,I10=0),"",ROUND(F10*I10,0)) -> 3575 | L10: =IF(OR(F10="",F10=0,J10=0),"",ROUND(F10*J10,0)) -> 4290 | M10: =Расценки!L9 -> 2500 | N10: =Расценки!M9 -> 2875 | O10: =IF(OR(K10="",M10="",M10=0),"",K10/M10-1) -> 0.43 | P10: =IF(OR(L10="",N10="",N10=0),"",L10/N10-1) -> 0.49217391 | Q10: =IF(O10="","—",IF(O10<-$C$3,"нормо-часы",IF(O10>$C$3,"расценка","равно"))) -> расценка | R10: =IF(P10="","—",IF(P10<-$C$3,"нормо-часы",IF(P10>$C$3,"расценка","равно"))) -> расценка | S10: =IF(OR(F10="",F10=0,M10=""),"",ROUND(M10/F10,0)) -> 385 | T10: =IF(OR(F10="",F10=0,N10=""),"",ROUND(N10/F10,0)) -> 442 | U10: =Расценки!F9 -> 4200 | V10: =Расценки!G9 -> 4830 | W10: =IF(OR(K10="",U10="",U10=0),"",(U10-K10)/U10) -> 0.14880952 | X10: =IF(OR(L10="",V10="",V10=0),"",(V10-L10)/V10) -> 0.11180124 | Y10: =Расценки!H9 -> 4767 | Z10: =Расценки!I9 -> 5720 | AA10: =Расценки!J9 -> 0.135 | AB10: =Расценки!K9 -> 0.18426501 | AC10: =IF(OR(K10="",Y10="",Y10=0),"",(Y10-K10)/Y10) -> 0.25005244 | AD10: =IF(OR(L10="",Z10="",Z10=0),"",(Z10-L10)/Z10) -> 0.25 | AE10: =IF(OR(Y10="",Y10=0),"",(Y10-M10)/Y10) -> 0.47556115 | AF10: =IF(OR(Z10="",Z10=0),"",(Z10-N10)/Z10) -> 0.49737762 | AG10: =IF(OR(K10="",Y10=""),"",Y10-K10) -> 1192 | AH10: =IF(OR(L10="",Z10=""),"",Z10-L10) -> 1430
A11: 1.1.5 | B11: Разборка бортовых камней с сохранением камня пригодного для дальнейшего использования | C11: мп | D11: BLG | E11: =INDEX('Нормо-час по специальностям'!$B$6:$B$26,MATCH(D11,'Нормо-час по специальностям'!$A$6:$A$26,0)) -> Дорожный рабочий / благоустройство | F11: 0.35 | G11: ЕНиР Е27 (бортовые камни, разборка) | H11: =IF(OR(F11="",F11=0),"",ROUND($G$3/F11,2)) -> 20 | I11: =INDEX('Нормо-час по специальностям'!$D$6:$D$26,MATCH(D11,'Нормо-час по специальностям'!$A$6:$A$26,0)) -> 650 | J11: =INDEX('Нормо-час по специальностям'!$E$6:$E$26,MATCH(D11,'Нормо-час по специальностям'!$A$6:$A$26,0)) -> 780 | K11: =IF(OR(F11="",F11=0,I11=0),"",ROUND(F11*I11,0)) -> 228 | L11: =IF(OR(F11="",F11=0,J11=0),"",ROUND(F11*J11,0)) -> 273 | M11: =Расценки!L10 -> 200 | N11: =Расценки!M10 -> 230 | O11: =IF(OR(K11="",M11="",M11=0),"",K11/M11-1) -> 0.14 | P11: =IF(OR(L11="",N11="",N11=0),"",L11/N11-1) -> 0.18695652 | Q11: =IF(O11="","—",IF(O11<-$C$3,"нормо-часы",IF(O11>$C$3,"расценка","равно"))) -> расценка | R11: =IF(P11="","—",IF(P11<-$C$3,"нормо-часы",IF(P11>$C$3,"расценка","равно"))) -> расценка | S11: =IF(OR(F11="",F11=0,M11=""),"",ROUND(M11/F11,0)) -> 571 | T11: =IF(OR(F11="",F11=0,N11=""),"",ROUND(N11/F11,0)) -> 657 | U11: =Расценки!F10 -> 350 | V11: =Расценки!G10 -> 402 | W11: =IF(OR(K11="",U11="",U11=0),"",(U11-K11)/U11) -> 0.34857143 | X11: =IF(OR(L11="",V11="",V11=0),"",(V11-L11)/V11) -> 0.32089552 | Y11: =Расценки!H10 -> 350 | Z11: =Расценки!I10 -> 402 | AA11: =Расценки!J10 -> 0 | AB11: =Расценки!K10 -> 0 | AC11: =IF(OR(K11="",Y11="",Y11=0),"",(Y11-K11)/Y11) -> 0.34857143 | AD11: =IF(OR(L11="",Z11="",Z11=0),"",(Z11-L11)/Z11) -> 0.32089552 | AE11: =IF(OR(Y11="",Y11=0),"",(Y11-M11)/Y11) -> 0.42857143 | AF11: =IF(OR(Z11="",Z11=0),"",(Z11-N11)/Z11) -> 0.4278607 | AG11: =IF(OR(K11="",Y11=""),"",Y11-K11) -> 122 | AH11: =IF(OR(L11="",Z11=""),"",Z11-L11) -> 129
A12: 1.1.6 | B12: Разборка тротуаров и дорожек из плит бетонных, брусчатки с сохранением пригодных для дальнейшего использования | C12: м2 | D12: BLG | E12: =INDEX('Нормо-час по специальностям'!$B$6:$B$26,MATCH(D12,'Нормо-час по специальностям'!$A$6:$A$26,0)) -> Дорожный рабочий / благоустройство | F12: 0.3 | G12: ЕНиР Е27 / Е20-1 | H12: =IF(OR(F12="",F12=0),"",ROUND($G$3/F12,2)) -> 23.33 | I12: =INDEX('Нормо-час по специальностям'!$D$6:$D$26,MATCH(D12,'Нормо-час по специальностям'!$A$6:$A$26,0)) -> 650 | J12: =INDEX('Нормо-час по специальностям'!$E$6:$E$26,MATCH(D12,'Нормо-час по специальностям'!$A$6:$A$26,0)) -> 780 | K12: =IF(OR(F12="",F12=0,I12=0),"",ROUND(F12*I12,0)) -> 195 | L12: =IF(OR(F12="",F12=0,J12=0),"",ROUND(F12*J12,0)) -> 234 | M12: =Расценки!L11 -> 150 | N12: =Расценки!M11 -> 172 | O12: =IF(OR(K12="",M12="",M12=0),"",K12/M12-1) -> 0.3 | P12: =IF(OR(L12="",N12="",N12=0),"",L12/N12-1) -> 0.36046512 | Q12: =IF(O12="","—",IF(O12<-$C$3,"нормо-часы",IF(O12>$C$3,"расценка","равно"))) -> расценка | R12: =IF(P12="","—",IF(P12<-$C$3,"нормо-часы",IF(P12>$C$3,"расценка","равно"))) -> расценка | S12: =IF(OR(F12="",F12=0,M12=""),"",ROUND(M12/F12,0)) -> 500 | T12: =IF(OR(F12="",F12=0,N12=""),"",ROUND(N12/F12,0)) -> 573 | U12: =Расценки!F11 -> 250 | V12: =Расценки!G11 -> 288 | W12: =IF(OR(K12="",U12="",U12=0),"",(U12-K12)/U12) -> 0.22 | X12: =IF(OR(L12="",V12="",V12=0),"",(V12-L12)/V12) -> 0.1875 | Y12: =Расценки!H11 -> 260 | Z12: =Расценки!I11 -> 312 | AA12: =Расценки!J11 -> 0.04 | AB12: =Расценки!K11 -> 0.083333333 | AC12: =IF(OR(K12="",Y12="",Y12=0),"",(Y12-K12)/Y12) -> 0.25 | AD12: =IF(OR(L12="",Z12="",Z12=0),"",(Z12-L12)/Z12) -> 0.25 | AE12: =IF(OR(Y12="",Y12=0),"",(Y12-M12)/Y12) -> 0.42307692 | AF12: =IF(OR(Z12="",Z12=0),"",(Z12-N12)/Z12) -> 0.44871795 | AG12: =IF(OR(K12="",Y12=""),"",Y12-K12) -> 65 | AH12: =IF(OR(L12="",Z12=""),"",Z12-L12) -> 78
A13: 1.1.N1 | B13: Разборка асфальтобетонного покрытия толщиной до 5 см отбойными молотками | C13: м2 | D13: BLG | E13: =INDEX('Нормо-час по специальностям'!$B$6:$B$26,MATCH(D13,'Нормо-час по специальностям'!$A$6:$A$26,0)) -> Дорожный рабочий / благоустройство | F13: 0.2 | G13: ЕНиР Е27 / Е20-1 | H13: =IF(OR(F13="",F13=0),"",ROUND($G$3/F13,2)) -> 35 | I13: =INDEX('Нормо-час по специальностям'!$D$6:$D$26,MATCH(D13,'Нормо-час по специальностям'!$A$6:$A$26,0)) -> 650 | J13: =INDEX('Нормо-час по специальностям'!$E$6:$E$26,MATCH(D13,'Нормо-час по специальностям'!$A$6:$A$26,0)) -> 780 | K13: =IF(OR(F13="",F13=0,I13=0),"",ROUND(F13*I13,0)) -> 130 | L13: =IF(OR(F13="",F13=0,J13=0),"",ROUND(F13*J13,0)) -> 156 | M13: =Расценки!L12 -> 120 | N13: =Расценки!M12 -> 138 | O13: =IF(OR(K13="",M13="",M13=0),"",K13/M13-1) -> 0.083333333 | P13: =IF(OR(L13="",N13="",N13=0),"",L13/N13-1) -> 0.13043478 | Q13: =IF(O13="","—",IF(O13<-$C$3,"нормо-часы",IF(O13>$C$3,"расценка","равно"))) -> равно | R13: =IF(P13="","—",IF(P13<-$C$3,"нормо-часы",IF(P13>$C$3,"расценка","равно"))) -> расценка | S13: =IF(OR(F13="",F13=0,M13=""),"",ROUND(M13/F13,0)) -> 600 | T13: =IF(OR(F13="",F13=0,N13=""),"",ROUND(N13/F13,0)) -> 690 | U13: =Расценки!F12 -> 200 | V13: =Расценки!G12 -> 230 | W13: =IF(OR(K13="",U13="",U13=0),"",(U13-K13)/U13) -> 0.35 | X13: =IF(OR(L13="",V13="",V13=0),"",(V13-L13)/V13) -> 0.32173913 | Y13: =Расценки!H12 -> 200 | Z13: =Расценки!I12 -> 230 | AA13: =Расценки!J12 -> 0 | AB13: =Расценки!K12 -> 0 | AC13: =IF(OR(K13="",Y13="",Y13=0),"",(Y13-K13)/Y13) -> 0.35 | AD13: =IF(OR(L13="",Z13="",Z13=0),"",(Z13-L13)/Z13) -> 0.32173913 | AE13: =IF(OR(Y13="",Y13=0),"",(Y13-M13)/Y13) -> 0.4 | AF13: =IF(OR(Z13="",Z13=0),"",(Z13-N13)/Z13) -> 0.4 | AG13: =IF(OR(K13="",Y13=""),"",Y13-K13) -> 70 | AH13: =IF(OR(L13="",Z13=""),"",Z13-L13) -> 74
A14: 1.1.N2 | B14: Демонтаж бетонных дорожных плит (ПАГ, 2П) с погрузкой | C14: м2 | D14: BLG | E14: =INDEX('Нормо-час по специальностям'!$B$6:$B$26,MATCH(D14,'Нормо-час по специальностям'!$A$6:$A$26,0)) -> Дорожный рабочий / благоустройство | F14: 0.25 | G14: ЕНиР Е27 | H14: =IF(OR(F14="",F14=0),"",ROUND($G$3/F14,2)) -> 28 | I14: =INDEX('Нормо-час по специальностям'!$D$6:$D$26,MATCH(D14,'Нормо-час по специальностям'!$A$6:$A$26,0)) -> 650 | J14: =INDEX('Нормо-час по специальностям'!$E$6:$E$26,MATCH(D14,'Нормо-час по специальностям'!$A$6:$A$26,0)) -> 780 | K14: =IF(OR(F14="",F14=0,I14=0),"",ROUND(F14*I14,0)) -> 163 | L14: =IF(OR(F14="",F14=0,J14=0),"",ROUND(F14*J14,0)) -> 195 | M14: =Расценки!L13 -> 280 | N14: =Расценки!M13 -> 322 | O14: =IF(OR(K14="",M14="",M14=0),"",K14/M14-1) -> -0.41785714 | P14: =IF(OR(L14="",N14="",N14=0),"",L14/N14-1) -> -0.39440994 | Q14: =IF(O14="","—",IF(O14<-$C$3,"нормо-часы",IF(O14>$C$3,"расценка","равно"))) -> нормо-часы | R14: =IF(P14="","—",IF(P14<-$C$3,"нормо-часы",IF(P14>$C$3,"расценка","равно"))) -> нормо-часы | S14: =IF(OR(F14="",F14=0,M14=""),"",ROUND(M14/F14,0)) -> 1120 | T14: =IF(OR(F14="",F14=0,N14=""),"",ROUND(N14/F14,0)) -> 1288 | U14: =Расценки!F13 -> 460 | V14: =Расценки!G13 -> 529 | W14: =IF(OR(K14="",U14="",U14=0),"",(U14-K14)/U14) -> 0.64565217 | X14: =IF(OR(L14="",V14="",V14=0),"",(V14-L14)/V14) -> 0.63137996 | Y14: =Расценки!H13 -> 460 | Z14: =Расценки!I13 -> 529 | AA14: =Расценки!J13 -> 0 | AB14: =Расценки!K13 -> 0 | AC14: =IF(OR(K14="",Y14="",Y14=0),"",(Y14-K14)/Y14) -> 0.64565217 | AD14: =IF(OR(L14="",Z14="",Z14=0),"",(Z14-L14)/Z14) -> 0.63137996 | AE14: =IF(OR(Y14="",Y14=0),"",(Y14-M14)/Y14) -> 0.39130435 | AF14: =IF(OR(Z14="",Z14=0),"",(Z14-N14)/Z14) -> 0.39130435 | AG14: =IF(OR(K14="",Y14=""),"",Y14-K14) -> 297 | AH14: =IF(OR(L14="",Z14=""),"",Z14-L14) -> 334
A15: 1.1.N3 | B15: Демонтаж ограждения из сетки/профлиста со стойками | C15: мп | D15: SVA | E15: =INDEX('Нормо-час по специальностям'!$B$6:$B$26,MATCH(D15,'Нормо-час по специальностям'!$A$6:$A$26,0)) -> Сварщик / монтажник МК | F15: 0.4 | G15: ГЭСНр 46-04 (разборка конструкций) ×0,85 | H15: =IF(OR(F15="",F15=0),"",ROUND($G$3/F15,2)) -> 17.5 | I15: =INDEX('Нормо-час по специальностям'!$D$6:$D$26,MATCH(D15,'Нормо-час по специальностям'!$A$6:$A$26,0)) -> 900 | J15: =INDEX('Нормо-час по специальностям'!$E$6:$E$26,MATCH(D15,'Нормо-час по специальностям'!$A$6:$A$26,0)) -> 1080 | K15: =IF(OR(F15="",F15=0,I15=0),"",ROUND(F15*I15,0)) -> 360 | L15: =IF(OR(F15="",F15=0,J15=0),"",ROUND(F15*J15,0)) -> 432 | M15: =Расценки!L14 -> 180 | N15: =Расценки!M14 -> 207 | O15: =IF(OR(K15="",M15="",M15=0),"",K15/M15-1) -> 1 | P15: =IF(OR(L15="",N15="",N15=0),"",L15/N15-1) -> 1.0869565 | Q15: =IF(O15="","—",IF(O15<-$C$3,"нормо-часы",IF(O15>$C$3,"расценка","равно"))) -> расценка | R15: =IF(P15="","—",IF(P15<-$C$3,"нормо-часы",IF(P15>$C$3,"расценка","равно"))) -> расценка | S15: =IF(OR(F15="",F15=0,M15=""),"",ROUND(M15/F15,0)) -> 450 | T15: =IF(OR(F15="",F15=0,N15=""),"",ROUND(N15/F15,0)) -> 518 | U15: =Расценки!F14 -> 300 | V15: =Расценки!G14 -> 345 | W15: =IF(OR(K15="",U15="",U15=0),"",(U15-K15)/U15) -> -0.2 | X15: =IF(OR(L15="",V15="",V15=0),"",(V15-L15)/V15) -> -0.25217391 | Y15: =Расценки!H14 -> 480 | Z15: =Расценки!I14 -> 576 | AA15: =Расценки!J14 -> 0.6 | AB15: =Расценки!K14 -> 0.66956522 | AC15: =IF(OR(K15="",Y15="",Y15=0),"",(Y15-K15)/Y15) -> 0.25 | AD15: =IF(OR(L15="",Z15="",Z15=0),"",(Z15-L15)/Z15) -> 0.25 | AE15: =IF(OR(Y15="",Y15=0),"",(Y15-M15)/Y15) -> 0.625 | AF15: =IF(OR(Z15="",Z15=0),"",(Z15-N15)/Z15) -> 0.640625 | AG15: =IF(OR(K15="",Y15=""),"",Y15-K15) -> 120 | AH15: =IF(OR(L15="",Z15=""),"",Z15-L15) -> 144
A16: 1.2 Демонтажные работы по фасаду
A17: 1.2.1 | B17: Отбивка штукатурки с поверхностей стен | C17: м2 | D17: RAZ | E17: =INDEX('Нормо-час по специальностям'!$B$6:$B$26,MATCH(D17,'Нормо-час по специальностям'!$A$6:$A$26,0)) -> Разнорабочий / демонтажник | F17: 0.35 | G17: ЕНиР Е20-1 (разборка конструкций при ремонте) | H17: =IF(OR(F17="",F17=0),"",ROUND($G$3/F17,2)) -> 20 | I17: =INDEX('Нормо-час по специальностям'!$D$6:$D$26,MATCH(D17,'Нормо-час по специальностям'!$A$6:$A$26,0)) -> 550 | J17: =INDEX('Нормо-час по специальностям'!$E$6:$E$26,MATCH(D17,'Нормо-час по специальностям'!$A$6:$A$26,0)) -> 660 | K17: =IF(OR(F17="",F17=0,I17=0),"",ROUND(F17*I17,0)) -> 193 | L17: =IF(OR(F17="",F17=0,J17=0),"",ROUND(F17*J17,0)) -> 231 | M17: =Расценки!L16 -> 180 | N17: =Расценки!M16 -> 207 | O17: =IF(OR(K17="",M17="",M17=0),"",K17/M17-1) -> 0.072222222 | P17: =IF(OR(L17="",N17="",N17=0),"",L17/N17-1) -> 0.11594203 | Q17: =IF(O17="","—",IF(O17<-$C$3,"нормо-часы",IF(O17>$C$3,"расценка","равно"))) -> равно | R17: =IF(P17="","—",IF(P17<-$C$3,"нормо-часы",IF(P17>$C$3,"расценка","равно"))) -> расценка | S17: =IF(OR(F17="",F17=0,M17=""),"",ROUND(M17/F17,0)) -> 514 | T17: =IF(OR(F17="",F17=0,N17=""),"",ROUND(N17/F17,0)) -> 591 | U17: =Расценки!F16 -> 300 | V17: =Расценки!G16 -> 345 | W17: =IF(OR(K17="",U17="",U17=0),"",(U17-K17)/U17) -> 0.35666667 | X17: =IF(OR(L17="",V17="",V17=0),"",(V17-L17)/V17) -> 0.33043478 | Y17: =Расценки!H16 -> 300 | Z17: =Расценки!I16 -> 345 | AA17: =Расценки!J16 -> 0 | AB17: =Расценки!K16 -> 0 | AC17: =IF(OR(K17="",Y17="",Y17=0),"",(Y17-K17)/Y17) -> 0.35666667 | AD17: =IF(OR(L17="",Z17="",Z17=0),"",(Z17-L17)/Z17) -> 0.33043478 | AE17: =IF(OR(Y17="",Y17=0),"",(Y17-M17)/Y17) -> 0.4 | AF17: =IF(OR(Z17="",Z17=0),"",(Z17-N17)/Z17) -> 0.4 | AG17: =IF(OR(K17="",Y17=""),"",Y17-K17) -> 107 | AH17: =IF(OR(L17="",Z17=""),"",Z17-L17) -> 114
A18: 1.2.2 | B18: Демонтаж облицовки из профилированного листа без разборки каркаса | C18: м2 | D18: RAZ | E18: =INDEX('Нормо-час по специальностям'!$B$6:$B$26,MATCH(D18,'Нормо-час по специальностям'!$A$6:$A$26,0)) -> Разнорабочий / демонтажник | F18: 0.25 | G18: ГЭСНр 46-04 (разборка конструкций) ×0,85 | H18: =IF(OR(F18="",F18=0),"",ROUND($G$3/F18,2)) -> 28 | I18: =INDEX('Нормо-час по специальностям'!$D$6:$D$26,MATCH(D18,'Нормо-час по специальностям'!$A$6:$A$26,0)) -> 550 | J18: =INDEX('Нормо-час по специальностям'!$E$6:$E$26,MATCH(D18,'Нормо-час по специальностям'!$A$6:$A$26,0)) -> 660 | K18: =IF(OR(F18="",F18=0,I18=0),"",ROUND(F18*I18,0)) -> 138 | L18: =IF(OR(F18="",F18=0,J18=0),"",ROUND(F18*J18,0)) -> 165 | M18: =Расценки!L17 -> 150 | N18: =Расценки!M17 -> 172 | O18: =IF(OR(K18="",M18="",M18=0),"",K18/M18-1) -> -0.08 | P18: =IF(OR(L18="",N18="",N18=0),"",L18/N18-1) -> -0.040697674 | Q18: =IF(O18="","—",IF(O18<-$C$3,"нормо-часы",IF(O18>$C$3,"расценка","равно"))) -> равно | R18: =IF(P18="","—",IF(P18<-$C$3,"нормо-часы",IF(P18>$C$3,"расценка","равно"))) -> равно | S18: =IF(OR(F18="",F18=0,M18=""),"",ROUND(M18/F18,0)) -> 600 | T18: =IF(OR(F18="",F18=0,N18=""),"",ROUND(N18/F18,0)) -> 688 | U18: =Расценки!F17 -> 250 | V18: =Расценки!G17 -> 288 | W18: =IF(OR(K18="",U18="",U18=0),"",(U18-K18)/U18) -> 0.448 | X18: =IF(OR(L18="",V18="",V18=0),"",(V18-L18)/V18) -> 0.42708333 | Y18: =Расценки!H17 -> 250 | Z18: =Расценки!I17 -> 288 | AA18: =Расценки!J17 -> 0 | AB18: =Расценки!K17 -> 0 | AC18: =IF(OR(K18="",Y18="",Y18=0),"",(Y18-K18)/Y18) -> 0.448 | AD18: =IF(OR(L18="",Z18="",Z18=0),"",(Z18-L18)/Z18) -> 0.42708333 | AE18: =IF(OR(Y18="",Y18=0),"",(Y18-M18)/Y18) -> 0.4 | AF18: =IF(OR(Z18="",Z18=0),"",(Z18-N18)/Z18) -> 0.40277778 | AG18: =IF(OR(K18="",Y18=""),"",Y18-K18) -> 112 | AH18: =IF(OR(L18="",Z18=""),"",Z18-L18) -> 123
A19: 1.2.3 | B19: Демонтаж облицовки из профилированного листа с разборкой каркаса | C19: м2 | D19: RAZ | E19: =INDEX('Нормо-час по специальностям'!$B$6:$B$26,MATCH(D19,'Нормо-час по специальностям'!$A$6:$A$26,0)) -> Разнорабочий / демонтажник | F19: 0.4 | G19: ГЭСНр 46-04 (разборка конструкций) ×0,85 | H19: =IF(OR(F19="",F19=0),"",ROUND($G$3/F19,2)) -> 17.5 | I19: =INDEX('Нормо-час по специальностям'!$D$6:$D$26,MATCH(D19,'Нормо-час по специальностям'!$A$6:$A$26,0)) -> 550 | J19: =INDEX('Нормо-час по специальностям'!$E$6:$E$26,MATCH(D19,'Нормо-час по специальностям'!$A$6:$A$26,0)) -> 660 | K19: =IF(OR(F19="",F19=0,I19=0),"",ROUND(F19*I19,0)) -> 220 | L19: =IF(OR(F19="",F19=0,J19=0),"",ROUND(F19*J19,0)) -> 264 | M19: =Расценки!L18 -> 230 | N19: =Расценки!M18 -> 264 | O19: =IF(OR(K19="",M19="",M19=0),"",K19/M19-1) -> -0.043478261 | P19: =IF(OR(L19="",N19="",N19=0),"",L19/N19-1) -> 0 | Q19: =IF(O19="","—",IF(O19<-$C$3,"нормо-часы",IF(O19>$C$3,"расценка","равно"))) -> равно | R19: =IF(P19="","—",IF(P19<-$C$3,"нормо-часы",IF(P19>$C$3,"расценка","равно"))) -> равно | S19: =IF(OR(F19="",F19=0,M19=""),"",ROUND(M19/F19,0)) -> 575 | T19: =IF(OR(F19="",F19=0,N19=""),"",ROUND(N19/F19,0)) -> 660 | U19: =Расценки!F18 -> 380 | V19: =Расценки!G18 -> 437 | W19: =IF(OR(K19="",U19="",U19=0),"",(U19-K19)/U19) -> 0.42105263 | X19: =IF(OR(L19="",V19="",V19=0),"",(V19-L19)/V19) -> 0.39588101 | Y19: =Расценки!H18 -> 380 | Z19: =Расценки!I18 -> 437 | AA19: =Расценки!J18 -> 0 | AB19: =Расценки!K18 -> 0 | AC19: =IF(OR(K19="",Y19="",Y19=0),"",(Y19-K19)/Y19) -> 0.42105263 | AD19: =IF(OR(L19="",Z19="",Z19=0),"",(Z19-L19)/Z19) -> 0.39588101 | AE19: =IF(OR(Y19="",Y19=0),"",(Y19-M19)/Y19) -> 0.39473684 | AF19: =IF(OR(Z19="",Z19=0),"",(Z19-N19)/Z19) -> 0.39588101 | AG19: =IF(OR(K19="",Y19=""),"",Y19-K19) -> 160 | AH19: =IF(OR(L19="",Z19=""),"",Z19-L19) -> 173
A20: 1.2.4 | B20: Демонтаж ограждающих конструкций стен из многослойных панелей (сэндвич-панели) | C20: м2 | D20: KRO | E20: =INDEX('Нормо-час по специальностям'!$B$6:$B$26,MATCH(D20,'Нормо-час по специальностям'!$A$6:$A$26,0)) -> Кровельщик | F20: 0.45 | G20: ГЭСНр 46-04 (разборка конструкций) ×0,85 | H20: =IF(OR(F20="",F20=0),"",ROUND($G$3/F20,2)) -> 15.56 | I20: =INDEX('Нормо-час по специальностям'!$D$6:$D$26,MATCH(D20,'Нормо-час по специальностям'!$A$6:$A$26,0)) -> 800 | J20: =INDEX('Нормо-час по специальностям'!$E$6:$E$26,MATCH(D20,'Нормо-час по специальностям'!$A$6:$A$26,0)) -> 950 | K20: =IF(OR(F20="",F20=0,I20=0),"",ROUND(F20*I20,0)) -> 360 | L20: =IF(OR(F20="",F20=0,J20=0),"",ROUND(F20*J20,0)) -> 428 | M20: =Расценки!L19 -> 230 | N20: =Расценки!M19 -> 264 | O20: =IF(OR(K20="",M20="",M20=0),"",K20/M20-1) -> 0.56521739 | P20: =IF(OR(L20="",N20="",N20=0),"",L20/N20-1) -> 0.62121212 | Q20: =IF(O20="","—",IF(O20<-$C$3,"нормо-часы",IF(O20>$C$3,"расценка","равно"))) -> расценка | R20: =IF(P20="","—",IF(P20<-$C$3,"нормо-часы",IF(P20>$C$3,"расценка","равно"))) -> расценка | S20: =IF(OR(F20="",F20=0,M20=""),"",ROUND(M20/F20,0)) -> 511 | T20: =IF(OR(F20="",F20=0,N20=""),"",ROUND(N20/F20,0)) -> 587 | U20: =Расценки!F19 -> 380 | V20: =Расценки!G19 -> 437 | W20: =IF(OR(K20="",U20="",U20=0),"",(U20-K20)/U20) -> 0.052631579 | X20: =IF(OR(L20="",V20="",V20=0),"",(V20-L20)/V20) -> 0.020594966 | Y20: =Расценки!H19 -> 480 | Z20: =Расценки!I19 -> 571 | AA20: =Расценки!J19 -> 0.26315789 | AB20: =Расценки!K19 -> 0.30663616 | AC20: =IF(OR(K20="",Y20="",Y20=0),"",(Y20-K20)/Y20) -> 0.25 | AD20: =IF(OR(L20="",Z20="",Z20=0),"",(Z20-L20)/Z20) -> 0.25043783 | AE20: =IF(OR(Y20="",Y20=0),"",(Y20-M20)/Y20) -> 0.52083333 | AF20: =IF(OR(Z20="",Z20=0),"",(Z20-N20)/Z20) -> 0.53765324 | AG20: =IF(OR(K20="",Y20=""),"",Y20-K20) -> 120 | AH20: =IF(OR(L20="",Z20=""),"",Z20-L20) -> 143
A21: 1.2.5 | B21: Демонтаж ограждающих конструкций стен из панелей "Алюкобонд" и металлического каркаса | C21: м2 | D21: FAS | E21: =INDEX('Нормо-час по специальностям'!$B$6:$B$26,MATCH(D21,'Нормо-час по специальностям'!$A$6:$A$26,0)) -> Фасадчик / промальпинист | F21: 0.9 | G21: ГЭСНр 46-04 (разборка конструкций) ×0,85 | H21: =IF(OR(F21="",F21=0),"",ROUND($G$3/F21,2)) -> 7.78 | I21: =INDEX('Нормо-час по специальностям'!$D$6:$D$26,MATCH(D21,'Нормо-час по специальностям'!$A$6:$A$26,0)) -> 1100 | J21: =INDEX('Нормо-час по специальностям'!$E$6:$E$26,MATCH(D21,'Нормо-час по специальностям'!$A$6:$A$26,0)) -> 1300 | K21: =IF(OR(F21="",F21=0,I21=0),"",ROUND(F21*I21,0)) -> 990 | L21: =IF(OR(F21="",F21=0,J21=0),"",ROUND(F21*J21,0)) -> 1170 | M21: =Расценки!L20 -> 650 | N21: =Расценки!M20 -> 747 | O21: =IF(OR(K21="",M21="",M21=0),"",K21/M21-1) -> 0.52307692 | P21: =IF(OR(L21="",N21="",N21=0),"",L21/N21-1) -> 0.56626506 | Q21: =IF(O21="","—",IF(O21<-$C$3,"нормо-часы",IF(O21>$C$3,"расценка","равно"))) -> расценка | R21: =IF(P21="","—",IF(P21<-$C$3,"нормо-часы",IF(P21>$C$3,"расценка","равно"))) -> расценка | S21: =IF(OR(F21="",F21=0,M21=""),"",ROUND(M21/F21,0)) -> 722 | T21: =IF(OR(F21="",F21=0,N21=""),"",ROUND(N21/F21,0)) -> 830 | U21: =Расценки!F20 -> 1100 | V21: =Расценки!G20 -> 1265 | W21: =IF(OR(K21="",U21="",U21=0),"",(U21-K21)/U21) -> 0.1 | X21: =IF(OR(L21="",V21="",V21=0),"",(V21-L21)/V21) -> 0.075098814 | Y21: =Расценки!H20 -> 1320 | Z21: =Расценки!I20 -> 1560 | AA21: =Расценки!J20 -> 0.2 | AB21: =Расценки!K20 -> 0.23320158 | AC21: =IF(OR(K21="",Y21="",Y21=0),"",(Y21-K21)/Y21) -> 0.25 | AD21: =IF(OR(L21="",Z21="",Z21=0),"",(Z21-L21)/Z21) -> 0.25 | AE21: =IF(OR(Y21="",Y21=0),"",(Y21-M21)/Y21) -> 0.50757576 | AF21: =IF(OR(Z21="",Z21=0),"",(Z21-N21)/Z21) -> 0.52115385 | AG21: =IF(OR(K21="",Y21=""),"",Y21-K21) -> 330 | AH21: =IF(OR(L21="",Z21=""),"",Z21-L21) -> 390
A22: 1.2.6 | B22: Демонтаж теплоизоляционного слоя стен | C22: м2 | D22: RAZ | E22: =INDEX('Нормо-час по специальностям'!$B$6:$B$26,MATCH(D22,'Нормо-час по специальностям'!$A$6:$A$26,0)) -> Разнорабочий / демонтажник | F22: 0.2 | G22: ГЭСНр 46-04 (разборка конструкций) ×0,85 | H22: =IF(OR(F22="",F22=0),"",ROUND($G$3/F22,2)) -> 35 | I22: =INDEX('Нормо-час по специальностям'!$D$6:$D$26,MATCH(D22,'Нормо-час по специальностям'!$A$6:$A$26,0)) -> 550 | J22: =INDEX('Нормо-час по специальностям'!$E$6:$E$26,MATCH(D22,'Нормо-час по специальностям'!$A$6:$A$26,0)) -> 660 | K22: =IF(OR(F22="",F22=0,I22=0),"",ROUND(F22*I22,0)) -> 110 | L22: =IF(OR(F22="",F22=0,J22=0),"",ROUND(F22*J22,0)) -> 132 | M22: =Расценки!L21 -> 120 | N22: =Расценки!M21 -> 138 | O22: =IF(OR(K22="",M22="",M22=0),"",K22/M22-1) -> -0.083333333 | P22: =IF(OR(L22="",N22="",N22=0),"",L22/N22-1) -> -0.043478261 | Q22: =IF(O22="","—",IF(O22<-$C$3,"нормо-часы",IF(O22>$C$3,"расценка","равно"))) -> равно | R22: =IF(P22="","—",IF(P22<-$C$3,"нормо-часы",IF(P22>$C$3,"расценка","равно"))) -> равно | S22: =IF(OR(F22="",F22=0,M22=""),"",ROUND(M22/F22,0)) -> 600 | T22: =IF(OR(F22="",F22=0,N22=""),"",ROUND(N22/F22,0)) -> 690 | U22: =Расценки!F21 -> 200 | V22: =Расценки!G21 -> 230 | W22: =IF(OR(K22="",U22="",U22=0),"",(U22-K22)/U22) -> 0.45 | X22: =IF(OR(L22="",V22="",V22=0),"",(V22-L22)/V22) -> 0.42608696 | Y22: =Расценки!H21 -> 200 | Z22: =Расценки!I21 -> 230 | AA22: =Расценки!J21 -> 0 | AB22: =Расценки!K21 -> 0 | AC22: =IF(OR(K22="",Y22="",Y22=0),"",(Y22-K22)/Y22) -> 0.45 | AD22: =IF(OR(L22="",Z22="",Z22=0),"",(Z22-L22)/Z22) -> 0.42608696 | AE22: =IF(OR(Y22="",Y22=0),"",(Y22-M22)/Y22) -> 0.4 | AF22: =IF(OR(Z22="",Z22=0),"",(Z22-N22)/Z22) -> 0.4 | AG22: =IF(OR(K22="",Y22=""),"",Y22-K22) -> 90 | AH22: =IF(OR(L22="",Z22=""),"",Z22-L22) -> 98
A23: 1.2.7 | B23: Разборка систем вентилируемых фасадов из плит "Керамогранит" с сохранением каркаса | C23: м2 | D23: FAS | E23: =INDEX('Нормо-час по специальностям'!$B$6:$B$26,MATCH(D23,'Нормо-час по специальностям'!$A$6:$A$26,0)) -> Фасадчик / промальпинист | F23: 0.6 | G23: ГЭСНр 46-04 (разборка конструкций) ×0,85 | H23: =IF(OR(F23="",F23=0),"",ROUND($G$3/F23,2)) -> 11.67 | I23: =INDEX('Нормо-час по специальностям'!$D$6:$D$26,MATCH(D23,'Нормо-час по специальностям'!$A$6:$A$26,0)) -> 1100 | J23: =INDEX('Нормо-час по специальностям'!$E$6:$E$26,MATCH(D23,'Нормо-час по специальностям'!$A$6:$A$26,0)) -> 1300 | K23: =IF(OR(F23="",F23=0,I23=0),"",ROUND(F23*I23,0)) -> 660 | L23: =IF(OR(F23="",F23=0,J23=0),"",ROUND(F23*J23,0)) -> 780 | M23: =Расценки!L22 -> 400 | N23: =Расценки!M22 -> 460 | O23: =IF(OR(K23="",M23="",M23=0),"",K23/M23-1) -> 0.65 | P23: =IF(OR(L23="",N23="",N23=0),"",L23/N23-1) -> 0.69565217 | Q23: =IF(O23="","—",IF(O23<-$C$3,"нормо-часы",IF(O23>$C$3,"расценка","равно"))) -> расценка | R23: =IF(P23="","—",IF(P23<-$C$3,"нормо-часы",IF(P23>$C$3,"расценка","равно"))) -> расценка | S23: =IF(OR(F23="",F23=0,M23=""),"",ROUND(M23/F23,0)) -> 667 | T23: =IF(OR(F23="",F23=0,N23=""),"",ROUND(N23/F23,0)) -> 767 | U23: =Расценки!F22 -> 650 | V23: =Расценки!G22 -> 747 | W23: =IF(OR(K23="",U23="",U23=0),"",(U23-K23)/U23) -> -0.015384615 | X23: =IF(OR(L23="",V23="",V23=0),"",(V23-L23)/V23) -> -0.044176707 | Y23: =Расценки!H22 -> 880 | Z23: =Расценки!I22 -> 1040 | AA23: =Расценки!J22 -> 0.35384615 | AB23: =Расценки!K22 -> 0.39223561 | AC23: =IF(OR(K23="",Y23="",Y23=0),"",(Y23-K23)/Y23) -> 0.25 | AD23: =IF(OR(L23="",Z23="",Z23=0),"",(Z23-L23)/Z23) -> 0.25 | AE23: =IF(OR(Y23="",Y23=0),"",(Y23-M23)/Y23) -> 0.54545455 | AF23: =IF(OR(Z23="",Z23=0),"",(Z23-N23)/Z23) -> 0.55769231 | AG23: =IF(OR(K23="",Y23=""),"",Y23-K23) -> 220 | AH23: =IF(OR(L23="",Z23=""),"",Z23-L23) -> 260
A24: 1.2.8 | B24: Разборка систем вентилируемых фасадов из плит "Керамогранит" с учетом каркаса | C24: м2 | D24: FAS | E24: =INDEX('Нормо-час по специальностям'!$B$6:$B$26,MATCH(D24,'Нормо-час по специальностям'!$A$6:$A$26,0)) -> Фасадчик / промальпинист | F24: 1 | G24: ГЭСНр 46-04 (разборка конструкций) ×0,85 | H24: =IF(OR(F24="",F24=0),"",ROUND($G$3/F24,2)) -> 7 | I24: =INDEX('Нормо-час по специальностям'!$D$6:$D$26,MATCH(D24,'Нормо-час по специальностям'!$A$6:$A$26,0)) -> 1100 | J24: =INDEX('Нормо-час по специальностям'!$E$6:$E$26,MATCH(D24,'Нормо-час по специальностям'!$A$6:$A$26,0)) -> 1300 | K24: =IF(OR(F24="",F24=0,I24=0),"",ROUND(F24*I24,0)) -> 1100 | L24: =IF(OR(F24="",F24=0,J24=0),"",ROUND(F24*J24,0)) -> 1300 | M24: =Расценки!L23 -> 650 | N24: =Расценки!M23 -> 747 | O24: =IF(OR(K24="",M24="",M24=0),"",K24/M24-1) -> 0.69230769 | P24: =IF(OR(L24="",N24="",N24=0),"",L24/N24-1) -> 0.74029451 | Q24: =IF(O24="","—",IF(O24<-$C$3,"нормо-часы",IF(O24>$C$3,"расценка","равно"))) -> расценка | R24: =IF(P24="","—",IF(P24<-$C$3,"нормо-часы",IF(P24>$C$3,"расценка","равно"))) -> расценка | S24: =IF(OR(F24="",F24=0,M24=""),"",ROUND(M24/F24,0)) -> 650 | T24: =IF(OR(F24="",F24=0,N24=""),"",ROUND(N24/F24,0)) -> 747 | U24: =Расценки!F23 -> 1100 | V24: =Расценки!G23 -> 1265 | W24: =IF(OR(K24="",U24="",U24=0),"",(U24-K24)/U24) -> 0 | X24: =IF(OR(L24="",V24="",V24=0),"",(V24-L24)/V24) -> -0.027667984 | Y24: =Расценки!H23 -> 1467 | Z24: =Расценки!I23 -> 1734 | AA24: =Расценки!J23 -> 0.33363636 | AB24: =Расценки!K23 -> 0.37075099 | AC24: =IF(OR(K24="",Y24="",Y24=0),"",(Y24-K24)/Y24) -> 0.25017042 | AD24: =IF(OR(L24="",Z24="",Z24=0),"",(Z24-L24)/Z24) -> 0.25028835 | AE24: =IF(OR(Y24="",Y24=0),"",(Y24-M24)/Y24) -> 0.55691888 | AF24: =IF(OR(Z24="",Z24=0),"",(Z24-N24)/Z24) -> 0.56920415 | AG24: =IF(OR(K24="",Y24=""),"",Y24-K24) -> 367 | AH24: =IF(OR(L24="",Z24=""),"",Z24-L24) -> 434
A25: 1.2.N1 | B25: Демонтаж металлического козырька/навеса над входом | C25: м2 | D25: SVA | E25: =INDEX('Нормо-час по специальностям'!$B$6:$B$26,MATCH(D25,'Нормо-час по специальностям'!$A$6:$A$26,0)) -> Сварщик / монтажник МК | F25: 1 | G25: ЕНиР Е5 (демонтаж МК ≈0,6–0,7 от монтажа) | H25: =IF(OR(F25="",F25=0),"",ROUND($G$3/F25,2)) -> 7 | I25: =INDEX('Нормо-час по специальностям'!$D$6:$D$26,MATCH(D25,'Нормо-час по специальностям'!$A$6:$A$26,0)) -> 900 | J25: =INDEX('Нормо-час по специальностям'!$E$6:$E$26,MATCH(D25,'Нормо-час по специальностям'!$A$6:$A$26,0)) -> 1080 | K25: =IF(OR(F25="",F25=0,I25=0),"",ROUND(F25*I25,0)) -> 900 | L25: =IF(OR(F25="",F25=0,J25=0),"",ROUND(F25*J25,0)) -> 1080 | M25: =Расценки!L24 -> 720 | N25: =Расценки!M24 -> 828 | O25: =IF(OR(K25="",M25="",M25=0),"",K25/M25-1) -> 0.25 | P25: =IF(OR(L25="",N25="",N25=0),"",L25/N25-1) -> 0.30434783 | Q25: =IF(O25="","—",IF(O25<-$C$3,"нормо-часы",IF(O25>$C$3,"расценка","равно"))) -> расценка | R25: =IF(P25="","—",IF(P25<-$C$3,"нормо-часы",IF(P25>$C$3,"расценка","равно"))) -> расценка | S25: =IF(OR(F25="",F25=0,M25=""),"",ROUND(M25/F25,0)) -> 720 | T25: =IF(OR(F25="",F25=0,N25=""),"",ROUND(N25/F25,0)) -> 828 | U25: =Расценки!F24 -> 1200 | V25: =Расценки!G24 -> 1380 | W25: =IF(OR(K25="",U25="",U25=0),"",(U25-K25)/U25) -> 0.25 | X25: =IF(OR(L25="",V25="",V25=0),"",(V25-L25)/V25) -> 0.2173913 | Y25: =Расценки!H24 -> 1200 | Z25: =Расценки!I24 -> 1440 | AA25: =Расценки!J24 -> 0 | AB25: =Расценки!K24 -> 0.043478261 | AC25: =IF(OR(K25="",Y25="",Y25=0),"",(Y25-K25)/Y25) -> 0.25 | AD25: =IF(OR(L25="",Z25="",Z25=0),"",(Z25-L25)/Z25) -> 0.25 | AE25: =IF(OR(Y25="",Y25=0),"",(Y25-M25)/Y25) -> 0.4 | AF25: =IF(OR(Z25="",Z25=0),"",(Z25-N25)/Z25) -> 0.425 | AG25: =IF(OR(K25="",Y25=""),"",Y25-K25) -> 300 | AH25: =IF(OR(L25="",Z25=""),"",Z25-L25) -> 360
A26: 1.3 Демонтажные работы по фундаменту
A27: 1.3.1 | B27: Разборка бутовых фундаментов | C27: м3 | D27: RAZ | E27: =INDEX('Нормо-час по специальностям'!$B$6:$B$26,MATCH(D27,'Нормо-час по специальностям'!$A$6:$A$26,0)) -> Разнорабочий / демонтажник | F27: 7.5 | G27: ГЭСНр 46-04 (разборка конструкций) ×0,85 | H27: =IF(OR(F27="",F27=0),"",ROUND($G$3/F27,2)) -> 0.93 | I27: =INDEX('Нормо-час по специальностям'!$D$6:$D$26,MATCH(D27,'Нормо-час по специальностям'!$A$6:$A$26,0)) -> 550 | J27: =INDEX('Нормо-час по специальностям'!$E$6:$E$26,MATCH(D27,'Нормо-час по специальностям'!$A$6:$A$26,0)) -> 660 | K27: =IF(OR(F27="",F27=0,I27=0),"",ROUND(F27*I27,0)) -> 4125 | L27: =IF(OR(F27="",F27=0,J27=0),"",ROUND(F27*J27,0)) -> 4950 | M27: =Расценки!L26 -> 2400 | N27: =Расценки!M26 -> 2760 | O27: =IF(OR(K27="",M27="",M27=0),"",K27/M27-1) -> 0.71875 | P27: =IF(OR(L27="",N27="",N27=0),"",L27/N27-1) -> 0.79347826 | Q27: =IF(O27="","—",IF(O27<-$C$3,"нормо-часы",IF(O27>$C$3,"расценка","равно"))) -> расценка | R27: =IF(P27="","—",IF(P27<-$C$3,"нормо-часы",IF(P27>$C$3,"расценка","равно"))) -> расценка | S27: =IF(OR(F27="",F27=0,M27=""),"",ROUND(M27/F27,0)) -> 320 | T27: =IF(OR(F27="",F27=0,N27=""),"",ROUND(N27/F27,0)) -> 368 | U27: =Расценки!F26 -> 4000 | V27: =Расценки!G26 -> 4600 | W27: =IF(OR(K27="",U27="",U27=0),"",(U27-K27)/U27) -> -0.03125 | X27: =IF(OR(L27="",V27="",V27=0),"",(V27-L27)/V27) -> -0.076086957 | Y27: =Расценки!H26 -> 5500 | Z27: =Расценки!I26 -> 6600 | AA27: =Расценки!J26 -> 0.375 | AB27: =Расценки!K26 -> 0.43478261 | AC27: =IF(OR(K27="",Y27="",Y27=0),"",(Y27-K27)/Y27) -> 0.25 | AD27: =IF(OR(L27="",Z27="",Z27=0),"",(Z27-L27)/Z27) -> 0.25 | AE27: =IF(OR(Y27="",Y27=0),"",(Y27-M27)/Y27) -> 0.56363636 | AF27: =IF(OR(Z27="",Z27=0),"",(Z27-N27)/Z27) -> 0.58181818 | AG27: =IF(OR(K27="",Y27=""),"",Y27-K27) -> 1375 | AH27: =IF(OR(L27="",Z27=""),"",Z27-L27) -> 1650
A28: 1.3.2 | B28: Разборка бетонных фундаментов | C28: м3 | D28: RAZ | E28: =INDEX('Нормо-час по специальностям'!$B$6:$B$26,MATCH(D28,'Нормо-час по специальностям'!$A$6:$A$26,0)) -> Разнорабочий / демонтажник | F28: 11 | G28: ГЭСНр 46-04 (разборка конструкций) ×0,85 | H28: =IF(OR(F28="",F28=0),"",ROUND($G$3/F28,2)) -> 0.64 | I28: =INDEX('Нормо-час по специальностям'!$D$6:$D$26,MATCH(D28,'Нормо-час по специальностям'!$A$6:$A$26,0)) -> 550 | J28: =INDEX('Нормо-час по специальностям'!$E$6:$E$26,MATCH(D28,'Нормо-час по специальностям'!$A$6:$A$26,0)) -> 660 | K28: =IF(OR(F28="",F28=0,I28=0),"",ROUND(F28*I28,0)) -> 6050 | L28: =IF(OR(F28="",F28=0,J28=0),"",ROUND(F28*J28,0)) -> 7260 | M28: =Расценки!L27 -> 4500 | N28: =Расценки!M27 -> 5310 | O28: =IF(OR(K28="",M28="",M28=0),"",K28/M28-1) -> 0.34444444 | P28: =IF(OR(L28="",N28="",N28=0),"",L28/N28-1) -> 0.36723164 | Q28: =IF(O28="","—",IF(O28<-$C$3,"нормо-часы",IF(O28>$C$3,"расценка","равно"))) -> расценка | R28: =IF(P28="","—",IF(P28<-$C$3,"нормо-часы",IF(P28>$C$3,"расценка","равно"))) -> расценка | S28: =IF(OR(F28="",F28=0,M28=""),"",ROUND(M28/F28,0)) -> 409 | T28: =IF(OR(F28="",F28=0,N28=""),"",ROUND(N28/F28,0)) -> 483 | U28: =Расценки!F27 -> 7500 | V28: =Расценки!G27 -> 9000 | W28: =IF(OR(K28="",U28="",U28=0),"",(U28-K28)/U28) -> 0.19333333 | X28: =IF(OR(L28="",V28="",V28=0),"",(V28-L28)/V28) -> 0.19333333 | Y28: =Расценки!H27 -> 8067 | Z28: =Расценки!I27 -> 9680 | AA28: =Расценки!J27 -> 0.0756 | AB28: =Расценки!K27 -> 0.075555556 | AC28: =IF(OR(K28="",Y28="",Y28=0),"",(Y28-K28)/Y28) -> 0.25003099 | AD28: =IF(OR(L28="",Z28="",Z28=0),"",(Z28-L28)/Z28) -> 0.25 | AE28: =IF(OR(Y28="",Y28=0),"",(Y28-M28)/Y28) -> 0.44217181 | AF28: =IF(OR(Z28="",Z28=0),"",(Z28-N28)/Z28) -> 0.45144628 | AG28: =IF(OR(K28="",Y28=""),"",Y28-K28) -> 2017 | AH28: =IF(OR(L28="",Z28=""),"",Z28-L28) -> 2420
A29: 1.3.3 | B29: Разборка железобетонных фундаментов | C29: м3 | D29: RAZ | E29: =INDEX('Нормо-час по специальностям'!$B$6:$B$26,MATCH(D29,'Нормо-час по специальностям'!$A$6:$A$26,0)) -> Разнорабочий / демонтажник | F29: 15 | G29: ГЭСНр 46-04 (разборка конструкций) ×0,85 | H29: =IF(OR(F29="",F29=0),"",ROUND($G$3/F29,2)) -> 0.47 | I29: =INDEX('Нормо-час по специальностям'!$D$6:$D$26,MATCH(D29,'Нормо-час по специальностям'!$A$6:$A$26,0)) -> 550 | J29: =INDEX('Нормо-час по специальностям'!$E$6:$E$26,MATCH(D29,'Нормо-час по специальностям'!$A$6:$A$26,0)) -> 660 | K29: =IF(OR(F29="",F29=0,I29=0),"",ROUND(F29*I29,0)) -> 8250 | L29: =IF(OR(F29="",F29=0,J29=0),"",ROUND(F29*J29,0)) -> 9900 | M29: =Расценки!L28 -> 6000 | N29: =Расценки!M28 -> 7080 | O29: =IF(OR(K29="",M29="",M29=0),"",K29/M29-1) -> 0.375 | P29: =IF(OR(L29="",N29="",N29=0),"",L29/N29-1) -> 0.39830508 | Q29: =IF(O29="","—",IF(O29<-$C$3,"нормо-часы",IF(O29>$C$3,"расценка","равно"))) -> расценка | R29: =IF(P29="","—",IF(P29<-$C$3,"нормо-часы",IF(P29>$C$3,"расценка","равно"))) -> расценка | S29: =IF(OR(F29="",F29=0,M29=""),"",ROUND(M29/F29,0)) -> 400 | T29: =IF(OR(F29="",F29=0,N29=""),"",ROUND(N29/F29,0)) -> 472 | U29: =Расценки!F28 -> 10000 | V29: =Расценки!G28 -> 12000 | W29: =IF(OR(K29="",U29="",U29=0),"",(U29-K29)/U29) -> 0.175 | X29: =IF(OR(L29="",V29="",V29=0),"",(V29-L29)/V29) -> 0.175 | Y29: =Расценки!H28 -> 11000 | Z29: =Расценки!I28 -> 13200 | AA29: =Расценки!J28 -> 0.1 | AB29: =Расценки!K28 -> 0.1 | AC29: =IF(OR(K29="",Y29="",Y29=0),"",(Y29-K29)/Y29) -> 0.25 | AD29: =IF(OR(L29="",Z29="",Z29=0),"",(Z29-L29)/Z29) -> 0.25 | AE29: =IF(OR(Y29="",Y29=0),"",(Y29-M29)/Y29) -> 0.45454545 | AF29: =IF(OR(Z29="",Z29=0),"",(Z29-N29)/Z29) -> 0.46363636 | AG29: =IF(OR(K29="",Y29=""),"",Y29-K29) -> 2750 | AH29: =IF(OR(L29="",Z29=""),"",Z29-L29) -> 3300
A30: 1.4 Демонтажные работы кровли
A31: 1.4.1 | B31: Очистка кровли от листвы и мусора | C31: м2 | D31: RAZ | E31: =INDEX('Нормо-час по специальностям'!$B$6:$B$26,MATCH(D31,'Нормо-час по специальностям'!$A$6:$A$26,0)) -> Разнорабочий / демонтажник | F31: 0.04 | G31: экспертно (аналог очистки снега) | H31: =IF(OR(F31="",F31=0),"",ROUND($G$3/F31,2)) -> 175 | I31: =INDEX('Нормо-час по специальностям'!$D$6:$D$26,MATCH(D31,'Нормо-час по специальностям'!$A$6:$A$26,0)) -> 550 | J31: =INDEX('Нормо-час по специальностям'!$E$6:$E$26,MATCH(D31,'Нормо-час по специальностям'!$A$6:$A$26,0)) -> 660 | K31: =IF(OR(F31="",F31=0,I31=0),"",ROUND(F31*I31,0)) -> 22 | L31: =IF(OR(F31="",F31=0,J31=0),"",ROUND(F31*J31,0)) -> 26 | M31: =Расценки!L30 -> 20 | N31: =Расценки!M30 -> 23 | O31: =IF(OR(K31="",M31="",M31=0),"",K31/M31-1) -> 0.1 | P31: =IF(OR(L31="",N31="",N31=0),"",L31/N31-1) -> 0.13043478 | Q31: =IF(O31="","—",IF(O31<-$C$3,"нормо-часы",IF(O31>$C$3,"расценка","равно"))) -> равно | R31: =IF(P31="","—",IF(P31<-$C$3,"нормо-часы",IF(P31>$C$3,"расценка","равно"))) -> расценка | S31: =IF(OR(F31="",F31=0,M31=""),"",ROUND(M31/F31,0)) -> 500 | T31: =IF(OR(F31="",F31=0,N31=""),"",ROUND(N31/F31,0)) -> 575 | U31: =Расценки!F30 -> 35 | V31: =Расценки!G30 -> 40 | W31: =IF(OR(K31="",U31="",U31=0),"",(U31-K31)/U31) -> 0.37142857 | X31: =IF(OR(L31="",V31="",V31=0),"",(V31-L31)/V31) -> 0.35 | Y31: =Расценки!H30 -> 35 | Z31: =Расценки!I30 -> 40 | AA31: =Расценки!J30 -> 0 | AB31: =Расценки!K30 -> 0 | AC31: =IF(OR(K31="",Y31="",Y31=0),"",(Y31-K31)/Y31) -> 0.37142857 | AD31: =IF(OR(L31="",Z31="",Z31=0),"",(Z31-L31)/Z31) -> 0.35 | AE31: =IF(OR(Y31="",Y31=0),"",(Y31-M31)/Y31) -> 0.42857143 | AF31: =IF(OR(Z31="",Z31=0),"",(Z31-N31)/Z31) -> 0.425 | AG31: =IF(OR(K31="",Y31=""),"",Y31-K31) -> 13 | AH31: =IF(OR(L31="",Z31=""),"",Z31-L31) -> 14
A32: 1.4.2 | B32: Очистка снега с крыш при толщине слоя до 20 см | C32: м2 | D32: RAZ | E32: =INDEX('Нормо-час по специальностям'!$B$6:$B$26,MATCH(D32,'Нормо-час по специальностям'!$A$6:$A$26,0)) -> Разнорабочий / демонтажник | F32: 0.04 | G32: НВ ТО (отраслевые нормы времени на ТО/ремонт) | H32: =IF(OR(F32="",F32=0),"",ROUND($G$3/F32,2)) -> 175 | I32: =INDEX('Нормо-час по специальностям'!$D$6:$D$26,MATCH(D32,'Нормо-час по специальностям'!$A$6:$A$26,0)) -> 550 | J32: =INDEX('Нормо-час по специальностям'!$E$6:$E$26,MATCH(D32,'Нормо-час по специальностям'!$A$6:$A$26,0)) -> 660 | K32: =IF(OR(F32="",F32=0,I32=0),"",ROUND(F32*I32,0)) -> 22 | L32: =IF(OR(F32="",F32=0,J32=0),"",ROUND(F32*J32,0)) -> 26 | M32: =Расценки!L31 -> 18 | N32: =Расценки!M31 -> 20.5 | O32: =IF(OR(K32="",M32="",M32=0),"",K32/M32-1) -> 0.22222222 | P32: =IF(OR(L32="",N32="",N32=0),"",L32/N32-1) -> 0.26829268 | Q32: =IF(O32="","—",IF(O32<-$C$3,"нормо-часы",IF(O32>$C$3,"расценка","равно"))) -> расценка | R32: =IF(P32="","—",IF(P32<-$C$3,"нормо-часы",IF(P32>$C$3,"расценка","равно"))) -> расценка | S32: =IF(OR(F32="",F32=0,M32=""),"",ROUND(M32/F32,0)) -> 450 | T32: =IF(OR(F32="",F32=0,N32=""),"",ROUND(N32/F32,0)) -> 513 | U32: =Расценки!F31 -> 30 | V32: =Расценки!G31 -> 34.5 | W32: =IF(OR(K32="",U32="",U32=0),"",(U32-K32)/U32) -> 0.26666667 | X32: =IF(OR(L32="",V32="",V32=0),"",(V32-L32)/V32) -> 0.24637681 | Y32: =Расценки!H31 -> 30 | Z32: =Расценки!I31 -> 35 | AA32: =Расценки!J31 -> 0 | AB32: =Расценки!K31 -> 0.014492754 | AC32: =IF(OR(K32="",Y32="",Y32=0),"",(Y32-K32)/Y32) -> 0.26666667 | AD32: =IF(OR(L32="",Z32="",Z32=0),"",(Z32-L32)/Z32) -> 0.25714286 | AE32: =IF(OR(Y32="",Y32=0),"",(Y32-M32)/Y32) -> 0.4 | AF32: =IF(OR(Z32="",Z32=0),"",(Z32-N32)/Z32) -> 0.41428571 | AG32: =IF(OR(K32="",Y32=""),"",Y32-K32) -> 8 | AH32: =IF(OR(L32="",Z32=""),"",Z32-L32) -> 9
A33: 1.4.3 | B33: Очистка снега с крыш, добавлять на каждые следующие 10 см увеличения толщины слоя | C33: м2 | D33: RAZ | E33: =INDEX('Нормо-час по специальностям'!$B$6:$B$26,MATCH(D33,'Нормо-час по специальностям'!$A$6:$A$26,0)) -> Разнорабочий / демонтажник | F33: 0.012 | G33: НВ ТО (отраслевые нормы времени на ТО/ремонт) | H33: =IF(OR(F33="",F33=0),"",ROUND($G$3/F33,2)) -> 583.33 | I33: =INDEX('Нормо-час по специальностям'!$D$6:$D$26,MATCH(D33,'Нормо-час по специальностям'!$A$6:$A$26,0)) -> 550 | J33: =INDEX('Нормо-час по специальностям'!$E$6:$E$26,MATCH(D33,'Нормо-час по специальностям'!$A$6:$A$26,0)) -> 660 | K33: =IF(OR(F33="",F33=0,I33=0),"",ROUND(F33*I33,0)) -> 7 | L33: =IF(OR(F33="",F33=0,J33=0),"",ROUND(F33*J33,0)) -> 8 | M33: =Расценки!L32 -> 5 | N33: =Расценки!M32 -> 6 | O33: =IF(OR(K33="",M33="",M33=0),"",K33/M33-1) -> 0.4 | P33: =IF(OR(L33="",N33="",N33=0),"",L33/N33-1) -> 0.33333333 | Q33: =IF(O33="","—",IF(O33<-$C$3,"нормо-часы",IF(O33>$C$3,"расценка","равно"))) -> расценка | R33: =IF(P33="","—",IF(P33<-$C$3,"нормо-часы",IF(P33>$C$3,"расценка","равно"))) -> расценка | S33: =IF(OR(F33="",F33=0,M33=""),"",ROUND(M33/F33,0)) -> 417 | T33: =IF(OR(F33="",F33=0,N33=""),"",ROUND(N33/F33,0)) -> 500 | U33: =Расценки!F32 -> 8 | V33: =Расценки!G32 -> 9 | W33: =IF(OR(K33="",U33="",U33=0),"",(U33-K33)/U33) -> 0.125 | X33: =IF(OR(L33="",V33="",V33=0),"",(V33-L33)/V33) -> 0.11111111 | Y33: =Расценки!H32 -> 10 | Z33: =Расценки!I32 -> 11 | AA33: =Расценки!J32 -> 0.25 | AB33: =Расценки!K32 -> 0.22222222 | AC33: =IF(OR(K33="",Y33="",Y33=0),"",(Y33-K33)/Y33) -> 0.3 | AD33: =IF(OR(L33="",Z33="",Z33=0),"",(Z33-L33)/Z33) -> 0.27272727 | AE33: =IF(OR(Y33="",Y33=0),"",(Y33-M33)/Y33) -> 0.5 | AF33: =IF(OR(Z33="",Z33=0),"",(Z33-N33)/Z33) -> 0.45454545 | AG33: =IF(OR(K33="",Y33=""),"",Y33-K33) -> 3 | AH33: =IF(OR(L33="",Z33=""),"",Z33-L33) -> 3
A34: 1.4.4 | B34: Разборка водосточных ПВХ труб | C34: мп | D34: KRO | E34: =INDEX('Нормо-час по специальностям'!$B$6:$B$26,MATCH(D34,'Нормо-час по специальностям'!$A$6:$A$26,0)) -> Кровельщик | F34: 0.15 | G34: ГЭСНр 58 (разборка кровель) ×0,85 | H34: =IF(OR(F34="",F34=0),"",ROUND($G$3/F34,2)) -> 46.67 | I34: =INDEX('Нормо-час по специальностям'!$D$6:$D$26,MATCH(D34,'Нормо-час по специальностям'!$A$6:$A$26,0)) -> 800 | J34: =INDEX('Нормо-час по специальностям'!$E$6:$E$26,MATCH(D34,'Нормо-час по специальностям'!$A$6:$A$26,0)) -> 950 | K34: =IF(OR(F34="",F34=0,I34=0),"",ROUND(F34*I34,0)) -> 120 | L34: =IF(OR(F34="",F34=0,J34=0),"",ROUND(F34*J34,0)) -> 143 | M34: =Расценки!L33 -> 70 | N34: =Расценки!M33 -> 80.5 | O34: =IF(OR(K34="",M34="",M34=0),"",K34/M34-1) -> 0.71428571 | P34: =IF(OR(L34="",N34="",N34=0),"",L34/N34-1) -> 0.77639752 | Q34: =IF(O34="","—",IF(O34<-$C$3,"нормо-часы",IF(O34>$C$3,"расценка","равно"))) -> расценка | R34: =IF(P34="","—",IF(P34<-$C$3,"нормо-часы",IF(P34>$C$3,"расценка","равно"))) -> расценка | S34: =IF(OR(F34="",F34=0,M34=""),"",ROUND(M34/F34,0)) -> 467 | T34: =IF(OR(F34="",F34=0,N34=""),"",ROUND(N34/F34,0)) -> 537 | U34: =Расценки!F33 -> 120 | V34: =Расценки!G33 -> 138 | W34: =IF(OR(K34="",U34="",U34=0),"",(U34-K34)/U34) -> 0 | X34: =IF(OR(L34="",V34="",V34=0),"",(V34-L34)/V34) -> -0.036231884 | Y34: =Расценки!H33 -> 160 | Z34: =Расценки!I33 -> 191 | AA34: =Расценки!J33 -> 0.33333333 | AB34: =Расценки!K33 -> 0.38405797 | AC34: =IF(OR(K34="",Y34="",Y34=0),"",(Y34-K34)/Y34) -> 0.25 | AD34: =IF(OR(L34="",Z34="",Z34=0),"",(Z34-L34)/Z34) -> 0.2513089 | AE34: =IF(OR(Y34="",Y34=0),"",(Y34-M34)/Y34) -> 0.5625 | AF34: =IF(OR(Z34="",Z34=0),"",(Z34-N34)/Z34) -> 0.57853403 | AG34: =IF(OR(K34="",Y34=""),"",Y34-K34) -> 40 | AH34: =IF(OR(L34="",Z34=""),"",Z34-L34) -> 48
A35: 1.4.5 | B35: Разборка водосточных труб металлических | C35: мп | D35: KRO | E35: =INDEX('Нормо-час по специальностям'!$B$6:$B$26,MATCH(D35,'Нормо-час по специальностям'!$A$6:$A$26,0)) -> Кровельщик | F35: 0.2 | G35: ГЭСНр 58 (разборка кровель) ×0,85 | H35: =IF(OR(F35="",F35=0),"",ROUND($G$3/F35,2)) -> 35 | I35: =INDEX('Нормо-час по специальностям'!$D$6:$D$26,MATCH(D35,'Нормо-час по специальностям'!$A$6:$A$26,0)) -> 800 | J35: =INDEX('Нормо-час по специальностям'!$E$6:$E$26,MATCH(D35,'Нормо-час по специальностям'!$A$6:$A$26,0)) -> 950 | K35: =IF(OR(F35="",F35=0,I35=0),"",ROUND(F35*I35,0)) -> 160 | L35: =IF(OR(F35="",F35=0,J35=0),"",ROUND(F35*J35,0)) -> 190 | M35: =Расценки!L34 -> 90 | N35: =Расценки!M34 -> 103 | O35: =IF(OR(K35="",M35="",M35=0),"",K35/M35-1) -> 0.77777778 | P35: =IF(OR(L35="",N35="",N35=0),"",L35/N35-1) -> 0.84466019 | Q35: =IF(O35="","—",IF(O35<-$C$3,"нормо-часы",IF(O35>$C$3,"расценка","равно"))) -> расценка | R35: =IF(P35="","—",IF(P35<-$C$3,"нормо-часы",IF(P35>$C$3,"расценка","равно"))) -> расценка | S35: =IF(OR(F35="",F35=0,M35=""),"",ROUND(M35/F35,0)) -> 450 | T35: =IF(OR(F35="",F35=0,N35=""),"",ROUND(N35/F35,0)) -> 515 | U35: =Расценки!F34 -> 150 | V35: =Расценки!G34 -> 172 | W35: =IF(OR(K35="",U35="",U35=0),"",(U35-K35)/U35) -> -0.066666667 | X35: =IF(OR(L35="",V35="",V35=0),"",(V35-L35)/V35) -> -0.10465116 | Y35: =Расценки!H34 -> 214 | Z35: =Расценки!I34 -> 254 | AA35: =Расценки!J34 -> 0.42666667 | AB35: =Расценки!K34 -> 0.47674419 | AC35: =IF(OR(K35="",Y35="",Y35=0),"",(Y35-K35)/Y35) -> 0.25233645 | AD35: =IF(OR(L35="",Z35="",Z35=0),"",(Z35-L35)/Z35) -> 0.2519685 | AE35: =IF(OR(Y35="",Y35=0),"",(Y35-M35)/Y35) -> 0.57943925 | AF35: =IF(OR(Z35="",Z35=0),"",(Z35-N35)/Z35) -> 0.59448819 | AG35: =IF(OR(K35="",Y35=""),"",Y35-K35) -> 54 | AH35: =IF(OR(L35="",Z35=""),"",Z35-L35) -> 64
A36: 1.4.6 | B36: Разборка выравнивающих стяжек цементно-песчаных на кровле | C36: м3 | D36: KRO | E36: =INDEX('Нормо-час по специальностям'!$B$6:$B$26,MATCH(D36,'Нормо-час по специальностям'!$A$6:$A$26,0)) -> Кровельщик | F36: 9.5 | G36: ГЭСНр 58 (разборка кровель) ×0,85; ЕНиР Е20-1 (разборка конструкций при ремонте) | H36: =IF(OR(F36="",F36=0),"",ROUND($G$3/F36,2)) -> 0.74 | I36: =INDEX('Нормо-час по специальностям'!$D$6:$D$26,MATCH(D36,'Нормо-час по специальностям'!$A$6:$A$26,0)) -> 800 | J36: =INDEX('Нормо-час по специальностям'!$E$6:$E$26,MATCH(D36,'Нормо-час по специальностям'!$A$6:$A$26,0)) -> 950 | K36: =IF(OR(F36="",F36=0,I36=0),"",ROUND(F36*I36,0)) -> 7600 | L36: =IF(OR(F36="",F36=0,J36=0),"",ROUND(F36*J36,0)) -> 9025 | M36: =Расценки!L35 -> 3600 | N36: =Расценки!M35 -> 4140 | O36: =IF(OR(K36="",M36="",M36=0),"",K36/M36-1) -> 1.1111111 | P36: =IF(OR(L36="",N36="",N36=0),"",L36/N36-1) -> 1.1799517 | Q36: =IF(O36="","—",IF(O36<-$C$3,"нормо-часы",IF(O36>$C$3,"расценка","равно"))) -> расценка | R36: =IF(P36="","—",IF(P36<-$C$3,"нормо-часы",IF(P36>$C$3,"расценка","равно"))) -> расценка | S36: =IF(OR(F36="",F36=0,M36=""),"",ROUND(M36/F36,0)) -> 379 | T36: =IF(OR(F36="",F36=0,N36=""),"",ROUND(N36/F36,0)) -> 436 | U36: =Расценки!F35 -> 6000 | V36: =Расценки!G35 -> 6900 | W36: =IF(OR(K36="",U36="",U36=0),"",(U36-K36)/U36) -> -0.26666667 | X36: =IF(OR(L36="",V36="",V36=0),"",(V36-L36)/V36) -> -0.30797101 | Y36: =Расценки!H35 -> 10134 | Z36: =Расценки!I35 -> 12034 | AA36: =Расценки!J35 -> 0.689 | AB36: =Расценки!K35 -> 0.74405797 | AC36: =IF(OR(K36="",Y36="",Y36=0),"",(Y36-K36)/Y36) -> 0.25004934 | AD36: =IF(OR(L36="",Z36="",Z36=0),"",(Z36-L36)/Z36) -> 0.25004155 | AE36: =IF(OR(Y36="",Y36=0),"",(Y36-M36)/Y36) -> 0.64476021 | AF36: =IF(OR(Z36="",Z36=0),"",(Z36-N36)/Z36) -> 0.65597474 | AG36: =IF(OR(K36="",Y36=""),"",Y36-K36) -> 2534 | AH36: =IF(OR(L36="",Z36=""),"",Z36-L36) -> 3009
A37: 1.4.7 | B37: Разборка монолитных перекрытий бетонных | C37: м3 | D37: RAZ | E37: =INDEX('Нормо-час по специальностям'!$B$6:$B$26,MATCH(D37,'Нормо-час по специальностям'!$A$6:$A$26,0)) -> Разнорабочий / демонтажник | F37: 13 | G37: ГЭСНр 46-04 (разборка конструкций) ×0,85 | H37: =IF(OR(F37="",F37=0),"",ROUND($G$3/F37,2)) -> 0.54 | I37: =INDEX('Нормо-час по специальностям'!$D$6:$D$26,MATCH(D37,'Нормо-час по специальностям'!$A$6:$A$26,0)) -> 550 | J37: =INDEX('Нормо-час по специальностям'!$E$6:$E$26,MATCH(D37,'Нормо-час по специальностям'!$A$6:$A$26,0)) -> 660 | K37: =IF(OR(F37="",F37=0,I37=0),"",ROUND(F37*I37,0)) -> 7150 | L37: =IF(OR(F37="",F37=0,J37=0),"",ROUND(F37*J37,0)) -> 8580 | M37: =Расценки!L36 -> 5100 | N37: =Расценки!M36 -> 5865 | O37: =IF(OR(K37="",M37="",M37=0),"",K37/M37-1) -> 0.40196078 | P37: =IF(OR(L37="",N37="",N37=0),"",L37/N37-1) -> 0.4629156 | Q37: =IF(O37="","—",IF(O37<-$C$3,"нормо-часы",IF(O37>$C$3,"расценка","равно"))) -> расценка | R37: =IF(P37="","—",IF(P37<-$C$3,"нормо-часы",IF(P37>$C$3,"расценка","равно"))) -> расценка | S37: =IF(OR(F37="",F37=0,M37=""),"",ROUND(M37/F37,0)) -> 392 | T37: =IF(OR(F37="",F37=0,N37=""),"",ROUND(N37/F37,0)) -> 451 | U37: =Расценки!F36 -> 8500 | V37: =Расценки!G36 -> 9775 | W37: =IF(OR(K37="",U37="",U37=0),"",(U37-K37)/U37) -> 0.15882353 | X37: =IF(OR(L37="",V37="",V37=0),"",(V37-L37)/V37) -> 0.12225064 | Y37: =Расценки!H36 -> 9534 | Z37: =Расценки!I36 -> 11440 | AA37: =Расценки!J36 -> 0.12164706 | AB37: =Расценки!K36 -> 0.17033248 | AC37: =IF(OR(K37="",Y37="",Y37=0),"",(Y37-K37)/Y37) -> 0.25005244 | AD37: =IF(OR(L37="",Z37="",Z37=0),"",(Z37-L37)/Z37) -> 0.25 | AE37: =IF(OR(Y37="",Y37=0),"",(Y37-M37)/Y37) -> 0.46507237 | AF37: =IF(OR(Z37="",Z37=0),"",(Z37-N37)/Z37) -> 0.48732517 | AG37: =IF(OR(K37="",Y37=""),"",Y37-K37) -> 2384 | AH37: =IF(OR(L37="",Z37=""),"",Z37-L37) -> 2860
A38: 1.4.8 | B38: Разборка монолитных перекрытий железобетонных | C38: м3 | D38: RAZ | E38: =INDEX('Нормо-час по специальностям'!$B$6:$B$26,MATCH(D38,'Нормо-час по специальностям'!$A$6:$A$26,0)) -> Разнорабочий / демонтажник | F38: 17 | G38: ГЭСНр 46-04 (разборка конструкций) ×0,85 | H38: =IF(OR(F38="",F38=0),"",ROUND($G$3/F38,2)) -> 0.41 | I38: =INDEX('Нормо-час по специальностям'!$D$6:$D$26,MATCH(D38,'Нормо-час по специальностям'!$A$6:$A$26,0)) -> 550 | J38: =INDEX('Нормо-час по специальностям'!$E$6:$E$26,MATCH(D38,'Нормо-час по специальностям'!$A$6:$A$26,0)) -> 660 | K38: =IF(OR(F38="",F38=0,I38=0),"",ROUND(F38*I38,0)) -> 9350 | L38: =IF(OR(F38="",F38=0,J38=0),"",ROUND(F38*J38,0)) -> 11220 | M38: =Расценки!L37 -> 6600 | N38: =Расценки!M37 -> 7788 | O38: =IF(OR(K38="",M38="",M38=0),"",K38/M38-1) -> 0.41666667 | P38: =IF(OR(L38="",N38="",N38=0),"",L38/N38-1) -> 0.44067797 | Q38: =IF(O38="","—",IF(O38<-$C$3,"нормо-часы",IF(O38>$C$3,"расценка","равно"))) -> расценка | R38: =IF(P38="","—",IF(P38<-$C$3,"нормо-часы",IF(P38>$C$3,"расценка","равно"))) -> расценка | S38: =IF(OR(F38="",F38=0,M38=""),"",ROUND(M38/F38,0)) -> 388 | T38: =IF(OR(F38="",F38=0,N38=""),"",ROUND(N38/F38,0)) -> 458 | U38: =Расценки!F37 -> 11000 | V38: =Расценки!G37 -> 13200 | W38: =IF(OR(K38="",U38="",U38=0),"",(U38-K38)/U38) -> 0.15 | X38: =IF(OR(L38="",V38="",V38=0),"",(V38-L38)/V38) -> 0.15 | Y38: =Расценки!H37 -> 12467 | Z38: =Расценки!I37 -> 14960 | AA38: =Расценки!J37 -> 0.13336364 | AB38: =Расценки!K37 -> 0.13333333 | AC38: =IF(OR(K38="",Y38="",Y38=0),"",(Y38-K38)/Y38) -> 0.25002005 | AD38: =IF(OR(L38="",Z38="",Z38=0),"",(Z38-L38)/Z38) -> 0.25 | AE38: =IF(OR(Y38="",Y38=0),"",(Y38-M38)/Y38) -> 0.47060239 | AF38: =IF(OR(Z38="",Z38=0),"",(Z38-N38)/Z38) -> 0.47941176 | AG38: =IF(OR(K38="",Y38=""),"",Y38-K38) -> 3117 | AH38: =IF(OR(L38="",Z38=""),"",Z38-L38) -> 3740
A39: 1.4.9 | B39: Разборка парапетных решеток | C39: мп | D39: KRO | E39: =INDEX('Нормо-час по специальностям'!$B$6:$B$26,MATCH(D39,'Нормо-час по специальностям'!$A$6:$A$26,0)) -> Кровельщик | F39: 0.4 | G39: ГЭСНр 58 (разборка кровель) ×0,85 | H39: =IF(OR(F39="",F39=0),"",ROUND($G$3/F39,2)) -> 17.5 | I39: =INDEX('Нормо-час по специальностям'!$D$6:$D$26,MATCH(D39,'Нормо-час по специальностям'!$A$6:$A$26,0)) -> 800 | J39: =INDEX('Нормо-час по специальностям'!$E$6:$E$26,MATCH(D39,'Нормо-час по специальностям'!$A$6:$A$26,0)) -> 950 | K39: =IF(OR(F39="",F39=0,I39=0),"",ROUND(F39*I39,0)) -> 320 | L39: =IF(OR(F39="",F39=0,J39=0),"",ROUND(F39*J39,0)) -> 380 | M39: =Расценки!L38 -> 150 | N39: =Расценки!M38 -> 172 | O39: =IF(OR(K39="",M39="",M39=0),"",K39/M39-1) -> 1.1333333 | P39: =IF(OR(L39="",N39="",N39=0),"",L39/N39-1) -> 1.2093023 | Q39: =IF(O39="","—",IF(O39<-$C$3,"нормо-часы",IF(O39>$C$3,"расценка","равно"))) -> расценка | R39: =IF(P39="","—",IF(P39<-$C$3,"нормо-часы",IF(P39>$C$3,"расценка","равно"))) -> расценка | S39: =IF(OR(F39="",F39=0,M39=""),"",ROUND(M39/F39,0)) -> 375 | T39: =IF(OR(F39="",F39=0,N39=""),"",ROUND(N39/F39,0)) -> 430 | U39: =Расценки!F38 -> 250 | V39: =Расценки!G38 -> 288 | W39: =IF(OR(K39="",U39="",U39=0),"",(U39-K39)/U39) -> -0.28 | X39: =IF(OR(L39="",V39="",V39=0),"",(V39-L39)/V39) -> -0.31944444 | Y39: =Расценки!H38 -> 427 | Z39: =Расценки!I38 -> 507 | AA39: =Расценки!J38 -> 0.708 | AB39: =Расценки!K38 -> 0.76041667 | AC39: =IF(OR(K39="",Y39="",Y39=0),"",(Y39-K39)/Y39) -> 0.25058548 | AD39: =IF(OR(L39="",Z39="",Z39=0),"",(Z39-L39)/Z39) -> 0.2504931 | AE39: =IF(OR(Y39="",Y39=0),"",(Y39-M39)/Y39) -> 0.64871194 | AF39: =IF(OR(Z39="",Z39=0),"",(Z39-N39)/Z39) -> 0.66074951 | AG39: =IF(OR(K39="",Y39=""),"",Y39-K39) -> 107 | AH39: =IF(OR(L39="",Z39=""),"",Z39-L39) -> 127
A40: 1.4.10 | B40: Разборка покрытий кровель из волнистых и полуволнистых асбестоцементных листов | C40: м2 | D40: KRO | E40: =INDEX('Нормо-час по специальностям'!$B$6:$B$26,MATCH(D40,'Нормо-час по специальностям'!$A$6:$A$26,0)) -> Кровельщик | F40: 0.25 | G40: ГЭСНр 58 (разборка кровель) ×0,85 | H40: =IF(OR(F40="",F40=0),"",ROUND($G$3/F40,2)) -> 28 | I40: =INDEX('Нормо-час по специальностям'!$D$6:$D$26,MATCH(D40,'Нормо-час по специальностям'!$A$6:$A$26,0)) -> 800 | J40: =INDEX('Нормо-час по специальностям'!$E$6:$E$26,MATCH(D40,'Нормо-час по специальностям'!$A$6:$A$26,0)) -> 950 | K40: =IF(OR(F40="",F40=0,I40=0),"",ROUND(F40*I40,0)) -> 200 | L40: =IF(OR(F40="",F40=0,J40=0),"",ROUND(F40*J40,0)) -> 238 | M40: =Расценки!L39 -> 130 | N40: =Расценки!M39 -> 150 | O40: =IF(OR(K40="",M40="",M40=0),"",K40/M40-1) -> 0.53846154 | P40: =IF(OR(L40="",N40="",N40=0),"",L40/N40-1) -> 0.58666667 | Q40: =IF(O40="","—",IF(O40<-$C$3,"нормо-часы",IF(O40>$C$3,"расценка","равно"))) -> расценка | R40: =IF(P40="","—",IF(P40<-$C$3,"нормо-часы",IF(P40>$C$3,"расценка","равно"))) -> расценка | S40: =IF(OR(F40="",F40=0,M40=""),"",ROUND(M40/F40,0)) -> 520 | T40: =IF(OR(F40="",F40=0,N40=""),"",ROUND(N40/F40,0)) -> 600 | U40: =Расценки!F39 -> 220 | V40: =Расценки!G39 -> 253 | W40: =IF(OR(K40="",U40="",U40=0),"",(U40-K40)/U40) -> 0.090909091 | X40: =IF(OR(L40="",V40="",V40=0),"",(V40-L40)/V40) -> 0.059288538 | Y40: =Расценки!H39 -> 267 | Z40: =Расценки!I39 -> 318 | AA40: =Расценки!J39 -> 0.21363636 | AB40: =Расценки!K39 -> 0.256917 | AC40: =IF(OR(K40="",Y40="",Y40=0),"",(Y40-K40)/Y40) -> 0.25093633 | AD40: =IF(OR(L40="",Z40="",Z40=0),"",(Z40-L40)/Z40) -> 0.25157233 | AE40: =IF(OR(Y40="",Y40=0),"",(Y40-M40)/Y40) -> 0.51310861 | AF40: =IF(OR(Z40="",Z40=0),"",(Z40-N40)/Z40) -> 0.52830189 | AG40: =IF(OR(K40="",Y40=""),"",Y40-K40) -> 67 | AH40: =IF(OR(L40="",Z40=""),"",Z40-L40) -> 80
A41: 1.4.11 | B41: Разборка покрытий кровель из листовой стали | C41: м2 | D41: KRO | E41: =INDEX('Нормо-час по специальностям'!$B$6:$B$26,MATCH(D41,'Нормо-час по специальностям'!$A$6:$A$26,0)) -> Кровельщик | F41: 0.18 | G41: ГЭСНр 58 (разборка кровель) ×0,85 | H41: =IF(OR(F41="",F41=0),"",ROUND($G$3/F41,2)) -> 38.89 | I41: =INDEX('Нормо-час по специальностям'!$D$6:$D$26,MATCH(D41,'Нормо-час по специальностям'!$A$6:$A$26,0)) -> 800 | J41: =INDEX('Нормо-час по специальностям'!$E$6:$E$26,MATCH(D41,'Нормо-час по специальностям'!$A$6:$A$26,0)) -> 950 | K41: =IF(OR(F41="",F41=0,I41=0),"",ROUND(F41*I41,0)) -> 144 | L41: =IF(OR(F41="",F41=0,J41=0),"",ROUND(F41*J41,0)) -> 171 | M41: =Расценки!L40 -> 90 | N41: =Расценки!M40 -> 103 | O41: =IF(OR(K41="",M41="",M41=0),"",K41/M41-1) -> 0.6 | P41: =IF(OR(L41="",N41="",N41=0),"",L41/N41-1) -> 0.66019417 | Q41: =IF(O41="","—",IF(O41<-$C$3,"нормо-часы",IF(O41>$C$3,"расценка","равно"))) -> расценка | R41: =IF(P41="","—",IF(P41<-$C$3,"нормо-часы",IF(P41>$C$3,"расценка","равно"))) -> расценка | S41: =IF(OR(F41="",F41=0,M41=""),"",ROUND(M41/F41,0)) -> 500 | T41: =IF(OR(F41="",F41=0,N41=""),"",ROUND(N41/F41,0)) -> 572 | U41: =Расценки!F40 -> 150 | V41: =Расценки!G40 -> 172 | W41: =IF(OR(K41="",U41="",U41=0),"",(U41-K41)/U41) -> 0.04 | X41: =IF(OR(L41="",V41="",V41=0),"",(V41-L41)/V41) -> 0.0058139535 | Y41: =Расценки!H40 -> 192 | Z41: =Расценки!I40 -> 228 | AA41: =Расценки!J40 -> 0.28 | AB41: =Расценки!K40 -> 0.3255814 | AC41: =IF(OR(K41="",Y41="",Y41=0),"",(Y41-K41)/Y41) -> 0.25 | AD41: =IF(OR(L41="",Z41="",Z41=0),"",(Z41-L41)/Z41) -> 0.25 | AE41: =IF(OR(Y41="",Y41=0),"",(Y41-M41)/Y41) -> 0.53125 | AF41: =IF(OR(Z41="",Z41=0),"",(Z41-N41)/Z41) -> 0.54824561 | AG41: =IF(OR(K41="",Y41=""),"",Y41-K41) -> 48 | AH41: =IF(OR(L41="",Z41=""),"",Z41-L41) -> 57
A42: 1.4.12 | B42: Разборка покрытий кровель из рулонных материалов (добавляется на каждый последующий слой сверх 4х слоев) | C42: м2 | D42: KRO | E42: =INDEX('Нормо-час по специальностям'!$B$6:$B$26,MATCH(D42,'Нормо-час по специальностям'!$A$6:$A$26,0)) -> Кровельщик | F42: 0.05 | G42: ГЭСНр 58 (разборка кровель) ×0,85 | H42: =IF(OR(F42="",F42=0),"",ROUND($G$3/F42,2)) -> 140 | I42: =INDEX('Нормо-час по специальностям'!$D$6:$D$26,MATCH(D42,'Нормо-час по специальностям'!$A$6:$A$26,0)) -> 800 | J42: =INDEX('Нормо-час по специальностям'!$E$6:$E$26,MATCH(D42,'Нормо-час по специальностям'!$A$6:$A$26,0)) -> 950 | K42: =IF(OR(F42="",F42=0,I42=0),"",ROUND(F42*I42,0)) -> 40 | L42: =IF(OR(F42="",F42=0,J42=0),"",ROUND(F42*J42,0)) -> 48 | M42: =Расценки!L41 -> 25 | N42: =Расценки!M41 -> 28.5 | O42: =IF(OR(K42="",M42="",M42=0),"",K42/M42-1) -> 0.6 | P42: =IF(OR(L42="",N42="",N42=0),"",L42/N42-1) -> 0.68421053 | Q42: =IF(O42="","—",IF(O42<-$C$3,"нормо-часы",IF(O42>$C$3,"расценка","равно"))) -> расценка | R42: =IF(P42="","—",IF(P42<-$C$3,"нормо-часы",IF(P42>$C$3,"расценка","равно"))) -> расценка | S42: =IF(OR(F42="",F42=0,M42=""),"",ROUND(M42/F42,0)) -> 500 | T42: =IF(OR(F42="",F42=0,N42=""),"",ROUND(N42/F42,0)) -> 570 | U42: =Расценки!F41 -> 40 | V42: =Расценки!G41 -> 46 | W42: =IF(OR(K42="",U42="",U42=0),"",(U42-K42)/U42) -> 0 | X42: =IF(OR(L42="",V42="",V42=0),"",(V42-L42)/V42) -> -0.043478261 | Y42: =Расценки!H41 -> 54 | Z42: =Расценки!I41 -> 64 | AA42: =Расценки!J41 -> 0.35 | AB42: =Расценки!K41 -> 0.39130435 | AC42: =IF(OR(K42="",Y42="",Y42=0),"",(Y42-K42)/Y42) -> 0.25925926 | AD42: =IF(OR(L42="",Z42="",Z42=0),"",(Z42-L42)/Z42) -> 0.25 | AE42: =IF(OR(Y42="",Y42=0),"",(Y42-M42)/Y42) -> 0.53703704 | AF42: =IF(OR(Z42="",Z42=0),"",(Z42-N42)/Z42) -> 0.5546875 | AG42: =IF(OR(K42="",Y42=""),"",Y42-K42) -> 14 | AH42: =IF(OR(L42="",Z42=""),"",Z42-L42) -> 16
... A50: 1.4.N5 | B50: Демонтаж зенитного фонаря / люка дымоудаления | C50: шт | D50: KRO | E50: =INDEX('Нормо-час по специальностям'!$B$6:$B$26,MATCH(D50,'Нормо-час по специальностям'!$A$6:$A$26,0)) -> Кровельщик | F50: 4 | G50: ГЭСНр 58 (разборка кровель) ×0,85 | H50: =IF(OR(F50="",F50=0),"",ROUND($G$3/F50,2)) -> 1.75 | I50: =INDEX('Нормо-час по специальностям'!$D$6:$D$26,MATCH(D50,'Нормо-час по специальностям'!$A$6:$A$26,0)) -> 800 | J50: =INDEX('Нормо-час по специальностям'!$E$6:$E$26,MATCH(D50,'Нормо-час по специальностям'!$A$6:$A$26,0)) -> 950 | K50: =IF(OR(F50="",F50=0,I50=0),"",ROUND(F50*I50,0)) -> 3200 | L50: =IF(OR(F50="",F50=0,J50=0),"",ROUND(F50*J50,0)) -> 3800 | M50: =Расценки!L49 -> 3600 | N50: =Расценки!M49 -> 4140 | O50: =IF(OR(K50="",M50="",M50=0),"",K50/M50-1) -> -0.11111111 | P50: =IF(OR(L50="",N50="",N50=0),"",L50/N50-1) -> -0.082125604 | Q50: =IF(O50="","—",IF(O50<-$C$3,"нормо-часы",IF(O50>$C$3,"расценка","равно"))) -> нормо-часы | R50: =IF(P50="","—",IF(P50<-$C$3,"нормо-часы",IF(P50>$C$3,"расценка","равно"))) -> равно | S50: =IF(OR(F50="",F50=0,M50=""),"",ROUND(M50/F50,0)) -> 900 | T50: =IF(OR(F50="",F50=0,N50=""),"",ROUND(N50/F50,0)) -> 1035 | U50: =Расценки!F49 -> 6000 | V50: =Расценки!G49 -> 6900 | W50: =IF(OR(K50="",U50="",U50=0),"",(U50-K50)/U50) -> 0.46666667 | X50: =IF(OR(L50="",V50="",V50=0),"",(V50-L50)/V50) -> 0.44927536 | Y50: =Расценки!H49 -> 6000 | Z50: =Расценки!I49 -> 6900 | AA50: =Расценки!J49 -> 0 | AB50: =Расценки!K49 -> 0 | AC50: =IF(OR(K50="",Y50="",Y50=0),"",(Y50-K50)/Y50) -> 0.46666667 | AD50: =IF(OR(L50="",Z50="",Z50=0),"",(Z50-L50)/Z50) -> 0.44927536 | AE50: =IF(OR(Y50="",Y50=0),"",(Y50-M50)/Y50) -> 0.4 | AF50: =IF(OR(Z50="",Z50=0),"",(Z50-N50)/Z50) -> 0.4 | AG50: =IF(OR(K50="",Y50=""),"",Y50-K50) -> 2800 | AH50: =IF(OR(L50="",Z50=""),"",Z50-L50) -> 3100
A51: 1.5 Демонтажные работы в здании
A52: 1.5.1 | B52: Демонтаж металлических балок, ригелей перекрытия, покрытия | C52: тн | D52: SVA | E52: =INDEX('Нормо-час по специальностям'!$B$6:$B$26,MATCH(D52,'Нормо-час по специальностям'!$A$6:$A$26,0)) -> Сварщик / монтажник МК | F52: 20 | G52: ЕНиР Е5 (демонтаж МК ≈0,6–0,7 от монтажа) | H52: =IF(OR(F52="",F52=0),"",ROUND($G$3/F52,2)) -> 0.35 | I52: =INDEX('Нормо-час по специальностям'!$D$6:$D$26,MATCH(D52,'Нормо-час по специальностям'!$A$6:$A$26,0)) -> 900 | J52: =INDEX('Нормо-час по специальностям'!$E$6:$E$26,MATCH(D52,'Нормо-час по специальностям'!$A$6:$A$26,0)) -> 1080 | K52: =IF(OR(F52="",F52=0,I52=0),"",ROUND(F52*I52,0)) -> 18000 | L52: =IF(OR(F52="",F52=0,J52=0),"",ROUND(F52*J52,0)) -> 21600 | M52: =Расценки!L51 -> 7200 | N52: =Расценки!M51 -> 8280 | O52: =IF(OR(K52="",M52="",M52=0),"",K52/M52-1) -> 1.5 | P52: =IF(OR(L52="",N52="",N52=0),"",L52/N52-1) -> 1.6086957 | Q52: =IF(O52="","—",IF(O52<-$C$3,"нормо-часы",IF(O52>$C$3,"расценка","равно"))) -> расценка | R52: =IF(P52="","—",IF(P52<-$C$3,"нормо-часы",IF(P52>$C$3,"расценка","равно"))) -> расценка | S52: =IF(OR(F52="",F52=0,M52=""),"",ROUND(M52/F52,0)) -> 360 | T52: =IF(OR(F52="",F52=0,N52=""),"",ROUND(N52/F52,0)) -> 414 | U52: =Расценки!F51 -> 12000 | V52: =Расценки!G51 -> 13800 | W52: =IF(OR(K52="",U52="",U52=0),"",(U52-K52)/U52) -> -0.5 | X52: =IF(OR(L52="",V52="",V52=0),"",(V52-L52)/V52) -> -0.56521739 | Y52: =Расценки!H51 -> 24000 | Z52: =Расценки!I51 -> 28800 | AA52: =Расценки!J51 -> 1 | AB52: =Расценки!K51 -> 1.0869565 | AC52: =IF(OR(K52="",Y52="",Y52=0),"",(Y52-K52)/Y52) -> 0.25 | AD52: =IF(OR(L52="",Z52="",Z52=0),"",(Z52-L52)/Z52) -> 0.25 | AE52: =IF(OR(Y52="",Y52=0),"",(Y52-M52)/Y52) -> 0.7 | AF52: =IF(OR(Z52="",Z52=0),"",(Z52-N52)/Z52) -> 0.7125 | AG52: =IF(OR(K52="",Y52=""),"",Y52-K52) -> 6000 | AH52: =IF(OR(L52="",Z52=""),"",Z52-L52) -> 7200
A53: 1.5.2 | B53: Демонтаж железобетонных конструкций. При объеме более 1 м3 - при помощи отбойных молотков | C53: м3 | D53: RAZ | E53: =INDEX('Нормо-час по специальностям'!$B$6:$B$26,MATCH(D53,'Нормо-час по специальностям'!$A$6:$A$26,0)) -> Разнорабочий / демонтажник | F53: 17 | G53: ГЭСНр 46-04 (разборка конструкций) ×0,85 | H53: =IF(OR(F53="",F53=0),"",ROUND($G$3/F53,2)) -> 0.41 | I53: =INDEX('Нормо-час по специальностям'!$D$6:$D$26,MATCH(D53,'Нормо-час по специальностям'!$A$6:$A$26,0)) -> 550 | J53: =INDEX('Нормо-час по специальностям'!$E$6:$E$26,MATCH(D53,'Нормо-час по специальностям'!$A$6:$A$26,0)) -> 660 | K53: =IF(OR(F53="",F53=0,I53=0),"",ROUND(F53*I53,0)) -> 9350 | L53: =IF(OR(F53="",F53=0,J53=0),"",ROUND(F53*J53,0)) -> 11220 | M53: =Расценки!L52 -> 6600 | N53: =Расценки!M52 -> 7788 | O53: =IF(OR(K53="",M53="",M53=0),"",K53/M53-1) -> 0.41666667 | P53: =IF(OR(L53="",N53="",N53=0),"",L53/N53-1) -> 0.44067797 | Q53: =IF(O53="","—",IF(O53<-$C$3,"нормо-часы",IF(O53>$C$3,"расценка","равно"))) -> расценка | R53: =IF(P53="","—",IF(P53<-$C$3,"нормо-часы",IF(P53>$C$3,"расценка","равно"))) -> расценка | S53: =IF(OR(F53="",F53=0,M53=""),"",ROUND(M53/F53,0)) -> 388 | T53: =IF(OR(F53="",F53=0,N53=""),"",ROUND(N53/F53,0)) -> 458 | U53: =Расценки!F52 -> 11000 | V53: =Расценки!G52 -> 13200 | W53: =IF(OR(K53="",U53="",U53=0),"",(U53-K53)/U53) -> 0.15 | X53: =IF(OR(L53="",V53="",V53=0),"",(V53-L53)/V53) -> 0.15 | Y53: =Расценки!H52 -> 12467 | Z53: =Расценки!I52 -> 14960 | AA53: =Расценки!J52 -> 0.13336364 | AB53: =Расценки!K52 -> 0.13333333 | AC53: =IF(OR(K53="",Y53="",Y53=0),"",(Y53-K53)/Y53) -> 0.25002005 | AD53: =IF(OR(L53="",Z53="",Z53=0),"",(Z53-L53)/Z53) -> 0.25 | AE53: =IF(OR(Y53="",Y53=0),"",(Y53-M53)/Y53) -> 0.47060239 | AF53: =IF(OR(Z53="",Z53=0),"",(Z53-N53)/Z53) -> 0.47941176 | AG53: =IF(OR(K53="",Y53=""),"",Y53-K53) -> 3117 | AH53: =IF(OR(L53="",Z53=""),"",Z53-L53) -> 3740
A54: 1.5.3 | B54: Демонтаж бетонных конструкций | C54: м3 | D54: RAZ | E54: =INDEX('Нормо-час по специальностям'!$B$6:$B$26,MATCH(D54,'Нормо-час по специальностям'!$A$6:$A$26,0)) -> Разнорабочий / демонтажник | F54: 13 | G54: ГЭСНр 46-04 (разборка конструкций) ×0,85 | H54: =IF(OR(F54="",F54=0),"",ROUND($G$3/F54,2)) -> 0.54 | I54: =INDEX('Нормо-час по специальностям'!$D$6:$D$26,MATCH(D54,'Нормо-час по специальностям'!$A$6:$A$26,0)) -> 550 | J54: =INDEX('Нормо-час по специальностям'!$E$6:$E$26,MATCH(D54,'Нормо-час по специальностям'!$A$6:$A$26,0)) -> 660 | K54: =IF(OR(F54="",F54=0,I54=0),"",ROUND(F54*I54,0)) -> 7150 | L54: =IF(OR(F54="",F54=0,J54=0),"",ROUND(F54*J54,0)) -> 8580 | M54: =Расценки!L53 -> 5100 | N54: =Расценки!M53 -> 6018 | O54: =IF(OR(K54="",M54="",M54=0),"",K54/M54-1) -> 0.40196078 | P54: =IF(OR(L54="",N54="",N54=0),"",L54/N54-1) -> 0.42572283 | Q54: =IF(O54="","—",IF(O54<-$C$3,"нормо-часы",IF(O54>$C$3,"расценка","равно"))) -> расценка | R54: =IF(P54="","—",IF(P54<-$C$3,"нормо-часы",IF(P54>$C$3,"расценка","равно"))) -> расценка | S54: =IF(OR(F54="",F54=0,M54=""),"",ROUND(M54/F54,0)) -> 392 | T54: =IF(OR(F54="",F54=0,N54=""),"",ROUND(N54/F54,0)) -> 463 | U54: =Расценки!F53 -> 8500 | V54: =Расценки!G53 -> 10200 | W54: =IF(OR(K54="",U54="",U54=0),"",(U54-K54)/U54) -> 0.15882353 | X54: =IF(OR(L54="",V54="",V54=0),"",(V54-L54)/V54) -> 0.15882353 | Y54: =Расценки!H53 -> 9534 | Z54: =Расценки!I53 -> 11440 | AA54: =Расценки!J53 -> 0.12164706 | AB54: =Расценки!K53 -> 0.12156863 | AC54: =IF(OR(K54="",Y54="",Y54=0),"",(Y54-K54)/Y54) -> 0.25005244 | AD54: =IF(OR(L54="",Z54="",Z54=0),"",(Z54-L54)/Z54) -> 0.25 | AE54: =IF(OR(Y54="",Y54=0),"",(Y54-M54)/Y54) -> 0.46507237 | AF54: =IF(OR(Z54="",Z54=0),"",(Z54-N54)/Z54) -> 0.47395105 | AG54: =IF(OR(K54="",Y54=""),"",Y54-K54) -> 2384 | AH54: =IF(OR(L54="",Z54=""),"",Z54-L54) -> 2860
A55: 1.5.4 | B55: Демонтаж металлоконструкций | C55: тн | D55: SVA | E55: =INDEX('Нормо-час по специальностям'!$B$6:$B$26,MATCH(D55,'Нормо-час по специальностям'!$A$6:$A$26,0)) -> Сварщик / монтажник МК | F55: 12 | G55: ЕНиР Е5 (демонтаж МК ≈0,6–0,7 от монтажа) | H55: =IF(OR(F55="",F55=0),"",ROUND($G$3/F55,2)) -> 0.58 | I55: =INDEX('Нормо-час по специальностям'!$D$6:$D$26,MATCH(D55,'Нормо-час по специальностям'!$A$6:$A$26,0)) -> 900 | J55: =INDEX('Нормо-час по специальностям'!$E$6:$E$26,MATCH(D55,'Нормо-час по специальностям'!$A$6:$A$26,0)) -> 1080 | K55: =IF(OR(F55="",F55=0,I55=0),"",ROUND(F55*I55,0)) -> 10800 | L55: =IF(OR(F55="",F55=0,J55=0),"",ROUND(F55*J55,0)) -> 12960 | M55: =Расценки!L54 -> 4500 | N55: =Расценки!M54 -> 5175 | O55: =IF(OR(K55="",M55="",M55=0),"",K55/M55-1) -> 1.4 | P55: =IF(OR(L55="",N55="",N55=0),"",L55/N55-1) -> 1.5043478 | Q55: =IF(O55="","—",IF(O55<-$C$3,"нормо-часы",IF(O55>$C$3,"расценка","равно"))) -> расценка | R55: =IF(P55="","—",IF(P55<-$C$3,"нормо-часы",IF(P55>$C$3,"расценка","равно"))) -> расценка | S55: =IF(OR(F55="",F55=0,M55=""),"",ROUND(M55/F55,0)) -> 375 | T55: =IF(OR(F55="",F55=0,N55=""),"",ROUND(N55/F55,0)) -> 431 | U55: =Расценки!F54 -> 7500 | V55: =Расценки!G54 -> 8625 | W55: =IF(OR(K55="",U55="",U55=0),"",(U55-K55)/U55) -> -0.44 | X55: =IF(OR(L55="",V55="",V55=0),"",(V55-L55)/V55) -> -0.5026087 | Y55: =Расценки!H54 -> 14400 | Z55: =Расценки!I54 -> 17280 | AA55: =Расценки!J54 -> 0.92 | AB55: =Расценки!K54 -> 1.0034783 | AC55: =IF(OR(K55="",Y55="",Y55=0),"",(Y55-K55)/Y55) -> 0.25 | AD55: =IF(OR(L55="",Z55="",Z55=0),"",(Z55-L55)/Z55) -> 0.25 | AE55: =IF(OR(Y55="",Y55=0),"",(Y55-M55)/Y55) -> 0.6875 | AF55: =IF(OR(Z55="",Z55=0),"",(Z55-N55)/Z55) -> 0.70052083 | AG55: =IF(OR(K55="",Y55=""),"",Y55-K55) -> 3600 | AH55: =IF(OR(L55="",Z55=""),"",Z55-L55) -> 4320
A56: 1.5.5 | B56: Алмазная резка железобетонных конструкций глубиной 230 мм | C56: м реза | D56: BET | E56: =INDEX('Нормо-час по специальностям'!$B$6:$B$26,MATCH(D56,'Нормо-час по специальностям'!$A$6:$A$26,0)) -> Бетонщик / арматурщик | F56: 1 | G56: паспорт стенорезной машины (выработка 1–1,5 м/ч при 230 мм, звено 2 чел.) | H56: =IF(OR(F56="",F56=0),"",ROUND($G$3/F56,2)) -> 7 | I56: =INDEX('Нормо-час по специальностям'!$D$6:$D$26,MATCH(D56,'Нормо-час по специальностям'!$A$6:$A$26,0)) -> 800 | J56: =INDEX('Нормо-час по специальностям'!$E$6:$E$26,MATCH(D56,'Нормо-час по специальностям'!$A$6:$A$26,0)) -> 950 | K56: =IF(OR(F56="",F56=0,I56=0),"",ROUND(F56*I56,0)) -> 800 | L56: =IF(OR(F56="",F56=0,J56=0),"",ROUND(F56*J56,0)) -> 950 | M56: =Расценки!L55 -> 1200 | N56: =Расценки!M55 -> 1380 | O56: =IF(OR(K56="",M56="",M56=0),"",K56/M56-1) -> -0.33333333 | P56: =IF(OR(L56="",N56="",N56=0),"",L56/N56-1) -> -0.3115942 | Q56: =IF(O56="","—",IF(O56<-$C$3,"нормо-часы",IF(O56>$C$3,"расценка","равно"))) -> нормо-часы | R56: =IF(P56="","—",IF(P56<-$C$3,"нормо-часы",IF(P56>$C$3,"расценка","равно"))) -> нормо-часы | S56: =IF(OR(F56="",F56=0,M56=""),"",ROUND(M56/F56,0)) -> 1200 | T56: =IF(OR(F56="",F56=0,N56=""),"",ROUND(N56/F56,0)) -> 1380 | U56: =Расценки!F55 -> 2000 | V56: =Расценки!G55 -> 2300 | W56: =IF(OR(K56="",U56="",U56=0),"",(U56-K56)/U56) -> 0.6 | X56: =IF(OR(L56="",V56="",V56=0),"",(V56-L56)/V56) -> 0.58695652 | Y56: =Расценки!H55 -> 2000 | Z56: =Расценки!I55 -> 2300 | AA56: =Расценки!J55 -> 0 | AB56: =Расценки!K55 -> 0 | AC56: =IF(OR(K56="",Y56="",Y56=0),"",(Y56-K56)/Y56) -> 0.6 | AD56: =IF(OR(L56="",Z56="",Z56=0),"",(Z56-L56)/Z56) -> 0.58695652 | AE56: =IF(OR(Y56="",Y56=0),"",(Y56-M56)/Y56) -> 0.4 | AF56: =IF(OR(Z56="",Z56=0),"",(Z56-N56)/Z56) -> 0.4 | AG56: =IF(OR(K56="",Y56=""),"",Y56-K56) -> 1200 | AH56: =IF(OR(L56="",Z56=""),"",Z56-L56) -> 1350
A57: 1.5.6 | B57: На каждые 100 мм увеличения глубины реза добавлять к расценке по алмазной резке ж/б конструкций | C57: м реза | D57: BET | E57: =INDEX('Нормо-час по специальностям'!$B$6:$B$26,MATCH(D57,'Нормо-час по специальностям'!$A$6:$A$26,0)) -> Бетонщик / арматурщик | F57: 0.4 | G57: паспорт стенорезной машины | H57: =IF(OR(F57="",F57=0),"",ROUND($G$3/F57,2)) -> 17.5 | I57: =INDEX('Нормо-час по специальностям'!$D$6:$D$26,MATCH(D57,'Нормо-час по специальностям'!$A$6:$A$26,0)) -> 800 | J57: =INDEX('Нормо-час по специальностям'!$E$6:$E$26,MATCH(D57,'Нормо-час по специальностям'!$A$6:$A$26,0)) -> 950 | K57: =IF(OR(F57="",F57=0,I57=0),"",ROUND(F57*I57,0)) -> 320 | L57: =IF(OR(F57="",F57=0,J57=0),"",ROUND(F57*J57,0)) -> 380 | M57: =Расценки!L56 -> 480 | N57: =Расценки!M56 -> 552 | O57: =IF(OR(K57="",M57="",M57=0),"",K57/M57-1) -> -0.33333333 | P57: =IF(OR(L57="",N57="",N57=0),"",L57/N57-1) -> -0.3115942 | Q57: =IF(O57="","—",IF(O57<-$C$3,"нормо-часы",IF(O57>$C$3,"расценка","равно"))) -> нормо-часы | R57: =IF(P57="","—",IF(P57<-$C$3,"нормо-часы",IF(P57>$C$3,"расценка","равно"))) -> нормо-часы | S57: =IF(OR(F57="",F57=0,M57=""),"",ROUND(M57/F57,0)) -> 1200 | T57: =IF(OR(F57="",F57=0,N57=""),"",ROUND(N57/F57,0)) -> 1380 | U57: =Расценки!F56 -> 800 | V57: =Расценки!G56 -> 920 | W57: =IF(OR(K57="",U57="",U57=0),"",(U57-K57)/U57) -> 0.6 | X57: =IF(OR(L57="",V57="",V57=0),"",(V57-L57)/V57) -> 0.58695652 | Y57: =Расценки!H56 -> 800 | Z57: =Расценки!I56 -> 920 | AA57: =Расценки!J56 -> 0 | AB57: =Расценки!K56 -> 0 | AC57: =IF(OR(K57="",Y57="",Y57=0),"",(Y57-K57)/Y57) -> 0.6 | AD57: =IF(OR(L57="",Z57="",Z57=0),"",(Z57-L57)/Z57) -> 0.58695652 | AE57: =IF(OR(Y57="",Y57=0),"",(Y57-M57)/Y57) -> 0.4 | AF57: =IF(OR(Z57="",Z57=0),"",(Z57-N57)/Z57) -> 0.4 | AG57: =IF(OR(K57="",Y57=""),"",Y57-K57) -> 480 | AH57: =IF(OR(L57="",Z57=""),"",Z57-L57) -> 540
A58: 1.5.N1 | B58: Алмазное бурение отверстия в ж/б Ø до 100 мм глубиной до 200 мм | C58: шт | D58: BET | E58: =INDEX('Нормо-час по специальностям'!$B$6:$B$26,MATCH(D58,'Нормо-час по специальностям'!$A$6:$A$26,0)) -> Бетонщик / арматурщик | F58: 0.6 | G58: паспорт установки алмазного бурения | H58: =IF(OR(F58="",F58=0),"",ROUND($G$3/F58,2)) -> 11.67 | I58: =INDEX('Нормо-час по специальностям'!$D$6:$D$26,MATCH(D58,'Нормо-час по специальностям'!$A$6:$A$26,0)) -> 800 | J58: =INDEX('Нормо-час по специальностям'!$E$6:$E$26,MATCH(D58,'Нормо-час по специальностям'!$A$6:$A$26,0)) -> 950 | K58: =IF(OR(F58="",F58=0,I58=0),"",ROUND(F58*I58,0)) -> 480 | L58: =IF(OR(F58="",F58=0,J58=0),"",ROUND(F58*J58,0)) -> 570 | M58: =Расценки!L57 -> 720 | N58: =Расценки!M57 -> 828 | O58: =IF(OR(K58="",M58="",M58=0),"",K58/M58-1) -> -0.33333333 | P58: =IF(OR(L58="",N58="",N58=0),"",L58/N58-1) -> -0.3115942 | Q58: =IF(O58="","—",IF(O58<-$C$3,"нормо-часы",IF(O58>$C$3,"расценка","равно"))) -> нормо-часы | R58: =IF(P58="","—",IF(P58<-$C$3,"нормо-часы",IF(P58>$C$3,"расценка","равно"))) -> нормо-часы | S58: =IF(OR(F58="",F58=0,M58=""),"",ROUND(M58/F58,0)) -> 1200 | T58: =IF(OR(F58="",F58=0,N58=""),"",ROUND(N58/F58,0)) -> 1380 | U58: =Расценки!F57 -> 1200 | V58: =Расценки!G57 -> 1380 | W58: =IF(OR(K58="",U58="",U58=0),"",(U58-K58)/U58) -> 0.6 | X58: =IF(OR(L58="",V58="",V58=0),"",(V58-L58)/V58) -> 0.58695652 | Y58: =Расценки!H57 -> 1200 | Z58: =Расценки!I57 -> 1380 | AA58: =Расценки!J57 -> 0 | AB58: =Расценки!K57 -> 0 | AC58: =IF(OR(K58="",Y58="",Y58=0),"",(Y58-K58)/Y58) -> 0.6 | AD58: =IF(OR(L58="",Z58="",Z58=0),"",(Z58-L58)/Z58) -> 0.58695652 | AE58: =IF(OR(Y58="",Y58=0),"",(Y58-M58)/Y58) -> 0.4 | AF58: =IF(OR(Z58="",Z58=0),"",(Z58-N58)/Z58) -> 0.4 | AG58: =IF(OR(K58="",Y58=""),"",Y58-K58) -> 720 | AH58: =IF(OR(L58="",Z58=""),"",Z58-L58) -> 810
A59: 1.5.N2 | B59: Демонтаж металлических лестниц, площадок, антресолей | C59: т | D59: SVA | E59: =INDEX('Нормо-час по специальностям'!$B$6:$B$26,MATCH(D59,'Нормо-час по специальностям'!$A$6:$A$26,0)) -> Сварщик / монтажник МК | F59: 18 | G59: ЕНиР Е5 (демонтаж МК ≈0,6–0,7 от монтажа) | H59: =IF(OR(F59="",F59=0),"",ROUND($G$3/F59,2)) -> 0.39 | I59: =INDEX('Нормо-час по специальностям'!$D$6:$D$26,MATCH(D59,'Нормо-час по специальностям'!$A$6:$A$26,0)) -> 900 | J59: =INDEX('Нормо-час по специальностям'!$E$6:$E$26,MATCH(D59,'Нормо-час по специальностям'!$A$6:$A$26,0)) -> 1080 | K59: =IF(OR(F59="",F59=0,I59=0),"",ROUND(F59*I59,0)) -> 16200 | L59: =IF(OR(F59="",F59=0,J59=0),"",ROUND(F59*J59,0)) -> 19440 | M59: =Расценки!L58 -> 7200 | N59: =Расценки!M58 -> 8280 | O59: =IF(OR(K59="",M59="",M59=0),"",K59/M59-1) -> 1.25 | P59: =IF(OR(L59="",N59="",N59=0),"",L59/N59-1) -> 1.3478261 | Q59: =IF(O59="","—",IF(O59<-$C$3,"нормо-часы",IF(O59>$C$3,"расценка","равно"))) -> расценка | R59: =IF(P59="","—",IF(P59<-$C$3,"нормо-часы",IF(P59>$C$3,"расценка","равно"))) -> расценка | S59: =IF(OR(F59="",F59=0,M59=""),"",ROUND(M59/F59,0)) -> 400 | T59: =IF(OR(F59="",F59=0,N59=""),"",ROUND(N59/F59,0)) -> 460 | U59: =Расценки!F58 -> 12000 | V59: =Расценки!G58 -> 13800 | W59: =IF(OR(K59="",U59="",U59=0),"",(U59-K59)/U59) -> -0.35 | X59: =IF(OR(L59="",V59="",V59=0),"",(V59-L59)/V59) -> -0.40869565 | Y59: =Расценки!H58 -> 21600 | Z59: =Расценки!I58 -> 25920 | AA59: =Расценки!J58 -> 0.8 | AB59: =Расценки!K58 -> 0.87826087 | AC59: =IF(OR(K59="",Y59="",Y59=0),"",(Y59-K59)/Y59) -> 0.25 | AD59: =IF(OR(L59="",Z59="",Z59=0),"",(Z59-L59)/Z59) -> 0.25 | AE59: =IF(OR(Y59="",Y59=0),"",(Y59-M59)/Y59) -> 0.66666667 | AF59: =IF(OR(Z59="",Z59=0),"",(Z59-N59)/Z59) -> 0.68055556 | AG59: =IF(OR(K59="",Y59=""),"",Y59-K59) -> 5400 | AH59: =IF(OR(L59="",Z59=""),"",Z59-L59) -> 6480
A60: 1.6 Демонтажные работы полов
A61: 1.6.1 | B61: Демонтаж стяжек полов до основания | C61: м3 | D61: RAZ | E61: =INDEX('Нормо-час по специальностям'!$B$6:$B$26,MATCH(D61,'Нормо-час по специальностям'!$A$6:$A$26,0)) -> Разнорабочий / демонтажник | F61: 9 | G61: ГЭСНр 57-02 (разборка полов) ×0,85 | H61: =IF(OR(F61="",F61=0),"",ROUND($G$3/F61,2)) -> 0.78 | I61: =INDEX('Нормо-час по специальностям'!$D$6:$D$26,MATCH(D61,'Нормо-час по специальностям'!$A$6:$A$26,0)) -> 550 | J61: =INDEX('Нормо-час по специальностям'!$E$6:$E$26,MATCH(D61,'Нормо-час по специальностям'!$A$6:$A$26,0)) -> 660 | K61: =IF(OR(F61="",F61=0,I61=0),"",ROUND(F61*I61,0)) -> 4950 | L61: =IF(OR(F61="",F61=0,J61=0),"",ROUND(F61*J61,0)) -> 5940 | M61: =Расценки!L60 -> 3900 | N61: =Расценки!M60 -> 4485 | O61: =IF(OR(K61="",M61="",M61=0),"",K61/M61-1) -> 0.26923077 | P61: =IF(OR(L61="",N61="",N61=0),"",L61/N61-1) -> 0.32441472 | Q61: =IF(O61="","—",IF(O61<-$C$3,"нормо-часы",IF(O61>$C$3,"расценка","равно"))) -> расценка | R61: =IF(P61="","—",IF(P61<-$C$3,"нормо-часы",IF(P61>$C$3,"расценка","равно"))) -> расценка | S61: =IF(OR(F61="",F61=0,M61=""),"",ROUND(M61/F61,0)) -> 433 | T61: =IF(OR(F61="",F61=0,N61=""),"",ROUND(N61/F61,0)) -> 498 | U61: =Расценки!F60 -> 6500 | V61: =Расценки!G60 -> 7475 | W61: =IF(OR(K61="",U61="",U61=0),"",(U61-K61)/U61) -> 0.23846154 | X61: =IF(OR(L61="",V61="",V61=0),"",(V61-L61)/V61) -> 0.20535117 | Y61: =Расценки!H60 -> 6600 | Z61: =Расценки!I60 -> 7920 | AA61: =Расценки!J60 -> 0.015384615 | AB61: =Расценки!K60 -> 0.059531773 | AC61: =IF(OR(K61="",Y61="",Y61=0),"",(Y61-K61)/Y61) -> 0.25 | AD61: =IF(OR(L61="",Z61="",Z61=0),"",(Z61-L61)/Z61) -> 0.25 | AE61: =IF(OR(Y61="",Y61=0),"",(Y61-M61)/Y61) -> 0.40909091 | AF61: =IF(OR(Z61="",Z61=0),"",(Z61-N61)/Z61) -> 0.43371212 | AG61: =IF(OR(K61="",Y61=""),"",Y61-K61) -> 1650 | AH61: =IF(OR(L61="",Z61=""),"",Z61-L61) -> 1980
A62: 1.6.2 | B62: Разборка бетонных оснований под полы | C62: м3 | D62: RAZ | E62: =INDEX('Нормо-час по специальностям'!$B$6:$B$26,MATCH(D62,'Нормо-час по специальностям'!$A$6:$A$26,0)) -> Разнорабочий / демонтажник | F62: 12 | G62: ГЭСНр 57-02 (разборка полов) ×0,85 | H62: =IF(OR(F62="",F62=0),"",ROUND($G$3/F62,2)) -> 0.58 | I62: =INDEX('Нормо-час по специальностям'!$D$6:$D$26,MATCH(D62,'Нормо-час по специальностям'!$A$6:$A$26,0)) -> 550 | J62: =INDEX('Нормо-час по специальностям'!$E$6:$E$26,MATCH(D62,'Нормо-час по специальностям'!$A$6:$A$26,0)) -> 660 | K62: =IF(OR(F62="",F62=0,I62=0),"",ROUND(F62*I62,0)) -> 6600 | L62: =IF(OR(F62="",F62=0,J62=0),"",ROUND(F62*J62,0)) -> 7920 | M62: =Расценки!L61 -> 4800 | N62: =Расценки!M61 -> 5520 | O62: =IF(OR(K62="",M62="",M62=0),"",K62/M62-1) -> 0.375 | P62: =IF(OR(L62="",N62="",N62=0),"",L62/N62-1) -> 0.43478261 | Q62: =IF(O62="","—",IF(O62<-$C$3,"нормо-часы",IF(O62>$C$3,"расценка","равно"))) -> расценка | R62: =IF(P62="","—",IF(P62<-$C$3,"нормо-часы",IF(P62>$C$3,"расценка","равно"))) -> расценка | S62: =IF(OR(F62="",F62=0,M62=""),"",ROUND(M62/F62,0)) -> 400 | T62: =IF(OR(F62="",F62=0,N62=""),"",ROUND(N62/F62,0)) -> 460 | U62: =Расценки!F61 -> 8000 | V62: =Расценки!G61 -> 9200 | W62: =IF(OR(K62="",U62="",U62=0),"",(U62-K62)/U62) -> 0.175 | X62: =IF(OR(L62="",V62="",V62=0),"",(V62-L62)/V62) -> 0.13913043 | Y62: =Расценки!H61 -> 8800 | Z62: =Расценки!I61 -> 10560 | AA62: =Расценки!J61 -> 0.1 | AB62: =Расценки!K61 -> 0.14782609 | AC62: =IF(OR(K62="",Y62="",Y62=0),"",(Y62-K62)/Y62) -> 0.25 | AD62: =IF(OR(L62="",Z62="",Z62=0),"",(Z62-L62)/Z62) -> 0.25 | AE62: =IF(OR(Y62="",Y62=0),"",(Y62-M62)/Y62) -> 0.45454545 | AF62: =IF(OR(Z62="",Z62=0),"",(Z62-N62)/Z62) -> 0.47727273 | AG62: =IF(OR(K62="",Y62=""),"",Y62-K62) -> 2200 | AH62: =IF(OR(L62="",Z62=""),"",Z62-L62) -> 2640
A63: 1.6.3 | B63: Разборка плинтусов деревянных и из пластмассовых материалов | C63: мп | D63: RAZ | E63: =INDEX('Нормо-час по специальностям'!$B$6:$B$26,MATCH(D63,'Нормо-час по специальностям'!$A$6:$A$26,0)) -> Разнорабочий / демонтажник | F63: 0.05 | G63: ГЭСНр 57-02 (разборка полов) ×0,85 | H63: =IF(OR(F63="",F63=0),"",ROUND($G$3/F63,2)) -> 140 | I63: =INDEX('Нормо-час по специальностям'!$D$6:$D$26,MATCH(D63,'Нормо-час по специальностям'!$A$6:$A$26,0)) -> 550 | J63: =INDEX('Нормо-час по специальностям'!$E$6:$E$26,MATCH(D63,'Нормо-час по специальностям'!$A$6:$A$26,0)) -> 660 | K63: =IF(OR(F63="",F63=0,I63=0),"",ROUND(F63*I63,0)) -> 28 | L63: =IF(OR(F63="",F63=0,J63=0),"",ROUND(F63*J63,0)) -> 33 | M63: =Расценки!L62 -> 30 | N63: =Расценки!M62 -> 34.5 | O63: =IF(OR(K63="",M63="",M63=0),"",K63/M63-1) -> -0.066666667 | P63: =IF(OR(L63="",N63="",N63=0),"",L63/N63-1) -> -0.043478261 | Q63: =IF(O63="","—",IF(O63<-$C$3,"нормо-часы",IF(O63>$C$3,"расценка","равно"))) -> равно | R63: =IF(P63="","—",IF(P63<-$C$3,"нормо-часы",IF(P63>$C$3,"расценка","равно"))) -> равно | S63: =IF(OR(F63="",F63=0,M63=""),"",ROUND(M63/F63,0)) -> 600 | T63: =IF(OR(F63="",F63=0,N63=""),"",ROUND(N63/F63,0)) -> 690 | U63: =Расценки!F62 -> 50 | V63: =Расценки!G62 -> 57.5 | W63: =IF(OR(K63="",U63="",U63=0),"",(U63-K63)/U63) -> 0.44 | X63: =IF(OR(L63="",V63="",V63=0),"",(V63-L63)/V63) -> 0.42608696 | Y63: =Расценки!H62 -> 50 | Z63: =Расценки!I62 -> 57.5 | AA63: =Расценки!J62 -> 0 | AB63: =Расценки!K62 -> 0 | AC63: =IF(OR(K63="",Y63="",Y63=0),"",(Y63-K63)/Y63) -> 0.44 | AD63: =IF(OR(L63="",Z63="",Z63=0),"",(Z63-L63)/Z63) -> 0.42608696 | AE63: =IF(OR(Y63="",Y63=0),"",(Y63-M63)/Y63) -> 0.4 | AF63: =IF(OR(Z63="",Z63=0),"",(Z63-N63)/Z63) -> 0.4 | AG63: =IF(OR(K63="",Y63=""),"",Y63-K63) -> 22 | AH63: =IF(OR(L63="",Z63=""),"",Z63-L63) -> 24.5
A64: 1.6.4 | B64: Разборка плинтусов цементных и из керамогранита | C64: мп | D64: RAZ | E64: =INDEX('Нормо-час по специальностям'!$B$6:$B$26,MATCH(D64,'Нормо-час по специальностям'!$A$6:$A$26,0)) -> Разнорабочий / демонтажник | F64: 0.12 | G64: ГЭСНр 57-02 (разборка полов) ×0,85 | H64: =IF(OR(F64="",F64=0),"",ROUND($G$3/F64,2)) -> 58.33 | I64: =INDEX('Нормо-час по специальностям'!$D$6:$D$26,MATCH(D64,'Нормо-час по специальностям'!$A$6:$A$26,0)) -> 550 | J64: =INDEX('Нормо-час по специальностям'!$E$6:$E$26,MATCH(D64,'Нормо-час по специальностям'!$A$6:$A$26,0)) -> 660 | K64: =IF(OR(F64="",F64=0,I64=0),"",ROUND(F64*I64,0)) -> 66 | L64: =IF(OR(F64="",F64=0,J64=0),"",ROUND(F64*J64,0)) -> 79 | M64: =Расценки!L63 -> 70 | N64: =Расценки!M63 -> 80.5 | O64: =IF(OR(K64="",M64="",M64=0),"",K64/M64-1) -> -0.057142857 | P64: =IF(OR(L64="",N64="",N64=0),"",L64/N64-1) -> -0.01863354 | Q64: =IF(O64="","—",IF(O64<-$C$3,"нормо-часы",IF(O64>$C$3,"расценка","равно"))) -> равно | R64: =IF(P64="","—",IF(P64<-$C$3,"нормо-часы",IF(P64>$C$3,"расценка","равно"))) -> равно | S64: =IF(OR(F64="",F64=0,M64=""),"",ROUND(M64/F64,0)) -> 583 | T64: =IF(OR(F64="",F64=0,N64=""),"",ROUND(N64/F64,0)) -> 671 | U64: =Расценки!F63 -> 120 | V64: =Расценки!G63 -> 138 | W64: =IF(OR(K64="",U64="",U64=0),"",(U64-K64)/U64) -> 0.45 | X64: =IF(OR(L64="",V64="",V64=0),"",(V64-L64)/V64) -> 0.42753623 | Y64: =Расценки!H63 -> 120 | Z64: =Расценки!I63 -> 138 | AA64: =Расценки!J63 -> 0 | AB64: =Расценки!K63 -> 0 | AC64: =IF(OR(K64="",Y64="",Y64=0),"",(Y64-K64)/Y64) -> 0.45 | AD64: =IF(OR(L64="",Z64="",Z64=0),"",(Z64-L64)/Z64) -> 0.42753623 | AE64: =IF(OR(Y64="",Y64=0),"",(Y64-M64)/Y64) -> 0.41666667 | AF64: =IF(OR(Z64="",Z64=0),"",(Z64-N64)/Z64) -> 0.41666667 | AG64: =IF(OR(K64="",Y64=""),"",Y64-K64) -> 54 | AH64: =IF(OR(L64="",Z64=""),"",Z64-L64) -> 59
A65: 1.6.5 | B65: Разборка покрытий полов из древесностружечных плит в один слой | C65: м2 | D65: RAZ | E65: =INDEX('Нормо-час по специальностям'!$B$6:$B$26,MATCH(D65,'Нормо-час по специальностям'!$A$6:$A$26,0)) -> Разнорабочий / демонтажник | F65: 0.12 | G65: ГЭСНр 57-02 (разборка полов) ×0,85 | H65: =IF(OR(F65="",F65=0),"",ROUND($G$3/F65,2)) -> 58.33 | I65: =INDEX('Нормо-час по специальностям'!$D$6:$D$26,MATCH(D65,'Нормо-час по специальностям'!$A$6:$A$26,0)) -> 550 | J65: =INDEX('Нормо-час по специальностям'!$E$6:$E$26,MATCH(D65,'Нормо-час по специальностям'!$A$6:$A$26,0)) -> 660 | K65: =IF(OR(F65="",F65=0,I65=0),"",ROUND(F65*I65,0)) -> 66 | L65: =IF(OR(F65="",F65=0,J65=0),"",ROUND(F65*J65,0)) -> 79 | M65: =Расценки!L64 -> 60 | N65: =Расценки!M64 -> 69 | O65: =IF(OR(K65="",M65="",M65=0),"",K65/M65-1) -> 0.1 | P65: =IF(OR(L65="",N65="",N65=0),"",L65/N65-1) -> 0.14492754 | Q65: =IF(O65="","—",IF(O65<-$C$3,"нормо-часы",IF(O65>$C$3,"расценка","равно"))) -> равно | R65: =IF(P65="","—",IF(P65<-$C$3,"нормо-часы",IF(P65>$C$3,"расценка","равно"))) -> расценка | S65: =IF(OR(F65="",F65=0,M65=""),"",ROUND(M65/F65,0)) -> 500 | T65: =IF(OR(F65="",F65=0,N65=""),"",ROUND(N65/F65,0)) -> 575 | U65: =Расценки!F64 -> 100 | V65: =Расценки!G64 -> 115 | W65: =IF(OR(K65="",U65="",U65=0),"",(U65-K65)/U65) -> 0.34 | X65: =IF(OR(L65="",V65="",V65=0),"",(V65-L65)/V65) -> 0.31304348 | Y65: =Расценки!H64 -> 100 | Z65: =Расценки!I64 -> 115 | AA65: =Расценки!J64 -> 0 | AB65: =Расценки!K64 -> 0 | AC65: =IF(OR(K65="",Y65="",Y65=0),"",(Y65-K65)/Y65) -> 0.34 | AD65: =IF(OR(L65="",Z65="",Z65=0),"",(Z65-L65)/Z65) -> 0.31304348 | AE65: =IF(OR(Y65="",Y65=0),"",(Y65-M65)/Y65) -> 0.4 | AF65: =IF(OR(Z65="",Z65=0),"",(Z65-N65)/Z65) -> 0.4 | AG65: =IF(OR(K65="",Y65=""),"",Y65-K65) -> 34 | AH65: =IF(OR(L65="",Z65=""),"",Z65-L65) -> 36
A66: 1.6.6 | B66: Разборка покрытий полов из керамических плиток | C66: м2 | D66: RAZ | E66: =INDEX('Нормо-час по специальностям'!$B$6:$B$26,MATCH(D66,'Нормо-час по специальностям'!$A$6:$A$26,0)) -> Разнорабочий / демонтажник | F66: 0.35 | G66: ГЭСНр 57-02 (разборка полов) ×0,85 | H66: =IF(OR(F66="",F66=0),"",ROUND($G$3/F66,2)) -> 20 | I66: =INDEX('Нормо-час по специальностям'!$D$6:$D$26,MATCH(D66,'Нормо-час по специальностям'!$A$6:$A$26,0)) -> 550 | J66: =INDEX('Нормо-час по специальностям'!$E$6:$E$26,MATCH(D66,'Нормо-час по специальностям'!$A$6:$A$26,0)) -> 660 | K66: =IF(OR(F66="",F66=0,I66=0),"",ROUND(F66*I66,0)) -> 193 | L66: =IF(OR(F66="",F66=0,J66=0),"",ROUND(F66*J66,0)) -> 231 | M66: =Расценки!L65 -> 180 | N66: =Расценки!M65 -> 207 | O66: =IF(OR(K66="",M66="",M66=0),"",K66/M66-1) -> 0.072222222 | P66: =IF(OR(L66="",N66="",N66=0),"",L66/N66-1) -> 0.11594203 | Q66: =IF(O66="","—",IF(O66<-$C$3,"нормо-часы",IF(O66>$C$3,"расценка","равно"))) -> равно | R66: =IF(P66="","—",IF(P66<-$C$3,"нормо-часы",IF(P66>$C$3,"расценка","равно"))) -> расценка | S66: =IF(OR(F66="",F66=0,M66=""),"",ROUND(M66/F66,0)) -> 514 | T66: =IF(OR(F66="",F66=0,N66=""),"",ROUND(N66/F66,0)) -> 591 | U66: =Расценки!F65 -> 300 | V66: =Расценки!G65 -> 345 | W66: =IF(OR(K66="",U66="",U66=0),"",(U66-K66)/U66) -> 0.35666667 | X66: =IF(OR(L66="",V66="",V66=0),"",(V66-L66)/V66) -> 0.33043478 | Y66: =Расценки!H65 -> 300 | Z66: =Расценки!I65 -> 345 | AA66: =Расценки!J65 -> 0 | AB66: =Расценки!K65 -> 0 | AC66: =IF(OR(K66="",Y66="",Y66=0),"",(Y66-K66)/Y66) -> 0.35666667 | AD66: =IF(OR(L66="",Z66="",Z66=0),"",(Z66-L66)/Z66) -> 0.33043478 | AE66: =IF(OR(Y66="",Y66=0),"",(Y66-M66)/Y66) -> 0.4 | AF66: =IF(OR(Z66="",Z66=0),"",(Z66-N66)/Z66) -> 0.4 | AG66: =IF(OR(K66="",Y66=""),"",Y66-K66) -> 107 | AH66: =IF(OR(L66="",Z66=""),"",Z66-L66) -> 114
A67: 1.6.7 | B67: Разборка покрытий полов из керамогранитных плит толщиной более 15 мм с расчисткой основания от клея | C67: м2 | D67: RAZ | E67: =INDEX('Нормо-час по специальностям'!$B$6:$B$26,MATCH(D67,'Нормо-час по специальностям'!$A$6:$A$26,0)) -> Разнорабочий / демонтажник | F67: 0.8 | G67: ГЭСНр 57-02 (разборка полов) ×0,85 | H67: =IF(OR(F67="",F67=0),"",ROUND($G$3/F67,2)) -> 8.75 | I67: =INDEX('Нормо-час по специальностям'!$D$6:$D$26,MATCH(D67,'Нормо-час по специальностям'!$A$6:$A$26,0)) -> 550 | J67: =INDEX('Нормо-час по специальностям'!$E$6:$E$26,MATCH(D67,'Нормо-час по специальностям'!$A$6:$A$26,0)) -> 660 | K67: =IF(OR(F67="",F67=0,I67=0),"",ROUND(F67*I67,0)) -> 440 | L67: =IF(OR(F67="",F67=0,J67=0),"",ROUND(F67*J67,0)) -> 528 | M67: =Расценки!L66 -> 400 | N67: =Расценки!M66 -> 460 | O67: =IF(OR(K67="",M67="",M67=0),"",K67/M67-1) -> 0.1 | P67: =IF(OR(L67="",N67="",N67=0),"",L67/N67-1) -> 0.14782609 | Q67: =IF(O67="","—",IF(O67<-$C$3,"нормо-часы",IF(O67>$C$3,"расценка","равно"))) -> равно | R67: =IF(P67="","—",IF(P67<-$C$3,"нормо-часы",IF(P67>$C$3,"расценка","равно"))) -> расценка | S67: =IF(OR(F67="",F67=0,M67=""),"",ROUND(M67/F67,0)) -> 500 | T67: =IF(OR(F67="",F67=0,N67=""),"",ROUND(N67/F67,0)) -> 575 | U67: =Расценки!F66 -> 650 | V67: =Расценки!G66 -> 747 | W67: =IF(OR(K67="",U67="",U67=0),"",(U67-K67)/U67) -> 0.32307692 | X67: =IF(OR(L67="",V67="",V67=0),"",(V67-L67)/V67) -> 0.29317269 | Y67: =Расценки!H66 -> 650 | Z67: =Расценки!I66 -> 747 | AA67: =Расценки!J66 -> 0 | AB67: =Расценки!K66 -> 0 | AC67: =IF(OR(K67="",Y67="",Y67=0),"",(Y67-K67)/Y67) -> 0.32307692 | AD67: =IF(OR(L67="",Z67="",Z67=0),"",(Z67-L67)/Z67) -> 0.29317269 | AE67: =IF(OR(Y67="",Y67=0),"",(Y67-M67)/Y67) -> 0.38461538 | AF67: =IF(OR(Z67="",Z67=0),"",(Z67-N67)/Z67) -> 0.38420348 | AG67: =IF(OR(K67="",Y67=""),"",Y67-K67) -> 210 | AH67: =IF(OR(L67="",Z67=""),"",Z67-L67) -> 219
A68: 1.6.8 | B68: Разборка покрытий полов из линолеума и релина | C68: м2 | D68: RAZ | E68: =INDEX('Нормо-час по специальностям'!$B$6:$B$26,MATCH(D68,'Нормо-час по специальностям'!$A$6:$A$26,0)) -> Разнорабочий / демонтажник | F68: 0.07 | G68: ГЭСНр 57-02 (разборка полов) ×0,85 | H68: =IF(OR(F68="",F68=0),"",ROUND($G$3/F68,2)) -> 100 | I68: =INDEX('Нормо-час по специальностям'!$D$6:$D$26,MATCH(D68,'Нормо-час по специальностям'!$A$6:$A$26,0)) -> 550 | J68: =INDEX('Нормо-час по специальностям'!$E$6:$E$26,MATCH(D68,'Нормо-час по специальностям'!$A$6:$A$26,0)) -> 660 | K68: =IF(OR(F68="",F68=0,I68=0),"",ROUND(F68*I68,0)) -> 39 | L68: =IF(OR(F68="",F68=0,J68=0),"",ROUND(F68*J68,0)) -> 46 | M68: =Расценки!L67 -> 50 | N68: =Расценки!M67 -> 57.5 | O68: =IF(OR(K68="",M68="",M68=0),"",K68/M68-1) -> -0.22 | P68: =IF(OR(L68="",N68="",N68=0),"",L68/N68-1) -> -0.2 | Q68: =IF(O68="","—",IF(O68<-$C$3,"нормо-часы",IF(O68>$C$3,"расценка","равно"))) -> нормо-часы | R68: =IF(P68="","—",IF(P68<-$C$3,"нормо-часы",IF(P68>$C$3,"расценка","равно"))) -> нормо-часы | S68: =IF(OR(F68="",F68=0,M68=""),"",ROUND(M68/F68,0)) -> 714 | T68: =IF(OR(F68="",F68=0,N68=""),"",ROUND(N68/F68,0)) -> 821 | U68: =Расценки!F67 -> 80 | V68: =Расценки!G67 -> 92 | W68: =IF(OR(K68="",U68="",U68=0),"",(U68-K68)/U68) -> 0.5125 | X68: =IF(OR(L68="",V68="",V68=0),"",(V68-L68)/V68) -> 0.5 | Y68: =Расценки!H67 -> 80 | Z68: =Расценки!I67 -> 92 | AA68: =Расценки!J67 -> 0 | AB68: =Расценки!K67 -> 0 | AC68: =IF(OR(K68="",Y68="",Y68=0),"",(Y68-K68)/Y68) -> 0.5125 | AD68: =IF(OR(L68="",Z68="",Z68=0),"",(Z68-L68)/Z68) -> 0.5 | AE68: =IF(OR(Y68="",Y68=0),"",(Y68-M68)/Y68) -> 0.375 | AF68: =IF(OR(Z68="",Z68=0),"",(Z68-N68)/Z68) -> 0.375 | AG68: =IF(OR(K68="",Y68=""),"",Y68-K68) -> 41 | AH68: =IF(OR(L68="",Z68=""),"",Z68-L68) -> 46
A69: 1.6.9 | B69: Снятие алюминиевого порога | C69: мп | D69: RAZ | E69: =INDEX('Нормо-час по специальностям'!$B$6:$B$26,MATCH(D69,'Нормо-час по специальностям'!$A$6:$A$26,0)) -> Разнорабочий / демонтажник | F69: 0.15 | G69: экспертно (аналог плинтуса) | H69: =IF(OR(F69="",F69=0),"",ROUND($G$3/F69,2)) -> 46.67 | I69: =INDEX('Нормо-час по специальностям'!$D$6:$D$26,MATCH(D69,'Нормо-час по специальностям'!$A$6:$A$26,0)) -> 550 | J69: =INDEX('Нормо-час по специальностям'!$E$6:$E$26,MATCH(D69,'Нормо-час по специальностям'!$A$6:$A$26,0)) -> 660 | K69: =IF(OR(F69="",F69=0,I69=0),"",ROUND(F69*I69,0)) -> 83 | L69: =IF(OR(F69="",F69=0,J69=0),"",ROUND(F69*J69,0)) -> 99 | M69: =Расценки!L68 -> 70 | N69: =Расценки!M68 -> 80.5 | O69: =IF(OR(K69="",M69="",M69=0),"",K69/M69-1) -> 0.18571429 | P69: =IF(OR(L69="",N69="",N69=0),"",L69/N69-1) -> 0.22981366 | Q69: =IF(O69="","—",IF(O69<-$C$3,"нормо-часы",IF(O69>$C$3,"расценка","равно"))) -> расценка | R69: =IF(P69="","—",IF(P69<-$C$3,"нормо-часы",IF(P69>$C$3,"расценка","равно"))) -> расценка | S69: =IF(OR(F69="",F69=0,M69=""),"",ROUND(M69/F69,0)) -> 467 | T69: =IF(OR(F69="",F69=0,N69=""),"",ROUND(N69/F69,0)) -> 537 | U69: =Расценки!F68 -> 120 | V69: =Расценки!G68 -> 138 | W69: =IF(OR(K69="",U69="",U69=0),"",(U69-K69)/U69) -> 0.30833333 | X69: =IF(OR(L69="",V69="",V69=0),"",(V69-L69)/V69) -> 0.2826087 | Y69: =Расценки!H68 -> 120 | Z69: =Расценки!I68 -> 138 | AA69: =Расценки!J68 -> 0 | AB69: =Расценки!K68 -> 0 | AC69: =IF(OR(K69="",Y69="",Y69=0),"",(Y69-K69)/Y69) -> 0.30833333 | AD69: =IF(OR(L69="",Z69="",Z69=0),"",(Z69-L69)/Z69) -> 0.2826087 | AE69: =IF(OR(Y69="",Y69=0),"",(Y69-M69)/Y69) -> 0.41666667 | AF69: =IF(OR(Z69="",Z69=0),"",(Z69-N69)/Z69) -> 0.41666667 | AG69: =IF(OR(K69="",Y69=""),"",Y69-K69) -> 37 | AH69: =IF(OR(L69="",Z69=""),"",Z69-L69) -> 39
A70: 1.6.10 | B70: Разборка покрытий полов из плиток поливинилхлоридных | C70: м2 | D70: RAZ | E70: =INDEX('Нормо-час по специальностям'!$B$6:$B$26,MATCH(D70,'Нормо-час по специальностям'!$A$6:$A$26,0)) -> Разнорабочий / демонтажник | F70: 0.18 | G70: ГЭСНр 57-02 (разборка полов) ×0,85 | H70: =IF(OR(F70="",F70=0),"",ROUND($G$3/F70,2)) -> 38.89 | I70: =INDEX('Нормо-час по специальностям'!$D$6:$D$26,MATCH(D70,'Нормо-час по специальностям'!$A$6:$A$26,0)) -> 550 | J70: =INDEX('Нормо-час по специальностям'!$E$6:$E$26,MATCH(D70,'Нормо-час по специальностям'!$A$6:$A$26,0)) -> 660 | K70: =IF(OR(F70="",F70=0,I70=0),"",ROUND(F70*I70,0)) -> 99 | L70: =IF(OR(F70="",F70=0,J70=0),"",ROUND(F70*J70,0)) -> 119 | M70: =Расценки!L69 -> 90 | N70: =Расценки!M69 -> 103 | O70: =IF(OR(K70="",M70="",M70=0),"",K70/M70-1) -> 0.1 | P70: =IF(OR(L70="",N70="",N70=0),"",L70/N70-1) -> 0.15533981 | Q70: =IF(O70="","—",IF(O70<-$C$3,"нормо-часы",IF(O70>$C$3,"расценка","равно"))) -> равно | R70: =IF(P70="","—",IF(P70<-$C$3,"нормо-часы",IF(P70>$C$3,"расценка","равно"))) -> расценка | S70: =IF(OR(F70="",F70=0,M70=""),"",ROUND(M70/F70,0)) -> 500 | T70: =IF(OR(F70="",F70=0,N70=""),"",ROUND(N70/F70,0)) -> 572 | U70: =Расценки!F69 -> 150 | V70: =Расценки!G69 -> 172 | W70: =IF(OR(K70="",U70="",U70=0),"",(U70-K70)/U70) -> 0.34 | X70: =IF(OR(L70="",V70="",V70=0),"",(V70-L70)/V70) -> 0.30813953 | Y70: =Расценки!H69 -> 150 | Z70: =Расценки!I69 -> 172 | AA70: =Расценки!J69 -> 0 | AB70: =Расценки!K69 -> 0 | AC70: =IF(OR(K70="",Y70="",Y70=0),"",(Y70-K70)/Y70) -> 0.34 | AD70: =IF(OR(L70="",Z70="",Z70=0),"",(Z70-L70)/Z70) -> 0.30813953 | AE70: =IF(OR(Y70="",Y70=0),"",(Y70-M70)/Y70) -> 0.4 | AF70: =IF(OR(Z70="",Z70=0),"",(Z70-N70)/Z70) -> 0.40116279 | AG70: =IF(OR(K70="",Y70=""),"",Y70-K70) -> 51 | AH70: =IF(OR(L70="",Z70=""),"",Z70-L70) -> 53
A71: 1.6.11 | B71: Разборка покрытий полов цементных толщиной до 150 мм | C71: м2 | D71: RAZ | E71: =INDEX('Нормо-час по специальностям'!$B$6:$B$26,MATCH(D71,'Нормо-час по специальностям'!$A$6:$A$26,0)) -> Разнорабочий / демонтажник | F71: 1.4 | G71: ГЭСНр 57-02 (разборка полов) ×0,85 | H71: =IF(OR(F71="",F71=0),"",ROUND($G$3/F71,2)) -> 5 | I71: =INDEX('Нормо-час по специальностям'!$D$6:$D$26,MATCH(D71,'Нормо-час по специальностям'!$A$6:$A$26,0)) -> 550 | J71: =INDEX('Нормо-час по специальностям'!$E$6:$E$26,MATCH(D71,'Нормо-час по специальностям'!$A$6:$A$26,0)) -> 660 | K71: =IF(OR(F71="",F71=0,I71=0),"",ROUND(F71*I71,0)) -> 770 | L71: =IF(OR(F71="",F71=0,J71=0),"",ROUND(F71*J71,0)) -> 924 | M71: =Расценки!L70 -> 600 | N71: =Расценки!M70 -> 690 | O71: =IF(OR(K71="",M71="",M71=0),"",K71/M71-1) -> 0.28333333 | P71: =IF(OR(L71="",N71="",N71=0),"",L71/N71-1) -> 0.33913043 | Q71: =IF(O71="","—",IF(O71<-$C$3,"нормо-часы",IF(O71>$C$3,"расценка","равно"))) -> расценка | R71: =IF(P71="","—",IF(P71<-$C$3,"нормо-часы",IF(P71>$C$3,"расценка","равно"))) -> расценка | S71: =IF(OR(F71="",F71=0,M71=""),"",ROUND(M71/F71,0)) -> 429 | T71: =IF(OR(F71="",F71=0,N71=""),"",ROUND(N71/F71,0)) -> 493 | U71: =Расценки!F70 -> 1000 | V71: =Расценки!G70 -> 1150 | W71: =IF(OR(K71="",U71="",U71=0),"",(U71-K71)/U71) -> 0.23 | X71: =IF(OR(L71="",V71="",V71=0),"",(V71-L71)/V71) -> 0.19652174 | Y71: =Расценки!H70 -> 1027 | Z71: =Расценки!I70 -> 1232 | AA71: =Расценки!J70 -> 0.027 | AB71: =Расценки!K70 -> 0.071304348 | AC71: =IF(OR(K71="",Y71="",Y71=0),"",(Y71-K71)/Y71) -> 0.25024343 | AD71: =IF(OR(L71="",Z71="",Z71=0),"",(Z71-L71)/Z71) -> 0.25 | AE71: =IF(OR(Y71="",Y71=0),"",(Y71-M71)/Y71) -> 0.4157741 | AF71: =IF(OR(Z71="",Z71=0),"",(Z71-N71)/Z71) -> 0.43993506 | AG71: =IF(OR(K71="",Y71=""),"",Y71-K71) -> 257 | AH71: =IF(OR(L71="",Z71=""),"",Z71-L71) -> 308
A72: 1.6.12 | B72: Разборка покрытий полов из керамогранитных плит толщиной до 15 мм с расчисткой основания от клея | C72: м2 | D72: RAZ | E72: =INDEX('Нормо-час по специальностям'!$B$6:$B$26,MATCH(D72,'Нормо-час по специальностям'!$A$6:$A$26,0)) -> Разнорабочий / демонтажник | F72: 0.55 | G72: ГЭСНр 57-02 (разборка полов) ×0,85 | H72: =IF(OR(F72="",F72=0),"",ROUND($G$3/F72,2)) -> 12.73 | I72: =INDEX('Нормо-час по специальностям'!$D$6:$D$26,MATCH(D72,'Нормо-час по специальностям'!$A$6:$A$26,0)) -> 550 | J72: =INDEX('Нормо-час по специальностям'!$E$6:$E$26,MATCH(D72,'Нормо-час по специальностям'!$A$6:$A$26,0)) -> 660 | K72: =IF(OR(F72="",F72=0,I72=0),"",ROUND(F72*I72,0)) -> 303 | L72: =IF(OR(F72="",F72=0,J72=0),"",ROUND(F72*J72,0)) -> 363 | M72: =Расценки!L71 -> 270 | N72: =Расценки!M71 -> 310 | O72: =IF(OR(K72="",M72="",M72=0),"",K72/M72-1) -> 0.12222222 | P72: =IF(OR(L72="",N72="",N72=0),"",L72/N72-1) -> 0.17096774 | Q72: =IF(O72="","—",IF(O72<-$C$3,"нормо-часы",IF(O72>$C$3,"расценка","равно"))) -> расценка | R72: =IF(P72="","—",IF(P72<-$C$3,"нормо-часы",IF(P72>$C$3,"расценка","равно"))) -> расценка | S72: =IF(OR(F72="",F72=0,M72=""),"",ROUND(M72/F72,0)) -> 491 | T72: =IF(OR(F72="",F72=0,N72=""),"",ROUND(N72/F72,0)) -> 564 | U72: =Расценки!F71 -> 450 | V72: =Расценки!G71 -> 518 | W72: =IF(OR(K72="",U72="",U72=0),"",(U72-K72)/U72) -> 0.32666667 | X72: =IF(OR(L72="",V72="",V72=0),"",(V72-L72)/V72) -> 0.2992278 | Y72: =Расценки!H71 -> 450 | Z72: =Расценки!I71 -> 518 | AA72: =Расценки!J71 -> 0 | AB72: =Расценки!K71 -> 0 | AC72: =IF(OR(K72="",Y72="",Y72=0),"",(Y72-K72)/Y72) -> 0.32666667 | AD72: =IF(OR(L72="",Z72="",Z72=0),"",(Z72-L72)/Z72) -> 0.2992278 | AE72: =IF(OR(Y72="",Y72=0),"",(Y72-M72)/Y72) -> 0.4 | AF72: =IF(OR(Z72="",Z72=0),"",(Z72-N72)/Z72) -> 0.4015444 | AG72: =IF(OR(K72="",Y72=""),"",Y72-K72) -> 147 | AH72: =IF(OR(L72="",Z72=""),"",Z72-L72) -> 155
... A76: 1.6.N4 | B76: Демонтаж фальшпола (съёмного) с опорами | C76: м2 | D76: RAZ | E76: =INDEX('Нормо-час по специальностям'!$B$6:$B$26,MATCH(D76,'Нормо-час по специальностям'!$A$6:$A$26,0)) -> Разнорабочий / демонтажник | F76: 0.3 | G76: ГЭСНр 57-02 (разборка полов) ×0,85 | H76: =IF(OR(F76="",F76=0),"",ROUND($G$3/F76,2)) -> 23.33 | I76: =INDEX('Нормо-час по специальностям'!$D$6:$D$26,MATCH(D76,'Нормо-час по специальностям'!$A$6:$A$26,0)) -> 550 | J76: =INDEX('Нормо-час по специальностям'!$E$6:$E$26,MATCH(D76,'Нормо-час по специальностям'!$A$6:$A$26,0)) -> 660 | K76: =IF(OR(F76="",F76=0,I76=0),"",ROUND(F76*I76,0)) -> 165 | L76: =IF(OR(F76="",F76=0,J76=0),"",ROUND(F76*J76,0)) -> 198 | M76: =Расценки!L75 -> 180 | N76: =Расценки!M75 -> 207 | O76: =IF(OR(K76="",M76="",M76=0),"",K76/M76-1) -> -0.083333333 | P76: =IF(OR(L76="",N76="",N76=0),"",L76/N76-1) -> -0.043478261 | Q76: =IF(O76="","—",IF(O76<-$C$3,"нормо-часы",IF(O76>$C$3,"расценка","равно"))) -> равно | R76: =IF(P76="","—",IF(P76<-$C$3,"нормо-часы",IF(P76>$C$3,"расценка","равно"))) -> равно | S76: =IF(OR(F76="",F76=0,M76=""),"",ROUND(M76/F76,0)) -> 600 | T76: =IF(OR(F76="",F76=0,N76=""),"",ROUND(N76/F76,0)) -> 690 | U76: =Расценки!F75 -> 300 | V76: =Расценки!G75 -> 345 | W76: =IF(OR(K76="",U76="",U76=0),"",(U76-K76)/U76) -> 0.45 | X76: =IF(OR(L76="",V76="",V76=0),"",(V76-L76)/V76) -> 0.42608696 | Y76: =Расценки!H75 -> 300 | Z76: =Расценки!I75 -> 345 | AA76: =Расценки!J75 -> 0 | AB76: =Расценки!K75 -> 0 | AC76: =IF(OR(K76="",Y76="",Y76=0),"",(Y76-K76)/Y76) -> 0.45 | AD76: =IF(OR(L76="",Z76="",Z76=0),"",(Z76-L76)/Z76) -> 0.42608696 | AE76: =IF(OR(Y76="",Y76=0),"",(Y76-M76)/Y76) -> 0.4 | AF76: =IF(OR(Z76="",Z76=0),"",(Z76-N76)/Z76) -> 0.4 | AG76: =IF(OR(K76="",Y76=""),"",Y76-K76) -> 135 | AH76: =IF(OR(L76="",Z76=""),"",Z76-L76) -> 147
A77: 1.7 Демонтажные работы потолка
A78: 1.7.1 | B78: Демонтаж утеплителя потолков | C78: м2 | D78: RAZ | E78: =INDEX('Нормо-час по специальностям'!$B$6:$B$26,MATCH(D78,'Нормо-час по специальностям'!$A$6:$A$26,0)) -> Разнорабочий / демонтажник | F78: 0.15 | G78: ГЭСНр 46-04 (разборка конструкций) ×0,85 | H78: =IF(OR(F78="",F78=0),"",ROUND($G$3/F78,2)) -> 46.67 | I78: =INDEX('Нормо-час по специальностям'!$D$6:$D$26,MATCH(D78,'Нормо-час по специальностям'!$A$6:$A$26,0)) -> 550 | J78: =INDEX('Нормо-час по специальностям'!$E$6:$E$26,MATCH(D78,'Нормо-час по специальностям'!$A$6:$A$26,0)) -> 660 | K78: =IF(OR(F78="",F78=0,I78=0),"",ROUND(F78*I78,0)) -> 83 | L78: =IF(OR(F78="",F78=0,J78=0),"",ROUND(F78*J78,0)) -> 99 | M78: =Расценки!L77 -> 70 | N78: =Расценки!M77 -> 80.5 | O78: =IF(OR(K78="",M78="",M78=0),"",K78/M78-1) -> 0.18571429 | P78: =IF(OR(L78="",N78="",N78=0),"",L78/N78-1) -> 0.22981366 | Q78: =IF(O78="","—",IF(O78<-$C$3,"нормо-часы",IF(O78>$C$3,"расценка","равно"))) -> расценка | R78: =IF(P78="","—",IF(P78<-$C$3,"нормо-часы",IF(P78>$C$3,"расценка","равно"))) -> расценка | S78: =IF(OR(F78="",F78=0,M78=""),"",ROUND(M78/F78,0)) -> 467 | T78: =IF(OR(F78="",F78=0,N78=""),"",ROUND(N78/F78,0)) -> 537 | U78: =Расценки!F77 -> 120 | V78: =Расценки!G77 -> 138 | W78: =IF(OR(K78="",U78="",U78=0),"",(U78-K78)/U78) -> 0.30833333 | X78: =IF(OR(L78="",V78="",V78=0),"",(V78-L78)/V78) -> 0.2826087 | Y78: =Расценки!H77 -> 120 | Z78: =Расценки!I77 -> 138 | AA78: =Расценки!J77 -> 0 | AB78: =Расценки!K77 -> 0 | AC78: =IF(OR(K78="",Y78="",Y78=0),"",(Y78-K78)/Y78) -> 0.30833333 | AD78: =IF(OR(L78="",Z78="",Z78=0),"",(Z78-L78)/Z78) -> 0.2826087 | AE78: =IF(OR(Y78="",Y78=0),"",(Y78-M78)/Y78) -> 0.41666667 | AF78: =IF(OR(Z78="",Z78=0),"",(Z78-N78)/Z78) -> 0.41666667 | AG78: =IF(OR(K78="",Y78=""),"",Y78-K78) -> 37 | AH78: =IF(OR(L78="",Z78=""),"",Z78-L78) -> 39
A79: 1.7.2 | B79: Отбивка штукатурки с поверхности потолка | C79: м2 | D79: OTD | E79: =INDEX('Нормо-час по специальностям'!$B$6:$B$26,MATCH(D79,'Нормо-час по специальностям'!$A$6:$A$26,0)) -> Отделочник (штукатур, маляр, ГКЛ) | F79: 0.5 | G79: ЕНиР Е20-1 (разборка конструкций при ремонте) | H79: =IF(OR(F79="",F79=0),"",ROUND($G$3/F79,2)) -> 14 | I79: =INDEX('Нормо-час по специальностям'!$D$6:$D$26,MATCH(D79,'Нормо-час по специальностям'!$A$6:$A$26,0)) -> 750 | J79: =INDEX('Нормо-час по специальностям'!$E$6:$E$26,MATCH(D79,'Нормо-час по специальностям'!$A$6:$A$26,0)) -> 900 | K79: =IF(OR(F79="",F79=0,I79=0),"",ROUND(F79*I79,0)) -> 375 | L79: =IF(OR(F79="",F79=0,J79=0),"",ROUND(F79*J79,0)) -> 450 | M79: =Расценки!L78 -> 210 | N79: =Расценки!M78 -> 241 | O79: =IF(OR(K79="",M79="",M79=0),"",K79/M79-1) -> 0.78571429 | P79: =IF(OR(L79="",N79="",N79=0),"",L79/N79-1) -> 0.86721992 | Q79: =IF(O79="","—",IF(O79<-$C$3,"нормо-часы",IF(O79>$C$3,"расценка","равно"))) -> расценка | R79: =IF(P79="","—",IF(P79<-$C$3,"нормо-часы",IF(P79>$C$3,"расценка","равно"))) -> расценка | S79: =IF(OR(F79="",F79=0,M79=""),"",ROUND(M79/F79,0)) -> 420 | T79: =IF(OR(F79="",F79=0,N79=""),"",ROUND(N79/F79,0)) -> 482 | U79: =Расценки!F78 -> 350 | V79: =Расценки!G78 -> 402 | W79: =IF(OR(K79="",U79="",U79=0),"",(U79-K79)/U79) -> -0.071428571 | X79: =IF(OR(L79="",V79="",V79=0),"",(V79-L79)/V79) -> -0.11940299 | Y79: =Расценки!H78 -> 500 | Z79: =Расценки!I78 -> 600 | AA79: =Расценки!J78 -> 0.42857143 | AB79: =Расценки!K78 -> 0.49253731 | AC79: =IF(OR(K79="",Y79="",Y79=0),"",(Y79-K79)/Y79) -> 0.25 | AD79: =IF(OR(L79="",Z79="",Z79=0),"",(Z79-L79)/Z79) -> 0.25 | AE79: =IF(OR(Y79="",Y79=0),"",(Y79-M79)/Y79) -> 0.58 | AF79: =IF(OR(Z79="",Z79=0),"",(Z79-N79)/Z79) -> 0.59833333 | AG79: =IF(OR(K79="",Y79=""),"",Y79-K79) -> 125 | AH79: =IF(OR(L79="",Z79=""),"",Z79-L79) -> 150
A80: 1.7.3 | B80: Разборка облицовки потолков из гипсокартонных листов с каркасом | C80: м2 | D80: OTD | E80: =INDEX('Нормо-час по специальностям'!$B$6:$B$26,MATCH(D80,'Нормо-час по специальностям'!$A$6:$A$26,0)) -> Отделочник (штукатур, маляр, ГКЛ) | F80: 0.25 | G80: ГЭСНр 46-04 (разборка конструкций) ×0,85 | H80: =IF(OR(F80="",F80=0),"",ROUND($G$3/F80,2)) -> 28 | I80: =INDEX('Нормо-час по специальностям'!$D$6:$D$26,MATCH(D80,'Нормо-час по специальностям'!$A$6:$A$26,0)) -> 750 | J80: =INDEX('Нормо-час по специальностям'!$E$6:$E$26,MATCH(D80,'Нормо-час по специальностям'!$A$6:$A$26,0)) -> 900 | K80: =IF(OR(F80="",F80=0,I80=0),"",ROUND(F80*I80,0)) -> 188 | L80: =IF(OR(F80="",F80=0,J80=0),"",ROUND(F80*J80,0)) -> 225 | M80: =Расценки!L79 -> 130 | N80: =Расценки!M79 -> 150 | O80: =IF(OR(K80="",M80="",M80=0),"",K80/M80-1) -> 0.44615385 | P80: =IF(OR(L80="",N80="",N80=0),"",L80/N80-1) -> 0.5 | Q80: =IF(O80="","—",IF(O80<-$C$3,"нормо-часы",IF(O80>$C$3,"расценка","равно"))) -> расценка | R80: =IF(P80="","—",IF(P80<-$C$3,"нормо-часы",IF(P80>$C$3,"расценка","равно"))) -> расценка | S80: =IF(OR(F80="",F80=0,M80=""),"",ROUND(M80/F80,0)) -> 520 | T80: =IF(OR(F80="",F80=0,N80=""),"",ROUND(N80/F80,0)) -> 600 | U80: =Расценки!F79 -> 220 | V80: =Расценки!G79 -> 253 | W80: =IF(OR(K80="",U80="",U80=0),"",(U80-K80)/U80) -> 0.14545455 | X80: =IF(OR(L80="",V80="",V80=0),"",(V80-L80)/V80) -> 0.11067194 | Y80: =Расценки!H79 -> 251 | Z80: =Расценки!I79 -> 300 | AA80: =Расценки!J79 -> 0.14090909 | AB80: =Расценки!K79 -> 0.18577075 | AC80: =IF(OR(K80="",Y80="",Y80=0),"",(Y80-K80)/Y80) -> 0.25099602 | AD80: =IF(OR(L80="",Z80="",Z80=0),"",(Z80-L80)/Z80) -> 0.25 | AE80: =IF(OR(Y80="",Y80=0),"",(Y80-M80)/Y80) -> 0.48207171 | AF80: =IF(OR(Z80="",Z80=0),"",(Z80-N80)/Z80) -> 0.5 | AG80: =IF(OR(K80="",Y80=""),"",Y80-K80) -> 63 | AH80: =IF(OR(L80="",Z80=""),"",Z80-L80) -> 75
A81: 1.7.4 | B81: Разборка подвесного потолка Грильято включая направляющие | C81: м2 | D81: OTD | E81: =INDEX('Нормо-час по специальностям'!$B$6:$B$26,MATCH(D81,'Нормо-час по специальностям'!$A$6:$A$26,0)) -> Отделочник (штукатур, маляр, ГКЛ) | F81: 0.2 | G81: экспертно (аналог 1.7.8) | H81: =IF(OR(F81="",F81=0),"",ROUND($G$3/F81,2)) -> 35 | I81: =INDEX('Нормо-час по специальностям'!$D$6:$D$26,MATCH(D81,'Нормо-час по специальностям'!$A$6:$A$26,0)) -> 750 | J81: =INDEX('Нормо-час по специальностям'!$E$6:$E$26,MATCH(D81,'Нормо-час по специальностям'!$A$6:$A$26,0)) -> 900 | K81: =IF(OR(F81="",F81=0,I81=0),"",ROUND(F81*I81,0)) -> 150 | L81: =IF(OR(F81="",F81=0,J81=0),"",ROUND(F81*J81,0)) -> 180 | M81: =Расценки!L80 -> 110 | N81: =Расценки!M80 -> 126 | O81: =IF(OR(K81="",M81="",M81=0),"",K81/M81-1) -> 0.36363636 | P81: =IF(OR(L81="",N81="",N81=0),"",L81/N81-1) -> 0.42857143 | Q81: =IF(O81="","—",IF(O81<-$C$3,"нормо-часы",IF(O81>$C$3,"расценка","равно"))) -> расценка | R81: =IF(P81="","—",IF(P81<-$C$3,"нормо-часы",IF(P81>$C$3,"расценка","равно"))) -> расценка | S81: =IF(OR(F81="",F81=0,M81=""),"",ROUND(M81/F81,0)) -> 550 | T81: =IF(OR(F81="",F81=0,N81=""),"",ROUND(N81/F81,0)) -> 630 | U81: =Расценки!F80 -> 180 | V81: =Расценки!G80 -> 207 | W81: =IF(OR(K81="",U81="",U81=0),"",(U81-K81)/U81) -> 0.16666667 | X81: =IF(OR(L81="",V81="",V81=0),"",(V81-L81)/V81) -> 0.13043478 | Y81: =Расценки!H80 -> 200 | Z81: =Расценки!I80 -> 240 | AA81: =Расценки!J80 -> 0.11111111 | AB81: =Расценки!K80 -> 0.15942029 | AC81: =IF(OR(K81="",Y81="",Y81=0),"",(Y81-K81)/Y81) -> 0.25 | AD81: =IF(OR(L81="",Z81="",Z81=0),"",(Z81-L81)/Z81) -> 0.25 | AE81: =IF(OR(Y81="",Y81=0),"",(Y81-M81)/Y81) -> 0.45 | AF81: =IF(OR(Z81="",Z81=0),"",(Z81-N81)/Z81) -> 0.475 | AG81: =IF(OR(K81="",Y81=""),"",Y81-K81) -> 50 | AH81: =IF(OR(L81="",Z81=""),"",Z81-L81) -> 60
A82: 1.7.5 | B82: Разборка подвесной системы потолка | C82: м2 | D82: OTD | E82: =INDEX('Нормо-час по специальностям'!$B$6:$B$26,MATCH(D82,'Нормо-час по специальностям'!$A$6:$A$26,0)) -> Отделочник (штукатур, маляр, ГКЛ) | F82: 0.12 | G82: экспертно (аналог 1.7.8, только каркас) | H82: =IF(OR(F82="",F82=0),"",ROUND($G$3/F82,2)) -> 58.33 | I82: =INDEX('Нормо-час по специальностям'!$D$6:$D$26,MATCH(D82,'Нормо-час по специальностям'!$A$6:$A$26,0)) -> 750 | J82: =INDEX('Нормо-час по специальностям'!$E$6:$E$26,MATCH(D82,'Нормо-час по специальностям'!$A$6:$A$26,0)) -> 900 | K82: =IF(OR(F82="",F82=0,I82=0),"",ROUND(F82*I82,0)) -> 90 | L82: =IF(OR(F82="",F82=0,J82=0),"",ROUND(F82*J82,0)) -> 108 | M82: =Расценки!L81 -> 70 | N82: =Расценки!M81 -> 80.5 | O82: =IF(OR(K82="",M82="",M82=0),"",K82/M82-1) -> 0.28571429 | P82: =IF(OR(L82="",N82="",N82=0),"",L82/N82-1) -> 0.34161491 | Q82: =IF(O82="","—",IF(O82<-$C$3,"нормо-часы",IF(O82>$C$3,"расценка","равно"))) -> расценка | R82: =IF(P82="","—",IF(P82<-$C$3,"нормо-часы",IF(P82>$C$3,"расценка","равно"))) -> расценка | S82: =IF(OR(F82="",F82=0,M82=""),"",ROUND(M82/F82,0)) -> 583 | T82: =IF(OR(F82="",F82=0,N82=""),"",ROUND(N82/F82,0)) -> 671 | U82: =Расценки!F81 -> 120 | V82: =Расценки!G81 -> 138 | W82: =IF(OR(K82="",U82="",U82=0),"",(U82-K82)/U82) -> 0.25 | X82: =IF(OR(L82="",V82="",V82=0),"",(V82-L82)/V82) -> 0.2173913 | Y82: =Расценки!H81 -> 120 | Z82: =Расценки!I81 -> 144 | AA82: =Расценки!J81 -> 0 | AB82: =Расценки!K81 -> 0.043478261 | AC82: =IF(OR(K82="",Y82="",Y82=0),"",(Y82-K82)/Y82) -> 0.25 | AD82: =IF(OR(L82="",Z82="",Z82=0),"",(Z82-L82)/Z82) -> 0.25 | AE82: =IF(OR(Y82="",Y82=0),"",(Y82-M82)/Y82) -> 0.41666667 | AF82: =IF(OR(Z82="",Z82=0),"",(Z82-N82)/Z82) -> 0.44097222 | AG82: =IF(OR(K82="",Y82=""),"",Y82-K82) -> 30 | AH82: =IF(OR(L82="",Z82=""),"",Z82-L82) -> 36
A83: 1.7.6 | B83: Разборка подвесных каркасов, подшивных потолков из металлических уголков (не применимо для направляющих) | C83: м2 | D83: OTD | E83: =INDEX('Нормо-час по специальностям'!$B$6:$B$26,MATCH(D83,'Нормо-час по специальностям'!$A$6:$A$26,0)) -> Отделочник (штукатур, маляр, ГКЛ) | F83: 0.18 | G83: ГЭСНр 46-04 (разборка конструкций) ×0,85 | H83: =IF(OR(F83="",F83=0),"",ROUND($G$3/F83,2)) -> 38.89 | I83: =INDEX('Нормо-час по специальностям'!$D$6:$D$26,MATCH(D83,'Нормо-час по специальностям'!$A$6:$A$26,0)) -> 750 | J83: =INDEX('Нормо-час по специальностям'!$E$6:$E$26,MATCH(D83,'Нормо-час по специальностям'!$A$6:$A$26,0)) -> 900 | K83: =IF(OR(F83="",F83=0,I83=0),"",ROUND(F83*I83,0)) -> 135 | L83: =IF(OR(F83="",F83=0,J83=0),"",ROUND(F83*J83,0)) -> 162 | M83: =Расценки!L82 -> 90 | N83: =Расценки!M82 -> 103 | O83: =IF(OR(K83="",M83="",M83=0),"",K83/M83-1) -> 0.5 | P83: =IF(OR(L83="",N83="",N83=0),"",L83/N83-1) -> 0.57281553 | Q83: =IF(O83="","—",IF(O83<-$C$3,"нормо-часы",IF(O83>$C$3,"расценка","равно"))) -> расценка | R83: =IF(P83="","—",IF(P83<-$C$3,"нормо-часы",IF(P83>$C$3,"расценка","равно"))) -> расценка | S83: =IF(OR(F83="",F83=0,M83=""),"",ROUND(M83/F83,0)) -> 500 | T83: =IF(OR(F83="",F83=0,N83=""),"",ROUND(N83/F83,0)) -> 572 | U83: =Расценки!F82 -> 150 | V83: =Расценки!G82 -> 172 | W83: =IF(OR(K83="",U83="",U83=0),"",(U83-K83)/U83) -> 0.1 | X83: =IF(OR(L83="",V83="",V83=0),"",(V83-L83)/V83) -> 0.058139535 | Y83: =Расценки!H82 -> 180 | Z83: =Расценки!I82 -> 216 | AA83: =Расценки!J82 -> 0.2 | AB83: =Расценки!K82 -> 0.25581395 | AC83: =IF(OR(K83="",Y83="",Y83=0),"",(Y83-K83)/Y83) -> 0.25 | AD83: =IF(OR(L83="",Z83="",Z83=0),"",(Z83-L83)/Z83) -> 0.25 | AE83: =IF(OR(Y83="",Y83=0),"",(Y83-M83)/Y83) -> 0.5 | AF83: =IF(OR(Z83="",Z83=0),"",(Z83-N83)/Z83) -> 0.52314815 | AG83: =IF(OR(K83="",Y83=""),"",Y83-K83) -> 45 | AH83: =IF(OR(L83="",Z83=""),"",Z83-L83) -> 54
A84: 1.7.7 | B84: Разборка подвесных потолков из металлических кассет, включая направляющие | C84: м2 | D84: OTD | E84: =INDEX('Нормо-час по специальностям'!$B$6:$B$26,MATCH(D84,'Нормо-час по специальностям'!$A$6:$A$26,0)) -> Отделочник (штукатур, маляр, ГКЛ) | F84: 0.22 | G84: экспертно (аналог 1.7.8) | H84: =IF(OR(F84="",F84=0),"",ROUND($G$3/F84,2)) -> 31.82 | I84: =INDEX('Нормо-час по специальностям'!$D$6:$D$26,MATCH(D84,'Нормо-час по специальностям'!$A$6:$A$26,0)) -> 750 | J84: =INDEX('Нормо-час по специальностям'!$E$6:$E$26,MATCH(D84,'Нормо-час по специальностям'!$A$6:$A$26,0)) -> 900 | K84: =IF(OR(F84="",F84=0,I84=0),"",ROUND(F84*I84,0)) -> 165 | L84: =IF(OR(F84="",F84=0,J84=0),"",ROUND(F84*J84,0)) -> 198 | M84: =Расценки!L83 -> 120 | N84: =Расценки!M83 -> 138 | O84: =IF(OR(K84="",M84="",M84=0),"",K84/M84-1) -> 0.375 | P84: =IF(OR(L84="",N84="",N84=0),"",L84/N84-1) -> 0.43478261 | Q84: =IF(O84="","—",IF(O84<-$C$3,"нормо-часы",IF(O84>$C$3,"расценка","равно"))) -> расценка | R84: =IF(P84="","—",IF(P84<-$C$3,"нормо-часы",IF(P84>$C$3,"расценка","равно"))) -> расценка | S84: =IF(OR(F84="",F84=0,M84=""),"",ROUND(M84/F84,0)) -> 545 | T84: =IF(OR(F84="",F84=0,N84=""),"",ROUND(N84/F84,0)) -> 627 | U84: =Расценки!F83 -> 200 | V84: =Расценки!G83 -> 230 | W84: =IF(OR(K84="",U84="",U84=0),"",(U84-K84)/U84) -> 0.175 | X84: =IF(OR(L84="",V84="",V84=0),"",(V84-L84)/V84) -> 0.13913043 | Y84: =Расценки!H83 -> 220 | Z84: =Расценки!I83 -> 264 | AA84: =Расценки!J83 -> 0.1 | AB84: =Расценки!K83 -> 0.14782609 | AC84: =IF(OR(K84="",Y84="",Y84=0),"",(Y84-K84)/Y84) -> 0.25 | AD84: =IF(OR(L84="",Z84="",Z84=0),"",(Z84-L84)/Z84) -> 0.25 | AE84: =IF(OR(Y84="",Y84=0),"",(Y84-M84)/Y84) -> 0.45454545 | AF84: =IF(OR(Z84="",Z84=0),"",(Z84-N84)/Z84) -> 0.47727273 | AG84: =IF(OR(K84="",Y84=""),"",Y84-K84) -> 55 | AH84: =IF(OR(L84="",Z84=""),"",Z84-L84) -> 66
A85: 1.7.8 | B85: Разборка подвесных потолков типа <Армстронг> включая направляющие | C85: м2 | D85: OTD | E85: =INDEX('Нормо-час по специальностям'!$B$6:$B$26,MATCH(D85,'Нормо-час по специальностям'!$A$6:$A$26,0)) -> Отделочник (штукатур, маляр, ГКЛ) | F85: 0.18 | G85: ГЭСНр 46-04 (разборка конструкций) ×0,85 | H85: =IF(OR(F85="",F85=0),"",ROUND($G$3/F85,2)) -> 38.89 | I85: =INDEX('Нормо-час по специальностям'!$D$6:$D$26,MATCH(D85,'Нормо-час по специальностям'!$A$6:$A$26,0)) -> 750 | J85: =INDEX('Нормо-час по специальностям'!$E$6:$E$26,MATCH(D85,'Нормо-час по специальностям'!$A$6:$A$26,0)) -> 900 | K85: =IF(OR(F85="",F85=0,I85=0),"",ROUND(F85*I85,0)) -> 135 | L85: =IF(OR(F85="",F85=0,J85=0),"",ROUND(F85*J85,0)) -> 162 | M85: =Расценки!L84 -> 110 | N85: =Расценки!M84 -> 126 | O85: =IF(OR(K85="",M85="",M85=0),"",K85/M85-1) -> 0.22727273 | P85: =IF(OR(L85="",N85="",N85=0),"",L85/N85-1) -> 0.28571429 | Q85: =IF(O85="","—",IF(O85<-$C$3,"нормо-часы",IF(O85>$C$3,"расценка","равно"))) -> расценка | R85: =IF(P85="","—",IF(P85<-$C$3,"нормо-часы",IF(P85>$C$3,"расценка","равно"))) -> расценка | S85: =IF(OR(F85="",F85=0,M85=""),"",ROUND(M85/F85,0)) -> 611 | T85: =IF(OR(F85="",F85=0,N85=""),"",ROUND(N85/F85,0)) -> 700 | U85: =Расценки!F84 -> 180 | V85: =Расценки!G84 -> 207 | W85: =IF(OR(K85="",U85="",U85=0),"",(U85-K85)/U85) -> 0.25 | X85: =IF(OR(L85="",V85="",V85=0),"",(V85-L85)/V85) -> 0.2173913 | Y85: =Расценки!H84 -> 180 | Z85: =Расценки!I84 -> 216 | AA85: =Расценки!J84 -> 0 | AB85: =Расценки!K84 -> 0.043478261 | AC85: =IF(OR(K85="",Y85="",Y85=0),"",(Y85-K85)/Y85) -> 0.25 | AD85: =IF(OR(L85="",Z85="",Z85=0),"",(Z85-L85)/Z85) -> 0.25 | AE85: =IF(OR(Y85="",Y85=0),"",(Y85-M85)/Y85) -> 0.38888889 | AF85: =IF(OR(Z85="",Z85=0),"",(Z85-N85)/Z85) -> 0.41666667 | AG85: =IF(OR(K85="",Y85=""),"",Y85-K85) -> 45 | AH85: =IF(OR(L85="",Z85=""),"",Z85-L85) -> 54
A86: 1.7.9 | B86: Разборка потолков реечных алюминиевых включая направляющие | C86: м2 | D86: OTD | E86: =INDEX('Нормо-час по специальностям'!$B$6:$B$26,MATCH(D86,'Нормо-час по специальностям'!$A$6:$A$26,0)) -> Отделочник (штукатур, маляр, ГКЛ) | F86: 0.22 | G86: ГЭСНр 46-04 (разборка конструкций) ×0,85 | H86: =IF(OR(F86="",F86=0),"",ROUND($G$3/F86,2)) -> 31.82 | I86: =INDEX('Нормо-час по специальностям'!$D$6:$D$26,MATCH(D86,'Нормо-час по специальностям'!$A$6:$A$26,0)) -> 750 | J86: =INDEX('Нормо-час по специальностям'!$E$6:$E$26,MATCH(D86,'Нормо-час по специальностям'!$A$6:$A$26,0)) -> 900 | K86: =IF(OR(F86="",F86=0,I86=0),"",ROUND(F86*I86,0)) -> 165 | L86: =IF(OR(F86="",F86=0,J86=0),"",ROUND(F86*J86,0)) -> 198 | M86: =Расценки!L85 -> 120 | N86: =Расценки!M85 -> 138 | O86: =IF(OR(K86="",M86="",M86=0),"",K86/M86-1) -> 0.375 | P86: =IF(OR(L86="",N86="",N86=0),"",L86/N86-1) -> 0.43478261 | Q86: =IF(O86="","—",IF(O86<-$C$3,"нормо-часы",IF(O86>$C$3,"расценка","равно"))) -> расценка | R86: =IF(P86="","—",IF(P86<-$C$3,"нормо-часы",IF(P86>$C$3,"расценка","равно"))) -> расценка | S86: =IF(OR(F86="",F86=0,M86=""),"",ROUND(M86/F86,0)) -> 545 | T86: =IF(OR(F86="",F86=0,N86=""),"",ROUND(N86/F86,0)) -> 627 | U86: =Расценки!F85 -> 200 | V86: =Расценки!G85 -> 230 | W86: =IF(OR(K86="",U86="",U86=0),"",(U86-K86)/U86) -> 0.175 | X86: =IF(OR(L86="",V86="",V86=0),"",(V86-L86)/V86) -> 0.13913043 | Y86: =Расценки!H85 -> 220 | Z86: =Расценки!I85 -> 264 | AA86: =Расценки!J85 -> 0.1 | AB86: =Расценки!K85 -> 0.14782609 | AC86: =IF(OR(K86="",Y86="",Y86=0),"",(Y86-K86)/Y86) -> 0.25 | AD86: =IF(OR(L86="",Z86="",Z86=0),"",(Z86-L86)/Z86) -> 0.25 | AE86: =IF(OR(Y86="",Y86=0),"",(Y86-M86)/Y86) -> 0.45454545 | AF86: =IF(OR(Z86="",Z86=0),"",(Z86-N86)/Z86) -> 0.47727273 | AG86: =IF(OR(K86="",Y86=""),"",Y86-K86) -> 55 | AH86: =IF(OR(L86="",Z86=""),"",Z86-L86) -> 66
A87: 1.7.10 | B87: Разборка реечного потолка из ламелей (потолок Кубота) | C87: м2 | D87: OTD | E87: =INDEX('Нормо-час по специальностям'!$B$6:$B$26,MATCH(D87,'Нормо-час по специальностям'!$A$6:$A$26,0)) -> Отделочник (штукатур, маляр, ГКЛ) | F87: 0.25 | G87: экспертно (аналог 1.7.9) | H87: =IF(OR(F87="",F87=0),"",ROUND($G$3/F87,2)) -> 28 | I87: =INDEX('Нормо-час по специальностям'!$D$6:$D$26,MATCH(D87,'Нормо-час по специальностям'!$A$6:$A$26,0)) -> 750 | J87: =INDEX('Нормо-час по специальностям'!$E$6:$E$26,MATCH(D87,'Нормо-час по специальностям'!$A$6:$A$26,0)) -> 900 | K87: =IF(OR(F87="",F87=0,I87=0),"",ROUND(F87*I87,0)) -> 188 | L87: =IF(OR(F87="",F87=0,J87=0),"",ROUND(F87*J87,0)) -> 225 | M87: =Расценки!L86 -> 140 | N87: =Расценки!M86 -> 161 | O87: =IF(OR(K87="",M87="",M87=0),"",K87/M87-1) -> 0.34285714 | P87: =IF(OR(L87="",N87="",N87=0),"",L87/N87-1) -> 0.39751553 | Q87: =IF(O87="","—",IF(O87<-$C$3,"нормо-часы",IF(O87>$C$3,"расценка","равно"))) -> расценка | R87: =IF(P87="","—",IF(P87<-$C$3,"нормо-часы",IF(P87>$C$3,"расценка","равно"))) -> расценка | S87: =IF(OR(F87="",F87=0,M87=""),"",ROUND(M87/F87,0)) -> 560 | T87: =IF(OR(F87="",F87=0,N87=""),"",ROUND(N87/F87,0)) -> 644 | U87: =Расценки!F86 -> 230 | V87: =Расценки!G86 -> 264 | W87: =IF(OR(K87="",U87="",U87=0),"",(U87-K87)/U87) -> 0.1826087 | X87: =IF(OR(L87="",V87="",V87=0),"",(V87-L87)/V87) -> 0.14772727 | Y87: =Расценки!H86 -> 251 | Z87: =Расценки!I86 -> 300 | AA87: =Расценки!J86 -> 0.091304348 | AB87: =Расценки!K86 -> 0.13636364 | AC87: =IF(OR(K87="",Y87="",Y87=0),"",(Y87-K87)/Y87) -> 0.25099602 | AD87: =IF(OR(L87="",Z87="",Z87=0),"",(Z87-L87)/Z87) -> 0.25 | AE87: =IF(OR(Y87="",Y87=0),"",(Y87-M87)/Y87) -> 0.44223108 | AF87: =IF(OR(Z87="",Z87=0),"",(Z87-N87)/Z87) -> 0.46333333 | AG87: =IF(OR(K87="",Y87=""),"",Y87-K87) -> 63 | AH87: =IF(OR(L87="",Z87=""),"",Z87-L87) -> 75
